Workbook

Sheet DASHBOARD
A1: DASHBOARD — PBMM Evidence: Analytics
A2: Control ID | B2: Control Name | C2: Primary Tool | D2: Tab | E2: Status
A3: AU-2 | B3: Auditable Events | D3: AU-2 | E3: ='AU-2'!B20 -> Not Started
A4: AU-3 | B4: Content of Audit Records | D4: AU-3 | E4: ='AU-3'!B20 -> Not Started
A5: AU-3(1) | B5: Content of Audit Records | D5: AU-3-1 | E5: ='AU-3-1'!B20 -> Not Started
A6: AU-5 | B6: Response To Audit Processing Failures | D6: AU-5 | E6: ='AU-5'!B20 -> Not Started
A7: AU-9(2) | B7: Protection of Audit Information | D7: AU-9-2 | E7: ='AU-9-2'!B20 -> Not Started
A8: AU-12 | B8: Audit Generation | D8: AU-12 | E8: ='AU-12'!B20 -> Not Started
A9: CM-2(3) | B9: Baseline Configuration | D9: CM-2-3 | E9: ='CM-2-3'!B20 -> Not Started
A10: CM-5(1) | B10: Access Restrictions for Change | D10: CM-5-1 | E10: ='CM-5-1'!B20 -> Not Started
A11: CM-6 | B11: Configuration Settings | D11: CM-6 | E11: ='CM-6'!B20 -> Not Started
A12: CM-7 | B12: Least Functionality | D12: CM-7 | E12: ='CM-7'!B20 -> Not Started
A13: CM-7(1) | B13: Least Functionality | D13: CM-7-1 | E13: ='CM-7-1'!B20 -> Not Started
A14: CP-6 | B14: Alternate Storage Site | D14: CP-6 | E14: ='CP-6'!B20 -> Not Started
A15: CP-6(2) | B15: Alternate Storage Site | D15: CP-6-2 | E15: ='CP-6-2'!B20 -> Not Started
A16: CP-7 | B16: Alternate Processing Site | D16: CP-7 | E16: ='CP-7'!B20 -> Not Started
A17: CP-7(4) | B17: Alternate Processing Site | D17: CP-7-4 | E17: ='CP-7-4'!B20 -> Not Started
A18: CP-9 | B18: Information System Backup | D18: CP-9 | E18: ='CP-9'!B20 -> Not Started
A19: CP-9(1) | B19: Information System Backup | D19: CP-9-1 | E19: ='CP-9-1'!B20 -> Not Started
A20: CP-9(2) | B20: Information System Backup | D20: CP-9-2 | E20: ='CP-9-2'!B20 -> Not Started
A21: CP-9(5) | B21: Information System Backup | D21: CP-9-5 | E21: ='CP-9-5'!B20 -> Not Started
A22: CP-10 | B22: Information System Recovery and Reconstitution | D22: CP-10 | E22: ='CP-10'!B20 -> Not Started
A23: CP-10(4) | B23: Information System Recovery and Reconstitution | D23: CP-10-4 | E23: ='CP-10-4'!B20 -> Not Started
A24: SA-9(5) | B24: External Information System Services | D24: SA-9-5 | E24: ='SA-9-5'!B20 -> Not Started
A25: SC-4 | B25: Information in Shared Resources | D25: SC-4 | E25: ='SC-4'!B20 -> Not Started
A26: SC-13 | B26: Cryptographic Protection | D26: SC-13 | E26: ='SC-13'!B20 -> Not Started
A27: SC-28 | B27: Protection of Information At Rest | D27: SC-28 | E27: ='SC-28'!B20 -> Not Started
A28: SC-28(1) | B28: Protection of Information At Rest | D28: SC-28-1 | E28: ='SC-28-1'!B20 -> Not Started
A29: SI-4(2) | B29: Information System Monitoring | D29: SI-4-2 | E29: ='SI-4-2'!B20 -> Not Started
A30: SI-6 | B30: Security Functional Verification | D30: SI-6 | E30: ='SI-6'!B20 -> Not Started
A32: Completion Metrics
A33: Total Controls | E33: =28 -> 28
A34: Not Started | E34: =COUNTIF(E3:E30,"Not Started") -> 28
A35: In Progress | E35: =COUNTIF(E3:E30,"In Progress") -> 0
A36: Evidence Provided | E36: =COUNTIF(E3:E30,"Evidence Provided") -> 0
A37: Under Review | E37: =COUNTIF(E3:E30,"Under Review") -> 0
A38: Passed | E38: =COUNTIF(E3:E30,"Passed") -> 0
A39: Failed | E39: =COUNTIF(E3:E30,"Failed") -> 0
A40: Accepted Exception | E40: =COUNTIF(E3:E30,"Accepted Exception") -> 0
A41: % Complete | E41: =IFERROR(COUNTIF(E3:E30,"Passed")/28,0) -> 0
A42: % Not Started | E42: =IFERROR(COUNTIF(E3:E30,"Not Started")/28,0) -> 1

Sheet TABLEAU_DE_BORD
A1: TABLEAU DE BORD — Suivi PBMM : Analytics
A2: ID Contrôle | B2: Nom du contrôle | C2: Outil principal | D2: Onglet | E2: Statut
A3: AU-2 | B3: Événements vérifiables | D3: AU-2 | E3: ='AU-2'!E20 -> Non commencé
A4: AU-3 | B4: Contenu des enregistrements de vérification | D4: AU-3 | E4: ='AU-3'!E20 -> Non commencé
A5: AU-3(1) | B5: Contenu des enregistrements de vérification | D5: AU-3-1 | E5: ='AU-3-1'!E20 -> Non commencé
A6: AU-5 | B6: Réponse aux échecs de traitement de vérification | D6: AU-5 | E6: ='AU-5'!E20 -> Non commencé
A7: AU-9(2) | B7: Protection des renseignements de vérification | D7: AU-9-2 | E7: ='AU-9-2'!E20 -> Non commencé
A8: AU-12 | B8: Génération des vérifications | D8: AU-12 | E8: ='AU-12'!E20 -> Non commencé
A9: CM-2(3) | B9: Configuration de base | D9: CM-2-3 | E9: ='CM-2-3'!E20 -> Non commencé
A10: CM-5(1) | B10: Restrictions d’accès pour les changements | D10: CM-5-1 | E10: ='CM-5-1'!E20 -> Non commencé
A11: CM-6 | B11: Paramètres de configuration | D11: CM-6 | E11: ='CM-6'!E20 -> Non commencé
A12: CM-7 | B12: Moindre fonctionnalité | D12: CM-7 | E12: ='CM-7'!E20 -> Non commencé
A13: CM-7(1) | B13: Moindre fonctionnalité | D13: CM-7-1 | E13: ='CM-7-1'!E20 -> Non commencé
A14: CP-6 | B14: Site de stockage auxiliaire | D14: CP-6 | E14: ='CP-6'!E20 -> Non commencé
A15: CP-6(2) | B15: Site de stockage auxiliaire | D15: CP-6-2 | E15: ='CP-6-2'!E20 -> Non commencé
A16: CP-7 | B16: Site de traitement auxiliaire | D16: CP-7 | E16: ='CP-7'!E20 -> Non commencé
A17: CP-7(4) | B17: Site de traitement auxiliaire | D17: CP-7-4 | E17: ='CP-7-4'!E20 -> Non commencé
A18: CP-9 | B18: Sauvegarde du système d’information | D18: CP-9 | E18: ='CP-9'!E20 -> Non commencé
A19: CP-9(1) | B19: Sauvegarde du système d’information | D19: CP-9-1 | E19: ='CP-9-1'!E20 -> Non commencé
A20: CP-9(2) | B20: Sauvegarde du système d’information | D20: CP-9-2 | E20: ='CP-9-2'!E20 -> Non commencé
A21: CP-9(5) | B21: Sauvegarde du système d’information | D21: CP-9-5 | E21: ='CP-9-5'!E20 -> Non commencé
A22: CP-10 | B22: Reprise et reconstitution du système d’information | D22: CP-10 | E22: ='CP-10'!E20 -> Non commencé
A23: CP-10(4) | B23: Reprise et reconstitution du système d’information | D23: CP-10-4 | E23: ='CP-10-4'!E20 -> Non commencé
A24: SA-9(5) | B24: Services de systèmes d’information externes | D24: SA-9-5 | E24: ='SA-9-5'!E20 -> Non commencé
A25: SC-4 | B25: Information dans les ressources partagées | D25: SC-4 | E25: ='SC-4'!E20 -> Non commencé
A26: SC-13 | B26: Protection cryptographique | D26: SC-13 | E26: ='SC-13'!E20 -> Non commencé
A27: SC-28 | B27: Protection de l’information inactive | D27: SC-28 | E27: ='SC-28'!E20 -> Non commencé
A28: SC-28(1) | B28: Protection de l’information inactive | D28: SC-28-1 | E28: ='SC-28-1'!E20 -> Non commencé
A29: SI-4(2) | B29: Surveillance du système d’information | D29: SI-4-2 | E29: ='SI-4-2'!E20 -> Non commencé
A30: SI-6 | B30: Vérification fonctionnelle de la sécurité | D30: SI-6 | E30: ='SI-6'!E20 -> Non commencé
A32: Métriques de complétude
A33: Nombre total de contrôles | E33: =28 -> 28
A34: Non commencés | E34: =COUNTIF(E3:E30,"Non commencé") -> 28
A35: En cours | E35: =COUNTIF(E3:E30,"En cours") -> 0
A36: Preuve fournie | E36: =COUNTIF(E3:E30,"Preuve fournie") -> 0
A37: En révision | E37: =COUNTIF(E3:E30,"En révision") -> 0
A38: Réussi | E38: =COUNTIF(E3:E30,"Réussi") -> 0
A39: Échec | E39: =COUNTIF(E3:E30,"Échec") -> 0
A40: Exception acceptée | E40: =COUNTIF(E3:E30,"Exception acceptée") -> 0
A41: % Complété | E41: =IFERROR(COUNTIF(E3:E30,"Réussi")/28,0) -> 0
A42: % Non commencés | E42: =IFERROR(COUNTIF(E3:E30,"Non commencé")/28,0) -> 1

Sheet AU-2
A1: Control AU-2 — Evidence Tracking | D1: Contrôle AU-2 — Suivi des preuves
A2: Control Information | D2: Informations du contrôle
A3: Control Identifier | B3: AU-2 | D3: Identifiant du contrôle | E3: AU-2
A4: Family | B4: Auditable Events | D4: Famille | E4: Événements vérifiables
A5: Profile | B5: CCCS Medium / PBMM Moderate | D5: Profil | E5: CCCS Moyen / PBMM Modéré
A6: Primary Evidence Tool | D6: Outil de preuve principal
A7: Contributing Tools | D7: Outils contributeurs
A8: Control Description | B8: (A) The organization determines that the information system is capable of auditing the following events: Successful and unsuccessful account logon events, account management events, object access, policy change, privilege functions, process tracking, and system events. For Web applications: all administrator activity, authentication checks, authorization checks, data deletions, data access, data changes, and permission changes. (B) The organization coordinates the security audit function with other organizational entities requiring audit-related information to enhance mutual support and to help guide the selection of auditable events. (C) The organization provides a rationale for why the auditable events are deemed to be adequate to support after-the-fact investigations of security incidents. (D) The organization determines what organizationally-defined audited events (a subset of the auditable events defined in AU-2 a.) and the frequency of (or situation requiring) auditing for each identified event. | D8: Description du contrôle | E8: (A) L’organisation détermine que le système d’information est capable de vérifier les événements suivants : événements d’ouverture de compte, réussis ou non, événements de gestion de compte, accès aux objets, changement de politique, fonctions de privilèges, suivi des processus et événements du système. Pour les applications Web : toutes les activités des administrateurs, les vérifications d’authentification, les vérifications d’autorisation, les suppressions de données, l’accès aux données, les changements de données et les changements d’autorisation. (B) L’organisation coordonne la fonction de vérification de la sécurité avec d’autres entités organisationnelles qui ont besoin de renseignements liés à la vérification pour améliorer le soutien mutuel et aider à orienter le choix des événements vérifiables. (C) L’organisation explique la raison pour laquelle les événements vérifiables sont jugés adéquats pour appuyer les enquêtes effectuées à la suite des incidents de sécurité. (D) L’organisation détermine les événements définis par l’organisation qui sont vérifiés (un sous-ensemble des événements vérifiables définis dans AU-2 a.) et la fréquence (ou la situation exigeant) des vérifications pour chaque événement identifié.
A9: Supplemental Guidance | B9: An event is any observable occurrence in an organizational information system. Organizations identify audit events as those events which are significant and relevant to the security of information systems and the environments in which those systems operate in order to meet specific and ongoing audit needs. Audit events can include, for example, password changes, failed logons, or failed accesses related to information systems, administrative privilege usage, or third-party credential usage. In determining the set of auditable events, organizations consider the auditing appropriate for each of the security controls to be implemented. To balance auditing requirements with other information system needs, this control also requires identifying that subset of auditable events that are audited at a given point in time. For example, organizations may determine that information systems must have the capability to log every file access both successful and unsuccessful, but not activate that capability except for specific circumstances due to the potential burden on system performance. Auditing requirements, including the need for auditable events, may be referenced in other security controls and control enhancements. Organizations also include auditable events that are required by applicable organizational policies, directives, and standards. Audit records can be generated at various levels of abstraction, including at the packet level as information traverses the network. Selecting the appropriate level of abstraction is a critical aspect of an audit capability and can facilitate the identification of root causes to problems. Organizations consider in the definition of auditable events, the auditing necessary to cover related events such as the steps in distributed, transaction-based processes (e.g., processes that are distributed across multiple organizations) and actions that occur in service-oriented architectures. The information system audits the following privileged user/process events at a minimum: (a) Successful and unsuccessful attempts to access, modify, or delete security objects (Security objects include audit data, system configuration files and file or users’ formal access permissions.) (b) Successful and unsuccessful logon attempts (c) Privileged activities or other system level access (see notes for AU-2 (4)) (d) Starting and ending time for user access to the system (e) Concurrent logons from different workstations (f) All program initiations (see notes for AU-2 (4)) In addition, the information system audits the following unprivileged user/process events at a minimum: (a) Successful and unsuccessful attempts to access, modify, or delete security objects (b) Successful and unsuccessful logon attempts (c) Starting and ending time for user access to the system (d) Concurrent logons from different workstations Related controls: AC-6, AC-17, AU-3, AU-12, MA-4, MP-2, MP-4, SI-4 | D9: Directives supplémentaires | E9: Un événement est toute occurrence observable dans un système d’information organisationnel. Les organisations désignent les événements vérifiables comme étant des événements importants et pertinents pour la sécurité des systèmes d’information et des environnements dans lesquels ces systèmes sont utilisés afin de répondre à des exigences de vérification particulières et continues. Les événements vérifiés peuvent comprendre, par exemple, les changements de mot de passe, les échecs d’ouverture de session ou les échecs accès liés aux systèmes d’information, l’utilisation des privilèges administratifs ou l’utilisation de justificatifs d’identité par des tiers. Lorsqu’elles déterminent l’ensemble des événements vérifiables, les organisations considèrent que la vérification est appropriée pour chacun des contrôles de sécurité à mettre en œuvre. Pour assurer l’équilibre entre les exigences en matière de vérification et les autres besoins du système d’information, ce contrôle exige également de déterminer le sous-ensemble d’événements vérifiables qui sont vérifiés à un moment donné. Par exemple, les organisations peuvent déterminer que les systèmes d’information doivent avoir la capacité d’enregistrer chaque accès aux fichiers, qu’il soit réussi ou non, mais n’activeront cette capacité que dans des circonstances particulières en raison du fardeau potentiel sur le rendement du système. Les exigences en matière de vérification, y compris la nécessité de déterminer des événements vérifiables, peuvent être mentionnées dans d’autres contrôles et améliorations des contrôles de sécurité. Les organisations incluent également les événements vérifiables qui sont exigés par les politiques, les directives et les normes organisationnelles applicables. Les enregistrements de vérification peuvent être générés à divers niveaux d’abstraction, y compris au niveau des paquets, à mesure que l’information traverse le réseau. Le choix du niveau d’abstraction approprié est un aspect essentiel d’une capacité de vérification et peut faciliter l’identification des causes profondes des problèmes. Dans la définition des événements vérifiables, les organisations prennent en compte la vérification nécessaire pour couvrir les événements connexes, comme les étapes des processus distribués, fondés sur les transactions (p. ex., les processus qui sont répartis entre de multiples organisations) et les actions qui ont lieu dans les architectures orientées service. Le système d’information vérifie au minimum les événements suivants liés aux utilisateurs/processus privilégiés : (a) Tentatives réussies et infructueuses d’accéder aux objets de sécurité, de les modifier ou de les supprimer (les objets de sécurité comprennent les données de vérification, les fichiers de configuration de système et les autorisations d’accès officielles des utilisateurs). (b) Tentatives d’ouverture de session réussies et infructueuses (c) Activités privilégiées ou autre accès au niveau du système (voir les notes pour AU-2 [4]) (d) Heures de début et de fin de l’accès des utilisateurs au système (e) Ouvertures de session simultanées à partir de différents postes de travail (f) Tous les lancements de programmes (voir les notes pour AU-2 [4]) De plus, le système d’information vérifie au minimum les événements suivants liés aux utilisateurs/processus non privilégiés : (a) Tentatives réussies et infructueuses d’accès, de modification ou de suppression d’objets de sécurité (b) Tentatives d’ouverture de session réussies et infructueuses (c) Heures de début et de fin de l’accès de l’utilisateur au système (d) Ouvertures de session simultanées à partir de différents postes de travail Contrôles connexes : AC-6, AC-17, AU-3, AU-12, MA-4, MP-2, MP-4, SI-4
A10: Test Case | D10: Cas de test
A11: Test | B11: TEST-AU-2 | D11: Test | E11: TEST-AU-2
A12: Requirement ID | B12: AU-2 | D12: ID Exigence | E12: AU-2
A13: Component | D13: Composant
A14: Requirement | D14: Exigence
A15: Contextual Design Description | D15: Description contextuelle du design
A16: Evidence Provided | D16: Preuve fournie
A17: Preparer Sign Off (Initials, Date) | D17: Signataire préparateur (Initiales, Date)
A18: Owner Sign Off (Initials, Date) | D18: Signataire propriétaire (Initiales, Date)
A19: Assessor Sign Off (Initials, Date) | D19: Signataire évaluateur (Initiales, Date)
A20: Status | B20: Not Started | D20: Statut | E20: Non commencé
A21: Comments | D21: Commentaires

Sheet AU-3
A1: Control AU-3 — Evidence Tracking | D1: Contrôle AU-3 — Suivi des preuves
A2: Control Information | D2: Informations du contrôle
A3: Control Identifier | B3: AU-3 | D3: Identifiant du contrôle | E3: AU-3
A4: Family | B4: Content of Audit Records | D4: Famille | E4: Contenu des enregistrements de vérification
A5: Profile | B5: CCCS Medium / PBMM Moderate | D5: Profil | E5: CCCS Moyen / PBMM Modéré
A6: Primary Evidence Tool | D6: Outil de preuve principal
A7: Contributing Tools | D7: Outils contributeurs
A8: Control Description | B8: (A) The information system generates audit records containing information that establishes what type of event occurred, when the event occurred, where the event occurred, the source of the event, the outcome of the event, and the identity of any individuals or subjects associated with the event. | D8: Description du contrôle | E8: (A) Le système d’information génère des enregistrements de vérification qui contiennent les renseignements permettant d’établir le type d’événement qui a eu lieu, le moment et l’endroit où l’événement a eu lieu, la source de l’événement, le résultat de l’événement, ainsi que l’identité de toute personne ou de tout sujet associé à l’événement.
A9: Supplemental Guidance | B9: Audit record content that may be necessary to satisfy the requirement of this control, includes, for example, time stamps, source and destination addresses, user/process identifiers, event descriptions, success/fail indications, filenames involved, and access control or flow control rules invoked. Event outcomes can include indicators of event success or failure and event-specific results (e.g., the security state of the information system after the event occurred). Related controls: AU-2, AU-8, AU-12, SI-11 | D9: Directives supplémentaires | E9: Le contenu des enregistrements de vérification qui peut être nécessaire pour satisfaire à l’exigence de ce contrôle comprend, par exemple, les estampilles temporelles, les adresses de source et de destination, les identifiants d’utilisateurs ou de processus, les descriptions d’événements, les indications de réussite ou d’échec, les noms des fichiers en cause et les règles de contrôle d’accès ou de flux invoquées. Les résultats de l’événement peuvent comprendre des indicateurs de réussite ou d’échec de l’événement et des résultats propres à l’événement (p. ex., l’état de sécurité du système d’information après l’événement). Contrôles connexes : AU-2, AU-8, AU-12, SI-11
A10: Test Case | D10: Cas de test
A11: Test | B11: TEST-AU-3 | D11: Test | E11: TEST-AU-3
A12: Requirement ID | B12: AU-3 | D12: ID Exigence | E12: AU-3
A13: Component | D13: Composant
A14: Requirement | D14: Exigence
A15: Contextual Design Description | D15: Description contextuelle du design
A16: Evidence Provided | D16: Preuve fournie
A17: Preparer Sign Off (Initials, Date) | D17: Signataire préparateur (Initiales, Date)
A18: Owner Sign Off (Initials, Date) | D18: Signataire propriétaire (Initiales, Date)
A19: Assessor Sign Off (Initials, Date) | D19: Signataire évaluateur (Initiales, Date)
A20: Status | B20: Not Started | D20: Statut | E20: Non commencé
A21: Comments | D21: Commentaires

Sheet AU-3-1
A1: Control AU-3(1) — Evidence Tracking | D1: Contrôle AU-3(1) — Suivi des preuves
A2: Control Information | D2: Informations du contrôle
A3: Control Identifier | B3: AU-3(1) | D3: Identifiant du contrôle | E3: AU-3(1)
A4: Family | B4: Content of Audit Records | D4: Famille | E4: Contenu des enregistrements de vérification
A5: Profile | B5: CCCS Medium / PBMM Moderate | D5: Profil | E5: CCCS Moyen / PBMM Modéré
A6: Primary Evidence Tool | D6: Outil de preuve principal
A7: Contributing Tools | D7: Outils contributeurs
A8: Control Description | B8: CONTENT OF AUDIT RECORDS | ADDITIONAL AUDIT INFORMATION The information system generates audit records containing the following additional information: session, connection, transaction, or activity duration; for client-server transactions, the number of bytes received and bytes sent; additional informational messages to diagnose or identify the event; characteristics that describe or identify the object or resource being acted upon. | D8: Description du contrôle | E8: CONTENU DES ENREGISTREMENTS DE VÉRIFICATION | RENSEIGNEMENTS DE VÉRIFICATION SUPPLÉMENTAIRES Le système d’information génère des enregistrements de vérification contenant les renseignements supplémentaires suivants : la durée de la session, de la connexion, de la transaction ou de l’activité; pour les transactions client-serveur, le nombre d’octets reçus et d’octets envoyés; des messages d’information supplémentaires pour diagnostiquer ou identifier l’événement; les caractéristiques qui décrivent ou identifient l’objet ou la ressource concernés.
A9: Supplemental Guidance | B9: Detailed information that organizations may consider in audit records includes, for example, full text recording of privileged commands or the individual identities of group account users. Organizations consider limiting the additional audit information to only that information explicitly needed for specific audit requirements. This facilitates the use of audit trails and audit logs by not including information that could potentially be misleading or could make it more difficult to locate information of interest. Additional guidance for enhancement (1): Audit events should always be capable of being associated with an individual identity. Associating audit events with a group or role is insufficient. | D9: Directives supplémentaires | E9: Les renseignements détaillés dont les organisations peuvent tenir compte dans les enregistrements de vérification comprennent, par exemple, l’enregistrement en texte intégral des commandes privilégiées ou les identités individuelles des utilisateurs de comptes de groupe. Les organisations devraient envisager de limiter les renseignements de vérification supplémentaires aux seuls renseignements explicitement nécessaires pour répondre à des exigences de vérification particulières. Cela facilitera l’utilisation des pistes de vérification et des journaux de vérification en n’incluant pas les renseignements qui pourraient être trompeurs ou rendre plus difficile la recherche de renseignements utiles. Conseils supplémentaires pour l’amélioration (1) : Les événements vérifiés devraient toujours pouvoir être associés à une identité individuelle. Associer des événements vérifiés à un groupe ou à un rôle est insuffisant.
A10: Test Case | D10: Cas de test
A11: Test | B11: TEST-AU-3(1) | D11: Test | E11: TEST-AU-3(1)
A12: Requirement ID | B12: AU-3(1) | D12: ID Exigence | E12: AU-3(1)
A13: Component | D13: Composant
A14: Requirement | D14: Exigence
A15: Contextual Design Description | D15: Description contextuelle du design
A16: Evidence Provided | D16: Preuve fournie
A17: Preparer Sign Off (Initials, Date) | D17: Signataire préparateur (Initiales, Date)
A18: Owner Sign Off (Initials, Date) | D18: Signataire propriétaire (Initiales, Date)
A19: Assessor Sign Off (Initials, Date) | D19: Signataire évaluateur (Initiales, Date)
A20: Status | B20: Not Started | D20: Statut | E20: Non commencé
A21: Comments | D21: Commentaires

Sheet AU-5
A1: Control AU-5 — Evidence Tracking | D1: Contrôle AU-5 — Suivi des preuves
A2: Control Information | D2: Informations du contrôle
A3: Control Identifier | B3: AU-5 | D3: Identifiant du contrôle | E3: AU-5
A4: Family | B4: Response To Audit Processing Failures | D4: Famille | E4: Réponse aux échecs de traitement de vérification
A5: Profile | B5: CCCS Medium / PBMM Moderate | D5: Profil | E5: CCCS Moyen / PBMM Modéré
A6: Primary Evidence Tool | D6: Outil de preuve principal
A7: Contributing Tools | D7: Outils contributeurs
A8: Control Description | B8: (A) The information system alerts organization-defined personnel or roles in the event of an audit processing failure; and (B) The information system overwrites the oldest audit records. | D8: Description du contrôle | E8: (A) Le système d’information alerte le personnel ou les rôles définis par l’organisation en cas d’échec de traitement de vérification; (B) Le système d’information écrase les enregistrements de vérification les plus anciens.
A9: Supplemental Guidance | B9: Audit processing failures include, for example, software/hardware errors, failures in the audit capturing mechanisms, and audit storage capacity being reached or exceeded. Organizations may choose to define additional actions for different audit processing failures (e.g., by type, by location, by severity, or a combination of such factors). This control applies to each audit data storage repository (i.e., distinct information system component where audit records are stored), the total audit storage capacity of organizations (i.e., all audit data storage repositories combined), or both. Related controls: AU-4, SI-12 | D9: Directives supplémentaires | E9: Les échecs de traitement de vérification comprennent, par exemple, les erreurs de logiciel ou de matériel, les défaillances des mécanismes de saisie des vérifications et la capacité de stockage atteinte ou dépassée pour les vérifications. Les organisations peuvent choisir de définir des mesures supplémentaires pour différents échecs de traitement de vérification (p. ex., par type, par emplacement, par gravité ou une combinaison de ces facteurs). Ce contrôle s’applique à chaque répertoire de stockage des données de vérification (c.-à -d. à chaque composant distinct du système d’information dans lequel les enregistrements de vérification sont conservés), à la capacité totale de stockage des vérifications des organisations (c.-à-d. tous les répertoires de stockage des données de vérification combinés), ou aux deux. Contrôles connexes : AU-4, SI-12
A10: Test Case | D10: Cas de test
A11: Test | B11: TEST-AU-5 | D11: Test | E11: TEST-AU-5
A12: Requirement ID | B12: AU-5 | D12: ID Exigence | E12: AU-5
A13: Component | D13: Composant
A14: Requirement | D14: Exigence
A15: Contextual Design Description | D15: Description contextuelle du design
A16: Evidence Provided | D16: Preuve fournie
A17: Preparer Sign Off (Initials, Date) | D17: Signataire préparateur (Initiales, Date)
A18: Owner Sign Off (Initials, Date) | D18: Signataire propriétaire (Initiales, Date)
A19: Assessor Sign Off (Initials, Date) | D19: Signataire évaluateur (Initiales, Date)
A20: Status | B20: Not Started | D20: Statut | E20: Non commencé
A21: Comments | D21: Commentaires

Sheet AU-9-2
A1: Control AU-9(2) — Evidence Tracking | D1: Contrôle AU-9(2) — Suivi des preuves
A2: Control Information | D2: Informations du contrôle
A3: Control Identifier | B3: AU-9(2) | D3: Identifiant du contrôle | E3: AU-9(2)
A4: Family | B4: Protection of Audit Information | D4: Famille | E4: Protection des renseignements de vérification
A5: Profile | B5: CCCS Medium / PBMM Moderate | D5: Profil | E5: CCCS Moyen / PBMM Modéré
A6: Primary Evidence Tool | D6: Outil de preuve principal
A7: Contributing Tools | D7: Outils contributeurs
A8: Control Description | B8: PROTECTION OF AUDIT INFORMATION | AUDIT BACKUP ON SEPARATE PHYSICAL SYSTEMS / COMPONENTS The information system backs up audit records at least weekly onto a physically different system or system component than the system or component being audited. | D8: Description du contrôle | E8: PROTECTION DES RENSEIGNEMENTS DE VÉRIFICATION | SAUVEGARDE DES VÉRIFICATIONS SUR DES SYSTÈMES/COMPOSANTS PHYSIQUES SÉPARÉS Le système d’information sauvegarde les enregistrements de vérification au moins une fois par semaine sur un système ou un composant système physiquement différent du système ou du composant faisant l’objet de la vérification.
A9: Supplemental Guidance | B9: This control enhancement helps to ensure that a compromise of the information system being audited does not also result in a compromise of the audit records. Related controls: AU-4, AU-5, AU-11. | D9: Directives supplémentaires | E9: Cette amélioration permet de s’assurer qu’une compromission du système d’information faisant l’objet d’une vérification n’entraîne pas également la compromission des enregistrements de vérification. Contrôles connexes : AU-4, AU-5, AU-11.
A10: Test Case | D10: Cas de test
A11: Test | B11: TEST-AU-9(2) | D11: Test | E11: TEST-AU-9(2)
A12: Requirement ID | B12: AU-9(2) | D12: ID Exigence | E12: AU-9(2)
A13: Component | D13: Composant
A14: Requirement | D14: Exigence
A15: Contextual Design Description | D15: Description contextuelle du design
A16: Evidence Provided | D16: Preuve fournie
A17: Preparer Sign Off (Initials, Date) | D17: Signataire préparateur (Initiales, Date)
A18: Owner Sign Off (Initials, Date) | D18: Signataire propriétaire (Initiales, Date)
A19: Assessor Sign Off (Initials, Date) | D19: Signataire évaluateur (Initiales, Date)
A20: Status | B20: Not Started | D20: Statut | E20: Non commencé
A21: Comments | D21: Commentaires

Sheet AU-12
A1: Control AU-12 — Evidence Tracking | D1: Contrôle AU-12 — Suivi des preuves
A2: Control Information | D2: Informations du contrôle
A3: Control Identifier | B3: AU-12 | D3: Identifiant du contrôle | E3: AU-12
A4: Family | B4: Audit Generation | D4: Famille | E4: Génération des vérifications
A5: Profile | B5: CCCS Medium / PBMM Moderate | D5: Profil | E5: CCCS Moyen / PBMM Modéré
A6: Primary Evidence Tool | D6: Outil de preuve principal
A7: Contributing Tools | D7: Outils contributeurs
A8: Control Description | B8: (A) The information system provides audit record generation capability for the auditable events defined in AU-2 a. of all information system and network components where audit capability is deployed/available. (B) The information system allows organization-defined personnel or roles to select which auditable events are to be audited by specific components of the information system. (C) The information system generates audit records for the events defined in AU-2 d. with the content defined in AU-3. | D8: Description du contrôle | E8: (A) Le système d’information offre une capacité de génération d’enregistrements de vérification pour les événements vérifiables définis dans AU-2 a. de tous les composants du système d’information et du réseau où la capacité de vérification est déployée/disponible. (B) Le système d’information permet au personnel ou aux rôles définis par l’organisation de choisir les événements vérifiables qui doivent être vérifiés par des composants précis du système d’information. (C) Le système d’information génère des enregistrements de vérification pour les événements définis dans AU-2 d. avec le contenu défini dans AU-3.
A9: Supplemental Guidance | B9: Audit records can be generated from many different information system components. The list of audited events is the set of events for which audits are to be generated. These events are typically a subset of all events for which the information system is capable of generating audit records. Related controls: AC-3, AU-2, AU-3, AU-6, AU-7 | D9: Directives supplémentaires | E9: Des enregistrements de vérification peuvent être générés à partir de nombreux composants du système d’information. La liste des événements vérifiés est l’ensemble des événements pour lesquels des vérifications doivent être produites. Ces événements sont habituellement un sous-ensemble de tous les événements pour lesquels le système d’information peut générer des enregistrements de vérification. Contrôles connexes : AC-3, AU-2, AU-3, AU-6, AU-7
A10: Test Case | D10: Cas de test
A11: Test | B11: TEST-AU-12 | D11: Test | E11: TEST-AU-12
A12: Requirement ID | B12: AU-12 | D12: ID Exigence | E12: AU-12
A13: Component | D13: Composant
A14: Requirement | D14: Exigence
A15: Contextual Design Description | D15: Description contextuelle du design
A16: Evidence Provided | D16: Preuve fournie
A17: Preparer Sign Off (Initials, Date) | D17: Signataire préparateur (Initiales, Date)
A18: Owner Sign Off (Initials, Date) | D18: Signataire propriétaire (Initiales, Date)
A19: Assessor Sign Off (Initials, Date) | D19: Signataire évaluateur (Initiales, Date)
A20: Status | B20: Not Started | D20: Statut | E20: Non commencé
A21: Comments | D21: Commentaires

Sheet CM-2-3
A1: Control CM-2(3) — Evidence Tracking | D1: Contrôle CM-2(3) — Suivi des preuves
A2: Control Information | D2: Informations du contrôle
A3: Control Identifier | B3: CM-2(3) | D3: Identifiant du contrôle | E3: CM-2(3)
A4: Family | B4: Baseline Configuration | D4: Famille | E4: Configuration de base
A5: Profile | B5: CCCS Medium / PBMM Moderate | D5: Profil | E5: CCCS Moyen / PBMM Modéré
A6: Primary Evidence Tool | D6: Outil de preuve principal
A7: Contributing Tools | D7: Outils contributeurs
A8: Control Description | B8: BASELINE CONFIGURATION | RETENTION OF PREVIOUS CONFIGURATIONS The organization retains the two most recent precious versions of baseline configurations of the information system to support rollback. | D8: Description du contrôle | E8: CONFIGURATION DE BASE | CONSERVATION DES CONFIGURATIONS PRÉCÉDENTES L’organisation conserve les deux versions utiles les plus récentes des configurations de base du système d’information pour la prise en charge des reprises.
A9: Supplemental Guidance | B9: Retaining previous versions of baseline configurations to support rollback may include, for example, hardware, software, firmware, configuration files, and configuration records. | D9: Directives supplémentaires | E9: La conservation des versions antérieures des configurations de base pour la prise en charge des reprises peut comprendre, par exemple, le matériel, les logiciels, les micrologiciels, les fichiers de configuration et les enregistrements de configuration.
A10: Test Case | D10: Cas de test
A11: Test | B11: TEST-CM-2(3) | D11: Test | E11: TEST-CM-2(3)
A12: Requirement ID | B12: CM-2(3) | D12: ID Exigence | E12: CM-2(3)
A13: Component | D13: Composant
A14: Requirement | D14: Exigence
A15: Contextual Design Description | D15: Description contextuelle du design
A16: Evidence Provided | D16: Preuve fournie
A17: Preparer Sign Off (Initials, Date) | D17: Signataire préparateur (Initiales, Date)
A18: Owner Sign Off (Initials, Date) | D18: Signataire propriétaire (Initiales, Date)
A19: Assessor Sign Off (Initials, Date) | D19: Signataire évaluateur (Initiales, Date)
A20: Status | B20: Not Started | D20: Statut | E20: Non commencé
A21: Comments | D21: Commentaires

Sheet CM-5-1
A1: Control CM-5(1) — Evidence Tracking | D1: Contrôle CM-5(1) — Suivi des preuves
A2: Control Information | D2: Informations du contrôle
A3: Control Identifier | B3: CM-5(1) | D3: Identifiant du contrôle | E3: CM-5(1)
A4: Family | B4: Access Restrictions for Change | D4: Famille | E4: Restrictions d’accès pour les changements
A5: Profile | B5: CCCS Medium / PBMM Moderate | D5: Profil | E5: CCCS Moyen / PBMM Modéré
A6: Primary Evidence Tool | D6: Outil de preuve principal
A7: Contributing Tools | D7: Outils contributeurs
A8: Control Description | B8: ACCESS RESTRICTIONS FOR CHANGE | AUTOMATED ACCESS ENFORCEMENT / AUDITING The information system enforces access restrictions and supports auditing of the enforcement actions. | D8: Description du contrôle | E8: RESTRICTIONS D’ACCÈS POUR LES CHANGEMENTS | CONTRÔLE AUTOMATISÉ DE L’ACCÈS/VÉRIFICATION Le système d’information applique les restrictions d’accès et prend en charge la vérification des contrôles appliqués.
A9: Supplemental Guidance | B9: Related controls: AU-2, AU-12, AU-6, CM-3, and CM-6. | D9: Directives supplémentaires | E9: Contrôles connexes : AU-2, AU-12, AU-6, CM-3 et CM-6.
A10: Test Case | D10: Cas de test
A11: Test | B11: TEST-CM-5(1) | D11: Test | E11: TEST-CM-5(1)
A12: Requirement ID | B12: CM-5(1) | D12: ID Exigence | E12: CM-5(1)
A13: Component | D13: Composant
A14: Requirement | D14: Exigence
A15: Contextual Design Description | D15: Description contextuelle du design
A16: Evidence Provided | D16: Preuve fournie
A17: Preparer Sign Off (Initials, Date) | D17: Signataire préparateur (Initiales, Date)
A18: Owner Sign Off (Initials, Date) | D18: Signataire propriétaire (Initiales, Date)
A19: Assessor Sign Off (Initials, Date) | D19: Signataire évaluateur (Initiales, Date)
A20: Status | B20: Not Started | D20: Statut | E20: Non commencé
A21: Comments | D21: Commentaires

Sheet CM-6
A1: Control CM-6 — Evidence Tracking | D1: Contrôle CM-6 — Suivi des preuves
A2: Control Information | D2: Informations du contrôle
A3: Control Identifier | B3: CM-6 | D3: Identifiant du contrôle | E3: CM-6
A4: Family | B4: Configuration Settings | D4: Famille | E4: Paramètres de configuration
A5: Profile | B5: CCCS Medium / PBMM Moderate | D5: Profil | E5: CCCS Moyen / PBMM Modéré
A6: Primary Evidence Tool | D6: Outil de preuve principal
A7: Contributing Tools | D7: Outils contributeurs
A8: Control Description | B8: (A) The organization establishes and documents configuration settings for information technology products employed within the information system using checklists from one or more of the following Center for Internet Security (CIS), National Institute of Standards and Technology (NIST), Defense Information Systems Agency (DISA) that reflect the most restrictive mode consistent with operational requirements. (B) The organization implements the configuration settings. (C) The organization identifies, documents, and approves any deviations from established configuration settings for any configurable infomation system components. (D) The organization monitors and controls changes to the configuration settings in accordance with organizational policies and procedures. | D8: Description du contrôle | E8: (A) L’organisation établit et documente les paramètres de configuration des produits de technologie de l’information utilisés dans le système d’information à l’aide de listes de vérification provenant d’un ou de plusieurs des éléments suivants : Center for Internet Security (CIS), National Institute of Standards and Technology (NIST), Defense Information Systems Agency (DISA), qui reflètent le mode le plus restrictif conformément aux exigences opérationnelles. (B) L’organisation met en œuvre les paramètres de configuration. (C) L’organisation identifie, documente et approuve tout écart par rapport aux paramètres de configuration établis pour les composants configurables du système d’information. (D) L’organisation surveille et contrôle les changements apportés aux paramètres de configuration conformément aux politiques et aux procédures de l’organisation.
A9: Supplemental Guidance | B9: Configuration settings are the set of parameters that can be changed in hardware, software, or firmware components of the information system that affect the security posture and/or functionality of the system. Information technology products for which security-related configuration settings can be defined include, for example, mainframe computers, servers (e.g., database, electronic mail, authentication, web, proxy, file, domain name), workstations, input/output devices (e.g., scanners, copiers, and printers), network components (e.g., firewalls, routers, gateways, voice and data switches, wireless access points, network appliances, sensors), operating systems, middleware, and applications. Security-related parameters are those parameters impacting the security state of information systems including the parameters required to satisfy other security control requirements. Security-related parameters include, for example: (i) registry settings; (ii) account, file, directory permission settings; and (iii) settings for functions, ports, protocols, services, and remote connections. Organizations establish organization-wide configuration settings and subsequently derive specific settings for information systems. The established settings become part of the systems configuration baselineCommon secure configurations (also referred to as security configuration checklists, lockdown and hardening guides, security reference guides, security technical implementation guides (STIG)) provide recognized, standardized, and established benchmarks that stipulate secure configuration settings for specific information technology platforms/products and instructions for configuring those information system components to meet operational requirements. Common secure configurations can be developed by a variety of organizations including, for example, information technology product developers, manufacturers, vendors, consortia, academia, industry, federal government organizations, and others in the public and private sectors. The Security Content Automation Protocol (SCAP) and the defined standards within the protocol (e.g., Common Configuration Enumeration) provide an effective method to uniquely identify, track, and control configuration settings. Related controls: AC-19, CM-2, CM-3, CM-7, SI-4. | D9: Directives supplémentaires | E9: Les paramètres de configuration sont l’ensemble de paramètres qui peuvent être modifiés dans les composants matériels, logiciels ou micrologiciels du système d’information et qui ont une incidence sur la posture de sécurité ou la fonctionnalité du système. Les produits de technologie de l’information pour lesquels les paramètres de configuration liés à la sécurité peuvent être définis comprennent, par exemple, les ordinateurs centraux, les serveurs (p. ex., base de données, courrier électronique, authentification, Web, mandataire, fichiers, noms de domaine), les postes de travail, les périphériques d’entrée et de sortie (p. ex., numériseurs, photocopieurs et imprimantes), les composants de réseau (p. ex., pare-feu, routeurs, passerelles, commutateurs de voix et de données, points d’accès sans fil, outils de réseau, capteurs), les systèmes d’exploitation, les intergiciels et les applications. Les paramètres liés à la sécurité sont les paramètres qui influent sur l’état de sécurité des systèmes d’information, y compris les paramètres requis pour satisfaire à d’autres exigences de contrôle de sécurité. Les paramètres liés à la sécurité comprennent, par exemple : (i) les paramètres des registres; (ii) les paramètres de comptes, de fichiers, d’autorisation de répertoires; (iii) les paramètres des fonctions, des ports, des protocoles, des services et des connexions à distance. Les organisations établissent les paramètres de configuration à l’échelle de l’organisation et en déduisent ensuite les paramètres particuliers pour les systèmes d’information. Les paramètres établis font partie des configurations de base des systèmes Les configurations sécurisées communes (aussi appelées listes de vérification de la configuration de sécurité, guides de verrouillage et de renforcement, guides de référence de sécurité, guides de mise en œuvre technique de la sécurité [STIG]) fournissent des repères reconnus, normalisés et établis qui stipulent les paramètres de configuration sécurisée pour des plateformes/produits de technologie de l’information particuliers et des instructions pour configurer ces composants de système d’information de manière à répondre aux exigences opérationnelles. Les configurations sécurisées communes peuvent être mises au point par diverses organisations, y compris, par exemple, les concepteurs de produits de technologie de l’information, les fabricants, les fournisseurs, les consortiums, le milieu universitaire, l’industrie, les organisations du gouvernement fédéral et d’autres intervenants des secteurs public et privé. Le protocole d’automatisation du contenu de sécurité SCAP (Security Content Automation Protocol) et les normes définies dans le protocole (p. ex., Common Configuration Enumeration) constituent une méthode efficace pour déterminer, suivre et contrôler de façon unique les paramètres de configuration. Contrôles connexes : AC-19, CM-2, CM-3, CM-7, SI-4.
A10: Test Case | D10: Cas de test
A11: Test | B11: TEST-CM-6 | D11: Test | E11: TEST-CM-6
A12: Requirement ID | B12: CM-6 | D12: ID Exigence | E12: CM-6
A13: Component | D13: Composant
A14: Requirement | D14: Exigence
A15: Contextual Design Description | D15: Description contextuelle du design
A16: Evidence Provided | D16: Preuve fournie
A17: Preparer Sign Off (Initials, Date) | D17: Signataire préparateur (Initiales, Date)
A18: Owner Sign Off (Initials, Date) | D18: Signataire propriétaire (Initiales, Date)
A19: Assessor Sign Off (Initials, Date) | D19: Signataire évaluateur (Initiales, Date)
A20: Status | B20: Not Started | D20: Statut | E20: Non commencé
A21: Comments | D21: Commentaires

Sheet CM-7
A1: Control CM-7 — Evidence Tracking | D1: Contrôle CM-7 — Suivi des preuves
A2: Control Information | D2: Informations du contrôle
A3: Control Identifier | B3: CM-7 | D3: Identifiant du contrôle | E3: CM-7
A4: Family | B4: Least Functionality | D4: Famille | E4: Moindre fonctionnalité
A5: Profile | B5: CCCS Medium / PBMM Moderate | D5: Profil | E5: CCCS Moyen / PBMM Modéré
A6: Primary Evidence Tool | D6: Outil de preuve principal
A7: Contributing Tools | D7: Outils contributeurs
A8: Control Description | B8: (A) The organization configures the information system to provide only essential capabilities. (B) The organization prohibits or restricts the use of identified functions, ports, protocols, and/or services following one or more standards from Center for Internet Security (CIS), National Institute of Standards and Technology (NIST), or Defense Information Systems Agency (DISA). | D8: Description du contrôle | E8: (A) L’organisation configure le système d’information pour n’offrir que les capacités essentielles. (B) L’organisation interdit ou restreint l’utilisation de fonctions, de ports, de protocoles et/ou de services identifiés en respectant une ou plusieurs normes du Center for Internet Security (CIS), du National Institute of Standards and Technology (NIST) ou de la Defense Information Systems Agency (DISA).
A9: Supplemental Guidance | B9: Information systems can provide a wide variety of functions and services. Some of the functions and services, provided by default, may not be necessary to support essential organizational operations (e.g., key missions, functions). Additionally, it is sometimes convenient to provide multiple services from single information system components, but doing so increases risk over limiting the services provided by any one component. Where feasible, organizations limit component functionality to a single function per device (e.g., email servers or web servers, but not both). Organizations review functions and services provided by information systems or individual components of information systems, to determine which functions and services are candidates for elimination (e.g., Voice over Internet Protocol (VoIP), Instant Messaging, auto-execute, and file sharing). Organizations consider disabling unused or unnecessary physical and logical ports/protocols (e.g., USB, FTP, IPv6, HTTP) on information systems to prevent unauthorized connection of devices, unauthorized transfer of information, or unauthorized tunnelling. Organizations can utilize network scanning tools, intrusion detection and prevention systems, and end-point protections such as firewalls and host-based intrusion detection systems to identify and prevent the use of prohibited functions, ports, protocols, and services. Related controls: AC-6, CM-2, RA-5, SA-5, SC-7 | D9: Directives supplémentaires | E9: Les systèmes d’information peuvent offrir une grande variété de fonctions et de services. Certaines fonctions et certains services, fournis par défaut, peuvent ne pas être nécessaires au soutien des opérations essentielles de l’organisation (p. ex., missions et fonctions clés). De plus, il est parfois pratique de fournir plusieurs services à partir de composants uniques du système d’information, mais cela augmente le risque de limiter les services fournis par un seul composant. Dans la mesure du possible, les organisations limitent la fonctionnalité des composants à une seule fonction par dispositif (p. ex., serveurs de courriel ou serveurs Web, mais pas les deux). Les organisations examinent les fonctions et les services fournis par les systèmes d’information ou les composants individuels des systèmes d’information afin de déterminer quelles fonctions et quels services peuvent être éliminés (p. ex., voix sur protocole Internet [VoIP], messagerie instantanée, auto-exécution et partage de fichiers). Les organisations envisagent de désactiver les ports/protocoles physiques et logiques inutilisés ou inutiles (p. ex., USB, FTP, IPv6, HTTP) sur les systèmes d’information afin de prévenir la connexion non autorisée d’appareils, le transfert non autorisé d’information ou la tunnellisation non autorisée. Les organisations peuvent utiliser des outils de balayage de réseau, des systèmes de détection et de prévention des intrusions et des mesures de protection d’extrémité comme des pare-feu et des systèmes de détection des intrusions basés sur l’hôte, pour identifier et prévenir l’utilisation de fonctions, de ports, de protocoles et de services interdits. Contrôles connexes : AC-6, CM-2, RA-5, SA-5, SC-7
A10: Test Case | D10: Cas de test
A11: Test | B11: TEST-CM-7 | D11: Test | E11: TEST-CM-7
A12: Requirement ID | B12: CM-7 | D12: ID Exigence | E12: CM-7
A13: Component | D13: Composant
A14: Requirement | D14: Exigence
A15: Contextual Design Description | D15: Description contextuelle du design
A16: Evidence Provided | D16: Preuve fournie
A17: Preparer Sign Off (Initials, Date) | D17: Signataire préparateur (Initiales, Date)
A18: Owner Sign Off (Initials, Date) | D18: Signataire propriétaire (Initiales, Date)
A19: Assessor Sign Off (Initials, Date) | D19: Signataire évaluateur (Initiales, Date)
A20: Status | B20: Not Started | D20: Statut | E20: Non commencé
A21: Comments | D21: Commentaires

Sheet CM-7-1
A1: Control CM-7(1) — Evidence Tracking | D1: Contrôle CM-7(1) — Suivi des preuves
A2: Control Information | D2: Informations du contrôle
A3: Control Identifier | B3: CM-7(1) | D3: Identifiant du contrôle | E3: CM-7(1)
A4: Family | B4: Least Functionality | D4: Famille | E4: Moindre fonctionnalité
A5: Profile | B5: CCCS Medium / PBMM Moderate | D5: Profil | E5: CCCS Moyen / PBMM Modéré
A6: Primary Evidence Tool | D6: Outil de preuve principal
A7: Contributing Tools | D7: Outils contributeurs
A8: Control Description | B8: LEAST FUNCTIONALITY | PERIODIC REVIEW The organization reviews the information system at least annually to identify unnecessary and/or non-secure functions, ports, protocols, and services; and The organization disables all functions, ports, protocols, and services within the information system deemed to be unnecessary and/or nonsecure. | D8: Description du contrôle | E8: MOINDRE FONCTIONNALITÉ | EXAMEN PÉRIODIQUE L’organisation revoit le système d’information au moins une fois par année afin de repérer les fonctions, les ports, les protocoles et les services inutiles ou non sécurisés; L’organisation désactive toutes les fonctions, tous les ports, tous les protocoles et tous les services du système d’information jugés inutiles ou non sécurisés.
A9: Supplemental Guidance | B9: The organization can either make a determination of the relative security of the function, port, protocol, and/or service or base the security decision on the assessment of other entities. Bluetooth, FTP, and peer-to-peer networking are examples of less than secure protocols. Related controls: AC-18, CM-7, IA-2. | D9: Directives supplémentaires | E9: L’organisation peut soit déterminer la sécurité relative de la fonction, du port, du protocole ou du service, soit baser sa décision en matière de sécurité sur l’évaluation d’autres entités. Bluetooth, FTP et l’interconnexion de réseaux d’égal à égal sont des exemples de protocoles moins sécurisés. Contrôles connexes : AC-18, CM-7, IA-2.
A10: Test Case | D10: Cas de test
A11: Test | B11: TEST-CM-7(1) | D11: Test | E11: TEST-CM-7(1)
A12: Requirement ID | B12: CM-7(1) | D12: ID Exigence | E12: CM-7(1)
A13: Component | D13: Composant
A14: Requirement | D14: Exigence
A15: Contextual Design Description | D15: Description contextuelle du design
A16: Evidence Provided | D16: Preuve fournie
A17: Preparer Sign Off (Initials, Date) | D17: Signataire préparateur (Initiales, Date)
A18: Owner Sign Off (Initials, Date) | D18: Signataire propriétaire (Initiales, Date)
A19: Assessor Sign Off (Initials, Date) | D19: Signataire évaluateur (Initiales, Date)
A20: Status | B20: Not Started | D20: Statut | E20: Non commencé
A21: Comments | D21: Commentaires

Sheet CP-6
A1: Control CP-6 — Evidence Tracking | D1: Contrôle CP-6 — Suivi des preuves
A2: Control Information | D2: Informations du contrôle
A3: Control Identifier | B3: CP-6 | D3: Identifiant du contrôle | E3: CP-6
A4: Family | B4: Alternate Storage Site | D4: Famille | E4: Site de stockage auxiliaire
A5: Profile | B5: CCCS Medium / PBMM Moderate | D5: Profil | E5: CCCS Moyen / PBMM Modéré
A6: Primary Evidence Tool | D6: Outil de preuve principal
A7: Contributing Tools | D7: Outils contributeurs
A8: Control Description | B8: (A) The organization establishes an alternate storage site including necessary agreements to permit the storage and retrieval of information system backup information. (B) The organization ensures that the alternate storage site provides information security safeguards equivalent to that of the primary site. | D8: Description du contrôle | E8: (A) L’organisation établit un site de stockage auxiliaire, incluant les ententes nécessaires pour permettre le stockage et l’extraction de l’information de sauvegarde du système d’information. (B) L’organisation veille à ce que le site de stockage auxiliaire offre des mesures de sécurité de l’information équivalentes à celles du site principal.
A9: Supplemental Guidance | B9: Alternate storage sites are sites that are geographically distinct from primary storage sites. An alternate storage site maintains duplicate copies of information and data in the event that the primary storage site is not available. Items covered by alternate storage site agreements include, for example, environmental conditions at alternate sites, access rules, physical and environmental protection requirements, and coordination of delivery/retrieval of backup media. Alternate storage sites reflect the requirements in contingency plans so that organizations can maintain essential missions/business functions despite disruption, compromise, or failure in organizational information systems. Related controls: CP-2, CP-7, CP-9, CP-10, MP-4 | D9: Directives supplémentaires | E9: Les sites de stockage auxiliaires sont des sites qui sont géographiquement séparés des sites de stockage principaux. Un site de stockage auxiliaire conserve des copies de l’information et des données advenant la non-disponibilité du site de stockage principal. Les éléments couverts par les accords sur les sites de stockage auxiliaires comprennent, par exemple, les conditions environnementales aux sites auxiliaires, les règles d’accès, les exigences en matière de protection physique et environnementale, et la coordination de la livraison/récupération des supports de sauvegarde. Les sites de stockage auxiliaires reflètent les exigences des plans d’urgence afin que les organisations puissent maintenir les fonctions opérationnelles et de mission essentielles malgré la perturbation, la compromission ou la défaillance des systèmes d’information organisationnels. Contrôles connexes : CP-2, CP-7, CP-9, CP-10, MP-4
A10: Test Case | D10: Cas de test
A11: Test | B11: TEST-CP-6 | D11: Test | E11: TEST-CP-6
A12: Requirement ID | B12: CP-6 | D12: ID Exigence | E12: CP-6
A13: Component | D13: Composant
A14: Requirement | D14: Exigence
A15: Contextual Design Description | D15: Description contextuelle du design
A16: Evidence Provided | D16: Preuve fournie
A17: Preparer Sign Off (Initials, Date) | D17: Signataire préparateur (Initiales, Date)
A18: Owner Sign Off (Initials, Date) | D18: Signataire propriétaire (Initiales, Date)
A19: Assessor Sign Off (Initials, Date) | D19: Signataire évaluateur (Initiales, Date)
A20: Status | B20: Not Started | D20: Statut | E20: Non commencé
A21: Comments | D21: Commentaires

Sheet CP-6-2
A1: Control CP-6(2) — Evidence Tracking | D1: Contrôle CP-6(2) — Suivi des preuves
A2: Control Information | D2: Informations du contrôle
A3: Control Identifier | B3: CP-6(2) | D3: Identifiant du contrôle | E3: CP-6(2)
A4: Family | B4: Alternate Storage Site | D4: Famille | E4: Site de stockage auxiliaire
A5: Profile | B5: CCCS Medium / PBMM Moderate | D5: Profil | E5: CCCS Moyen / PBMM Modéré
A6: Primary Evidence Tool | D6: Outil de preuve principal
A7: Contributing Tools | D7: Outils contributeurs
A8: Control Description | B8: ALTERNATE STORAGE SITE | RECOVERY TIME / POINT OBJECTIVES The organization configures the alternate storage site to facilitate recovery operations in accordance with recovery time and recovery point objectives. | D8: Description du contrôle | E8: SITE DE STOCKAGE AUXILIAIRE | OBJECTIFS EN MATIÈRE DE DÉLAIS/POINTS DE REPRISE L’organisation configure le site de stockage auxiliaire de manière à faciliter les opérations de reprise conformément aux objectifs en matière de délais et de points de reprise.
A9: Supplemental Guidance | D9: Directives supplémentaires
A10: Test Case | D10: Cas de test
A11: Test | B11: TEST-CP-6(2) | D11: Test | E11: TEST-CP-6(2)
A12: Requirement ID | B12: CP-6(2) | D12: ID Exigence | E12: CP-6(2)
A13: Component | D13: Composant
A14: Requirement | D14: Exigence
A15: Contextual Design Description | D15: Description contextuelle du design
A16: Evidence Provided | D16: Preuve fournie
A17: Preparer Sign Off (Initials, Date) | D17: Signataire préparateur (Initiales, Date)
A18: Owner Sign Off (Initials, Date) | D18: Signataire propriétaire (Initiales, Date)
A19: Assessor Sign Off (Initials, Date) | D19: Signataire évaluateur (Initiales, Date)
A20: Status | B20: Not Started | D20: Statut | E20: Non commencé
A21: Comments | D21: Commentaires

Sheet CP-7
A1: Control CP-7 — Evidence Tracking | D1: Contrôle CP-7 — Suivi des preuves
A2: Control Information | D2: Informations du contrôle
A3: Control Identifier | B3: CP-7 | D3: Identifiant du contrôle | E3: CP-7
A4: Family | B4: Alternate Processing Site | D4: Famille | E4: Site de traitement auxiliaire
A5: Profile | B5: CCCS Medium / PBMM Moderate | D5: Profil | E5: CCCS Moyen / PBMM Modéré
A6: Primary Evidence Tool | D6: Outil de preuve principal
A7: Contributing Tools | D7: Outils contributeurs
A8: Control Description | B8: (A) The organization establishes an alternate processing site including necessary agreements to permit the transfer and resumption of organization-defined information system operations for essential missions/business functions within organization-defined time period consistent with recovery time and recovery point objectives when the primary processing capabilities are unavailable. (B) The organization ensures that equipment and supplies required to transfer and resume operations are available at the alternate processing site or contracts are in place to support delivery to the site within the organization-defined time period for transfer/resumption. (C) The organization ensures that the alternate processing site provides information security safeguards equivalent to that of the primary site. | D8: Description du contrôle | E8: (A) L’organisation établit un site de traitement auxiliaire, y compris les ententes nécessaires pour permettre le transfert et la reprise des opérations du système d’information définies par l’organisation pour les missions et les fonctions opérationnelles essentielles à l’intérieur d’une période définie par l’organisation, conformément aux objectifs en matière de délais de reprise et de points de reprise lorsque les capacités de traitement principales ne sont pas disponibles. (B) L’organisation veille à ce que l’équipement et les fournitures nécessaires au transfert et à la reprise des activités soient disponibles au site de traitement auxiliaire, ou à ce que des contrats soient en place pour soutenir la livraison au site à l’intérieur de la période définie par l’organisation pour le transfert ou la reprise. (C) L’organisation veille à ce que le site de traitement auxiliaire offre des mesures de sécurité de l’information équivalentes à celles du site principal.
A9: Supplemental Guidance | B9: Alternate processing sites are sites that are geographically distinct from primary processing sites. An alternate processing site provides processing capability in the event that the primary processing site is not available. Items covered by alternate processing site agreements include, for example, environmental conditions at alternate sites, access rules, physical and environmental protection requirements, and coordination for the transfer/assignment of personnel. Requirements are specifically allocated to alternate processing sites that reflect the requirements in contingency plans to maintain essential missions/business functions despite disruption, compromise, or failure in organizational information systems. Related controls: CP-2, CP-6, CP-8, CP-9, CP-10, MA-6 | D9: Directives supplémentaires | E9: Les sites de traitement auxiliaires sont des sites qui sont géographiquement séparés des sites de traitement principaux. Un site de traitement auxiliaire offre une capacité de traitement lorsque le site de traitement principal n’est pas disponible. Les éléments couverts par les accords sur les sites de traitement auxiliaires comprennent, par exemple, les conditions environnementales aux sites auxiliaires, les règles d’accès, les exigences en matière de protection physique et environnementale, et la coordination pour le transfert ou l’attribution du personnel. Les exigences spécifiquement attribuées aux sites de traitement auxiliaires reflètent les exigences des plans d’urgence pour maintenir les fonctions opérationnelles et de mission essentielles malgré la perturbation, la compromission ou la défaillance des systèmes d’information organisationnels. Contrôles connexes : CP-2, CP-6, CP-8, CP-9, CP-10, MA-6
A10: Test Case | D10: Cas de test
A11: Test | B11: TEST-CP-7 | D11: Test | E11: TEST-CP-7
A12: Requirement ID | B12: CP-7 | D12: ID Exigence | E12: CP-7
A13: Component | D13: Composant
A14: Requirement | D14: Exigence
A15: Contextual Design Description | D15: Description contextuelle du design
A16: Evidence Provided | D16: Preuve fournie
A17: Preparer Sign Off (Initials, Date) | D17: Signataire préparateur (Initiales, Date)
A18: Owner Sign Off (Initials, Date) | D18: Signataire propriétaire (Initiales, Date)
A19: Assessor Sign Off (Initials, Date) | D19: Signataire évaluateur (Initiales, Date)
A20: Status | B20: Not Started | D20: Statut | E20: Non commencé
A21: Comments | D21: Commentaires

Sheet CP-7-4
A1: Control CP-7(4) — Evidence Tracking | D1: Contrôle CP-7(4) — Suivi des preuves
A2: Control Information | D2: Informations du contrôle
A3: Control Identifier | B3: CP-7(4) | D3: Identifiant du contrôle | E3: CP-7(4)
A4: Family | B4: Alternate Processing Site | D4: Famille | E4: Site de traitement auxiliaire
A5: Profile | B5: CCCS Medium / PBMM Moderate | D5: Profil | E5: CCCS Moyen / PBMM Modéré
A6: Primary Evidence Tool | D6: Outil de preuve principal
A7: Contributing Tools | D7: Outils contributeurs
A8: Control Description | B8: ALTERNATE PROCESSING SITE | PREPARATION FOR USE The organization prepares the alternate processing site so that the site is ready to be used as the operational site supporting essential missions and business functions. | D8: Description du contrôle | E8: SITE DE TRAITEMENT AUXILIAIRE | PRÉPARATION À L’UTILISATION L’organisation prépare le site de traitement auxiliaire de manière à ce que le site soit prêt à être utilisé comme site opérationnel prenant en charge les fonctions opérationnelles et les missions essentielles.
A9: Supplemental Guidance | B9: Site preparation includes, for example, establishing configuration settings for information system components at the alternate processing site consistent with the requirements for such settings at the primary site and ensuring that essential supplies and other logistical considerations are in place. Related controls: CM-2, CM-6. | D9: Directives supplémentaires | E9: La préparation du site comprend, par exemple, l’établissement des paramètres de configuration pour les composants du système d’information au site de traitement auxiliaire, conformément aux exigences pour ces paramètres au site principal, et l’assurance que les fournitures essentielles et autres considérations logistiques sont en place. Contrôles connexes : CM-2, CM-6.
A10: Test Case | D10: Cas de test
A11: Test | B11: TEST-CP-7(4) | D11: Test | E11: TEST-CP-7(4)
A12: Requirement ID | B12: CP-7(4) | D12: ID Exigence | E12: CP-7(4)
A13: Component | D13: Composant
A14: Requirement | D14: Exigence
A15: Contextual Design Description | D15: Description contextuelle du design
A16: Evidence Provided | D16: Preuve fournie
A17: Preparer Sign Off (Initials, Date) | D17: Signataire préparateur (Initiales, Date)
A18: Owner Sign Off (Initials, Date) | D18: Signataire propriétaire (Initiales, Date)
A19: Assessor Sign Off (Initials, Date) | D19: Signataire évaluateur (Initiales, Date)
A20: Status | B20: Not Started | D20: Statut | E20: Non commencé
A21: Comments | D21: Commentaires

Sheet CP-9
A1: Control CP-9 — Evidence Tracking | D1: Contrôle CP-9 — Suivi des preuves
A2: Control Information | D2: Informations du contrôle
A3: Control Identifier | B3: CP-9 | D3: Identifiant du contrôle | E3: CP-9
A4: Family | B4: Information System Backup | D4: Famille | E4: Sauvegarde du système d’information
A5: Profile | B5: CCCS Medium / PBMM Moderate | D5: Profil | E5: CCCS Moyen / PBMM Modéré
A6: Primary Evidence Tool | D6: Outil de preuve principal
A7: Contributing Tools | D7: Outils contributeurs
A8: Control Description | B8: (A) The organization conducts backups of user-level information contained in the information system daily incremental; weekly full. (B) The organization conducts backups of system-level information contained in the information system daily incremental; weekly full. (C) The organization conducts backups of information system documentation including security-related documentation daily incremental; weekly full. (D) The organization protects the confidentiality, integrity, and availability of backup information at storage locations. (AA) The organization determines retention periods for essential business information and archived backups. | D8: Description du contrôle | E8: (A) L’organisation effectue des sauvegardes incrémentielles quotidiennes et des sauvegardes hebdomadaires complètes de l’information au niveau de l’utilisateur qui est contenue dans le système d’information. (B) L’organisation effectue des sauvegardes incrémentielles quotidiennes et des sauvegardes hebdomadaires complètes de l’information au niveau du système contenue dans le système d’information. (C) L’organisation effectue des sauvegardes incrémentielles quotidiennes et des sauvegardes hebdomadaires complètes de la documentation relative au système d’information, y compris la documentation liée à la sécurité. (D) L’organisation protège la confidentialité, l’intégrité et la disponibilité de l’information de sauvegarde aux emplacements de stockage. (AA) L’organisation détermine les périodes de conservation des renseignements opérationnels essentiels et des sauvegardes archivées.
A9: Supplemental Guidance | B9: System-level information includes, for example, system-state information, operating system and application software, and licenses. User-level information includes any information other than system-level information. Mechanisms employed by organizations to protect the integrity of information system backups include, for example, digital signatures and cryptographic hashes. Protection of system backup information while in transit is beyond the scope of this control. Information system backups reflect the requirements in contingency plans as well as other organizational requirements for backing up information. Related controls: CP-2, CP-6, MP-4, MP-5, SC-13 | D9: Directives supplémentaires | E9: L’information au niveau du système comprend, par exemple, l’information sur l’état du système, le système d’exploitation, les logiciels d’application et les licences. L’information au niveau de l’utilisateur comprend toute information autre que l’information au niveau du système. Les mécanismes employés par les organisations pour protéger l’intégrité des sauvegardes du système d’information comprennent, par exemple, les signatures numériques et le hachage cryptographique. La protection de l’information de sauvegarde du système pendant le transport dépasse la portée de ce contrôle. Les sauvegardes du système d’information reflètent les exigences des plans d’urgence ainsi que d’autres exigences organisationnelles relatives à la sauvegarde de l’information. Contrôles connexes : CP-2, CP-6, MP-4, MP-5, SC-13
A10: Test Case | D10: Cas de test
A11: Test | B11: TEST-CP-9 | D11: Test | E11: TEST-CP-9
A12: Requirement ID | B12: CP-9 | D12: ID Exigence | E12: CP-9
A13: Component | D13: Composant
A14: Requirement | D14: Exigence
A15: Contextual Design Description | D15: Description contextuelle du design
A16: Evidence Provided | D16: Preuve fournie
A17: Preparer Sign Off (Initials, Date) | D17: Signataire préparateur (Initiales, Date)
A18: Owner Sign Off (Initials, Date) | D18: Signataire propriétaire (Initiales, Date)
A19: Assessor Sign Off (Initials, Date) | D19: Signataire évaluateur (Initiales, Date)
A20: Status | B20: Not Started | D20: Statut | E20: Non commencé
A21: Comments | D21: Commentaires

Sheet CP-9-1
A1: Control CP-9(1) — Evidence Tracking | D1: Contrôle CP-9(1) — Suivi des preuves
A2: Control Information | D2: Informations du contrôle
A3: Control Identifier | B3: CP-9(1) | D3: Identifiant du contrôle | E3: CP-9(1)
A4: Family | B4: Information System Backup | D4: Famille | E4: Sauvegarde du système d’information
A5: Profile | B5: CCCS Medium / PBMM Moderate | D5: Profil | E5: CCCS Moyen / PBMM Modéré
A6: Primary Evidence Tool | D6: Outil de preuve principal
A7: Contributing Tools | D7: Outils contributeurs
A8: Control Description | B8: INFORMATION SYSTEM BACKUP | TESTING FOR RELIABILITY / INTEGRITY The organization tests backup information at least annually to verify media reliability and information integrity. | D8: Description du contrôle | E8: SAUVEGARDE DU SYSTÈME D’INFORMATION | VÉRIFICATION DE LA FIABILITÉ ET DE L’INTÉGRITÉ L’organisation teste l’information de sauvegarde au moins une fois par année pour vérifier la fiabilité des supports et l’intégrité de l’information.
A9: Supplemental Guidance | B9: Related control: CP-4. | D9: Directives supplémentaires | E9: Contrôle connexe : CP-4.
A10: Test Case | D10: Cas de test
A11: Test | B11: TEST-CP-9(1) | D11: Test | E11: TEST-CP-9(1)
A12: Requirement ID | B12: CP-9(1) | D12: ID Exigence | E12: CP-9(1)
A13: Component | D13: Composant
A14: Requirement | D14: Exigence
A15: Contextual Design Description | D15: Description contextuelle du design
A16: Evidence Provided | D16: Preuve fournie
A17: Preparer Sign Off (Initials, Date) | D17: Signataire préparateur (Initiales, Date)
A18: Owner Sign Off (Initials, Date) | D18: Signataire propriétaire (Initiales, Date)
A19: Assessor Sign Off (Initials, Date) | D19: Signataire évaluateur (Initiales, Date)
A20: Status | B20: Not Started | D20: Statut | E20: Non commencé
A21: Comments | D21: Commentaires

Sheet CP-9-2
A1: Control CP-9(2) — Evidence Tracking | D1: Contrôle CP-9(2) — Suivi des preuves
A2: Control Information | D2: Informations du contrôle
A3: Control Identifier | B3: CP-9(2) | D3: Identifiant du contrôle | E3: CP-9(2)
A4: Family | B4: Information System Backup | D4: Famille | E4: Sauvegarde du système d’information
A5: Profile | B5: CCCS Medium / PBMM Moderate | D5: Profil | E5: CCCS Moyen / PBMM Modéré
A6: Primary Evidence Tool | D6: Outil de preuve principal
A7: Contributing Tools | D7: Outils contributeurs
A8: Control Description | B8: INFORMATION SYSTEM BACKUP | TEST RESTORATION USING SAMPLING The organization uses a sample of backup information in the restoration of selected information system functions as part of contingency plan testing. | D8: Description du contrôle | E8: SAUVEGARDE DU SYSTÈME D’INFORMATION | ESSAIS DE RESTAURATION AU MOYEN DE L’ÉCHANTILLONNAGE L’organisation utilise un échantillon de l’information de sauvegarde pour restaurer certaines fonctions du système d’information dans le cadre de la mise à l’essai du plan d’urgence.
A9: Supplemental Guidance | B9: Related control: CP-4. | D9: Directives supplémentaires | E9: Contrôle connexe : CP-4.
A10: Test Case | D10: Cas de test
A11: Test | B11: TEST-CP-9(2) | D11: Test | E11: TEST-CP-9(2)
A12: Requirement ID | B12: CP-9(2) | D12: ID Exigence | E12: CP-9(2)
A13: Component | D13: Composant
A14: Requirement | D14: Exigence
A15: Contextual Design Description | D15: Description contextuelle du design
A16: Evidence Provided | D16: Preuve fournie
A17: Preparer Sign Off (Initials, Date) | D17: Signataire préparateur (Initiales, Date)
A18: Owner Sign Off (Initials, Date) | D18: Signataire propriétaire (Initiales, Date)
A19: Assessor Sign Off (Initials, Date) | D19: Signataire évaluateur (Initiales, Date)
A20: Status | B20: Not Started | D20: Statut | E20: Non commencé
A21: Comments | D21: Commentaires

Sheet CP-9-5
A1: Control CP-9(5) — Evidence Tracking | D1: Contrôle CP-9(5) — Suivi des preuves
A2: Control Information | D2: Informations du contrôle
A3: Control Identifier | B3: CP-9(5) | D3: Identifiant du contrôle | E3: CP-9(5)
A4: Family | B4: Information System Backup | D4: Famille | E4: Sauvegarde du système d’information
A5: Profile | B5: CCCS Medium / PBMM Moderate | D5: Profil | E5: CCCS Moyen / PBMM Modéré
A6: Primary Evidence Tool | D6: Outil de preuve principal
A7: Contributing Tools | D7: Outils contributeurs
A8: Control Description | B8: INFORMATION SYSTEM BACKUP | TRANSFER TO ALTERNATE STORAGE SITE The organization transfers information system backup information to the alternate storage site at organization-defined time period and transfer rate consistent with the recovery time and recovery point objectives. | D8: Description du contrôle | E8: SAUVEGARDE DU SYSTÈME D’INFORMATION | TRANSFERT À UN SITE DE STOCKAGE AUXILIAIRE L’organisation transfère l’information de sauvegarde du système d’information au site de stockage auxiliaire au moment et à la vitesse de transfert définis par l’organisation conformément aux objectifs en matière de délais et de points de reprise.
A9: Supplemental Guidance | B9: Information system backup information can be transferred to alternate storage sites either electronically or by physical shipment of storage media. | D9: Directives supplémentaires | E9: Les données de sauvegarde du système d’information peuvent être transférées à des sites de stockage auxiliaires par voie électronique ou par envoi physique de supports de stockage.
A10: Test Case | D10: Cas de test
A11: Test | B11: TEST-CP-9(5) | D11: Test | E11: TEST-CP-9(5)
A12: Requirement ID | B12: CP-9(5) | D12: ID Exigence | E12: CP-9(5)
A13: Component | D13: Composant
A14: Requirement | D14: Exigence
A15: Contextual Design Description | D15: Description contextuelle du design
A16: Evidence Provided | D16: Preuve fournie
A17: Preparer Sign Off (Initials, Date) | D17: Signataire préparateur (Initiales, Date)
A18: Owner Sign Off (Initials, Date) | D18: Signataire propriétaire (Initiales, Date)
A19: Assessor Sign Off (Initials, Date) | D19: Signataire évaluateur (Initiales, Date)
A20: Status | B20: Not Started | D20: Statut | E20: Non commencé
A21: Comments | D21: Commentaires

Sheet CP-10
A1: Control CP-10 — Evidence Tracking | D1: Contrôle CP-10 — Suivi des preuves
A2: Control Information | D2: Informations du contrôle
A3: Control Identifier | B3: CP-10 | D3: Identifiant du contrôle | E3: CP-10
A4: Family | B4: Information System Recovery and Reconstitution | D4: Famille | E4: Reprise et reconstitution du système d’information
A5: Profile | B5: CCCS Medium / PBMM Moderate | D5: Profil | E5: CCCS Moyen / PBMM Modéré
A6: Primary Evidence Tool | D6: Outil de preuve principal
A7: Contributing Tools | D7: Outils contributeurs
A8: Control Description | B8: (A) The organization provides for the recovery and reconstitution of the information system to a known state after a disruption, compromise, or failure. | D8: Description du contrôle | E8: (A) L’organisation assure la reprise et la reconstitution du système d’information dans un état connu après une perturbation, une compromission ou une défaillance.
A9: Supplemental Guidance | B9: Recovery is executing information system contingency plan activities to restore organizational missions/business functions. Reconstitution takes place following recovery and includes activities for returning organizational information systems to fully operational states. Recovery and reconstitution operations reflect mission and business priorities, recovery point/time and reconstitution objectives, and established organizational metrics consistent with contingency plan requirements. Reconstitution includes the deactivation of any interim information system capabilities that may have been needed during recovery operations. Reconstitution also includes assessments of fully restored information system capabilities, reestablishment of continuous monitoring activities, potential information system reauthorizations, and activities to prepare the systems against future disruptions, compromises, or failures. Recovery/reconstitution capabilities employed by organizations can include both automated mechanisms and manual procedures. Related controls: CA-2, CA-6, CA-7, CP-2, CP-4, CP-6, CP-7, CP-9, SC-24 | D9: Directives supplémentaires | E9: La reprise consiste à exécuter les activités du plan d’urgence du système d’information pour restaurer les fonctions opérationnelles et de mission de l’organisation. La reconstitution a lieu après la reprise et comprend les activités permettant de remettre les systèmes d’information organisationnels à l’état pleinement opérationnel. Les opérations de reprise et de reconstitution reflètent les priorités opérationnelles et de mission, les objectifs en matière de délais, de points de reprise et de reconstitution, de même que les paramètres organisationnels établis conformément aux exigences du plan d’urgence. La reconstitution comprend la désactivation de toute capacité provisoire du système d’information ayant pu être nécessaire pendant les opérations de reprise. La reconstitution comprend également l’évaluation des capacités entièrement restaurées du système d’information, le rétablissement des activités de surveillance continue, les réautorisations possibles du système d’information et les activités visant à préparer les systèmes à faire face aux perturbations, compromissions ou défaillances futures. Les capacités de reprise et de reconstitution utilisées par les organisations peuvent comprendre des mécanismes automatisés et des procédures manuelles. Contrôles connexes : CA-2, CA-6, CA-7, CP-2, CP-4, CP-6, CP-7, CP-9, SC-24
A10: Test Case | D10: Cas de test
A11: Test | B11: TEST-CP-10 | D11: Test | E11: TEST-CP-10
A12: Requirement ID | B12: CP-10 | D12: ID Exigence | E12: CP-10
A13: Component | D13: Composant
A14: Requirement | D14: Exigence
A15: Contextual Design Description | D15: Description contextuelle du design
A16: Evidence Provided | D16: Preuve fournie
A17: Preparer Sign Off (Initials, Date) | D17: Signataire préparateur (Initiales, Date)
A18: Owner Sign Off (Initials, Date) | D18: Signataire propriétaire (Initiales, Date)
A19: Assessor Sign Off (Initials, Date) | D19: Signataire évaluateur (Initiales, Date)
A20: Status | B20: Not Started | D20: Statut | E20: Non commencé
A21: Comments | D21: Commentaires

Sheet CP-10-4
A1: Control CP-10(4) — Evidence Tracking | D1: Contrôle CP-10(4) — Suivi des preuves
A2: Control Information | D2: Informations du contrôle
A3: Control Identifier | B3: CP-10(4) | D3: Identifiant du contrôle | E3: CP-10(4)
A4: Family | B4: Information System Recovery and Reconstitution | D4: Famille | E4: Reprise et reconstitution du système d’information
A5: Profile | B5: CCCS Medium / PBMM Moderate | D5: Profil | E5: CCCS Moyen / PBMM Modéré
A6: Primary Evidence Tool | D6: Outil de preuve principal
A7: Contributing Tools | D7: Outils contributeurs
A8: Control Description | B8: INFORMATION SYSTEM RECOVERY AND RECONSTITUTION | RESTORE WITHIN TIME PERIOD The organization provides the capability to restore information system components within organization-defined restoration time-periods from configuration-controlled and integrity-protected information representing a known, operational state for the components. | D8: Description du contrôle | E8: REPRISE ET RECONSTITUTION DU SYSTÈME D’INFORMATION | RESTAURATION DANS LE DÉLAI IMPARTI L’organisation fournit la capacité de restaurer les composants du système d’information dans les délais de restauration définis par l’organisation à partir de l’information contrôlée par la configuration et protégée par l’intégrité qui représente un état de fonctionnement connu pour les composants.
A9: Supplemental Guidance | B9: Restoration of information system components includes, for example, re-imaging which restores components to known, operational states. Related control: CM-2. | D9: Directives supplémentaires | E9: La restauration des composants du système d’information comprend, par exemple, la reconfiguration permettant de restaurer les composants aux états de fonctionnement connus. Contrôle connexe : CM-2.
A10: Test Case | D10: Cas de test
A11: Test | B11: TEST-CP-10(4) | D11: Test | E11: TEST-CP-10(4)
A12: Requirement ID | B12: CP-10(4) | D12: ID Exigence | E12: CP-10(4)
A13: Component | D13: Composant
A14: Requirement | D14: Exigence
A15: Contextual Design Description | D15: Description contextuelle du design
A16: Evidence Provided | D16: Preuve fournie
A17: Preparer Sign Off (Initials, Date) | D17: Signataire préparateur (Initiales, Date)
A18: Owner Sign Off (Initials, Date) | D18: Signataire propriétaire (Initiales, Date)
A19: Assessor Sign Off (Initials, Date) | D19: Signataire évaluateur (Initiales, Date)
A20: Status | B20: Not Started | D20: Statut | E20: Non commencé
A21: Comments | D21: Commentaires

Sheet SA-9-5
A1: Control SA-9(5) — Evidence Tracking | D1: Contrôle SA-9(5) — Suivi des preuves
A2: Control Information | D2: Informations du contrôle
A3: Control Identifier | B3: SA-9(5) | D3: Identifiant du contrôle | E3: SA-9(5)
A4: Family | B4: External Information System Services | D4: Famille | E4: Services de systèmes d’information externes
A5: Profile | B5: CCCS Medium / PBMM Moderate | D5: Profil | E5: CCCS Moyen / PBMM Modéré
A6: Primary Evidence Tool | D6: Outil de preuve principal
A7: Contributing Tools | D7: Outils contributeurs
A8: Control Description | B8: EXTERNAL INFORMATION SYSTEMS | PROCESSING, STORAGE, AND SERVICE LOCATION The organization restricts the location of information processing, information/data, and information system services to locations witihin Canada based on ITPIN 2017-02 for Direction on Data Residency (https://www.canada.ca/en/treasury-board-secretariat/services/information-technology/policy-implementation-notices/direction-electronic-data-residency.html). | D8: Description du contrôle | E8: SYSTÈMES D’INFORMATION EXTERNES | EMPLACEMENT DU TRAITEMENT, DU STOCKAGE ET DES SERVICES L’organisation restreint la résidence du traitement de l’information, du stockage de l’information et des données, ainsi que des services de systèmes d’information aux endroits situés à l’intérieur du Canada, conformément à l’avis AMPTI 2017-02, Orientation relative à la résidence des données électroniques (https://www.canada.ca/fr/gouvernement/systeme/gouvernement-numerique/technologiques-modernes-nouveaux/orientation-relative-residence-donnees-electroniques.html).
A9: Supplemental Guidance | B9: The location of information processing, information/data storage, or information system services that are critical to organizations can have a direct impact on the ability of those organizations to successfully execute their missions/business functions. This situation exists when external providers control the location of processing, storage or services. The criteria external providers use for the selection of processing, storage, or service locations may be different from organizational criteria. For example, organizations may want to ensure that data/information storage locations are restricted to certain locations to facilitate incident response activities (e.g., forensic analyses, after-the-fact investigations) in case of information security breaches/compromises. Such incident response activities may be adversely affected by the governing laws or protocols in the locations where processing and storage occur and/or the locations from which information system services emanate. | D9: Directives supplémentaires | E9: L’emplacement des services de traitement de l’information et de stockage de l’information et des données ou des services de systèmes d’information qui sont essentiels pour les organisations peut avoir une incidence directe sur la capacité de ces organisations d’exécuter avec succès leurs fonctions opérationnelles et de mission. Cette situation existe lorsque des fournisseurs externes contrôlent l’emplacement du traitement, de l’entreposage ou des services. Les critères utilisés par les fournisseurs externes pour choisir les lieux de traitement, d’entreposage ou de service peuvent être différents des critères de l’organisation. Par exemple, les organisations pourraient vouloir s’assurer que les emplacements de stockage des données ou de l’information se limitent à certains endroits afin de faciliter les activités d’intervention (p. ex., analyses judiciaires, enquêtes après coup) en cas d’incident représentant une atteinte à, ou une compromission de la sécurité de l’information. Ces activités d’intervention en cas d’incident peuvent être affectées négativement par les lois ou les protocoles en vigueur aux endroits où le traitement et l’entreposage ont lieu ou aux endroits d’où proviennent les services de systèmes d’information.
A10: Test Case | D10: Cas de test
A11: Test | B11: TEST-SA-9(5) | D11: Test | E11: TEST-SA-9(5)
A12: Requirement ID | B12: SA-9(5) | D12: ID Exigence | E12: SA-9(5)
A13: Component | D13: Composant
A14: Requirement | D14: Exigence
A15: Contextual Design Description | D15: Description contextuelle du design
A16: Evidence Provided | D16: Preuve fournie
A17: Preparer Sign Off (Initials, Date) | D17: Signataire préparateur (Initiales, Date)
A18: Owner Sign Off (Initials, Date) | D18: Signataire propriétaire (Initiales, Date)
A19: Assessor Sign Off (Initials, Date) | D19: Signataire évaluateur (Initiales, Date)
A20: Status | B20: Not Started | D20: Statut | E20: Non commencé
A21: Comments | D21: Commentaires

Sheet SC-4
A1: Control SC-4 — Evidence Tracking | D1: Contrôle SC-4 — Suivi des preuves
A2: Control Information | D2: Informations du contrôle
A3: Control Identifier | B3: SC-4 | D3: Identifiant du contrôle | E3: SC-4
A4: Family | B4: Information in Shared Resources | D4: Famille | E4: Information dans les ressources partagées
A5: Profile | B5: CCCS Medium / PBMM Moderate | D5: Profil | E5: CCCS Moyen / PBMM Modéré
A6: Primary Evidence Tool | D6: Outil de preuve principal
A7: Contributing Tools | D7: Outils contributeurs
A8: Control Description | B8: (A) The information system prevents unauthorized and unintended information transfer via shared system resources. | D8: Description du contrôle | E8: (A) Le système d’information empêche le transfert non autorisé et non intentionnel d’information par le biais des ressources partagées du système.
A9: Supplemental Guidance | B9: This control prevents information, including encrypted representations of information, produced by the actions of prior users/roles (or the actions of processes acting on behalf of prior users/roles) from being available to any current users/roles (or current processes) that obtain access to shared system resources (e.g., registers, main memory, hard disks) after those resources have been released back to information systems. The control of information in shared resources is also commonly referred to as object reuse and residual information protection. This control does not address: (i) information remanence which refers to residual representation of data that has been nominally erased or removed; (ii) covert channels (including storage and/or timing channels) where shared resources are manipulated to violate information flow restrictions; or (iii) components within information systems for which there are only single users/roles. Related controls: AC-3, AC-4, MP-6 | D9: Directives supplémentaires | E9: Ce contrôle empêche l’information, y compris les représentations chiffrées de l’information, produites par les actions des utilisateurs/rôles antérieurs (ou les actions des processus agissant pour le compte des utilisateurs/rôles antérieurs) d’être accessible aux utilisateurs/rôles actuels (ou aux processus actuels) qui obtiennent l’accès aux ressources partagées du système (p. ex., registres, mémoire principale, disques durs) après que ces ressources ont été retournées aux systèmes d’information. Le contrôle de l’information dans les ressources partagées est aussi communément appelé réutilisation d’objets et protection de l’information résiduelle. Ce contrôle ne porte pas sur : (i) la rémanence de l’information qui désigne la représentation résiduelle des données qui ont été nominalement effacées ou supprimées; (ii) les canaux cachés (y compris les canaux de stockage ou de synchronisation) où les ressources partagées sont manipulées pour violer les restrictions de circulation de l’information; ou (iii) les composants des systèmes d’information pour lesquels il n’y a qu’un seul utilisateur/rôle. Contrôles connexes : AC-3, AC-4, MP-6
A10: Test Case | D10: Cas de test
A11: Test | B11: TEST-SC-4 | D11: Test | E11: TEST-SC-4
A12: Requirement ID | B12: SC-4 | D12: ID Exigence | E12: SC-4
A13: Component | D13: Composant
A14: Requirement | D14: Exigence
A15: Contextual Design Description | D15: Description contextuelle du design
A16: Evidence Provided | D16: Preuve fournie
A17: Preparer Sign Off (Initials, Date) | D17: Signataire préparateur (Initiales, Date)
A18: Owner Sign Off (Initials, Date) | D18: Signataire propriétaire (Initiales, Date)
A19: Assessor Sign Off (Initials, Date) | D19: Signataire évaluateur (Initiales, Date)
A20: Status | B20: Not Started | D20: Statut | E20: Non commencé
A21: Comments | D21: Commentaires

Sheet SC-13
A1: Control SC-13 — Evidence Tracking | D1: Contrôle SC-13 — Suivi des preuves
A2: Control Information | D2: Informations du contrôle
A3: Control Identifier | B3: SC-13 | D3: Identifiant du contrôle | E3: SC-13
A4: Family | B4: Cryptographic Protection | D4: Famille | E4: Protection cryptographique
A5: Profile | B5: CCCS Medium / PBMM Moderate | D5: Profil | E5: CCCS Moyen / PBMM Modéré
A6: Primary Evidence Tool | D6: Outil de preuve principal
A7: Contributing Tools | D7: Outils contributeurs
A8: Control Description | B8: (A) The information system implements CSE approved cryptography in accordance with applicable organizational policies, directives and standards. | D8: Description du contrôle | E8: (A) Le système d’information met en œuvre la cryptographie approuvée par le CST conformément aux politiques, aux directives et aux normes organisationnelles applicables.
A9: Supplemental Guidance | B9: Cryptography can be employed to support a variety of security solutions including, for example, the protection of sensitive information, the provision of digital signatures, and the enforcement of information separation when authorized individuals have the necessary clearances for such information but lack the necessary formal access approvals. Cryptography can also be used to support random number generation and hash generation. Generally applicable cryptographic standards include FIPS-validated cryptography. This control does not impose any requirements on organizations to use cryptography. However, if cryptography is required based on the selection of other security controls or policies, organizations document each type of cryptographic use and the type of cryptography required (e.g., protection of classified information: FIPS-validated cryptography). Related controls: AC-2, AC-3, AC-7, AC-17, AC-18, AU-9, AU-10, CM-11, CP-9, IA-3, IA-7, MA-4, MP-2, MP-4, MP-5, SA-4, SC-8, SC-12, SC-28, SI-7 | D9: Directives supplémentaires | E9: La cryptographie peut être utilisée pour la prise en charge d’une variété de solutions de sécurité, y compris, par exemple, la protection des renseignements de nature sensible, la fourniture de signatures numériques, et l’application de la séparation des renseignements lorsque les personnes autorisées ont les autorisations de sécurité nécessaires pour ces renseignements, mais qu’elles n’ont pas les autorisations d’accès officielles nécessaires. La cryptographie peut également être utilisée pour permettre la génération de nombres aléatoires et la génération de hachages. Les normes cryptographiques généralement applicables comprennent la cryptographie conforme aux normes FIPS. Ce contrôle n’oblige pas les organisations à utiliser la cryptographie. Toutefois, si la cryptographie est requise en fonction de la sélection d’autres contrôles ou politiques de sécurité, les organisations documentent chaque type d’utilisation cryptographique et le type de cryptographie requis (p. ex., protection de l’information classifiée : cryptographie conforme aux normes FIPS). Contrôles connexes : AC-2, AC-3, AC-7, AC-17, AC-18, AU-9, AU-10, CM-11, CP-9, IA-3, IA-7, MA-4, MP-2, MP-4, MP-5, SA-4, SC-8, SC-12, SC-28, SI-7
A10: Test Case | D10: Cas de test
A11: Test | B11: TEST-SC-13 | D11: Test | E11: TEST-SC-13
A12: Requirement ID | B12: SC-13 | D12: ID Exigence | E12: SC-13
A13: Component | D13: Composant
A14: Requirement | D14: Exigence
A15: Contextual Design Description | D15: Description contextuelle du design
A16: Evidence Provided | D16: Preuve fournie
A17: Preparer Sign Off (Initials, Date) | D17: Signataire préparateur (Initiales, Date)
A18: Owner Sign Off (Initials, Date) | D18: Signataire propriétaire (Initiales, Date)
A19: Assessor Sign Off (Initials, Date) | D19: Signataire évaluateur (Initiales, Date)
A20: Status | B20: Not Started | D20: Statut | E20: Non commencé
A21: Comments | D21: Commentaires

Sheet SC-28
A1: Control SC-28 — Evidence Tracking | D1: Contrôle SC-28 — Suivi des preuves
A2: Control Information | D2: Informations du contrôle
A3: Control Identifier | B3: SC-28 | D3: Identifiant du contrôle | E3: SC-28
A4: Family | B4: Protection of Information At Rest | D4: Famille | E4: Protection de l’information inactive
A5: Profile | B5: CCCS Medium / PBMM Moderate | D5: Profil | E5: CCCS Moyen / PBMM Modéré
A6: Primary Evidence Tool | D6: Outil de preuve principal
A7: Contributing Tools | D7: Outils contributeurs
A8: Control Description | B8: (A) The information system protects the confidentiality and integrity of all information not cleared for public release and all data with a higher than low integrity requirement. | D8: Description du contrôle | E8: (A) Le système d’information protège la confidentialité et l’intégrité de tous les renseignements dont la diffusion publique n’est pas autorisée et de toutes les données pour lesquelles les exigences d’intégrité ne sont pas faibles.
A9: Supplemental Guidance | B9: This control addresses the confidentiality and integrity of information at rest and covers user information and system information. Information at rest refers to the state of information when it is located on storage devices as specific components of information systems. System-related information requiring protection includes, for example, configurations or rule sets for firewalls, gateways, intrusion detection/prevention systems, filtering routers, and authenticator content. Organizations may employ different mechanisms to achieve confidentiality and integrity protections, including the use of cryptographic mechanisms and file share scanning. Integrity protection can be achieved, for example, by implementing Write-Once-Read-Many (WORM) technologies. Organizations may also employ other security controls including, for example, secure off-line storage in lieu of online storage when adequate protection of information at rest cannot otherwise be achieved and/or continuous monitoring to identify malicious code at rest. Related controls: AC-3, AC-6, CA-7, CM-3, CM-5, CM-6, PE-3, SC-8, SC-13, SI-3, SI-7 | D9: Directives supplémentaires | E9: Ce contrôle porte sur la confidentialité et l’intégrité de l’information inactive et couvre l’information sur les utilisateurs et le système. L’information inactive fait référence à l’état de l’information lorsqu’elle se trouve sur des dispositifs de stockage en tant que composants particuliers des systèmes d’information. Les renseignements relatifs au système qui nécessitent une protection comprennent, par exemple, les configurations ou les ensembles de règles pour les pare-feu, les passerelles, les systèmes de détection et de prévention des intrusions, les routeurs de filtrage et le contenu des authentifiants. Les organisations peuvent utiliser différents mécanismes pour assurer la protection de la confidentialité et de l’intégrité, y compris les mécanismes cryptographiques et le balayage des fichiers partagés. La protection de l’intégrité peut être assurée, par exemple, en mettant en œuvre des technologies qui rendent les supports non réinscriptibles. Les organisations peuvent également utiliser d’autres contrôles de sécurité, y compris, par exemple, le stockage hors ligne sécurisé au lieu du stockage en ligne lorsque la protection de l’information inactive ne peut être assurée autrement, ou la surveillance continue pour repérer du code malveillant inactif. Contrôles connexes : AC-3, AC-6, CA-7, CM-3, CM-5, CM-6, PE-3, SC-8, SC-13, SI-3, SI-7
A10: Test Case | D10: Cas de test
A11: Test | B11: TEST-SC-28 | D11: Test | E11: TEST-SC-28
A12: Requirement ID | B12: SC-28 | D12: ID Exigence | E12: SC-28
A13: Component | D13: Composant
A14: Requirement | D14: Exigence
A15: Contextual Design Description | D15: Description contextuelle du design
A16: Evidence Provided | D16: Preuve fournie
A17: Preparer Sign Off (Initials, Date) | D17: Signataire préparateur (Initiales, Date)
A18: Owner Sign Off (Initials, Date) | D18: Signataire propriétaire (Initiales, Date)
A19: Assessor Sign Off (Initials, Date) | D19: Signataire évaluateur (Initiales, Date)
A20: Status | B20: Not Started | D20: Statut | E20: Non commencé
A21: Comments | D21: Commentaires

Sheet SC-28-1
A1: Control SC-28(1) — Evidence Tracking | D1: Contrôle SC-28(1) — Suivi des preuves
A2: Control Information | D2: Informations du contrôle
A3: Control Identifier | B3: SC-28(1) | D3: Identifiant du contrôle | E3: SC-28(1)
A4: Family | B4: Protection of Information At Rest | D4: Famille | E4: Protection de l’information inactive
A5: Profile | B5: CCCS Medium / PBMM Moderate | D5: Profil | E5: CCCS Moyen / PBMM Modéré
A6: Primary Evidence Tool | D6: Outil de preuve principal
A7: Contributing Tools | D7: Outils contributeurs
A8: Control Description | B8: PROTECTION OF INFORMATION AT REST | CRYPTOGRAPHIC PROTECTION The information system implements cryptographic mechanisms to prevent unauthorized disclosure and modification of all information not cleared for public release and all data with a higher than low integrity requirements. | D8: Description du contrôle | E8: PROTECTION DE L’INFORMATION INACTIVE | PROTECTION CRYPTOGRAPHIQUE Le système d’information met en œuvre des mécanismes cryptographiques pour prévenir la divulgation et la modification non autorisées de tous les renseignements dont la diffusion publique n’est pas autorisée et de toutes les données pour lesquelles les exigences d’intégrité ne sont pas faibles.
A9: Supplemental Guidance | B9: Selection of cryptographic mechanisms is based on the need to protect the confidentiality and integrity of organizational information. The strength of mechanism is commensurate with the security category and/or classification of the information. This control enhancement applies to significant concentrations of digital media in organizational areas designated for media storage and also to limited quantities of media generally associated with information system components in operational environments (e.g., portable storage devices, mobile devices). Organizations have the flexibility to either encrypt all information on storage devices (i.e., full disk encryption) or encrypt specific data structures (e.g., files, records, or fields). Organizations employing cryptographic mechanisms to protect information at rest also consider cryptographic key management solutions. Related controls: AC-19, SC-12. | D9: Directives supplémentaires | E9: Le choix des mécanismes cryptographiques est fonction du besoin de protection de la confidentialité et de l’intégrité de l’information de l’organisation. La force du mécanisme est proportionnelle à la catégorie de sécurité ou à la classification de l’information. Cette amélioration du contrôle s’applique aux concentrations importantes de supports numériques dans les zones de l’organisation qui sont désignées pour le stockage des supports, et également aux quantités limitées de supports généralement associés aux composants de systèmes d’information dans les environnements opérationnels (p. ex., dispositifs de stockage portatifs, appareils mobiles). Les organisations ont la possibilité de chiffrer toute l’information sur les dispositifs de stockage (c.-à-d. le chiffrement complet du disque) ou de chiffrer des structures de données particulières (p. ex., fichiers, enregistrements ou champs). Les organisations qui utilisent des mécanismes cryptographiques pour protéger l’information inactive envisagent également des solutions de gestion des clés cryptographiques. Contrôles connexes : AC-19, SC-12.
A10: Test Case | D10: Cas de test
A11: Test | B11: TEST-SC-28(1) | D11: Test | E11: TEST-SC-28(1)
A12: Requirement ID | B12: SC-28(1) | D12: ID Exigence | E12: SC-28(1)
A13: Component | D13: Composant
A14: Requirement | D14: Exigence
A15: Contextual Design Description | D15: Description contextuelle du design
A16: Evidence Provided | D16: Preuve fournie
A17: Preparer Sign Off (Initials, Date) | D17: Signataire préparateur (Initiales, Date)
A18: Owner Sign Off (Initials, Date) | D18: Signataire propriétaire (Initiales, Date)
A19: Assessor Sign Off (Initials, Date) | D19: Signataire évaluateur (Initiales, Date)
A20: Status | B20: Not Started | D20: Statut | E20: Non commencé
A21: Comments | D21: Commentaires

Sheet SI-4-2
A1: Control SI-4(2) — Evidence Tracking | D1: Contrôle SI-4(2) — Suivi des preuves
A2: Control Information | D2: Informations du contrôle
A3: Control Identifier | B3: SI-4(2) | D3: Identifiant du contrôle | E3: SI-4(2)
A4: Family | B4: Information System Monitoring | D4: Famille | E4: Surveillance du système d’information
A5: Profile | B5: CCCS Medium / PBMM Moderate | D5: Profil | E5: CCCS Moyen / PBMM Modéré
A6: Primary Evidence Tool | D6: Outil de preuve principal
A7: Contributing Tools | D7: Outils contributeurs
A8: Control Description | B8: INFORMATION SYSTEM MONITORING | AUTOMATED TOOLS FOR REAL-TIME ANALYSIS The organization employs automated tools to support near real-time analysis of events. | D8: Description du contrôle | E8: SURVEILLANCE DU SYSTÈME D’INFORMATION | OUTILS AUTOMATISÉS POUR L’ANALYSE EN TEMPS RÉEL L’organisation utilise des outils automatisés pour appuyer l’analyse des événements en temps quasi réel.
A9: Supplemental Guidance | B9: Automated tools include, for example, host-based, network-based, transport-based, or storage-based event monitoring tools or Security Information and Event Management (SIEM) technologies that provide real time analysis of alerts and/or notifications generated by organizational information systems. | D9: Directives supplémentaires | E9: Les outils automatisés comprennent, par exemple, des outils de surveillance des événements basés sur l’hôte, le réseau, le transport ou le stockage, ou des technologies de gestion de l’information et des événements de sécurité (SIEM) qui fournissent une analyse en temps réel des alertes et/ou des notifications générées par les systèmes d’information de l’organisation.
A10: Test Case | D10: Cas de test
A11: Test | B11: TEST-SI-4(2) | D11: Test | E11: TEST-SI-4(2)
A12: Requirement ID | B12: SI-4(2) | D12: ID Exigence | E12: SI-4(2)
A13: Component | D13: Composant
A14: Requirement | D14: Exigence
A15: Contextual Design Description | D15: Description contextuelle du design
A16: Evidence Provided | D16: Preuve fournie
A17: Preparer Sign Off (Initials, Date) | D17: Signataire préparateur (Initiales, Date)
A18: Owner Sign Off (Initials, Date) | D18: Signataire propriétaire (Initiales, Date)
A19: Assessor Sign Off (Initials, Date) | D19: Signataire évaluateur (Initiales, Date)
A20: Status | B20: Not Started | D20: Statut | E20: Non commencé
A21: Comments | D21: Commentaires

Sheet SI-6
A1: Control SI-6 — Evidence Tracking | D1: Contrôle SI-6 — Suivi des preuves
A2: Control Information | D2: Informations du contrôle
A3: Control Identifier | B3: SI-6 | D3: Identifiant du contrôle | E3: SI-6
A4: Family | B4: Security Functional Verification | D4: Famille | E4: Vérification fonctionnelle de la sécurité
A5: Profile | B5: CCCS Medium / PBMM Moderate | D5: Profil | E5: CCCS Moyen / PBMM Modéré
A6: Primary Evidence Tool | D6: Outil de preuve principal
A7: Contributing Tools | D7: Outils contributeurs
A8: Control Description | B8: (A) The information system verifies the correct operation of organization-defined security functions. (B) The information system performs this verification organization-defined system transitional states including at least system startup and restart and at least monthly. (C) The information system notifies organization-defined personnel or roles including system administrators and security personnel of failed security verification tests. (D) The information system takes organization-defined action(s) when anomalies are discovered and notifies system administrators and security personnel. | D8: Description du contrôle | E8: (A) Le système d’information vérifie le bon fonctionnement des fonctions de sécurité définies par l’organisation. (B) Le système d’information effectue cette vérification des phases de transition définies par l’organisation, y compris au moins le démarrage et le redémarrage du système et au moins une fois par mois. (C) Le système d’information informe le personnel ou les rôles définis par l’organisation, y compris les administrateurs de système et le personnel de sécurité, des tests de vérification de sécurité qui ont échoué. (D) Le système d’information prend des mesures définies par l’organisation lorsque des anomalies sont découvertes et en informe les administrateurs du système et le personnel de sécurité.
A9: Supplemental Guidance | B9: Transitional states for information systems include, for example, system start-up, restart, shutdown, and abort. Notifications provided by information systems include, for example, electronic alerts to system administrators, messages to local computer consoles, and/or hardware indications such as lights. Related controls: CA-7, CM-6 | D9: Directives supplémentaires | E9: Les phases de transition pour les systèmes d’information comprennent, par exemple, le démarrage, le redémarrage, l’arrêt et l’interruption du système. Les notifications fournies par les systèmes d’information comprennent, par exemple, des alertes électroniques aux administrateurs du système, des messages aux consoles d’ordinateurs locales ou des indications matérielles telles que des voyants. Contrôles connexes : CA-7, CM-6
A10: Test Case | D10: Cas de test
A11: Test | B11: TEST-SI-6 | D11: Test | E11: TEST-SI-6
A12: Requirement ID | B12: SI-6 | D12: ID Exigence | E12: SI-6
A13: Component | D13: Composant
A14: Requirement | D14: Exigence
A15: Contextual Design Description | D15: Description contextuelle du design
A16: Evidence Provided | D16: Preuve fournie
A17: Preparer Sign Off (Initials, Date) | D17: Signataire préparateur (Initiales, Date)
A18: Owner Sign Off (Initials, Date) | D18: Signataire propriétaire (Initiales, Date)
A19: Assessor Sign Off (Initials, Date) | D19: Signataire évaluateur (Initiales, Date)
A20: Status | B20: Not Started | D20: Statut | E20: Non commencé
A21: Comments | D21: Commentaires
