Workbook

Sheet DASHBOARD
A1: DASHBOARD — PBMM Evidence: Compute
A2: Control ID | B2: Control Name | C2: Primary Tool | D2: Tab | E2: Status
A3: AC-6 | B3: Least Privilege | D3: AC-6 | E3: ='AC-6'!B20 -> Not Started
A4: AC-6(1) | B4: Least Privilege | D4: AC-6-1 | E4: ='AC-6-1'!B20 -> Not Started
A5: AC-7 | B5: Unsuccessful Login Attempts | D5: AC-7 | E5: ='AC-7'!B20 -> Not Started
A6: AC-8 | B6: System Use Notification | D6: AC-8 | E6: ='AC-8'!B20 -> Not Started
A7: AC-11 | B7: Session Lock | D7: AC-11 | E7: ='AC-11'!B20 -> Not Started
A8: AC-11(1) | B8: Session Lock | D8: AC-11-1 | E8: ='AC-11-1'!B20 -> Not Started
A9: AC-12 | B9: Session Termination | D9: AC-12 | E9: ='AC-12'!B20 -> Not Started
A10: AC-17(1) | B10: Remote Access | D10: AC-17-1 | E10: ='AC-17-1'!B20 -> Not Started
A11: AC-17(2) | B11: Remote Access | D11: AC-17-2 | E11: ='AC-17-2'!B20 -> Not Started
A12: AC-17(100) | B12: Remote Access | D12: AC-17-100 | E12: ='AC-17-100'!B20 -> Not Started
A13: AU-2 | B13: Auditable Events | D13: AU-2 | E13: ='AU-2'!B20 -> Not Started
A14: AU-3 | B14: Content of Audit Records | D14: AU-3 | E14: ='AU-3'!B20 -> Not Started
A15: AU-3(1) | B15: Content of Audit Records | D15: AU-3-1 | E15: ='AU-3-1'!B20 -> Not Started
A16: AU-9(2) | B16: Protection of Audit Information | D16: AU-9-2 | E16: ='AU-9-2'!B20 -> Not Started
A17: AU-12 | B17: Audit Generation | D17: AU-12 | E17: ='AU-12'!B20 -> Not Started
A18: CA-3(5) | B18: Information System Connections | D18: CA-3-5 | E18: ='CA-3-5'!B20 -> Not Started
A19: CA-9 | B19: Internal System Connections | D19: CA-9 | E19: ='CA-9'!B20 -> Not Started
A20: CM-6 | B20: Configuration Settings | D20: CM-6 | E20: ='CM-6'!B20 -> Not Started
A21: CM-7 | B21: Least Functionality | D21: CM-7 | E21: ='CM-7'!B20 -> Not Started
A22: CM-7(1) | B22: Least Functionality | D22: CM-7-1 | E22: ='CM-7-1'!B20 -> Not Started
A23: CM-7(5) | B23: Least Functionality | D23: CM-7-5 | E23: ='CM-7-5'!B20 -> Not Started
A24: CM-11 | B24: User Installed Software | D24: CM-11 | E24: ='CM-11'!B20 -> Not Started
A25: CP-6 | B25: Alternate Storage Site | D25: CP-6 | E25: ='CP-6'!B20 -> Not Started
A26: CP-6(2) | B26: Alternate Storage Site | D26: CP-6-2 | E26: ='CP-6-2'!B20 -> Not Started
A27: CP-7 | B27: Alternate Processing Site | D27: CP-7 | E27: ='CP-7'!B20 -> Not Started
A28: CP-7(4) | B28: Alternate Processing Site | D28: CP-7-4 | E28: ='CP-7-4'!B20 -> Not Started
A29: CP-9 | B29: Information System Backup | D29: CP-9 | E29: ='CP-9'!B20 -> Not Started
A30: CP-9(1) | B30: Information System Backup | D30: CP-9-1 | E30: ='CP-9-1'!B20 -> Not Started
A31: CP-9(2) | B31: Information System Backup | D31: CP-9-2 | E31: ='CP-9-2'!B20 -> Not Started
A32: CP-9(5) | B32: Information System Backup | D32: CP-9-5 | E32: ='CP-9-5'!B20 -> Not Started
A33: CP-10 | B33: Information System Recovery and Reconstitution | D33: CP-10 | E33: ='CP-10'!B20 -> Not Started
A34: CP-10(4) | B34: Information System Recovery and Reconstitution | D34: CP-10-4 | E34: ='CP-10-4'!B20 -> Not Started
A35: IA-5(6) | B35: Authenticator Management | D35: IA-5-6 | E35: ='IA-5-6'!B20 -> Not Started
A36: IA-5(7) | B36: Authenticator Management | D36: IA-5-7 | E36: ='IA-5-7'!B20 -> Not Started
A37: SA-9(5) | B37: External Information System Services | D37: SA-9-5 | E37: ='SA-9-5'!B20 -> Not Started
A38: SA-10(1) | B38: Developer Configuration Management | D38: SA-10-1 | E38: ='SA-10-1'!B20 -> Not Started
A39: SC-2 | B39: Application Partitioning | D39: SC-2 | E39: ='SC-2'!B20 -> Not Started
A40: SC-6 | B40: Resource Availability | D40: SC-6 | E40: ='SC-6'!B20 -> Not Started
A41: SC-7(7) | B41: Boundary Protection | D41: SC-7-7 | E41: ='SC-7-7'!B20 -> Not Started
A42: SC-7(12) | B42: Boundary Protection | D42: SC-7-12 | E42: ='SC-7-12'!B20 -> Not Started
A43: SC-8 | B43: Transmission Confidentiality and Integrity | D43: SC-8 | E43: ='SC-8'!B20 -> Not Started
A44: SC-8(1) | B44: Transmission Confidentiality and Integrity | D44: SC-8-1 | E44: ='SC-8-1'!B20 -> Not Started
A45: SC-10 | B45: Network Disconnect | D45: SC-10 | E45: ='SC-10'!B20 -> Not Started
A46: SC-13 | B46: Cryptographic Protection | D46: SC-13 | E46: ='SC-13'!B20 -> Not Started
A47: SC-18 | B47: Mobile Code | D47: SC-18 | E47: ='SC-18'!B20 -> Not Started
A48: SC-18(3) | B48: Mobile Code | D48: SC-18-3 | E48: ='SC-18-3'!B20 -> Not Started
A49: SC-18(4) | B49: Mobile Code | D49: SC-18-4 | E49: ='SC-18-4'!B20 -> Not Started
A50: SC-23 | B50: Session Authenticity | D50: SC-23 | E50: ='SC-23'!B20 -> Not Started
A51: SC-23(1) | B51: Session Authenticity | D51: SC-23-1 | E51: ='SC-23-1'!B20 -> Not Started
A52: SC-28 | B52: Protection of Information At Rest | D52: SC-28 | E52: ='SC-28'!B20 -> Not Started
A53: SC-28(1) | B53: Protection of Information At Rest | D53: SC-28-1 | E53: ='SC-28-1'!B20 -> Not Started
A54: SC-39 | B54: Process Isolation | D54: SC-39 | E54: ='SC-39'!B20 -> Not Started
A55: SI-4(2) | B55: Information System Monitoring | D55: SI-4-2 | E55: ='SI-4-2'!B20 -> Not Started
A56: SI-4(4) | B56: Information System Monitoring | D56: SI-4-4 | E56: ='SI-4-4'!B20 -> Not Started
A57: SI-4(23) | B57: Information System Monitoring | D57: SI-4-23 | E57: ='SI-4-23'!B20 -> Not Started
A58: SI-6 | B58: Security Functional Verification | D58: SI-6 | E58: ='SI-6'!B20 -> Not Started
A59: SI-7 | B59: Software, Firmware, and Information Integrity | D59: SI-7 | E59: ='SI-7'!B20 -> Not Started
A60: SI-7(1) | B60: Software, Firmware, and Information Integrity | D60: SI-7-1 | E60: ='SI-7-1'!B20 -> Not Started
A61: SI-11 | B61: Error Handling | D61: SI-11 | E61: ='SI-11'!B20 -> Not Started
A62: SI-16 | B62: Memory Protection | D62: SI-16 | E62: ='SI-16'!B20 -> Not Started
A64: Completion Metrics
A65: Total Controls | E65: =60 -> 60
A66: Not Started | E66: =COUNTIF(E3:E62,"Not Started") -> 60
A67: In Progress | E67: =COUNTIF(E3:E62,"In Progress") -> 0
A68: Evidence Provided | E68: =COUNTIF(E3:E62,"Evidence Provided") -> 0
A69: Under Review | E69: =COUNTIF(E3:E62,"Under Review") -> 0
A70: Passed | E70: =COUNTIF(E3:E62,"Passed") -> 0
A71: Failed | E71: =COUNTIF(E3:E62,"Failed") -> 0
A72: Accepted Exception | E72: =COUNTIF(E3:E62,"Accepted Exception") -> 0
A73: % Complete | E73: =IFERROR(COUNTIF(E3:E62,"Passed")/60,0) -> 0
A74: % Not Started | E74: =IFERROR(COUNTIF(E3:E62,"Not Started")/60,0) -> 1

Sheet TABLEAU_DE_BORD
A1: TABLEAU DE BORD — Suivi PBMM : Compute
A2: ID Contrôle | B2: Nom du contrôle | C2: Outil principal | D2: Onglet | E2: Statut
A3: AC-6 | B3: Moindre privilège | D3: AC-6 | E3: ='AC-6'!E20 -> Non commencé
A4: AC-6(1) | B4: Moindre privilège | D4: AC-6-1 | E4: ='AC-6-1'!E20 -> Non commencé
A5: AC-7 | B5: Tentatives infructueuses d’ouverture de session | D5: AC-7 | E5: ='AC-7'!E20 -> Non commencé
A6: AC-8 | B6: Avis d’utilisation du système | D6: AC-8 | E6: ='AC-8'!E20 -> Non commencé
A7: AC-11 | B7: Verrouillage de session | D7: AC-11 | E7: ='AC-11'!E20 -> Non commencé
A8: AC-11(1) | B8: Verrouillage de session | D8: AC-11-1 | E8: ='AC-11-1'!E20 -> Non commencé
A9: AC-12 | B9: Fermeture de session | D9: AC-12 | E9: ='AC-12'!E20 -> Non commencé
A10: AC-17(1) | B10: Accès à distance | D10: AC-17-1 | E10: ='AC-17-1'!E20 -> Non commencé
A11: AC-17(2) | B11: Accès à distance | D11: AC-17-2 | E11: ='AC-17-2'!E20 -> Non commencé
A12: AC-17(100) | B12: Accès à distance | D12: AC-17-100 | E12: ='AC-17-100'!E20 -> Non commencé
A13: AU-2 | B13: Événements vérifiables | D13: AU-2 | E13: ='AU-2'!E20 -> Non commencé
A14: AU-3 | B14: Contenu des enregistrements de vérification | D14: AU-3 | E14: ='AU-3'!E20 -> Non commencé
A15: AU-3(1) | B15: Contenu des enregistrements de vérification | D15: AU-3-1 | E15: ='AU-3-1'!E20 -> Non commencé
A16: AU-9(2) | B16: Protection des renseignements de vérification | D16: AU-9-2 | E16: ='AU-9-2'!E20 -> Non commencé
A17: AU-12 | B17: Génération des vérifications | D17: AU-12 | E17: ='AU-12'!E20 -> Non commencé
A18: CA-3(5) | B18: Connexions aux systèmes d’information | D18: CA-3-5 | E18: ='CA-3-5'!E20 -> Non commencé
A19: CA-9 | B19: Connexions internes au système | D19: CA-9 | E19: ='CA-9'!E20 -> Non commencé
A20: CM-6 | B20: Paramètres de configuration | D20: CM-6 | E20: ='CM-6'!E20 -> Non commencé
A21: CM-7 | B21: Moindre fonctionnalité | D21: CM-7 | E21: ='CM-7'!E20 -> Non commencé
A22: CM-7(1) | B22: Moindre fonctionnalité | D22: CM-7-1 | E22: ='CM-7-1'!E20 -> Non commencé
A23: CM-7(5) | B23: Moindre fonctionnalité | D23: CM-7-5 | E23: ='CM-7-5'!E20 -> Non commencé
A24: CM-11 | B24: Logiciel installé par l’utilisateur | D24: CM-11 | E24: ='CM-11'!E20 -> Non commencé
A25: CP-6 | B25: Site de stockage auxiliaire | D25: CP-6 | E25: ='CP-6'!E20 -> Non commencé
A26: CP-6(2) | B26: Site de stockage auxiliaire | D26: CP-6-2 | E26: ='CP-6-2'!E20 -> Non commencé
A27: CP-7 | B27: Site de traitement auxiliaire | D27: CP-7 | E27: ='CP-7'!E20 -> Non commencé
A28: CP-7(4) | B28: Site de traitement auxiliaire | D28: CP-7-4 | E28: ='CP-7-4'!E20 -> Non commencé
A29: CP-9 | B29: Sauvegarde du système d’information | D29: CP-9 | E29: ='CP-9'!E20 -> Non commencé
A30: CP-9(1) | B30: Sauvegarde du système d’information | D30: CP-9-1 | E30: ='CP-9-1'!E20 -> Non commencé
A31: CP-9(2) | B31: Sauvegarde du système d’information | D31: CP-9-2 | E31: ='CP-9-2'!E20 -> Non commencé
A32: CP-9(5) | B32: Sauvegarde du système d’information | D32: CP-9-5 | E32: ='CP-9-5'!E20 -> Non commencé
A33: CP-10 | B33: Reprise et reconstitution du système d’information | D33: CP-10 | E33: ='CP-10'!E20 -> Non commencé
A34: CP-10(4) | B34: Reprise et reconstitution du système d’information | D34: CP-10-4 | E34: ='CP-10-4'!E20 -> Non commencé
A35: IA-5(6) | B35: Gestion des authentifiants | D35: IA-5-6 | E35: ='IA-5-6'!E20 -> Non commencé
A36: IA-5(7) | B36: Gestion des authentifiants | D36: IA-5-7 | E36: ='IA-5-7'!E20 -> Non commencé
A37: SA-9(5) | B37: Services de systèmes d’information externes | D37: SA-9-5 | E37: ='SA-9-5'!E20 -> Non commencé
A38: SA-10(1) | B38: Gestion de la configuration par le développeur | D38: SA-10-1 | E38: ='SA-10-1'!E20 -> Non commencé
A39: SC-2 | B39: Partitionnement des applications | D39: SC-2 | E39: ='SC-2'!E20 -> Non commencé
A40: SC-6 | B40: Disponibilité des ressources | D40: SC-6 | E40: ='SC-6'!E20 -> Non commencé
A41: SC-7(7) | B41: Protection des frontières | D41: SC-7-7 | E41: ='SC-7-7'!E20 -> Non commencé
A42: SC-7(12) | B42: Protection des frontières | D42: SC-7-12 | E42: ='SC-7-12'!E20 -> Non commencé
A43: SC-8 | B43: Confidentialité et intégrité des transmissions | D43: SC-8 | E43: ='SC-8'!E20 -> Non commencé
A44: SC-8(1) | B44: Confidentialité et intégrité des transmissions | D44: SC-8-1 | E44: ='SC-8-1'!E20 -> Non commencé
A45: SC-10 | B45: Débranchement du réseau | D45: SC-10 | E45: ='SC-10'!E20 -> Non commencé
A46: SC-13 | B46: Protection cryptographique | D46: SC-13 | E46: ='SC-13'!E20 -> Non commencé
A47: SC-18 | B47: Code mobile | D47: SC-18 | E47: ='SC-18'!E20 -> Non commencé
A48: SC-18(3) | B48: Code mobile | D48: SC-18-3 | E48: ='SC-18-3'!E20 -> Non commencé
A49: SC-18(4) | B49: Code mobile | D49: SC-18-4 | E49: ='SC-18-4'!E20 -> Non commencé
A50: SC-23 | B50: Authenticité des sessions | D50: SC-23 | E50: ='SC-23'!E20 -> Non commencé
A51: SC-23(1) | B51: Authenticité des sessions | D51: SC-23-1 | E51: ='SC-23-1'!E20 -> Non commencé
A52: SC-28 | B52: Protection de l’information inactive | D52: SC-28 | E52: ='SC-28'!E20 -> Non commencé
A53: SC-28(1) | B53: Protection de l’information inactive | D53: SC-28-1 | E53: ='SC-28-1'!E20 -> Non commencé
A54: SC-39 | B54: Isolement des processus | D54: SC-39 | E54: ='SC-39'!E20 -> Non commencé
A55: SI-4(2) | B55: Surveillance du système d’information | D55: SI-4-2 | E55: ='SI-4-2'!E20 -> Non commencé
A56: SI-4(4) | B56: Surveillance du système d’information | D56: SI-4-4 | E56: ='SI-4-4'!E20 -> Non commencé
A57: SI-4(23) | B57: Surveillance du système d’information | D57: SI-4-23 | E57: ='SI-4-23'!E20 -> Non commencé
A58: SI-6 | B58: Vérification fonctionnelle de la sécurité | D58: SI-6 | E58: ='SI-6'!E20 -> Non commencé
A59: SI-7 | B59: Logiciels, micrologiciels et intégrité de l’information | D59: SI-7 | E59: ='SI-7'!E20 -> Non commencé
A60: SI-7(1) | B60: Logiciels, micrologiciels et intégrité de l’information | D60: SI-7-1 | E60: ='SI-7-1'!E20 -> Non commencé
A61: SI-11 | B61: Traitement des erreurs | D61: SI-11 | E61: ='SI-11'!E20 -> Non commencé
A62: SI-16 | B62: Protection de la mémoire | D62: SI-16 | E62: ='SI-16'!E20 -> Non commencé
A64: Métriques de complétude
A65: Nombre total de contrôles | E65: =60 -> 60
A66: Non commencés | E66: =COUNTIF(E3:E62,"Non commencé") -> 60
A67: En cours | E67: =COUNTIF(E3:E62,"En cours") -> 0
A68: Preuve fournie | E68: =COUNTIF(E3:E62,"Preuve fournie") -> 0
A69: En révision | E69: =COUNTIF(E3:E62,"En révision") -> 0
A70: Réussi | E70: =COUNTIF(E3:E62,"Réussi") -> 0
A71: Échec | E71: =COUNTIF(E3:E62,"Échec") -> 0
A72: Exception acceptée | E72: =COUNTIF(E3:E62,"Exception acceptée") -> 0
A73: % Complété | E73: =IFERROR(COUNTIF(E3:E62,"Réussi")/60,0) -> 0
A74: % Non commencés | E74: =IFERROR(COUNTIF(E3:E62,"Non commencé")/60,0) -> 1

Sheet AC-6
A1: Control AC-6 — Evidence Tracking | D1: Contrôle AC-6 — Suivi des preuves
A2: Control Information | D2: Informations du contrôle
A3: Control Identifier | B3: AC-6 | D3: Identifiant du contrôle | E3: AC-6
A4: Family | B4: Least Privilege | D4: Famille | E4: Moindre privilège
A5: Profile | B5: CCCS Medium / PBMM Moderate | D5: Profil | E5: CCCS Moyen / PBMM Modéré
A6: Primary Evidence Tool | D6: Outil de preuve principal
A7: Contributing Tools | D7: Outils contributeurs
A8: Control Description | B8: (A) The organization employs the principle of least privilege, allowing only authorized accesses for users (or processes acting on behalf of users) which are necessary to accomplish assigned tasks in accordance with organizational missions and business functions. | D8: Description du contrôle | E8: (A) L’organisation utilise le principe du moindre privilège, qui permet seulement les accès autorisés aux utilisateurs (ou aux processus qui agissent pour le compte des utilisateurs) qui sont nécessaires pour accomplir les tâches assignées conformément aux missions et aux fonctions opérationnelles de l’organisation.
A9: Supplemental Guidance | B9: Organizations employ least privilege for specific duties and information systems. The principle of least privilege is also applied to information system processes, ensuring that the processes operate at privilege levels no higher than necessary to accomplish required organizational missions/business functions. Organizations consider the creation of additional processes, roles, and information system accounts as necessary, to achieve least privilege. Organizations also apply least privilege to the development, implementation, and operation of organizational information systems. Related controls: AC-2, AC-3, AC-5, CM-6, CM-7, PL-2 | D9: Directives supplémentaires | E9: Les organisations utilisent le moindre privilège pour certaines tâches et certains systèmes d’information. Le principe du moindre privilège s’applique également aux processus du système d’information, ce qui fait en sorte que les processus ne fonctionnent pas à des niveaux de privilège plus élevés que nécessaire pour accomplir les missions et les fonctions opérationnelles requises de l’organisation. Les organisations envisagent la création de processus, de rôles et de comptes de système d’information supplémentaires lorsque nécessaire, pour obtenir le moindre privilège. Les organisations appliquent également le moindre privilège au développement, à la mise en œuvre et à l’exploitation de leurs systèmes d’information. Contrôles connexes : AC-2, AC-3, AC-5, CM-6, CM-7, PL-2
A10: Test Case | D10: Cas de test
A11: Test | B11: TEST-AC-6 | D11: Test | E11: TEST-AC-6
A12: Requirement ID | B12: AC-6 | D12: ID Exigence | E12: AC-6
A13: Component | D13: Composant
A14: Requirement | D14: Exigence
A15: Contextual Design Description | D15: Description contextuelle du design
A16: Evidence Provided | D16: Preuve fournie
A17: Preparer Sign Off (Initials, Date) | D17: Signataire préparateur (Initiales, Date)
A18: Owner Sign Off (Initials, Date) | D18: Signataire propriétaire (Initiales, Date)
A19: Assessor Sign Off (Initials, Date) | D19: Signataire évaluateur (Initiales, Date)
A20: Status | B20: Not Started | D20: Statut | E20: Non commencé
A21: Comments | D21: Commentaires

Sheet AC-6-1
A1: Control AC-6(1) — Evidence Tracking | D1: Contrôle AC-6(1) — Suivi des preuves
A2: Control Information | D2: Informations du contrôle
A3: Control Identifier | B3: AC-6(1) | D3: Identifiant du contrôle | E3: AC-6(1)
A4: Family | B4: Least Privilege | D4: Famille | E4: Moindre privilège
A5: Profile | B5: CCCS Medium / PBMM Moderate | D5: Profil | E5: CCCS Moyen / PBMM Modéré
A6: Primary Evidence Tool | D6: Outil de preuve principal
A7: Contributing Tools | D7: Outils contributeurs
A8: Control Description | B8: LEAST PRIVILEGE | AUTHORIZE ACCESS TO SECURITY FUNCTIONS The organization explicitly authorizes access to all security functions not publicly accessible and all security-relevant information not publicly available. | D8: Description du contrôle | E8: MOINDRE PRIVILÈGE | AUTORISATION D’ACCÈS AUX FONCTIONS DE SÉCURITÉ L’organisation autorise explicitement l’accès à toutes les fonctions de sécurité qui ne sont pas accessibles au public et à toute l’information pertinente à la sécurité qui n’est pas accessible au public.
A9: Supplemental Guidance | B9: Security functions include, for example, establishing system accounts, configuring access authorizations (i.e., permissions, privileges), setting events to be audited, and setting intrusion detection parameters. Security-relevant information includes, for example, filtering rules for routers/firewalls, cryptographic key management information, configuration parameters for security services, and access control lists. Explicitly authorized personnel include, for example, security administrators, system and network administrators, system security officers, system maintenance personnel, system programmers, and other privileged users. Related controls: AC-17, AC-18, AC-19. | D9: Directives supplémentaires | E9: Les fonctions de sécurité comprennent, par exemple, l’établissement des comptes système, la configuration des autorisations d’accès (c.-à-d. les permissions, les privilèges), le réglage des événements à vérifier, et l’établissement des paramètres de détection des intrusions. Les renseignements pertinents pour la sécurité comprennent, par exemple, les règles de filtrage pour les routeurs/pare-feu, l’information de gestion des clés cryptographiques, les paramètres de configuration pour les services de sécurité et les listes de contrôle d’accès. Le personnel explicitement autorisé comprend, par exemple, les administrateurs de la sécurité, les administrateurs de systèmes et de réseaux, les agents de sécurité des systèmes, le personnel de maintenance des systèmes, les programmeurs de systèmes et d’autres utilisateurs privilégiés. Contrôles connexes : AC-17, AC-18, AC-19.
A10: Test Case | D10: Cas de test
A11: Test | B11: TEST-AC-6(1) | D11: Test | E11: TEST-AC-6(1)
A12: Requirement ID | B12: AC-6(1) | D12: ID Exigence | E12: AC-6(1)
A13: Component | D13: Composant
A14: Requirement | D14: Exigence
A15: Contextual Design Description | D15: Description contextuelle du design
A16: Evidence Provided | D16: Preuve fournie
A17: Preparer Sign Off (Initials, Date) | D17: Signataire préparateur (Initiales, Date)
A18: Owner Sign Off (Initials, Date) | D18: Signataire propriétaire (Initiales, Date)
A19: Assessor Sign Off (Initials, Date) | D19: Signataire évaluateur (Initiales, Date)
A20: Status | B20: Not Started | D20: Statut | E20: Non commencé
A21: Comments | D21: Commentaires

Sheet AC-7
A1: Control AC-7 — Evidence Tracking | D1: Contrôle AC-7 — Suivi des preuves
A2: Control Information | D2: Informations du contrôle
A3: Control Identifier | B3: AC-7 | D3: Identifiant du contrôle | E3: AC-7
A4: Family | B4: Unsuccessful Login Attempts | D4: Famille | E4: Tentatives infructueuses d’ouverture de session
A5: Profile | B5: CCCS Medium / PBMM Moderate | D5: Profil | E5: CCCS Moyen / PBMM Modéré
A6: Primary Evidence Tool | D6: Outil de preuve principal
A7: Contributing Tools | D7: Outils contributeurs
A8: Control Description | B8: (A) The information system enforces a limit of not more than three consecutive invalid logon attempts by a user during a 15-minute time period. (B) The information system automatically locks the account/node for a minimum of three (3) hours or until unlocked by an administrator. | D8: Description du contrôle | E8: (A) Le système d’information impose une limite de trois tentatives invalides consécutives d’ouverture de session par un utilisateur pendant une période de 15 minutes. (B) Le système d’information verrouille automatiquement le compte ou le nœud pendant au moins trois (3) heures ou jusqu’à ce qu’un administrateur le déverrouille.
A9: Supplemental Guidance | B9: Due to the potential for denial of service, automatic lockouts initiated by the information system are usually temporary and automatically release after a predetermined time period established by the organization. If a delay algorithm is selected, the organization may choose to employ different algorithms for different information system components based on the capabilities of those components. Response to unsuccessful login attempts may be implemented at both the operating system and the application levels. This control applies to all accesses other than those accesses explicitly identified and documented by the organization in AC-14. This security control/enhancement requires careful balance between usability and security. Care needs to be taken to ensure that the appropriate balance between the two seemingly conflicting requirements is achieved. If possible, an increasing time-out period should be used to deter determined attackers. For example, an original time-out of 5 minutes can become 10 minutes after the next 3 unsuccessful attempts, then 20 minutes, then 40 minutes, etc. | D9: Directives supplémentaires | E9: En raison de la possibilité de refus de service, les verrouillages automatiques déclenchés par le système d’information sont habituellement temporaires et automatiquement annulés après une période prédéterminée établie par l’organisation. Si un algorithme d’attente est sélectionné, l’organisation peut choisir d’utiliser différents algorithmes pour différents composants du système d’information en fonction des capacités de ces composants. La réponse aux tentatives d’ouverture de session infructueuses peut être mise en œuvre à la fois au niveau du système d’exploitation et de l’application. Ce contrôle s’applique à tous les accès autres que ceux explicitement identifiés et documentés par l’organisation dans AC-14. Ce contrôle ou cette amélioration de sécurité exige un équilibre prudent entre la facilité d’utilisation et la sécurité. Il faut veiller à assurer l’équilibre approprié entre ces deux exigences apparemment contradictoires. Dans la mesure du possible, une période de temporisation plus longue devrait être utilisée pour dissuader les attaquants déterminés. Par exemple, une temporisation initiale de 5 minutes peut devenir 10 minutes après les 3 tentatives infructueuses suivantes, puis 20 minutes, puis 40 minutes, etc.
A10: Test Case | D10: Cas de test
A11: Test | B11: TEST-AC-7 | D11: Test | E11: TEST-AC-7
A12: Requirement ID | B12: AC-7 | D12: ID Exigence | E12: AC-7
A13: Component | D13: Composant
A14: Requirement | D14: Exigence
A15: Contextual Design Description | D15: Description contextuelle du design
A16: Evidence Provided | D16: Preuve fournie
A17: Preparer Sign Off (Initials, Date) | D17: Signataire préparateur (Initiales, Date)
A18: Owner Sign Off (Initials, Date) | D18: Signataire propriétaire (Initiales, Date)
A19: Assessor Sign Off (Initials, Date) | D19: Signataire évaluateur (Initiales, Date)
A20: Status | B20: Not Started | D20: Statut | E20: Non commencé
A21: Comments | D21: Commentaires

Sheet AC-8
A1: Control AC-8 — Evidence Tracking | D1: Contrôle AC-8 — Suivi des preuves
A2: Control Information | D2: Informations du contrôle
A3: Control Identifier | B3: AC-8 | D3: Identifiant du contrôle | E3: AC-8
A4: Family | B4: System Use Notification | D4: Famille | E4: Avis d’utilisation du système
A5: Profile | B5: CCCS Medium / PBMM Moderate | D5: Profil | E5: CCCS Moyen / PBMM Modéré
A6: Primary Evidence Tool | D6: Outil de preuve principal
A7: Contributing Tools | D7: Outils contributeurs
A8: Control Description | B8: (A) The information system displays to users a organization-defined system use notification message or banner before granting access to the system that provides privacy and security notices in accordance with organization's network use policies. (B) The information system retains the notification message or banner on the screen until users acknowledge the usage conditions and take explicit actions to log on to or further access the information system. (C) The information system for publicly accessible systems: (a) Displays system use information before granting further access; (b) Displays references, if any, to monitoring, recording, or auditing that are consistent with privacy accommodations for such systems that generally prohibit those activities; and (c) Includes a description of the authorized uses of the system. | D8: Description du contrôle | E8: (A) Le système d’information affiche aux utilisateurs une bannière ou un message d’utilisation du système, défini par l’organisation avant d’accorder l’accès au système, qui fournit des avis de confidentialité et de sécurité conformément aux politiques d’utilisation du réseau de l’organisation. (B) Le système d’information maintient le message ou la bannière de notification à l’écran jusqu’à ce que les utilisateurs acceptent les conditions d’utilisation et prennent des mesures explicites pour ouvrir une session ou continuer d’accéder au système d’information. (C) Le système d’information pour les systèmes accessibles au public : (a) Affiche l’information sur l’utilisation du système avant d’accorder l’accès; (b) Affiche les références, le cas échéant, à la surveillance, à l’enregistrement ou à la vérification qui sont conformes aux dispositions de protection de la vie privée pour de tels systèmes qui interdisent généralement ces activités; (c) Comprend une description des utilisations autorisées du système.
A9: Supplemental Guidance | B9: System use notifications can be implemented using messages or warning banners displayed before individuals log in to information systems. System use notifications are used only for access via logon interfaces with human users and are not required when such human interfaces do not exist. Organizations consider system use notification messages/banners displayed in multiple languages based on specific organizational needs and the demographics of information system users. Organizations should also consult with legal services for review and approval of warning banner content | D9: Directives supplémentaires | E9: Les avis d’utilisation du système peuvent être mis en œuvre au moyen de bannières d’avertissement ou de messages affichés avant que les personnes n’ouvrent une session dans les systèmes d’information. Les avis d’utilisation du système sont utilisés uniquement pour l’accès par le biais d’interfaces d’ouverture de session avec des utilisateurs humains et ne sont pas nécessaires en l’absence de telles interfaces humaines. Les organisations envisageront d’utiliser des messages et des bannières d’avis d’utilisation du système affichés dans plusieurs langues en fonction des besoins particuliers de l’organisation et des caractéristiques démographiques des utilisateurs du système d’information. Les organisations doivent également consulter les services juridiques pour l’examen et l’approbation du contenu de la bannière d’avertissement.
A10: Test Case | D10: Cas de test
A11: Test | B11: TEST-AC-8 | D11: Test | E11: TEST-AC-8
A12: Requirement ID | B12: AC-8 | D12: ID Exigence | E12: AC-8
A13: Component | D13: Composant
A14: Requirement | D14: Exigence
A15: Contextual Design Description | D15: Description contextuelle du design
A16: Evidence Provided | D16: Preuve fournie
A17: Preparer Sign Off (Initials, Date) | D17: Signataire préparateur (Initiales, Date)
A18: Owner Sign Off (Initials, Date) | D18: Signataire propriétaire (Initiales, Date)
A19: Assessor Sign Off (Initials, Date) | D19: Signataire évaluateur (Initiales, Date)
A20: Status | B20: Not Started | D20: Statut | E20: Non commencé
A21: Comments | D21: Commentaires

Sheet AC-11
A1: Control AC-11 — Evidence Tracking | D1: Contrôle AC-11 — Suivi des preuves
A2: Control Information | D2: Informations du contrôle
A3: Control Identifier | B3: AC-11 | D3: Identifiant du contrôle | E3: AC-11
A4: Family | B4: Session Lock | D4: Famille | E4: Verrouillage de session
A5: Profile | B5: CCCS Medium / PBMM Moderate | D5: Profil | E5: CCCS Moyen / PBMM Modéré
A6: Primary Evidence Tool | D6: Outil de preuve principal
A7: Contributing Tools | D7: Outils contributeurs
A8: Control Description | B8: (A) The information system prevents further access to the system by initiating a session lock after 15 minutes of inactivity or upon receiving a request from a user. (B) The information system retains the session lock until the user re-establishes access using established identification and authentication procedures. | D8: Description du contrôle | E8: (A) Le système d’information empêche tout accès supplémentaire au système en amorçant un verrouillage de session après 15 minutes d’inactivité ou après en avoir reçu la demande de la part d’un utilisateur. (B) Le système d’information maintient le verrouillage de session jusqu’à ce que l’utilisateur rétablisse l’accès en utilisant les procédures d’identification et d’authentification établies.
A9: Supplemental Guidance | B9: Session locks are temporary actions taken when users stop work and move away from the immediate vicinity of information systems but do not want to log out because of the temporary nature of their absences. Session locks are implemented where session activities can be determined. This is typically at the operating system level, but can also be at the application level. Session locks are not an acceptable substitute for logging out of information systems, for example, if organizations require users to log out at the end of workdays. Related control: AC-7 | D9: Directives supplémentaires | E9: Les verrouillages de session sont des mesures temporaires prises lorsque les utilisateurs arrêtent de travailler et s’éloignent du voisinage immédiat des systèmes d’information, mais ne veulent pas fermer leur session en raison de la nature temporaire de leur absence. Les verrouillages de session sont mis en œuvre là où les activités de session peuvent être déterminées. C’est habituellement au niveau du système d’exploitation, mais cela peut aussi être au niveau de l’application. Les verrouillages de session ne constituent pas un substitut acceptable à la déconnexion des systèmes d’information, par exemple, si les organisations demandent aux utilisateurs de fermer leur session à la fin des journées de travail. Contrôle connexe : AC-7
A10: Test Case | D10: Cas de test
A11: Test | B11: TEST-AC-11 | D11: Test | E11: TEST-AC-11
A12: Requirement ID | B12: AC-11 | D12: ID Exigence | E12: AC-11
A13: Component | D13: Composant
A14: Requirement | D14: Exigence
A15: Contextual Design Description | D15: Description contextuelle du design
A16: Evidence Provided | D16: Preuve fournie
A17: Preparer Sign Off (Initials, Date) | D17: Signataire préparateur (Initiales, Date)
A18: Owner Sign Off (Initials, Date) | D18: Signataire propriétaire (Initiales, Date)
A19: Assessor Sign Off (Initials, Date) | D19: Signataire évaluateur (Initiales, Date)
A20: Status | B20: Not Started | D20: Statut | E20: Non commencé
A21: Comments | D21: Commentaires

Sheet AC-11-1
A1: Control AC-11(1) — Evidence Tracking | D1: Contrôle AC-11(1) — Suivi des preuves
A2: Control Information | D2: Informations du contrôle
A3: Control Identifier | B3: AC-11(1) | D3: Identifiant du contrôle | E3: AC-11(1)
A4: Family | B4: Session Lock | D4: Famille | E4: Verrouillage de session
A5: Profile | B5: CCCS Medium / PBMM Moderate | D5: Profil | E5: CCCS Moyen / PBMM Modéré
A6: Primary Evidence Tool | D6: Outil de preuve principal
A7: Contributing Tools | D7: Outils contributeurs
A8: Control Description | B8: SESSION LOCK | PATTERN-HIDING DISPLAYS The information system conceals, via the session lock, information previously visible on the display with a publicly viewable image. | D8: Description du contrôle | E8: VERROUILLAGE DE SESSION | MASQUES D’ÉCRAN Le système d’information masque, par l’intermédiaire du verrouillage de session, l’information précédemment visible sur l’écran au moyen d’une image visible publiquement.
A9: Supplemental Guidance | B9: Publicly viewable images can include static or dynamic images, for example, patterns used with screen savers, photographic images, solid colors, clock, battery life indicator, or a blank screen, with the additional caveat that none of the images convey sensitive information. | D9: Directives supplémentaires | E9: Les images accessibles au public peuvent comprendre des images statiques ou dynamiques, par exemple, des motifs utilisés avec des économiseurs d’écran, des images photographiques, des couleurs unies, une horloge, un indicateur de durée de vie de la batterie ou un écran vide, pourvu qu’aucune de ces images ne transmette d’information sensible.
A10: Test Case | D10: Cas de test
A11: Test | B11: TEST-AC-11(1) | D11: Test | E11: TEST-AC-11(1)
A12: Requirement ID | B12: AC-11(1) | D12: ID Exigence | E12: AC-11(1)
A13: Component | D13: Composant
A14: Requirement | D14: Exigence
A15: Contextual Design Description | D15: Description contextuelle du design
A16: Evidence Provided | D16: Preuve fournie
A17: Preparer Sign Off (Initials, Date) | D17: Signataire préparateur (Initiales, Date)
A18: Owner Sign Off (Initials, Date) | D18: Signataire propriétaire (Initiales, Date)
A19: Assessor Sign Off (Initials, Date) | D19: Signataire évaluateur (Initiales, Date)
A20: Status | B20: Not Started | D20: Statut | E20: Non commencé
A21: Comments | D21: Commentaires

Sheet AC-12
A1: Control AC-12 — Evidence Tracking | D1: Contrôle AC-12 — Suivi des preuves
A2: Control Information | D2: Informations du contrôle
A3: Control Identifier | B3: AC-12 | D3: Identifiant du contrôle | E3: AC-12
A4: Family | B4: Session Termination | D4: Famille | E4: Fermeture de session
A5: Profile | B5: CCCS Medium / PBMM Moderate | D5: Profil | E5: CCCS Moyen / PBMM Modéré
A6: Primary Evidence Tool | D6: Outil de preuve principal
A7: Contributing Tools | D7: Outils contributeurs
A8: Control Description | B8: (A) The information system automatically terminates a user session after a maximum of 24 hours of inactivity or upon request by the user. | D8: Description du contrôle | E8: (A) Le système d’information met automatiquement fin à une session utilisateur après un maximum de 24 heures d’inactivité ou à la demande de l’utilisateur.
A9: Supplemental Guidance | B9: This control addresses the termination of user-initiated logical sessions in contrast to SC-10 which addresses the termination of network connections that are associated with communications sessions (i.e., network disconnect). A logical session (for local, network, and remote access) is initiated whenever a user (or process acting on behalf of a user) accesses an organizational information system. Such user sessions can be terminated (and thus terminate user access) without terminating network sessions. Session termination terminates all processes associated with a user’s logical session except those processes that are specifically created by the user (i.e., session owner) to continue after the session is terminated. Conditions or trigger events requiring automatic session termination can include, for example, organization-defined periods of user inactivity, targeted responses to certain types of incidents, time-of-day restrictions on information system use. Related controls: SC-10, SC-23 | D9: Directives supplémentaires | E9: Ce contrôle traite de la fermeture des sessions logiques ouvertes par l’utilisateur, contrairement au SC-10, qui traite de l’interruption des connexions réseau associées aux sessions de communication (c.-à-d. déconnexion de réseau). Une session logique (pour l’accès local, réseau, et distant) est lancée chaque fois qu’un utilisateur (ou un processus agissant pour le compte d’un utilisateur) accède à un système d’information de l’organisation. Ces sessions d’utilisateur peuvent être interrompues (ce qui met fin à l’accès utilisateur) sans mettre fin aux sessions de réseau. La fermeture de session met fin à tous les processus associés à la session logique d’un utilisateur, à l’exception des processus créés spécifiquement par l’utilisateur (c.-à-d. le propriétaire de la session) pour se poursuivre après la fermeture de la session. Les conditions ou les événements déclencheurs exigeant une fermeture de session automatique peuvent comprendre, par exemple, les périodes d’inactivité définies par l’organisation, les réponses ciblées à certains types d’incidents, les restrictions d’utilisation du système d’information en fonction de l’heure du jour. Contrôles connexes : SC-10, SC-23
A10: Test Case | D10: Cas de test
A11: Test | B11: TEST-AC-12 | D11: Test | E11: TEST-AC-12
A12: Requirement ID | B12: AC-12 | D12: ID Exigence | E12: AC-12
A13: Component | D13: Composant
A14: Requirement | D14: Exigence
A15: Contextual Design Description | D15: Description contextuelle du design
A16: Evidence Provided | D16: Preuve fournie
A17: Preparer Sign Off (Initials, Date) | D17: Signataire préparateur (Initiales, Date)
A18: Owner Sign Off (Initials, Date) | D18: Signataire propriétaire (Initiales, Date)
A19: Assessor Sign Off (Initials, Date) | D19: Signataire évaluateur (Initiales, Date)
A20: Status | B20: Not Started | D20: Statut | E20: Non commencé
A21: Comments | D21: Commentaires

Sheet AC-17-1
A1: Control AC-17(1) — Evidence Tracking | D1: Contrôle AC-17(1) — Suivi des preuves
A2: Control Information | D2: Informations du contrôle
A3: Control Identifier | B3: AC-17(1) | D3: Identifiant du contrôle | E3: AC-17(1)
A4: Family | B4: Remote Access | D4: Famille | E4: Accès à distance
A5: Profile | B5: CCCS Medium / PBMM Moderate | D5: Profil | E5: CCCS Moyen / PBMM Modéré
A6: Primary Evidence Tool | D6: Outil de preuve principal
A7: Contributing Tools | D7: Outils contributeurs
A8: Control Description | B8: REMOTE ACCESS | AUTOMATED MONITORING / CONTROL The information system monitors and controls remote access methods. | D8: Description du contrôle | E8: ACCÈS À DISTANCE | SURVEILLANCE ET CONTRÔLE AUTOMATISÉS Le système d’information surveille et contrôle les méthodes d’accès à distance.
A9: Supplemental Guidance | B9: Automated monitoring and control of remote access sessions allows organizations to detect cyber-attacks and also ensure ongoing compliance with remote access policies by auditing connection activities of remote users on a variety of information system components (e.g., servers, workstations, notebook computers, smart phones, and tablets). Related controls: AU-2, AU-12. | D9: Directives supplémentaires | E9: La surveillance et le contrôle automatisés des sessions avec accès à distance permettent aux organisations de détecter les cyberattaques et d’assurer la conformité continue aux politiques d’accès à distance en vérifiant les activités de connexion des utilisateurs distants sur une variété de composants du système d’information (p. ex., serveurs, postes de travail, ordinateurs portatifs, téléphones intelligents et tablettes). Contrôles connexes : AU-2, AU-12.
A10: Test Case | D10: Cas de test
A11: Test | B11: TEST-AC-17(1) | D11: Test | E11: TEST-AC-17(1)
A12: Requirement ID | B12: AC-17(1) | D12: ID Exigence | E12: AC-17(1)
A13: Component | D13: Composant
A14: Requirement | D14: Exigence
A15: Contextual Design Description | D15: Description contextuelle du design
A16: Evidence Provided | D16: Preuve fournie
A17: Preparer Sign Off (Initials, Date) | D17: Signataire préparateur (Initiales, Date)
A18: Owner Sign Off (Initials, Date) | D18: Signataire propriétaire (Initiales, Date)
A19: Assessor Sign Off (Initials, Date) | D19: Signataire évaluateur (Initiales, Date)
A20: Status | B20: Not Started | D20: Statut | E20: Non commencé
A21: Comments | D21: Commentaires

Sheet AC-17-2
A1: Control AC-17(2) — Evidence Tracking | D1: Contrôle AC-17(2) — Suivi des preuves
A2: Control Information | D2: Informations du contrôle
A3: Control Identifier | B3: AC-17(2) | D3: Identifiant du contrôle | E3: AC-17(2)
A4: Family | B4: Remote Access | D4: Famille | E4: Accès à distance
A5: Profile | B5: CCCS Medium / PBMM Moderate | D5: Profil | E5: CCCS Moyen / PBMM Modéré
A6: Primary Evidence Tool | D6: Outil de preuve principal
A7: Contributing Tools | D7: Outils contributeurs
A8: Control Description | B8: REMOTE ACCESS | PROTECTION OF CONFIDENTIALITY / INTEGRITY USING ENCRYPTION The information system implements cryptographic mechanisms to protect the confidentiality and integrity of remote access sessions. The cryptography must be compliant with the requirements of SC-13. | D8: Description du contrôle | E8: ACCÈS À DISTANCE | PROTECTION DE LA CONFIDENTIALITÉ ET DE L’INTÉGRITÉ AU MOYEN DU CHIFFREMENT Le système d’information met en œuvre des mécanismes cryptographiques pour protéger la confidentialité et l’intégrité des sessions d’accès à distance. La cryptographie doit être conforme aux exigences de SC-13.
A9: Supplemental Guidance | B9: Guidance on the encryption strength of mechanism can be obtained from CSE upon request. | D9: Directives supplémentaires | E9: Le CST peut, sur demande, conseiller l’organisation quant à la puissance de chiffrement du mécanisme.
A10: Test Case | D10: Cas de test
A11: Test | B11: TEST-AC-17(2) | D11: Test | E11: TEST-AC-17(2)
A12: Requirement ID | B12: AC-17(2) | D12: ID Exigence | E12: AC-17(2)
A13: Component | D13: Composant
A14: Requirement | D14: Exigence
A15: Contextual Design Description | D15: Description contextuelle du design
A16: Evidence Provided | D16: Preuve fournie
A17: Preparer Sign Off (Initials, Date) | D17: Signataire préparateur (Initiales, Date)
A18: Owner Sign Off (Initials, Date) | D18: Signataire propriétaire (Initiales, Date)
A19: Assessor Sign Off (Initials, Date) | D19: Signataire évaluateur (Initiales, Date)
A20: Status | B20: Not Started | D20: Statut | E20: Non commencé
A21: Comments | D21: Commentaires

Sheet AC-17-100
A1: Control AC-17(100) — Evidence Tracking | D1: Contrôle AC-17(100) — Suivi des preuves
A2: Control Information | D2: Informations du contrôle
A3: Control Identifier | B3: AC-17(100) | D3: Identifiant du contrôle | E3: AC-17(100)
A4: Family | B4: Remote Access | D4: Famille | E4: Accès à distance
A5: Profile | B5: CCCS Medium / PBMM Moderate | D5: Profil | E5: CCCS Moyen / PBMM Modéré
A6: Primary Evidence Tool | D6: Outil de preuve principal
A7: Contributing Tools | D7: Outils contributeurs
A8: Control Description | B8: Remote access to privileged accounts is performed on dedicated management consoles governed entirely by the system’s security policies and used exclusively for this purpose (e.g. Internet access not allowed). | D8: Description du contrôle | E8: L’accès à distance aux comptes privilégiés se fait sur des consoles de gestion dédiées entièrement régies par les politiques de sécurité du système et utilisées exclusivement à cette fin (p. ex., accès Internet interdit).
A9: Supplemental Guidance | D9: Directives supplémentaires
A10: Test Case | D10: Cas de test
A11: Test | B11: TEST-AC-17(100) | D11: Test | E11: TEST-AC-17(100)
A12: Requirement ID | B12: AC-17(100) | D12: ID Exigence | E12: AC-17(100)
A13: Component | D13: Composant
A14: Requirement | D14: Exigence
A15: Contextual Design Description | D15: Description contextuelle du design
A16: Evidence Provided | D16: Preuve fournie
A17: Preparer Sign Off (Initials, Date) | D17: Signataire préparateur (Initiales, Date)
A18: Owner Sign Off (Initials, Date) | D18: Signataire propriétaire (Initiales, Date)
A19: Assessor Sign Off (Initials, Date) | D19: Signataire évaluateur (Initiales, Date)
A20: Status | B20: Not Started | D20: Statut | E20: Non commencé
A21: Comments | D21: Commentaires

Sheet AU-2
A1: Control AU-2 — Evidence Tracking | D1: Contrôle AU-2 — Suivi des preuves
A2: Control Information | D2: Informations du contrôle
A3: Control Identifier | B3: AU-2 | D3: Identifiant du contrôle | E3: AU-2
A4: Family | B4: Auditable Events | D4: Famille | E4: Événements vérifiables
A5: Profile | B5: CCCS Medium / PBMM Moderate | D5: Profil | E5: CCCS Moyen / PBMM Modéré
A6: Primary Evidence Tool | D6: Outil de preuve principal
A7: Contributing Tools | D7: Outils contributeurs
A8: Control Description | B8: (A) The organization determines that the information system is capable of auditing the following events: Successful and unsuccessful account logon events, account management events, object access, policy change, privilege functions, process tracking, and system events. For Web applications: all administrator activity, authentication checks, authorization checks, data deletions, data access, data changes, and permission changes. (B) The organization coordinates the security audit function with other organizational entities requiring audit-related information to enhance mutual support and to help guide the selection of auditable events. (C) The organization provides a rationale for why the auditable events are deemed to be adequate to support after-the-fact investigations of security incidents. (D) The organization determines what organizationally-defined audited events (a subset of the auditable events defined in AU-2 a.) and the frequency of (or situation requiring) auditing for each identified event. | D8: Description du contrôle | E8: (A) L’organisation détermine que le système d’information est capable de vérifier les événements suivants : événements d’ouverture de compte, réussis ou non, événements de gestion de compte, accès aux objets, changement de politique, fonctions de privilèges, suivi des processus et événements du système. Pour les applications Web : toutes les activités des administrateurs, les vérifications d’authentification, les vérifications d’autorisation, les suppressions de données, l’accès aux données, les changements de données et les changements d’autorisation. (B) L’organisation coordonne la fonction de vérification de la sécurité avec d’autres entités organisationnelles qui ont besoin de renseignements liés à la vérification pour améliorer le soutien mutuel et aider à orienter le choix des événements vérifiables. (C) L’organisation explique la raison pour laquelle les événements vérifiables sont jugés adéquats pour appuyer les enquêtes effectuées à la suite des incidents de sécurité. (D) L’organisation détermine les événements définis par l’organisation qui sont vérifiés (un sous-ensemble des événements vérifiables définis dans AU-2 a.) et la fréquence (ou la situation exigeant) des vérifications pour chaque événement identifié.
A9: Supplemental Guidance | B9: An event is any observable occurrence in an organizational information system. Organizations identify audit events as those events which are significant and relevant to the security of information systems and the environments in which those systems operate in order to meet specific and ongoing audit needs. Audit events can include, for example, password changes, failed logons, or failed accesses related to information systems, administrative privilege usage, or third-party credential usage. In determining the set of auditable events, organizations consider the auditing appropriate for each of the security controls to be implemented. To balance auditing requirements with other information system needs, this control also requires identifying that subset of auditable events that are audited at a given point in time. For example, organizations may determine that information systems must have the capability to log every file access both successful and unsuccessful, but not activate that capability except for specific circumstances due to the potential burden on system performance. Auditing requirements, including the need for auditable events, may be referenced in other security controls and control enhancements. Organizations also include auditable events that are required by applicable organizational policies, directives, and standards. Audit records can be generated at various levels of abstraction, including at the packet level as information traverses the network. Selecting the appropriate level of abstraction is a critical aspect of an audit capability and can facilitate the identification of root causes to problems. Organizations consider in the definition of auditable events, the auditing necessary to cover related events such as the steps in distributed, transaction-based processes (e.g., processes that are distributed across multiple organizations) and actions that occur in service-oriented architectures. The information system audits the following privileged user/process events at a minimum: (a) Successful and unsuccessful attempts to access, modify, or delete security objects (Security objects include audit data, system configuration files and file or users’ formal access permissions.) (b) Successful and unsuccessful logon attempts (c) Privileged activities or other system level access (see notes for AU-2 (4)) (d) Starting and ending time for user access to the system (e) Concurrent logons from different workstations (f) All program initiations (see notes for AU-2 (4)) In addition, the information system audits the following unprivileged user/process events at a minimum: (a) Successful and unsuccessful attempts to access, modify, or delete security objects (b) Successful and unsuccessful logon attempts (c) Starting and ending time for user access to the system (d) Concurrent logons from different workstations Related controls: AC-6, AC-17, AU-3, AU-12, MA-4, MP-2, MP-4, SI-4 | D9: Directives supplémentaires | E9: Un événement est toute occurrence observable dans un système d’information organisationnel. Les organisations désignent les événements vérifiables comme étant des événements importants et pertinents pour la sécurité des systèmes d’information et des environnements dans lesquels ces systèmes sont utilisés afin de répondre à des exigences de vérification particulières et continues. Les événements vérifiés peuvent comprendre, par exemple, les changements de mot de passe, les échecs d’ouverture de session ou les échecs accès liés aux systèmes d’information, l’utilisation des privilèges administratifs ou l’utilisation de justificatifs d’identité par des tiers. Lorsqu’elles déterminent l’ensemble des événements vérifiables, les organisations considèrent que la vérification est appropriée pour chacun des contrôles de sécurité à mettre en œuvre. Pour assurer l’équilibre entre les exigences en matière de vérification et les autres besoins du système d’information, ce contrôle exige également de déterminer le sous-ensemble d’événements vérifiables qui sont vérifiés à un moment donné. Par exemple, les organisations peuvent déterminer que les systèmes d’information doivent avoir la capacité d’enregistrer chaque accès aux fichiers, qu’il soit réussi ou non, mais n’activeront cette capacité que dans des circonstances particulières en raison du fardeau potentiel sur le rendement du système. Les exigences en matière de vérification, y compris la nécessité de déterminer des événements vérifiables, peuvent être mentionnées dans d’autres contrôles et améliorations des contrôles de sécurité. Les organisations incluent également les événements vérifiables qui sont exigés par les politiques, les directives et les normes organisationnelles applicables. Les enregistrements de vérification peuvent être générés à divers niveaux d’abstraction, y compris au niveau des paquets, à mesure que l’information traverse le réseau. Le choix du niveau d’abstraction approprié est un aspect essentiel d’une capacité de vérification et peut faciliter l’identification des causes profondes des problèmes. Dans la définition des événements vérifiables, les organisations prennent en compte la vérification nécessaire pour couvrir les événements connexes, comme les étapes des processus distribués, fondés sur les transactions (p. ex., les processus qui sont répartis entre de multiples organisations) et les actions qui ont lieu dans les architectures orientées service. Le système d’information vérifie au minimum les événements suivants liés aux utilisateurs/processus privilégiés : (a) Tentatives réussies et infructueuses d’accéder aux objets de sécurité, de les modifier ou de les supprimer (les objets de sécurité comprennent les données de vérification, les fichiers de configuration de système et les autorisations d’accès officielles des utilisateurs). (b) Tentatives d’ouverture de session réussies et infructueuses (c) Activités privilégiées ou autre accès au niveau du système (voir les notes pour AU-2 [4]) (d) Heures de début et de fin de l’accès des utilisateurs au système (e) Ouvertures de session simultanées à partir de différents postes de travail (f) Tous les lancements de programmes (voir les notes pour AU-2 [4]) De plus, le système d’information vérifie au minimum les événements suivants liés aux utilisateurs/processus non privilégiés : (a) Tentatives réussies et infructueuses d’accès, de modification ou de suppression d’objets de sécurité (b) Tentatives d’ouverture de session réussies et infructueuses (c) Heures de début et de fin de l’accès de l’utilisateur au système (d) Ouvertures de session simultanées à partir de différents postes de travail Contrôles connexes : AC-6, AC-17, AU-3, AU-12, MA-4, MP-2, MP-4, SI-4
A10: Test Case | D10: Cas de test
A11: Test | B11: TEST-AU-2 | D11: Test | E11: TEST-AU-2
A12: Requirement ID | B12: AU-2 | D12: ID Exigence | E12: AU-2
A13: Component | D13: Composant
A14: Requirement | D14: Exigence
A15: Contextual Design Description | D15: Description contextuelle du design
A16: Evidence Provided | D16: Preuve fournie
A17: Preparer Sign Off (Initials, Date) | D17: Signataire préparateur (Initiales, Date)
A18: Owner Sign Off (Initials, Date) | D18: Signataire propriétaire (Initiales, Date)
A19: Assessor Sign Off (Initials, Date) | D19: Signataire évaluateur (Initiales, Date)
A20: Status | B20: Not Started | D20: Statut | E20: Non commencé
A21: Comments | D21: Commentaires

Sheet AU-3
A1: Control AU-3 — Evidence Tracking | D1: Contrôle AU-3 — Suivi des preuves
A2: Control Information | D2: Informations du contrôle
A3: Control Identifier | B3: AU-3 | D3: Identifiant du contrôle | E3: AU-3
A4: Family | B4: Content of Audit Records | D4: Famille | E4: Contenu des enregistrements de vérification
A5: Profile | B5: CCCS Medium / PBMM Moderate | D5: Profil | E5: CCCS Moyen / PBMM Modéré
A6: Primary Evidence Tool | D6: Outil de preuve principal
A7: Contributing Tools | D7: Outils contributeurs
A8: Control Description | B8: (A) The information system generates audit records containing information that establishes what type of event occurred, when the event occurred, where the event occurred, the source of the event, the outcome of the event, and the identity of any individuals or subjects associated with the event. | D8: Description du contrôle | E8: (A) Le système d’information génère des enregistrements de vérification qui contiennent les renseignements permettant d’établir le type d’événement qui a eu lieu, le moment et l’endroit où l’événement a eu lieu, la source de l’événement, le résultat de l’événement, ainsi que l’identité de toute personne ou de tout sujet associé à l’événement.
A9: Supplemental Guidance | B9: Audit record content that may be necessary to satisfy the requirement of this control, includes, for example, time stamps, source and destination addresses, user/process identifiers, event descriptions, success/fail indications, filenames involved, and access control or flow control rules invoked. Event outcomes can include indicators of event success or failure and event-specific results (e.g., the security state of the information system after the event occurred). Related controls: AU-2, AU-8, AU-12, SI-11 | D9: Directives supplémentaires | E9: Le contenu des enregistrements de vérification qui peut être nécessaire pour satisfaire à l’exigence de ce contrôle comprend, par exemple, les estampilles temporelles, les adresses de source et de destination, les identifiants d’utilisateurs ou de processus, les descriptions d’événements, les indications de réussite ou d’échec, les noms des fichiers en cause et les règles de contrôle d’accès ou de flux invoquées. Les résultats de l’événement peuvent comprendre des indicateurs de réussite ou d’échec de l’événement et des résultats propres à l’événement (p. ex., l’état de sécurité du système d’information après l’événement). Contrôles connexes : AU-2, AU-8, AU-12, SI-11
A10: Test Case | D10: Cas de test
A11: Test | B11: TEST-AU-3 | D11: Test | E11: TEST-AU-3
A12: Requirement ID | B12: AU-3 | D12: ID Exigence | E12: AU-3
A13: Component | D13: Composant
A14: Requirement | D14: Exigence
A15: Contextual Design Description | D15: Description contextuelle du design
A16: Evidence Provided | D16: Preuve fournie
A17: Preparer Sign Off (Initials, Date) | D17: Signataire préparateur (Initiales, Date)
A18: Owner Sign Off (Initials, Date) | D18: Signataire propriétaire (Initiales, Date)
A19: Assessor Sign Off (Initials, Date) | D19: Signataire évaluateur (Initiales, Date)
A20: Status | B20: Not Started | D20: Statut | E20: Non commencé
A21: Comments | D21: Commentaires

Sheet AU-3-1
A1: Control AU-3(1) — Evidence Tracking | D1: Contrôle AU-3(1) — Suivi des preuves
A2: Control Information | D2: Informations du contrôle
A3: Control Identifier | B3: AU-3(1) | D3: Identifiant du contrôle | E3: AU-3(1)
A4: Family | B4: Content of Audit Records | D4: Famille | E4: Contenu des enregistrements de vérification
A5: Profile | B5: CCCS Medium / PBMM Moderate | D5: Profil | E5: CCCS Moyen / PBMM Modéré
A6: Primary Evidence Tool | D6: Outil de preuve principal
A7: Contributing Tools | D7: Outils contributeurs
A8: Control Description | B8: CONTENT OF AUDIT RECORDS | ADDITIONAL AUDIT INFORMATION The information system generates audit records containing the following additional information: session, connection, transaction, or activity duration; for client-server transactions, the number of bytes received and bytes sent; additional informational messages to diagnose or identify the event; characteristics that describe or identify the object or resource being acted upon. | D8: Description du contrôle | E8: CONTENU DES ENREGISTREMENTS DE VÉRIFICATION | RENSEIGNEMENTS DE VÉRIFICATION SUPPLÉMENTAIRES Le système d’information génère des enregistrements de vérification contenant les renseignements supplémentaires suivants : la durée de la session, de la connexion, de la transaction ou de l’activité; pour les transactions client-serveur, le nombre d’octets reçus et d’octets envoyés; des messages d’information supplémentaires pour diagnostiquer ou identifier l’événement; les caractéristiques qui décrivent ou identifient l’objet ou la ressource concernés.
A9: Supplemental Guidance | B9: Detailed information that organizations may consider in audit records includes, for example, full text recording of privileged commands or the individual identities of group account users. Organizations consider limiting the additional audit information to only that information explicitly needed for specific audit requirements. This facilitates the use of audit trails and audit logs by not including information that could potentially be misleading or could make it more difficult to locate information of interest. Additional guidance for enhancement (1): Audit events should always be capable of being associated with an individual identity. Associating audit events with a group or role is insufficient. | D9: Directives supplémentaires | E9: Les renseignements détaillés dont les organisations peuvent tenir compte dans les enregistrements de vérification comprennent, par exemple, l’enregistrement en texte intégral des commandes privilégiées ou les identités individuelles des utilisateurs de comptes de groupe. Les organisations devraient envisager de limiter les renseignements de vérification supplémentaires aux seuls renseignements explicitement nécessaires pour répondre à des exigences de vérification particulières. Cela facilitera l’utilisation des pistes de vérification et des journaux de vérification en n’incluant pas les renseignements qui pourraient être trompeurs ou rendre plus difficile la recherche de renseignements utiles. Conseils supplémentaires pour l’amélioration (1) : Les événements vérifiés devraient toujours pouvoir être associés à une identité individuelle. Associer des événements vérifiés à un groupe ou à un rôle est insuffisant.
A10: Test Case | D10: Cas de test
A11: Test | B11: TEST-AU-3(1) | D11: Test | E11: TEST-AU-3(1)
A12: Requirement ID | B12: AU-3(1) | D12: ID Exigence | E12: AU-3(1)
A13: Component | D13: Composant
A14: Requirement | D14: Exigence
A15: Contextual Design Description | D15: Description contextuelle du design
A16: Evidence Provided | D16: Preuve fournie
A17: Preparer Sign Off (Initials, Date) | D17: Signataire préparateur (Initiales, Date)
A18: Owner Sign Off (Initials, Date) | D18: Signataire propriétaire (Initiales, Date)
A19: Assessor Sign Off (Initials, Date) | D19: Signataire évaluateur (Initiales, Date)
A20: Status | B20: Not Started | D20: Statut | E20: Non commencé
A21: Comments | D21: Commentaires

Sheet AU-9-2
A1: Control AU-9(2) — Evidence Tracking | D1: Contrôle AU-9(2) — Suivi des preuves
A2: Control Information | D2: Informations du contrôle
A3: Control Identifier | B3: AU-9(2) | D3: Identifiant du contrôle | E3: AU-9(2)
A4: Family | B4: Protection of Audit Information | D4: Famille | E4: Protection des renseignements de vérification
A5: Profile | B5: CCCS Medium / PBMM Moderate | D5: Profil | E5: CCCS Moyen / PBMM Modéré
A6: Primary Evidence Tool | D6: Outil de preuve principal
A7: Contributing Tools | D7: Outils contributeurs
A8: Control Description | B8: PROTECTION OF AUDIT INFORMATION | AUDIT BACKUP ON SEPARATE PHYSICAL SYSTEMS / COMPONENTS The information system backs up audit records at least weekly onto a physically different system or system component than the system or component being audited. | D8: Description du contrôle | E8: PROTECTION DES RENSEIGNEMENTS DE VÉRIFICATION | SAUVEGARDE DES VÉRIFICATIONS SUR DES SYSTÈMES/COMPOSANTS PHYSIQUES SÉPARÉS Le système d’information sauvegarde les enregistrements de vérification au moins une fois par semaine sur un système ou un composant système physiquement différent du système ou du composant faisant l’objet de la vérification.
A9: Supplemental Guidance | B9: This control enhancement helps to ensure that a compromise of the information system being audited does not also result in a compromise of the audit records. Related controls: AU-4, AU-5, AU-11. | D9: Directives supplémentaires | E9: Cette amélioration permet de s’assurer qu’une compromission du système d’information faisant l’objet d’une vérification n’entraîne pas également la compromission des enregistrements de vérification. Contrôles connexes : AU-4, AU-5, AU-11.
A10: Test Case | D10: Cas de test
A11: Test | B11: TEST-AU-9(2) | D11: Test | E11: TEST-AU-9(2)
A12: Requirement ID | B12: AU-9(2) | D12: ID Exigence | E12: AU-9(2)
A13: Component | D13: Composant
A14: Requirement | D14: Exigence
A15: Contextual Design Description | D15: Description contextuelle du design
A16: Evidence Provided | D16: Preuve fournie
A17: Preparer Sign Off (Initials, Date) | D17: Signataire préparateur (Initiales, Date)
A18: Owner Sign Off (Initials, Date) | D18: Signataire propriétaire (Initiales, Date)
A19: Assessor Sign Off (Initials, Date) | D19: Signataire évaluateur (Initiales, Date)
A20: Status | B20: Not Started | D20: Statut | E20: Non commencé
A21: Comments | D21: Commentaires

Sheet AU-12
A1: Control AU-12 — Evidence Tracking | D1: Contrôle AU-12 — Suivi des preuves
A2: Control Information | D2: Informations du contrôle
A3: Control Identifier | B3: AU-12 | D3: Identifiant du contrôle | E3: AU-12
A4: Family | B4: Audit Generation | D4: Famille | E4: Génération des vérifications
A5: Profile | B5: CCCS Medium / PBMM Moderate | D5: Profil | E5: CCCS Moyen / PBMM Modéré
A6: Primary Evidence Tool | D6: Outil de preuve principal
A7: Contributing Tools | D7: Outils contributeurs
A8: Control Description | B8: (A) The information system provides audit record generation capability for the auditable events defined in AU-2 a. of all information system and network components where audit capability is deployed/available. (B) The information system allows organization-defined personnel or roles to select which auditable events are to be audited by specific components of the information system. (C) The information system generates audit records for the events defined in AU-2 d. with the content defined in AU-3. | D8: Description du contrôle | E8: (A) Le système d’information offre une capacité de génération d’enregistrements de vérification pour les événements vérifiables définis dans AU-2 a. de tous les composants du système d’information et du réseau où la capacité de vérification est déployée/disponible. (B) Le système d’information permet au personnel ou aux rôles définis par l’organisation de choisir les événements vérifiables qui doivent être vérifiés par des composants précis du système d’information. (C) Le système d’information génère des enregistrements de vérification pour les événements définis dans AU-2 d. avec le contenu défini dans AU-3.
A9: Supplemental Guidance | B9: Audit records can be generated from many different information system components. The list of audited events is the set of events for which audits are to be generated. These events are typically a subset of all events for which the information system is capable of generating audit records. Related controls: AC-3, AU-2, AU-3, AU-6, AU-7 | D9: Directives supplémentaires | E9: Des enregistrements de vérification peuvent être générés à partir de nombreux composants du système d’information. La liste des événements vérifiés est l’ensemble des événements pour lesquels des vérifications doivent être produites. Ces événements sont habituellement un sous-ensemble de tous les événements pour lesquels le système d’information peut générer des enregistrements de vérification. Contrôles connexes : AC-3, AU-2, AU-3, AU-6, AU-7
A10: Test Case | D10: Cas de test
A11: Test | B11: TEST-AU-12 | D11: Test | E11: TEST-AU-12
A12: Requirement ID | B12: AU-12 | D12: ID Exigence | E12: AU-12
A13: Component | D13: Composant
A14: Requirement | D14: Exigence
A15: Contextual Design Description | D15: Description contextuelle du design
A16: Evidence Provided | D16: Preuve fournie
A17: Preparer Sign Off (Initials, Date) | D17: Signataire préparateur (Initiales, Date)
A18: Owner Sign Off (Initials, Date) | D18: Signataire propriétaire (Initiales, Date)
A19: Assessor Sign Off (Initials, Date) | D19: Signataire évaluateur (Initiales, Date)
A20: Status | B20: Not Started | D20: Statut | E20: Non commencé
A21: Comments | D21: Commentaires

Sheet CA-3-5
A1: Control CA-3(5) — Evidence Tracking | D1: Contrôle CA-3(5) — Suivi des preuves
A2: Control Information | D2: Informations du contrôle
A3: Control Identifier | B3: CA-3(5) | D3: Identifiant du contrôle | E3: CA-3(5)
A4: Family | B4: Information System Connections | D4: Famille | E4: Connexions aux systèmes d’information
A5: Profile | B5: CCCS Medium / PBMM Moderate | D5: Profil | E5: CCCS Moyen / PBMM Modéré
A6: Primary Evidence Tool | D6: Outil de preuve principal
A7: Contributing Tools | D7: Outils contributeurs
A8: Control Description | B8: SYSTEM INTERCONNECTIONS | RESTRICTIONS ON EXTERNAL SYSTEM CONNECTIONS The organization employs allow-all, deny-by-exception; deny-all policy for allowing any systems to connect to external information systems. | D8: Description du contrôle | E8: INTERCONNEXIONS DES SYSTÈMES | RESTRICTIONS SUR LES CONNEXIONS AUX RÉSEAUX EXTERNES L’organisation a recours à la méthode « permettre tout, refuser par exception, refuser tout » pour permettre aux systèmes de se connecter à des systèmes d’information externes.
A9: Supplemental Guidance | B9: Organizations can constrain information system connectivity to external domains (e.g., websites) by employing one of two policies with regard to such connectivity: (i) allow-all, deny by exception, also known as blacklisting (the weaker of the two policies); or (ii) deny-all, allow by exception, also known as whitelisting (the stronger of the two policies). For either policy, organizations determine what exceptions, if any, are acceptable. Related control: CM-7. | D9: Directives supplémentaires | E9: Les organisations peuvent limiter la connectivité des systèmes d’information à des domaines externes (p. ex., sites Web) en utilisant l’une des deux politiques relatives à cette connectivité : (i) permettre tout, refuser par exception, aussi appelée liste noire (la plus faible des deux politiques); ou (ii) refuser tout, permettre par exception, aussi appelée liste blanche (la plus forte des deux politiques). Pour l’une ou l’autre politique, les organisations déterminent les exceptions applicables, le cas échéant. Contrôle connexe : CM-7.
A10: Test Case | D10: Cas de test
A11: Test | B11: TEST-CA-3(5) | D11: Test | E11: TEST-CA-3(5)
A12: Requirement ID | B12: CA-3(5) | D12: ID Exigence | E12: CA-3(5)
A13: Component | D13: Composant
A14: Requirement | D14: Exigence
A15: Contextual Design Description | D15: Description contextuelle du design
A16: Evidence Provided | D16: Preuve fournie
A17: Preparer Sign Off (Initials, Date) | D17: Signataire préparateur (Initiales, Date)
A18: Owner Sign Off (Initials, Date) | D18: Signataire propriétaire (Initiales, Date)
A19: Assessor Sign Off (Initials, Date) | D19: Signataire évaluateur (Initiales, Date)
A20: Status | B20: Not Started | D20: Statut | E20: Non commencé
A21: Comments | D21: Commentaires

Sheet CA-9
A1: Control CA-9 — Evidence Tracking | D1: Contrôle CA-9 — Suivi des preuves
A2: Control Information | D2: Informations du contrôle
A3: Control Identifier | B3: CA-9 | D3: Identifiant du contrôle | E3: CA-9
A4: Family | B4: Internal System Connections | D4: Famille | E4: Connexions internes au système
A5: Profile | B5: CCCS Medium / PBMM Moderate | D5: Profil | E5: CCCS Moyen / PBMM Modéré
A6: Primary Evidence Tool | D6: Outil de preuve principal
A7: Contributing Tools | D7: Outils contributeurs
A8: Control Description | B8: (A) The organization authorizes internal connections of information system components or classes of components to the information system. (B) The organization documents, for each internal connection, the interface characteristics, security requirements, and the nature of the information communicated. | D8: Description du contrôle | E8: (A) L’organisation autorise les connexions internes de composants du système d’information ou de catégories de composants au système d’information. (B) L’organisation documente, pour chaque connexion interne, les caractéristiques de l’interface, les exigences de sécurité et la nature de l’information communiquée.
A9: Supplemental Guidance | B9: This control applies to connections between organizational information systems and (separate) constituent system components (i.e., intra-system connections) including, for example, system connections with mobile devices, notebook/desktop computers, printers, copiers, facsimile machines, scanners, sensors, and servers. Instead of authorizing each individual internal connection, organizations can authorize internal connections for a class of components with common characteristics and/or configurations, for example, all digital printers, scanners, and copiers with a specified processing, storage, and transmission capability or all smart phones with a specific baseline configuration. Related controls: AC-3, AC-4, AC-18, AC-19, AU-2, AU-12, CA-7, CM-2, IA-3, SC-7, SI-4 | D9: Directives supplémentaires | E9: Ce contrôle s’applique aux connexions entre les systèmes d’information organisationnels et les composants (distincts) des systèmes constituants (c.-à-d. les connexions intrasystème) y compris, par exemple, les connexions système avec les appareils mobiles, les ordinateurs portatifs/de bureau, les imprimantes, les photocopieurs, les télécopieurs, les numériseurs, les capteurs et les serveurs. Au lieu d’autoriser chaque connexion interne individuelle, les organisations peuvent autoriser les connexions internes pour une catégorie de composants ayant des caractéristiques ou des configurations communes, par exemple, toutes les imprimantes et tous les numériseurs et photocopieurs numériques ayant une capacité de traitement, de stockage et de transmission spécifiée ou tous les téléphones intelligents ayant une configuration de base spécifique. Contrôles connexes : AC-3, AC-4, AC-18, AC-19, AU-2, AU-12, CA-7, CM-2, IA-3, SC-7, SI-4
A10: Test Case | D10: Cas de test
A11: Test | B11: TEST-CA-9 | D11: Test | E11: TEST-CA-9
A12: Requirement ID | B12: CA-9 | D12: ID Exigence | E12: CA-9
A13: Component | D13: Composant
A14: Requirement | D14: Exigence
A15: Contextual Design Description | D15: Description contextuelle du design
A16: Evidence Provided | D16: Preuve fournie
A17: Preparer Sign Off (Initials, Date) | D17: Signataire préparateur (Initiales, Date)
A18: Owner Sign Off (Initials, Date) | D18: Signataire propriétaire (Initiales, Date)
A19: Assessor Sign Off (Initials, Date) | D19: Signataire évaluateur (Initiales, Date)
A20: Status | B20: Not Started | D20: Statut | E20: Non commencé
A21: Comments | D21: Commentaires

Sheet CM-6
A1: Control CM-6 — Evidence Tracking | D1: Contrôle CM-6 — Suivi des preuves
A2: Control Information | D2: Informations du contrôle
A3: Control Identifier | B3: CM-6 | D3: Identifiant du contrôle | E3: CM-6
A4: Family | B4: Configuration Settings | D4: Famille | E4: Paramètres de configuration
A5: Profile | B5: CCCS Medium / PBMM Moderate | D5: Profil | E5: CCCS Moyen / PBMM Modéré
A6: Primary Evidence Tool | D6: Outil de preuve principal
A7: Contributing Tools | D7: Outils contributeurs
A8: Control Description | B8: (A) The organization establishes and documents configuration settings for information technology products employed within the information system using checklists from one or more of the following Center for Internet Security (CIS), National Institute of Standards and Technology (NIST), Defense Information Systems Agency (DISA) that reflect the most restrictive mode consistent with operational requirements. (B) The organization implements the configuration settings. (C) The organization identifies, documents, and approves any deviations from established configuration settings for any configurable infomation system components. (D) The organization monitors and controls changes to the configuration settings in accordance with organizational policies and procedures. | D8: Description du contrôle | E8: (A) L’organisation établit et documente les paramètres de configuration des produits de technologie de l’information utilisés dans le système d’information à l’aide de listes de vérification provenant d’un ou de plusieurs des éléments suivants : Center for Internet Security (CIS), National Institute of Standards and Technology (NIST), Defense Information Systems Agency (DISA), qui reflètent le mode le plus restrictif conformément aux exigences opérationnelles. (B) L’organisation met en œuvre les paramètres de configuration. (C) L’organisation identifie, documente et approuve tout écart par rapport aux paramètres de configuration établis pour les composants configurables du système d’information. (D) L’organisation surveille et contrôle les changements apportés aux paramètres de configuration conformément aux politiques et aux procédures de l’organisation.
A9: Supplemental Guidance | B9: Configuration settings are the set of parameters that can be changed in hardware, software, or firmware components of the information system that affect the security posture and/or functionality of the system. Information technology products for which security-related configuration settings can be defined include, for example, mainframe computers, servers (e.g., database, electronic mail, authentication, web, proxy, file, domain name), workstations, input/output devices (e.g., scanners, copiers, and printers), network components (e.g., firewalls, routers, gateways, voice and data switches, wireless access points, network appliances, sensors), operating systems, middleware, and applications. Security-related parameters are those parameters impacting the security state of information systems including the parameters required to satisfy other security control requirements. Security-related parameters include, for example: (i) registry settings; (ii) account, file, directory permission settings; and (iii) settings for functions, ports, protocols, services, and remote connections. Organizations establish organization-wide configuration settings and subsequently derive specific settings for information systems. The established settings become part of the systems configuration baselineCommon secure configurations (also referred to as security configuration checklists, lockdown and hardening guides, security reference guides, security technical implementation guides (STIG)) provide recognized, standardized, and established benchmarks that stipulate secure configuration settings for specific information technology platforms/products and instructions for configuring those information system components to meet operational requirements. Common secure configurations can be developed by a variety of organizations including, for example, information technology product developers, manufacturers, vendors, consortia, academia, industry, federal government organizations, and others in the public and private sectors. The Security Content Automation Protocol (SCAP) and the defined standards within the protocol (e.g., Common Configuration Enumeration) provide an effective method to uniquely identify, track, and control configuration settings. Related controls: AC-19, CM-2, CM-3, CM-7, SI-4. | D9: Directives supplémentaires | E9: Les paramètres de configuration sont l’ensemble de paramètres qui peuvent être modifiés dans les composants matériels, logiciels ou micrologiciels du système d’information et qui ont une incidence sur la posture de sécurité ou la fonctionnalité du système. Les produits de technologie de l’information pour lesquels les paramètres de configuration liés à la sécurité peuvent être définis comprennent, par exemple, les ordinateurs centraux, les serveurs (p. ex., base de données, courrier électronique, authentification, Web, mandataire, fichiers, noms de domaine), les postes de travail, les périphériques d’entrée et de sortie (p. ex., numériseurs, photocopieurs et imprimantes), les composants de réseau (p. ex., pare-feu, routeurs, passerelles, commutateurs de voix et de données, points d’accès sans fil, outils de réseau, capteurs), les systèmes d’exploitation, les intergiciels et les applications. Les paramètres liés à la sécurité sont les paramètres qui influent sur l’état de sécurité des systèmes d’information, y compris les paramètres requis pour satisfaire à d’autres exigences de contrôle de sécurité. Les paramètres liés à la sécurité comprennent, par exemple : (i) les paramètres des registres; (ii) les paramètres de comptes, de fichiers, d’autorisation de répertoires; (iii) les paramètres des fonctions, des ports, des protocoles, des services et des connexions à distance. Les organisations établissent les paramètres de configuration à l’échelle de l’organisation et en déduisent ensuite les paramètres particuliers pour les systèmes d’information. Les paramètres établis font partie des configurations de base des systèmes Les configurations sécurisées communes (aussi appelées listes de vérification de la configuration de sécurité, guides de verrouillage et de renforcement, guides de référence de sécurité, guides de mise en œuvre technique de la sécurité [STIG]) fournissent des repères reconnus, normalisés et établis qui stipulent les paramètres de configuration sécurisée pour des plateformes/produits de technologie de l’information particuliers et des instructions pour configurer ces composants de système d’information de manière à répondre aux exigences opérationnelles. Les configurations sécurisées communes peuvent être mises au point par diverses organisations, y compris, par exemple, les concepteurs de produits de technologie de l’information, les fabricants, les fournisseurs, les consortiums, le milieu universitaire, l’industrie, les organisations du gouvernement fédéral et d’autres intervenants des secteurs public et privé. Le protocole d’automatisation du contenu de sécurité SCAP (Security Content Automation Protocol) et les normes définies dans le protocole (p. ex., Common Configuration Enumeration) constituent une méthode efficace pour déterminer, suivre et contrôler de façon unique les paramètres de configuration. Contrôles connexes : AC-19, CM-2, CM-3, CM-7, SI-4.
A10: Test Case | D10: Cas de test
A11: Test | B11: TEST-CM-6 | D11: Test | E11: TEST-CM-6
A12: Requirement ID | B12: CM-6 | D12: ID Exigence | E12: CM-6
A13: Component | D13: Composant
A14: Requirement | D14: Exigence
A15: Contextual Design Description | D15: Description contextuelle du design
A16: Evidence Provided | D16: Preuve fournie
A17: Preparer Sign Off (Initials, Date) | D17: Signataire préparateur (Initiales, Date)
A18: Owner Sign Off (Initials, Date) | D18: Signataire propriétaire (Initiales, Date)
A19: Assessor Sign Off (Initials, Date) | D19: Signataire évaluateur (Initiales, Date)
A20: Status | B20: Not Started | D20: Statut | E20: Non commencé
A21: Comments | D21: Commentaires

Sheet CM-7
A1: Control CM-7 — Evidence Tracking | D1: Contrôle CM-7 — Suivi des preuves
A2: Control Information | D2: Informations du contrôle
A3: Control Identifier | B3: CM-7 | D3: Identifiant du contrôle | E3: CM-7
A4: Family | B4: Least Functionality | D4: Famille | E4: Moindre fonctionnalité
A5: Profile | B5: CCCS Medium / PBMM Moderate | D5: Profil | E5: CCCS Moyen / PBMM Modéré
A6: Primary Evidence Tool | D6: Outil de preuve principal
A7: Contributing Tools | D7: Outils contributeurs
A8: Control Description | B8: (A) The organization configures the information system to provide only essential capabilities. (B) The organization prohibits or restricts the use of identified functions, ports, protocols, and/or services following one or more standards from Center for Internet Security (CIS), National Institute of Standards and Technology (NIST), or Defense Information Systems Agency (DISA). | D8: Description du contrôle | E8: (A) L’organisation configure le système d’information pour n’offrir que les capacités essentielles. (B) L’organisation interdit ou restreint l’utilisation de fonctions, de ports, de protocoles et/ou de services identifiés en respectant une ou plusieurs normes du Center for Internet Security (CIS), du National Institute of Standards and Technology (NIST) ou de la Defense Information Systems Agency (DISA).
A9: Supplemental Guidance | B9: Information systems can provide a wide variety of functions and services. Some of the functions and services, provided by default, may not be necessary to support essential organizational operations (e.g., key missions, functions). Additionally, it is sometimes convenient to provide multiple services from single information system components, but doing so increases risk over limiting the services provided by any one component. Where feasible, organizations limit component functionality to a single function per device (e.g., email servers or web servers, but not both). Organizations review functions and services provided by information systems or individual components of information systems, to determine which functions and services are candidates for elimination (e.g., Voice over Internet Protocol (VoIP), Instant Messaging, auto-execute, and file sharing). Organizations consider disabling unused or unnecessary physical and logical ports/protocols (e.g., USB, FTP, IPv6, HTTP) on information systems to prevent unauthorized connection of devices, unauthorized transfer of information, or unauthorized tunnelling. Organizations can utilize network scanning tools, intrusion detection and prevention systems, and end-point protections such as firewalls and host-based intrusion detection systems to identify and prevent the use of prohibited functions, ports, protocols, and services. Related controls: AC-6, CM-2, RA-5, SA-5, SC-7 | D9: Directives supplémentaires | E9: Les systèmes d’information peuvent offrir une grande variété de fonctions et de services. Certaines fonctions et certains services, fournis par défaut, peuvent ne pas être nécessaires au soutien des opérations essentielles de l’organisation (p. ex., missions et fonctions clés). De plus, il est parfois pratique de fournir plusieurs services à partir de composants uniques du système d’information, mais cela augmente le risque de limiter les services fournis par un seul composant. Dans la mesure du possible, les organisations limitent la fonctionnalité des composants à une seule fonction par dispositif (p. ex., serveurs de courriel ou serveurs Web, mais pas les deux). Les organisations examinent les fonctions et les services fournis par les systèmes d’information ou les composants individuels des systèmes d’information afin de déterminer quelles fonctions et quels services peuvent être éliminés (p. ex., voix sur protocole Internet [VoIP], messagerie instantanée, auto-exécution et partage de fichiers). Les organisations envisagent de désactiver les ports/protocoles physiques et logiques inutilisés ou inutiles (p. ex., USB, FTP, IPv6, HTTP) sur les systèmes d’information afin de prévenir la connexion non autorisée d’appareils, le transfert non autorisé d’information ou la tunnellisation non autorisée. Les organisations peuvent utiliser des outils de balayage de réseau, des systèmes de détection et de prévention des intrusions et des mesures de protection d’extrémité comme des pare-feu et des systèmes de détection des intrusions basés sur l’hôte, pour identifier et prévenir l’utilisation de fonctions, de ports, de protocoles et de services interdits. Contrôles connexes : AC-6, CM-2, RA-5, SA-5, SC-7
A10: Test Case | D10: Cas de test
A11: Test | B11: TEST-CM-7 | D11: Test | E11: TEST-CM-7
A12: Requirement ID | B12: CM-7 | D12: ID Exigence | E12: CM-7
A13: Component | D13: Composant
A14: Requirement | D14: Exigence
A15: Contextual Design Description | D15: Description contextuelle du design
A16: Evidence Provided | D16: Preuve fournie
A17: Preparer Sign Off (Initials, Date) | D17: Signataire préparateur (Initiales, Date)
A18: Owner Sign Off (Initials, Date) | D18: Signataire propriétaire (Initiales, Date)
A19: Assessor Sign Off (Initials, Date) | D19: Signataire évaluateur (Initiales, Date)
A20: Status | B20: Not Started | D20: Statut | E20: Non commencé
A21: Comments | D21: Commentaires

Sheet CM-7-1
A1: Control CM-7(1) — Evidence Tracking | D1: Contrôle CM-7(1) — Suivi des preuves
A2: Control Information | D2: Informations du contrôle
A3: Control Identifier | B3: CM-7(1) | D3: Identifiant du contrôle | E3: CM-7(1)
A4: Family | B4: Least Functionality | D4: Famille | E4: Moindre fonctionnalité
A5: Profile | B5: CCCS Medium / PBMM Moderate | D5: Profil | E5: CCCS Moyen / PBMM Modéré
A6: Primary Evidence Tool | D6: Outil de preuve principal
A7: Contributing Tools | D7: Outils contributeurs
A8: Control Description | B8: LEAST FUNCTIONALITY | PERIODIC REVIEW The organization reviews the information system at least annually to identify unnecessary and/or non-secure functions, ports, protocols, and services; and The organization disables all functions, ports, protocols, and services within the information system deemed to be unnecessary and/or nonsecure. | D8: Description du contrôle | E8: MOINDRE FONCTIONNALITÉ | EXAMEN PÉRIODIQUE L’organisation revoit le système d’information au moins une fois par année afin de repérer les fonctions, les ports, les protocoles et les services inutiles ou non sécurisés; L’organisation désactive toutes les fonctions, tous les ports, tous les protocoles et tous les services du système d’information jugés inutiles ou non sécurisés.
A9: Supplemental Guidance | B9: The organization can either make a determination of the relative security of the function, port, protocol, and/or service or base the security decision on the assessment of other entities. Bluetooth, FTP, and peer-to-peer networking are examples of less than secure protocols. Related controls: AC-18, CM-7, IA-2. | D9: Directives supplémentaires | E9: L’organisation peut soit déterminer la sécurité relative de la fonction, du port, du protocole ou du service, soit baser sa décision en matière de sécurité sur l’évaluation d’autres entités. Bluetooth, FTP et l’interconnexion de réseaux d’égal à égal sont des exemples de protocoles moins sécurisés. Contrôles connexes : AC-18, CM-7, IA-2.
A10: Test Case | D10: Cas de test
A11: Test | B11: TEST-CM-7(1) | D11: Test | E11: TEST-CM-7(1)
A12: Requirement ID | B12: CM-7(1) | D12: ID Exigence | E12: CM-7(1)
A13: Component | D13: Composant
A14: Requirement | D14: Exigence
A15: Contextual Design Description | D15: Description contextuelle du design
A16: Evidence Provided | D16: Preuve fournie
A17: Preparer Sign Off (Initials, Date) | D17: Signataire préparateur (Initiales, Date)
A18: Owner Sign Off (Initials, Date) | D18: Signataire propriétaire (Initiales, Date)
A19: Assessor Sign Off (Initials, Date) | D19: Signataire évaluateur (Initiales, Date)
A20: Status | B20: Not Started | D20: Statut | E20: Non commencé
A21: Comments | D21: Commentaires

Sheet CM-7-5
A1: Control CM-7(5) — Evidence Tracking | D1: Contrôle CM-7(5) — Suivi des preuves
A2: Control Information | D2: Informations du contrôle
A3: Control Identifier | B3: CM-7(5) | D3: Identifiant du contrôle | E3: CM-7(5)
A4: Family | B4: Least Functionality | D4: Famille | E4: Moindre fonctionnalité
A5: Profile | B5: CCCS Medium / PBMM Moderate | D5: Profil | E5: CCCS Moyen / PBMM Modéré
A6: Primary Evidence Tool | D6: Outil de preuve principal
A7: Contributing Tools | D7: Outils contributeurs
A8: Control Description | B8: LEAST FUNCTIONALITY | AUTHORIZED SOFTWARE / WHITELISTING (a) The organization identifies authorized software programs in baseline configuration and information system component inventory; (b) The organization employs a deny-all, permit-by-exception policy to allow the execution of authorized software programs on the information system; and (c) The organization reviews and updates the list of authorized software programs at least annually or when there is a change. | D8: Description du contrôle | E8: MOINDRE FONCTIONNALITÉ | LOGICIELS AUTORISÉS/LISTES BLANCHES (a) L’organisation détermine les programmes logiciels autorisés dans la configuration de base et l’inventaire des composants du système d’information; (b) L’organisation a recours à une politique « refuser tout, autoriser par exception » pour permettre l’exécution de programmes logiciels autorisés dans le système d’information; (c) L’organisation revoit et met à jour la liste des logiciels autorisés au moins une fois par année ou lorsqu’il y a un changement.
A9: Supplemental Guidance | B9: The process used to identify software programs that are authorized to execute on organizational information systems is commonly referred to as whitelisting. In addition to whitelisting, organizations consider verifying the integrity of white-listed software programs using, for example, cryptographic checksums, digital signatures, or hash functions. Verification of white-listed software can occur either prior to execution or at system start-up. Related controls: CM-2, CM-6, CM-8, SA-10, SC-34, SI-7 | D9: Directives supplémentaires | E9: Le processus utilisé pour déterminer les programmes logiciels dont l’exécution est autorisée sur les systèmes d’information organisationnels est communément appelé liste blanche. En plus de la liste blanche, les organisations envisagent de vérifier l’intégrité des logiciels qui figurent sur la liste blanche en utilisant, par exemple, des totaux de contrôle cryptographique, des signatures numériques ou des fonctions de hachage. La vérification des logiciels de la liste blanche peut avoir lieu avant l’exécution ou lors du démarrage du système. Contrôles connexes : CM-2, CM-6, CM-8, SA-10, SC-34, SI-7
A10: Test Case | D10: Cas de test
A11: Test | B11: TEST-CM-7(5) | D11: Test | E11: TEST-CM-7(5)
A12: Requirement ID | B12: CM-7(5) | D12: ID Exigence | E12: CM-7(5)
A13: Component | D13: Composant
A14: Requirement | D14: Exigence
A15: Contextual Design Description | D15: Description contextuelle du design
A16: Evidence Provided | D16: Preuve fournie
A17: Preparer Sign Off (Initials, Date) | D17: Signataire préparateur (Initiales, Date)
A18: Owner Sign Off (Initials, Date) | D18: Signataire propriétaire (Initiales, Date)
A19: Assessor Sign Off (Initials, Date) | D19: Signataire évaluateur (Initiales, Date)
A20: Status | B20: Not Started | D20: Statut | E20: Non commencé
A21: Comments | D21: Commentaires

Sheet CM-11
A1: Control CM-11 — Evidence Tracking | D1: Contrôle CM-11 — Suivi des preuves
A2: Control Information | D2: Informations du contrôle
A3: Control Identifier | B3: CM-11 | D3: Identifiant du contrôle | E3: CM-11
A4: Family | B4: User Installed Software | D4: Famille | E4: Logiciel installé par l’utilisateur
A5: Profile | B5: CCCS Medium / PBMM Moderate | D5: Profil | E5: CCCS Moyen / PBMM Modéré
A6: Primary Evidence Tool | D6: Outil de preuve principal
A7: Contributing Tools | D7: Outils contributeurs
A8: Control Description | B8: (A) The organization establishes organization-defined policies governing the installation of software by users. (B) The organization enforces software installation policies through organization-defined methods. (C) The organization monitors policy compliance continuously via 7(5). | D8: Description du contrôle | E8: (A) L’organisation définit et établit des politiques régissant l’installation de logiciels par les utilisateurs. (B) L’organisation applique les politiques d’installation de logiciels au moyen de méthodes définies par l’organisation. (C) L’organisation surveille continuellement la conformité aux politiques au moyen du contrôle 7(5).
A9: Supplemental Guidance | B9: If provided the necessary privileges, users have the ability to install software in organizational information systems. To maintain control over the types of software installed, organizations identify permitted and prohibited actions regarding software installation. Permitted software installations may include, for example, updates and security patches to existing software and downloading applications from organization-approved “app stores.” Prohibited software installations may include, for example, software with unknown or suspect pedigrees or software that organizations consider potentially malicious. The policies organizations select governing user-installed software may be organization-developed or provided by some external entity. Policy enforcement methods include procedural methods (e.g., periodic examination of user accounts), automated methods (e.g., configuration settings implemented on organizational information systems), or both. Related controls: AC-3, CM-2, CM-3, CM-5, CM-6, CM-7, PL-4 | D9: Directives supplémentaires | E9: Si on leur accorde les privilèges nécessaires, les utilisateurs peuvent installer des logiciels dans les systèmes d’information organisationnels. Pour garder le contrôle sur les types de logiciels installés, les organisations déterminent les actions permises et interdites relativement à l’installation de logiciels. Les installations logicielles autorisées peuvent comprendre, par exemple, des mises à jour et des correctifs de sécurité aux logiciels existants et le téléchargement d’applications à partir de « boutiques d’applications » approuvées par l’organisation. Les installations logicielles interdites peuvent comprendre, par exemple, les logiciels dont le contenu est inconnu ou suspect ou les logiciels que les organisations considèrent comme potentiellement malveillants. Les politiques choisies par les organisations pour régir les logiciels installés par les utilisateurs peuvent être élaborées par l’organisation même ou fournies par une entité externe. Les méthodes d’application des politiques comprennent les méthodes procédurales (p. ex., examen périodique des comptes des utilisateurs), les méthodes automatisées (p. ex., les paramètres de configuration mis en œuvre dans les systèmes d’information organisationnels), ou les deux. Contrôles connexes : AC-3, CM-2, CM-3, CM-5, CM-6, CM-7, PL-4
A10: Test Case | D10: Cas de test
A11: Test | B11: TEST-CM-11 | D11: Test | E11: TEST-CM-11
A12: Requirement ID | B12: CM-11 | D12: ID Exigence | E12: CM-11
A13: Component | D13: Composant
A14: Requirement | D14: Exigence
A15: Contextual Design Description | D15: Description contextuelle du design
A16: Evidence Provided | D16: Preuve fournie
A17: Preparer Sign Off (Initials, Date) | D17: Signataire préparateur (Initiales, Date)
A18: Owner Sign Off (Initials, Date) | D18: Signataire propriétaire (Initiales, Date)
A19: Assessor Sign Off (Initials, Date) | D19: Signataire évaluateur (Initiales, Date)
A20: Status | B20: Not Started | D20: Statut | E20: Non commencé
A21: Comments | D21: Commentaires

Sheet CP-6
A1: Control CP-6 — Evidence Tracking | D1: Contrôle CP-6 — Suivi des preuves
A2: Control Information | D2: Informations du contrôle
A3: Control Identifier | B3: CP-6 | D3: Identifiant du contrôle | E3: CP-6
A4: Family | B4: Alternate Storage Site | D4: Famille | E4: Site de stockage auxiliaire
A5: Profile | B5: CCCS Medium / PBMM Moderate | D5: Profil | E5: CCCS Moyen / PBMM Modéré
A6: Primary Evidence Tool | D6: Outil de preuve principal
A7: Contributing Tools | D7: Outils contributeurs
A8: Control Description | B8: (A) The organization establishes an alternate storage site including necessary agreements to permit the storage and retrieval of information system backup information. (B) The organization ensures that the alternate storage site provides information security safeguards equivalent to that of the primary site. | D8: Description du contrôle | E8: (A) L’organisation établit un site de stockage auxiliaire, incluant les ententes nécessaires pour permettre le stockage et l’extraction de l’information de sauvegarde du système d’information. (B) L’organisation veille à ce que le site de stockage auxiliaire offre des mesures de sécurité de l’information équivalentes à celles du site principal.
A9: Supplemental Guidance | B9: Alternate storage sites are sites that are geographically distinct from primary storage sites. An alternate storage site maintains duplicate copies of information and data in the event that the primary storage site is not available. Items covered by alternate storage site agreements include, for example, environmental conditions at alternate sites, access rules, physical and environmental protection requirements, and coordination of delivery/retrieval of backup media. Alternate storage sites reflect the requirements in contingency plans so that organizations can maintain essential missions/business functions despite disruption, compromise, or failure in organizational information systems. Related controls: CP-2, CP-7, CP-9, CP-10, MP-4 | D9: Directives supplémentaires | E9: Les sites de stockage auxiliaires sont des sites qui sont géographiquement séparés des sites de stockage principaux. Un site de stockage auxiliaire conserve des copies de l’information et des données advenant la non-disponibilité du site de stockage principal. Les éléments couverts par les accords sur les sites de stockage auxiliaires comprennent, par exemple, les conditions environnementales aux sites auxiliaires, les règles d’accès, les exigences en matière de protection physique et environnementale, et la coordination de la livraison/récupération des supports de sauvegarde. Les sites de stockage auxiliaires reflètent les exigences des plans d’urgence afin que les organisations puissent maintenir les fonctions opérationnelles et de mission essentielles malgré la perturbation, la compromission ou la défaillance des systèmes d’information organisationnels. Contrôles connexes : CP-2, CP-7, CP-9, CP-10, MP-4
A10: Test Case | D10: Cas de test
A11: Test | B11: TEST-CP-6 | D11: Test | E11: TEST-CP-6
A12: Requirement ID | B12: CP-6 | D12: ID Exigence | E12: CP-6
A13: Component | D13: Composant
A14: Requirement | D14: Exigence
A15: Contextual Design Description | D15: Description contextuelle du design
A16: Evidence Provided | D16: Preuve fournie
A17: Preparer Sign Off (Initials, Date) | D17: Signataire préparateur (Initiales, Date)
A18: Owner Sign Off (Initials, Date) | D18: Signataire propriétaire (Initiales, Date)
A19: Assessor Sign Off (Initials, Date) | D19: Signataire évaluateur (Initiales, Date)
A20: Status | B20: Not Started | D20: Statut | E20: Non commencé
A21: Comments | D21: Commentaires

Sheet CP-6-2
A1: Control CP-6(2) — Evidence Tracking | D1: Contrôle CP-6(2) — Suivi des preuves
A2: Control Information | D2: Informations du contrôle
A3: Control Identifier | B3: CP-6(2) | D3: Identifiant du contrôle | E3: CP-6(2)
A4: Family | B4: Alternate Storage Site | D4: Famille | E4: Site de stockage auxiliaire
A5: Profile | B5: CCCS Medium / PBMM Moderate | D5: Profil | E5: CCCS Moyen / PBMM Modéré
A6: Primary Evidence Tool | D6: Outil de preuve principal
A7: Contributing Tools | D7: Outils contributeurs
A8: Control Description | B8: ALTERNATE STORAGE SITE | RECOVERY TIME / POINT OBJECTIVES The organization configures the alternate storage site to facilitate recovery operations in accordance with recovery time and recovery point objectives. | D8: Description du contrôle | E8: SITE DE STOCKAGE AUXILIAIRE | OBJECTIFS EN MATIÈRE DE DÉLAIS/POINTS DE REPRISE L’organisation configure le site de stockage auxiliaire de manière à faciliter les opérations de reprise conformément aux objectifs en matière de délais et de points de reprise.
A9: Supplemental Guidance | D9: Directives supplémentaires
A10: Test Case | D10: Cas de test
A11: Test | B11: TEST-CP-6(2) | D11: Test | E11: TEST-CP-6(2)
A12: Requirement ID | B12: CP-6(2) | D12: ID Exigence | E12: CP-6(2)
A13: Component | D13: Composant
A14: Requirement | D14: Exigence
A15: Contextual Design Description | D15: Description contextuelle du design
A16: Evidence Provided | D16: Preuve fournie
A17: Preparer Sign Off (Initials, Date) | D17: Signataire préparateur (Initiales, Date)
A18: Owner Sign Off (Initials, Date) | D18: Signataire propriétaire (Initiales, Date)
A19: Assessor Sign Off (Initials, Date) | D19: Signataire évaluateur (Initiales, Date)
A20: Status | B20: Not Started | D20: Statut | E20: Non commencé
A21: Comments | D21: Commentaires

Sheet CP-7
A1: Control CP-7 — Evidence Tracking | D1: Contrôle CP-7 — Suivi des preuves
A2: Control Information | D2: Informations du contrôle
A3: Control Identifier | B3: CP-7 | D3: Identifiant du contrôle | E3: CP-7
A4: Family | B4: Alternate Processing Site | D4: Famille | E4: Site de traitement auxiliaire
A5: Profile | B5: CCCS Medium / PBMM Moderate | D5: Profil | E5: CCCS Moyen / PBMM Modéré
A6: Primary Evidence Tool | D6: Outil de preuve principal
A7: Contributing Tools | D7: Outils contributeurs
A8: Control Description | B8: (A) The organization establishes an alternate processing site including necessary agreements to permit the transfer and resumption of organization-defined information system operations for essential missions/business functions within organization-defined time period consistent with recovery time and recovery point objectives when the primary processing capabilities are unavailable. (B) The organization ensures that equipment and supplies required to transfer and resume operations are available at the alternate processing site or contracts are in place to support delivery to the site within the organization-defined time period for transfer/resumption. (C) The organization ensures that the alternate processing site provides information security safeguards equivalent to that of the primary site. | D8: Description du contrôle | E8: (A) L’organisation établit un site de traitement auxiliaire, y compris les ententes nécessaires pour permettre le transfert et la reprise des opérations du système d’information définies par l’organisation pour les missions et les fonctions opérationnelles essentielles à l’intérieur d’une période définie par l’organisation, conformément aux objectifs en matière de délais de reprise et de points de reprise lorsque les capacités de traitement principales ne sont pas disponibles. (B) L’organisation veille à ce que l’équipement et les fournitures nécessaires au transfert et à la reprise des activités soient disponibles au site de traitement auxiliaire, ou à ce que des contrats soient en place pour soutenir la livraison au site à l’intérieur de la période définie par l’organisation pour le transfert ou la reprise. (C) L’organisation veille à ce que le site de traitement auxiliaire offre des mesures de sécurité de l’information équivalentes à celles du site principal.
A9: Supplemental Guidance | B9: Alternate processing sites are sites that are geographically distinct from primary processing sites. An alternate processing site provides processing capability in the event that the primary processing site is not available. Items covered by alternate processing site agreements include, for example, environmental conditions at alternate sites, access rules, physical and environmental protection requirements, and coordination for the transfer/assignment of personnel. Requirements are specifically allocated to alternate processing sites that reflect the requirements in contingency plans to maintain essential missions/business functions despite disruption, compromise, or failure in organizational information systems. Related controls: CP-2, CP-6, CP-8, CP-9, CP-10, MA-6 | D9: Directives supplémentaires | E9: Les sites de traitement auxiliaires sont des sites qui sont géographiquement séparés des sites de traitement principaux. Un site de traitement auxiliaire offre une capacité de traitement lorsque le site de traitement principal n’est pas disponible. Les éléments couverts par les accords sur les sites de traitement auxiliaires comprennent, par exemple, les conditions environnementales aux sites auxiliaires, les règles d’accès, les exigences en matière de protection physique et environnementale, et la coordination pour le transfert ou l’attribution du personnel. Les exigences spécifiquement attribuées aux sites de traitement auxiliaires reflètent les exigences des plans d’urgence pour maintenir les fonctions opérationnelles et de mission essentielles malgré la perturbation, la compromission ou la défaillance des systèmes d’information organisationnels. Contrôles connexes : CP-2, CP-6, CP-8, CP-9, CP-10, MA-6
A10: Test Case | D10: Cas de test
A11: Test | B11: TEST-CP-7 | D11: Test | E11: TEST-CP-7
A12: Requirement ID | B12: CP-7 | D12: ID Exigence | E12: CP-7
A13: Component | D13: Composant
A14: Requirement | D14: Exigence
A15: Contextual Design Description | D15: Description contextuelle du design
A16: Evidence Provided | D16: Preuve fournie
A17: Preparer Sign Off (Initials, Date) | D17: Signataire préparateur (Initiales, Date)
A18: Owner Sign Off (Initials, Date) | D18: Signataire propriétaire (Initiales, Date)
A19: Assessor Sign Off (Initials, Date) | D19: Signataire évaluateur (Initiales, Date)
A20: Status | B20: Not Started | D20: Statut | E20: Non commencé
A21: Comments | D21: Commentaires

Sheet CP-7-4
A1: Control CP-7(4) — Evidence Tracking | D1: Contrôle CP-7(4) — Suivi des preuves
A2: Control Information | D2: Informations du contrôle
A3: Control Identifier | B3: CP-7(4) | D3: Identifiant du contrôle | E3: CP-7(4)
A4: Family | B4: Alternate Processing Site | D4: Famille | E4: Site de traitement auxiliaire
A5: Profile | B5: CCCS Medium / PBMM Moderate | D5: Profil | E5: CCCS Moyen / PBMM Modéré
A6: Primary Evidence Tool | D6: Outil de preuve principal
A7: Contributing Tools | D7: Outils contributeurs
A8: Control Description | B8: ALTERNATE PROCESSING SITE | PREPARATION FOR USE The organization prepares the alternate processing site so that the site is ready to be used as the operational site supporting essential missions and business functions. | D8: Description du contrôle | E8: SITE DE TRAITEMENT AUXILIAIRE | PRÉPARATION À L’UTILISATION L’organisation prépare le site de traitement auxiliaire de manière à ce que le site soit prêt à être utilisé comme site opérationnel prenant en charge les fonctions opérationnelles et les missions essentielles.
A9: Supplemental Guidance | B9: Site preparation includes, for example, establishing configuration settings for information system components at the alternate processing site consistent with the requirements for such settings at the primary site and ensuring that essential supplies and other logistical considerations are in place. Related controls: CM-2, CM-6. | D9: Directives supplémentaires | E9: La préparation du site comprend, par exemple, l’établissement des paramètres de configuration pour les composants du système d’information au site de traitement auxiliaire, conformément aux exigences pour ces paramètres au site principal, et l’assurance que les fournitures essentielles et autres considérations logistiques sont en place. Contrôles connexes : CM-2, CM-6.
A10: Test Case | D10: Cas de test
A11: Test | B11: TEST-CP-7(4) | D11: Test | E11: TEST-CP-7(4)
A12: Requirement ID | B12: CP-7(4) | D12: ID Exigence | E12: CP-7(4)
A13: Component | D13: Composant
A14: Requirement | D14: Exigence
A15: Contextual Design Description | D15: Description contextuelle du design
A16: Evidence Provided | D16: Preuve fournie
A17: Preparer Sign Off (Initials, Date) | D17: Signataire préparateur (Initiales, Date)
A18: Owner Sign Off (Initials, Date) | D18: Signataire propriétaire (Initiales, Date)
A19: Assessor Sign Off (Initials, Date) | D19: Signataire évaluateur (Initiales, Date)
A20: Status | B20: Not Started | D20: Statut | E20: Non commencé
A21: Comments | D21: Commentaires

Sheet CP-9
A1: Control CP-9 — Evidence Tracking | D1: Contrôle CP-9 — Suivi des preuves
A2: Control Information | D2: Informations du contrôle
A3: Control Identifier | B3: CP-9 | D3: Identifiant du contrôle | E3: CP-9
A4: Family | B4: Information System Backup | D4: Famille | E4: Sauvegarde du système d’information
A5: Profile | B5: CCCS Medium / PBMM Moderate | D5: Profil | E5: CCCS Moyen / PBMM Modéré
A6: Primary Evidence Tool | D6: Outil de preuve principal
A7: Contributing Tools | D7: Outils contributeurs
A8: Control Description | B8: (A) The organization conducts backups of user-level information contained in the information system daily incremental; weekly full. (B) The organization conducts backups of system-level information contained in the information system daily incremental; weekly full. (C) The organization conducts backups of information system documentation including security-related documentation daily incremental; weekly full. (D) The organization protects the confidentiality, integrity, and availability of backup information at storage locations. (AA) The organization determines retention periods for essential business information and archived backups. | D8: Description du contrôle | E8: (A) L’organisation effectue des sauvegardes incrémentielles quotidiennes et des sauvegardes hebdomadaires complètes de l’information au niveau de l’utilisateur qui est contenue dans le système d’information. (B) L’organisation effectue des sauvegardes incrémentielles quotidiennes et des sauvegardes hebdomadaires complètes de l’information au niveau du système contenue dans le système d’information. (C) L’organisation effectue des sauvegardes incrémentielles quotidiennes et des sauvegardes hebdomadaires complètes de la documentation relative au système d’information, y compris la documentation liée à la sécurité. (D) L’organisation protège la confidentialité, l’intégrité et la disponibilité de l’information de sauvegarde aux emplacements de stockage. (AA) L’organisation détermine les périodes de conservation des renseignements opérationnels essentiels et des sauvegardes archivées.
A9: Supplemental Guidance | B9: System-level information includes, for example, system-state information, operating system and application software, and licenses. User-level information includes any information other than system-level information. Mechanisms employed by organizations to protect the integrity of information system backups include, for example, digital signatures and cryptographic hashes. Protection of system backup information while in transit is beyond the scope of this control. Information system backups reflect the requirements in contingency plans as well as other organizational requirements for backing up information. Related controls: CP-2, CP-6, MP-4, MP-5, SC-13 | D9: Directives supplémentaires | E9: L’information au niveau du système comprend, par exemple, l’information sur l’état du système, le système d’exploitation, les logiciels d’application et les licences. L’information au niveau de l’utilisateur comprend toute information autre que l’information au niveau du système. Les mécanismes employés par les organisations pour protéger l’intégrité des sauvegardes du système d’information comprennent, par exemple, les signatures numériques et le hachage cryptographique. La protection de l’information de sauvegarde du système pendant le transport dépasse la portée de ce contrôle. Les sauvegardes du système d’information reflètent les exigences des plans d’urgence ainsi que d’autres exigences organisationnelles relatives à la sauvegarde de l’information. Contrôles connexes : CP-2, CP-6, MP-4, MP-5, SC-13
A10: Test Case | D10: Cas de test
A11: Test | B11: TEST-CP-9 | D11: Test | E11: TEST-CP-9
A12: Requirement ID | B12: CP-9 | D12: ID Exigence | E12: CP-9
A13: Component | D13: Composant
A14: Requirement | D14: Exigence
A15: Contextual Design Description | D15: Description contextuelle du design
A16: Evidence Provided | D16: Preuve fournie
A17: Preparer Sign Off (Initials, Date) | D17: Signataire préparateur (Initiales, Date)
A18: Owner Sign Off (Initials, Date) | D18: Signataire propriétaire (Initiales, Date)
A19: Assessor Sign Off (Initials, Date) | D19: Signataire évaluateur (Initiales, Date)
A20: Status | B20: Not Started | D20: Statut | E20: Non commencé
A21: Comments | D21: Commentaires

Sheet CP-9-1
A1: Control CP-9(1) — Evidence Tracking | D1: Contrôle CP-9(1) — Suivi des preuves
A2: Control Information | D2: Informations du contrôle
A3: Control Identifier | B3: CP-9(1) | D3: Identifiant du contrôle | E3: CP-9(1)
A4: Family | B4: Information System Backup | D4: Famille | E4: Sauvegarde du système d’information
A5: Profile | B5: CCCS Medium / PBMM Moderate | D5: Profil | E5: CCCS Moyen / PBMM Modéré
A6: Primary Evidence Tool | D6: Outil de preuve principal
A7: Contributing Tools | D7: Outils contributeurs
A8: Control Description | B8: INFORMATION SYSTEM BACKUP | TESTING FOR RELIABILITY / INTEGRITY The organization tests backup information at least annually to verify media reliability and information integrity. | D8: Description du contrôle | E8: SAUVEGARDE DU SYSTÈME D’INFORMATION | VÉRIFICATION DE LA FIABILITÉ ET DE L’INTÉGRITÉ L’organisation teste l’information de sauvegarde au moins une fois par année pour vérifier la fiabilité des supports et l’intégrité de l’information.
A9: Supplemental Guidance | B9: Related control: CP-4. | D9: Directives supplémentaires | E9: Contrôle connexe : CP-4.
A10: Test Case | D10: Cas de test
A11: Test | B11: TEST-CP-9(1) | D11: Test | E11: TEST-CP-9(1)
A12: Requirement ID | B12: CP-9(1) | D12: ID Exigence | E12: CP-9(1)
A13: Component | D13: Composant
A14: Requirement | D14: Exigence
A15: Contextual Design Description | D15: Description contextuelle du design
A16: Evidence Provided | D16: Preuve fournie
A17: Preparer Sign Off (Initials, Date) | D17: Signataire préparateur (Initiales, Date)
A18: Owner Sign Off (Initials, Date) | D18: Signataire propriétaire (Initiales, Date)
A19: Assessor Sign Off (Initials, Date) | D19: Signataire évaluateur (Initiales, Date)
A20: Status | B20: Not Started | D20: Statut | E20: Non commencé
A21: Comments | D21: Commentaires

Sheet CP-9-2
A1: Control CP-9(2) — Evidence Tracking | D1: Contrôle CP-9(2) — Suivi des preuves
A2: Control Information | D2: Informations du contrôle
A3: Control Identifier | B3: CP-9(2) | D3: Identifiant du contrôle | E3: CP-9(2)
A4: Family | B4: Information System Backup | D4: Famille | E4: Sauvegarde du système d’information
A5: Profile | B5: CCCS Medium / PBMM Moderate | D5: Profil | E5: CCCS Moyen / PBMM Modéré
A6: Primary Evidence Tool | D6: Outil de preuve principal
A7: Contributing Tools | D7: Outils contributeurs
A8: Control Description | B8: INFORMATION SYSTEM BACKUP | TEST RESTORATION USING SAMPLING The organization uses a sample of backup information in the restoration of selected information system functions as part of contingency plan testing. | D8: Description du contrôle | E8: SAUVEGARDE DU SYSTÈME D’INFORMATION | ESSAIS DE RESTAURATION AU MOYEN DE L’ÉCHANTILLONNAGE L’organisation utilise un échantillon de l’information de sauvegarde pour restaurer certaines fonctions du système d’information dans le cadre de la mise à l’essai du plan d’urgence.
A9: Supplemental Guidance | B9: Related control: CP-4. | D9: Directives supplémentaires | E9: Contrôle connexe : CP-4.
A10: Test Case | D10: Cas de test
A11: Test | B11: TEST-CP-9(2) | D11: Test | E11: TEST-CP-9(2)
A12: Requirement ID | B12: CP-9(2) | D12: ID Exigence | E12: CP-9(2)
A13: Component | D13: Composant
A14: Requirement | D14: Exigence
A15: Contextual Design Description | D15: Description contextuelle du design
A16: Evidence Provided | D16: Preuve fournie
A17: Preparer Sign Off (Initials, Date) | D17: Signataire préparateur (Initiales, Date)
A18: Owner Sign Off (Initials, Date) | D18: Signataire propriétaire (Initiales, Date)
A19: Assessor Sign Off (Initials, Date) | D19: Signataire évaluateur (Initiales, Date)
A20: Status | B20: Not Started | D20: Statut | E20: Non commencé
A21: Comments | D21: Commentaires

Sheet CP-9-5
A1: Control CP-9(5) — Evidence Tracking | D1: Contrôle CP-9(5) — Suivi des preuves
A2: Control Information | D2: Informations du contrôle
A3: Control Identifier | B3: CP-9(5) | D3: Identifiant du contrôle | E3: CP-9(5)
A4: Family | B4: Information System Backup | D4: Famille | E4: Sauvegarde du système d’information
A5: Profile | B5: CCCS Medium / PBMM Moderate | D5: Profil | E5: CCCS Moyen / PBMM Modéré
A6: Primary Evidence Tool | D6: Outil de preuve principal
A7: Contributing Tools | D7: Outils contributeurs
A8: Control Description | B8: INFORMATION SYSTEM BACKUP | TRANSFER TO ALTERNATE STORAGE SITE The organization transfers information system backup information to the alternate storage site at organization-defined time period and transfer rate consistent with the recovery time and recovery point objectives. | D8: Description du contrôle | E8: SAUVEGARDE DU SYSTÈME D’INFORMATION | TRANSFERT À UN SITE DE STOCKAGE AUXILIAIRE L’organisation transfère l’information de sauvegarde du système d’information au site de stockage auxiliaire au moment et à la vitesse de transfert définis par l’organisation conformément aux objectifs en matière de délais et de points de reprise.
A9: Supplemental Guidance | B9: Information system backup information can be transferred to alternate storage sites either electronically or by physical shipment of storage media. | D9: Directives supplémentaires | E9: Les données de sauvegarde du système d’information peuvent être transférées à des sites de stockage auxiliaires par voie électronique ou par envoi physique de supports de stockage.
A10: Test Case | D10: Cas de test
A11: Test | B11: TEST-CP-9(5) | D11: Test | E11: TEST-CP-9(5)
A12: Requirement ID | B12: CP-9(5) | D12: ID Exigence | E12: CP-9(5)
A13: Component | D13: Composant
A14: Requirement | D14: Exigence
A15: Contextual Design Description | D15: Description contextuelle du design
A16: Evidence Provided | D16: Preuve fournie
A17: Preparer Sign Off (Initials, Date) | D17: Signataire préparateur (Initiales, Date)
A18: Owner Sign Off (Initials, Date) | D18: Signataire propriétaire (Initiales, Date)
A19: Assessor Sign Off (Initials, Date) | D19: Signataire évaluateur (Initiales, Date)
A20: Status | B20: Not Started | D20: Statut | E20: Non commencé
A21: Comments | D21: Commentaires

Sheet CP-10
A1: Control CP-10 — Evidence Tracking | D1: Contrôle CP-10 — Suivi des preuves
A2: Control Information | D2: Informations du contrôle
A3: Control Identifier | B3: CP-10 | D3: Identifiant du contrôle | E3: CP-10
A4: Family | B4: Information System Recovery and Reconstitution | D4: Famille | E4: Reprise et reconstitution du système d’information
A5: Profile | B5: CCCS Medium / PBMM Moderate | D5: Profil | E5: CCCS Moyen / PBMM Modéré
A6: Primary Evidence Tool | D6: Outil de preuve principal
A7: Contributing Tools | D7: Outils contributeurs
A8: Control Description | B8: (A) The organization provides for the recovery and reconstitution of the information system to a known state after a disruption, compromise, or failure. | D8: Description du contrôle | E8: (A) L’organisation assure la reprise et la reconstitution du système d’information dans un état connu après une perturbation, une compromission ou une défaillance.
A9: Supplemental Guidance | B9: Recovery is executing information system contingency plan activities to restore organizational missions/business functions. Reconstitution takes place following recovery and includes activities for returning organizational information systems to fully operational states. Recovery and reconstitution operations reflect mission and business priorities, recovery point/time and reconstitution objectives, and established organizational metrics consistent with contingency plan requirements. Reconstitution includes the deactivation of any interim information system capabilities that may have been needed during recovery operations. Reconstitution also includes assessments of fully restored information system capabilities, reestablishment of continuous monitoring activities, potential information system reauthorizations, and activities to prepare the systems against future disruptions, compromises, or failures. Recovery/reconstitution capabilities employed by organizations can include both automated mechanisms and manual procedures. Related controls: CA-2, CA-6, CA-7, CP-2, CP-4, CP-6, CP-7, CP-9, SC-24 | D9: Directives supplémentaires | E9: La reprise consiste à exécuter les activités du plan d’urgence du système d’information pour restaurer les fonctions opérationnelles et de mission de l’organisation. La reconstitution a lieu après la reprise et comprend les activités permettant de remettre les systèmes d’information organisationnels à l’état pleinement opérationnel. Les opérations de reprise et de reconstitution reflètent les priorités opérationnelles et de mission, les objectifs en matière de délais, de points de reprise et de reconstitution, de même que les paramètres organisationnels établis conformément aux exigences du plan d’urgence. La reconstitution comprend la désactivation de toute capacité provisoire du système d’information ayant pu être nécessaire pendant les opérations de reprise. La reconstitution comprend également l’évaluation des capacités entièrement restaurées du système d’information, le rétablissement des activités de surveillance continue, les réautorisations possibles du système d’information et les activités visant à préparer les systèmes à faire face aux perturbations, compromissions ou défaillances futures. Les capacités de reprise et de reconstitution utilisées par les organisations peuvent comprendre des mécanismes automatisés et des procédures manuelles. Contrôles connexes : CA-2, CA-6, CA-7, CP-2, CP-4, CP-6, CP-7, CP-9, SC-24
A10: Test Case | D10: Cas de test
A11: Test | B11: TEST-CP-10 | D11: Test | E11: TEST-CP-10
A12: Requirement ID | B12: CP-10 | D12: ID Exigence | E12: CP-10
A13: Component | D13: Composant
A14: Requirement | D14: Exigence
A15: Contextual Design Description | D15: Description contextuelle du design
A16: Evidence Provided | D16: Preuve fournie
A17: Preparer Sign Off (Initials, Date) | D17: Signataire préparateur (Initiales, Date)
A18: Owner Sign Off (Initials, Date) | D18: Signataire propriétaire (Initiales, Date)
A19: Assessor Sign Off (Initials, Date) | D19: Signataire évaluateur (Initiales, Date)
A20: Status | B20: Not Started | D20: Statut | E20: Non commencé
A21: Comments | D21: Commentaires

Sheet CP-10-4
A1: Control CP-10(4) — Evidence Tracking | D1: Contrôle CP-10(4) — Suivi des preuves
A2: Control Information | D2: Informations du contrôle
A3: Control Identifier | B3: CP-10(4) | D3: Identifiant du contrôle | E3: CP-10(4)
A4: Family | B4: Information System Recovery and Reconstitution | D4: Famille | E4: Reprise et reconstitution du système d’information
A5: Profile | B5: CCCS Medium / PBMM Moderate | D5: Profil | E5: CCCS Moyen / PBMM Modéré
A6: Primary Evidence Tool | D6: Outil de preuve principal
A7: Contributing Tools | D7: Outils contributeurs
A8: Control Description | B8: INFORMATION SYSTEM RECOVERY AND RECONSTITUTION | RESTORE WITHIN TIME PERIOD The organization provides the capability to restore information system components within organization-defined restoration time-periods from configuration-controlled and integrity-protected information representing a known, operational state for the components. | D8: Description du contrôle | E8: REPRISE ET RECONSTITUTION DU SYSTÈME D’INFORMATION | RESTAURATION DANS LE DÉLAI IMPARTI L’organisation fournit la capacité de restaurer les composants du système d’information dans les délais de restauration définis par l’organisation à partir de l’information contrôlée par la configuration et protégée par l’intégrité qui représente un état de fonctionnement connu pour les composants.
A9: Supplemental Guidance | B9: Restoration of information system components includes, for example, re-imaging which restores components to known, operational states. Related control: CM-2. | D9: Directives supplémentaires | E9: La restauration des composants du système d’information comprend, par exemple, la reconfiguration permettant de restaurer les composants aux états de fonctionnement connus. Contrôle connexe : CM-2.
A10: Test Case | D10: Cas de test
A11: Test | B11: TEST-CP-10(4) | D11: Test | E11: TEST-CP-10(4)
A12: Requirement ID | B12: CP-10(4) | D12: ID Exigence | E12: CP-10(4)
A13: Component | D13: Composant
A14: Requirement | D14: Exigence
A15: Contextual Design Description | D15: Description contextuelle du design
A16: Evidence Provided | D16: Preuve fournie
A17: Preparer Sign Off (Initials, Date) | D17: Signataire préparateur (Initiales, Date)
A18: Owner Sign Off (Initials, Date) | D18: Signataire propriétaire (Initiales, Date)
A19: Assessor Sign Off (Initials, Date) | D19: Signataire évaluateur (Initiales, Date)
A20: Status | B20: Not Started | D20: Statut | E20: Non commencé
A21: Comments | D21: Commentaires

Sheet IA-5-6
A1: Control IA-5(6) — Evidence Tracking | D1: Contrôle IA-5(6) — Suivi des preuves
A2: Control Information | D2: Informations du contrôle
A3: Control Identifier | B3: IA-5(6) | D3: Identifiant du contrôle | E3: IA-5(6)
A4: Family | B4: Authenticator Management | D4: Famille | E4: Gestion des authentifiants
A5: Profile | B5: CCCS Medium / PBMM Moderate | D5: Profil | E5: CCCS Moyen / PBMM Modéré
A6: Primary Evidence Tool | D6: Outil de preuve principal
A7: Contributing Tools | D7: Outils contributeurs
A8: Control Description | B8: AUTHENTICATOR MANAGEMENT | PROTECTION OF AUTHENTICATORS The organization protects authenticators commensurate with the security category of the information to which use of the authenticator permits access. | D8: Description du contrôle | E8: GESTION DES AUTHENTIFIANTS | PROTECTION DES AUTHENTIFIANTS L’organisation assure une protection des authentifiants qui est proportionnelle à la catégorie de sécurité de l’information à laquelle les authentifiants permettent l’accès.
A9: Supplemental Guidance | B9: For information systems containing multiple security categories of information without reliable physical or logical separation between categories, authenticators used to grant access to the systems are protected commensurate with the highest security category of information on the systems. | D9: Directives supplémentaires | E9: Dans le cas des systèmes d’information qui contiennent plusieurs catégories de sécurité de l’information sans séparation physique ou logique fiable entre les catégories, les authentifiants utilisés pour accorder l’accès aux systèmes sont protégés conformément à la catégorie de sécurité de l’information la plus élevée sur les systèmes.
A10: Test Case | D10: Cas de test
A11: Test | B11: TEST-IA-5(6) | D11: Test | E11: TEST-IA-5(6)
A12: Requirement ID | B12: IA-5(6) | D12: ID Exigence | E12: IA-5(6)
A13: Component | D13: Composant
A14: Requirement | D14: Exigence
A15: Contextual Design Description | D15: Description contextuelle du design
A16: Evidence Provided | D16: Preuve fournie
A17: Preparer Sign Off (Initials, Date) | D17: Signataire préparateur (Initiales, Date)
A18: Owner Sign Off (Initials, Date) | D18: Signataire propriétaire (Initiales, Date)
A19: Assessor Sign Off (Initials, Date) | D19: Signataire évaluateur (Initiales, Date)
A20: Status | B20: Not Started | D20: Statut | E20: Non commencé
A21: Comments | D21: Commentaires

Sheet IA-5-7
A1: Control IA-5(7) — Evidence Tracking | D1: Contrôle IA-5(7) — Suivi des preuves
A2: Control Information | D2: Informations du contrôle
A3: Control Identifier | B3: IA-5(7) | D3: Identifiant du contrôle | E3: IA-5(7)
A4: Family | B4: Authenticator Management | D4: Famille | E4: Gestion des authentifiants
A5: Profile | B5: CCCS Medium / PBMM Moderate | D5: Profil | E5: CCCS Moyen / PBMM Modéré
A6: Primary Evidence Tool | D6: Outil de preuve principal
A7: Contributing Tools | D7: Outils contributeurs
A8: Control Description | B8: AUTHENTICATOR MANAGEMENT | NO EMBEDDED UNENCRYPTED STATIC AUTHENTICATORS The organization ensures that unencrypted static authenticators are not embedded in applications or access scripts or stored on function keys. | D8: Description du contrôle | E8: GESTION DES AUTHENTIFIANTS | AUCUN AUTHENTIFIANT STATIQUE INTÉGRÉ NON CHIFFRÉ L’organisation veille à ce que les authentifiants statiques non chiffrés ne soient pas intégrés dans les applications ou les scripts d’accès ou stockés sur les clés de fonction.
A9: Supplemental Guidance | B9: Organizations exercise caution in determining whether embedded or stored authenticators are in encrypted or unencrypted form. If authenticators are used in the manner stored, then those representations are considered unencrypted authenticators. This is irrespective of whether that representation is perhaps an encrypted version of something else (e.g., a password). | D9: Directives supplémentaires | E9: Les organisations usent de prudence lorsqu’il s’agit de déterminer si les authentifiants intégrés ou stockés sont chiffrés ou non chiffrés. Si les authentifiants sont utilisés sous leur forme stockée, ces représentations sont alors considérées comme étant des authentifiants non chiffrés. Cela n’a rien à voir avec le fait que cette représentation puisse être une version chiffrée de quelque chose d’autre (p. ex., un mot de passe).
A10: Test Case | D10: Cas de test
A11: Test | B11: TEST-IA-5(7) | D11: Test | E11: TEST-IA-5(7)
A12: Requirement ID | B12: IA-5(7) | D12: ID Exigence | E12: IA-5(7)
A13: Component | D13: Composant
A14: Requirement | D14: Exigence
A15: Contextual Design Description | D15: Description contextuelle du design
A16: Evidence Provided | D16: Preuve fournie
A17: Preparer Sign Off (Initials, Date) | D17: Signataire préparateur (Initiales, Date)
A18: Owner Sign Off (Initials, Date) | D18: Signataire propriétaire (Initiales, Date)
A19: Assessor Sign Off (Initials, Date) | D19: Signataire évaluateur (Initiales, Date)
A20: Status | B20: Not Started | D20: Statut | E20: Non commencé
A21: Comments | D21: Commentaires

Sheet SA-9-5
A1: Control SA-9(5) — Evidence Tracking | D1: Contrôle SA-9(5) — Suivi des preuves
A2: Control Information | D2: Informations du contrôle
A3: Control Identifier | B3: SA-9(5) | D3: Identifiant du contrôle | E3: SA-9(5)
A4: Family | B4: External Information System Services | D4: Famille | E4: Services de systèmes d’information externes
A5: Profile | B5: CCCS Medium / PBMM Moderate | D5: Profil | E5: CCCS Moyen / PBMM Modéré
A6: Primary Evidence Tool | D6: Outil de preuve principal
A7: Contributing Tools | D7: Outils contributeurs
A8: Control Description | B8: EXTERNAL INFORMATION SYSTEMS | PROCESSING, STORAGE, AND SERVICE LOCATION The organization restricts the location of information processing, information/data, and information system services to locations witihin Canada based on ITPIN 2017-02 for Direction on Data Residency (https://www.canada.ca/en/treasury-board-secretariat/services/information-technology/policy-implementation-notices/direction-electronic-data-residency.html). | D8: Description du contrôle | E8: SYSTÈMES D’INFORMATION EXTERNES | EMPLACEMENT DU TRAITEMENT, DU STOCKAGE ET DES SERVICES L’organisation restreint la résidence du traitement de l’information, du stockage de l’information et des données, ainsi que des services de systèmes d’information aux endroits situés à l’intérieur du Canada, conformément à l’avis AMPTI 2017-02, Orientation relative à la résidence des données électroniques (https://www.canada.ca/fr/gouvernement/systeme/gouvernement-numerique/technologiques-modernes-nouveaux/orientation-relative-residence-donnees-electroniques.html).
A9: Supplemental Guidance | B9: The location of information processing, information/data storage, or information system services that are critical to organizations can have a direct impact on the ability of those organizations to successfully execute their missions/business functions. This situation exists when external providers control the location of processing, storage or services. The criteria external providers use for the selection of processing, storage, or service locations may be different from organizational criteria. For example, organizations may want to ensure that data/information storage locations are restricted to certain locations to facilitate incident response activities (e.g., forensic analyses, after-the-fact investigations) in case of information security breaches/compromises. Such incident response activities may be adversely affected by the governing laws or protocols in the locations where processing and storage occur and/or the locations from which information system services emanate. | D9: Directives supplémentaires | E9: L’emplacement des services de traitement de l’information et de stockage de l’information et des données ou des services de systèmes d’information qui sont essentiels pour les organisations peut avoir une incidence directe sur la capacité de ces organisations d’exécuter avec succès leurs fonctions opérationnelles et de mission. Cette situation existe lorsque des fournisseurs externes contrôlent l’emplacement du traitement, de l’entreposage ou des services. Les critères utilisés par les fournisseurs externes pour choisir les lieux de traitement, d’entreposage ou de service peuvent être différents des critères de l’organisation. Par exemple, les organisations pourraient vouloir s’assurer que les emplacements de stockage des données ou de l’information se limitent à certains endroits afin de faciliter les activités d’intervention (p. ex., analyses judiciaires, enquêtes après coup) en cas d’incident représentant une atteinte à, ou une compromission de la sécurité de l’information. Ces activités d’intervention en cas d’incident peuvent être affectées négativement par les lois ou les protocoles en vigueur aux endroits où le traitement et l’entreposage ont lieu ou aux endroits d’où proviennent les services de systèmes d’information.
A10: Test Case | D10: Cas de test
A11: Test | B11: TEST-SA-9(5) | D11: Test | E11: TEST-SA-9(5)
A12: Requirement ID | B12: SA-9(5) | D12: ID Exigence | E12: SA-9(5)
A13: Component | D13: Composant
A14: Requirement | D14: Exigence
A15: Contextual Design Description | D15: Description contextuelle du design
A16: Evidence Provided | D16: Preuve fournie
A17: Preparer Sign Off (Initials, Date) | D17: Signataire préparateur (Initiales, Date)
A18: Owner Sign Off (Initials, Date) | D18: Signataire propriétaire (Initiales, Date)
A19: Assessor Sign Off (Initials, Date) | D19: Signataire évaluateur (Initiales, Date)
A20: Status | B20: Not Started | D20: Statut | E20: Non commencé
A21: Comments | D21: Commentaires

Sheet SA-10-1
A1: Control SA-10(1) — Evidence Tracking | D1: Contrôle SA-10(1) — Suivi des preuves
A2: Control Information | D2: Informations du contrôle
A3: Control Identifier | B3: SA-10(1) | D3: Identifiant du contrôle | E3: SA-10(1)
A4: Family | B4: Developer Configuration Management | D4: Famille | E4: Gestion de la configuration par le développeur
A5: Profile | B5: CCCS Medium / PBMM Moderate | D5: Profil | E5: CCCS Moyen / PBMM Modéré
A6: Primary Evidence Tool | D6: Outil de preuve principal
A7: Contributing Tools | D7: Outils contributeurs
A8: Control Description | B8: DEVELOPER CONFIGURATION MANAGEMENT | SOFTWARE / FIRMWARE INTEGRITY VERIFICATION The organization requires the developer of the information system, system component, or information system service to enable integrity verification of software and firmware components. | D8: Description du contrôle | E8: GESTION DE LA CONFIGURATION PAR LE DÉVELOPPEUR | VÉRIFICATION DE L’INTÉGRITÉ DES LOGICIELS ET DES MICROLOGICIELS L’organisation exige que le développeur du système d’information, du composant de système ou du service de système d’information permette la vérification de l’intégrité des composants logiciels et micrologiciels.
A9: Supplemental Guidance | B9: This control enhancement allows organizations to detect unauthorized changes to software and firmware components through the use of tools, techniques, and/or mechanisms provided by developers. Integrity checking mechanisms can also address counterfeiting of software and firmware components. Organizations verify the integrity of software and firmware components, for example, through secure one-way hashes provided by developers. Delivered software and firmware components also include any updates to such components. Related control: SI-7. | D9: Directives supplémentaires | E9: Cette amélioration du contrôle permet aux organisations de détecter les changements non autorisés aux composants logiciels et micrologiciels au moyen d’outils, de techniques ou de mécanismes fournis par les développeurs. Les mécanismes de vérification de l’intégrité peuvent également s’attaquer aux contrefaçons de composants logiciels et micrologiciels. Les organisations vérifient l’intégrité des composants logiciels et micrologiciels, par exemple, au moyen de hachages sécurisés à sens unique fournis par les développeurs. Les composants logiciels et micrologiciels fournis comprennent également toute mise à jour de ces composants. Contrôle connexe : SI-7.
A10: Test Case | D10: Cas de test
A11: Test | B11: TEST-SA-10(1) | D11: Test | E11: TEST-SA-10(1)
A12: Requirement ID | B12: SA-10(1) | D12: ID Exigence | E12: SA-10(1)
A13: Component | D13: Composant
A14: Requirement | D14: Exigence
A15: Contextual Design Description | D15: Description contextuelle du design
A16: Evidence Provided | D16: Preuve fournie
A17: Preparer Sign Off (Initials, Date) | D17: Signataire préparateur (Initiales, Date)
A18: Owner Sign Off (Initials, Date) | D18: Signataire propriétaire (Initiales, Date)
A19: Assessor Sign Off (Initials, Date) | D19: Signataire évaluateur (Initiales, Date)
A20: Status | B20: Not Started | D20: Statut | E20: Non commencé
A21: Comments | D21: Commentaires

Sheet SC-2
A1: Control SC-2 — Evidence Tracking | D1: Contrôle SC-2 — Suivi des preuves
A2: Control Information | D2: Informations du contrôle
A3: Control Identifier | B3: SC-2 | D3: Identifiant du contrôle | E3: SC-2
A4: Family | B4: Application Partitioning | D4: Famille | E4: Partitionnement des applications
A5: Profile | B5: CCCS Medium / PBMM Moderate | D5: Profil | E5: CCCS Moyen / PBMM Modéré
A6: Primary Evidence Tool | D6: Outil de preuve principal
A7: Contributing Tools | D7: Outils contributeurs
A8: Control Description | B8: (A) The information system separates user functionality (including user interface services) from information system management functionality. | D8: Description du contrôle | E8: (A) Le système d’information sépare la fonctionnalité de l’utilisateur (y compris les services d’interface utilisateur) de la fonctionnalité de gestion du système d’information.
A9: Supplemental Guidance | B9: Information system management functionality includes, for example, functions necessary to administer databases, network components, workstations, or servers, and typically requires privileged user access. The separation of user functionality from information system management functionality is either physical or logical. Organizations implement separation of system management-related functionality from user functionality by using different computers, different central processing units, different instances of operating systems, different network addresses, virtualization techniques, or combinations of these or other methods, as appropriate. This type of separation includes, for example, web administrative interfaces that use separate authentication methods (e.g., using a logical separation, web administrators would use 2-factor authentication and normal users of the web application would use username/password authentication). Separation of system and user functionality may include isolating administrative interfaces on different domains and with additional access controls. Related controls: SA-4, SA-8, SC-3 | D9: Directives supplémentaires | E9: La fonctionnalité de gestion du système d’information comprend, par exemple, les fonctions nécessaires à l’administration des bases de données, des composants de réseau, des postes de travail ou des serveurs, et exige habituellement un accès utilisateur privilégié. La séparation de la fonctionnalité de l’utilisateur de la fonctionnalité de gestion du système d’information est soit physique, soit logique. Les organisations mettent en œuvre la séparation de la fonctionnalité de gestion du système de la fonctionnalité de l’utilisateur en utilisant différents ordinateurs, différentes unités centrales de traitement, différentes instances de systèmes d’exploitation, différentes adresses réseau, des techniques de virtualisation ou des combinaisons de ces méthodes ou d’autres méthodes, selon le cas. Ce type de séparation comprend, par exemple, les interfaces administratives Web qui utilisent des méthodes d’authentification séparées (p. ex., en utilisant une séparation logique, les administrateurs Web utiliseraient l’authentification à deux facteurs et les utilisateurs habituels de l’application Web utiliseraient l’authentification par nom d’utilisateur/mot de passe). La séparation des fonctions du système et de l’utilisateur peut comprendre l’isolement des interfaces administratives dans différents domaines et avec des contrôles d’accès supplémentaires. Contrôles connexes : SA-4, SA-8, SC-3
A10: Test Case | D10: Cas de test
A11: Test | B11: TEST-SC-2 | D11: Test | E11: TEST-SC-2
A12: Requirement ID | B12: SC-2 | D12: ID Exigence | E12: SC-2
A13: Component | D13: Composant
A14: Requirement | D14: Exigence
A15: Contextual Design Description | D15: Description contextuelle du design
A16: Evidence Provided | D16: Preuve fournie
A17: Preparer Sign Off (Initials, Date) | D17: Signataire préparateur (Initiales, Date)
A18: Owner Sign Off (Initials, Date) | D18: Signataire propriétaire (Initiales, Date)
A19: Assessor Sign Off (Initials, Date) | D19: Signataire évaluateur (Initiales, Date)
A20: Status | B20: Not Started | D20: Statut | E20: Non commencé
A21: Comments | D21: Commentaires

Sheet SC-6
A1: Control SC-6 — Evidence Tracking | D1: Contrôle SC-6 — Suivi des preuves
A2: Control Information | D2: Informations du contrôle
A3: Control Identifier | B3: SC-6 | D3: Identifiant du contrôle | E3: SC-6
A4: Family | B4: Resource Availability | D4: Famille | E4: Disponibilité des ressources
A5: Profile | B5: CCCS Medium / PBMM Moderate | D5: Profil | E5: CCCS Moyen / PBMM Modéré
A6: Primary Evidence Tool | D6: Outil de preuve principal
A7: Contributing Tools | D7: Outils contributeurs
A8: Control Description | B8: (A) The information system protects the availability of resources by allocating organization-defined resources by priority; quota, or organization-defined security safeguards. | D8: Description du contrôle | E8: (A) Le système d’information préserve la disponibilité des ressources en répartissant les ressources définies par l’organisation en fonction de leur priorité, des quotas, ou des garanties de sécurité définies par l’organisation.
A9: Supplemental Guidance | B9: Priority protection helps prevent lower-priority processes from delaying or interfering with the information system servicing any higher-priority processes. Quotas prevent users or processes from obtaining more than predetermined amounts of resources. This control does not apply to information system components for which there are only single users/roles | D9: Directives supplémentaires | E9: La protection en fonction de la priorité aide à empêcher les processus moins prioritaires de retarder ou d’entraver la prise en charge des processus plus prioritaires par le système d’information. Les quotas empêchent les utilisateurs ou les processus d’obtenir plus de ressources que les quantités prédéterminées. Ce contrôle ne s’applique pas aux composants du système d’information pour lesquels il n’y a qu’un seul utilisateur/rôle.
A10: Test Case | D10: Cas de test
A11: Test | B11: TEST-SC-6 | D11: Test | E11: TEST-SC-6
A12: Requirement ID | B12: SC-6 | D12: ID Exigence | E12: SC-6
A13: Component | D13: Composant
A14: Requirement | D14: Exigence
A15: Contextual Design Description | D15: Description contextuelle du design
A16: Evidence Provided | D16: Preuve fournie
A17: Preparer Sign Off (Initials, Date) | D17: Signataire préparateur (Initiales, Date)
A18: Owner Sign Off (Initials, Date) | D18: Signataire propriétaire (Initiales, Date)
A19: Assessor Sign Off (Initials, Date) | D19: Signataire évaluateur (Initiales, Date)
A20: Status | B20: Not Started | D20: Statut | E20: Non commencé
A21: Comments | D21: Commentaires

Sheet SC-7-7
A1: Control SC-7(7) — Evidence Tracking | D1: Contrôle SC-7(7) — Suivi des preuves
A2: Control Information | D2: Informations du contrôle
A3: Control Identifier | B3: SC-7(7) | D3: Identifiant du contrôle | E3: SC-7(7)
A4: Family | B4: Boundary Protection | D4: Famille | E4: Protection des frontières
A5: Profile | B5: CCCS Medium / PBMM Moderate | D5: Profil | E5: CCCS Moyen / PBMM Modéré
A6: Primary Evidence Tool | D6: Outil de preuve principal
A7: Contributing Tools | D7: Outils contributeurs
A8: Control Description | B8: BOUNDARY PROTECTION | PREVENT SPLIT TUNNELLING FOR REMOTE DEVICES The information system, in conjunction with a remote device, prevents the device from simultaneously establishing non-remote connections with the system and communicating via some other connection to resources in external networks. | D8: Description du contrôle | E8: PROTECTION DES FRONTIÈRES | EMPÊCHER LA TUNNELLISATION À DOUBLE CIRCUIT POUR LES DISPOSITIFS DISTANTS Le système d’information, en conjonction avec un dispositif à distance, empêche le dispositif d’établir simultanément des connexions non distantes avec le système et de communiquer par une autre connexion à des ressources dans les réseaux externes.
A9: Supplemental Guidance | B9: This control enhancement is implemented within remote devices (e.g., notebook computers) through configuration settings to disable split tunnelling in those devices, and by preventing those configuration settings from being readily configurable by users. This control enhancement is implemented within the information system by the detection of split tunnelling (or of configuration settings that allow split tunnelling) in the remote device, and by prohibiting the connection if the remote device is using split tunnelling. Split tunnelling might be desirable by remote users to communicate with local information system resources such as printers/file servers. However, split tunnelling would in effect allow unauthorized external connections, making the system more vulnerable to attack and to exfiltration of organizational information. The use of VPNs for remote connections, when adequately provisioned with appropriate security controls, may provide the organization with sufficient assurance that it can effectively treat such connections as non-remote connections from the confidentiality and integrity perspective. VPNs thus provide a means for allowing non-remote communications paths from remote devices. The use of an adequately provisioned VPN does not eliminate the need for preventing split tunnelling. | D9: Directives supplémentaires | E9: Cette amélioration du contrôle est mise en œuvre dans les dispositifs distants (p. ex., les ordinateurs portatifs) au moyen des paramètres de configuration pour désactiver la tunnellisation à double effet de circuit dans ces dispositifs, et en empêchant que ces paramètres de configuration soient facilement configurables par les utilisateurs. Cette amélioration du contrôle est mise en œuvre dans le système d’information par la détection de la tunnellisation à double effet de circuit (ou des paramètres de configuration qui permettent la tunnellisation à double effet de circuit) dans le dispositif à distance, et par l’interdiction de la connexion si le dispositif distant utilise la tunnellisation à double effet de circuit. Les utilisateurs à distance pourraient souhaiter utiliser la tunnellisation à double effet de circuit pour communiquer avec les ressources du système d’information local, comme les imprimantes et les serveurs de fichiers. Toutefois, la tunnellisation à double effet de circuit permettrait en fait des connexions externes non autorisées, ce qui rendrait le système plus vulnérable aux attaques et à l’exfiltration d’information de l’organisation. L’utilisation de RPV pour les connexions à distance, lorsqu’ils sont dotés de contrôles de sécurité appropriés, peut donner à l’organisation l’assurance suffisante qu’elle peut traiter efficacement de telles connexions en tant que connexions distantes du point de vue de la confidentialité et de l’intégrité. Les RPV offrent donc un moyen de permettre des voies de communication locales à partir des dispositifs distants. L’utilisation d’un RPV adéquatement provisionné n’élimine pas la nécessité d’empêcher la tunnellisation à double effet de circuit.
A10: Test Case | D10: Cas de test
A11: Test | B11: TEST-SC-7(7) | D11: Test | E11: TEST-SC-7(7)
A12: Requirement ID | B12: SC-7(7) | D12: ID Exigence | E12: SC-7(7)
A13: Component | D13: Composant
A14: Requirement | D14: Exigence
A15: Contextual Design Description | D15: Description contextuelle du design
A16: Evidence Provided | D16: Preuve fournie
A17: Preparer Sign Off (Initials, Date) | D17: Signataire préparateur (Initiales, Date)
A18: Owner Sign Off (Initials, Date) | D18: Signataire propriétaire (Initiales, Date)
A19: Assessor Sign Off (Initials, Date) | D19: Signataire évaluateur (Initiales, Date)
A20: Status | B20: Not Started | D20: Statut | E20: Non commencé
A21: Comments | D21: Commentaires

Sheet SC-7-12
A1: Control SC-7(12) — Evidence Tracking | D1: Contrôle SC-7(12) — Suivi des preuves
A2: Control Information | D2: Informations du contrôle
A3: Control Identifier | B3: SC-7(12) | D3: Identifiant du contrôle | E3: SC-7(12)
A4: Family | B4: Boundary Protection | D4: Famille | E4: Protection des frontières
A5: Profile | B5: CCCS Medium / PBMM Moderate | D5: Profil | E5: CCCS Moyen / PBMM Modéré
A6: Primary Evidence Tool | D6: Outil de preuve principal
A7: Contributing Tools | D7: Outils contributeurs
A8: Control Description | B8: BOUNDARY PROTECTION | HOST-BASED PROTECTION The organization implements organization-defined host-based boundary protection mechanisms at organization-defined information system components. | D8: Description du contrôle | E8: PROTECTION DES FRONTIÈRES | PROTECTION BASÉE SUR L’HÔTE L’organisation met en œuvre des mécanismes de protection des frontières définis par l’organisation pour les composants de système d’information définis par l’organisation.
A9: Supplemental Guidance | B9: Host-based boundary protection mechanisms include, for example, host-based firewalls. Information system components employing host-based boundary protection mechanisms include, for example, servers, workstations, and mobile devices. | D9: Directives supplémentaires | E9: Les mécanismes de protection des frontières basée sur l’hôte comprennent, par exemple, des pare-feu basés sur l’hôte. Les composants du système d’information qui utilisent des mécanismes de protection des frontières basée sur l’hôte comprennent, par exemple, les serveurs, les postes de travail et les appareils mobiles.
A10: Test Case | D10: Cas de test
A11: Test | B11: TEST-SC-7(12) | D11: Test | E11: TEST-SC-7(12)
A12: Requirement ID | B12: SC-7(12) | D12: ID Exigence | E12: SC-7(12)
A13: Component | D13: Composant
A14: Requirement | D14: Exigence
A15: Contextual Design Description | D15: Description contextuelle du design
A16: Evidence Provided | D16: Preuve fournie
A17: Preparer Sign Off (Initials, Date) | D17: Signataire préparateur (Initiales, Date)
A18: Owner Sign Off (Initials, Date) | D18: Signataire propriétaire (Initiales, Date)
A19: Assessor Sign Off (Initials, Date) | D19: Signataire évaluateur (Initiales, Date)
A20: Status | B20: Not Started | D20: Statut | E20: Non commencé
A21: Comments | D21: Commentaires

Sheet SC-8
A1: Control SC-8 — Evidence Tracking | D1: Contrôle SC-8 — Suivi des preuves
A2: Control Information | D2: Informations du contrôle
A3: Control Identifier | B3: SC-8 | D3: Identifiant du contrôle | E3: SC-8
A4: Family | B4: Transmission Confidentiality and Integrity | D4: Famille | E4: Confidentialité et intégrité des transmissions
A5: Profile | B5: CCCS Medium / PBMM Moderate | D5: Profil | E5: CCCS Moyen / PBMM Modéré
A6: Primary Evidence Tool | D6: Outil de preuve principal
A7: Contributing Tools | D7: Outils contributeurs
A8: Control Description | B8: (A) The information system protects the confidentiality and integrity of transmitted information. | D8: Description du contrôle | E8: (A) Le système d’information protège la confidentialité et l’intégrité de l’information transmise.
A9: Supplemental Guidance | B9: This control applies to both internal and external networks and all types of information system components from which information can be transmitted (e.g., servers, mobile devices, notebook computers, printers, copiers, scanners, facsimile machines). Communication paths outside the physical protection of a controlled boundary are exposed to the possibility of interception and modification. Protecting the confidentiality and/or integrity of organizational information can be accomplished by physical means (e.g., by employing protected distribution systems) or by logical means (e.g., employing encryption techniques). Organizations relying on commercial providers offering transmission services as commodity services rather than as fully dedicated services (i.e., services which can be highly specialized to individual customer needs), may find it difficult to obtain the necessary assurances regarding the implementation of needed security controls for transmission confidentiality/integrity. In such situations, organizations determine what types of confidentiality/integrity services are available in standard, commercial telecommunication service packages. If it is infeasible or impractical to obtain the necessary security controls and assurances of control effectiveness through appropriate contracting vehicles, organizations implement appropriate compensating security controls or explicitly accept the additional risk. Related controls: AC-17, PE-4 | D9: Directives supplémentaires | E9: Ce contrôle s’applique aux réseaux internes et externes et à tous les types de composants du système d’information à partir desquels de l’information peut être transmise (p. ex., serveurs, appareils mobiles, ordinateurs portatifs, imprimantes, photocopieurs, numériseurs, télécopieurs). Les voies de communication à l’extérieur de la protection physique d’une frontière contrôlée sont exposées à des risques d’interception et de modification. La protection de la confidentialité ou de l’intégrité de l’information organisationnelle peut se faire par des moyens physiques (p. ex., en utilisant des systèmes de distribution protégés) ou logiques (p. ex., en utilisant des techniques de chiffrement). Les organisations qui comptent sur des fournisseurs commerciaux offrant des services de transmission à titre de services de base plutôt que de services entièrement dédiés (c.-à-d. des services qui peuvent être hautement spécialisés pour répondre aux besoins de clients individuels), peuvent avoir de la difficulté à obtenir les assurances nécessaires concernant la mise en œuvre des contrôles de sécurité nécessaires pour la confidentialité et l’intégrité des transmissions. Dans de telles situations, les organisations déterminent les types de services de confidentialité et d’intégrité disponibles dans les forfaits de services de télécommunications commerciaux standard. S’il n’est pas pratique ou s’il est impossible d’obtenir les contrôles de sécurité nécessaires et l’assurance de l’efficacité des contrôles au moyen des mécanismes de passation de marchés appropriés, les organisations mettent en œuvre des contrôles de sécurité compensatoires appropriés ou acceptent explicitement le risque supplémentaire. Contrôles connexes : AC-17, PE-4
A10: Test Case | D10: Cas de test
A11: Test | B11: TEST-SC-8 | D11: Test | E11: TEST-SC-8
A12: Requirement ID | B12: SC-8 | D12: ID Exigence | E12: SC-8
A13: Component | D13: Composant
A14: Requirement | D14: Exigence
A15: Contextual Design Description | D15: Description contextuelle du design
A16: Evidence Provided | D16: Preuve fournie
A17: Preparer Sign Off (Initials, Date) | D17: Signataire préparateur (Initiales, Date)
A18: Owner Sign Off (Initials, Date) | D18: Signataire propriétaire (Initiales, Date)
A19: Assessor Sign Off (Initials, Date) | D19: Signataire évaluateur (Initiales, Date)
A20: Status | B20: Not Started | D20: Statut | E20: Non commencé
A21: Comments | D21: Commentaires

Sheet SC-8-1
A1: Control SC-8(1) — Evidence Tracking | D1: Contrôle SC-8(1) — Suivi des preuves
A2: Control Information | D2: Informations du contrôle
A3: Control Identifier | B3: SC-8(1) | D3: Identifiant du contrôle | E3: SC-8(1)
A4: Family | B4: Transmission Confidentiality and Integrity | D4: Famille | E4: Confidentialité et intégrité des transmissions
A5: Profile | B5: CCCS Medium / PBMM Moderate | D5: Profil | E5: CCCS Moyen / PBMM Modéré
A6: Primary Evidence Tool | D6: Outil de preuve principal
A7: Contributing Tools | D7: Outils contributeurs
A8: Control Description | B8: TRANSMISSION CONFIDENTIALITY AND INTEGRITY | CRYPTOGRAPHIC OR ALTERNATE PHYSICAL PROTECTION The information system implements cryptographic mechanisms to prevent unauthorized disclosure of information and detect changes to information during transmission unless otherwise protected by physical security safeguards applied in applied in accordance with, or uses an adequate risk-based approach aligned with the practices specified in TBS and RCMP physical security standards and any related provisions of the Industrial Security Program. The cryptography must be compliant with the requirements of control SC-13. | D8: Description du contrôle | E8: CONFIDENTIALITÉ ET INTÉGRITÉ DES TRANSMISSIONS | PROTECTION CRYPTOGRAPHIQUE OU AUTRE PROTECTION PHYSIQUE Le système d’information déploie des mécanismes cryptographiques pour prévenir la divulgation non autorisée d’information et détecter les modifications de l’information durant la transmission, à moins d’être autrement protégé par des mesures de sécurité physiques appliquées selon une approche adéquate en fonction du risque qui s’harmonise avec les pratiques spécifiées dans les normes de sécurité physique du SCT et de la GRC et les dispositions connexes du Programme de sécurité industrielle. La cryptographie doit être conforme aux exigences du contrôle SC-13.
A9: Supplemental Guidance | B9: Encrypting information for transmission protects information from unauthorized disclosure and modification. Cryptographic mechanisms implemented to protect information integrity include, for example, cryptographic hash functions which have common application in digital signatures, checksums, and message authentication codes. Alternative physical security safeguards include, for example, protected distribution systems. Related control: SC-13. | D9: Directives supplémentaires | E9: Le chiffrement de l’information pour la transmission protège l’information contre la divulgation et la modification non autorisées. Les mécanismes cryptographiques mis en œuvre pour protéger l’intégrité de l’information comprennent, par exemple, les fonctions de hachage cryptographique qui ont une application commune dans les signatures numériques, les sommes de contrôle et les codes d’authentification des messages. Les autres mesures de sécurité physiques comprennent, par exemple, les réseaux de distribution protégés. Contrôle connexe : SC-13.
A10: Test Case | D10: Cas de test
A11: Test | B11: TEST-SC-8(1) | D11: Test | E11: TEST-SC-8(1)
A12: Requirement ID | B12: SC-8(1) | D12: ID Exigence | E12: SC-8(1)
A13: Component | D13: Composant
A14: Requirement | D14: Exigence
A15: Contextual Design Description | D15: Description contextuelle du design
A16: Evidence Provided | D16: Preuve fournie
A17: Preparer Sign Off (Initials, Date) | D17: Signataire préparateur (Initiales, Date)
A18: Owner Sign Off (Initials, Date) | D18: Signataire propriétaire (Initiales, Date)
A19: Assessor Sign Off (Initials, Date) | D19: Signataire évaluateur (Initiales, Date)
A20: Status | B20: Not Started | D20: Statut | E20: Non commencé
A21: Comments | D21: Commentaires

Sheet SC-10
A1: Control SC-10 — Evidence Tracking | D1: Contrôle SC-10 — Suivi des preuves
A2: Control Information | D2: Informations du contrôle
A3: Control Identifier | B3: SC-10 | D3: Identifiant du contrôle | E3: SC-10
A4: Family | B4: Network Disconnect | D4: Famille | E4: Débranchement du réseau
A5: Profile | B5: CCCS Medium / PBMM Moderate | D5: Profil | E5: CCCS Moyen / PBMM Modéré
A6: Primary Evidence Tool | D6: Outil de preuve principal
A7: Contributing Tools | D7: Outils contributeurs
A8: Control Description | B8: (A) The information system terminates the network connection associated with a communications session at the end of the session or after no longer than 30 minutes for RAS-based sessions or no longer than 60 minutes for non-interactive user sessions of inactivity. | D8: Description du contrôle | E8: (A) Le système d’information met fin à la connexion réseau associée à une session de communication à la fin de la séance ou après un maximum de 30 minutes pour les sessions basées sur le service d’accès à distance (SAD) ou de 60 minutes d’inactivité pour les sessions d’utilisateur non interactives.
A9: Supplemental Guidance | B9: This control applies to both internal and external networks. Terminating network connections associated with communications sessions include, for example, de-allocating associated TCP/IP address/port pairs at the operating system level, or de-allocating networking assignments at the application level if multiple application sessions are using a single, operating system-level network connection. Time periods of inactivity may be established by organizations and include, for example, time periods by type of network access or for specific network accesses | D9: Directives supplémentaires | E9: Ce contrôle s’applique aux réseaux internes et externes. La fin des connexions réseau associées aux sessions de communication comprend, par exemple, la désattribution des paires d’adresses/ports TCP/IP associées au niveau du système d’exploitation, ou la désattribution des tâches de réseautique au niveau de l’application si plusieurs sessions d’application utilisent une seule connexion réseau au niveau du système d’exploitation. Des périodes d’inactivité peuvent être établies par les organisations et comprendre, par exemple, des périodes par type d’accès au réseau ou pour des accès réseau particuliers.
A10: Test Case | D10: Cas de test
A11: Test | B11: TEST-SC-10 | D11: Test | E11: TEST-SC-10
A12: Requirement ID | B12: SC-10 | D12: ID Exigence | E12: SC-10
A13: Component | D13: Composant
A14: Requirement | D14: Exigence
A15: Contextual Design Description | D15: Description contextuelle du design
A16: Evidence Provided | D16: Preuve fournie
A17: Preparer Sign Off (Initials, Date) | D17: Signataire préparateur (Initiales, Date)
A18: Owner Sign Off (Initials, Date) | D18: Signataire propriétaire (Initiales, Date)
A19: Assessor Sign Off (Initials, Date) | D19: Signataire évaluateur (Initiales, Date)
A20: Status | B20: Not Started | D20: Statut | E20: Non commencé
A21: Comments | D21: Commentaires

Sheet SC-13
A1: Control SC-13 — Evidence Tracking | D1: Contrôle SC-13 — Suivi des preuves
A2: Control Information | D2: Informations du contrôle
A3: Control Identifier | B3: SC-13 | D3: Identifiant du contrôle | E3: SC-13
A4: Family | B4: Cryptographic Protection | D4: Famille | E4: Protection cryptographique
A5: Profile | B5: CCCS Medium / PBMM Moderate | D5: Profil | E5: CCCS Moyen / PBMM Modéré
A6: Primary Evidence Tool | D6: Outil de preuve principal
A7: Contributing Tools | D7: Outils contributeurs
A8: Control Description | B8: (A) The information system implements CSE approved cryptography in accordance with applicable organizational policies, directives and standards. | D8: Description du contrôle | E8: (A) Le système d’information met en œuvre la cryptographie approuvée par le CST conformément aux politiques, aux directives et aux normes organisationnelles applicables.
A9: Supplemental Guidance | B9: Cryptography can be employed to support a variety of security solutions including, for example, the protection of sensitive information, the provision of digital signatures, and the enforcement of information separation when authorized individuals have the necessary clearances for such information but lack the necessary formal access approvals. Cryptography can also be used to support random number generation and hash generation. Generally applicable cryptographic standards include FIPS-validated cryptography. This control does not impose any requirements on organizations to use cryptography. However, if cryptography is required based on the selection of other security controls or policies, organizations document each type of cryptographic use and the type of cryptography required (e.g., protection of classified information: FIPS-validated cryptography). Related controls: AC-2, AC-3, AC-7, AC-17, AC-18, AU-9, AU-10, CM-11, CP-9, IA-3, IA-7, MA-4, MP-2, MP-4, MP-5, SA-4, SC-8, SC-12, SC-28, SI-7 | D9: Directives supplémentaires | E9: La cryptographie peut être utilisée pour la prise en charge d’une variété de solutions de sécurité, y compris, par exemple, la protection des renseignements de nature sensible, la fourniture de signatures numériques, et l’application de la séparation des renseignements lorsque les personnes autorisées ont les autorisations de sécurité nécessaires pour ces renseignements, mais qu’elles n’ont pas les autorisations d’accès officielles nécessaires. La cryptographie peut également être utilisée pour permettre la génération de nombres aléatoires et la génération de hachages. Les normes cryptographiques généralement applicables comprennent la cryptographie conforme aux normes FIPS. Ce contrôle n’oblige pas les organisations à utiliser la cryptographie. Toutefois, si la cryptographie est requise en fonction de la sélection d’autres contrôles ou politiques de sécurité, les organisations documentent chaque type d’utilisation cryptographique et le type de cryptographie requis (p. ex., protection de l’information classifiée : cryptographie conforme aux normes FIPS). Contrôles connexes : AC-2, AC-3, AC-7, AC-17, AC-18, AU-9, AU-10, CM-11, CP-9, IA-3, IA-7, MA-4, MP-2, MP-4, MP-5, SA-4, SC-8, SC-12, SC-28, SI-7
A10: Test Case | D10: Cas de test
A11: Test | B11: TEST-SC-13 | D11: Test | E11: TEST-SC-13
A12: Requirement ID | B12: SC-13 | D12: ID Exigence | E12: SC-13
A13: Component | D13: Composant
A14: Requirement | D14: Exigence
A15: Contextual Design Description | D15: Description contextuelle du design
A16: Evidence Provided | D16: Preuve fournie
A17: Preparer Sign Off (Initials, Date) | D17: Signataire préparateur (Initiales, Date)
A18: Owner Sign Off (Initials, Date) | D18: Signataire propriétaire (Initiales, Date)
A19: Assessor Sign Off (Initials, Date) | D19: Signataire évaluateur (Initiales, Date)
A20: Status | B20: Not Started | D20: Statut | E20: Non commencé
A21: Comments | D21: Commentaires

Sheet SC-18
A1: Control SC-18 — Evidence Tracking | D1: Contrôle SC-18 — Suivi des preuves
A2: Control Information | D2: Informations du contrôle
A3: Control Identifier | B3: SC-18 | D3: Identifiant du contrôle | E3: SC-18
A4: Family | B4: Mobile Code | D4: Famille | E4: Code mobile
A5: Profile | B5: CCCS Medium / PBMM Moderate | D5: Profil | E5: CCCS Moyen / PBMM Modéré
A6: Primary Evidence Tool | D6: Outil de preuve principal
A7: Contributing Tools | D7: Outils contributeurs
A8: Control Description | B8: (A) The organization defines acceptable and unacceptable mobile code and mobile code technologies. (B) The organization establishes usage restrictions and implementation guidance for acceptable mobile code and mobile code technologies. (C) The organization authorizes, monitors, and controls the use of mobile code within the information system. | D8: Description du contrôle | E8: (A) L’organisation définit les codes mobiles et les technologies de codes mobiles acceptables et inacceptables. (B) L’organisation établit des restrictions d’utilisation et des directives de mise en œuvre pour le code mobile et les technologies de code mobile acceptables. (C) L’organisation autorise, surveille et contrôle l’utilisation du code mobile dans le système d’information.
A9: Supplemental Guidance | B9: Decisions regarding the employment of mobile code within organizational information systems are based on the potential for the code to cause damage to the systems if used maliciously. Mobile code technologies include, for example, Java, JavaScript, ActiveX, Postscript, PDF, Shockwave movies, Flash animations, and VBScript. Usage restrictions and implementation guidance apply to both the selection and use of mobile code installed on servers and mobile code downloaded and executed on individual workstations and devices (e.g., smart phones). Mobile code policy and procedures address preventing the development, acquisition, or introduction of unacceptable mobile code within organizational information systems. Related controls: AU-2, AU-12, CM-2, CM-6, SI-3 | D9: Directives supplémentaires | E9: Les décisions concernant l’utilisation du code mobile dans les systèmes d’information de l’organisation sont basées sur le potentiel de dommages causés aux systèmes si le code est utilisé de façon malveillante. Les technologies de code mobile comprennent, par exemple, Java, JavaScript, ActiveX, Postcript, PDF, les films Shockwave, les animations Flash et VBScript. Les restrictions d’utilisation et les directives de mise en œuvre s’appliquent à la fois à la sélection et à l’utilisation du code mobile installé sur les serveurs et du code mobile téléchargé et exécuté sur des postes de travail et des appareils individuels (p. ex., téléphones intelligents). La politique et les procédures relatives au code mobile visent à prévenir l’élaboration, l’acquisition ou l’introduction de code mobile inacceptable dans les systèmes d’information de l’organisation. Contrôles connexes : AU-2, AU-12, CM-2, CM-6, SI-3
A10: Test Case | D10: Cas de test
A11: Test | B11: TEST-SC-18 | D11: Test | E11: TEST-SC-18
A12: Requirement ID | B12: SC-18 | D12: ID Exigence | E12: SC-18
A13: Component | D13: Composant
A14: Requirement | D14: Exigence
A15: Contextual Design Description | D15: Description contextuelle du design
A16: Evidence Provided | D16: Preuve fournie
A17: Preparer Sign Off (Initials, Date) | D17: Signataire préparateur (Initiales, Date)
A18: Owner Sign Off (Initials, Date) | D18: Signataire propriétaire (Initiales, Date)
A19: Assessor Sign Off (Initials, Date) | D19: Signataire évaluateur (Initiales, Date)
A20: Status | B20: Not Started | D20: Statut | E20: Non commencé
A21: Comments | D21: Commentaires

Sheet SC-18-3
A1: Control SC-18(3) — Evidence Tracking | D1: Contrôle SC-18(3) — Suivi des preuves
A2: Control Information | D2: Informations du contrôle
A3: Control Identifier | B3: SC-18(3) | D3: Identifiant du contrôle | E3: SC-18(3)
A4: Family | B4: Mobile Code | D4: Famille | E4: Code mobile
A5: Profile | B5: CCCS Medium / PBMM Moderate | D5: Profil | E5: CCCS Moyen / PBMM Modéré
A6: Primary Evidence Tool | D6: Outil de preuve principal
A7: Contributing Tools | D7: Outils contributeurs
A8: Control Description | B8: MOBILE CODE | PREVENT DOWNLOADING / EXECUTION The information system prevents the download and execution of all unacceptable mobile code and mobile code technologies defined under SC-18. | D8: Description du contrôle | E8: CODE MOBILE | EMPÊCHER LE TÉLÉCHARGEMENT ET L’EXÉCUTION Le système d’information empêche le téléchargement et l’exécution de tout code mobile et de toute technologie de code mobile inacceptables définis dans SC-18.
A9: Supplemental Guidance | D9: Directives supplémentaires
A10: Test Case | D10: Cas de test
A11: Test | B11: TEST-SC-18(3) | D11: Test | E11: TEST-SC-18(3)
A12: Requirement ID | B12: SC-18(3) | D12: ID Exigence | E12: SC-18(3)
A13: Component | D13: Composant
A14: Requirement | D14: Exigence
A15: Contextual Design Description | D15: Description contextuelle du design
A16: Evidence Provided | D16: Preuve fournie
A17: Preparer Sign Off (Initials, Date) | D17: Signataire préparateur (Initiales, Date)
A18: Owner Sign Off (Initials, Date) | D18: Signataire propriétaire (Initiales, Date)
A19: Assessor Sign Off (Initials, Date) | D19: Signataire évaluateur (Initiales, Date)
A20: Status | B20: Not Started | D20: Statut | E20: Non commencé
A21: Comments | D21: Commentaires

Sheet SC-18-4
A1: Control SC-18(4) — Evidence Tracking | D1: Contrôle SC-18(4) — Suivi des preuves
A2: Control Information | D2: Informations du contrôle
A3: Control Identifier | B3: SC-18(4) | D3: Identifiant du contrôle | E3: SC-18(4)
A4: Family | B4: Mobile Code | D4: Famille | E4: Code mobile
A5: Profile | B5: CCCS Medium / PBMM Moderate | D5: Profil | E5: CCCS Moyen / PBMM Modéré
A6: Primary Evidence Tool | D6: Outil de preuve principal
A7: Contributing Tools | D7: Outils contributeurs
A8: Control Description | B8: MOBILE CODE | PREVENT AUTOMATIC EXECUTION The information system prevents the automatic execution of mobile code in software applications and such as but not limited to email, scriptable document/file editing applications that support documents with embedded code (e.g., MS Office applications/documents), etc. and prompts the user for permission. and enforces organization-defined actions prior to executing the code. | D8: Description du contrôle | E8: CODE MOBILE | PRÉVENIR L’EXÉCUTION AUTOMATIQUE Le système d’information empêche l’exécution automatique du code mobile dans les applications logicielles, par exemple, sans s’y limiter, le courriel, les applications de modification de documents ou de fichiers scriptibles qui prennent en charge les documents avec un code intégré (p. ex., applications/documents MS Office), etc., et demande l’autorisation de l’utilisateur, et applique les mesures définies par l’organisation avant d’exécuter le code.
A9: Supplemental Guidance | B9: Actions enforced before executing mobile code, include, for example, prompting users prior to opening electronic mail attachments. Preventing automatic execution of mobile code includes, for example, disabling auto execute features on information system components employing portable storage devices such as Compact Disks (CDs), Digital Video Disks (DVDs), and Universal Serial Bus (USB) devices. | D9: Directives supplémentaires | E9: Les mesures appliquées avant l’exécution du code mobile comprennent, par exemple, le fait d’inviter les utilisateurs à confirmer avant d’ouvrir les pièces jointes au courrier électronique. La prévention de l’exécution automatique du code mobile comprend, par exemple, la désactivation des fonctions d’exécution automatique sur les composants du système d’information utilisant des dispositifs de stockage portatifs comme les disques compacts (CD), les vidéodisques numériques (DVD) et les dispositifs de bus série universel (USB).
A10: Test Case | D10: Cas de test
A11: Test | B11: TEST-SC-18(4) | D11: Test | E11: TEST-SC-18(4)
A12: Requirement ID | B12: SC-18(4) | D12: ID Exigence | E12: SC-18(4)
A13: Component | D13: Composant
A14: Requirement | D14: Exigence
A15: Contextual Design Description | D15: Description contextuelle du design
A16: Evidence Provided | D16: Preuve fournie
A17: Preparer Sign Off (Initials, Date) | D17: Signataire préparateur (Initiales, Date)
A18: Owner Sign Off (Initials, Date) | D18: Signataire propriétaire (Initiales, Date)
A19: Assessor Sign Off (Initials, Date) | D19: Signataire évaluateur (Initiales, Date)
A20: Status | B20: Not Started | D20: Statut | E20: Non commencé
A21: Comments | D21: Commentaires

Sheet SC-23
A1: Control SC-23 — Evidence Tracking | D1: Contrôle SC-23 — Suivi des preuves
A2: Control Information | D2: Informations du contrôle
A3: Control Identifier | B3: SC-23 | D3: Identifiant du contrôle | E3: SC-23
A4: Family | B4: Session Authenticity | D4: Famille | E4: Authenticité des sessions
A5: Profile | B5: CCCS Medium / PBMM Moderate | D5: Profil | E5: CCCS Moyen / PBMM Modéré
A6: Primary Evidence Tool | D6: Outil de preuve principal
A7: Contributing Tools | D7: Outils contributeurs
A8: Control Description | B8: (A) The information system protects the authenticity of communications sessions. | D8: Description du contrôle | E8: (A) Le système d’information protège l’authenticité des sessions de communication.
A9: Supplemental Guidance | B9: This control addresses communications protection at the session, versus packet level (e.g., sessions in service-oriented architectures providing web-based services) and establishes grounds for confidence at both ends of communications sessions in ongoing identities of other parties and in the validity of information transmitted. Authenticity protection includes, for example, protecting against man-in-the-middle attacks/session hijacking and the insertion of false information into sessions. Related controls: SC-8, SC-10, SC-11 | D9: Directives supplémentaires | E9: Ce contrôle porte sur la protection des communications au niveau des sessions plutôt qu’au niveau des paquets (p. ex., les sessions dans les architectures orientées service fournissant des services Web) et établit des motifs de confiance, aux deux extrémités des sessions de communication, dans les identités continues des autres parties et dans la validité de l’information transmise. La protection de l’authenticité comprend, par exemple, la protection contre les attaques de l’intercepteur ou les détournements de sessions et l’insertion de faux renseignements dans les sessions. Contrôles connexes : SC-8, SC-10, SC-11
A10: Test Case | D10: Cas de test
A11: Test | B11: TEST-SC-23 | D11: Test | E11: TEST-SC-23
A12: Requirement ID | B12: SC-23 | D12: ID Exigence | E12: SC-23
A13: Component | D13: Composant
A14: Requirement | D14: Exigence
A15: Contextual Design Description | D15: Description contextuelle du design
A16: Evidence Provided | D16: Preuve fournie
A17: Preparer Sign Off (Initials, Date) | D17: Signataire préparateur (Initiales, Date)
A18: Owner Sign Off (Initials, Date) | D18: Signataire propriétaire (Initiales, Date)
A19: Assessor Sign Off (Initials, Date) | D19: Signataire évaluateur (Initiales, Date)
A20: Status | B20: Not Started | D20: Statut | E20: Non commencé
A21: Comments | D21: Commentaires

Sheet SC-23-1
A1: Control SC-23(1) — Evidence Tracking | D1: Contrôle SC-23(1) — Suivi des preuves
A2: Control Information | D2: Informations du contrôle
A3: Control Identifier | B3: SC-23(1) | D3: Identifiant du contrôle | E3: SC-23(1)
A4: Family | B4: Session Authenticity | D4: Famille | E4: Authenticité des sessions
A5: Profile | B5: CCCS Medium / PBMM Moderate | D5: Profil | E5: CCCS Moyen / PBMM Modéré
A6: Primary Evidence Tool | D6: Outil de preuve principal
A7: Contributing Tools | D7: Outils contributeurs
A8: Control Description | B8: SESSION AUTHENTICITY | INVALIDATE SESSION IDENTIFIERS AT LOGOUT The information system invalidates session identifiers upon user logout or other session termination. | D8: Description du contrôle | E8: AUTHENTICITÉ DES SESSIONS | INVALIDATION DES IDENTIFIANTS DE SESSION DÈS LA FERMETURE DE SESSION Le système d’information invalide les identifiants de session dès la fermeture de session par l’utilisateur ou à toute autre fin de session.
A9: Supplemental Guidance | B9: This control enhancement curtails the ability of adversaries from capturing and continuing to employ previously valid session IDs. | D9: Directives supplémentaires | E9: Cette amélioration du contrôle empêche les adversaires de saisir et de continuer d’utiliser des ID de session valides.
A10: Test Case | D10: Cas de test
A11: Test | B11: TEST-SC-23(1) | D11: Test | E11: TEST-SC-23(1)
A12: Requirement ID | B12: SC-23(1) | D12: ID Exigence | E12: SC-23(1)
A13: Component | D13: Composant
A14: Requirement | D14: Exigence
A15: Contextual Design Description | D15: Description contextuelle du design
A16: Evidence Provided | D16: Preuve fournie
A17: Preparer Sign Off (Initials, Date) | D17: Signataire préparateur (Initiales, Date)
A18: Owner Sign Off (Initials, Date) | D18: Signataire propriétaire (Initiales, Date)
A19: Assessor Sign Off (Initials, Date) | D19: Signataire évaluateur (Initiales, Date)
A20: Status | B20: Not Started | D20: Statut | E20: Non commencé
A21: Comments | D21: Commentaires

Sheet SC-28
A1: Control SC-28 — Evidence Tracking | D1: Contrôle SC-28 — Suivi des preuves
A2: Control Information | D2: Informations du contrôle
A3: Control Identifier | B3: SC-28 | D3: Identifiant du contrôle | E3: SC-28
A4: Family | B4: Protection of Information At Rest | D4: Famille | E4: Protection de l’information inactive
A5: Profile | B5: CCCS Medium / PBMM Moderate | D5: Profil | E5: CCCS Moyen / PBMM Modéré
A6: Primary Evidence Tool | D6: Outil de preuve principal
A7: Contributing Tools | D7: Outils contributeurs
A8: Control Description | B8: (A) The information system protects the confidentiality and integrity of all information not cleared for public release and all data with a higher than low integrity requirement. | D8: Description du contrôle | E8: (A) Le système d’information protège la confidentialité et l’intégrité de tous les renseignements dont la diffusion publique n’est pas autorisée et de toutes les données pour lesquelles les exigences d’intégrité ne sont pas faibles.
A9: Supplemental Guidance | B9: This control addresses the confidentiality and integrity of information at rest and covers user information and system information. Information at rest refers to the state of information when it is located on storage devices as specific components of information systems. System-related information requiring protection includes, for example, configurations or rule sets for firewalls, gateways, intrusion detection/prevention systems, filtering routers, and authenticator content. Organizations may employ different mechanisms to achieve confidentiality and integrity protections, including the use of cryptographic mechanisms and file share scanning. Integrity protection can be achieved, for example, by implementing Write-Once-Read-Many (WORM) technologies. Organizations may also employ other security controls including, for example, secure off-line storage in lieu of online storage when adequate protection of information at rest cannot otherwise be achieved and/or continuous monitoring to identify malicious code at rest. Related controls: AC-3, AC-6, CA-7, CM-3, CM-5, CM-6, PE-3, SC-8, SC-13, SI-3, SI-7 | D9: Directives supplémentaires | E9: Ce contrôle porte sur la confidentialité et l’intégrité de l’information inactive et couvre l’information sur les utilisateurs et le système. L’information inactive fait référence à l’état de l’information lorsqu’elle se trouve sur des dispositifs de stockage en tant que composants particuliers des systèmes d’information. Les renseignements relatifs au système qui nécessitent une protection comprennent, par exemple, les configurations ou les ensembles de règles pour les pare-feu, les passerelles, les systèmes de détection et de prévention des intrusions, les routeurs de filtrage et le contenu des authentifiants. Les organisations peuvent utiliser différents mécanismes pour assurer la protection de la confidentialité et de l’intégrité, y compris les mécanismes cryptographiques et le balayage des fichiers partagés. La protection de l’intégrité peut être assurée, par exemple, en mettant en œuvre des technologies qui rendent les supports non réinscriptibles. Les organisations peuvent également utiliser d’autres contrôles de sécurité, y compris, par exemple, le stockage hors ligne sécurisé au lieu du stockage en ligne lorsque la protection de l’information inactive ne peut être assurée autrement, ou la surveillance continue pour repérer du code malveillant inactif. Contrôles connexes : AC-3, AC-6, CA-7, CM-3, CM-5, CM-6, PE-3, SC-8, SC-13, SI-3, SI-7
A10: Test Case | D10: Cas de test
A11: Test | B11: TEST-SC-28 | D11: Test | E11: TEST-SC-28
A12: Requirement ID | B12: SC-28 | D12: ID Exigence | E12: SC-28
A13: Component | D13: Composant
A14: Requirement | D14: Exigence
A15: Contextual Design Description | D15: Description contextuelle du design
A16: Evidence Provided | D16: Preuve fournie
A17: Preparer Sign Off (Initials, Date) | D17: Signataire préparateur (Initiales, Date)
A18: Owner Sign Off (Initials, Date) | D18: Signataire propriétaire (Initiales, Date)
A19: Assessor Sign Off (Initials, Date) | D19: Signataire évaluateur (Initiales, Date)
A20: Status | B20: Not Started | D20: Statut | E20: Non commencé
A21: Comments | D21: Commentaires

Sheet SC-28-1
A1: Control SC-28(1) — Evidence Tracking | D1: Contrôle SC-28(1) — Suivi des preuves
A2: Control Information | D2: Informations du contrôle
A3: Control Identifier | B3: SC-28(1) | D3: Identifiant du contrôle | E3: SC-28(1)
A4: Family | B4: Protection of Information At Rest | D4: Famille | E4: Protection de l’information inactive
A5: Profile | B5: CCCS Medium / PBMM Moderate | D5: Profil | E5: CCCS Moyen / PBMM Modéré
A6: Primary Evidence Tool | D6: Outil de preuve principal
A7: Contributing Tools | D7: Outils contributeurs
A8: Control Description | B8: PROTECTION OF INFORMATION AT REST | CRYPTOGRAPHIC PROTECTION The information system implements cryptographic mechanisms to prevent unauthorized disclosure and modification of all information not cleared for public release and all data with a higher than low integrity requirements. | D8: Description du contrôle | E8: PROTECTION DE L’INFORMATION INACTIVE | PROTECTION CRYPTOGRAPHIQUE Le système d’information met en œuvre des mécanismes cryptographiques pour prévenir la divulgation et la modification non autorisées de tous les renseignements dont la diffusion publique n’est pas autorisée et de toutes les données pour lesquelles les exigences d’intégrité ne sont pas faibles.
A9: Supplemental Guidance | B9: Selection of cryptographic mechanisms is based on the need to protect the confidentiality and integrity of organizational information. The strength of mechanism is commensurate with the security category and/or classification of the information. This control enhancement applies to significant concentrations of digital media in organizational areas designated for media storage and also to limited quantities of media generally associated with information system components in operational environments (e.g., portable storage devices, mobile devices). Organizations have the flexibility to either encrypt all information on storage devices (i.e., full disk encryption) or encrypt specific data structures (e.g., files, records, or fields). Organizations employing cryptographic mechanisms to protect information at rest also consider cryptographic key management solutions. Related controls: AC-19, SC-12. | D9: Directives supplémentaires | E9: Le choix des mécanismes cryptographiques est fonction du besoin de protection de la confidentialité et de l’intégrité de l’information de l’organisation. La force du mécanisme est proportionnelle à la catégorie de sécurité ou à la classification de l’information. Cette amélioration du contrôle s’applique aux concentrations importantes de supports numériques dans les zones de l’organisation qui sont désignées pour le stockage des supports, et également aux quantités limitées de supports généralement associés aux composants de systèmes d’information dans les environnements opérationnels (p. ex., dispositifs de stockage portatifs, appareils mobiles). Les organisations ont la possibilité de chiffrer toute l’information sur les dispositifs de stockage (c.-à-d. le chiffrement complet du disque) ou de chiffrer des structures de données particulières (p. ex., fichiers, enregistrements ou champs). Les organisations qui utilisent des mécanismes cryptographiques pour protéger l’information inactive envisagent également des solutions de gestion des clés cryptographiques. Contrôles connexes : AC-19, SC-12.
A10: Test Case | D10: Cas de test
A11: Test | B11: TEST-SC-28(1) | D11: Test | E11: TEST-SC-28(1)
A12: Requirement ID | B12: SC-28(1) | D12: ID Exigence | E12: SC-28(1)
A13: Component | D13: Composant
A14: Requirement | D14: Exigence
A15: Contextual Design Description | D15: Description contextuelle du design
A16: Evidence Provided | D16: Preuve fournie
A17: Preparer Sign Off (Initials, Date) | D17: Signataire préparateur (Initiales, Date)
A18: Owner Sign Off (Initials, Date) | D18: Signataire propriétaire (Initiales, Date)
A19: Assessor Sign Off (Initials, Date) | D19: Signataire évaluateur (Initiales, Date)
A20: Status | B20: Not Started | D20: Statut | E20: Non commencé
A21: Comments | D21: Commentaires

Sheet SC-39
A1: Control SC-39 — Evidence Tracking | D1: Contrôle SC-39 — Suivi des preuves
A2: Control Information | D2: Informations du contrôle
A3: Control Identifier | B3: SC-39 | D3: Identifiant du contrôle | E3: SC-39
A4: Family | B4: Process Isolation | D4: Famille | E4: Isolement des processus
A5: Profile | B5: CCCS Medium / PBMM Moderate | D5: Profil | E5: CCCS Moyen / PBMM Modéré
A6: Primary Evidence Tool | D6: Outil de preuve principal
A7: Contributing Tools | D7: Outils contributeurs
A8: Control Description | B8: (A) The information system maintains a separate execution domain for each executing process. | D8: Description du contrôle | E8: (A) Le système d’information maintient un domaine d’exécution séparé pour chaque processus d’exécution.
A9: Supplemental Guidance | B9: Information systems can maintain separate execution domains for each executing process by assigning each process a separate address space. Each information system process has a distinct address space so that communication between processes is performed in a manner controlled through the security functions, and one process cannot modify the executing code of another process. Maintaining separate execution domains for executing processes can be achieved, for example, by implementing separate address spaces. This capability is available in most commercial operating systems that employ multi-state processor technologies. Related controls: AC-3, AC-4, AC-6, SA-4, SA-5, SA-8, SC-2, SC-3 | D9: Directives supplémentaires | E9: Les systèmes d’information peuvent maintenir des domaines d’exécution séparés pour chaque processus d’exécution en attribuant à chaque processus un espace d’adresse séparé. Chaque processus du système d’information a un espace d’adresse distinct, de sorte que la communication entre les processus est effectuée d’une manière contrôlée par les fonctions de sécurité, et qu’un processus ne peut pas modifier le code d’exécution d’un autre processus. Le maintien de domaines d’exécution séparés pour l’exécution des processus peut être réalisé, par exemple, en mettant en œuvre des espaces d’adresse séparés. Cette capacité est disponible dans la plupart des systèmes d’exploitation commerciaux qui utilisent des technologies de processeurs multi-états. Contrôles connexes : AC-3, AC-4, AC-6, SA-4, SA-5, SA-8, SC-2, SC-3
A10: Test Case | D10: Cas de test
A11: Test | B11: TEST-SC-39 | D11: Test | E11: TEST-SC-39
A12: Requirement ID | B12: SC-39 | D12: ID Exigence | E12: SC-39
A13: Component | D13: Composant
A14: Requirement | D14: Exigence
A15: Contextual Design Description | D15: Description contextuelle du design
A16: Evidence Provided | D16: Preuve fournie
A17: Preparer Sign Off (Initials, Date) | D17: Signataire préparateur (Initiales, Date)
A18: Owner Sign Off (Initials, Date) | D18: Signataire propriétaire (Initiales, Date)
A19: Assessor Sign Off (Initials, Date) | D19: Signataire évaluateur (Initiales, Date)
A20: Status | B20: Not Started | D20: Statut | E20: Non commencé
A21: Comments | D21: Commentaires

Sheet SI-4-2
A1: Control SI-4(2) — Evidence Tracking | D1: Contrôle SI-4(2) — Suivi des preuves
A2: Control Information | D2: Informations du contrôle
A3: Control Identifier | B3: SI-4(2) | D3: Identifiant du contrôle | E3: SI-4(2)
A4: Family | B4: Information System Monitoring | D4: Famille | E4: Surveillance du système d’information
A5: Profile | B5: CCCS Medium / PBMM Moderate | D5: Profil | E5: CCCS Moyen / PBMM Modéré
A6: Primary Evidence Tool | D6: Outil de preuve principal
A7: Contributing Tools | D7: Outils contributeurs
A8: Control Description | B8: INFORMATION SYSTEM MONITORING | AUTOMATED TOOLS FOR REAL-TIME ANALYSIS The organization employs automated tools to support near real-time analysis of events. | D8: Description du contrôle | E8: SURVEILLANCE DU SYSTÈME D’INFORMATION | OUTILS AUTOMATISÉS POUR L’ANALYSE EN TEMPS RÉEL L’organisation utilise des outils automatisés pour appuyer l’analyse des événements en temps quasi réel.
A9: Supplemental Guidance | B9: Automated tools include, for example, host-based, network-based, transport-based, or storage-based event monitoring tools or Security Information and Event Management (SIEM) technologies that provide real time analysis of alerts and/or notifications generated by organizational information systems. | D9: Directives supplémentaires | E9: Les outils automatisés comprennent, par exemple, des outils de surveillance des événements basés sur l’hôte, le réseau, le transport ou le stockage, ou des technologies de gestion de l’information et des événements de sécurité (SIEM) qui fournissent une analyse en temps réel des alertes et/ou des notifications générées par les systèmes d’information de l’organisation.
A10: Test Case | D10: Cas de test
A11: Test | B11: TEST-SI-4(2) | D11: Test | E11: TEST-SI-4(2)
A12: Requirement ID | B12: SI-4(2) | D12: ID Exigence | E12: SI-4(2)
A13: Component | D13: Composant
A14: Requirement | D14: Exigence
A15: Contextual Design Description | D15: Description contextuelle du design
A16: Evidence Provided | D16: Preuve fournie
A17: Preparer Sign Off (Initials, Date) | D17: Signataire préparateur (Initiales, Date)
A18: Owner Sign Off (Initials, Date) | D18: Signataire propriétaire (Initiales, Date)
A19: Assessor Sign Off (Initials, Date) | D19: Signataire évaluateur (Initiales, Date)
A20: Status | B20: Not Started | D20: Statut | E20: Non commencé
A21: Comments | D21: Commentaires

Sheet SI-4-4
A1: Control SI-4(4) — Evidence Tracking | D1: Contrôle SI-4(4) — Suivi des preuves
A2: Control Information | D2: Informations du contrôle
A3: Control Identifier | B3: SI-4(4) | D3: Identifiant du contrôle | E3: SI-4(4)
A4: Family | B4: Information System Monitoring | D4: Famille | E4: Surveillance du système d’information
A5: Profile | B5: CCCS Medium / PBMM Moderate | D5: Profil | E5: CCCS Moyen / PBMM Modéré
A6: Primary Evidence Tool | D6: Outil de preuve principal
A7: Contributing Tools | D7: Outils contributeurs
A8: Control Description | B8: INFORMATION SYSTEM MONITORING | INBOUND AND OUTBOUND COMMUNICATIONS TRAFFIC The information system monitors inbound and outbound communications traffic continously for unusual or unauthorized activities or conditions. | D8: Description du contrôle | E8: SURVEILLANCE DU SYSTÈME D’INFORMATION | COMMUNICATIONS ENTRANTES ET SORTANTES Le système d’information surveille les communications entrantes et sortantes de façon continue pour détecter les activités ou les conditions inhabituelles ou non autorisées.
