Workbook

Sheet DASHBOARD
A1: DASHBOARD — PBMM Evidence: DevOps
A2: Control ID | B2: Control Name | C2: Primary Tool | D2: Tab | E2: Status
A3: AC-2(4) | B3: Account Management | D3: AC-2-4 | E3: ='AC-2-4'!B20 -> Not Started
A4: AC-2(5) | B4: Account Management | D4: AC-2-5 | E4: ='AC-2-5'!B20 -> Not Started
A5: AC-2(7) | B5: Account Management | D5: AC-2-7 | E5: ='AC-2-7'!B20 -> Not Started
A6: AC-6 | B6: Least Privilege | D6: AC-6 | E6: ='AC-6'!B20 -> Not Started
A7: AC-6(1) | B7: Least Privilege | D7: AC-6-1 | E7: ='AC-6-1'!B20 -> Not Started
A8: AC-6(9) | B8: Least Privilege | D8: AC-6-9 | E8: ='AC-6-9'!B20 -> Not Started
A9: AC-17(1) | B9: Remote Access | D9: AC-17-1 | E9: ='AC-17-1'!B20 -> Not Started
A10: AU-2 | B10: Auditable Events | D10: AU-2 | E10: ='AU-2'!B20 -> Not Started
A11: AU-3 | B11: Content of Audit Records | D11: AU-3 | E11: ='AU-3'!B20 -> Not Started
A12: AU-3(1) | B12: Content of Audit Records | D12: AU-3-1 | E12: ='AU-3-1'!B20 -> Not Started
A13: AU-5 | B13: Response To Audit Processing Failures | D13: AU-5 | E13: ='AU-5'!B20 -> Not Started
A14: AU-6(1) | B14: Audit Review, Analysis, and Reporting | D14: AU-6-1 | E14: ='AU-6-1'!B20 -> Not Started
A15: AU-6(3) | B15: Audit Review, Analysis, and Reporting | D15: AU-6-3 | E15: ='AU-6-3'!B20 -> Not Started
A16: AU-7 | B16: Audit Reduction and Report Generation | D16: AU-7 | E16: ='AU-7'!B20 -> Not Started
A17: AU-7(1) | B17: Audit Reduction and Report Generation | D17: AU-7-1 | E17: ='AU-7-1'!B20 -> Not Started
A18: AU-8 | B18: Time Stamps | D18: AU-8 | E18: ='AU-8'!B20 -> Not Started
A19: AU-8(1) | B19: Time Stamps | D19: AU-8-1 | E19: ='AU-8-1'!B20 -> Not Started
A20: AU-9 | B20: Protection of Audit Information | D20: AU-9 | E20: ='AU-9'!B20 -> Not Started
A21: AU-9(2) | B21: Protection of Audit Information | D21: AU-9-2 | E21: ='AU-9-2'!B20 -> Not Started
A22: AU-9(4) | B22: Protection of Audit Information | D22: AU-9-4 | E22: ='AU-9-4'!B20 -> Not Started
A23: AU-11 | B23: Audit Record Retention | D23: AU-11 | E23: ='AU-11'!B20 -> Not Started
A24: AU-12 | B24: Audit Generation | D24: AU-12 | E24: ='AU-12'!B20 -> Not Started
A25: CM-3 | B25: Configuration Change Control | D25: CM-3 | E25: ='CM-3'!B20 -> Not Started
A26: CM-5(1) | B26: Access Restrictions for Change | D26: CM-5-1 | E26: ='CM-5-1'!B20 -> Not Started
A27: CM-5(6) | B27: Access Restrictions for Change | D27: CM-5-6 | E27: ='CM-5-6'!B20 -> Not Started
A28: CM-6 | B28: Configuration Settings | D28: CM-6 | E28: ='CM-6'!B20 -> Not Started
A29: CM-7 | B29: Least Functionality | D29: CM-7 | E29: ='CM-7'!B20 -> Not Started
A30: CM-7(1) | B30: Least Functionality | D30: CM-7-1 | E30: ='CM-7-1'!B20 -> Not Started
A31: CP-10 | B31: Information System Recovery and Reconstitution | D31: CP-10 | E31: ='CP-10'!B20 -> Not Started
A32: CP-10(4) | B32: Information System Recovery and Reconstitution | D32: CP-10-4 | E32: ='CP-10-4'!B20 -> Not Started
A33: IA-5(7) | B33: Authenticator Management | D33: IA-5-7 | E33: ='IA-5-7'!B20 -> Not Started
A34: MA-4 | B34: Non-Local Maintenance | D34: MA-4 | E34: ='MA-4'!B20 -> Not Started
A35: MA-4(1) | B35: Non-Local Maintenance | D35: MA-4-1 | E35: ='MA-4-1'!B20 -> Not Started
A36: SA-9(5) | B36: External Information System Services | D36: SA-9-5 | E36: ='SA-9-5'!B20 -> Not Started
A37: SA-11(1) | B37: Developer Security Testing | D37: SA-11-1 | E37: ='SA-11-1'!B20 -> Not Started
A38: SA-11(8) | B38: Developer Security Testing | D38: SA-11-8 | E38: ='SA-11-8'!B20 -> Not Started
A39: SC-7 | B39: Boundary Protection | D39: SC-7 | E39: ='SC-7'!B20 -> Not Started
A40: SC-18 | B40: Mobile Code | D40: SC-18 | E40: ='SC-18'!B20 -> Not Started
A41: SI-4 | B41: Information System Monitoring | D41: SI-4 | E41: ='SI-4'!B20 -> Not Started
A42: SI-4(1) | B42: Information System Monitoring | D42: SI-4-1 | E42: ='SI-4-1'!B20 -> Not Started
A43: SI-4(2) | B43: Information System Monitoring | D43: SI-4-2 | E43: ='SI-4-2'!B20 -> Not Started
A44: SI-4(4) | B44: Information System Monitoring | D44: SI-4-4 | E44: ='SI-4-4'!B20 -> Not Started
A45: SI-4(5) | B45: Information System Monitoring | D45: SI-4-5 | E45: ='SI-4-5'!B20 -> Not Started
A46: SI-4(11) | B46: Information System Monitoring | D46: SI-4-11 | E46: ='SI-4-11'!B20 -> Not Started
A47: SI-6 | B47: Security Functional Verification | D47: SI-6 | E47: ='SI-6'!B20 -> Not Started
A48: SI-7(7) | B48: Software, Firmware, and Information Integrity | D48: SI-7-7 | E48: ='SI-7-7'!B20 -> Not Started
A49: SI-11 | B49: Error Handling | D49: SI-11 | E49: ='SI-11'!B20 -> Not Started
A51: Completion Metrics
A52: Total Controls | E52: =47 -> 47
A53: Not Started | E53: =COUNTIF(E3:E49,"Not Started") -> 47
A54: In Progress | E54: =COUNTIF(E3:E49,"In Progress") -> 0
A55: Evidence Provided | E55: =COUNTIF(E3:E49,"Evidence Provided") -> 0
A56: Under Review | E56: =COUNTIF(E3:E49,"Under Review") -> 0
A57: Passed | E57: =COUNTIF(E3:E49,"Passed") -> 0
A58: Failed | E58: =COUNTIF(E3:E49,"Failed") -> 0
A59: Accepted Exception | E59: =COUNTIF(E3:E49,"Accepted Exception") -> 0
A60: % Complete | E60: =IFERROR(COUNTIF(E3:E49,"Passed")/47,0) -> 0
A61: % Not Started | E61: =IFERROR(COUNTIF(E3:E49,"Not Started")/47,0) -> 1

Sheet TABLEAU_DE_BORD
A1: TABLEAU DE BORD — Suivi PBMM : DevOps
A2: ID Contrôle | B2: Nom du contrôle | C2: Outil principal | D2: Onglet | E2: Statut
A3: AC-2(4) | B3: Gestion des comptes | D3: AC-2-4 | E3: ='AC-2-4'!E20 -> Non commencé
A4: AC-2(5) | B4: Gestion des comptes | D4: AC-2-5 | E4: ='AC-2-5'!E20 -> Non commencé
A5: AC-2(7) | B5: Gestion des comptes | D5: AC-2-7 | E5: ='AC-2-7'!E20 -> Non commencé
A6: AC-6 | B6: Moindre privilège | D6: AC-6 | E6: ='AC-6'!E20 -> Non commencé
A7: AC-6(1) | B7: Moindre privilège | D7: AC-6-1 | E7: ='AC-6-1'!E20 -> Non commencé
A8: AC-6(9) | B8: Moindre privilège | D8: AC-6-9 | E8: ='AC-6-9'!E20 -> Non commencé
A9: AC-17(1) | B9: Accès à distance | D9: AC-17-1 | E9: ='AC-17-1'!E20 -> Non commencé
A10: AU-2 | B10: Événements vérifiables | D10: AU-2 | E10: ='AU-2'!E20 -> Non commencé
A11: AU-3 | B11: Contenu des enregistrements de vérification | D11: AU-3 | E11: ='AU-3'!E20 -> Non commencé
A12: AU-3(1) | B12: Contenu des enregistrements de vérification | D12: AU-3-1 | E12: ='AU-3-1'!E20 -> Non commencé
A13: AU-5 | B13: Réponse aux échecs de traitement de vérification | D13: AU-5 | E13: ='AU-5'!E20 -> Non commencé
A14: AU-6(1) | B14: Examen, analyse et rapport de vérification | D14: AU-6-1 | E14: ='AU-6-1'!E20 -> Non commencé
A15: AU-6(3) | B15: Examen, analyse et rapport de vérification | D15: AU-6-3 | E15: ='AU-6-3'!E20 -> Non commencé
A16: AU-7 | B16: Réduction des vérifications et production de rapports | D16: AU-7 | E16: ='AU-7'!E20 -> Non commencé
A17: AU-7(1) | B17: Réduction des vérifications et production de rapports | D17: AU-7-1 | E17: ='AU-7-1'!E20 -> Non commencé
A18: AU-8 | B18: Estampilles temporelles | D18: AU-8 | E18: ='AU-8'!E20 -> Non commencé
A19: AU-8(1) | B19: Estampilles temporelles | D19: AU-8-1 | E19: ='AU-8-1'!E20 -> Non commencé
A20: AU-9 | B20: Protection des renseignements de vérification | D20: AU-9 | E20: ='AU-9'!E20 -> Non commencé
A21: AU-9(2) | B21: Protection des renseignements de vérification | D21: AU-9-2 | E21: ='AU-9-2'!E20 -> Non commencé
A22: AU-9(4) | B22: Protection des renseignements de vérification | D22: AU-9-4 | E22: ='AU-9-4'!E20 -> Non commencé
A23: AU-11 | B23: Conservation des enregistrements de vérification | D23: AU-11 | E23: ='AU-11'!E20 -> Non commencé
A24: AU-12 | B24: Génération des vérifications | D24: AU-12 | E24: ='AU-12'!E20 -> Non commencé
A25: CM-3 | B25: Contrôle des changements de configuration | D25: CM-3 | E25: ='CM-3'!E20 -> Non commencé
A26: CM-5(1) | B26: Restrictions d’accès pour les changements | D26: CM-5-1 | E26: ='CM-5-1'!E20 -> Non commencé
A27: CM-5(6) | B27: Restrictions d’accès pour les changements | D27: CM-5-6 | E27: ='CM-5-6'!E20 -> Non commencé
A28: CM-6 | B28: Paramètres de configuration | D28: CM-6 | E28: ='CM-6'!E20 -> Non commencé
A29: CM-7 | B29: Moindre fonctionnalité | D29: CM-7 | E29: ='CM-7'!E20 -> Non commencé
A30: CM-7(1) | B30: Moindre fonctionnalité | D30: CM-7-1 | E30: ='CM-7-1'!E20 -> Non commencé
A31: CP-10 | B31: Reprise et reconstitution du système d’information | D31: CP-10 | E31: ='CP-10'!E20 -> Non commencé
A32: CP-10(4) | B32: Reprise et reconstitution du système d’information | D32: CP-10-4 | E32: ='CP-10-4'!E20 -> Non commencé
A33: IA-5(7) | B33: Gestion des authentifiants | D33: IA-5-7 | E33: ='IA-5-7'!E20 -> Non commencé
A34: MA-4 | B34: Maintenance non locale | D34: MA-4 | E34: ='MA-4'!E20 -> Non commencé
A35: MA-4(1) | B35: Maintenance non locale | D35: MA-4-1 | E35: ='MA-4-1'!E20 -> Non commencé
A36: SA-9(5) | B36: Services de systèmes d’information externes | D36: SA-9-5 | E36: ='SA-9-5'!E20 -> Non commencé
A37: SA-11(1) | B37: Essais de sécurité du développeur | D37: SA-11-1 | E37: ='SA-11-1'!E20 -> Non commencé
A38: SA-11(8) | B38: Essais de sécurité du développeur | D38: SA-11-8 | E38: ='SA-11-8'!E20 -> Non commencé
A39: SC-7 | B39: Protection des frontières | D39: SC-7 | E39: ='SC-7'!E20 -> Non commencé
A40: SC-18 | B40: Code mobile | D40: SC-18 | E40: ='SC-18'!E20 -> Non commencé
A41: SI-4 | B41: Surveillance du système d’information | D41: SI-4 | E41: ='SI-4'!E20 -> Non commencé
A42: SI-4(1) | B42: Surveillance du système d’information | D42: SI-4-1 | E42: ='SI-4-1'!E20 -> Non commencé
A43: SI-4(2) | B43: Surveillance du système d’information | D43: SI-4-2 | E43: ='SI-4-2'!E20 -> Non commencé
A44: SI-4(4) | B44: Surveillance du système d’information | D44: SI-4-4 | E44: ='SI-4-4'!E20 -> Non commencé
A45: SI-4(5) | B45: Surveillance du système d’information | D45: SI-4-5 | E45: ='SI-4-5'!E20 -> Non commencé
A46: SI-4(11) | B46: Surveillance du système d’information | D46: SI-4-11 | E46: ='SI-4-11'!E20 -> Non commencé
A47: SI-6 | B47: Vérification fonctionnelle de la sécurité | D47: SI-6 | E47: ='SI-6'!E20 -> Non commencé
A48: SI-7(7) | B48: Logiciels, micrologiciels et intégrité de l’information | D48: SI-7-7 | E48: ='SI-7-7'!E20 -> Non commencé
A49: SI-11 | B49: Traitement des erreurs | D49: SI-11 | E49: ='SI-11'!E20 -> Non commencé
A51: Métriques de complétude
A52: Nombre total de contrôles | E52: =47 -> 47
A53: Non commencés | E53: =COUNTIF(E3:E49,"Non commencé") -> 47
A54: En cours | E54: =COUNTIF(E3:E49,"En cours") -> 0
A55: Preuve fournie | E55: =COUNTIF(E3:E49,"Preuve fournie") -> 0
A56: En révision | E56: =COUNTIF(E3:E49,"En révision") -> 0
A57: Réussi | E57: =COUNTIF(E3:E49,"Réussi") -> 0
A58: Échec | E58: =COUNTIF(E3:E49,"Échec") -> 0
A59: Exception acceptée | E59: =COUNTIF(E3:E49,"Exception acceptée") -> 0
A60: % Complété | E60: =IFERROR(COUNTIF(E3:E49,"Réussi")/47,0) -> 0
A61: % Non commencés | E61: =IFERROR(COUNTIF(E3:E49,"Non commencé")/47,0) -> 1

Sheet AC-2-4
A1: Control AC-2(4) — Evidence Tracking | D1: Contrôle AC-2(4) — Suivi des preuves
A2: Control Information | D2: Informations du contrôle
A3: Control Identifier | B3: AC-2(4) | D3: Identifiant du contrôle | E3: AC-2(4)
A4: Family | B4: Account Management | D4: Famille | E4: Gestion des comptes
A5: Profile | B5: CCCS Medium / PBMM Moderate | D5: Profil | E5: CCCS Moyen / PBMM Modéré
A6: Primary Evidence Tool | D6: Outil de preuve principal
A7: Contributing Tools | D7: Outils contributeurs
A8: Control Description | B8: ACCOUNT MANAGEMENT | AUTOMATED AUDIT ACTIONS The information system automatically audits account creation, modification, enabling, disabling, and removal actions, and notifies responsible managers. Related controls: AU-2, AU-12. | D8: Description du contrôle | E8: GESTION DES COMPTES | MESURES DE VÉRIFICATION AUTOMATISÉES Le système d’information vérifie automatiquement les opérations de création, de modification, d’activation, de désactivation et de retrait des comptes, et avise les gestionnaires responsables. Contrôles connexes : AU-2, AU-12.
A9: Supplemental Guidance | D9: Directives supplémentaires
A10: Test Case | D10: Cas de test
A11: Test | B11: TEST-AC-2(4) | D11: Test | E11: TEST-AC-2(4)
A12: Requirement ID | B12: AC-2(4) | D12: ID Exigence | E12: AC-2(4)
A13: Component | D13: Composant
A14: Requirement | D14: Exigence
A15: Contextual Design Description | D15: Description contextuelle du design
A16: Evidence Provided | D16: Preuve fournie
A17: Preparer Sign Off (Initials, Date) | D17: Signataire préparateur (Initiales, Date)
A18: Owner Sign Off (Initials, Date) | D18: Signataire propriétaire (Initiales, Date)
A19: Assessor Sign Off (Initials, Date) | D19: Signataire évaluateur (Initiales, Date)
A20: Status | B20: Not Started | D20: Statut | E20: Non commencé
A21: Comments | D21: Commentaires

Sheet AC-2-5
A1: Control AC-2(5) — Evidence Tracking | D1: Contrôle AC-2(5) — Suivi des preuves
A2: Control Information | D2: Informations du contrôle
A3: Control Identifier | B3: AC-2(5) | D3: Identifiant du contrôle | E3: AC-2(5)
A4: Family | B4: Account Management | D4: Famille | E4: Gestion des comptes
A5: Profile | B5: CCCS Medium / PBMM Moderate | D5: Profil | E5: CCCS Moyen / PBMM Modéré
A6: Primary Evidence Tool | D6: Outil de preuve principal
A7: Contributing Tools | D7: Outils contributeurs
A8: Control Description | B8: ACCOUNT MANAGEMENT | INACTIVITY LOGOUT The organization requires that users log out at the end of the users’ standard work period unless otherwise defined in formal organizational policy. Related controls: SC-23 | D8: Description du contrôle | E8: GESTION DES COMPTES | FERMETURE DE SESSION INACTIVE L’organisation exige que les utilisateurs ferment leur session à la fin de leur période de travail normale, à moins d’indication contraire dans la politique officielle de l’organisation. Contrôles connexes : SC-23
A9: Supplemental Guidance | D9: Directives supplémentaires
A10: Test Case | D10: Cas de test
A11: Test | B11: TEST-AC-2(5) | D11: Test | E11: TEST-AC-2(5)
A12: Requirement ID | B12: AC-2(5) | D12: ID Exigence | E12: AC-2(5)
A13: Component | D13: Composant
A14: Requirement | D14: Exigence
A15: Contextual Design Description | D15: Description contextuelle du design
A16: Evidence Provided | D16: Preuve fournie
A17: Preparer Sign Off (Initials, Date) | D17: Signataire préparateur (Initiales, Date)
A18: Owner Sign Off (Initials, Date) | D18: Signataire propriétaire (Initiales, Date)
A19: Assessor Sign Off (Initials, Date) | D19: Signataire évaluateur (Initiales, Date)
A20: Status | B20: Not Started | D20: Statut | E20: Non commencé
A21: Comments | D21: Commentaires

Sheet AC-2-7
A1: Control AC-2(7) — Evidence Tracking | D1: Contrôle AC-2(7) — Suivi des preuves
A2: Control Information | D2: Informations du contrôle
A3: Control Identifier | B3: AC-2(7) | D3: Identifiant du contrôle | E3: AC-2(7)
A4: Family | B4: Account Management | D4: Famille | E4: Gestion des comptes
A5: Profile | B5: CCCS Medium / PBMM Moderate | D5: Profil | E5: CCCS Moyen / PBMM Modéré
A6: Primary Evidence Tool | D6: Outil de preuve principal
A7: Contributing Tools | D7: Outils contributeurs
A8: Control Description | B8: ACCOUNT MANAGEMENT | ROLE-BASED SCHEMES (a) The organization establishes and administers privileged user accounts in accordance with a role-based access scheme that organizes allowed information system access and privileges into roles; (b) The organization monitors privileged role assignments; and (c) The organization disables (or revokes) privileged user assignments within 24 hours or sooner when privileged role assignments are no longer appropriate. | D8: Description du contrôle | E8: GESTION DES COMPTES | SCHÉMAS FONDÉS SUR LES RÔLES (a) L’organisation établit et administre les comptes d’utilisateurs privilégiés conformément à un système d’accès basé sur les rôles qui organise les autorisations d’accès au système d’information et les privilèges en fonction des rôles; (b) L’organisation surveille les affectations de rôles privilégiés; (c) L’organisation désactive (ou révoque) les affectations d’utilisateurs privilégiés dans les 24 heures ou plus lorsque les affectations de rôles privilégiés ne sont plus appropriées.
A9: Supplemental Guidance | B9: Privileged roles are organization-defined roles assigned to individuals that allow those individuals to perform certain security-relevant functions that ordinary users are not authorized to perform. These privileged roles include, for example, key management, account management, network and system administration, database administration, and web administration. | D9: Directives supplémentaires | E9: Les rôles privilégiés sont des rôles définis par l’organisation et attribués à des personnes pour leur permettre d’exécuter certaines fonctions ayant une influence sur la sécurité que les utilisateurs ordinaires ne sont pas autorisés à exécuter. Ces rôles privilégiés comprennent, par exemple, la gestion des clés, la gestion des comptes, l’administration des réseaux et des systèmes, l’administration des bases de données et l’administration Web.
A10: Test Case | D10: Cas de test
A11: Test | B11: TEST-AC-2(7) | D11: Test | E11: TEST-AC-2(7)
A12: Requirement ID | B12: AC-2(7) | D12: ID Exigence | E12: AC-2(7)
A13: Component | D13: Composant
A14: Requirement | D14: Exigence
A15: Contextual Design Description | D15: Description contextuelle du design
A16: Evidence Provided | D16: Preuve fournie
A17: Preparer Sign Off (Initials, Date) | D17: Signataire préparateur (Initiales, Date)
A18: Owner Sign Off (Initials, Date) | D18: Signataire propriétaire (Initiales, Date)
A19: Assessor Sign Off (Initials, Date) | D19: Signataire évaluateur (Initiales, Date)
A20: Status | B20: Not Started | D20: Statut | E20: Non commencé
A21: Comments | D21: Commentaires

Sheet AC-6
A1: Control AC-6 — Evidence Tracking | D1: Contrôle AC-6 — Suivi des preuves
A2: Control Information | D2: Informations du contrôle
A3: Control Identifier | B3: AC-6 | D3: Identifiant du contrôle | E3: AC-6
A4: Family | B4: Least Privilege | D4: Famille | E4: Moindre privilège
A5: Profile | B5: CCCS Medium / PBMM Moderate | D5: Profil | E5: CCCS Moyen / PBMM Modéré
A6: Primary Evidence Tool | D6: Outil de preuve principal
A7: Contributing Tools | D7: Outils contributeurs
A8: Control Description | B8: (A) The organization employs the principle of least privilege, allowing only authorized accesses for users (or processes acting on behalf of users) which are necessary to accomplish assigned tasks in accordance with organizational missions and business functions. | D8: Description du contrôle | E8: (A) L’organisation utilise le principe du moindre privilège, qui permet seulement les accès autorisés aux utilisateurs (ou aux processus qui agissent pour le compte des utilisateurs) qui sont nécessaires pour accomplir les tâches assignées conformément aux missions et aux fonctions opérationnelles de l’organisation.
A9: Supplemental Guidance | B9: Organizations employ least privilege for specific duties and information systems. The principle of least privilege is also applied to information system processes, ensuring that the processes operate at privilege levels no higher than necessary to accomplish required organizational missions/business functions. Organizations consider the creation of additional processes, roles, and information system accounts as necessary, to achieve least privilege. Organizations also apply least privilege to the development, implementation, and operation of organizational information systems. Related controls: AC-2, AC-3, AC-5, CM-6, CM-7, PL-2 | D9: Directives supplémentaires | E9: Les organisations utilisent le moindre privilège pour certaines tâches et certains systèmes d’information. Le principe du moindre privilège s’applique également aux processus du système d’information, ce qui fait en sorte que les processus ne fonctionnent pas à des niveaux de privilège plus élevés que nécessaire pour accomplir les missions et les fonctions opérationnelles requises de l’organisation. Les organisations envisagent la création de processus, de rôles et de comptes de système d’information supplémentaires lorsque nécessaire, pour obtenir le moindre privilège. Les organisations appliquent également le moindre privilège au développement, à la mise en œuvre et à l’exploitation de leurs systèmes d’information. Contrôles connexes : AC-2, AC-3, AC-5, CM-6, CM-7, PL-2
A10: Test Case | D10: Cas de test
A11: Test | B11: TEST-AC-6 | D11: Test | E11: TEST-AC-6
A12: Requirement ID | B12: AC-6 | D12: ID Exigence | E12: AC-6
A13: Component | D13: Composant
A14: Requirement | D14: Exigence
A15: Contextual Design Description | D15: Description contextuelle du design
A16: Evidence Provided | D16: Preuve fournie
A17: Preparer Sign Off (Initials, Date) | D17: Signataire préparateur (Initiales, Date)
A18: Owner Sign Off (Initials, Date) | D18: Signataire propriétaire (Initiales, Date)
A19: Assessor Sign Off (Initials, Date) | D19: Signataire évaluateur (Initiales, Date)
A20: Status | B20: Not Started | D20: Statut | E20: Non commencé
A21: Comments | D21: Commentaires

Sheet AC-6-1
A1: Control AC-6(1) — Evidence Tracking | D1: Contrôle AC-6(1) — Suivi des preuves
A2: Control Information | D2: Informations du contrôle
A3: Control Identifier | B3: AC-6(1) | D3: Identifiant du contrôle | E3: AC-6(1)
A4: Family | B4: Least Privilege | D4: Famille | E4: Moindre privilège
A5: Profile | B5: CCCS Medium / PBMM Moderate | D5: Profil | E5: CCCS Moyen / PBMM Modéré
A6: Primary Evidence Tool | D6: Outil de preuve principal
A7: Contributing Tools | D7: Outils contributeurs
A8: Control Description | B8: LEAST PRIVILEGE | AUTHORIZE ACCESS TO SECURITY FUNCTIONS The organization explicitly authorizes access to all security functions not publicly accessible and all security-relevant information not publicly available. | D8: Description du contrôle | E8: MOINDRE PRIVILÈGE | AUTORISATION D’ACCÈS AUX FONCTIONS DE SÉCURITÉ L’organisation autorise explicitement l’accès à toutes les fonctions de sécurité qui ne sont pas accessibles au public et à toute l’information pertinente à la sécurité qui n’est pas accessible au public.
A9: Supplemental Guidance | B9: Security functions include, for example, establishing system accounts, configuring access authorizations (i.e., permissions, privileges), setting events to be audited, and setting intrusion detection parameters. Security-relevant information includes, for example, filtering rules for routers/firewalls, cryptographic key management information, configuration parameters for security services, and access control lists. Explicitly authorized personnel include, for example, security administrators, system and network administrators, system security officers, system maintenance personnel, system programmers, and other privileged users. Related controls: AC-17, AC-18, AC-19. | D9: Directives supplémentaires | E9: Les fonctions de sécurité comprennent, par exemple, l’établissement des comptes système, la configuration des autorisations d’accès (c.-à-d. les permissions, les privilèges), le réglage des événements à vérifier, et l’établissement des paramètres de détection des intrusions. Les renseignements pertinents pour la sécurité comprennent, par exemple, les règles de filtrage pour les routeurs/pare-feu, l’information de gestion des clés cryptographiques, les paramètres de configuration pour les services de sécurité et les listes de contrôle d’accès. Le personnel explicitement autorisé comprend, par exemple, les administrateurs de la sécurité, les administrateurs de systèmes et de réseaux, les agents de sécurité des systèmes, le personnel de maintenance des systèmes, les programmeurs de systèmes et d’autres utilisateurs privilégiés. Contrôles connexes : AC-17, AC-18, AC-19.
A10: Test Case | D10: Cas de test
A11: Test | B11: TEST-AC-6(1) | D11: Test | E11: TEST-AC-6(1)
A12: Requirement ID | B12: AC-6(1) | D12: ID Exigence | E12: AC-6(1)
A13: Component | D13: Composant
A14: Requirement | D14: Exigence
A15: Contextual Design Description | D15: Description contextuelle du design
A16: Evidence Provided | D16: Preuve fournie
A17: Preparer Sign Off (Initials, Date) | D17: Signataire préparateur (Initiales, Date)
A18: Owner Sign Off (Initials, Date) | D18: Signataire propriétaire (Initiales, Date)
A19: Assessor Sign Off (Initials, Date) | D19: Signataire évaluateur (Initiales, Date)
A20: Status | B20: Not Started | D20: Statut | E20: Non commencé
A21: Comments | D21: Commentaires

Sheet AC-6-9
A1: Control AC-6(9) — Evidence Tracking | D1: Contrôle AC-6(9) — Suivi des preuves
A2: Control Information | D2: Informations du contrôle
A3: Control Identifier | B3: AC-6(9) | D3: Identifiant du contrôle | E3: AC-6(9)
A4: Family | B4: Least Privilege | D4: Famille | E4: Moindre privilège
A5: Profile | B5: CCCS Medium / PBMM Moderate | D5: Profil | E5: CCCS Moyen / PBMM Modéré
A6: Primary Evidence Tool | D6: Outil de preuve principal
A7: Contributing Tools | D7: Outils contributeurs
A8: Control Description | B8: LEAST PRIVILEGE | AUDITING USE OF PRIVILEGED FUNCTIONS The information system audits the execution of privileged functions. | D8: Description du contrôle | E8: MOINDRE PRIVILÈGE | VÉRIFICATION DE L’UTILISATION DES FONCTIONS PRIVILÉGIÉES Le système d’information vérifie l’exécution des fonctions privilégiées.
A9: Supplemental Guidance | B9: Misuse of privileged functions, either intentionally or unintentionally by authorized users, or by unauthorized external entities that have compromised information system accounts, is a serious and ongoing concern and can have significant adverse impacts on organizations. Auditing the use of privileged functions is one way to detect such misuse, and in doing so, help mitigate the risk from insider threats and the advanced persistent threat (APT). Related control: AU-2. | D9: Directives supplémentaires | E9: L’utilisation abusive des fonctions privilégiées, intentionnellement ou non, par des utilisateurs autorisés ou par des entités externes non autorisées qui ont compromis des comptes de système d’information, est une préoccupation grave et constante qui peut avoir des répercussions négatives importantes sur les organisations. La vérification de l’utilisation des fonctions privilégiées est une façon de détecter un tel abus et, ce faisant, de contribuer à atténuer le risque de menaces internes et de menaces persistantes avancées (MPA). Contrôle connexe : AU-2.
A10: Test Case | D10: Cas de test
A11: Test | B11: TEST-AC-6(9) | D11: Test | E11: TEST-AC-6(9)
A12: Requirement ID | B12: AC-6(9) | D12: ID Exigence | E12: AC-6(9)
A13: Component | D13: Composant
A14: Requirement | D14: Exigence
A15: Contextual Design Description | D15: Description contextuelle du design
A16: Evidence Provided | D16: Preuve fournie
A17: Preparer Sign Off (Initials, Date) | D17: Signataire préparateur (Initiales, Date)
A18: Owner Sign Off (Initials, Date) | D18: Signataire propriétaire (Initiales, Date)
A19: Assessor Sign Off (Initials, Date) | D19: Signataire évaluateur (Initiales, Date)
A20: Status | B20: Not Started | D20: Statut | E20: Non commencé
A21: Comments | D21: Commentaires

Sheet AC-17-1
A1: Control AC-17(1) — Evidence Tracking | D1: Contrôle AC-17(1) — Suivi des preuves
A2: Control Information | D2: Informations du contrôle
A3: Control Identifier | B3: AC-17(1) | D3: Identifiant du contrôle | E3: AC-17(1)
A4: Family | B4: Remote Access | D4: Famille | E4: Accès à distance
A5: Profile | B5: CCCS Medium / PBMM Moderate | D5: Profil | E5: CCCS Moyen / PBMM Modéré
A6: Primary Evidence Tool | D6: Outil de preuve principal
A7: Contributing Tools | D7: Outils contributeurs
A8: Control Description | B8: REMOTE ACCESS | AUTOMATED MONITORING / CONTROL The information system monitors and controls remote access methods. | D8: Description du contrôle | E8: ACCÈS À DISTANCE | SURVEILLANCE ET CONTRÔLE AUTOMATISÉS Le système d’information surveille et contrôle les méthodes d’accès à distance.
A9: Supplemental Guidance | B9: Automated monitoring and control of remote access sessions allows organizations to detect cyber-attacks and also ensure ongoing compliance with remote access policies by auditing connection activities of remote users on a variety of information system components (e.g., servers, workstations, notebook computers, smart phones, and tablets). Related controls: AU-2, AU-12. | D9: Directives supplémentaires | E9: La surveillance et le contrôle automatisés des sessions avec accès à distance permettent aux organisations de détecter les cyberattaques et d’assurer la conformité continue aux politiques d’accès à distance en vérifiant les activités de connexion des utilisateurs distants sur une variété de composants du système d’information (p. ex., serveurs, postes de travail, ordinateurs portatifs, téléphones intelligents et tablettes). Contrôles connexes : AU-2, AU-12.
A10: Test Case | D10: Cas de test
A11: Test | B11: TEST-AC-17(1) | D11: Test | E11: TEST-AC-17(1)
A12: Requirement ID | B12: AC-17(1) | D12: ID Exigence | E12: AC-17(1)
A13: Component | D13: Composant
A14: Requirement | D14: Exigence
A15: Contextual Design Description | D15: Description contextuelle du design
A16: Evidence Provided | D16: Preuve fournie
A17: Preparer Sign Off (Initials, Date) | D17: Signataire préparateur (Initiales, Date)
A18: Owner Sign Off (Initials, Date) | D18: Signataire propriétaire (Initiales, Date)
A19: Assessor Sign Off (Initials, Date) | D19: Signataire évaluateur (Initiales, Date)
A20: Status | B20: Not Started | D20: Statut | E20: Non commencé
A21: Comments | D21: Commentaires

Sheet AU-2
A1: Control AU-2 — Evidence Tracking | D1: Contrôle AU-2 — Suivi des preuves
A2: Control Information | D2: Informations du contrôle
A3: Control Identifier | B3: AU-2 | D3: Identifiant du contrôle | E3: AU-2
A4: Family | B4: Auditable Events | D4: Famille | E4: Événements vérifiables
A5: Profile | B5: CCCS Medium / PBMM Moderate | D5: Profil | E5: CCCS Moyen / PBMM Modéré
A6: Primary Evidence Tool | D6: Outil de preuve principal
A7: Contributing Tools | D7: Outils contributeurs
A8: Control Description | B8: (A) The organization determines that the information system is capable of auditing the following events: Successful and unsuccessful account logon events, account management events, object access, policy change, privilege functions, process tracking, and system events. For Web applications: all administrator activity, authentication checks, authorization checks, data deletions, data access, data changes, and permission changes. (B) The organization coordinates the security audit function with other organizational entities requiring audit-related information to enhance mutual support and to help guide the selection of auditable events. (C) The organization provides a rationale for why the auditable events are deemed to be adequate to support after-the-fact investigations of security incidents. (D) The organization determines what organizationally-defined audited events (a subset of the auditable events defined in AU-2 a.) and the frequency of (or situation requiring) auditing for each identified event. | D8: Description du contrôle | E8: (A) L’organisation détermine que le système d’information est capable de vérifier les événements suivants : événements d’ouverture de compte, réussis ou non, événements de gestion de compte, accès aux objets, changement de politique, fonctions de privilèges, suivi des processus et événements du système. Pour les applications Web : toutes les activités des administrateurs, les vérifications d’authentification, les vérifications d’autorisation, les suppressions de données, l’accès aux données, les changements de données et les changements d’autorisation. (B) L’organisation coordonne la fonction de vérification de la sécurité avec d’autres entités organisationnelles qui ont besoin de renseignements liés à la vérification pour améliorer le soutien mutuel et aider à orienter le choix des événements vérifiables. (C) L’organisation explique la raison pour laquelle les événements vérifiables sont jugés adéquats pour appuyer les enquêtes effectuées à la suite des incidents de sécurité. (D) L’organisation détermine les événements définis par l’organisation qui sont vérifiés (un sous-ensemble des événements vérifiables définis dans AU-2 a.) et la fréquence (ou la situation exigeant) des vérifications pour chaque événement identifié.
A9: Supplemental Guidance | B9: An event is any observable occurrence in an organizational information system. Organizations identify audit events as those events which are significant and relevant to the security of information systems and the environments in which those systems operate in order to meet specific and ongoing audit needs. Audit events can include, for example, password changes, failed logons, or failed accesses related to information systems, administrative privilege usage, or third-party credential usage. In determining the set of auditable events, organizations consider the auditing appropriate for each of the security controls to be implemented. To balance auditing requirements with other information system needs, this control also requires identifying that subset of auditable events that are audited at a given point in time. For example, organizations may determine that information systems must have the capability to log every file access both successful and unsuccessful, but not activate that capability except for specific circumstances due to the potential burden on system performance. Auditing requirements, including the need for auditable events, may be referenced in other security controls and control enhancements. Organizations also include auditable events that are required by applicable organizational policies, directives, and standards. Audit records can be generated at various levels of abstraction, including at the packet level as information traverses the network. Selecting the appropriate level of abstraction is a critical aspect of an audit capability and can facilitate the identification of root causes to problems. Organizations consider in the definition of auditable events, the auditing necessary to cover related events such as the steps in distributed, transaction-based processes (e.g., processes that are distributed across multiple organizations) and actions that occur in service-oriented architectures. The information system audits the following privileged user/process events at a minimum: (a) Successful and unsuccessful attempts to access, modify, or delete security objects (Security objects include audit data, system configuration files and file or users’ formal access permissions.) (b) Successful and unsuccessful logon attempts (c) Privileged activities or other system level access (see notes for AU-2 (4)) (d) Starting and ending time for user access to the system (e) Concurrent logons from different workstations (f) All program initiations (see notes for AU-2 (4)) In addition, the information system audits the following unprivileged user/process events at a minimum: (a) Successful and unsuccessful attempts to access, modify, or delete security objects (b) Successful and unsuccessful logon attempts (c) Starting and ending time for user access to the system (d) Concurrent logons from different workstations Related controls: AC-6, AC-17, AU-3, AU-12, MA-4, MP-2, MP-4, SI-4 | D9: Directives supplémentaires | E9: Un événement est toute occurrence observable dans un système d’information organisationnel. Les organisations désignent les événements vérifiables comme étant des événements importants et pertinents pour la sécurité des systèmes d’information et des environnements dans lesquels ces systèmes sont utilisés afin de répondre à des exigences de vérification particulières et continues. Les événements vérifiés peuvent comprendre, par exemple, les changements de mot de passe, les échecs d’ouverture de session ou les échecs accès liés aux systèmes d’information, l’utilisation des privilèges administratifs ou l’utilisation de justificatifs d’identité par des tiers. Lorsqu’elles déterminent l’ensemble des événements vérifiables, les organisations considèrent que la vérification est appropriée pour chacun des contrôles de sécurité à mettre en œuvre. Pour assurer l’équilibre entre les exigences en matière de vérification et les autres besoins du système d’information, ce contrôle exige également de déterminer le sous-ensemble d’événements vérifiables qui sont vérifiés à un moment donné. Par exemple, les organisations peuvent déterminer que les systèmes d’information doivent avoir la capacité d’enregistrer chaque accès aux fichiers, qu’il soit réussi ou non, mais n’activeront cette capacité que dans des circonstances particulières en raison du fardeau potentiel sur le rendement du système. Les exigences en matière de vérification, y compris la nécessité de déterminer des événements vérifiables, peuvent être mentionnées dans d’autres contrôles et améliorations des contrôles de sécurité. Les organisations incluent également les événements vérifiables qui sont exigés par les politiques, les directives et les normes organisationnelles applicables. Les enregistrements de vérification peuvent être générés à divers niveaux d’abstraction, y compris au niveau des paquets, à mesure que l’information traverse le réseau. Le choix du niveau d’abstraction approprié est un aspect essentiel d’une capacité de vérification et peut faciliter l’identification des causes profondes des problèmes. Dans la définition des événements vérifiables, les organisations prennent en compte la vérification nécessaire pour couvrir les événements connexes, comme les étapes des processus distribués, fondés sur les transactions (p. ex., les processus qui sont répartis entre de multiples organisations) et les actions qui ont lieu dans les architectures orientées service. Le système d’information vérifie au minimum les événements suivants liés aux utilisateurs/processus privilégiés : (a) Tentatives réussies et infructueuses d’accéder aux objets de sécurité, de les modifier ou de les supprimer (les objets de sécurité comprennent les données de vérification, les fichiers de configuration de système et les autorisations d’accès officielles des utilisateurs). (b) Tentatives d’ouverture de session réussies et infructueuses (c) Activités privilégiées ou autre accès au niveau du système (voir les notes pour AU-2 [4]) (d) Heures de début et de fin de l’accès des utilisateurs au système (e) Ouvertures de session simultanées à partir de différents postes de travail (f) Tous les lancements de programmes (voir les notes pour AU-2 [4]) De plus, le système d’information vérifie au minimum les événements suivants liés aux utilisateurs/processus non privilégiés : (a) Tentatives réussies et infructueuses d’accès, de modification ou de suppression d’objets de sécurité (b) Tentatives d’ouverture de session réussies et infructueuses (c) Heures de début et de fin de l’accès de l’utilisateur au système (d) Ouvertures de session simultanées à partir de différents postes de travail Contrôles connexes : AC-6, AC-17, AU-3, AU-12, MA-4, MP-2, MP-4, SI-4
A10: Test Case | D10: Cas de test
A11: Test | B11: TEST-AU-2 | D11: Test | E11: TEST-AU-2
A12: Requirement ID | B12: AU-2 | D12: ID Exigence | E12: AU-2
A13: Component | D13: Composant
A14: Requirement | D14: Exigence
A15: Contextual Design Description | D15: Description contextuelle du design
A16: Evidence Provided | D16: Preuve fournie
A17: Preparer Sign Off (Initials, Date) | D17: Signataire préparateur (Initiales, Date)
A18: Owner Sign Off (Initials, Date) | D18: Signataire propriétaire (Initiales, Date)
A19: Assessor Sign Off (Initials, Date) | D19: Signataire évaluateur (Initiales, Date)
A20: Status | B20: Not Started | D20: Statut | E20: Non commencé
A21: Comments | D21: Commentaires

Sheet AU-3
A1: Control AU-3 — Evidence Tracking | D1: Contrôle AU-3 — Suivi des preuves
A2: Control Information | D2: Informations du contrôle
A3: Control Identifier | B3: AU-3 | D3: Identifiant du contrôle | E3: AU-3
A4: Family | B4: Content of Audit Records | D4: Famille | E4: Contenu des enregistrements de vérification
A5: Profile | B5: CCCS Medium / PBMM Moderate | D5: Profil | E5: CCCS Moyen / PBMM Modéré
A6: Primary Evidence Tool | D6: Outil de preuve principal
A7: Contributing Tools | D7: Outils contributeurs
A8: Control Description | B8: (A) The information system generates audit records containing information that establishes what type of event occurred, when the event occurred, where the event occurred, the source of the event, the outcome of the event, and the identity of any individuals or subjects associated with the event. | D8: Description du contrôle | E8: (A) Le système d’information génère des enregistrements de vérification qui contiennent les renseignements permettant d’établir le type d’événement qui a eu lieu, le moment et l’endroit où l’événement a eu lieu, la source de l’événement, le résultat de l’événement, ainsi que l’identité de toute personne ou de tout sujet associé à l’événement.
A9: Supplemental Guidance | B9: Audit record content that may be necessary to satisfy the requirement of this control, includes, for example, time stamps, source and destination addresses, user/process identifiers, event descriptions, success/fail indications, filenames involved, and access control or flow control rules invoked. Event outcomes can include indicators of event success or failure and event-specific results (e.g., the security state of the information system after the event occurred). Related controls: AU-2, AU-8, AU-12, SI-11 | D9: Directives supplémentaires | E9: Le contenu des enregistrements de vérification qui peut être nécessaire pour satisfaire à l’exigence de ce contrôle comprend, par exemple, les estampilles temporelles, les adresses de source et de destination, les identifiants d’utilisateurs ou de processus, les descriptions d’événements, les indications de réussite ou d’échec, les noms des fichiers en cause et les règles de contrôle d’accès ou de flux invoquées. Les résultats de l’événement peuvent comprendre des indicateurs de réussite ou d’échec de l’événement et des résultats propres à l’événement (p. ex., l’état de sécurité du système d’information après l’événement). Contrôles connexes : AU-2, AU-8, AU-12, SI-11
A10: Test Case | D10: Cas de test
A11: Test | B11: TEST-AU-3 | D11: Test | E11: TEST-AU-3
A12: Requirement ID | B12: AU-3 | D12: ID Exigence | E12: AU-3
A13: Component | D13: Composant
A14: Requirement | D14: Exigence
A15: Contextual Design Description | D15: Description contextuelle du design
A16: Evidence Provided | D16: Preuve fournie
A17: Preparer Sign Off (Initials, Date) | D17: Signataire préparateur (Initiales, Date)
A18: Owner Sign Off (Initials, Date) | D18: Signataire propriétaire (Initiales, Date)
A19: Assessor Sign Off (Initials, Date) | D19: Signataire évaluateur (Initiales, Date)
A20: Status | B20: Not Started | D20: Statut | E20: Non commencé
A21: Comments | D21: Commentaires

Sheet AU-3-1
A1: Control AU-3(1) — Evidence Tracking | D1: Contrôle AU-3(1) — Suivi des preuves
A2: Control Information | D2: Informations du contrôle
A3: Control Identifier | B3: AU-3(1) | D3: Identifiant du contrôle | E3: AU-3(1)
A4: Family | B4: Content of Audit Records | D4: Famille | E4: Contenu des enregistrements de vérification
A5: Profile | B5: CCCS Medium / PBMM Moderate | D5: Profil | E5: CCCS Moyen / PBMM Modéré
A6: Primary Evidence Tool | D6: Outil de preuve principal
A7: Contributing Tools | D7: Outils contributeurs
A8: Control Description | B8: CONTENT OF AUDIT RECORDS | ADDITIONAL AUDIT INFORMATION The information system generates audit records containing the following additional information: session, connection, transaction, or activity duration; for client-server transactions, the number of bytes received and bytes sent; additional informational messages to diagnose or identify the event; characteristics that describe or identify the object or resource being acted upon. | D8: Description du contrôle | E8: CONTENU DES ENREGISTREMENTS DE VÉRIFICATION | RENSEIGNEMENTS DE VÉRIFICATION SUPPLÉMENTAIRES Le système d’information génère des enregistrements de vérification contenant les renseignements supplémentaires suivants : la durée de la session, de la connexion, de la transaction ou de l’activité; pour les transactions client-serveur, le nombre d’octets reçus et d’octets envoyés; des messages d’information supplémentaires pour diagnostiquer ou identifier l’événement; les caractéristiques qui décrivent ou identifient l’objet ou la ressource concernés.
A9: Supplemental Guidance | B9: Detailed information that organizations may consider in audit records includes, for example, full text recording of privileged commands or the individual identities of group account users. Organizations consider limiting the additional audit information to only that information explicitly needed for specific audit requirements. This facilitates the use of audit trails and audit logs by not including information that could potentially be misleading or could make it more difficult to locate information of interest. Additional guidance for enhancement (1): Audit events should always be capable of being associated with an individual identity. Associating audit events with a group or role is insufficient. | D9: Directives supplémentaires | E9: Les renseignements détaillés dont les organisations peuvent tenir compte dans les enregistrements de vérification comprennent, par exemple, l’enregistrement en texte intégral des commandes privilégiées ou les identités individuelles des utilisateurs de comptes de groupe. Les organisations devraient envisager de limiter les renseignements de vérification supplémentaires aux seuls renseignements explicitement nécessaires pour répondre à des exigences de vérification particulières. Cela facilitera l’utilisation des pistes de vérification et des journaux de vérification en n’incluant pas les renseignements qui pourraient être trompeurs ou rendre plus difficile la recherche de renseignements utiles. Conseils supplémentaires pour l’amélioration (1) : Les événements vérifiés devraient toujours pouvoir être associés à une identité individuelle. Associer des événements vérifiés à un groupe ou à un rôle est insuffisant.
A10: Test Case | D10: Cas de test
A11: Test | B11: TEST-AU-3(1) | D11: Test | E11: TEST-AU-3(1)
A12: Requirement ID | B12: AU-3(1) | D12: ID Exigence | E12: AU-3(1)
A13: Component | D13: Composant
A14: Requirement | D14: Exigence
A15: Contextual Design Description | D15: Description contextuelle du design
A16: Evidence Provided | D16: Preuve fournie
A17: Preparer Sign Off (Initials, Date) | D17: Signataire préparateur (Initiales, Date)
A18: Owner Sign Off (Initials, Date) | D18: Signataire propriétaire (Initiales, Date)
A19: Assessor Sign Off (Initials, Date) | D19: Signataire évaluateur (Initiales, Date)
A20: Status | B20: Not Started | D20: Statut | E20: Non commencé
A21: Comments | D21: Commentaires

Sheet AU-5
A1: Control AU-5 — Evidence Tracking | D1: Contrôle AU-5 — Suivi des preuves
A2: Control Information | D2: Informations du contrôle
A3: Control Identifier | B3: AU-5 | D3: Identifiant du contrôle | E3: AU-5
A4: Family | B4: Response To Audit Processing Failures | D4: Famille | E4: Réponse aux échecs de traitement de vérification
A5: Profile | B5: CCCS Medium / PBMM Moderate | D5: Profil | E5: CCCS Moyen / PBMM Modéré
A6: Primary Evidence Tool | D6: Outil de preuve principal
A7: Contributing Tools | D7: Outils contributeurs
A8: Control Description | B8: (A) The information system alerts organization-defined personnel or roles in the event of an audit processing failure; and (B) The information system overwrites the oldest audit records. | D8: Description du contrôle | E8: (A) Le système d’information alerte le personnel ou les rôles définis par l’organisation en cas d’échec de traitement de vérification; (B) Le système d’information écrase les enregistrements de vérification les plus anciens.
A9: Supplemental Guidance | B9: Audit processing failures include, for example, software/hardware errors, failures in the audit capturing mechanisms, and audit storage capacity being reached or exceeded. Organizations may choose to define additional actions for different audit processing failures (e.g., by type, by location, by severity, or a combination of such factors). This control applies to each audit data storage repository (i.e., distinct information system component where audit records are stored), the total audit storage capacity of organizations (i.e., all audit data storage repositories combined), or both. Related controls: AU-4, SI-12 | D9: Directives supplémentaires | E9: Les échecs de traitement de vérification comprennent, par exemple, les erreurs de logiciel ou de matériel, les défaillances des mécanismes de saisie des vérifications et la capacité de stockage atteinte ou dépassée pour les vérifications. Les organisations peuvent choisir de définir des mesures supplémentaires pour différents échecs de traitement de vérification (p. ex., par type, par emplacement, par gravité ou une combinaison de ces facteurs). Ce contrôle s’applique à chaque répertoire de stockage des données de vérification (c.-à -d. à chaque composant distinct du système d’information dans lequel les enregistrements de vérification sont conservés), à la capacité totale de stockage des vérifications des organisations (c.-à-d. tous les répertoires de stockage des données de vérification combinés), ou aux deux. Contrôles connexes : AU-4, SI-12
A10: Test Case | D10: Cas de test
A11: Test | B11: TEST-AU-5 | D11: Test | E11: TEST-AU-5
A12: Requirement ID | B12: AU-5 | D12: ID Exigence | E12: AU-5
A13: Component | D13: Composant
A14: Requirement | D14: Exigence
A15: Contextual Design Description | D15: Description contextuelle du design
A16: Evidence Provided | D16: Preuve fournie
A17: Preparer Sign Off (Initials, Date) | D17: Signataire préparateur (Initiales, Date)
A18: Owner Sign Off (Initials, Date) | D18: Signataire propriétaire (Initiales, Date)
A19: Assessor Sign Off (Initials, Date) | D19: Signataire évaluateur (Initiales, Date)
A20: Status | B20: Not Started | D20: Statut | E20: Non commencé
A21: Comments | D21: Commentaires

Sheet AU-6-1
A1: Control AU-6(1) — Evidence Tracking | D1: Contrôle AU-6(1) — Suivi des preuves
A2: Control Information | D2: Informations du contrôle
A3: Control Identifier | B3: AU-6(1) | D3: Identifiant du contrôle | E3: AU-6(1)
A4: Family | B4: Audit Review, Analysis, and Reporting | D4: Famille | E4: Examen, analyse et rapport de vérification
A5: Profile | B5: CCCS Medium / PBMM Moderate | D5: Profil | E5: CCCS Moyen / PBMM Modéré
A6: Primary Evidence Tool | D6: Outil de preuve principal
A7: Contributing Tools | D7: Outils contributeurs
A8: Control Description | B8: AUDIT REVIEW, ANALYSIS, AND REPORTING | PROCESS INTEGRATION The organization employs automated mechanisms to integrate audit review, analysis, and reporting processes to support organizational processes for investigation and response to suspicious activities. | D8: Description du contrôle | E8: EXAMEN, ANALYSE ET RAPPORT DE VÉRIFICATION | INTÉGRATION DES PROCESSUS L’organisation utilise des mécanismes automatisés pour intégrer les processus d’examen, d’analyse et de production de rapports de vérification afin de soutenir les processus organisationnels d’enquête et d’intervention en cas d’activités suspectes.
A9: Supplemental Guidance | B9: Organizational processes benefiting from integrated audit review, analysis, and reporting include, for example, incident response, continuous monitoring, and contingency planning. Related control: AU-12. | D9: Directives supplémentaires | E9: Les processus organisationnels qui bénéficient de l’intégration de l’examen, de l’analyse et de la production de rapports de vérification sont notamment l’intervention en cas d’incident, la surveillance continue et la planification d’urgence. Contrôle connexe : AU-12.
A10: Test Case | D10: Cas de test
A11: Test | B11: TEST-AU-6(1) | D11: Test | E11: TEST-AU-6(1)
A12: Requirement ID | B12: AU-6(1) | D12: ID Exigence | E12: AU-6(1)
A13: Component | D13: Composant
A14: Requirement | D14: Exigence
A15: Contextual Design Description | D15: Description contextuelle du design
A16: Evidence Provided | D16: Preuve fournie
A17: Preparer Sign Off (Initials, Date) | D17: Signataire préparateur (Initiales, Date)
A18: Owner Sign Off (Initials, Date) | D18: Signataire propriétaire (Initiales, Date)
A19: Assessor Sign Off (Initials, Date) | D19: Signataire évaluateur (Initiales, Date)
A20: Status | B20: Not Started | D20: Statut | E20: Non commencé
A21: Comments | D21: Commentaires

Sheet AU-6-3
A1: Control AU-6(3) — Evidence Tracking | D1: Contrôle AU-6(3) — Suivi des preuves
A2: Control Information | D2: Informations du contrôle
A3: Control Identifier | B3: AU-6(3) | D3: Identifiant du contrôle | E3: AU-6(3)
A4: Family | B4: Audit Review, Analysis, and Reporting | D4: Famille | E4: Examen, analyse et rapport de vérification
A5: Profile | B5: CCCS Medium / PBMM Moderate | D5: Profil | E5: CCCS Moyen / PBMM Modéré
A6: Primary Evidence Tool | D6: Outil de preuve principal
A7: Contributing Tools | D7: Outils contributeurs
A8: Control Description | B8: AUDIT REVIEW, ANALYSIS, AND REPORTING | CORRELATE AUDIT REPOSITORIES The organization analyzes and correlates audit records across different repositories to gain organization-wide situational awareness. | D8: Description du contrôle | E8: EXAMEN, ANALYSE ET RAPPORT DE VÉRIFICATION | MISE EN CORRÉLATION DES RÉPERTOIRES DE VÉRIFICATION L’organisation analyse et met en corrélation les enregistrements de vérification entre les différents répertoires afin d’acquérir une connaissance globale de la situation dans l’ensemble de l’organisation.
A9: Supplemental Guidance | B9: Organization-wide situational awareness includes awareness across all three tiers of risk management (i.e., organizational, mission/business process, and information system) and supports cross-organization awareness. Related controls: AU-12, IR-4. | D9: Directives supplémentaires | E9: La connaissance de la situation dans l’ensemble de l’organisation comprend la connaissance aux trois niveaux de la gestion des risques (c.-à-d. au niveau de l’organisation, de la mission/des processus opérationnels, et du système d’information) et appuie une connaissance transorganisationnelle de la situation. Contrôles connexes : AU-12, IR-4.
A10: Test Case | D10: Cas de test
A11: Test | B11: TEST-AU-6(3) | D11: Test | E11: TEST-AU-6(3)
A12: Requirement ID | B12: AU-6(3) | D12: ID Exigence | E12: AU-6(3)
A13: Component | D13: Composant
A14: Requirement | D14: Exigence
A15: Contextual Design Description | D15: Description contextuelle du design
A16: Evidence Provided | D16: Preuve fournie
A17: Preparer Sign Off (Initials, Date) | D17: Signataire préparateur (Initiales, Date)
A18: Owner Sign Off (Initials, Date) | D18: Signataire propriétaire (Initiales, Date)
A19: Assessor Sign Off (Initials, Date) | D19: Signataire évaluateur (Initiales, Date)
A20: Status | B20: Not Started | D20: Statut | E20: Non commencé
A21: Comments | D21: Commentaires

Sheet AU-7
A1: Control AU-7 — Evidence Tracking | D1: Contrôle AU-7 — Suivi des preuves
A2: Control Information | D2: Informations du contrôle
A3: Control Identifier | B3: AU-7 | D3: Identifiant du contrôle | E3: AU-7
A4: Family | B4: Audit Reduction and Report Generation | D4: Famille | E4: Réduction des vérifications et production de rapports
A5: Profile | B5: CCCS Medium / PBMM Moderate | D5: Profil | E5: CCCS Moyen / PBMM Modéré
A6: Primary Evidence Tool | D6: Outil de preuve principal
A7: Contributing Tools | D7: Outils contributeurs
A8: Control Description | B8: (A) The information system provides an audit reduction and report generation capability that supports on-demand audit review, analysis, and reporting requirements and after-the-fact investigations of security incidents. (B) The information system provides an audit reduction and report generation capability that does not alter the original content or time ordering of audit records. | D8: Description du contrôle | E8: (A) Le système d’information offre une capacité de réduction des vérifications et de production de rapports prenant en charge les examens, les analyses et les rapports de vérification sur demande ainsi que les enquêtes à la suite d’incidents de sécurité. (B) Le système d’information offre une capacité de réduction de la vérification et de production de rapports qui ne modifie pas le contenu original ou l’ordre chronologique des enregistrements de vérification.
A9: Supplemental Guidance | B9: Audit reduction is a process that manipulates collected audit information and organizes such information in a summary format that is more meaningful to analysts. Audit reduction and report generation capabilities do not always emanate from the same information system or from the same organizational entities conducting auditing activities. Audit reduction capability can include, for example, modern data mining techniques with advanced data filters to identify anomalous behaviour in audit records. The report generation capability provided by the information system can generate customizable reports. Time ordering of audit records can be a significant issue if the granularity of the timestamp in the record is insufficient. Related control: AU-6 | D9: Directives supplémentaires | E9: La réduction de la vérification est un processus qui permet de manipuler l’information recueillie et de l’organiser dans un format sommaire plus significatif pour les analystes. Les capacités de réduction des vérifications et de production de rapports ne proviennent pas toujours du système d’information ou des entités organisationnelles qui mènent les activités de vérification. La capacité de réduction des vérifications peut comprendre, par exemple, des techniques modernes d’exploration de données avec filtres de données avancés pour déceler les comportements anormaux dans les enregistrements de vérification. La capacité de production de rapports fournie par le système d’information permet de générer des rapports personnalisables. L’ordre chronologique des enregistrements de vérification peut poser un problème important si la granularité de l’estampille temporelle dans l’enregistrement est insuffisante. Contrôle connexe : AU-6
A10: Test Case | D10: Cas de test
A11: Test | B11: TEST-AU-7 | D11: Test | E11: TEST-AU-7
A12: Requirement ID | B12: AU-7 | D12: ID Exigence | E12: AU-7
A13: Component | D13: Composant
A14: Requirement | D14: Exigence
A15: Contextual Design Description | D15: Description contextuelle du design
A16: Evidence Provided | D16: Preuve fournie
A17: Preparer Sign Off (Initials, Date) | D17: Signataire préparateur (Initiales, Date)
A18: Owner Sign Off (Initials, Date) | D18: Signataire propriétaire (Initiales, Date)
A19: Assessor Sign Off (Initials, Date) | D19: Signataire évaluateur (Initiales, Date)
A20: Status | B20: Not Started | D20: Statut | E20: Non commencé
A21: Comments | D21: Commentaires

Sheet AU-7-1
A1: Control AU-7(1) — Evidence Tracking | D1: Contrôle AU-7(1) — Suivi des preuves
A2: Control Information | D2: Informations du contrôle
A3: Control Identifier | B3: AU-7(1) | D3: Identifiant du contrôle | E3: AU-7(1)
A4: Family | B4: Audit Reduction and Report Generation | D4: Famille | E4: Réduction des vérifications et production de rapports
A5: Profile | B5: CCCS Medium / PBMM Moderate | D5: Profil | E5: CCCS Moyen / PBMM Modéré
A6: Primary Evidence Tool | D6: Outil de preuve principal
A7: Contributing Tools | D7: Outils contributeurs
A8: Control Description | B8: AUDIT REDUCTION AND REPORT GENERATION | AUTOMATIC PROCESSING The information system provides the capability to process audit records for events of interest based on all audit fields specified in AU-2, AU-3 and AU-3(1). | D8: Description du contrôle | E8: RÉDUCTION DES VÉRIFICATIONS ET PRODUCTION DE RAPPORTS | TRAITEMENT AUTOMATIQUE Le système d’information permet de traiter les enregistrements de vérification relatifs aux événements d’intérêt en fonction de tous les champs de vérification précisés dans AU-2, AU-3 et AU-3(1).
A9: Supplemental Guidance | B9: Events of interest can be identified by the content of specific audit record fields including, for example, identities of individuals, event types, event locations, event times, event dates, system resources involved, IP addresses involved, or information objects accessed. Organizations may define audit event criteria to any degree of granularity required, for example, locations selectable by general networking location (e.g., by network or sub-network) or selectable by specific information system component. Related controls: AU-2, AU-12. | D9: Directives supplémentaires | E9: Les événements d’intérêt peuvent être définis par le contenu des champs particuliers de l’enregistrement de vérification, y compris, par exemple, les identités des personnes, les types d’événements, les emplacements des événements, les heures des événements, les dates des événements, les ressources du système en cause, les adresses IP en cause ou les objets d’information consultés. Les organisations peuvent définir les critères des événements de vérification à n’importe quel degré de granularité requis, par exemple, les emplacements que l’on peut sélectionner par emplacement de réseautique général (p. ex., par réseau ou sous-réseau) ou par composant de système d’information particulier. Contrôles connexes : AU-2, AU-12.
A10: Test Case | D10: Cas de test
A11: Test | B11: TEST-AU-7(1) | D11: Test | E11: TEST-AU-7(1)
A12: Requirement ID | B12: AU-7(1) | D12: ID Exigence | E12: AU-7(1)
A13: Component | D13: Composant
A14: Requirement | D14: Exigence
A15: Contextual Design Description | D15: Description contextuelle du design
A16: Evidence Provided | D16: Preuve fournie
A17: Preparer Sign Off (Initials, Date) | D17: Signataire préparateur (Initiales, Date)
A18: Owner Sign Off (Initials, Date) | D18: Signataire propriétaire (Initiales, Date)
A19: Assessor Sign Off (Initials, Date) | D19: Signataire évaluateur (Initiales, Date)
A20: Status | B20: Not Started | D20: Statut | E20: Non commencé
A21: Comments | D21: Commentaires

Sheet AU-8
A1: Control AU-8 — Evidence Tracking | D1: Contrôle AU-8 — Suivi des preuves
A2: Control Information | D2: Informations du contrôle
A3: Control Identifier | B3: AU-8 | D3: Identifiant du contrôle | E3: AU-8
A4: Family | B4: Time Stamps | D4: Famille | E4: Estampilles temporelles
A5: Profile | B5: CCCS Medium / PBMM Moderate | D5: Profil | E5: CCCS Moyen / PBMM Modéré
A6: Primary Evidence Tool | D6: Outil de preuve principal
A7: Contributing Tools | D7: Outils contributeurs
A8: Control Description | B8: (A) The information system uses internal system clocks to generate time stamps for audit records. (B) The information system records time stamps for audit records that can be mapped to Coordinated Universal Time (UTC) or Greenwich Mean Time (GMT) within 1 second precision. | D8: Description du contrôle | E8: (A) Le système d’information utilise les horloges système internes afin de générer les estampilles temporelles pour les enregistrements de vérification. (B) Le système d’information enregistre des estampilles temporelles pour les enregistrements de vérification qui peuvent être mappées sur le temps universel coordonné (UTC) ou l’heure moyenne de Greenwich (GMT) à la seconde près.
A9: Supplemental Guidance | B9: Time stamps generated by the information system include date and time. Time is commonly expressed in Coordinated Universal Time (UTC) or local time with an offset from UTC. Granularity of time measurements refers to the degree of synchronization between information system clocks and reference clocks, for example, clocks synchronizing within hundreds of milliseconds or within tens of milliseconds. Organizations may define different time granularities for different system components. Time service can also be critical to other security capabilities such as access control and identification and authentication, depending on the nature of the mechanisms used to support those capabilities. Related controls: AU-3, AU-12 | D9: Directives supplémentaires | E9: Les estampilles temporelles générées par le système d’information comprennent la date et l’heure. L’heure est généralement exprimée en temps universel coordonné (UTC) ou selon l’heure locale avec indication du décalage par rapport à l’UTC. La granularité des mesures du temps désigne le niveau de synchronisation entre les horloges du système d’information et les horloges de référence, par exemple, des horloges synchronisées à quelques centaines ou dizaines de millisecondes près. Les organisations peuvent définir différentes granularités temporelles pour différents composants du système. Le service de l’heure peut également être essentiel à d’autres capacités de sécurité comme le contrôle d’accès, l’identification et l’authentification, selon la nature des mécanismes utilisés pour soutenir ces capacités. Contrôles connexes : AU-3, AU-12
A10: Test Case | D10: Cas de test
A11: Test | B11: TEST-AU-8 | D11: Test | E11: TEST-AU-8
A12: Requirement ID | B12: AU-8 | D12: ID Exigence | E12: AU-8
A13: Component | D13: Composant
A14: Requirement | D14: Exigence
A15: Contextual Design Description | D15: Description contextuelle du design
A16: Evidence Provided | D16: Preuve fournie
A17: Preparer Sign Off (Initials, Date) | D17: Signataire préparateur (Initiales, Date)
A18: Owner Sign Off (Initials, Date) | D18: Signataire propriétaire (Initiales, Date)
A19: Assessor Sign Off (Initials, Date) | D19: Signataire évaluateur (Initiales, Date)
A20: Status | B20: Not Started | D20: Statut | E20: Non commencé
A21: Comments | D21: Commentaires

Sheet AU-8-1
A1: Control AU-8(1) — Evidence Tracking | D1: Contrôle AU-8(1) — Suivi des preuves
A2: Control Information | D2: Informations du contrôle
A3: Control Identifier | B3: AU-8(1) | D3: Identifiant du contrôle | E3: AU-8(1)
A4: Family | B4: Time Stamps | D4: Famille | E4: Estampilles temporelles
A5: Profile | B5: CCCS Medium / PBMM Moderate | D5: Profil | E5: CCCS Moyen / PBMM Modéré
A6: Primary Evidence Tool | D6: Outil de preuve principal
A7: Contributing Tools | D7: Outils contributeurs
A8: Control Description | B8: TIME STAMPS | SYNCHRONIZATION WITH AUTHORITATIVE TIME SOURCE (a) The information system compares the internal information system clocks at least every 24 hours with an organization-defined authoritative time source; and (b) The information system synchronizes the internal system clocks to the authoritative time source when the time difference is greater than 1 millisecond. | D8: Description du contrôle | E8: ESTAMPILLES TEMPORELLES | SYNCHRONISATION AVEC UNE SOURCE D’HORODATAGE RECONNUE (a) Le système d’information compare les horloges internes du système d’information au moins toutes les 24 heures avec une source d’horodatage reconnue définie par l’organisation. (b) Le système d’information synchronise les horloges internes du système avec la source d’horodatage reconnue lorsque la différence de temps est supérieure à 1 milliseconde.
A9: Supplemental Guidance | B9: This control enhancement provides uniformity of time stamps for information systems with multiple system clocks and systems connected over a network. | D9: Directives supplémentaires | E9: Cette amélioration du contrôle assure l’uniformité des estampilles temporelles pour les systèmes d’information dotés de nombreuses horloges et les systèmes sur un réseau.
A10: Test Case | D10: Cas de test
A11: Test | B11: TEST-AU-8(1) | D11: Test | E11: TEST-AU-8(1)
A12: Requirement ID | B12: AU-8(1) | D12: ID Exigence | E12: AU-8(1)
A13: Component | D13: Composant
A14: Requirement | D14: Exigence
A15: Contextual Design Description | D15: Description contextuelle du design
A16: Evidence Provided | D16: Preuve fournie
A17: Preparer Sign Off (Initials, Date) | D17: Signataire préparateur (Initiales, Date)
A18: Owner Sign Off (Initials, Date) | D18: Signataire propriétaire (Initiales, Date)
A19: Assessor Sign Off (Initials, Date) | D19: Signataire évaluateur (Initiales, Date)
A20: Status | B20: Not Started | D20: Statut | E20: Non commencé
A21: Comments | D21: Commentaires

Sheet AU-9
A1: Control AU-9 — Evidence Tracking | D1: Contrôle AU-9 — Suivi des preuves
A2: Control Information | D2: Informations du contrôle
A3: Control Identifier | B3: AU-9 | D3: Identifiant du contrôle | E3: AU-9
A4: Family | B4: Protection of Audit Information | D4: Famille | E4: Protection des renseignements de vérification
A5: Profile | B5: CCCS Medium / PBMM Moderate | D5: Profil | E5: CCCS Moyen / PBMM Modéré
A6: Primary Evidence Tool | D6: Outil de preuve principal
A7: Contributing Tools | D7: Outils contributeurs
A8: Control Description | B8: (A) The information system protects audit information and audit tools from unauthorized access, modification, and deletion. | D8: Description du contrôle | E8: (A) Le système d’information protège les renseignements de vérification et les outils de vérification contre l’accès, la modification et la suppression non autorisés.
A9: Supplemental Guidance | B9: Audit information includes all information (e.g., audit records, audit settings, and audit reports) needed to successfully audit information system activity. This control focuses on technical protection of audit information. Physical protection of audit information is addressed by media protection controls and physical and environmental protection controls. Related controls: AC-3, AC-6, MP-2, MP-4, PE-2, PE-3, PE-6 | D9: Directives supplémentaires | E9: Les renseignements de vérification comprennent tous les renseignements (p. ex., les enregistrements de vérification, les paramètres de vérification et les rapports de vérification) nécessaires pour vérifier avec succès l’activité du système d’information. Ce contrôle est axé sur la protection technique des renseignements de vérification. La protection physique des renseignements de vérification est assurée par des contrôles de protection des supports et des contrôles de protection physique et environnementale. Contrôles connexes : AC-3, AC-6, MP-2, MP-4, PE-2, PE-3, PE-6
A10: Test Case | D10: Cas de test
A11: Test | B11: TEST-AU-9 | D11: Test | E11: TEST-AU-9
A12: Requirement ID | B12: AU-9 | D12: ID Exigence | E12: AU-9
A13: Component | D13: Composant
A14: Requirement | D14: Exigence
A15: Contextual Design Description | D15: Description contextuelle du design
A16: Evidence Provided | D16: Preuve fournie
A17: Preparer Sign Off (Initials, Date) | D17: Signataire préparateur (Initiales, Date)
A18: Owner Sign Off (Initials, Date) | D18: Signataire propriétaire (Initiales, Date)
A19: Assessor Sign Off (Initials, Date) | D19: Signataire évaluateur (Initiales, Date)
A20: Status | B20: Not Started | D20: Statut | E20: Non commencé
A21: Comments | D21: Commentaires

Sheet AU-9-2
A1: Control AU-9(2) — Evidence Tracking | D1: Contrôle AU-9(2) — Suivi des preuves
A2: Control Information | D2: Informations du contrôle
A3: Control Identifier | B3: AU-9(2) | D3: Identifiant du contrôle | E3: AU-9(2)
A4: Family | B4: Protection of Audit Information | D4: Famille | E4: Protection des renseignements de vérification
A5: Profile | B5: CCCS Medium / PBMM Moderate | D5: Profil | E5: CCCS Moyen / PBMM Modéré
A6: Primary Evidence Tool | D6: Outil de preuve principal
A7: Contributing Tools | D7: Outils contributeurs
A8: Control Description | B8: PROTECTION OF AUDIT INFORMATION | AUDIT BACKUP ON SEPARATE PHYSICAL SYSTEMS / COMPONENTS The information system backs up audit records at least weekly onto a physically different system or system component than the system or component being audited. | D8: Description du contrôle | E8: PROTECTION DES RENSEIGNEMENTS DE VÉRIFICATION | SAUVEGARDE DES VÉRIFICATIONS SUR DES SYSTÈMES/COMPOSANTS PHYSIQUES SÉPARÉS Le système d’information sauvegarde les enregistrements de vérification au moins une fois par semaine sur un système ou un composant système physiquement différent du système ou du composant faisant l’objet de la vérification.
A9: Supplemental Guidance | B9: This control enhancement helps to ensure that a compromise of the information system being audited does not also result in a compromise of the audit records. Related controls: AU-4, AU-5, AU-11. | D9: Directives supplémentaires | E9: Cette amélioration permet de s’assurer qu’une compromission du système d’information faisant l’objet d’une vérification n’entraîne pas également la compromission des enregistrements de vérification. Contrôles connexes : AU-4, AU-5, AU-11.
A10: Test Case | D10: Cas de test
A11: Test | B11: TEST-AU-9(2) | D11: Test | E11: TEST-AU-9(2)
A12: Requirement ID | B12: AU-9(2) | D12: ID Exigence | E12: AU-9(2)
A13: Component | D13: Composant
A14: Requirement | D14: Exigence
A15: Contextual Design Description | D15: Description contextuelle du design
A16: Evidence Provided | D16: Preuve fournie
A17: Preparer Sign Off (Initials, Date) | D17: Signataire préparateur (Initiales, Date)
A18: Owner Sign Off (Initials, Date) | D18: Signataire propriétaire (Initiales, Date)
A19: Assessor Sign Off (Initials, Date) | D19: Signataire évaluateur (Initiales, Date)
A20: Status | B20: Not Started | D20: Statut | E20: Non commencé
A21: Comments | D21: Commentaires

Sheet AU-9-4
A1: Control AU-9(4) — Evidence Tracking | D1: Contrôle AU-9(4) — Suivi des preuves
A2: Control Information | D2: Informations du contrôle
A3: Control Identifier | B3: AU-9(4) | D3: Identifiant du contrôle | E3: AU-9(4)
A4: Family | B4: Protection of Audit Information | D4: Famille | E4: Protection des renseignements de vérification
A5: Profile | B5: CCCS Medium / PBMM Moderate | D5: Profil | E5: CCCS Moyen / PBMM Modéré
A6: Primary Evidence Tool | D6: Outil de preuve principal
A7: Contributing Tools | D7: Outils contributeurs
A8: Control Description | B8: PROTECTION OF AUDIT INFORMATION | ACCESS BY SUBSET OF PRIVILEGED USERS The organization authorizes access to management of audit functionality to only an organization-defined subset of privileged users. | D8: Description du contrôle | E8: PROTECTION DES RENSEIGNEMENTS DE VÉRIFICATION | ACCÈS PAR SOUS-ENSEMBLE D’UTILISATEURS PRIVILÉGIÉS L’organisation n’autorise l’accès à la fonction de gestion de la vérification qu’à un sous-ensemble d’utilisateurs privilégiés défini par l’organisation seulement.
A9: Supplemental Guidance | B9: Individuals with privileged access to an information system and who are also the subject of an audit by that system, may affect the reliability of audit information by inhibiting audit activities or modifying audit records. This control enhancement requires that privileged access be further defined between audit-related privileges and other privileges, thus limiting the users with audit-related privileges. Related control: AC-5. | D9: Directives supplémentaires | E9: Les personnes qui ont un accès privilégié à un système d’information et qui font également l’objet d’une vérification par ce système peuvent nuire à la fiabilité de l’information de vérification en entravant les activités de vérification ou en modifiant les enregistrements de vérification. Cette amélioration du contrôle exige que l’accès privilégié soit mieux défini entre les privilèges liés à la vérification et les autres privilèges, de manière à limiter le nombre d’utilisateurs ayant des privilèges liés à la vérification. Contrôle connexe : AC-5.
A10: Test Case | D10: Cas de test
A11: Test | B11: TEST-AU-9(4) | D11: Test | E11: TEST-AU-9(4)
A12: Requirement ID | B12: AU-9(4) | D12: ID Exigence | E12: AU-9(4)
A13: Component | D13: Composant
A14: Requirement | D14: Exigence
A15: Contextual Design Description | D15: Description contextuelle du design
A16: Evidence Provided | D16: Preuve fournie
A17: Preparer Sign Off (Initials, Date) | D17: Signataire préparateur (Initiales, Date)
A18: Owner Sign Off (Initials, Date) | D18: Signataire propriétaire (Initiales, Date)
A19: Assessor Sign Off (Initials, Date) | D19: Signataire évaluateur (Initiales, Date)
A20: Status | B20: Not Started | D20: Statut | E20: Non commencé
A21: Comments | D21: Commentaires

Sheet AU-11
A1: Control AU-11 — Evidence Tracking | D1: Contrôle AU-11 — Suivi des preuves
A2: Control Information | D2: Informations du contrôle
A3: Control Identifier | B3: AU-11 | D3: Identifiant du contrôle | E3: AU-11
A4: Family | B4: Audit Record Retention | D4: Famille | E4: Conservation des enregistrements de vérification
A5: Profile | B5: CCCS Medium / PBMM Moderate | D5: Profil | E5: CCCS Moyen / PBMM Modéré
A6: Primary Evidence Tool | D6: Outil de preuve principal
A7: Contributing Tools | D7: Outils contributeurs
A8: Control Description | B8: (A) The CSP retains audit records for at least 90 days to provide support for after-the-fact investigations of security incidents and to meet regulatory and organizational information retention requirements. (B) The client retains audit records and logs for at least 3 months online and at least 6 months in storage. (C) The client retains all audit records and logs associated with a security incident for at least 5 years. | D8: Description du contrôle | E8: (A) Le FSI conserve les enregistrements de vérification pendant au moins 90 jours afin de soutenir les enquêtes faisant suite aux incidents de sécurité et de respecter les exigences réglementaires et organisationnelles en matière de conservation de l’information. (B) Le client conserve les enregistrements et les journaux de vérification pendant au moins 3 mois en ligne et au moins 6 mois en mémoire. (C) Le client conserve pendant au moins 5 ans tous les enregistrements et journaux de vérification associés à un incident de sécurité.
A9: Supplemental Guidance | B9: Organizations retain audit records until it is determined that they are no longer needed for administrative, legal, audit, or other operational purposes. This includes, for example, retention and availability of audit records relative to legal requests, subpoenas, and law enforcement actions. Organizations develop standard categories of audit records relative to such types of actions and standard response processes for each type of action. Related controls: AU-4, AU-5, AU-9, MP-6 | D9: Directives supplémentaires | E9: Les organisations conservent les enregistrements de vérification jusqu’à ce qu’il soit déterminé qu’ils ne sont plus nécessaires à des fins administratives, juridiques, de vérification ou à d’autres fins opérationnelles. Cela comprend, par exemple, la conservation et la disponibilité des enregistrements de vérification relatifs aux demandes légales, aux citations à comparaître et aux mesures d’application de la loi. Les organisations établissent des catégories normalisées d’enregistrements de vérification par rapport à ces types de mesures ainsi que des processus de réponse normalisés pour chaque type de mesure. Contrôles connexes : AU-4, AU-5, AU-9, MP-6
A10: Test Case | D10: Cas de test
A11: Test | B11: TEST-AU-11 | D11: Test | E11: TEST-AU-11
A12: Requirement ID | B12: AU-11 | D12: ID Exigence | E12: AU-11
A13: Component | D13: Composant
A14: Requirement | D14: Exigence
A15: Contextual Design Description | D15: Description contextuelle du design
A16: Evidence Provided | D16: Preuve fournie
A17: Preparer Sign Off (Initials, Date) | D17: Signataire préparateur (Initiales, Date)
A18: Owner Sign Off (Initials, Date) | D18: Signataire propriétaire (Initiales, Date)
A19: Assessor Sign Off (Initials, Date) | D19: Signataire évaluateur (Initiales, Date)
A20: Status | B20: Not Started | D20: Statut | E20: Non commencé
A21: Comments | D21: Commentaires

Sheet AU-12
A1: Control AU-12 — Evidence Tracking | D1: Contrôle AU-12 — Suivi des preuves
A2: Control Information | D2: Informations du contrôle
A3: Control Identifier | B3: AU-12 | D3: Identifiant du contrôle | E3: AU-12
A4: Family | B4: Audit Generation | D4: Famille | E4: Génération des vérifications
A5: Profile | B5: CCCS Medium / PBMM Moderate | D5: Profil | E5: CCCS Moyen / PBMM Modéré
A6: Primary Evidence Tool | D6: Outil de preuve principal
A7: Contributing Tools | D7: Outils contributeurs
A8: Control Description | B8: (A) The information system provides audit record generation capability for the auditable events defined in AU-2 a. of all information system and network components where audit capability is deployed/available. (B) The information system allows organization-defined personnel or roles to select which auditable events are to be audited by specific components of the information system. (C) The information system generates audit records for the events defined in AU-2 d. with the content defined in AU-3. | D8: Description du contrôle | E8: (A) Le système d’information offre une capacité de génération d’enregistrements de vérification pour les événements vérifiables définis dans AU-2 a. de tous les composants du système d’information et du réseau où la capacité de vérification est déployée/disponible. (B) Le système d’information permet au personnel ou aux rôles définis par l’organisation de choisir les événements vérifiables qui doivent être vérifiés par des composants précis du système d’information. (C) Le système d’information génère des enregistrements de vérification pour les événements définis dans AU-2 d. avec le contenu défini dans AU-3.
A9: Supplemental Guidance | B9: Audit records can be generated from many different information system components. The list of audited events is the set of events for which audits are to be generated. These events are typically a subset of all events for which the information system is capable of generating audit records. Related controls: AC-3, AU-2, AU-3, AU-6, AU-7 | D9: Directives supplémentaires | E9: Des enregistrements de vérification peuvent être générés à partir de nombreux composants du système d’information. La liste des événements vérifiés est l’ensemble des événements pour lesquels des vérifications doivent être produites. Ces événements sont habituellement un sous-ensemble de tous les événements pour lesquels le système d’information peut générer des enregistrements de vérification. Contrôles connexes : AC-3, AU-2, AU-3, AU-6, AU-7
A10: Test Case | D10: Cas de test
A11: Test | B11: TEST-AU-12 | D11: Test | E11: TEST-AU-12
A12: Requirement ID | B12: AU-12 | D12: ID Exigence | E12: AU-12
A13: Component | D13: Composant
A14: Requirement | D14: Exigence
A15: Contextual Design Description | D15: Description contextuelle du design
A16: Evidence Provided | D16: Preuve fournie
A17: Preparer Sign Off (Initials, Date) | D17: Signataire préparateur (Initiales, Date)
A18: Owner Sign Off (Initials, Date) | D18: Signataire propriétaire (Initiales, Date)
A19: Assessor Sign Off (Initials, Date) | D19: Signataire évaluateur (Initiales, Date)
A20: Status | B20: Not Started | D20: Statut | E20: Non commencé
A21: Comments | D21: Commentaires

Sheet CM-3
A1: Control CM-3 — Evidence Tracking | D1: Contrôle CM-3 — Suivi des preuves
A2: Control Information | D2: Informations du contrôle
A3: Control Identifier | B3: CM-3 | D3: Identifiant du contrôle | E3: CM-3
A4: Family | B4: Configuration Change Control | D4: Famille | E4: Contrôle des changements de configuration
A5: Profile | B5: CCCS Medium / PBMM Moderate | D5: Profil | E5: CCCS Moyen / PBMM Modéré
A6: Primary Evidence Tool | D6: Outil de preuve principal
A7: Contributing Tools | D7: Outils contributeurs
A8: Control Description | B8: (A) The organization determines the types of changes to the information system that are configuration-controlled. (B) The organization reviews proposed configuration-controlled changes to the information system and approves or disapproves such changes with explicit consideration for security impact analyses. (C) The organization documents configuration change decisions associated with the information system. (D) The organization implements approved configuration-controlled changes to the information system. (E) The organization retains records of configuration-controlled changes to the information system for at least 90 days. (F) The organization audits and reviews activities associated with configuration-controlled changes to the information system. (G) The organization coordinates and provides oversight for configuration change control activities through a central communication process that includes organizational governance bodies that convenes at least annually. | D8: Description du contrôle | E8: (A) L’organisation détermine les types de changements au système d’information qui sont contrôlés par la configuration. (B) L’organisation examine les changements proposés au système d’information qui sont contrôlés par la configuration et approuve ou désapprouve ces changements en tenant compte explicitement des analyses des répercussions sur la sécurité. (C) L’organisation documente les décisions sur les changements de configuration associés au système d’information. (D) L’organisation met en œuvre les changements approuvés au système d’information qui sont contrôlés par la configuration. (E) L’organisation conserve pendant au moins 90 jours les enregistrements des changements apportés au système d’information qui sont contrôlés par la configuration. (F) L’organisation vérifie et examine les activités associées aux changements apportés au système d’information qui sont contrôlés par la configuration. (G) L’organisation coordonne et surveille les activités de contrôle des changements de configuration au moyen d’un processus de communication central comprenant des organismes de gouvernance organisationnelle qui se réunissent au moins une fois par année.
A9: Supplemental Guidance | B9: Configuration change controls for organizational information systems involve the systematic proposal, justification, implementation, testing, review, and disposition of changes to the systems, including system upgrades and modifications. Configuration change control includes changes to baseline configurations for components and configuration items of information systems, changes to configuration settings for information technology products (e.g., operating systems, applications, firewalls, routers, and mobile devices), unscheduled/unauthorized changes, and changes to remediate vulnerabilities. Typical processes for managing configuration changes to information systems include, for example, Configuration Control Boards that approve proposed changes to systems. For new development information systems or systems undergoing major upgrades, organizations consider including representatives from development organizations on the Configuration Control Boards. Auditing of changes includes activities before and after changes are made to organizational information systems and the auditing activities required to implement such changes. Related controls: CA-7, CM-2, CM-4, CM-5, CM-6, CM-9, SA-10, SI-2, SI-12 | D9: Directives supplémentaires | E9: Les contrôles des changements de configuration pour les systèmes d’information organisationnels comprennent la proposition systématique, la justification, la mise en œuvre, les essais, l’examen et la disposition des changements aux systèmes, y compris les mises à niveau et les modifications des systèmes. Le contrôle des changements de configuration comprend les changements apportés aux configurations de base des composants et des éléments de configuration des systèmes d’information, les changements apportés aux paramètres de configuration des produits de technologie de l’information (p. ex., systèmes d’exploitation, applications, pare-feu, routeurs et appareils mobiles), les changements imprévus ou non autorisés et les changements visant à corriger les vulnérabilités. Les processus types de gestion des changements de configuration des systèmes d’information comprennent, par exemple, les comités de contrôle de la configuration qui approuvent les changements proposés aux systèmes. En ce qui concerne les nouveaux systèmes d’information en développement ou les systèmes faisant l’objet de mises à niveau importantes, les organisations envisagent d’inclure des représentants des organisations de développement dans les comités de contrôle de la configuration. La vérification des changements comprend les activités menées avant et après les changements apportés aux systèmes d’information organisationnels et les activités de vérification nécessaires à la mise en œuvre de ces changements. Contrôles connexes : CA-7, CM-2, CM-4, CM-5, CM-6, CM-9, SA-10, SI-2, SI-12
A10: Test Case | D10: Cas de test
A11: Test | B11: TEST-CM-3 | D11: Test | E11: TEST-CM-3
A12: Requirement ID | B12: CM-3 | D12: ID Exigence | E12: CM-3
A13: Component | D13: Composant
A14: Requirement | D14: Exigence
A15: Contextual Design Description | D15: Description contextuelle du design
A16: Evidence Provided | D16: Preuve fournie
A17: Preparer Sign Off (Initials, Date) | D17: Signataire préparateur (Initiales, Date)
A18: Owner Sign Off (Initials, Date) | D18: Signataire propriétaire (Initiales, Date)
A19: Assessor Sign Off (Initials, Date) | D19: Signataire évaluateur (Initiales, Date)
A20: Status | B20: Not Started | D20: Statut | E20: Non commencé
A21: Comments | D21: Commentaires

Sheet CM-5-1
A1: Control CM-5(1) — Evidence Tracking | D1: Contrôle CM-5(1) — Suivi des preuves
A2: Control Information | D2: Informations du contrôle
A3: Control Identifier | B3: CM-5(1) | D3: Identifiant du contrôle | E3: CM-5(1)
A4: Family | B4: Access Restrictions for Change | D4: Famille | E4: Restrictions d’accès pour les changements
A5: Profile | B5: CCCS Medium / PBMM Moderate | D5: Profil | E5: CCCS Moyen / PBMM Modéré
A6: Primary Evidence Tool | D6: Outil de preuve principal
A7: Contributing Tools | D7: Outils contributeurs
A8: Control Description | B8: ACCESS RESTRICTIONS FOR CHANGE | AUTOMATED ACCESS ENFORCEMENT / AUDITING The information system enforces access restrictions and supports auditing of the enforcement actions. | D8: Description du contrôle | E8: RESTRICTIONS D’ACCÈS POUR LES CHANGEMENTS | CONTRÔLE AUTOMATISÉ DE L’ACCÈS/VÉRIFICATION Le système d’information applique les restrictions d’accès et prend en charge la vérification des contrôles appliqués.
A9: Supplemental Guidance | B9: Related controls: AU-2, AU-12, AU-6, CM-3, and CM-6. | D9: Directives supplémentaires | E9: Contrôles connexes : AU-2, AU-12, AU-6, CM-3 et CM-6.
A10: Test Case | D10: Cas de test
A11: Test | B11: TEST-CM-5(1) | D11: Test | E11: TEST-CM-5(1)
A12: Requirement ID | B12: CM-5(1) | D12: ID Exigence | E12: CM-5(1)
A13: Component | D13: Composant
A14: Requirement | D14: Exigence
A15: Contextual Design Description | D15: Description contextuelle du design
A16: Evidence Provided | D16: Preuve fournie
A17: Preparer Sign Off (Initials, Date) | D17: Signataire préparateur (Initiales, Date)
A18: Owner Sign Off (Initials, Date) | D18: Signataire propriétaire (Initiales, Date)
A19: Assessor Sign Off (Initials, Date) | D19: Signataire évaluateur (Initiales, Date)
A20: Status | B20: Not Started | D20: Statut | E20: Non commencé
A21: Comments | D21: Commentaires

Sheet CM-5-6
A1: Control CM-5(6) — Evidence Tracking | D1: Contrôle CM-5(6) — Suivi des preuves
A2: Control Information | D2: Informations du contrôle
A3: Control Identifier | B3: CM-5(6) | D3: Identifiant du contrôle | E3: CM-5(6)
A4: Family | B4: Access Restrictions for Change | D4: Famille | E4: Restrictions d’accès pour les changements
A5: Profile | B5: CCCS Medium / PBMM Moderate | D5: Profil | E5: CCCS Moyen / PBMM Modéré
A6: Primary Evidence Tool | D6: Outil de preuve principal
A7: Contributing Tools | D7: Outils contributeurs
A8: Control Description | B8: ACCESS RESTRICTIONS FOR CHANGE | LIMIT LIBRARY PRIVILEGES The organization limits privileges to change software resident within software libraries. | D8: Description du contrôle | E8: RESTRICTIONS D’ACCÈS POUR LES CHANGEMENTS | LIMITER LES PRIVILÈGES RELATIFS AUX BIBLIOTHÈQUES L’organisation limite les privilèges relatifs aux modifications du logiciel résidant dans les bibliothèques de logiciels.
A9: Supplemental Guidance | B9: Software libraries include privileged programs. Related control: AC-2. | D9: Directives supplémentaires | E9: Les bibliothèques de logiciels comprennent des programmes privilégiés. Contrôle connexe : AC-2.
A10: Test Case | D10: Cas de test
A11: Test | B11: TEST-CM-5(6) | D11: Test | E11: TEST-CM-5(6)
A12: Requirement ID | B12: CM-5(6) | D12: ID Exigence | E12: CM-5(6)
A13: Component | D13: Composant
A14: Requirement | D14: Exigence
A15: Contextual Design Description | D15: Description contextuelle du design
A16: Evidence Provided | D16: Preuve fournie
A17: Preparer Sign Off (Initials, Date) | D17: Signataire préparateur (Initiales, Date)
A18: Owner Sign Off (Initials, Date) | D18: Signataire propriétaire (Initiales, Date)
A19: Assessor Sign Off (Initials, Date) | D19: Signataire évaluateur (Initiales, Date)
A20: Status | B20: Not Started | D20: Statut | E20: Non commencé
A21: Comments | D21: Commentaires

Sheet CM-6
A1: Control CM-6 — Evidence Tracking | D1: Contrôle CM-6 — Suivi des preuves
A2: Control Information | D2: Informations du contrôle
A3: Control Identifier | B3: CM-6 | D3: Identifiant du contrôle | E3: CM-6
A4: Family | B4: Configuration Settings | D4: Famille | E4: Paramètres de configuration
A5: Profile | B5: CCCS Medium / PBMM Moderate | D5: Profil | E5: CCCS Moyen / PBMM Modéré
A6: Primary Evidence Tool | D6: Outil de preuve principal
A7: Contributing Tools | D7: Outils contributeurs
A8: Control Description | B8: (A) The organization establishes and documents configuration settings for information technology products employed within the information system using checklists from one or more of the following Center for Internet Security (CIS), National Institute of Standards and Technology (NIST), Defense Information Systems Agency (DISA) that reflect the most restrictive mode consistent with operational requirements. (B) The organization implements the configuration settings. (C) The organization identifies, documents, and approves any deviations from established configuration settings for any configurable infomation system components. (D) The organization monitors and controls changes to the configuration settings in accordance with organizational policies and procedures. | D8: Description du contrôle | E8: (A) L’organisation établit et documente les paramètres de configuration des produits de technologie de l’information utilisés dans le système d’information à l’aide de listes de vérification provenant d’un ou de plusieurs des éléments suivants : Center for Internet Security (CIS), National Institute of Standards and Technology (NIST), Defense Information Systems Agency (DISA), qui reflètent le mode le plus restrictif conformément aux exigences opérationnelles. (B) L’organisation met en œuvre les paramètres de configuration. (C) L’organisation identifie, documente et approuve tout écart par rapport aux paramètres de configuration établis pour les composants configurables du système d’information. (D) L’organisation surveille et contrôle les changements apportés aux paramètres de configuration conformément aux politiques et aux procédures de l’organisation.
A9: Supplemental Guidance | B9: Configuration settings are the set of parameters that can be changed in hardware, software, or firmware components of the information system that affect the security posture and/or functionality of the system. Information technology products for which security-related configuration settings can be defined include, for example, mainframe computers, servers (e.g., database, electronic mail, authentication, web, proxy, file, domain name), workstations, input/output devices (e.g., scanners, copiers, and printers), network components (e.g., firewalls, routers, gateways, voice and data switches, wireless access points, network appliances, sensors), operating systems, middleware, and applications. Security-related parameters are those parameters impacting the security state of information systems including the parameters required to satisfy other security control requirements. Security-related parameters include, for example: (i) registry settings; (ii) account, file, directory permission settings; and (iii) settings for functions, ports, protocols, services, and remote connections. Organizations establish organization-wide configuration settings and subsequently derive specific settings for information systems. The established settings become part of the systems configuration baselineCommon secure configurations (also referred to as security configuration checklists, lockdown and hardening guides, security reference guides, security technical implementation guides (STIG)) provide recognized, standardized, and established benchmarks that stipulate secure configuration settings for specific information technology platforms/products and instructions for configuring those information system components to meet operational requirements. Common secure configurations can be developed by a variety of organizations including, for example, information technology product developers, manufacturers, vendors, consortia, academia, industry, federal government organizations, and others in the public and private sectors. The Security Content Automation Protocol (SCAP) and the defined standards within the protocol (e.g., Common Configuration Enumeration) provide an effective method to uniquely identify, track, and control configuration settings. Related controls: AC-19, CM-2, CM-3, CM-7, SI-4. | D9: Directives supplémentaires | E9: Les paramètres de configuration sont l’ensemble de paramètres qui peuvent être modifiés dans les composants matériels, logiciels ou micrologiciels du système d’information et qui ont une incidence sur la posture de sécurité ou la fonctionnalité du système. Les produits de technologie de l’information pour lesquels les paramètres de configuration liés à la sécurité peuvent être définis comprennent, par exemple, les ordinateurs centraux, les serveurs (p. ex., base de données, courrier électronique, authentification, Web, mandataire, fichiers, noms de domaine), les postes de travail, les périphériques d’entrée et de sortie (p. ex., numériseurs, photocopieurs et imprimantes), les composants de réseau (p. ex., pare-feu, routeurs, passerelles, commutateurs de voix et de données, points d’accès sans fil, outils de réseau, capteurs), les systèmes d’exploitation, les intergiciels et les applications. Les paramètres liés à la sécurité sont les paramètres qui influent sur l’état de sécurité des systèmes d’information, y compris les paramètres requis pour satisfaire à d’autres exigences de contrôle de sécurité. Les paramètres liés à la sécurité comprennent, par exemple : (i) les paramètres des registres; (ii) les paramètres de comptes, de fichiers, d’autorisation de répertoires; (iii) les paramètres des fonctions, des ports, des protocoles, des services et des connexions à distance. Les organisations établissent les paramètres de configuration à l’échelle de l’organisation et en déduisent ensuite les paramètres particuliers pour les systèmes d’information. Les paramètres établis font partie des configurations de base des systèmes Les configurations sécurisées communes (aussi appelées listes de vérification de la configuration de sécurité, guides de verrouillage et de renforcement, guides de référence de sécurité, guides de mise en œuvre technique de la sécurité [STIG]) fournissent des repères reconnus, normalisés et établis qui stipulent les paramètres de configuration sécurisée pour des plateformes/produits de technologie de l’information particuliers et des instructions pour configurer ces composants de système d’information de manière à répondre aux exigences opérationnelles. Les configurations sécurisées communes peuvent être mises au point par diverses organisations, y compris, par exemple, les concepteurs de produits de technologie de l’information, les fabricants, les fournisseurs, les consortiums, le milieu universitaire, l’industrie, les organisations du gouvernement fédéral et d’autres intervenants des secteurs public et privé. Le protocole d’automatisation du contenu de sécurité SCAP (Security Content Automation Protocol) et les normes définies dans le protocole (p. ex., Common Configuration Enumeration) constituent une méthode efficace pour déterminer, suivre et contrôler de façon unique les paramètres de configuration. Contrôles connexes : AC-19, CM-2, CM-3, CM-7, SI-4.
A10: Test Case | D10: Cas de test
A11: Test | B11: TEST-CM-6 | D11: Test | E11: TEST-CM-6
A12: Requirement ID | B12: CM-6 | D12: ID Exigence | E12: CM-6
A13: Component | D13: Composant
A14: Requirement | D14: Exigence
A15: Contextual Design Description | D15: Description contextuelle du design
A16: Evidence Provided | D16: Preuve fournie
A17: Preparer Sign Off (Initials, Date) | D17: Signataire préparateur (Initiales, Date)
A18: Owner Sign Off (Initials, Date) | D18: Signataire propriétaire (Initiales, Date)
A19: Assessor Sign Off (Initials, Date) | D19: Signataire évaluateur (Initiales, Date)
A20: Status | B20: Not Started | D20: Statut | E20: Non commencé
A21: Comments | D21: Commentaires

Sheet CM-7
A1: Control CM-7 — Evidence Tracking | D1: Contrôle CM-7 — Suivi des preuves
A2: Control Information | D2: Informations du contrôle
A3: Control Identifier | B3: CM-7 | D3: Identifiant du contrôle | E3: CM-7
A4: Family | B4: Least Functionality | D4: Famille | E4: Moindre fonctionnalité
A5: Profile | B5: CCCS Medium / PBMM Moderate | D5: Profil | E5: CCCS Moyen / PBMM Modéré
A6: Primary Evidence Tool | D6: Outil de preuve principal
A7: Contributing Tools | D7: Outils contributeurs
A8: Control Description | B8: (A) The organization configures the information system to provide only essential capabilities. (B) The organization prohibits or restricts the use of identified functions, ports, protocols, and/or services following one or more standards from Center for Internet Security (CIS), National Institute of Standards and Technology (NIST), or Defense Information Systems Agency (DISA). | D8: Description du contrôle | E8: (A) L’organisation configure le système d’information pour n’offrir que les capacités essentielles. (B) L’organisation interdit ou restreint l’utilisation de fonctions, de ports, de protocoles et/ou de services identifiés en respectant une ou plusieurs normes du Center for Internet Security (CIS), du National Institute of Standards and Technology (NIST) ou de la Defense Information Systems Agency (DISA).
A9: Supplemental Guidance | B9: Information systems can provide a wide variety of functions and services. Some of the functions and services, provided by default, may not be necessary to support essential organizational operations (e.g., key missions, functions). Additionally, it is sometimes convenient to provide multiple services from single information system components, but doing so increases risk over limiting the services provided by any one component. Where feasible, organizations limit component functionality to a single function per device (e.g., email servers or web servers, but not both). Organizations review functions and services provided by information systems or individual components of information systems, to determine which functions and services are candidates for elimination (e.g., Voice over Internet Protocol (VoIP), Instant Messaging, auto-execute, and file sharing). Organizations consider disabling unused or unnecessary physical and logical ports/protocols (e.g., USB, FTP, IPv6, HTTP) on information systems to prevent unauthorized connection of devices, unauthorized transfer of information, or unauthorized tunnelling. Organizations can utilize network scanning tools, intrusion detection and prevention systems, and end-point protections such as firewalls and host-based intrusion detection systems to identify and prevent the use of prohibited functions, ports, protocols, and services. Related controls: AC-6, CM-2, RA-5, SA-5, SC-7 | D9: Directives supplémentaires | E9: Les systèmes d’information peuvent offrir une grande variété de fonctions et de services. Certaines fonctions et certains services, fournis par défaut, peuvent ne pas être nécessaires au soutien des opérations essentielles de l’organisation (p. ex., missions et fonctions clés). De plus, il est parfois pratique de fournir plusieurs services à partir de composants uniques du système d’information, mais cela augmente le risque de limiter les services fournis par un seul composant. Dans la mesure du possible, les organisations limitent la fonctionnalité des composants à une seule fonction par dispositif (p. ex., serveurs de courriel ou serveurs Web, mais pas les deux). Les organisations examinent les fonctions et les services fournis par les systèmes d’information ou les composants individuels des systèmes d’information afin de déterminer quelles fonctions et quels services peuvent être éliminés (p. ex., voix sur protocole Internet [VoIP], messagerie instantanée, auto-exécution et partage de fichiers). Les organisations envisagent de désactiver les ports/protocoles physiques et logiques inutilisés ou inutiles (p. ex., USB, FTP, IPv6, HTTP) sur les systèmes d’information afin de prévenir la connexion non autorisée d’appareils, le transfert non autorisé d’information ou la tunnellisation non autorisée. Les organisations peuvent utiliser des outils de balayage de réseau, des systèmes de détection et de prévention des intrusions et des mesures de protection d’extrémité comme des pare-feu et des systèmes de détection des intrusions basés sur l’hôte, pour identifier et prévenir l’utilisation de fonctions, de ports, de protocoles et de services interdits. Contrôles connexes : AC-6, CM-2, RA-5, SA-5, SC-7
A10: Test Case | D10: Cas de test
A11: Test | B11: TEST-CM-7 | D11: Test | E11: TEST-CM-7
A12: Requirement ID | B12: CM-7 | D12: ID Exigence | E12: CM-7
A13: Component | D13: Composant
A14: Requirement | D14: Exigence
A15: Contextual Design Description | D15: Description contextuelle du design
A16: Evidence Provided | D16: Preuve fournie
A17: Preparer Sign Off (Initials, Date) | D17: Signataire préparateur (Initiales, Date)
A18: Owner Sign Off (Initials, Date) | D18: Signataire propriétaire (Initiales, Date)
A19: Assessor Sign Off (Initials, Date) | D19: Signataire évaluateur (Initiales, Date)
A20: Status | B20: Not Started | D20: Statut | E20: Non commencé
A21: Comments | D21: Commentaires

Sheet CM-7-1
A1: Control CM-7(1) — Evidence Tracking | D1: Contrôle CM-7(1) — Suivi des preuves
A2: Control Information | D2: Informations du contrôle
A3: Control Identifier | B3: CM-7(1) | D3: Identifiant du contrôle | E3: CM-7(1)
A4: Family | B4: Least Functionality | D4: Famille | E4: Moindre fonctionnalité
A5: Profile | B5: CCCS Medium / PBMM Moderate | D5: Profil | E5: CCCS Moyen / PBMM Modéré
A6: Primary Evidence Tool | D6: Outil de preuve principal
A7: Contributing Tools | D7: Outils contributeurs
A8: Control Description | B8: LEAST FUNCTIONALITY | PERIODIC REVIEW The organization reviews the information system at least annually to identify unnecessary and/or non-secure functions, ports, protocols, and services; and The organization disables all functions, ports, protocols, and services within the information system deemed to be unnecessary and/or nonsecure. | D8: Description du contrôle | E8: MOINDRE FONCTIONNALITÉ | EXAMEN PÉRIODIQUE L’organisation revoit le système d’information au moins une fois par année afin de repérer les fonctions, les ports, les protocoles et les services inutiles ou non sécurisés; L’organisation désactive toutes les fonctions, tous les ports, tous les protocoles et tous les services du système d’information jugés inutiles ou non sécurisés.
A9: Supplemental Guidance | B9: The organization can either make a determination of the relative security of the function, port, protocol, and/or service or base the security decision on the assessment of other entities. Bluetooth, FTP, and peer-to-peer networking are examples of less than secure protocols. Related controls: AC-18, CM-7, IA-2. | D9: Directives supplémentaires | E9: L’organisation peut soit déterminer la sécurité relative de la fonction, du port, du protocole ou du service, soit baser sa décision en matière de sécurité sur l’évaluation d’autres entités. Bluetooth, FTP et l’interconnexion de réseaux d’égal à égal sont des exemples de protocoles moins sécurisés. Contrôles connexes : AC-18, CM-7, IA-2.
A10: Test Case | D10: Cas de test
A11: Test | B11: TEST-CM-7(1) | D11: Test | E11: TEST-CM-7(1)
A12: Requirement ID | B12: CM-7(1) | D12: ID Exigence | E12: CM-7(1)
A13: Component | D13: Composant
A14: Requirement | D14: Exigence
A15: Contextual Design Description | D15: Description contextuelle du design
A16: Evidence Provided | D16: Preuve fournie
A17: Preparer Sign Off (Initials, Date) | D17: Signataire préparateur (Initiales, Date)
A18: Owner Sign Off (Initials, Date) | D18: Signataire propriétaire (Initiales, Date)
A19: Assessor Sign Off (Initials, Date) | D19: Signataire évaluateur (Initiales, Date)
A20: Status | B20: Not Started | D20: Statut | E20: Non commencé
A21: Comments | D21: Commentaires

Sheet CP-10
A1: Control CP-10 — Evidence Tracking | D1: Contrôle CP-10 — Suivi des preuves
A2: Control Information | D2: Informations du contrôle
A3: Control Identifier | B3: CP-10 | D3: Identifiant du contrôle | E3: CP-10
A4: Family | B4: Information System Recovery and Reconstitution | D4: Famille | E4: Reprise et reconstitution du système d’information
A5: Profile | B5: CCCS Medium / PBMM Moderate | D5: Profil | E5: CCCS Moyen / PBMM Modéré
A6: Primary Evidence Tool | D6: Outil de preuve principal
A7: Contributing Tools | D7: Outils contributeurs
A8: Control Description | B8: (A) The organization provides for the recovery and reconstitution of the information system to a known state after a disruption, compromise, or failure. | D8: Description du contrôle | E8: (A) L’organisation assure la reprise et la reconstitution du système d’information dans un état connu après une perturbation, une compromission ou une défaillance.
A9: Supplemental Guidance | B9: Recovery is executing information system contingency plan activities to restore organizational missions/business functions. Reconstitution takes place following recovery and includes activities for returning organizational information systems to fully operational states. Recovery and reconstitution operations reflect mission and business priorities, recovery point/time and reconstitution objectives, and established organizational metrics consistent with contingency plan requirements. Reconstitution includes the deactivation of any interim information system capabilities that may have been needed during recovery operations. Reconstitution also includes assessments of fully restored information system capabilities, reestablishment of continuous monitoring activities, potential information system reauthorizations, and activities to prepare the systems against future disruptions, compromises, or failures. Recovery/reconstitution capabilities employed by organizations can include both automated mechanisms and manual procedures. Related controls: CA-2, CA-6, CA-7, CP-2, CP-4, CP-6, CP-7, CP-9, SC-24 | D9: Directives supplémentaires | E9: La reprise consiste à exécuter les activités du plan d’urgence du système d’information pour restaurer les fonctions opérationnelles et de mission de l’organisation. La reconstitution a lieu après la reprise et comprend les activités permettant de remettre les systèmes d’information organisationnels à l’état pleinement opérationnel. Les opérations de reprise et de reconstitution reflètent les priorités opérationnelles et de mission, les objectifs en matière de délais, de points de reprise et de reconstitution, de même que les paramètres organisationnels établis conformément aux exigences du plan d’urgence. La reconstitution comprend la désactivation de toute capacité provisoire du système d’information ayant pu être nécessaire pendant les opérations de reprise. La reconstitution comprend également l’évaluation des capacités entièrement restaurées du système d’information, le rétablissement des activités de surveillance continue, les réautorisations possibles du système d’information et les activités visant à préparer les systèmes à faire face aux perturbations, compromissions ou défaillances futures. Les capacités de reprise et de reconstitution utilisées par les organisations peuvent comprendre des mécanismes automatisés et des procédures manuelles. Contrôles connexes : CA-2, CA-6, CA-7, CP-2, CP-4, CP-6, CP-7, CP-9, SC-24
A10: Test Case | D10: Cas de test
A11: Test | B11: TEST-CP-10 | D11: Test | E11: TEST-CP-10
A12: Requirement ID | B12: CP-10 | D12: ID Exigence | E12: CP-10
A13: Component | D13: Composant
A14: Requirement | D14: Exigence
A15: Contextual Design Description | D15: Description contextuelle du design
A16: Evidence Provided | D16: Preuve fournie
A17: Preparer Sign Off (Initials, Date) | D17: Signataire préparateur (Initiales, Date)
A18: Owner Sign Off (Initials, Date) | D18: Signataire propriétaire (Initiales, Date)
A19: Assessor Sign Off (Initials, Date) | D19: Signataire évaluateur (Initiales, Date)
A20: Status | B20: Not Started | D20: Statut | E20: Non commencé
A21: Comments | D21: Commentaires

Sheet CP-10-4
A1: Control CP-10(4) — Evidence Tracking | D1: Contrôle CP-10(4) — Suivi des preuves
A2: Control Information | D2: Informations du contrôle
A3: Control Identifier | B3: CP-10(4) | D3: Identifiant du contrôle | E3: CP-10(4)
A4: Family | B4: Information System Recovery and Reconstitution | D4: Famille | E4: Reprise et reconstitution du système d’information
A5: Profile | B5: CCCS Medium / PBMM Moderate | D5: Profil | E5: CCCS Moyen / PBMM Modéré
A6: Primary Evidence Tool | D6: Outil de preuve principal
A7: Contributing Tools | D7: Outils contributeurs
A8: Control Description | B8: INFORMATION SYSTEM RECOVERY AND RECONSTITUTION | RESTORE WITHIN TIME PERIOD The organization provides the capability to restore information system components within organization-defined restoration time-periods from configuration-controlled and integrity-protected information representing a known, operational state for the components. | D8: Description du contrôle | E8: REPRISE ET RECONSTITUTION DU SYSTÈME D’INFORMATION | RESTAURATION DANS LE DÉLAI IMPARTI L’organisation fournit la capacité de restaurer les composants du système d’information dans les délais de restauration définis par l’organisation à partir de l’information contrôlée par la configuration et protégée par l’intégrité qui représente un état de fonctionnement connu pour les composants.
A9: Supplemental Guidance | B9: Restoration of information system components includes, for example, re-imaging which restores components to known, operational states. Related control: CM-2. | D9: Directives supplémentaires | E9: La restauration des composants du système d’information comprend, par exemple, la reconfiguration permettant de restaurer les composants aux états de fonctionnement connus. Contrôle connexe : CM-2.
A10: Test Case | D10: Cas de test
A11: Test | B11: TEST-CP-10(4) | D11: Test | E11: TEST-CP-10(4)
A12: Requirement ID | B12: CP-10(4) | D12: ID Exigence | E12: CP-10(4)
A13: Component | D13: Composant
A14: Requirement | D14: Exigence
A15: Contextual Design Description | D15: Description contextuelle du design
A16: Evidence Provided | D16: Preuve fournie
A17: Preparer Sign Off (Initials, Date) | D17: Signataire préparateur (Initiales, Date)
A18: Owner Sign Off (Initials, Date) | D18: Signataire propriétaire (Initiales, Date)
A19: Assessor Sign Off (Initials, Date) | D19: Signataire évaluateur (Initiales, Date)
A20: Status | B20: Not Started | D20: Statut | E20: Non commencé
A21: Comments | D21: Commentaires

Sheet IA-5-7
A1: Control IA-5(7) — Evidence Tracking | D1: Contrôle IA-5(7) — Suivi des preuves
A2: Control Information | D2: Informations du contrôle
A3: Control Identifier | B3: IA-5(7) | D3: Identifiant du contrôle | E3: IA-5(7)
A4: Family | B4: Authenticator Management | D4: Famille | E4: Gestion des authentifiants
A5: Profile | B5: CCCS Medium / PBMM Moderate | D5: Profil | E5: CCCS Moyen / PBMM Modéré
A6: Primary Evidence Tool | D6: Outil de preuve principal
A7: Contributing Tools | D7: Outils contributeurs
A8: Control Description | B8: AUTHENTICATOR MANAGEMENT | NO EMBEDDED UNENCRYPTED STATIC AUTHENTICATORS The organization ensures that unencrypted static authenticators are not embedded in applications or access scripts or stored on function keys. | D8: Description du contrôle | E8: GESTION DES AUTHENTIFIANTS | AUCUN AUTHENTIFIANT STATIQUE INTÉGRÉ NON CHIFFRÉ L’organisation veille à ce que les authentifiants statiques non chiffrés ne soient pas intégrés dans les applications ou les scripts d’accès ou stockés sur les clés de fonction.
A9: Supplemental Guidance | B9: Organizations exercise caution in determining whether embedded or stored authenticators are in encrypted or unencrypted form. If authenticators are used in the manner stored, then those representations are considered unencrypted authenticators. This is irrespective of whether that representation is perhaps an encrypted version of something else (e.g., a password). | D9: Directives supplémentaires | E9: Les organisations usent de prudence lorsqu’il s’agit de déterminer si les authentifiants intégrés ou stockés sont chiffrés ou non chiffrés. Si les authentifiants sont utilisés sous leur forme stockée, ces représentations sont alors considérées comme étant des authentifiants non chiffrés. Cela n’a rien à voir avec le fait que cette représentation puisse être une version chiffrée de quelque chose d’autre (p. ex., un mot de passe).
A10: Test Case | D10: Cas de test
A11: Test | B11: TEST-IA-5(7) | D11: Test | E11: TEST-IA-5(7)
A12: Requirement ID | B12: IA-5(7) | D12: ID Exigence | E12: IA-5(7)
A13: Component | D13: Composant
A14: Requirement | D14: Exigence
A15: Contextual Design Description | D15: Description contextuelle du design
A16: Evidence Provided | D16: Preuve fournie
A17: Preparer Sign Off (Initials, Date) | D17: Signataire préparateur (Initiales, Date)
A18: Owner Sign Off (Initials, Date) | D18: Signataire propriétaire (Initiales, Date)
A19: Assessor Sign Off (Initials, Date) | D19: Signataire évaluateur (Initiales, Date)
A20: Status | B20: Not Started | D20: Statut | E20: Non commencé
A21: Comments | D21: Commentaires

Sheet MA-4
A1: Control MA-4 — Evidence Tracking | D1: Contrôle MA-4 — Suivi des preuves
A2: Control Information | D2: Informations du contrôle
A3: Control Identifier | B3: MA-4 | D3: Identifiant du contrôle | E3: MA-4
A4: Family | B4: Non-Local Maintenance | D4: Famille | E4: Maintenance non locale
A5: Profile | B5: CCCS Medium / PBMM Moderate | D5: Profil | E5: CCCS Moyen / PBMM Modéré
A6: Primary Evidence Tool | D6: Outil de preuve principal
A7: Contributing Tools | D7: Outils contributeurs
A8: Control Description | B8: (A) The organization approves and monitors nonlocal maintenance and diagnostic activities. (B) The organization allows the use of non-local maintenance and diagnostic tools only as consistent with organizational policy and as documented in the security plan for the information system. (C) The organization employs strong authenticators in the establishment of nonlocal maintenance and diagnostic sessions. (D) The organization maintains records for nonlocal maintenance and diagnostic activities. | D8: Description du contrôle | E8: (A) L’organisation approuve et surveille les activités de maintenance et de diagnostic non locales. (B) L’organisation ne permet l’utilisation d’outils de maintenance et de diagnostic non locaux que dans la mesure où ils sont conformes à la politique de l’organisation et documentés dans le plan de sécurité du système d’information. (C) L’organisation utilise des authentifiants puissants pour les ouvertures de sessions de maintenance et de diagnostic non locales. (D) L’organisation tient des registres pour les activités de maintenance et de diagnostic non locales.
A9: Supplemental Guidance | B9: Nonlocal maintenance and diagnostic activities are those activities conducted by individuals communicating through a network, either an external network (e.g., the Internet) or an internal network. Local maintenance and diagnostic activities are those activities carried out by individuals physically present at the information system or information system component and not communicating across a network connection. Authentication techniques used in the establishment of nonlocal maintenance and diagnostic sessions reflect the network access requirements in IA-2. Typically, strong authentication requires authenticators that are resistant to replay attacks and employ multifactor authentication. Strong authenticators include, for example, PKI where certificates are stored on a token protected by a password, passphrase, or biometric. Enforcing requirements in MA-4 is accomplished in part by other controls. Related controls: AC-2, AC-3, AC-6, AC-17, AU-2, AU-3, IA-2, IA-4, IA-5, IA-8, MA-2, MA-5, MP-6, PL-2, SC-7, SC-10, SC-17 | D9: Directives supplémentaires | E9: Les activités de maintenance et de diagnostic non locales sont des activités menées par des personnes qui communiquent par l’entremise d’un réseau externe (p. ex., Internet) ou interne. Les activités de maintenance et de diagnostic locales sont les activités menées par des personnes physiquement présentes sur les lieux du système d’information ou du composant du système d’information et qui ne communiquent pas au moyen d’une connexion réseau. Les techniques d’authentification utilisées pour les ouvertures de sessions de maintenance et de diagnostic non locales reflètent les exigences d’accès au réseau dans IA-2. En règle générale, une authentification forte nécessite des authentifiants qui résistent aux attaques par réinsertion et utilisent l’authentification multifactorielle. Les authentifiants puissants comprennent, par exemple, l’ICP, où les certificats sont stockés sur un jeton protégé par un mot de passe, une phrase de passe ou des données biométriques. L’application des exigences du contrôle MA-4 est assurée en partie par d’autres contrôles. Contrôles connexes : AC-2, AC-3, AC-6, AC-17, AU-2, AU-3, IA-2, IA-4, IA-5, IA-8, MA-2, MA-5, MP-6, PL-2, SC-7, SC-10, SC-17
A10: Test Case | D10: Cas de test
A11: Test | B11: TEST-MA-4 | D11: Test | E11: TEST-MA-4
A12: Requirement ID | B12: MA-4 | D12: ID Exigence | E12: MA-4
A13: Component | D13: Composant
A14: Requirement | D14: Exigence
A15: Contextual Design Description | D15: Description contextuelle du design
A16: Evidence Provided | D16: Preuve fournie
A17: Preparer Sign Off (Initials, Date) | D17: Signataire préparateur (Initiales, Date)
A18: Owner Sign Off (Initials, Date) | D18: Signataire propriétaire (Initiales, Date)
A19: Assessor Sign Off (Initials, Date) | D19: Signataire évaluateur (Initiales, Date)
A20: Status | B20: Not Started | D20: Statut | E20: Non commencé
A21: Comments | D21: Commentaires

Sheet MA-4-1
A1: Control MA-4(1) — Evidence Tracking | D1: Contrôle MA-4(1) — Suivi des preuves
A2: Control Information | D2: Informations du contrôle
A3: Control Identifier | B3: MA-4(1) | D3: Identifiant du contrôle | E3: MA-4(1)
A4: Family | B4: Non-Local Maintenance | D4: Famille | E4: Maintenance non locale
A5: Profile | B5: CCCS Medium / PBMM Moderate | D5: Profil | E5: CCCS Moyen / PBMM Modéré
A6: Primary Evidence Tool | D6: Outil de preuve principal
A7: Contributing Tools | D7: Outils contributeurs
A8: Control Description | B8: NONLOCAL MAINTENANCE | AUDITING AND REVIEW (a) The organization audits nonlocal maintenance and diagnostic sessions as defined in the organizations formal audit policy (AU-2, AU-6, AU-12); and (b) The organization reviews the records of the maintenance and diagnostic sessions. | D8: Description du contrôle | E8: MAINTENANCE NON LOCALE | VÉRIFICATION ET EXAMEN (a) L’organisation vérifie les sessions de maintenance et de diagnostic non locales telles que définies dans la politique de vérification officielle de l’organisation (AU-2, AU-6, AU-12); (b) L’organisation examine les enregistrements des sessions de maintenance et de diagnostic.
A9: Supplemental Guidance | B9: Related controls: AU-2, AU-6, AU-12. | D9: Directives supplémentaires | E9: Contrôles connexes : AU-2, AU-6, AU-12.
A10: Test Case | D10: Cas de test
A11: Test | B11: TEST-MA-4(1) | D11: Test | E11: TEST-MA-4(1)
A12: Requirement ID | B12: MA-4(1) | D12: ID Exigence | E12: MA-4(1)
A13: Component | D13: Composant
A14: Requirement | D14: Exigence
A15: Contextual Design Description | D15: Description contextuelle du design
A16: Evidence Provided | D16: Preuve fournie
A17: Preparer Sign Off (Initials, Date) | D17: Signataire préparateur (Initiales, Date)
A18: Owner Sign Off (Initials, Date) | D18: Signataire propriétaire (Initiales, Date)
A19: Assessor Sign Off (Initials, Date) | D19: Signataire évaluateur (Initiales, Date)
A20: Status | B20: Not Started | D20: Statut | E20: Non commencé
A21: Comments | D21: Commentaires

Sheet SA-9-5
A1: Control SA-9(5) — Evidence Tracking | D1: Contrôle SA-9(5) — Suivi des preuves
A2: Control Information | D2: Informations du contrôle
A3: Control Identifier | B3: SA-9(5) | D3: Identifiant du contrôle | E3: SA-9(5)
A4: Family | B4: External Information System Services | D4: Famille | E4: Services de systèmes d’information externes
A5: Profile | B5: CCCS Medium / PBMM Moderate | D5: Profil | E5: CCCS Moyen / PBMM Modéré
A6: Primary Evidence Tool | D6: Outil de preuve principal
A7: Contributing Tools | D7: Outils contributeurs
A8: Control Description | B8: EXTERNAL INFORMATION SYSTEMS | PROCESSING, STORAGE, AND SERVICE LOCATION The organization restricts the location of information processing, information/data, and information system services to locations witihin Canada based on ITPIN 2017-02 for Direction on Data Residency (https://www.canada.ca/en/treasury-board-secretariat/services/information-technology/policy-implementation-notices/direction-electronic-data-residency.html). | D8: Description du contrôle | E8: SYSTÈMES D’INFORMATION EXTERNES | EMPLACEMENT DU TRAITEMENT, DU STOCKAGE ET DES SERVICES L’organisation restreint la résidence du traitement de l’information, du stockage de l’information et des données, ainsi que des services de systèmes d’information aux endroits situés à l’intérieur du Canada, conformément à l’avis AMPTI 2017-02, Orientation relative à la résidence des données électroniques (https://www.canada.ca/fr/gouvernement/systeme/gouvernement-numerique/technologiques-modernes-nouveaux/orientation-relative-residence-donnees-electroniques.html).
A9: Supplemental Guidance | B9: The location of information processing, information/data storage, or information system services that are critical to organizations can have a direct impact on the ability of those organizations to successfully execute their missions/business functions. This situation exists when external providers control the location of processing, storage or services. The criteria external providers use for the selection of processing, storage, or service locations may be different from organizational criteria. For example, organizations may want to ensure that data/information storage locations are restricted to certain locations to facilitate incident response activities (e.g., forensic analyses, after-the-fact investigations) in case of information security breaches/compromises. Such incident response activities may be adversely affected by the governing laws or protocols in the locations where processing and storage occur and/or the locations from which information system services emanate. | D9: Directives supplémentaires | E9: L’emplacement des services de traitement de l’information et de stockage de l’information et des données ou des services de systèmes d’information qui sont essentiels pour les organisations peut avoir une incidence directe sur la capacité de ces organisations d’exécuter avec succès leurs fonctions opérationnelles et de mission. Cette situation existe lorsque des fournisseurs externes contrôlent l’emplacement du traitement, de l’entreposage ou des services. Les critères utilisés par les fournisseurs externes pour choisir les lieux de traitement, d’entreposage ou de service peuvent être différents des critères de l’organisation. Par exemple, les organisations pourraient vouloir s’assurer que les emplacements de stockage des données ou de l’information se limitent à certains endroits afin de faciliter les activités d’intervention (p. ex., analyses judiciaires, enquêtes après coup) en cas d’incident représentant une atteinte à, ou une compromission de la sécurité de l’information. Ces activités d’intervention en cas d’incident peuvent être affectées négativement par les lois ou les protocoles en vigueur aux endroits où le traitement et l’entreposage ont lieu ou aux endroits d’où proviennent les services de systèmes d’information.
A10: Test Case | D10: Cas de test
A11: Test | B11: TEST-SA-9(5) | D11: Test | E11: TEST-SA-9(5)
A12: Requirement ID | B12: SA-9(5) | D12: ID Exigence | E12: SA-9(5)
A13: Component | D13: Composant
A14: Requirement | D14: Exigence
A15: Contextual Design Description | D15: Description contextuelle du design
A16: Evidence Provided | D16: Preuve fournie
A17: Preparer Sign Off (Initials, Date) | D17: Signataire préparateur (Initiales, Date)
A18: Owner Sign Off (Initials, Date) | D18: Signataire propriétaire (Initiales, Date)
A19: Assessor Sign Off (Initials, Date) | D19: Signataire évaluateur (Initiales, Date)
A20: Status | B20: Not Started | D20: Statut | E20: Non commencé
A21: Comments | D21: Commentaires

Sheet SA-11-1
A1: Control SA-11(1) — Evidence Tracking | D1: Contrôle SA-11(1) — Suivi des preuves
A2: Control Information | D2: Informations du contrôle
A3: Control Identifier | B3: SA-11(1) | D3: Identifiant du contrôle | E3: SA-11(1)
A4: Family | B4: Developer Security Testing | D4: Famille | E4: Essais de sécurité du développeur
A5: Profile | B5: CCCS Medium / PBMM Moderate | D5: Profil | E5: CCCS Moyen / PBMM Modéré
A6: Primary Evidence Tool | D6: Outil de preuve principal
A7: Contributing Tools | D7: Outils contributeurs
A8: Control Description | B8: DEVELOPER SECURITY TESTING AND EVALUATION | STATIC CODE ANALYSIS The organization requires the developer of the information system, system component, or information system service to employ static code analysis tools to identify common flaws and document the results of the analysis. | D8: Description du contrôle | E8: ESSAIS ET ÉVALUATION DE LA SÉCURITÉ PAR LE DÉVELOPPEUR | ANALYSE DU CODE STATIQUE L’organisation exige que le développeur du système d’information, du composant du système ou du service du système d’information utilise des outils d’analyse du code statique pour repérer les défauts courants et documenter les résultats de l’analyse.
A9: Supplemental Guidance | B9: Static code analysis provides a technology and methodology for security reviews. Such analysis can be used to identify security vulnerabilities and enforce security coding practices. Static code analysis is most effective when used early in the development process, when each code change can be automatically scanned for potential weaknesses. Static analysis can provide clear remediation guidance along with defects to enable developers to fix such defects. Evidence of correct implementation of static analysis can include, for example, aggregate defect density for critical defect types, evidence that defects were inspected by developers or security professionals, and evidence that defects were fixed. An excessively high density of ignored findings (commonly referred to as ignored or false positives) indicates a potential problem with the analysis process or tool. In such cases, organizations weigh the validity of the evidence against evidence from other sources. | D9: Directives supplémentaires | E9: L’analyse du code statique fournit une technologie et une méthodologie pour les examens de sécurité. Une telle analyse peut servir à déterminer les vulnérabilités en matière de sécurité et à appliquer les pratiques de codage de sécurité. L’analyse du code statique sera plus efficace si elle est utilisée tôt dans le processus de développement, alors que chaque changement de code peut automatiquement être soumis à un balayage permettant de déceler les faiblesses potentielles. L’analyse statique peut fournir des directives claires sur les mesures correctives ainsi que sur les défauts afin de permettre aux développeurs de corriger ces défauts. Les preuves de la mise en œuvre correcte de l’analyse statique peuvent comprendre, par exemple, la densité globale des défauts pour les types de défauts critiques, des preuves que les défauts ont été inspectés par des développeurs ou des professionnels de la sécurité, et des preuves que les défauts ont été corrigés. Une densité excessivement élevée de résultats ignorés (communément appelés faux positifs) indique un problème potentiel avec le processus ou l’outil d’analyse. Dans de tels cas, les organisations évaluent la validité de la preuve par rapport à celle d’autres sources.
A10: Test Case | D10: Cas de test
A11: Test | B11: TEST-SA-11(1) | D11: Test | E11: TEST-SA-11(1)
A12: Requirement ID | B12: SA-11(1) | D12: ID Exigence | E12: SA-11(1)
A13: Component | D13: Composant
A14: Requirement | D14: Exigence
A15: Contextual Design Description | D15: Description contextuelle du design
A16: Evidence Provided | D16: Preuve fournie
A17: Preparer Sign Off (Initials, Date) | D17: Signataire préparateur (Initiales, Date)
A18: Owner Sign Off (Initials, Date) | D18: Signataire propriétaire (Initiales, Date)
A19: Assessor Sign Off (Initials, Date) | D19: Signataire évaluateur (Initiales, Date)
A20: Status | B20: Not Started | D20: Statut | E20: Non commencé
A21: Comments | D21: Commentaires

Sheet SA-11-8
A1: Control SA-11(8) — Evidence Tracking | D1: Contrôle SA-11(8) — Suivi des preuves
A2: Control Information | D2: Informations du contrôle
A3: Control Identifier | B3: SA-11(8) | D3: Identifiant du contrôle | E3: SA-11(8)
A4: Family | B4: Developer Security Testing | D4: Famille | E4: Essais de sécurité du développeur
A5: Profile | B5: CCCS Medium / PBMM Moderate | D5: Profil | E5: CCCS Moyen / PBMM Modéré
A6: Primary Evidence Tool | D6: Outil de preuve principal
A7: Contributing Tools | D7: Outils contributeurs
A8: Control Description | B8: DEVELOPER SECURITY TESTING AND EVALUATION | DYNAMIC CODE ANALYSIS The organization requires the developer of the information system, system component, or information system service to employ dynamic code analysis tools to identify common flaws and document the results of the analysis. | D8: Description du contrôle | E8: ESSAIS ET ÉVALUATION DE LA SÉCURITÉ PAR LE DÉVELOPPEUR | ANALYSE DU CODE DYNAMIQUE L’organisation exige que le développeur du système d’information, du composant du système ou du service du système d’information utilise des outils d’analyse du code dynamique pour repérer les vulnérabilités courantes et documenter les résultats de l’analyse.
A9: Supplemental Guidance | B9: Dynamic code analysis provides run-time verification of software programs, using tools capable of monitoring programs for memory corruption, user privilege issues, and other potential security problems. Dynamic code analysis employs run-time tools to help to ensure that security functionality performs in the manner in which it was designed. A specialized type of dynamic analysis, known as fuzz testing, induces program failures by deliberately introducing malformed or random data into software programs. Fuzz testing strategies derive from the intended use of applications and the functional and design specifications for the applications. To understand the scope of dynamic code analysis and hence the assurance provided, organizations may also consider conducting code coverage analysis (checking the degree to which the code has been tested using metrics such as percent of subroutines tested or percent of program statements called during execution of the test suite) and/or concordance analysis. | D9: Directives supplémentaires | E9: L’analyse du code dynamique permet de vérifier le temps d’exécution des programmes logiciels à l’aide d’outils capables de surveiller les programmes en ce qui a trait à la corruption de la mémoire, aux problèmes liés aux privilèges d’utilisateur et à d’autres problèmes de sécurité potentiels. L’analyse dynamique du code fait appel à des outils à l’exécution pour s’assurer que les fonctionnalités de sécurité fonctionnent de la façon dont elles ont été conçues. Un type spécialisé d’analyse dynamique, connu sous le nom de test à données aléatoires (fuzz testing), induit des échecs du programme en introduisant délibérément des données erronées ou aléatoires dans des programmes logiciels. Les stratégies de test à données aléatoires déployées dépendent de l’utilisation prévue des applications et des spécifications fonctionnelles et de conception pour les applications. Pour comprendre la portée de l’analyse dynamique du code et, par conséquent, l’assurance fournie, les organisations peuvent également envisager d’effectuer une analyse de la couverture du code (en vérifiant la mesure dans laquelle le code a été mis à l’essai à l’aide de paramètres comme le pourcentage des sous-programmes testés ou le pourcentage des instructions du programme appelées pendant l’exécution de la série d’essais) ou une analyse de concordance.
A10: Test Case | D10: Cas de test
A11: Test | B11: TEST-SA-11(8) | D11: Test | E11: TEST-SA-11(8)
A12: Requirement ID | B12: SA-11(8) | D12: ID Exigence | E12: SA-11(8)
A13: Component | D13: Composant
A14: Requirement | D14: Exigence
A15: Contextual Design Description | D15: Description contextuelle du design
A16: Evidence Provided | D16: Preuve fournie
A17: Preparer Sign Off (Initials, Date) | D17: Signataire préparateur (Initiales, Date)
A18: Owner Sign Off (Initials, Date) | D18: Signataire propriétaire (Initiales, Date)
A19: Assessor Sign Off (Initials, Date) | D19: Signataire évaluateur (Initiales, Date)
A20: Status | B20: Not Started | D20: Statut | E20: Non commencé
A21: Comments | D21: Commentaires

Sheet SC-7
A1: Control SC-7 — Evidence Tracking | D1: Contrôle SC-7 — Suivi des preuves
A2: Control Information | D2: Informations du contrôle
A3: Control Identifier | B3: SC-7 | D3: Identifiant du contrôle | E3: SC-7
A4: Family | B4: Boundary Protection | D4: Famille | E4: Protection des frontières
A5: Profile | B5: CCCS Medium / PBMM Moderate | D5: Profil | E5: CCCS Moyen / PBMM Modéré
A6: Primary Evidence Tool | D6: Outil de preuve principal
A7: Contributing Tools | D7: Outils contributeurs
A8: Control Description | B8: (A) The information system monitors and controls communications at the external boundary of the system and at key internal boundaries within the system. (B) The information system implements sub-networks for publicly accessible system components that are physically or logically separated from internal organizational networks. (C) The information system connects to external networks or information systems only through managed interfaces consisting of boundary protection devices arranged in accordance with an organizational security architecture. | D8: Description du contrôle | E8: (A) Le système d’information surveille et contrôle les communications à la frontière externe du système et aux frontières internes clés du système. (B) Le système d’information met en œuvre des sous-réseaux pour des composants du système accessibles au public qui sont physiquement ou logiquement séparés des réseaux organisationnels internes. (C) Le système d’information ne se connecte à des réseaux ou à des systèmes d’information externes que par des interfaces gérées comprenant des dispositifs de protection des frontières organisés conformément à une architecture de sécurité organisationnelle.
A9: Supplemental Guidance | B9: Managed interfaces include, for example, gateways, routers, firewalls, guards, network-based malicious code analysis and virtualization systems, or encrypted tunnels implemented within a security architecture (e.g., routers protecting firewalls or application gateways residing on protected sub-networks). Sub-networks that are physically or logically separated from internal networks are referred to as demilitarized zones or DMZs. Restricting or prohibiting interfaces within organizational information systems includes, for example, restricting external web traffic to designated web servers within managed interfaces and prohibiting external traffic that appears to be spoofing internal addresses. Organizations consider the shared nature of commercial telecommunications services in the implementation of security controls associated with the use of such services. Commercial telecommunications services are commonly based on network components and consolidated management systems shared by all attached commercial customers, and may also include third party-provided access lines and other service elements. Such transmission services may represent sources of increased risk despite contract security provisions. Related controls: AC-4, AC-17, CA-3, CM-7, CP-8, IR-4, RA-3, SC-5, SC-13 | D9: Directives supplémentaires | E9: Les interfaces gérées comprennent, par exemple, les passerelles, les routeurs, les pare-feu, les gardiens, les systèmes d’analyse et de virtualisation de codes malveillants basés sur le réseau, ou les tunnels chiffrés mis en œuvre dans une architecture de sécurité (p. ex., les routeurs protégeant les pare-feu ou les passerelles d’application résidant sur des sous-réseaux protégés). Les sous-réseaux qui sont physiquement ou logiquement séparés des réseaux internes sont appelés « zones démilitarisées » ou « ZD ». La restriction ou l’interdiction des interfaces dans les systèmes d’information de l’organisation comprend, par exemple, la restriction du trafic Web externe aux serveurs Web désignés dans les interfaces gérées et l’interdiction du trafic externe qui semble usurper les adresses internes. Les organisations tiennent compte de la nature commune des services de télécommunications commerciaux dans la mise en œuvre des contrôles de sécurité associés à l’utilisation de tels services. Les services de télécommunications commerciaux sont généralement fondés sur des composants de réseau et des systèmes de gestion consolidés partagés par tous les clients commerciaux attenants, et peuvent également comprendre des lignes d’accès fournies par des tiers et d’autres éléments de service. Ces services de transmission peuvent représenter des sources de risque accru malgré les dispositions relatives à la sécurité dans les contrats. Contrôles connexes : AC-4, AC-17, CA-3, CM-7, CP-8, IR-4, RA-3, SC-5, SC-13
A10: Test Case | D10: Cas de test
A11: Test | B11: TEST-SC-7 | D11: Test | E11: TEST-SC-7
A12: Requirement ID | B12: SC-7 | D12: ID Exigence | E12: SC-7
A13: Component | D13: Composant
A14: Requirement | D14: Exigence
A15: Contextual Design Description | D15: Description contextuelle du design
A16: Evidence Provided | D16: Preuve fournie
A17: Preparer Sign Off (Initials, Date) | D17: Signataire préparateur (Initiales, Date)
A18: Owner Sign Off (Initials, Date) | D18: Signataire propriétaire (Initiales, Date)
A19: Assessor Sign Off (Initials, Date) | D19: Signataire évaluateur (Initiales, Date)
A20: Status | B20: Not Started | D20: Statut | E20: Non commencé
A21: Comments | D21: Commentaires

Sheet SC-18
A1: Control SC-18 — Evidence Tracking | D1: Contrôle SC-18 — Suivi des preuves
A2: Control Information | D2: Informations du contrôle
A3: Control Identifier | B3: SC-18 | D3: Identifiant du contrôle | E3: SC-18
A4: Family | B4: Mobile Code | D4: Famille | E4: Code mobile
A5: Profile | B5: CCCS Medium / PBMM Moderate | D5: Profil | E5: CCCS Moyen / PBMM Modéré
A6: Primary Evidence Tool | D6: Outil de preuve principal
A7: Contributing Tools | D7: Outils contributeurs
A8: Control Description | B8: (A) The organization defines acceptable and unacceptable mobile code and mobile code technologies. (B) The organization establishes usage restrictions and implementation guidance for acceptable mobile code and mobile code technologies. (C) The organization authorizes, monitors, and controls the use of mobile code within the information system. | D8: Description du contrôle | E8: (A) L’organisation définit les codes mobiles et les technologies de codes mobiles acceptables et inacceptables. (B) L’organisation établit des restrictions d’utilisation et des directives de mise en œuvre pour le code mobile et les technologies de code mobile acceptables. (C) L’organisation autorise, surveille et contrôle l’utilisation du code mobile dans le système d’information.
A9: Supplemental Guidance | B9: Decisions regarding the employment of mobile code within organizational information systems are based on the potential for the code to cause damage to the systems if used maliciously. Mobile code technologies include, for example, Java, JavaScript, ActiveX, Postscript, PDF, Shockwave movies, Flash animations, and VBScript. Usage restrictions and implementation guidance apply to both the selection and use of mobile code installed on servers and mobile code downloaded and executed on individual workstations and devices (e.g., smart phones). Mobile code policy and procedures address preventing the development, acquisition, or introduction of unacceptable mobile code within organizational information systems. Related controls: AU-2, AU-12, CM-2, CM-6, SI-3 | D9: Directives supplémentaires | E9: Les décisions concernant l’utilisation du code mobile dans les systèmes d’information de l’organisation sont basées sur le potentiel de dommages causés aux systèmes si le code est utilisé de façon malveillante. Les technologies de code mobile comprennent, par exemple, Java, JavaScript, ActiveX, Postcript, PDF, les films Shockwave, les animations Flash et VBScript. Les restrictions d’utilisation et les directives de mise en œuvre s’appliquent à la fois à la sélection et à l’utilisation du code mobile installé sur les serveurs et du code mobile téléchargé et exécuté sur des postes de travail et des appareils individuels (p. ex., téléphones intelligents). La politique et les procédures relatives au code mobile visent à prévenir l’élaboration, l’acquisition ou l’introduction de code mobile inacceptable dans les systèmes d’information de l’organisation. Contrôles connexes : AU-2, AU-12, CM-2, CM-6, SI-3
A10: Test Case | D10: Cas de test
A11: Test | B11: TEST-SC-18 | D11: Test | E11: TEST-SC-18
A12: Requirement ID | B12: SC-18 | D12: ID Exigence | E12: SC-18
A13: Component | D13: Composant
A14: Requirement | D14: Exigence
A15: Contextual Design Description | D15: Description contextuelle du design
A16: Evidence Provided | D16: Preuve fournie
A17: Preparer Sign Off (Initials, Date) | D17: Signataire préparateur (Initiales, Date)
A18: Owner Sign Off (Initials, Date) | D18: Signataire propriétaire (Initiales, Date)
A19: Assessor Sign Off (Initials, Date) | D19: Signataire évaluateur (Initiales, Date)
A20: Status | B20: Not Started | D20: Statut | E20: Non commencé
A21: Comments | D21: Commentaires

Sheet SI-4
A1: Control SI-4 — Evidence Tracking | D1: Contrôle SI-4 — Suivi des preuves
A2: Control Information | D2: Informations du contrôle
A3: Control Identifier | B3: SI-4 | D3: Identifiant du contrôle | E3: SI-4
A4: Family | B4: Information System Monitoring | D4: Famille | E4: Surveillance du système d’information
A5: Profile | B5: CCCS Medium / PBMM Moderate | D5: Profil | E5: CCCS Moyen / PBMM Modéré
A6: Primary Evidence Tool | D6: Outil de preuve principal
A7: Contributing Tools | D7: Outils contributeurs
A8: Control Description | B8: (A) The organization monitors the information system to detect: (a) Attacks and indicators of potential attacks in accordance with organization-defined monitoring objectives; and (b) Unauthorized local, network, and remote connections; (B) The organization identifies unauthorized use of the information system through organization-defined techniques and methods. (C) The organization deploys monitoring devices: (i) strategically within the information system to collect organization-determined essential information; and (ii) at ad hoc locations within the system to track specific types of transactions of interest to the organization. (D) The organization protects information obtained from intrusion-monitoring tools from unauthorized access, modification, and deletion. (E) The organization heightens the level of information system monitoring activity whenever there is an indication of increased risk to organizational operations and assets, individuals, other organizations, or Canada based on law enforcement information, intelligence information, or other credible sources of information. (F) The organization obtains legal opinion with regard to information system monitoring activities in accordance with orgnanizational policies, directives and standards. (G) The organization provides organization-defined information system monitoring information to organization-defined personnel or roles at an organization-defined frequency. | D8: Description du contrôle | E8: (A) L’organisation surveille le système d’information pour détecter : (a) les attaques et indicateurs d’attaques potentielles conformément aux objectifs de surveillance définis par l’organisation; (b) les connexions locales, de réseau et à distance non autorisées; (B) L’organisation détecte l’utilisation non autorisée du système d’information au moyen de techniques et de méthodes définies par l’organisation. (C) L’organisation déploie des dispositifs de surveillance : (i) de façon stratégique au sein du système d’information pour recueillir les renseignements essentiels déterminés par l’organisation; (ii) à des endroits spéciaux dans le système pour faire le suivi de certains types de transactions d’intérêt pour l’organisation. (D) L’organisation protège l’information obtenue des outils de surveillance des intrusions contre l’accès, la modification et la suppression non autorisés. (E) L’organisation augmente le niveau de l’activité de surveillance du système d’information chaque fois qu’il y a indication d’un risque accru pour les opérations et les biens de l’organisation, les personnes, les autres organisations ou le Canada sur la base de renseignements concernant l’application de la loi, de renseignements de sécurité ou d’autres sources d’information crédibles. (F) L’organisation obtient un avis juridique concernant les activités de surveillance du système d’information conformément aux politiques, aux directives et aux normes de l’organisation. (G) L’organisation fournit les renseignements relatifs à la surveillance du système d’information définis par l’organisation au personnel ou aux rôles définis par l’organisation à une fréquence définie par l’organisation.
A9: Supplemental Guidance | B9: Information system monitoring includes external and internal monitoring. External monitoring includes the observation of events occurring at the information system boundary (i.e., part of perimeter defence and boundary protection). Internal monitoring includes the observation of events occurring within the information system. Organizations can monitor information systems, for example, by observing audit activities in real time or by observing other system aspects such as access patterns, characteristics of access, and other actions. The monitoring objectives may guide determination of the events. Information system monitoring capability is achieved through a variety of tools and techniques (e.g., intrusion detection systems, intrusion prevention systems, malicious code protection software, scanning tools, audit record monitoring software, network monitoring software). Strategic locations for monitoring devices include, for example, selected perimeter locations and near server farms supporting critical applications, with such devices typically being employed at the managed interfaces associated with controls SC-7 and AC-17. The granularity of monitoring information collected is based on organizational monitoring objectives and the capability of information systems to support such objectives. Specific types of transactions of interest include, for example, HTTP traffic that bypasses HTTP proxies. Information system monitoring is an integral part of organizational continuous monitoring and incident response programs. Output from system monitoring serves as input to continuous monitoring and incident response programs. A network connection is any connection with a device that communicates through a network (e.g., local area network, Internet). A remote connection is any connection with a device communicating through an external network (e.g., the Internet). Local, network, and remote connections can be either wired or wireless. Related controls: AC-3, AC-4, AC-8, AC-17, AU-2, AU-6, AU-7, AU-9, AU-12, CA-7, IR-4, PE-3, RA-5, SC-7, SC-26, SC-35, SI-3, SI-7 | D9: Directives supplémentaires | E9: La surveillance du système d’information comprend la surveillance externe et interne. La surveillance externe comprend l’observation d’événements qui se produisent à la frontière du système d’information (c.-à-d. qu’elle fait partie de la défense du périmètre et de la protection des frontières). La surveillance interne comprend l’observation des événements qui se produisent au sein du système d’information. Les organisations peuvent surveiller les systèmes d’information, par exemple en observant les activités de vérification en temps réel ou en observant d’autres aspects du système, comme les profils d’accès, les caractéristiques de l’accès et d’autres mesures. Les objectifs de surveillance peuvent guider la détermination des événements. La capacité de surveillance des systèmes d’information est assurée par divers outils et techniques (p. ex., systèmes de détection des intrusions, systèmes de prévention des intrusions, logiciels de protection contre le code malveillant, outils de balayage, logiciel de surveillance des enregistrements de vérification, logiciel de surveillance de réseau). Les emplacements stratégiques pour les dispositifs de surveillance comprennent, par exemple, des emplacements périmétriques choisis et près des grappes de serveurs prenant en charge les applications critiques, ces dispositifs étant habituellement utilisés aux interfaces gérées associées aux contrôles SC-7 et AC-17. La granularité des données de surveillance recueillies est fonction des objectifs de surveillance de l’organisation et de la capacité des systèmes d’information à appuyer de tels objectifs. Les types particuliers de transactions d’intérêt comprennent, par exemple, le trafic HTTP qui contourne les mandataires HTTP. La surveillance du système d’information fait partie intégrante des programmes de surveillance continue et d’intervention en cas d’incident de l’organisation. Les résultats de la surveillance des systèmes servent d’intrants aux programmes de surveillance continue et d’intervention en cas d’incident. Une connexion réseau est toute connexion avec un appareil qui communique par l’entremise d’un réseau (p. ex., réseau local, Internet). Une connexion distante est toute connexion avec un appareil qui communique par l’entremise d’un réseau externe (p. ex., Internet). Les connexions locales, réseau et distantes peuvent être câblées ou sans fil. Contrôles connexes : AC-3, AC-4, AC-8, AC-17, AU-2, AU-6, AU-7, AU-9, AU-12, CA-7, IR-4, PE-3, RA-5, SC-7, SC-26, SC-35, SI-3, SI-7
A10: Test Case | D10: Cas de test
A11: Test | B11: TEST-SI-4 | D11: Test | E11: TEST-SI-4
A12: Requirement ID | B12: SI-4 | D12: ID Exigence | E12: SI-4
A13: Component | D13: Composant
A14: Requirement | D14: Exigence
A15: Contextual Design Description | D15: Description contextuelle du design
A16: Evidence Provided | D16: Preuve fournie
A17: Preparer Sign Off (Initials, Date) | D17: Signataire préparateur (Initiales, Date)
A18: Owner Sign Off (Initials, Date) | D18: Signataire propriétaire (Initiales, Date)
A19: Assessor Sign Off (Initials, Date) | D19: Signataire évaluateur (Initiales, Date)
A20: Status | B20: Not Started | D20: Statut | E20: Non commencé
A21: Comments | D21: Commentaires

Sheet SI-4-1
A1: Control SI-4(1) — Evidence Tracking | D1: Contrôle SI-4(1) — Suivi des preuves
A2: Control Information | D2: Informations du contrôle
A3: Control Identifier | B3: SI-4(1) | D3: Identifiant du contrôle | E3: SI-4(1)
A4: Family | B4: Information System Monitoring | D4: Famille | E4: Surveillance du système d’information
A5: Profile | B5: CCCS Medium / PBMM Moderate | D5: Profil | E5: CCCS Moyen / PBMM Modéré
A6: Primary Evidence Tool | D6: Outil de preuve principal
A7: Contributing Tools | D7: Outils contributeurs
A8: Control Description | B8: INFORMATION SYSTEM MONITORING | SYSTEM-WIDE INTRUSION DETECTION SYSTEM The organization connects and configures individual intrusion detection tools into an information system-wide intrusion detection system. | D8: Description du contrôle | E8: SURVEILLANCE DU SYSTÈME D’INFORMATION | SYSTÈME DE DÉTECTION DES INTRUSIONS À L’ÉCHELLE DU SYSTÈME L’organisation connecte et configure les outils de détection d’intrusion individuels en un système de détection d’intrusion global pour l’ensemble du système d’information.
A9: Supplemental Guidance | D9: Directives supplémentaires
A10: Test Case | D10: Cas de test
A11: Test | B11: TEST-SI-4(1) | D11: Test | E11: TEST-SI-4(1)
A12: Requirement ID | B12: SI-4(1) | D12: ID Exigence | E12: SI-4(1)
A13: Component | D13: Composant
A14: Requirement | D14: Exigence
A15: Contextual Design Description | D15: Description contextuelle du design
A16: Evidence Provided | D16: Preuve fournie
A17: Preparer Sign Off (Initials, Date) | D17: Signataire préparateur (Initiales, Date)
A18: Owner Sign Off (Initials, Date) | D18: Signataire propriétaire (Initiales, Date)
A19: Assessor Sign Off (Initials, Date) | D19: Signataire évaluateur (Initiales, Date)
A20: Status | B20: Not Started | D20: Statut | E20: Non commencé
A21: Comments | D21: Commentaires

Sheet SI-4-2
A1: Control SI-4(2) — Evidence Tracking | D1: Contrôle SI-4(2) — Suivi des preuves
A2: Control Information | D2: Informations du contrôle
A3: Control Identifier | B3: SI-4(2) | D3: Identifiant du contrôle | E3: SI-4(2)
A4: Family | B4: Information System Monitoring | D4: Famille | E4: Surveillance du système d’information
A5: Profile | B5: CCCS Medium / PBMM Moderate | D5: Profil | E5: CCCS Moyen / PBMM Modéré
A6: Primary Evidence Tool | D6: Outil de preuve principal
A7: Contributing Tools | D7: Outils contributeurs
A8: Control Description | B8: INFORMATION SYSTEM MONITORING | AUTOMATED TOOLS FOR REAL-TIME ANALYSIS The organization employs automated tools to support near real-time analysis of events. | D8: Description du contrôle | E8: SURVEILLANCE DU SYSTÈME D’INFORMATION | OUTILS AUTOMATISÉS POUR L’ANALYSE EN TEMPS RÉEL L’organisation utilise des outils automatisés pour appuyer l’analyse des événements en temps quasi réel.
A9: Supplemental Guidance | B9: Automated tools include, for example, host-based, network-based, transport-based, or storage-based event monitoring tools or Security Information and Event Management (SIEM) technologies that provide real time analysis of alerts and/or notifications generated by organizational information systems. | D9: Directives supplémentaires | E9: Les outils automatisés comprennent, par exemple, des outils de surveillance des événements basés sur l’hôte, le réseau, le transport ou le stockage, ou des technologies de gestion de l’information et des événements de sécurité (SIEM) qui fournissent une analyse en temps réel des alertes et/ou des notifications générées par les systèmes d’information de l’organisation.
A10: Test Case | D10: Cas de test
A11: Test | B11: TEST-SI-4(2) | D11: Test | E11: TEST-SI-4(2)
A12: Requirement ID | B12: SI-4(2) | D12: ID Exigence | E12: SI-4(2)
A13: Component | D13: Composant
A14: Requirement | D14: Exigence
A15: Contextual Design Description | D15: Description contextuelle du design
A16: Evidence Provided | D16: Preuve fournie
A17: Preparer Sign Off (Initials, Date) | D17: Signataire préparateur (Initiales, Date)
A18: Owner Sign Off (Initials, Date) | D18: Signataire propriétaire (Initiales, Date)
A19: Assessor Sign Off (Initials, Date) | D19: Signataire évaluateur (Initiales, Date)
A20: Status | B20: Not Started | D20: Statut | E20: Non commencé
A21: Comments | D21: Commentaires

Sheet SI-4-4
A1: Control SI-4(4) — Evidence Tracking | D1: Contrôle SI-4(4) — Suivi des preuves
A2: Control Information | D2: Informations du contrôle
A3: Control Identifier | B3: SI-4(4) | D3: Identifiant du contrôle | E3: SI-4(4)
A4: Family | B4: Information System Monitoring | D4: Famille | E4: Surveillance du système d’information
A5: Profile | B5: CCCS Medium / PBMM Moderate | D5: Profil | E5: CCCS Moyen / PBMM Modéré
A6: Primary Evidence Tool | D6: Outil de preuve principal
A7: Contributing Tools | D7: Outils contributeurs
A8: Control Description | B8: INFORMATION SYSTEM MONITORING | INBOUND AND OUTBOUND COMMUNICATIONS TRAFFIC The information system monitors inbound and outbound communications traffic continously for unusual or unauthorized activities or conditions. | D8: Description du contrôle | E8: SURVEILLANCE DU SYSTÈME D’INFORMATION | COMMUNICATIONS ENTRANTES ET SORTANTES Le système d’information surveille les communications entrantes et sortantes de façon continue pour détecter les activités ou les conditions inhabituelles ou non autorisées.
A9: Supplemental Guidance | B9: Unusual/unauthorized activities or conditions related to information system inbound and outbound communications traffic include, for example, internal traffic that indicates the presence of malicious code within organizational information systems or propagating among system components, the unauthorized exporting of information, or signalling to external information systems. Evidence of malicious code is used to identify potentially compromised information systems or information system components. | D9: Directives supplémentaires | E9: Les activités ou les conditions inhabituelles ou non autorisées liées aux communications entrantes et sortantes du système d’information comprennent, par exemple, le trafic interne indiquant la présence de code malveillant dans les systèmes d’information de l’organisation ou se propageant dans les composants du système, l’exportation non autorisée d’information ou la signalisation vers des systèmes d’information externes. Les preuves de la présence du code malveillant sont utilisées pour identifier les systèmes d’information ou les composants de systèmes d’information potentiellement compromis.
A10: Test Case | D10: Cas de test
A11: Test | B11: TEST-SI-4(4) | D11: Test | E11: TEST-SI-4(4)
A12: Requirement ID | B12: SI-4(4) | D12: ID Exigence | E12: SI-4(4)
A13: Component | D13: Composant
A14: Requirement | D14: Exigence
A15: Contextual Design Description | D15: Description contextuelle du design
A16: Evidence Provided | D16: Preuve fournie
A17: Preparer Sign Off (Initials, Date) | D17: Signataire préparateur (Initiales, Date)
A18: Owner Sign Off (Initials, Date) | D18: Signataire propriétaire (Initiales, Date)
A19: Assessor Sign Off (Initials, Date) | D19: Signataire évaluateur (Initiales, Date)
A20: Status | B20: Not Started | D20: Statut | E20: Non commencé
A21: Comments | D21: Commentaires

Sheet SI-4-5
A1: Control SI-4(5) — Evidence Tracking | D1: Contrôle SI-4(5) — Suivi des preuves
A2: Control Information | D2: Informations du contrôle
A3: Control Identifier | B3: SI-4(5) | D3: Identifiant du contrôle | E3: SI-4(5)
A4: Family | B4: Information System Monitoring | D4: Famille | E4: Surveillance du système d’information
A5: Profile | B5: CCCS Medium / PBMM Moderate | D5: Profil | E5: CCCS Moyen / PBMM Modéré
A6: Primary Evidence Tool | D6: Outil de preuve principal
A7: Contributing Tools | D7: Outils contributeurs
A8: Control Description | B8: INFORMATION SYSTEM MONITORING | SYSTEM-GENERATED ALERTS The information system alerts organization-defined personnel or roles and client governance bodies when organization-defined compromise or potential compromise indicators occur. | D8: Description du contrôle | E8: SURVEILLANCE DU SYSTÈME D’INFORMATION | ALERTES GÉNÉRÉES PAR LE SYSTÈME Le système d’information alerte le personnel ou les rôles définis par l’organisation et les organes de gouvernance du client lorsque des indicateurs de compromission ou de compromission potentielle définis par l’organisation sont détectés.
A9: Supplemental Guidance | B9: Alerts may be generated from a variety of sources, including, for example, audit records or inputs from malicious code protection mechanisms, intrusion detection or prevention mechanisms, or boundary protection devices such as firewalls, gateways, and routers. Alerts can be transmitted, for example, telephonically, by electronic mail messages, or by text messaging. Organizational personnel on the notification list can include, for example, system administrators, mission/business owners, system owners, or information system security officers. Related controls: AU-5, PE-6. | D9: Directives supplémentaires | E9: Les alertes peuvent provenir de diverses sources, y compris, par exemple, des enregistrements de vérification ou des données provenant de mécanismes de protection contre le code malveillant, de mécanismes de détection ou de prévention des intrusions, ou de dispositifs de protection des frontières comme les pare-feu, les passerelles et les routeurs. Les alertes peuvent être transmises, par exemple, par téléphone, par courrier électronique ou par messagerie texte. Le personnel de l’organisation figurant sur la liste de notification peut comprendre, par exemple, des administrateurs de système, des responsables opérationnels ou de mission, des propriétaires de système ou des agents de sécurité de système d’information. Contrôles connexes : AU-5, PE-6.
A10: Test Case | D10: Cas de test
A11: Test | B11: TEST-SI-4(5) | D11: Test | E11: TEST-SI-4(5)
A12: Requirement ID | B12: SI-4(5) | D12: ID Exigence | E12: SI-4(5)
A13: Component | D13: Composant
A14: Requirement | D14: Exigence
A15: Contextual Design Description | D15: Description contextuelle du design
A16: Evidence Provided | D16: Preuve fournie
A17: Preparer Sign Off (Initials, Date) | D17: Signataire préparateur (Initiales, Date)
A18: Owner Sign Off (Initials, Date) | D18: Signataire propriétaire (Initiales, Date)
A19: Assessor Sign Off (Initials, Date) | D19: Signataire évaluateur (Initiales, Date)
A20: Status | B20: Not Started | D20: Statut | E20: Non commencé
A21: Comments | D21: Commentaires

Sheet SI-4-11
A1: Control SI-4(11) — Evidence Tracking | D1: Contrôle SI-4(11) — Suivi des preuves
A2: Control Information | D2: Informations du contrôle
A3: Control Identifier | B3: SI-4(11) | D3: Identifiant du contrôle | E3: SI-4(11)
A4: Family | B4: Information System Monitoring | D4: Famille | E4: Surveillance du système d’information
A5: Profile | B5: CCCS Medium / PBMM Moderate | D5: Profil | E5: CCCS Moyen / PBMM Modéré
A6: Primary Evidence Tool | D6: Outil de preuve principal
A7: Contributing Tools | D7: Outils contributeurs
A8: Control Description | B8: INFORMATION SYSTEM MONITORING | ANALYZE COMMUNICATIONS TRAFFIC ANOMALIES The organization analyzes outbound communications traffic at the external boundary of the information system and selected organization-defined interior points within the system (e.g., sub-networks, subsystems) to discover anomalies. | D8: Description du contrôle | E8: SURVEILLANCE DU SYSTÈME D’INFORMATION | ANALYSE DES ANOMALIES DANS LES COMMUNICATIONS L’organisation analyse les communications sortantes à la frontière externe du système d’information et à certains points définis par l’organisation à l’intérieur du système (p. ex. sous-réseaux, sous-systèmes) pour découvrir des anomalies.
A9: Supplemental Guidance | B9: Anomalies within organizational information systems include, for example, large file transfers, long-time persistent connections, unusual protocols and ports in use, and attempted communications with suspected malicious external addresses. | D9: Directives supplémentaires | E9: Les anomalies dans les systèmes d’information de l’organisation comprennent, par exemple, les transferts de fichiers volumineux, les connexions persistantes de longue durée, les protocoles et les ports inhabituels utilisés et les tentatives de communication avec des adresses externes soupçonnées de malveillance.
A10: Test Case | D10: Cas de test
A11: Test | B11: TEST-SI-4(11) | D11: Test | E11: TEST-SI-4(11)
A12: Requirement ID | B12: SI-4(11) | D12: ID Exigence | E12: SI-4(11)
A13: Component | D13: Composant
A14: Requirement | D14: Exigence
A15: Contextual Design Description | D15: Description contextuelle du design
A16: Evidence Provided | D16: Preuve fournie
A17: Preparer Sign Off (Initials, Date) | D17: Signataire préparateur (Initiales, Date)
A18: Owner Sign Off (Initials, Date) | D18: Signataire propriétaire (Initiales, Date)
A19: Assessor Sign Off (Initials, Date) | D19: Signataire évaluateur (Initiales, Date)
A20: Status | B20: Not Started | D20: Statut | E20: Non commencé
A21: Comments | D21: Commentaires

Sheet SI-6
A1: Control SI-6 — Evidence Tracking | D1: Contrôle SI-6 — Suivi des preuves
A2: Control Information | D2: Informations du contrôle
A3: Control Identifier | B3: SI-6 | D3: Identifiant du contrôle | E3: SI-6
A4: Family | B4: Security Functional Verification | D4: Famille | E4: Vérification fonctionnelle de la sécurité
A5: Profile | B5: CCCS Medium / PBMM Moderate | D5: Profil | E5: CCCS Moyen / PBMM Modéré
A6: Primary Evidence Tool | D6: Outil de preuve principal
A7: Contributing Tools | D7: Outils contributeurs
A8: Control Description | B8: (A) The information system verifies the correct operation of organization-defined security functions. (B) The information system performs this verification organization-defined system transitional states including at least system startup and restart and at least monthly. (C) The information system notifies organization-defined personnel or roles including system administrators and security personnel of failed security verification tests. (D) The information system takes organization-defined action(s) when anomalies are discovered and notifies system administrators and security personnel. | D8: Description du contrôle | E8: (A) Le système d’information vérifie le bon fonctionnement des fonctions de sécurité définies par l’organisation. (B) Le système d’information effectue cette vérification des phases de transition définies par l’organisation, y compris au moins le démarrage et le redémarrage du système et au moins une fois par mois. (C) Le système d’information informe le personnel ou les rôles définis par l’organisation, y compris les administrateurs de système et le personnel de sécurité, des tests de vérification de sécurité qui ont échoué. (D) Le système d’information prend des mesures définies par l’organisation lorsque des anomalies sont découvertes et en informe les administrateurs du système et le personnel de sécurité.
A9: Supplemental Guidance | B9: Transitional states for information systems include, for example, system start-up, restart, shutdown, and abort. Notifications provided by information systems include, for example, electronic alerts to system administrators, messages to local computer consoles, and/or hardware indications such as lights. Related controls: CA-7, CM-6 | D9: Directives supplémentaires | E9: Les phases de transition pour les systèmes d’information comprennent, par exemple, le démarrage, le redémarrage, l’arrêt et l’interruption du système. Les notifications fournies par les systèmes d’information comprennent, par exemple, des alertes électroniques aux administrateurs du système, des messages aux consoles d’ordinateurs locales ou des indications matérielles telles que des voyants. Contrôles connexes : CA-7, CM-6
A10: Test Case | D10: Cas de test
A11: Test | B11: TEST-SI-6 | D11: Test | E11: TEST-SI-6
A12: Requirement ID | B12: SI-6 | D12: ID Exigence | E12: SI-6
A13: Component | D13: Composant
A14: Requirement | D14: Exigence
A15: Contextual Design Description | D15: Description contextuelle du design
A16: Evidence Provided | D16: Preuve fournie
A17: Preparer Sign Off (Initials, Date) | D17: Signataire préparateur (Initiales, Date)
A18: Owner Sign Off (Initials, Date) | D18: Signataire propriétaire (Initiales, Date)
A19: Assessor Sign Off (Initials, Date) | D19: Signataire évaluateur (Initiales, Date)
A20: Status | B20: Not Started | D20: Statut | E20: Non commencé
A21: Comments | D21: Commentaires

Sheet SI-7-7
A1: Control SI-7(7) — Evidence Tracking | D1: Contrôle SI-7(7) — Suivi des preuves
A2: Control Information | D2: Informations du contrôle
A3: Control Identifier | B3: SI-7(7) | D3: Identifiant du contrôle | E3: SI-7(7)
A4: Family | B4: Software, Firmware, and Information Integrity | D4: Famille | E4: Logiciels, micrologiciels et intégrité de l’information
A5: Profile | B5: CCCS Medium / PBMM Moderate | D5: Profil | E5: CCCS Moyen / PBMM Modéré
A6: Primary Evidence Tool | D6: Outil de preuve principal
A7: Contributing Tools | D7: Outils contributeurs
A8: Control Description | B8: SOFTWARE, FIRMWARE, AND INFORMATION INTEGRITY | INTEGRATION OF DETECTION AND RESPONSE The organization incorporates the detection of unauthorized organization-defined security-relevant changes to the information system into the organizational incident response capability. | D8: Description du contrôle | E8: INTÉGRITÉ DES LOGICIELS, DES MICROLOGICIELS ET DE L’INFORMATION | INTÉGRATION DE LA DÉTECTION ET DE L’INTERVENTION L’organisation intègre la détection des changements non autorisés qu’elle définit comme pertinents pour la sécurité du système d’information dans sa capacité d’intervention en cas d’incident.
A9: Supplemental Guidance | B9: This control enhancement helps to ensure that detected events are tracked, monitored, corrected, and available for historical purposes. Maintaining historical records is important both for being able to identify and discern adversary actions over an extended period of time and for possible legal actions. Security-relevant changes include, for example, unauthorized changes to established configuration settings or unauthorized elevation of information system privileges. Related controls: IR-4, IR-5, SI-4. | D9: Directives supplémentaires | E9: Cette amélioration du contrôle permet de s’assurer que les événements détectés sont suivis, surveillés, corrigés et disponibles à des fins historiques. Il est important de tenir des registres de l’historique pour être en mesure d’identifier et de discerner les actions adverses sur une période prolongée et pour d’éventuelles actions en justice. Les changements pertinents pour la sécurité comprennent, par exemple, les changements non autorisés aux paramètres de configuration établis ou l’élévation non autorisée des privilèges du système d’information. Contrôles connexes : IR-4, IR-5, SI-4.
A10: Test Case | D10: Cas de test
A11: Test | B11: TEST-SI-7(7) | D11: Test | E11: TEST-SI-7(7)
A12: Requirement ID | B12: SI-7(7) | D12: ID Exigence | E12: SI-7(7)
A13: Component | D13: Composant
A14: Requirement | D14: Exigence
A15: Contextual Design Description | D15: Description contextuelle du design
A16: Evidence Provided | D16: Preuve fournie
A17: Preparer Sign Off (Initials, Date) | D17: Signataire préparateur (Initiales, Date)
A18: Owner Sign Off (Initials, Date) | D18: Signataire propriétaire (Initiales, Date)
A19: Assessor Sign Off (Initials, Date) | D19: Signataire évaluateur (Initiales, Date)
A20: Status | B20: Not Started | D20: Statut | E20: Non commencé
A21: Comments | D21: Commentaires

Sheet SI-11
A1: Control SI-11 — Evidence Tracking | D1: Contrôle SI-11 — Suivi des preuves
A2: Control Information | D2: Informations du contrôle
A3: Control Identifier | B3: SI-11 | D3: Identifiant du contrôle | E3: SI-11
A4: Family | B4: Error Handling | D4: Famille | E4: Traitement des erreurs
A5: Profile | B5: CCCS Medium / PBMM Moderate | D5: Profil | E5: CCCS Moyen / PBMM Modéré
A6: Primary Evidence Tool | D6: Outil de preuve principal
A7: Contributing Tools | D7: Outils contributeurs
A8: Control Description | B8: (A) The information system generates error messages that provide information necessary for corrective actions without revealing information that could be exploited by adversaries. (B) The information system reveals error messages only to organization-defined personnel or roles. | D8: Description du contrôle | E8: (A) Le système d’information génère des messages d’erreur qui fournissent l’information nécessaire aux mesures correctives sans révéler l’information qui pourrait être exploitée par des adversaires. (B) Le système d’information ne révèle les messages d’erreur qu’au personnel ou aux rôles définis par l’organisation.
A9: Supplemental Guidance | B9: Organizations carefully consider the structure/content of error messages. The extent to which information systems are able to identify and handle error conditions is guided by organizational policy and operational requirements. Information that could be exploited by adversaries includes, for example, erroneous logon attempts with passwords entered by mistake as the username, mission/business information that can be derived from (if not stated explicitly by) information recorded, and personal information such as account numbers, social security numbers, and credit card numbers. In addition, error messages may provide a covert channel for transmitting information. Related controls: AU-2, AU-3, SC-31 | D9: Directives supplémentaires | E9: Les organisations examinent attentivement la structure et le contenu des messages d’erreur. La mesure dans laquelle les systèmes d’information peuvent déterminer et gérer les conditions d’erreur est fonction des politiques et des exigences opérationnelles de l’organisation. Les renseignements qui pourraient être exploités par des adversaires comprennent, par exemple, les tentatives d’ouverture de session erronées avec des mots de passe entrés par erreur en tant que nom d’utilisateur, des renseignements sur la mission ou les opérations qui peuvent être déduits de (voire être explicitement indiqués par) l’information saisie, et des renseignements personnels comme des numéros de compte, des numéros de sécurité sociale et des numéros de carte de crédit. De plus, les messages d’erreur peuvent servir de voie secrète pour transmettre de l’information. Contrôles connexes : AU-2, AU-3, SC-31
A10: Test Case | D10: Cas de test
A11: Test | B11: TEST-SI-11 | D11: Test | E11: TEST-SI-11
A12: Requirement ID | B12: SI-11 | D12: ID Exigence | E12: SI-11
A13: Component | D13: Composant
A14: Requirement | D14: Exigence
A15: Contextual Design Description | D15: Description contextuelle du design
A16: Evidence Provided | D16: Preuve fournie
A17: Preparer Sign Off (Initials, Date) | D17: Signataire préparateur (Initiales, Date)
A18: Owner Sign Off (Initials, Date) | D18: Signataire propriétaire (Initiales, Date)
A19: Assessor Sign Off (Initials, Date) | D19: Signataire évaluateur (Initiales, Date)
A20: Status | B20: Not Started | D20: Statut | E20: Non commencé
A21: Comments | D21: Commentaires
