Workbook

Sheet DASHBOARD
A1: DASHBOARD — PBMM Evidence: Hybrid + Multicloud
A2: Control ID | B2: Control Name | C2: Primary Tool | D2: Tab | E2: Status
A3: AC-2(4) | B3: Account Management | D3: AC-2-4 | E3: ='AC-2-4'!B20 -> Not Started
A4: AC-2(5) | B4: Account Management | D4: AC-2-5 | E4: ='AC-2-5'!B20 -> Not Started
A5: AC-2(7) | B5: Account Management | D5: AC-2-7 | E5: ='AC-2-7'!B20 -> Not Started
A6: AC-6 | B6: Least Privilege | D6: AC-6 | E6: ='AC-6'!B20 -> Not Started
A7: AC-6(1) | B7: Least Privilege | D7: AC-6-1 | E7: ='AC-6-1'!B20 -> Not Started
A8: AC-6(9) | B8: Least Privilege | D8: AC-6-9 | E8: ='AC-6-9'!B20 -> Not Started
A9: AC-17(1) | B9: Remote Access | D9: AC-17-1 | E9: ='AC-17-1'!B20 -> Not Started
A10: AU-2 | B10: Auditable Events | D10: AU-2 | E10: ='AU-2'!B20 -> Not Started
A11: AU-3 | B11: Content of Audit Records | D11: AU-3 | E11: ='AU-3'!B20 -> Not Started
A12: AU-3(1) | B12: Content of Audit Records | D12: AU-3-1 | E12: ='AU-3-1'!B20 -> Not Started
A13: AU-5 | B13: Response To Audit Processing Failures | D13: AU-5 | E13: ='AU-5'!B20 -> Not Started
A14: AU-6(1) | B14: Audit Review, Analysis, and Reporting | D14: AU-6-1 | E14: ='AU-6-1'!B20 -> Not Started
A15: AU-6(3) | B15: Audit Review, Analysis, and Reporting | D15: AU-6-3 | E15: ='AU-6-3'!B20 -> Not Started
A16: AU-7 | B16: Audit Reduction and Report Generation | D16: AU-7 | E16: ='AU-7'!B20 -> Not Started
A17: AU-7(1) | B17: Audit Reduction and Report Generation | D17: AU-7-1 | E17: ='AU-7-1'!B20 -> Not Started
A18: AU-8 | B18: Time Stamps | D18: AU-8 | E18: ='AU-8'!B20 -> Not Started
A19: AU-8(1) | B19: Time Stamps | D19: AU-8-1 | E19: ='AU-8-1'!B20 -> Not Started
A20: AU-9 | B20: Protection of Audit Information | D20: AU-9 | E20: ='AU-9'!B20 -> Not Started
A21: AU-9(2) | B21: Protection of Audit Information | D21: AU-9-2 | E21: ='AU-9-2'!B20 -> Not Started
A22: AU-9(4) | B22: Protection of Audit Information | D22: AU-9-4 | E22: ='AU-9-4'!B20 -> Not Started
A23: AU-11 | B23: Audit Record Retention | D23: AU-11 | E23: ='AU-11'!B20 -> Not Started
A24: AU-12 | B24: Audit Generation | D24: AU-12 | E24: ='AU-12'!B20 -> Not Started
A25: CA-9 | B25: Internal System Connections | D25: CA-9 | E25: ='CA-9'!B20 -> Not Started
A26: CM-5(1) | B26: Access Restrictions for Change | D26: CM-5-1 | E26: ='CM-5-1'!B20 -> Not Started
A27: CM-5(6) | B27: Access Restrictions for Change | D27: CM-5-6 | E27: ='CM-5-6'!B20 -> Not Started
A28: CM-6 | B28: Configuration Settings | D28: CM-6 | E28: ='CM-6'!B20 -> Not Started
A29: CM-7 | B29: Least Functionality | D29: CM-7 | E29: ='CM-7'!B20 -> Not Started
A30: CM-7(1) | B30: Least Functionality | D30: CM-7-1 | E30: ='CM-7-1'!B20 -> Not Started
A31: CP-6 | B31: Alternate Storage Site | D31: CP-6 | E31: ='CP-6'!B20 -> Not Started
A32: CP-6(2) | B32: Alternate Storage Site | D32: CP-6-2 | E32: ='CP-6-2'!B20 -> Not Started
A33: CP-7 | B33: Alternate Processing Site | D33: CP-7 | E33: ='CP-7'!B20 -> Not Started
A34: CP-7(4) | B34: Alternate Processing Site | D34: CP-7-4 | E34: ='CP-7-4'!B20 -> Not Started
A35: CP-9 | B35: Information System Backup | D35: CP-9 | E35: ='CP-9'!B20 -> Not Started
A36: CP-9(1) | B36: Information System Backup | D36: CP-9-1 | E36: ='CP-9-1'!B20 -> Not Started
A37: CP-9(2) | B37: Information System Backup | D37: CP-9-2 | E37: ='CP-9-2'!B20 -> Not Started
A38: CP-9(5) | B38: Information System Backup | D38: CP-9-5 | E38: ='CP-9-5'!B20 -> Not Started
A39: CP-10 | B39: Information System Recovery and Reconstitution | D39: CP-10 | E39: ='CP-10'!B20 -> Not Started
A40: CP-10(2) | B40: Information System Recovery and Reconstitution | D40: CP-10-2 | E40: ='CP-10-2'!B20 -> Not Started
A41: CP-10(4) | B41: Information System Recovery and Reconstitution | D41: CP-10-4 | E41: ='CP-10-4'!B20 -> Not Started
A42: IA-5(7) | B42: Authenticator Management | D42: IA-5-7 | E42: ='IA-5-7'!B20 -> Not Started
A43: RA-5 | B43: Vulnerability Scanning | D43: RA-5 | E43: ='RA-5'!B20 -> Not Started
A44: RA-5(1) | B44: Vulnerability Scanning | D44: RA-5-1 | E44: ='RA-5-1'!B20 -> Not Started
A45: RA-5(2) | B45: Vulnerability Scanning | D45: RA-5-2 | E45: ='RA-5-2'!B20 -> Not Started
A46: RA-5(3) | B46: Vulnerability Scanning | D46: RA-5-3 | E46: ='RA-5-3'!B20 -> Not Started
A47: RA-5(5) | B47: Vulnerability Scanning | D47: RA-5-5 | E47: ='RA-5-5'!B20 -> Not Started
A48: RA-5(6) | B48: Vulnerability Scanning | D48: RA-5-6 | E48: ='RA-5-6'!B20 -> Not Started
A49: RA-5(8) | B49: Vulnerability Scanning | D49: RA-5-8 | E49: ='RA-5-8'!B20 -> Not Started
A50: SA-9(5) | B50: External Information System Services | D50: SA-9-5 | E50: ='SA-9-5'!B20 -> Not Started
A51: SA-11(1) | B51: Developer Security Testing | D51: SA-11-1 | E51: ='SA-11-1'!B20 -> Not Started
A52: SA-11(8) | B52: Developer Security Testing | D52: SA-11-8 | E52: ='SA-11-8'!B20 -> Not Started
A53: SC-5 | B53: Denial of Service Protection | D53: SC-5 | E53: ='SC-5'!B20 -> Not Started
A54: SC-7 | B54: Boundary Protection | D54: SC-7 | E54: ='SC-7'!B20 -> Not Started
A55: SC-13 | B55: Cryptographic Protection | D55: SC-13 | E55: ='SC-13'!B20 -> Not Started
A56: SC-28 | B56: Protection of Information At Rest | D56: SC-28 | E56: ='SC-28'!B20 -> Not Started
A57: SC-28(1) | B57: Protection of Information At Rest | D57: SC-28-1 | E57: ='SC-28-1'!B20 -> Not Started
A58: SI-2 | B58: Flaw Remediation | D58: SI-2 | E58: ='SI-2'!B20 -> Not Started
A59: SI-2(2) | B59: Flaw Remediation | D59: SI-2-2 | E59: ='SI-2-2'!B20 -> Not Started
A60: SI-3 | B60: Malicious Code Protection | D60: SI-3 | E60: ='SI-3'!B20 -> Not Started
A61: SI-3(1) | B61: Malicious Code Protection | D61: SI-3-1 | E61: ='SI-3-1'!B20 -> Not Started
A62: SI-3(2) | B62: Malicious Code Protection | D62: SI-3-2 | E62: ='SI-3-2'!B20 -> Not Started
A63: SI-3(7) | B63: Malicious Code Protection | D63: SI-3-7 | E63: ='SI-3-7'!B20 -> Not Started
A64: SI-4 | B64: Information System Monitoring | D64: SI-4 | E64: ='SI-4'!B20 -> Not Started
A65: SI-4(1) | B65: Information System Monitoring | D65: SI-4-1 | E65: ='SI-4-1'!B20 -> Not Started
A66: SI-4(2) | B66: Information System Monitoring | D66: SI-4-2 | E66: ='SI-4-2'!B20 -> Not Started
A67: SI-4(4) | B67: Information System Monitoring | D67: SI-4-4 | E67: ='SI-4-4'!B20 -> Not Started
A68: SI-4(5) | B68: Information System Monitoring | D68: SI-4-5 | E68: ='SI-4-5'!B20 -> Not Started
A69: SI-4(11) | B69: Information System Monitoring | D69: SI-4-11 | E69: ='SI-4-11'!B20 -> Not Started
A70: SI-6 | B70: Security Functional Verification | D70: SI-6 | E70: ='SI-6'!B20 -> Not Started
A71: SI-7(7) | B71: Software, Firmware, and Information Integrity | D71: SI-7-7 | E71: ='SI-7-7'!B20 -> Not Started
A72: SI-11 | B72: Error Handling | D72: SI-11 | E72: ='SI-11'!B20 -> Not Started
A74: Completion Metrics
A75: Total Controls | E75: =70 -> 70
A76: Not Started | E76: =COUNTIF(E3:E72,"Not Started") -> 70
A77: In Progress | E77: =COUNTIF(E3:E72,"In Progress") -> 0
A78: Evidence Provided | E78: =COUNTIF(E3:E72,"Evidence Provided") -> 0
A79: Under Review | E79: =COUNTIF(E3:E72,"Under Review") -> 0
A80: Passed | E80: =COUNTIF(E3:E72,"Passed") -> 0
A81: Failed | E81: =COUNTIF(E3:E72,"Failed") -> 0
A82: Accepted Exception | E82: =COUNTIF(E3:E72,"Accepted Exception") -> 0
A83: % Complete | E83: =IFERROR(COUNTIF(E3:E72,"Passed")/70,0) -> 0
A84: % Not Started | E84: =IFERROR(COUNTIF(E3:E72,"Not Started")/70,0) -> 1

Sheet TABLEAU_DE_BORD
A1: TABLEAU DE BORD — Suivi PBMM : Hybrid + Multicloud
A2: ID Contrôle | B2: Nom du contrôle | C2: Outil principal | D2: Onglet | E2: Statut
A3: AC-2(4) | B3: Gestion des comptes | D3: AC-2-4 | E3: ='AC-2-4'!E20 -> Non commencé
A4: AC-2(5) | B4: Gestion des comptes | D4: AC-2-5 | E4: ='AC-2-5'!E20 -> Non commencé
A5: AC-2(7) | B5: Gestion des comptes | D5: AC-2-7 | E5: ='AC-2-7'!E20 -> Non commencé
A6: AC-6 | B6: Moindre privilège | D6: AC-6 | E6: ='AC-6'!E20 -> Non commencé
A7: AC-6(1) | B7: Moindre privilège | D7: AC-6-1 | E7: ='AC-6-1'!E20 -> Non commencé
A8: AC-6(9) | B8: Moindre privilège | D8: AC-6-9 | E8: ='AC-6-9'!E20 -> Non commencé
A9: AC-17(1) | B9: Accès à distance | D9: AC-17-1 | E9: ='AC-17-1'!E20 -> Non commencé
A10: AU-2 | B10: Événements vérifiables | D10: AU-2 | E10: ='AU-2'!E20 -> Non commencé
A11: AU-3 | B11: Contenu des enregistrements de vérification | D11: AU-3 | E11: ='AU-3'!E20 -> Non commencé
A12: AU-3(1) | B12: Contenu des enregistrements de vérification | D12: AU-3-1 | E12: ='AU-3-1'!E20 -> Non commencé
A13: AU-5 | B13: Réponse aux échecs de traitement de vérification | D13: AU-5 | E13: ='AU-5'!E20 -> Non commencé
A14: AU-6(1) | B14: Examen, analyse et rapport de vérification | D14: AU-6-1 | E14: ='AU-6-1'!E20 -> Non commencé
A15: AU-6(3) | B15: Examen, analyse et rapport de vérification | D15: AU-6-3 | E15: ='AU-6-3'!E20 -> Non commencé
A16: AU-7 | B16: Réduction des vérifications et production de rapports | D16: AU-7 | E16: ='AU-7'!E20 -> Non commencé
A17: AU-7(1) | B17: Réduction des vérifications et production de rapports | D17: AU-7-1 | E17: ='AU-7-1'!E20 -> Non commencé
A18: AU-8 | B18: Estampilles temporelles | D18: AU-8 | E18: ='AU-8'!E20 -> Non commencé
A19: AU-8(1) | B19: Estampilles temporelles | D19: AU-8-1 | E19: ='AU-8-1'!E20 -> Non commencé
A20: AU-9 | B20: Protection des renseignements de vérification | D20: AU-9 | E20: ='AU-9'!E20 -> Non commencé
A21: AU-9(2) | B21: Protection des renseignements de vérification | D21: AU-9-2 | E21: ='AU-9-2'!E20 -> Non commencé
A22: AU-9(4) | B22: Protection des renseignements de vérification | D22: AU-9-4 | E22: ='AU-9-4'!E20 -> Non commencé
A23: AU-11 | B23: Conservation des enregistrements de vérification | D23: AU-11 | E23: ='AU-11'!E20 -> Non commencé
A24: AU-12 | B24: Génération des vérifications | D24: AU-12 | E24: ='AU-12'!E20 -> Non commencé
A25: CA-9 | B25: Connexions internes au système | D25: CA-9 | E25: ='CA-9'!E20 -> Non commencé
A26: CM-5(1) | B26: Restrictions d’accès pour les changements | D26: CM-5-1 | E26: ='CM-5-1'!E20 -> Non commencé
A27: CM-5(6) | B27: Restrictions d’accès pour les changements | D27: CM-5-6 | E27: ='CM-5-6'!E20 -> Non commencé
A28: CM-6 | B28: Paramètres de configuration | D28: CM-6 | E28: ='CM-6'!E20 -> Non commencé
A29: CM-7 | B29: Moindre fonctionnalité | D29: CM-7 | E29: ='CM-7'!E20 -> Non commencé
A30: CM-7(1) | B30: Moindre fonctionnalité | D30: CM-7-1 | E30: ='CM-7-1'!E20 -> Non commencé
A31: CP-6 | B31: Site de stockage auxiliaire | D31: CP-6 | E31: ='CP-6'!E20 -> Non commencé
A32: CP-6(2) | B32: Site de stockage auxiliaire | D32: CP-6-2 | E32: ='CP-6-2'!E20 -> Non commencé
A33: CP-7 | B33: Site de traitement auxiliaire | D33: CP-7 | E33: ='CP-7'!E20 -> Non commencé
A34: CP-7(4) | B34: Site de traitement auxiliaire | D34: CP-7-4 | E34: ='CP-7-4'!E20 -> Non commencé
A35: CP-9 | B35: Sauvegarde du système d’information | D35: CP-9 | E35: ='CP-9'!E20 -> Non commencé
A36: CP-9(1) | B36: Sauvegarde du système d’information | D36: CP-9-1 | E36: ='CP-9-1'!E20 -> Non commencé
A37: CP-9(2) | B37: Sauvegarde du système d’information | D37: CP-9-2 | E37: ='CP-9-2'!E20 -> Non commencé
A38: CP-9(5) | B38: Sauvegarde du système d’information | D38: CP-9-5 | E38: ='CP-9-5'!E20 -> Non commencé
A39: CP-10 | B39: Reprise et reconstitution du système d’information | D39: CP-10 | E39: ='CP-10'!E20 -> Non commencé
A40: CP-10(2) | B40: Reprise et reconstitution du système d’information | D40: CP-10-2 | E40: ='CP-10-2'!E20 -> Non commencé
A41: CP-10(4) | B41: Reprise et reconstitution du système d’information | D41: CP-10-4 | E41: ='CP-10-4'!E20 -> Non commencé
A42: IA-5(7) | B42: Gestion des authentifiants | D42: IA-5-7 | E42: ='IA-5-7'!E20 -> Non commencé
A43: RA-5 | B43: Analyse des vulnérabilités | D43: RA-5 | E43: ='RA-5'!E20 -> Non commencé
A44: RA-5(1) | B44: Analyse des vulnérabilités | D44: RA-5-1 | E44: ='RA-5-1'!E20 -> Non commencé
A45: RA-5(2) | B45: Analyse des vulnérabilités | D45: RA-5-2 | E45: ='RA-5-2'!E20 -> Non commencé
A46: RA-5(3) | B46: Analyse des vulnérabilités | D46: RA-5-3 | E46: ='RA-5-3'!E20 -> Non commencé
A47: RA-5(5) | B47: Analyse des vulnérabilités | D47: RA-5-5 | E47: ='RA-5-5'!E20 -> Non commencé
A48: RA-5(6) | B48: Analyse des vulnérabilités | D48: RA-5-6 | E48: ='RA-5-6'!E20 -> Non commencé
A49: RA-5(8) | B49: Analyse des vulnérabilités | D49: RA-5-8 | E49: ='RA-5-8'!E20 -> Non commencé
A50: SA-9(5) | B50: Services de systèmes d’information externes | D50: SA-9-5 | E50: ='SA-9-5'!E20 -> Non commencé
A51: SA-11(1) | B51: Essais de sécurité du développeur | D51: SA-11-1 | E51: ='SA-11-1'!E20 -> Non commencé
A52: SA-11(8) | B52: Essais de sécurité du développeur | D52: SA-11-8 | E52: ='SA-11-8'!E20 -> Non commencé
A53: SC-5 | B53: Protection contre le déni de service | D53: SC-5 | E53: ='SC-5'!E20 -> Non commencé
A54: SC-7 | B54: Protection des frontières | D54: SC-7 | E54: ='SC-7'!E20 -> Non commencé
A55: SC-13 | B55: Protection cryptographique | D55: SC-13 | E55: ='SC-13'!E20 -> Non commencé
A56: SC-28 | B56: Protection de l’information inactive | D56: SC-28 | E56: ='SC-28'!E20 -> Non commencé
A57: SC-28(1) | B57: Protection de l’information inactive | D57: SC-28-1 | E57: ='SC-28-1'!E20 -> Non commencé
A58: SI-2 | B58: Correction des défauts | D58: SI-2 | E58: ='SI-2'!E20 -> Non commencé
A59: SI-2(2) | B59: Correction des défauts | D59: SI-2-2 | E59: ='SI-2-2'!E20 -> Non commencé
A60: SI-3 | B60: Protection contre le code malveillant | D60: SI-3 | E60: ='SI-3'!E20 -> Non commencé
A61: SI-3(1) | B61: Protection contre le code malveillant | D61: SI-3-1 | E61: ='SI-3-1'!E20 -> Non commencé
A62: SI-3(2) | B62: Protection contre le code malveillant | D62: SI-3-2 | E62: ='SI-3-2'!E20 -> Non commencé
A63: SI-3(7) | B63: Protection contre le code malveillant | D63: SI-3-7 | E63: ='SI-3-7'!E20 -> Non commencé
A64: SI-4 | B64: Surveillance du système d’information | D64: SI-4 | E64: ='SI-4'!E20 -> Non commencé
A65: SI-4(1) | B65: Surveillance du système d’information | D65: SI-4-1 | E65: ='SI-4-1'!E20 -> Non commencé
A66: SI-4(2) | B66: Surveillance du système d’information | D66: SI-4-2 | E66: ='SI-4-2'!E20 -> Non commencé
A67: SI-4(4) | B67: Surveillance du système d’information | D67: SI-4-4 | E67: ='SI-4-4'!E20 -> Non commencé
A68: SI-4(5) | B68: Surveillance du système d’information | D68: SI-4-5 | E68: ='SI-4-5'!E20 -> Non commencé
A69: SI-4(11) | B69: Surveillance du système d’information | D69: SI-4-11 | E69: ='SI-4-11'!E20 -> Non commencé
A70: SI-6 | B70: Vérification fonctionnelle de la sécurité | D70: SI-6 | E70: ='SI-6'!E20 -> Non commencé
A71: SI-7(7) | B71: Logiciels, micrologiciels et intégrité de l’information | D71: SI-7-7 | E71: ='SI-7-7'!E20 -> Non commencé
A72: SI-11 | B72: Traitement des erreurs | D72: SI-11 | E72: ='SI-11'!E20 -> Non commencé
A74: Métriques de complétude
A75: Nombre total de contrôles | E75: =70 -> 70
A76: Non commencés | E76: =COUNTIF(E3:E72,"Non commencé") -> 70
A77: En cours | E77: =COUNTIF(E3:E72,"En cours") -> 0
A78: Preuve fournie | E78: =COUNTIF(E3:E72,"Preuve fournie") -> 0
A79: En révision | E79: =COUNTIF(E3:E72,"En révision") -> 0
A80: Réussi | E80: =COUNTIF(E3:E72,"Réussi") -> 0
A81: Échec | E81: =COUNTIF(E3:E72,"Échec") -> 0
A82: Exception acceptée | E82: =COUNTIF(E3:E72,"Exception acceptée") -> 0
A83: % Complété | E83: =IFERROR(COUNTIF(E3:E72,"Réussi")/70,0) -> 0
A84: % Non commencés | E84: =IFERROR(COUNTIF(E3:E72,"Non commencé")/70,0) -> 1

Sheet AC-2-4
A1: Control AC-2(4) — Evidence Tracking | D1: Contrôle AC-2(4) — Suivi des preuves
A2: Control Information | D2: Informations du contrôle
A3: Control Identifier | B3: AC-2(4) | D3: Identifiant du contrôle | E3: AC-2(4)
A4: Family | B4: Account Management | D4: Famille | E4: Gestion des comptes
A5: Profile | B5: CCCS Medium / PBMM Moderate | D5: Profil | E5: CCCS Moyen / PBMM Modéré
A6: Primary Evidence Tool | D6: Outil de preuve principal
A7: Contributing Tools | D7: Outils contributeurs
A8: Control Description | B8: ACCOUNT MANAGEMENT | AUTOMATED AUDIT ACTIONS The information system automatically audits account creation, modification, enabling, disabling, and removal actions, and notifies responsible managers. Related controls: AU-2, AU-12. | D8: Description du contrôle | E8: GESTION DES COMPTES | MESURES DE VÉRIFICATION AUTOMATISÉES Le système d’information vérifie automatiquement les opérations de création, de modification, d’activation, de désactivation et de retrait des comptes, et avise les gestionnaires responsables. Contrôles connexes : AU-2, AU-12.
A9: Supplemental Guidance | D9: Directives supplémentaires
A10: Test Case | D10: Cas de test
A11: Test | B11: TEST-AC-2(4) | D11: Test | E11: TEST-AC-2(4)
A12: Requirement ID | B12: AC-2(4) | D12: ID Exigence | E12: AC-2(4)
A13: Component | D13: Composant
A14: Requirement | D14: Exigence
A15: Contextual Design Description | D15: Description contextuelle du design
A16: Evidence Provided | D16: Preuve fournie
A17: Preparer Sign Off (Initials, Date) | D17: Signataire préparateur (Initiales, Date)
A18: Owner Sign Off (Initials, Date) | D18: Signataire propriétaire (Initiales, Date)
A19: Assessor Sign Off (Initials, Date) | D19: Signataire évaluateur (Initiales, Date)
A20: Status | B20: Not Started | D20: Statut | E20: Non commencé
A21: Comments | D21: Commentaires

Sheet AC-2-5
A1: Control AC-2(5) — Evidence Tracking | D1: Contrôle AC-2(5) — Suivi des preuves
A2: Control Information | D2: Informations du contrôle
A3: Control Identifier | B3: AC-2(5) | D3: Identifiant du contrôle | E3: AC-2(5)
A4: Family | B4: Account Management | D4: Famille | E4: Gestion des comptes
A5: Profile | B5: CCCS Medium / PBMM Moderate | D5: Profil | E5: CCCS Moyen / PBMM Modéré
A6: Primary Evidence Tool | D6: Outil de preuve principal
A7: Contributing Tools | D7: Outils contributeurs
A8: Control Description | B8: ACCOUNT MANAGEMENT | INACTIVITY LOGOUT The organization requires that users log out at the end of the users’ standard work period unless otherwise defined in formal organizational policy. Related controls: SC-23 | D8: Description du contrôle | E8: GESTION DES COMPTES | FERMETURE DE SESSION INACTIVE L’organisation exige que les utilisateurs ferment leur session à la fin de leur période de travail normale, à moins d’indication contraire dans la politique officielle de l’organisation. Contrôles connexes : SC-23
A9: Supplemental Guidance | D9: Directives supplémentaires
A10: Test Case | D10: Cas de test
A11: Test | B11: TEST-AC-2(5) | D11: Test | E11: TEST-AC-2(5)
A12: Requirement ID | B12: AC-2(5) | D12: ID Exigence | E12: AC-2(5)
A13: Component | D13: Composant
A14: Requirement | D14: Exigence
A15: Contextual Design Description | D15: Description contextuelle du design
A16: Evidence Provided | D16: Preuve fournie
A17: Preparer Sign Off (Initials, Date) | D17: Signataire préparateur (Initiales, Date)
A18: Owner Sign Off (Initials, Date) | D18: Signataire propriétaire (Initiales, Date)
A19: Assessor Sign Off (Initials, Date) | D19: Signataire évaluateur (Initiales, Date)
A20: Status | B20: Not Started | D20: Statut | E20: Non commencé
A21: Comments | D21: Commentaires

Sheet AC-2-7
A1: Control AC-2(7) — Evidence Tracking | D1: Contrôle AC-2(7) — Suivi des preuves
A2: Control Information | D2: Informations du contrôle
A3: Control Identifier | B3: AC-2(7) | D3: Identifiant du contrôle | E3: AC-2(7)
A4: Family | B4: Account Management | D4: Famille | E4: Gestion des comptes
A5: Profile | B5: CCCS Medium / PBMM Moderate | D5: Profil | E5: CCCS Moyen / PBMM Modéré
A6: Primary Evidence Tool | D6: Outil de preuve principal
A7: Contributing Tools | D7: Outils contributeurs
A8: Control Description | B8: ACCOUNT MANAGEMENT | ROLE-BASED SCHEMES (a) The organization establishes and administers privileged user accounts in accordance with a role-based access scheme that organizes allowed information system access and privileges into roles; (b) The organization monitors privileged role assignments; and (c) The organization disables (or revokes) privileged user assignments within 24 hours or sooner when privileged role assignments are no longer appropriate. | D8: Description du contrôle | E8: GESTION DES COMPTES | SCHÉMAS FONDÉS SUR LES RÔLES (a) L’organisation établit et administre les comptes d’utilisateurs privilégiés conformément à un système d’accès basé sur les rôles qui organise les autorisations d’accès au système d’information et les privilèges en fonction des rôles; (b) L’organisation surveille les affectations de rôles privilégiés; (c) L’organisation désactive (ou révoque) les affectations d’utilisateurs privilégiés dans les 24 heures ou plus lorsque les affectations de rôles privilégiés ne sont plus appropriées.
A9: Supplemental Guidance | B9: Privileged roles are organization-defined roles assigned to individuals that allow those individuals to perform certain security-relevant functions that ordinary users are not authorized to perform. These privileged roles include, for example, key management, account management, network and system administration, database administration, and web administration. | D9: Directives supplémentaires | E9: Les rôles privilégiés sont des rôles définis par l’organisation et attribués à des personnes pour leur permettre d’exécuter certaines fonctions ayant une influence sur la sécurité que les utilisateurs ordinaires ne sont pas autorisés à exécuter. Ces rôles privilégiés comprennent, par exemple, la gestion des clés, la gestion des comptes, l’administration des réseaux et des systèmes, l’administration des bases de données et l’administration Web.
A10: Test Case | D10: Cas de test
A11: Test | B11: TEST-AC-2(7) | D11: Test | E11: TEST-AC-2(7)
A12: Requirement ID | B12: AC-2(7) | D12: ID Exigence | E12: AC-2(7)
A13: Component | D13: Composant
A14: Requirement | D14: Exigence
A15: Contextual Design Description | D15: Description contextuelle du design
A16: Evidence Provided | D16: Preuve fournie
A17: Preparer Sign Off (Initials, Date) | D17: Signataire préparateur (Initiales, Date)
A18: Owner Sign Off (Initials, Date) | D18: Signataire propriétaire (Initiales, Date)
A19: Assessor Sign Off (Initials, Date) | D19: Signataire évaluateur (Initiales, Date)
A20: Status | B20: Not Started | D20: Statut | E20: Non commencé
A21: Comments | D21: Commentaires

Sheet AC-6
A1: Control AC-6 — Evidence Tracking | D1: Contrôle AC-6 — Suivi des preuves
A2: Control Information | D2: Informations du contrôle
A3: Control Identifier | B3: AC-6 | D3: Identifiant du contrôle | E3: AC-6
A4: Family | B4: Least Privilege | D4: Famille | E4: Moindre privilège
A5: Profile | B5: CCCS Medium / PBMM Moderate | D5: Profil | E5: CCCS Moyen / PBMM Modéré
A6: Primary Evidence Tool | D6: Outil de preuve principal
A7: Contributing Tools | D7: Outils contributeurs
A8: Control Description | B8: (A) The organization employs the principle of least privilege, allowing only authorized accesses for users (or processes acting on behalf of users) which are necessary to accomplish assigned tasks in accordance with organizational missions and business functions. | D8: Description du contrôle | E8: (A) L’organisation utilise le principe du moindre privilège, qui permet seulement les accès autorisés aux utilisateurs (ou aux processus qui agissent pour le compte des utilisateurs) qui sont nécessaires pour accomplir les tâches assignées conformément aux missions et aux fonctions opérationnelles de l’organisation.
A9: Supplemental Guidance | B9: Organizations employ least privilege for specific duties and information systems. The principle of least privilege is also applied to information system processes, ensuring that the processes operate at privilege levels no higher than necessary to accomplish required organizational missions/business functions. Organizations consider the creation of additional processes, roles, and information system accounts as necessary, to achieve least privilege. Organizations also apply least privilege to the development, implementation, and operation of organizational information systems. Related controls: AC-2, AC-3, AC-5, CM-6, CM-7, PL-2 | D9: Directives supplémentaires | E9: Les organisations utilisent le moindre privilège pour certaines tâches et certains systèmes d’information. Le principe du moindre privilège s’applique également aux processus du système d’information, ce qui fait en sorte que les processus ne fonctionnent pas à des niveaux de privilège plus élevés que nécessaire pour accomplir les missions et les fonctions opérationnelles requises de l’organisation. Les organisations envisagent la création de processus, de rôles et de comptes de système d’information supplémentaires lorsque nécessaire, pour obtenir le moindre privilège. Les organisations appliquent également le moindre privilège au développement, à la mise en œuvre et à l’exploitation de leurs systèmes d’information. Contrôles connexes : AC-2, AC-3, AC-5, CM-6, CM-7, PL-2
A10: Test Case | D10: Cas de test
A11: Test | B11: TEST-AC-6 | D11: Test | E11: TEST-AC-6
A12: Requirement ID | B12: AC-6 | D12: ID Exigence | E12: AC-6
A13: Component | D13: Composant
A14: Requirement | D14: Exigence
A15: Contextual Design Description | D15: Description contextuelle du design
A16: Evidence Provided | D16: Preuve fournie
A17: Preparer Sign Off (Initials, Date) | D17: Signataire préparateur (Initiales, Date)
A18: Owner Sign Off (Initials, Date) | D18: Signataire propriétaire (Initiales, Date)
A19: Assessor Sign Off (Initials, Date) | D19: Signataire évaluateur (Initiales, Date)
A20: Status | B20: Not Started | D20: Statut | E20: Non commencé
A21: Comments | D21: Commentaires

Sheet AC-6-1
A1: Control AC-6(1) — Evidence Tracking | D1: Contrôle AC-6(1) — Suivi des preuves
A2: Control Information | D2: Informations du contrôle
A3: Control Identifier | B3: AC-6(1) | D3: Identifiant du contrôle | E3: AC-6(1)
A4: Family | B4: Least Privilege | D4: Famille | E4: Moindre privilège
A5: Profile | B5: CCCS Medium / PBMM Moderate | D5: Profil | E5: CCCS Moyen / PBMM Modéré
A6: Primary Evidence Tool | D6: Outil de preuve principal
A7: Contributing Tools | D7: Outils contributeurs
A8: Control Description | B8: LEAST PRIVILEGE | AUTHORIZE ACCESS TO SECURITY FUNCTIONS The organization explicitly authorizes access to all security functions not publicly accessible and all security-relevant information not publicly available. | D8: Description du contrôle | E8: MOINDRE PRIVILÈGE | AUTORISATION D’ACCÈS AUX FONCTIONS DE SÉCURITÉ L’organisation autorise explicitement l’accès à toutes les fonctions de sécurité qui ne sont pas accessibles au public et à toute l’information pertinente à la sécurité qui n’est pas accessible au public.
A9: Supplemental Guidance | B9: Security functions include, for example, establishing system accounts, configuring access authorizations (i.e., permissions, privileges), setting events to be audited, and setting intrusion detection parameters. Security-relevant information includes, for example, filtering rules for routers/firewalls, cryptographic key management information, configuration parameters for security services, and access control lists. Explicitly authorized personnel include, for example, security administrators, system and network administrators, system security officers, system maintenance personnel, system programmers, and other privileged users. Related controls: AC-17, AC-18, AC-19. | D9: Directives supplémentaires | E9: Les fonctions de sécurité comprennent, par exemple, l’établissement des comptes système, la configuration des autorisations d’accès (c.-à-d. les permissions, les privilèges), le réglage des événements à vérifier, et l’établissement des paramètres de détection des intrusions. Les renseignements pertinents pour la sécurité comprennent, par exemple, les règles de filtrage pour les routeurs/pare-feu, l’information de gestion des clés cryptographiques, les paramètres de configuration pour les services de sécurité et les listes de contrôle d’accès. Le personnel explicitement autorisé comprend, par exemple, les administrateurs de la sécurité, les administrateurs de systèmes et de réseaux, les agents de sécurité des systèmes, le personnel de maintenance des systèmes, les programmeurs de systèmes et d’autres utilisateurs privilégiés. Contrôles connexes : AC-17, AC-18, AC-19.
A10: Test Case | D10: Cas de test
A11: Test | B11: TEST-AC-6(1) | D11: Test | E11: TEST-AC-6(1)
A12: Requirement ID | B12: AC-6(1) | D12: ID Exigence | E12: AC-6(1)
A13: Component | D13: Composant
A14: Requirement | D14: Exigence
A15: Contextual Design Description | D15: Description contextuelle du design
A16: Evidence Provided | D16: Preuve fournie
A17: Preparer Sign Off (Initials, Date) | D17: Signataire préparateur (Initiales, Date)
A18: Owner Sign Off (Initials, Date) | D18: Signataire propriétaire (Initiales, Date)
A19: Assessor Sign Off (Initials, Date) | D19: Signataire évaluateur (Initiales, Date)
A20: Status | B20: Not Started | D20: Statut | E20: Non commencé
A21: Comments | D21: Commentaires

Sheet AC-6-9
A1: Control AC-6(9) — Evidence Tracking | D1: Contrôle AC-6(9) — Suivi des preuves
A2: Control Information | D2: Informations du contrôle
A3: Control Identifier | B3: AC-6(9) | D3: Identifiant du contrôle | E3: AC-6(9)
A4: Family | B4: Least Privilege | D4: Famille | E4: Moindre privilège
A5: Profile | B5: CCCS Medium / PBMM Moderate | D5: Profil | E5: CCCS Moyen / PBMM Modéré
A6: Primary Evidence Tool | D6: Outil de preuve principal
A7: Contributing Tools | D7: Outils contributeurs
A8: Control Description | B8: LEAST PRIVILEGE | AUDITING USE OF PRIVILEGED FUNCTIONS The information system audits the execution of privileged functions. | D8: Description du contrôle | E8: MOINDRE PRIVILÈGE | VÉRIFICATION DE L’UTILISATION DES FONCTIONS PRIVILÉGIÉES Le système d’information vérifie l’exécution des fonctions privilégiées.
A9: Supplemental Guidance | B9: Misuse of privileged functions, either intentionally or unintentionally by authorized users, or by unauthorized external entities that have compromised information system accounts, is a serious and ongoing concern and can have significant adverse impacts on organizations. Auditing the use of privileged functions is one way to detect such misuse, and in doing so, help mitigate the risk from insider threats and the advanced persistent threat (APT). Related control: AU-2. | D9: Directives supplémentaires | E9: L’utilisation abusive des fonctions privilégiées, intentionnellement ou non, par des utilisateurs autorisés ou par des entités externes non autorisées qui ont compromis des comptes de système d’information, est une préoccupation grave et constante qui peut avoir des répercussions négatives importantes sur les organisations. La vérification de l’utilisation des fonctions privilégiées est une façon de détecter un tel abus et, ce faisant, de contribuer à atténuer le risque de menaces internes et de menaces persistantes avancées (MPA). Contrôle connexe : AU-2.
A10: Test Case | D10: Cas de test
A11: Test | B11: TEST-AC-6(9) | D11: Test | E11: TEST-AC-6(9)
A12: Requirement ID | B12: AC-6(9) | D12: ID Exigence | E12: AC-6(9)
A13: Component | D13: Composant
A14: Requirement | D14: Exigence
A15: Contextual Design Description | D15: Description contextuelle du design
A16: Evidence Provided | D16: Preuve fournie
A17: Preparer Sign Off (Initials, Date) | D17: Signataire préparateur (Initiales, Date)
A18: Owner Sign Off (Initials, Date) | D18: Signataire propriétaire (Initiales, Date)
A19: Assessor Sign Off (Initials, Date) | D19: Signataire évaluateur (Initiales, Date)
A20: Status | B20: Not Started | D20: Statut | E20: Non commencé
A21: Comments | D21: Commentaires

Sheet AC-17-1
A1: Control AC-17(1) — Evidence Tracking | D1: Contrôle AC-17(1) — Suivi des preuves
A2: Control Information | D2: Informations du contrôle
A3: Control Identifier | B3: AC-17(1) | D3: Identifiant du contrôle | E3: AC-17(1)
A4: Family | B4: Remote Access | D4: Famille | E4: Accès à distance
A5: Profile | B5: CCCS Medium / PBMM Moderate | D5: Profil | E5: CCCS Moyen / PBMM Modéré
A6: Primary Evidence Tool | D6: Outil de preuve principal
A7: Contributing Tools | D7: Outils contributeurs
A8: Control Description | B8: REMOTE ACCESS | AUTOMATED MONITORING / CONTROL The information system monitors and controls remote access methods. | D8: Description du contrôle | E8: ACCÈS À DISTANCE | SURVEILLANCE ET CONTRÔLE AUTOMATISÉS Le système d’information surveille et contrôle les méthodes d’accès à distance.
A9: Supplemental Guidance | B9: Automated monitoring and control of remote access sessions allows organizations to detect cyber-attacks and also ensure ongoing compliance with remote access policies by auditing connection activities of remote users on a variety of information system components (e.g., servers, workstations, notebook computers, smart phones, and tablets). Related controls: AU-2, AU-12. | D9: Directives supplémentaires | E9: La surveillance et le contrôle automatisés des sessions avec accès à distance permettent aux organisations de détecter les cyberattaques et d’assurer la conformité continue aux politiques d’accès à distance en vérifiant les activités de connexion des utilisateurs distants sur une variété de composants du système d’information (p. ex., serveurs, postes de travail, ordinateurs portatifs, téléphones intelligents et tablettes). Contrôles connexes : AU-2, AU-12.
A10: Test Case | D10: Cas de test
A11: Test | B11: TEST-AC-17(1) | D11: Test | E11: TEST-AC-17(1)
A12: Requirement ID | B12: AC-17(1) | D12: ID Exigence | E12: AC-17(1)
A13: Component | D13: Composant
A14: Requirement | D14: Exigence
A15: Contextual Design Description | D15: Description contextuelle du design
A16: Evidence Provided | D16: Preuve fournie
A17: Preparer Sign Off (Initials, Date) | D17: Signataire préparateur (Initiales, Date)
A18: Owner Sign Off (Initials, Date) | D18: Signataire propriétaire (Initiales, Date)
A19: Assessor Sign Off (Initials, Date) | D19: Signataire évaluateur (Initiales, Date)
A20: Status | B20: Not Started | D20: Statut | E20: Non commencé
A21: Comments | D21: Commentaires

Sheet AU-2
A1: Control AU-2 — Evidence Tracking | D1: Contrôle AU-2 — Suivi des preuves
A2: Control Information | D2: Informations du contrôle
A3: Control Identifier | B3: AU-2 | D3: Identifiant du contrôle | E3: AU-2
A4: Family | B4: Auditable Events | D4: Famille | E4: Événements vérifiables
A5: Profile | B5: CCCS Medium / PBMM Moderate | D5: Profil | E5: CCCS Moyen / PBMM Modéré
A6: Primary Evidence Tool | D6: Outil de preuve principal
A7: Contributing Tools | D7: Outils contributeurs
A8: Control Description | B8: (A) The organization determines that the information system is capable of auditing the following events: Successful and unsuccessful account logon events, account management events, object access, policy change, privilege functions, process tracking, and system events. For Web applications: all administrator activity, authentication checks, authorization checks, data deletions, data access, data changes, and permission changes. (B) The organization coordinates the security audit function with other organizational entities requiring audit-related information to enhance mutual support and to help guide the selection of auditable events. (C) The organization provides a rationale for why the auditable events are deemed to be adequate to support after-the-fact investigations of security incidents. (D) The organization determines what organizationally-defined audited events (a subset of the auditable events defined in AU-2 a.) and the frequency of (or situation requiring) auditing for each identified event. | D8: Description du contrôle | E8: (A) L’organisation détermine que le système d’information est capable de vérifier les événements suivants : événements d’ouverture de compte, réussis ou non, événements de gestion de compte, accès aux objets, changement de politique, fonctions de privilèges, suivi des processus et événements du système. Pour les applications Web : toutes les activités des administrateurs, les vérifications d’authentification, les vérifications d’autorisation, les suppressions de données, l’accès aux données, les changements de données et les changements d’autorisation. (B) L’organisation coordonne la fonction de vérification de la sécurité avec d’autres entités organisationnelles qui ont besoin de renseignements liés à la vérification pour améliorer le soutien mutuel et aider à orienter le choix des événements vérifiables. (C) L’organisation explique la raison pour laquelle les événements vérifiables sont jugés adéquats pour appuyer les enquêtes effectuées à la suite des incidents de sécurité. (D) L’organisation détermine les événements définis par l’organisation qui sont vérifiés (un sous-ensemble des événements vérifiables définis dans AU-2 a.) et la fréquence (ou la situation exigeant) des vérifications pour chaque événement identifié.
A9: Supplemental Guidance | B9: An event is any observable occurrence in an organizational information system. Organizations identify audit events as those events which are significant and relevant to the security of information systems and the environments in which those systems operate in order to meet specific and ongoing audit needs. Audit events can include, for example, password changes, failed logons, or failed accesses related to information systems, administrative privilege usage, or third-party credential usage. In determining the set of auditable events, organizations consider the auditing appropriate for each of the security controls to be implemented. To balance auditing requirements with other information system needs, this control also requires identifying that subset of auditable events that are audited at a given point in time. For example, organizations may determine that information systems must have the capability to log every file access both successful and unsuccessful, but not activate that capability except for specific circumstances due to the potential burden on system performance. Auditing requirements, including the need for auditable events, may be referenced in other security controls and control enhancements. Organizations also include auditable events that are required by applicable organizational policies, directives, and standards. Audit records can be generated at various levels of abstraction, including at the packet level as information traverses the network. Selecting the appropriate level of abstraction is a critical aspect of an audit capability and can facilitate the identification of root causes to problems. Organizations consider in the definition of auditable events, the auditing necessary to cover related events such as the steps in distributed, transaction-based processes (e.g., processes that are distributed across multiple organizations) and actions that occur in service-oriented architectures. The information system audits the following privileged user/process events at a minimum: (a) Successful and unsuccessful attempts to access, modify, or delete security objects (Security objects include audit data, system configuration files and file or users’ formal access permissions.) (b) Successful and unsuccessful logon attempts (c) Privileged activities or other system level access (see notes for AU-2 (4)) (d) Starting and ending time for user access to the system (e) Concurrent logons from different workstations (f) All program initiations (see notes for AU-2 (4)) In addition, the information system audits the following unprivileged user/process events at a minimum: (a) Successful and unsuccessful attempts to access, modify, or delete security objects (b) Successful and unsuccessful logon attempts (c) Starting and ending time for user access to the system (d) Concurrent logons from different workstations Related controls: AC-6, AC-17, AU-3, AU-12, MA-4, MP-2, MP-4, SI-4 | D9: Directives supplémentaires | E9: Un événement est toute occurrence observable dans un système d’information organisationnel. Les organisations désignent les événements vérifiables comme étant des événements importants et pertinents pour la sécurité des systèmes d’information et des environnements dans lesquels ces systèmes sont utilisés afin de répondre à des exigences de vérification particulières et continues. Les événements vérifiés peuvent comprendre, par exemple, les changements de mot de passe, les échecs d’ouverture de session ou les échecs accès liés aux systèmes d’information, l’utilisation des privilèges administratifs ou l’utilisation de justificatifs d’identité par des tiers. Lorsqu’elles déterminent l’ensemble des événements vérifiables, les organisations considèrent que la vérification est appropriée pour chacun des contrôles de sécurité à mettre en œuvre. Pour assurer l’équilibre entre les exigences en matière de vérification et les autres besoins du système d’information, ce contrôle exige également de déterminer le sous-ensemble d’événements vérifiables qui sont vérifiés à un moment donné. Par exemple, les organisations peuvent déterminer que les systèmes d’information doivent avoir la capacité d’enregistrer chaque accès aux fichiers, qu’il soit réussi ou non, mais n’activeront cette capacité que dans des circonstances particulières en raison du fardeau potentiel sur le rendement du système. Les exigences en matière de vérification, y compris la nécessité de déterminer des événements vérifiables, peuvent être mentionnées dans d’autres contrôles et améliorations des contrôles de sécurité. Les organisations incluent également les événements vérifiables qui sont exigés par les politiques, les directives et les normes organisationnelles applicables. Les enregistrements de vérification peuvent être générés à divers niveaux d’abstraction, y compris au niveau des paquets, à mesure que l’information traverse le réseau. Le choix du niveau d’abstraction approprié est un aspect essentiel d’une capacité de vérification et peut faciliter l’identification des causes profondes des problèmes. Dans la définition des événements vérifiables, les organisations prennent en compte la vérification nécessaire pour couvrir les événements connexes, comme les étapes des processus distribués, fondés sur les transactions (p. ex., les processus qui sont répartis entre de multiples organisations) et les actions qui ont lieu dans les architectures orientées service. Le système d’information vérifie au minimum les événements suivants liés aux utilisateurs/processus privilégiés : (a) Tentatives réussies et infructueuses d’accéder aux objets de sécurité, de les modifier ou de les supprimer (les objets de sécurité comprennent les données de vérification, les fichiers de configuration de système et les autorisations d’accès officielles des utilisateurs). (b) Tentatives d’ouverture de session réussies et infructueuses (c) Activités privilégiées ou autre accès au niveau du système (voir les notes pour AU-2 [4]) (d) Heures de début et de fin de l’accès des utilisateurs au système (e) Ouvertures de session simultanées à partir de différents postes de travail (f) Tous les lancements de programmes (voir les notes pour AU-2 [4]) De plus, le système d’information vérifie au minimum les événements suivants liés aux utilisateurs/processus non privilégiés : (a) Tentatives réussies et infructueuses d’accès, de modification ou de suppression d’objets de sécurité (b) Tentatives d’ouverture de session réussies et infructueuses (c) Heures de début et de fin de l’accès de l’utilisateur au système (d) Ouvertures de session simultanées à partir de différents postes de travail Contrôles connexes : AC-6, AC-17, AU-3, AU-12, MA-4, MP-2, MP-4, SI-4
A10: Test Case | D10: Cas de test
A11: Test | B11: TEST-AU-2 | D11: Test | E11: TEST-AU-2
A12: Requirement ID | B12: AU-2 | D12: ID Exigence | E12: AU-2
A13: Component | D13: Composant
A14: Requirement | D14: Exigence
A15: Contextual Design Description | D15: Description contextuelle du design
A16: Evidence Provided | D16: Preuve fournie
A17: Preparer Sign Off (Initials, Date) | D17: Signataire préparateur (Initiales, Date)
A18: Owner Sign Off (Initials, Date) | D18: Signataire propriétaire (Initiales, Date)
A19: Assessor Sign Off (Initials, Date) | D19: Signataire évaluateur (Initiales, Date)
A20: Status | B20: Not Started | D20: Statut | E20: Non commencé
A21: Comments | D21: Commentaires

Sheet AU-3
A1: Control AU-3 — Evidence Tracking | D1: Contrôle AU-3 — Suivi des preuves
A2: Control Information | D2: Informations du contrôle
A3: Control Identifier | B3: AU-3 | D3: Identifiant du contrôle | E3: AU-3
A4: Family | B4: Content of Audit Records | D4: Famille | E4: Contenu des enregistrements de vérification
A5: Profile | B5: CCCS Medium / PBMM Moderate | D5: Profil | E5: CCCS Moyen / PBMM Modéré
A6: Primary Evidence Tool | D6: Outil de preuve principal
A7: Contributing Tools | D7: Outils contributeurs
A8: Control Description | B8: (A) The information system generates audit records containing information that establishes what type of event occurred, when the event occurred, where the event occurred, the source of the event, the outcome of the event, and the identity of any individuals or subjects associated with the event. | D8: Description du contrôle | E8: (A) Le système d’information génère des enregistrements de vérification qui contiennent les renseignements permettant d’établir le type d’événement qui a eu lieu, le moment et l’endroit où l’événement a eu lieu, la source de l’événement, le résultat de l’événement, ainsi que l’identité de toute personne ou de tout sujet associé à l’événement.
A9: Supplemental Guidance | B9: Audit record content that may be necessary to satisfy the requirement of this control, includes, for example, time stamps, source and destination addresses, user/process identifiers, event descriptions, success/fail indications, filenames involved, and access control or flow control rules invoked. Event outcomes can include indicators of event success or failure and event-specific results (e.g., the security state of the information system after the event occurred). Related controls: AU-2, AU-8, AU-12, SI-11 | D9: Directives supplémentaires | E9: Le contenu des enregistrements de vérification qui peut être nécessaire pour satisfaire à l’exigence de ce contrôle comprend, par exemple, les estampilles temporelles, les adresses de source et de destination, les identifiants d’utilisateurs ou de processus, les descriptions d’événements, les indications de réussite ou d’échec, les noms des fichiers en cause et les règles de contrôle d’accès ou de flux invoquées. Les résultats de l’événement peuvent comprendre des indicateurs de réussite ou d’échec de l’événement et des résultats propres à l’événement (p. ex., l’état de sécurité du système d’information après l’événement). Contrôles connexes : AU-2, AU-8, AU-12, SI-11
A10: Test Case | D10: Cas de test
A11: Test | B11: TEST-AU-3 | D11: Test | E11: TEST-AU-3
A12: Requirement ID | B12: AU-3 | D12: ID Exigence | E12: AU-3
A13: Component | D13: Composant
A14: Requirement | D14: Exigence
A15: Contextual Design Description | D15: Description contextuelle du design
A16: Evidence Provided | D16: Preuve fournie
A17: Preparer Sign Off (Initials, Date) | D17: Signataire préparateur (Initiales, Date)
A18: Owner Sign Off (Initials, Date) | D18: Signataire propriétaire (Initiales, Date)
A19: Assessor Sign Off (Initials, Date) | D19: Signataire évaluateur (Initiales, Date)
A20: Status | B20: Not Started | D20: Statut | E20: Non commencé
A21: Comments | D21: Commentaires

Sheet AU-3-1
A1: Control AU-3(1) — Evidence Tracking | D1: Contrôle AU-3(1) — Suivi des preuves
A2: Control Information | D2: Informations du contrôle
A3: Control Identifier | B3: AU-3(1) | D3: Identifiant du contrôle | E3: AU-3(1)
A4: Family | B4: Content of Audit Records | D4: Famille | E4: Contenu des enregistrements de vérification
A5: Profile | B5: CCCS Medium / PBMM Moderate | D5: Profil | E5: CCCS Moyen / PBMM Modéré
A6: Primary Evidence Tool | D6: Outil de preuve principal
A7: Contributing Tools | D7: Outils contributeurs
A8: Control Description | B8: CONTENT OF AUDIT RECORDS | ADDITIONAL AUDIT INFORMATION The information system generates audit records containing the following additional information: session, connection, transaction, or activity duration; for client-server transactions, the number of bytes received and bytes sent; additional informational messages to diagnose or identify the event; characteristics that describe or identify the object or resource being acted upon. | D8: Description du contrôle | E8: CONTENU DES ENREGISTREMENTS DE VÉRIFICATION | RENSEIGNEMENTS DE VÉRIFICATION SUPPLÉMENTAIRES Le système d’information génère des enregistrements de vérification contenant les renseignements supplémentaires suivants : la durée de la session, de la connexion, de la transaction ou de l’activité; pour les transactions client-serveur, le nombre d’octets reçus et d’octets envoyés; des messages d’information supplémentaires pour diagnostiquer ou identifier l’événement; les caractéristiques qui décrivent ou identifient l’objet ou la ressource concernés.
A9: Supplemental Guidance | B9: Detailed information that organizations may consider in audit records includes, for example, full text recording of privileged commands or the individual identities of group account users. Organizations consider limiting the additional audit information to only that information explicitly needed for specific audit requirements. This facilitates the use of audit trails and audit logs by not including information that could potentially be misleading or could make it more difficult to locate information of interest. Additional guidance for enhancement (1): Audit events should always be capable of being associated with an individual identity. Associating audit events with a group or role is insufficient. | D9: Directives supplémentaires | E9: Les renseignements détaillés dont les organisations peuvent tenir compte dans les enregistrements de vérification comprennent, par exemple, l’enregistrement en texte intégral des commandes privilégiées ou les identités individuelles des utilisateurs de comptes de groupe. Les organisations devraient envisager de limiter les renseignements de vérification supplémentaires aux seuls renseignements explicitement nécessaires pour répondre à des exigences de vérification particulières. Cela facilitera l’utilisation des pistes de vérification et des journaux de vérification en n’incluant pas les renseignements qui pourraient être trompeurs ou rendre plus difficile la recherche de renseignements utiles. Conseils supplémentaires pour l’amélioration (1) : Les événements vérifiés devraient toujours pouvoir être associés à une identité individuelle. Associer des événements vérifiés à un groupe ou à un rôle est insuffisant.
A10: Test Case | D10: Cas de test
A11: Test | B11: TEST-AU-3(1) | D11: Test | E11: TEST-AU-3(1)
A12: Requirement ID | B12: AU-3(1) | D12: ID Exigence | E12: AU-3(1)
A13: Component | D13: Composant
A14: Requirement | D14: Exigence
A15: Contextual Design Description | D15: Description contextuelle du design
A16: Evidence Provided | D16: Preuve fournie
A17: Preparer Sign Off (Initials, Date) | D17: Signataire préparateur (Initiales, Date)
A18: Owner Sign Off (Initials, Date) | D18: Signataire propriétaire (Initiales, Date)
A19: Assessor Sign Off (Initials, Date) | D19: Signataire évaluateur (Initiales, Date)
A20: Status | B20: Not Started | D20: Statut | E20: Non commencé
A21: Comments | D21: Commentaires

Sheet AU-5
A1: Control AU-5 — Evidence Tracking | D1: Contrôle AU-5 — Suivi des preuves
A2: Control Information | D2: Informations du contrôle
A3: Control Identifier | B3: AU-5 | D3: Identifiant du contrôle | E3: AU-5
A4: Family | B4: Response To Audit Processing Failures | D4: Famille | E4: Réponse aux échecs de traitement de vérification
A5: Profile | B5: CCCS Medium / PBMM Moderate | D5: Profil | E5: CCCS Moyen / PBMM Modéré
A6: Primary Evidence Tool | D6: Outil de preuve principal
A7: Contributing Tools | D7: Outils contributeurs
A8: Control Description | B8: (A) The information system alerts organization-defined personnel or roles in the event of an audit processing failure; and (B) The information system overwrites the oldest audit records. | D8: Description du contrôle | E8: (A) Le système d’information alerte le personnel ou les rôles définis par l’organisation en cas d’échec de traitement de vérification; (B) Le système d’information écrase les enregistrements de vérification les plus anciens.
A9: Supplemental Guidance | B9: Audit processing failures include, for example, software/hardware errors, failures in the audit capturing mechanisms, and audit storage capacity being reached or exceeded. Organizations may choose to define additional actions for different audit processing failures (e.g., by type, by location, by severity, or a combination of such factors). This control applies to each audit data storage repository (i.e., distinct information system component where audit records are stored), the total audit storage capacity of organizations (i.e., all audit data storage repositories combined), or both. Related controls: AU-4, SI-12 | D9: Directives supplémentaires | E9: Les échecs de traitement de vérification comprennent, par exemple, les erreurs de logiciel ou de matériel, les défaillances des mécanismes de saisie des vérifications et la capacité de stockage atteinte ou dépassée pour les vérifications. Les organisations peuvent choisir de définir des mesures supplémentaires pour différents échecs de traitement de vérification (p. ex., par type, par emplacement, par gravité ou une combinaison de ces facteurs). Ce contrôle s’applique à chaque répertoire de stockage des données de vérification (c.-à -d. à chaque composant distinct du système d’information dans lequel les enregistrements de vérification sont conservés), à la capacité totale de stockage des vérifications des organisations (c.-à-d. tous les répertoires de stockage des données de vérification combinés), ou aux deux. Contrôles connexes : AU-4, SI-12
A10: Test Case | D10: Cas de test
A11: Test | B11: TEST-AU-5 | D11: Test | E11: TEST-AU-5
A12: Requirement ID | B12: AU-5 | D12: ID Exigence | E12: AU-5
A13: Component | D13: Composant
A14: Requirement | D14: Exigence
A15: Contextual Design Description | D15: Description contextuelle du design
A16: Evidence Provided | D16: Preuve fournie
A17: Preparer Sign Off (Initials, Date) | D17: Signataire préparateur (Initiales, Date)
A18: Owner Sign Off (Initials, Date) | D18: Signataire propriétaire (Initiales, Date)
A19: Assessor Sign Off (Initials, Date) | D19: Signataire évaluateur (Initiales, Date)
A20: Status | B20: Not Started | D20: Statut | E20: Non commencé
A21: Comments | D21: Commentaires

Sheet AU-6-1
A1: Control AU-6(1) — Evidence Tracking | D1: Contrôle AU-6(1) — Suivi des preuves
A2: Control Information | D2: Informations du contrôle
A3: Control Identifier | B3: AU-6(1) | D3: Identifiant du contrôle | E3: AU-6(1)
A4: Family | B4: Audit Review, Analysis, and Reporting | D4: Famille | E4: Examen, analyse et rapport de vérification
A5: Profile | B5: CCCS Medium / PBMM Moderate | D5: Profil | E5: CCCS Moyen / PBMM Modéré
A6: Primary Evidence Tool | D6: Outil de preuve principal
A7: Contributing Tools | D7: Outils contributeurs
A8: Control Description | B8: AUDIT REVIEW, ANALYSIS, AND REPORTING | PROCESS INTEGRATION The organization employs automated mechanisms to integrate audit review, analysis, and reporting processes to support organizational processes for investigation and response to suspicious activities. | D8: Description du contrôle | E8: EXAMEN, ANALYSE ET RAPPORT DE VÉRIFICATION | INTÉGRATION DES PROCESSUS L’organisation utilise des mécanismes automatisés pour intégrer les processus d’examen, d’analyse et de production de rapports de vérification afin de soutenir les processus organisationnels d’enquête et d’intervention en cas d’activités suspectes.
A9: Supplemental Guidance | B9: Organizational processes benefiting from integrated audit review, analysis, and reporting include, for example, incident response, continuous monitoring, and contingency planning. Related control: AU-12. | D9: Directives supplémentaires | E9: Les processus organisationnels qui bénéficient de l’intégration de l’examen, de l’analyse et de la production de rapports de vérification sont notamment l’intervention en cas d’incident, la surveillance continue et la planification d’urgence. Contrôle connexe : AU-12.
A10: Test Case | D10: Cas de test
A11: Test | B11: TEST-AU-6(1) | D11: Test | E11: TEST-AU-6(1)
A12: Requirement ID | B12: AU-6(1) | D12: ID Exigence | E12: AU-6(1)
A13: Component | D13: Composant
A14: Requirement | D14: Exigence
A15: Contextual Design Description | D15: Description contextuelle du design
A16: Evidence Provided | D16: Preuve fournie
A17: Preparer Sign Off (Initials, Date) | D17: Signataire préparateur (Initiales, Date)
A18: Owner Sign Off (Initials, Date) | D18: Signataire propriétaire (Initiales, Date)
A19: Assessor Sign Off (Initials, Date) | D19: Signataire évaluateur (Initiales, Date)
A20: Status | B20: Not Started | D20: Statut | E20: Non commencé
A21: Comments | D21: Commentaires

Sheet AU-6-3
A1: Control AU-6(3) — Evidence Tracking | D1: Contrôle AU-6(3) — Suivi des preuves
A2: Control Information | D2: Informations du contrôle
A3: Control Identifier | B3: AU-6(3) | D3: Identifiant du contrôle | E3: AU-6(3)
A4: Family | B4: Audit Review, Analysis, and Reporting | D4: Famille | E4: Examen, analyse et rapport de vérification
A5: Profile | B5: CCCS Medium / PBMM Moderate | D5: Profil | E5: CCCS Moyen / PBMM Modéré
A6: Primary Evidence Tool | D6: Outil de preuve principal
A7: Contributing Tools | D7: Outils contributeurs
A8: Control Description | B8: AUDIT REVIEW, ANALYSIS, AND REPORTING | CORRELATE AUDIT REPOSITORIES The organization analyzes and correlates audit records across different repositories to gain organization-wide situational awareness. | D8: Description du contrôle | E8: EXAMEN, ANALYSE ET RAPPORT DE VÉRIFICATION | MISE EN CORRÉLATION DES RÉPERTOIRES DE VÉRIFICATION L’organisation analyse et met en corrélation les enregistrements de vérification entre les différents répertoires afin d’acquérir une connaissance globale de la situation dans l’ensemble de l’organisation.
A9: Supplemental Guidance | B9: Organization-wide situational awareness includes awareness across all three tiers of risk management (i.e., organizational, mission/business process, and information system) and supports cross-organization awareness. Related controls: AU-12, IR-4. | D9: Directives supplémentaires | E9: La connaissance de la situation dans l’ensemble de l’organisation comprend la connaissance aux trois niveaux de la gestion des risques (c.-à-d. au niveau de l’organisation, de la mission/des processus opérationnels, et du système d’information) et appuie une connaissance transorganisationnelle de la situation. Contrôles connexes : AU-12, IR-4.
A10: Test Case | D10: Cas de test
A11: Test | B11: TEST-AU-6(3) | D11: Test | E11: TEST-AU-6(3)
A12: Requirement ID | B12: AU-6(3) | D12: ID Exigence | E12: AU-6(3)
A13: Component | D13: Composant
A14: Requirement | D14: Exigence
A15: Contextual Design Description | D15: Description contextuelle du design
A16: Evidence Provided | D16: Preuve fournie
A17: Preparer Sign Off (Initials, Date) | D17: Signataire préparateur (Initiales, Date)
A18: Owner Sign Off (Initials, Date) | D18: Signataire propriétaire (Initiales, Date)
A19: Assessor Sign Off (Initials, Date) | D19: Signataire évaluateur (Initiales, Date)
A20: Status | B20: Not Started | D20: Statut | E20: Non commencé
A21: Comments | D21: Commentaires

Sheet AU-7
A1: Control AU-7 — Evidence Tracking | D1: Contrôle AU-7 — Suivi des preuves
A2: Control Information | D2: Informations du contrôle
A3: Control Identifier | B3: AU-7 | D3: Identifiant du contrôle | E3: AU-7
A4: Family | B4: Audit Reduction and Report Generation | D4: Famille | E4: Réduction des vérifications et production de rapports
A5: Profile | B5: CCCS Medium / PBMM Moderate | D5: Profil | E5: CCCS Moyen / PBMM Modéré
A6: Primary Evidence Tool | D6: Outil de preuve principal
A7: Contributing Tools | D7: Outils contributeurs
A8: Control Description | B8: (A) The information system provides an audit reduction and report generation capability that supports on-demand audit review, analysis, and reporting requirements and after-the-fact investigations of security incidents. (B) The information system provides an audit reduction and report generation capability that does not alter the original content or time ordering of audit records. | D8: Description du contrôle | E8: (A) Le système d’information offre une capacité de réduction des vérifications et de production de rapports prenant en charge les examens, les analyses et les rapports de vérification sur demande ainsi que les enquêtes à la suite d’incidents de sécurité. (B) Le système d’information offre une capacité de réduction de la vérification et de production de rapports qui ne modifie pas le contenu original ou l’ordre chronologique des enregistrements de vérification.
A9: Supplemental Guidance | B9: Audit reduction is a process that manipulates collected audit information and organizes such information in a summary format that is more meaningful to analysts. Audit reduction and report generation capabilities do not always emanate from the same information system or from the same organizational entities conducting auditing activities. Audit reduction capability can include, for example, modern data mining techniques with advanced data filters to identify anomalous behaviour in audit records. The report generation capability provided by the information system can generate customizable reports. Time ordering of audit records can be a significant issue if the granularity of the timestamp in the record is insufficient. Related control: AU-6 | D9: Directives supplémentaires | E9: La réduction de la vérification est un processus qui permet de manipuler l’information recueillie et de l’organiser dans un format sommaire plus significatif pour les analystes. Les capacités de réduction des vérifications et de production de rapports ne proviennent pas toujours du système d’information ou des entités organisationnelles qui mènent les activités de vérification. La capacité de réduction des vérifications peut comprendre, par exemple, des techniques modernes d’exploration de données avec filtres de données avancés pour déceler les comportements anormaux dans les enregistrements de vérification. La capacité de production de rapports fournie par le système d’information permet de générer des rapports personnalisables. L’ordre chronologique des enregistrements de vérification peut poser un problème important si la granularité de l’estampille temporelle dans l’enregistrement est insuffisante. Contrôle connexe : AU-6
A10: Test Case | D10: Cas de test
A11: Test | B11: TEST-AU-7 | D11: Test | E11: TEST-AU-7
A12: Requirement ID | B12: AU-7 | D12: ID Exigence | E12: AU-7
A13: Component | D13: Composant
A14: Requirement | D14: Exigence
A15: Contextual Design Description | D15: Description contextuelle du design
A16: Evidence Provided | D16: Preuve fournie
A17: Preparer Sign Off (Initials, Date) | D17: Signataire préparateur (Initiales, Date)
A18: Owner Sign Off (Initials, Date) | D18: Signataire propriétaire (Initiales, Date)
A19: Assessor Sign Off (Initials, Date) | D19: Signataire évaluateur (Initiales, Date)
A20: Status | B20: Not Started | D20: Statut | E20: Non commencé
A21: Comments | D21: Commentaires

Sheet AU-7-1
A1: Control AU-7(1) — Evidence Tracking | D1: Contrôle AU-7(1) — Suivi des preuves
A2: Control Information | D2: Informations du contrôle
A3: Control Identifier | B3: AU-7(1) | D3: Identifiant du contrôle | E3: AU-7(1)
A4: Family | B4: Audit Reduction and Report Generation | D4: Famille | E4: Réduction des vérifications et production de rapports
A5: Profile | B5: CCCS Medium / PBMM Moderate | D5: Profil | E5: CCCS Moyen / PBMM Modéré
A6: Primary Evidence Tool | D6: Outil de preuve principal
A7: Contributing Tools | D7: Outils contributeurs
A8: Control Description | B8: AUDIT REDUCTION AND REPORT GENERATION | AUTOMATIC PROCESSING The information system provides the capability to process audit records for events of interest based on all audit fields specified in AU-2, AU-3 and AU-3(1). | D8: Description du contrôle | E8: RÉDUCTION DES VÉRIFICATIONS ET PRODUCTION DE RAPPORTS | TRAITEMENT AUTOMATIQUE Le système d’information permet de traiter les enregistrements de vérification relatifs aux événements d’intérêt en fonction de tous les champs de vérification précisés dans AU-2, AU-3 et AU-3(1).
A9: Supplemental Guidance | B9: Events of interest can be identified by the content of specific audit record fields including, for example, identities of individuals, event types, event locations, event times, event dates, system resources involved, IP addresses involved, or information objects accessed. Organizations may define audit event criteria to any degree of granularity required, for example, locations selectable by general networking location (e.g., by network or sub-network) or selectable by specific information system component. Related controls: AU-2, AU-12. | D9: Directives supplémentaires | E9: Les événements d’intérêt peuvent être définis par le contenu des champs particuliers de l’enregistrement de vérification, y compris, par exemple, les identités des personnes, les types d’événements, les emplacements des événements, les heures des événements, les dates des événements, les ressources du système en cause, les adresses IP en cause ou les objets d’information consultés. Les organisations peuvent définir les critères des événements de vérification à n’importe quel degré de granularité requis, par exemple, les emplacements que l’on peut sélectionner par emplacement de réseautique général (p. ex., par réseau ou sous-réseau) ou par composant de système d’information particulier. Contrôles connexes : AU-2, AU-12.
A10: Test Case | D10: Cas de test
A11: Test | B11: TEST-AU-7(1) | D11: Test | E11: TEST-AU-7(1)
A12: Requirement ID | B12: AU-7(1) | D12: ID Exigence | E12: AU-7(1)
A13: Component | D13: Composant
A14: Requirement | D14: Exigence
A15: Contextual Design Description | D15: Description contextuelle du design
A16: Evidence Provided | D16: Preuve fournie
A17: Preparer Sign Off (Initials, Date) | D17: Signataire préparateur (Initiales, Date)
A18: Owner Sign Off (Initials, Date) | D18: Signataire propriétaire (Initiales, Date)
A19: Assessor Sign Off (Initials, Date) | D19: Signataire évaluateur (Initiales, Date)
A20: Status | B20: Not Started | D20: Statut | E20: Non commencé
A21: Comments | D21: Commentaires

Sheet AU-8
A1: Control AU-8 — Evidence Tracking | D1: Contrôle AU-8 — Suivi des preuves
A2: Control Information | D2: Informations du contrôle
A3: Control Identifier | B3: AU-8 | D3: Identifiant du contrôle | E3: AU-8
A4: Family | B4: Time Stamps | D4: Famille | E4: Estampilles temporelles
A5: Profile | B5: CCCS Medium / PBMM Moderate | D5: Profil | E5: CCCS Moyen / PBMM Modéré
A6: Primary Evidence Tool | D6: Outil de preuve principal
A7: Contributing Tools | D7: Outils contributeurs
A8: Control Description | B8: (A) The information system uses internal system clocks to generate time stamps for audit records. (B) The information system records time stamps for audit records that can be mapped to Coordinated Universal Time (UTC) or Greenwich Mean Time (GMT) within 1 second precision. | D8: Description du contrôle | E8: (A) Le système d’information utilise les horloges système internes afin de générer les estampilles temporelles pour les enregistrements de vérification. (B) Le système d’information enregistre des estampilles temporelles pour les enregistrements de vérification qui peuvent être mappées sur le temps universel coordonné (UTC) ou l’heure moyenne de Greenwich (GMT) à la seconde près.
A9: Supplemental Guidance | B9: Time stamps generated by the information system include date and time. Time is commonly expressed in Coordinated Universal Time (UTC) or local time with an offset from UTC. Granularity of time measurements refers to the degree of synchronization between information system clocks and reference clocks, for example, clocks synchronizing within hundreds of milliseconds or within tens of milliseconds. Organizations may define different time granularities for different system components. Time service can also be critical to other security capabilities such as access control and identification and authentication, depending on the nature of the mechanisms used to support those capabilities. Related controls: AU-3, AU-12 | D9: Directives supplémentaires | E9: Les estampilles temporelles générées par le système d’information comprennent la date et l’heure. L’heure est généralement exprimée en temps universel coordonné (UTC) ou selon l’heure locale avec indication du décalage par rapport à l’UTC. La granularité des mesures du temps désigne le niveau de synchronisation entre les horloges du système d’information et les horloges de référence, par exemple, des horloges synchronisées à quelques centaines ou dizaines de millisecondes près. Les organisations peuvent définir différentes granularités temporelles pour différents composants du système. Le service de l’heure peut également être essentiel à d’autres capacités de sécurité comme le contrôle d’accès, l’identification et l’authentification, selon la nature des mécanismes utilisés pour soutenir ces capacités. Contrôles connexes : AU-3, AU-12
A10: Test Case | D10: Cas de test
A11: Test | B11: TEST-AU-8 | D11: Test | E11: TEST-AU-8
A12: Requirement ID | B12: AU-8 | D12: ID Exigence | E12: AU-8
A13: Component | D13: Composant
A14: Requirement | D14: Exigence
A15: Contextual Design Description | D15: Description contextuelle du design
A16: Evidence Provided | D16: Preuve fournie
A17: Preparer Sign Off (Initials, Date) | D17: Signataire préparateur (Initiales, Date)
A18: Owner Sign Off (Initials, Date) | D18: Signataire propriétaire (Initiales, Date)
A19: Assessor Sign Off (Initials, Date) | D19: Signataire évaluateur (Initiales, Date)
A20: Status | B20: Not Started | D20: Statut | E20: Non commencé
A21: Comments | D21: Commentaires

Sheet AU-8-1
A1: Control AU-8(1) — Evidence Tracking | D1: Contrôle AU-8(1) — Suivi des preuves
A2: Control Information | D2: Informations du contrôle
A3: Control Identifier | B3: AU-8(1) | D3: Identifiant du contrôle | E3: AU-8(1)
A4: Family | B4: Time Stamps | D4: Famille | E4: Estampilles temporelles
A5: Profile | B5: CCCS Medium / PBMM Moderate | D5: Profil | E5: CCCS Moyen / PBMM Modéré
A6: Primary Evidence Tool | D6: Outil de preuve principal
A7: Contributing Tools | D7: Outils contributeurs
A8: Control Description | B8: TIME STAMPS | SYNCHRONIZATION WITH AUTHORITATIVE TIME SOURCE (a) The information system compares the internal information system clocks at least every 24 hours with an organization-defined authoritative time source; and (b) The information system synchronizes the internal system clocks to the authoritative time source when the time difference is greater than 1 millisecond. | D8: Description du contrôle | E8: ESTAMPILLES TEMPORELLES | SYNCHRONISATION AVEC UNE SOURCE D’HORODATAGE RECONNUE (a) Le système d’information compare les horloges internes du système d’information au moins toutes les 24 heures avec une source d’horodatage reconnue définie par l’organisation. (b) Le système d’information synchronise les horloges internes du système avec la source d’horodatage reconnue lorsque la différence de temps est supérieure à 1 milliseconde.
A9: Supplemental Guidance | B9: This control enhancement provides uniformity of time stamps for information systems with multiple system clocks and systems connected over a network. | D9: Directives supplémentaires | E9: Cette amélioration du contrôle assure l’uniformité des estampilles temporelles pour les systèmes d’information dotés de nombreuses horloges et les systèmes sur un réseau.
A10: Test Case | D10: Cas de test
A11: Test | B11: TEST-AU-8(1) | D11: Test | E11: TEST-AU-8(1)
A12: Requirement ID | B12: AU-8(1) | D12: ID Exigence | E12: AU-8(1)
A13: Component | D13: Composant
A14: Requirement | D14: Exigence
A15: Contextual Design Description | D15: Description contextuelle du design
A16: Evidence Provided | D16: Preuve fournie
A17: Preparer Sign Off (Initials, Date) | D17: Signataire préparateur (Initiales, Date)
A18: Owner Sign Off (Initials, Date) | D18: Signataire propriétaire (Initiales, Date)
A19: Assessor Sign Off (Initials, Date) | D19: Signataire évaluateur (Initiales, Date)
A20: Status | B20: Not Started | D20: Statut | E20: Non commencé
A21: Comments | D21: Commentaires

Sheet AU-9
A1: Control AU-9 — Evidence Tracking | D1: Contrôle AU-9 — Suivi des preuves
A2: Control Information | D2: Informations du contrôle
A3: Control Identifier | B3: AU-9 | D3: Identifiant du contrôle | E3: AU-9
A4: Family | B4: Protection of Audit Information | D4: Famille | E4: Protection des renseignements de vérification
A5: Profile | B5: CCCS Medium / PBMM Moderate | D5: Profil | E5: CCCS Moyen / PBMM Modéré
A6: Primary Evidence Tool | D6: Outil de preuve principal
A7: Contributing Tools | D7: Outils contributeurs
A8: Control Description | B8: (A) The information system protects audit information and audit tools from unauthorized access, modification, and deletion. | D8: Description du contrôle | E8: (A) Le système d’information protège les renseignements de vérification et les outils de vérification contre l’accès, la modification et la suppression non autorisés.
A9: Supplemental Guidance | B9: Audit information includes all information (e.g., audit records, audit settings, and audit reports) needed to successfully audit information system activity. This control focuses on technical protection of audit information. Physical protection of audit information is addressed by media protection controls and physical and environmental protection controls. Related controls: AC-3, AC-6, MP-2, MP-4, PE-2, PE-3, PE-6 | D9: Directives supplémentaires | E9: Les renseignements de vérification comprennent tous les renseignements (p. ex., les enregistrements de vérification, les paramètres de vérification et les rapports de vérification) nécessaires pour vérifier avec succès l’activité du système d’information. Ce contrôle est axé sur la protection technique des renseignements de vérification. La protection physique des renseignements de vérification est assurée par des contrôles de protection des supports et des contrôles de protection physique et environnementale. Contrôles connexes : AC-3, AC-6, MP-2, MP-4, PE-2, PE-3, PE-6
A10: Test Case | D10: Cas de test
A11: Test | B11: TEST-AU-9 | D11: Test | E11: TEST-AU-9
A12: Requirement ID | B12: AU-9 | D12: ID Exigence | E12: AU-9
A13: Component | D13: Composant
A14: Requirement | D14: Exigence
A15: Contextual Design Description | D15: Description contextuelle du design
A16: Evidence Provided | D16: Preuve fournie
A17: Preparer Sign Off (Initials, Date) | D17: Signataire préparateur (Initiales, Date)
A18: Owner Sign Off (Initials, Date) | D18: Signataire propriétaire (Initiales, Date)
A19: Assessor Sign Off (Initials, Date) | D19: Signataire évaluateur (Initiales, Date)
A20: Status | B20: Not Started | D20: Statut | E20: Non commencé
A21: Comments | D21: Commentaires

Sheet AU-9-2
A1: Control AU-9(2) — Evidence Tracking | D1: Contrôle AU-9(2) — Suivi des preuves
A2: Control Information | D2: Informations du contrôle
A3: Control Identifier | B3: AU-9(2) | D3: Identifiant du contrôle | E3: AU-9(2)
A4: Family | B4: Protection of Audit Information | D4: Famille | E4: Protection des renseignements de vérification
A5: Profile | B5: CCCS Medium / PBMM Moderate | D5: Profil | E5: CCCS Moyen / PBMM Modéré
A6: Primary Evidence Tool | D6: Outil de preuve principal
A7: Contributing Tools | D7: Outils contributeurs
A8: Control Description | B8: PROTECTION OF AUDIT INFORMATION | AUDIT BACKUP ON SEPARATE PHYSICAL SYSTEMS / COMPONENTS The information system backs up audit records at least weekly onto a physically different system or system component than the system or component being audited. | D8: Description du contrôle | E8: PROTECTION DES RENSEIGNEMENTS DE VÉRIFICATION | SAUVEGARDE DES VÉRIFICATIONS SUR DES SYSTÈMES/COMPOSANTS PHYSIQUES SÉPARÉS Le système d’information sauvegarde les enregistrements de vérification au moins une fois par semaine sur un système ou un composant système physiquement différent du système ou du composant faisant l’objet de la vérification.
A9: Supplemental Guidance | B9: This control enhancement helps to ensure that a compromise of the information system being audited does not also result in a compromise of the audit records. Related controls: AU-4, AU-5, AU-11. | D9: Directives supplémentaires | E9: Cette amélioration permet de s’assurer qu’une compromission du système d’information faisant l’objet d’une vérification n’entraîne pas également la compromission des enregistrements de vérification. Contrôles connexes : AU-4, AU-5, AU-11.
A10: Test Case | D10: Cas de test
A11: Test | B11: TEST-AU-9(2) | D11: Test | E11: TEST-AU-9(2)
A12: Requirement ID | B12: AU-9(2) | D12: ID Exigence | E12: AU-9(2)
A13: Component | D13: Composant
A14: Requirement | D14: Exigence
A15: Contextual Design Description | D15: Description contextuelle du design
A16: Evidence Provided | D16: Preuve fournie
A17: Preparer Sign Off (Initials, Date) | D17: Signataire préparateur (Initiales, Date)
A18: Owner Sign Off (Initials, Date) | D18: Signataire propriétaire (Initiales, Date)
A19: Assessor Sign Off (Initials, Date) | D19: Signataire évaluateur (Initiales, Date)
A20: Status | B20: Not Started | D20: Statut | E20: Non commencé
A21: Comments | D21: Commentaires

Sheet AU-9-4
A1: Control AU-9(4) — Evidence Tracking | D1: Contrôle AU-9(4) — Suivi des preuves
A2: Control Information | D2: Informations du contrôle
A3: Control Identifier | B3: AU-9(4) | D3: Identifiant du contrôle | E3: AU-9(4)
A4: Family | B4: Protection of Audit Information | D4: Famille | E4: Protection des renseignements de vérification
A5: Profile | B5: CCCS Medium / PBMM Moderate | D5: Profil | E5: CCCS Moyen / PBMM Modéré
A6: Primary Evidence Tool | D6: Outil de preuve principal
A7: Contributing Tools | D7: Outils contributeurs
A8: Control Description | B8: PROTECTION OF AUDIT INFORMATION | ACCESS BY SUBSET OF PRIVILEGED USERS The organization authorizes access to management of audit functionality to only an organization-defined subset of privileged users. | D8: Description du contrôle | E8: PROTECTION DES RENSEIGNEMENTS DE VÉRIFICATION | ACCÈS PAR SOUS-ENSEMBLE D’UTILISATEURS PRIVILÉGIÉS L’organisation n’autorise l’accès à la fonction de gestion de la vérification qu’à un sous-ensemble d’utilisateurs privilégiés défini par l’organisation seulement.
A9: Supplemental Guidance | B9: Individuals with privileged access to an information system and who are also the subject of an audit by that system, may affect the reliability of audit information by inhibiting audit activities or modifying audit records. This control enhancement requires that privileged access be further defined between audit-related privileges and other privileges, thus limiting the users with audit-related privileges. Related control: AC-5. | D9: Directives supplémentaires | E9: Les personnes qui ont un accès privilégié à un système d’information et qui font également l’objet d’une vérification par ce système peuvent nuire à la fiabilité de l’information de vérification en entravant les activités de vérification ou en modifiant les enregistrements de vérification. Cette amélioration du contrôle exige que l’accès privilégié soit mieux défini entre les privilèges liés à la vérification et les autres privilèges, de manière à limiter le nombre d’utilisateurs ayant des privilèges liés à la vérification. Contrôle connexe : AC-5.
A10: Test Case | D10: Cas de test
A11: Test | B11: TEST-AU-9(4) | D11: Test | E11: TEST-AU-9(4)
A12: Requirement ID | B12: AU-9(4) | D12: ID Exigence | E12: AU-9(4)
A13: Component | D13: Composant
A14: Requirement | D14: Exigence
A15: Contextual Design Description | D15: Description contextuelle du design
A16: Evidence Provided | D16: Preuve fournie
A17: Preparer Sign Off (Initials, Date) | D17: Signataire préparateur (Initiales, Date)
A18: Owner Sign Off (Initials, Date) | D18: Signataire propriétaire (Initiales, Date)
A19: Assessor Sign Off (Initials, Date) | D19: Signataire évaluateur (Initiales, Date)
A20: Status | B20: Not Started | D20: Statut | E20: Non commencé
A21: Comments | D21: Commentaires

Sheet AU-11
A1: Control AU-11 — Evidence Tracking | D1: Contrôle AU-11 — Suivi des preuves
A2: Control Information | D2: Informations du contrôle
A3: Control Identifier | B3: AU-11 | D3: Identifiant du contrôle | E3: AU-11
A4: Family | B4: Audit Record Retention | D4: Famille | E4: Conservation des enregistrements de vérification
A5: Profile | B5: CCCS Medium / PBMM Moderate | D5: Profil | E5: CCCS Moyen / PBMM Modéré
A6: Primary Evidence Tool | D6: Outil de preuve principal
A7: Contributing Tools | D7: Outils contributeurs
A8: Control Description | B8: (A) The CSP retains audit records for at least 90 days to provide support for after-the-fact investigations of security incidents and to meet regulatory and organizational information retention requirements. (B) The client retains audit records and logs for at least 3 months online and at least 6 months in storage. (C) The client retains all audit records and logs associated with a security incident for at least 5 years. | D8: Description du contrôle | E8: (A) Le FSI conserve les enregistrements de vérification pendant au moins 90 jours afin de soutenir les enquêtes faisant suite aux incidents de sécurité et de respecter les exigences réglementaires et organisationnelles en matière de conservation de l’information. (B) Le client conserve les enregistrements et les journaux de vérification pendant au moins 3 mois en ligne et au moins 6 mois en mémoire. (C) Le client conserve pendant au moins 5 ans tous les enregistrements et journaux de vérification associés à un incident de sécurité.
A9: Supplemental Guidance | B9: Organizations retain audit records until it is determined that they are no longer needed for administrative, legal, audit, or other operational purposes. This includes, for example, retention and availability of audit records relative to legal requests, subpoenas, and law enforcement actions. Organizations develop standard categories of audit records relative to such types of actions and standard response processes for each type of action. Related controls: AU-4, AU-5, AU-9, MP-6 | D9: Directives supplémentaires | E9: Les organisations conservent les enregistrements de vérification jusqu’à ce qu’il soit déterminé qu’ils ne sont plus nécessaires à des fins administratives, juridiques, de vérification ou à d’autres fins opérationnelles. Cela comprend, par exemple, la conservation et la disponibilité des enregistrements de vérification relatifs aux demandes légales, aux citations à comparaître et aux mesures d’application de la loi. Les organisations établissent des catégories normalisées d’enregistrements de vérification par rapport à ces types de mesures ainsi que des processus de réponse normalisés pour chaque type de mesure. Contrôles connexes : AU-4, AU-5, AU-9, MP-6
A10: Test Case | D10: Cas de test
A11: Test | B11: TEST-AU-11 | D11: Test | E11: TEST-AU-11
A12: Requirement ID | B12: AU-11 | D12: ID Exigence | E12: AU-11
A13: Component | D13: Composant
A14: Requirement | D14: Exigence
A15: Contextual Design Description | D15: Description contextuelle du design
A16: Evidence Provided | D16: Preuve fournie
A17: Preparer Sign Off (Initials, Date) | D17: Signataire préparateur (Initiales, Date)
A18: Owner Sign Off (Initials, Date) | D18: Signataire propriétaire (Initiales, Date)
A19: Assessor Sign Off (Initials, Date) | D19: Signataire évaluateur (Initiales, Date)
A20: Status | B20: Not Started | D20: Statut | E20: Non commencé
A21: Comments | D21: Commentaires

Sheet AU-12
A1: Control AU-12 — Evidence Tracking | D1: Contrôle AU-12 — Suivi des preuves
A2: Control Information | D2: Informations du contrôle
A3: Control Identifier | B3: AU-12 | D3: Identifiant du contrôle | E3: AU-12
A4: Family | B4: Audit Generation | D4: Famille | E4: Génération des vérifications
A5: Profile | B5: CCCS Medium / PBMM Moderate | D5: Profil | E5: CCCS Moyen / PBMM Modéré
A6: Primary Evidence Tool | D6: Outil de preuve principal
A7: Contributing Tools | D7: Outils contributeurs
A8: Control Description | B8: (A) The information system provides audit record generation capability for the auditable events defined in AU-2 a. of all information system and network components where audit capability is deployed/available. (B) The information system allows organization-defined personnel or roles to select which auditable events are to be audited by specific components of the information system. (C) The information system generates audit records for the events defined in AU-2 d. with the content defined in AU-3. | D8: Description du contrôle | E8: (A) Le système d’information offre une capacité de génération d’enregistrements de vérification pour les événements vérifiables définis dans AU-2 a. de tous les composants du système d’information et du réseau où la capacité de vérification est déployée/disponible. (B) Le système d’information permet au personnel ou aux rôles définis par l’organisation de choisir les événements vérifiables qui doivent être vérifiés par des composants précis du système d’information. (C) Le système d’information génère des enregistrements de vérification pour les événements définis dans AU-2 d. avec le contenu défini dans AU-3.
A9: Supplemental Guidance | B9: Audit records can be generated from many different information system components. The list of audited events is the set of events for which audits are to be generated. These events are typically a subset of all events for which the information system is capable of generating audit records. Related controls: AC-3, AU-2, AU-3, AU-6, AU-7 | D9: Directives supplémentaires | E9: Des enregistrements de vérification peuvent être générés à partir de nombreux composants du système d’information. La liste des événements vérifiés est l’ensemble des événements pour lesquels des vérifications doivent être produites. Ces événements sont habituellement un sous-ensemble de tous les événements pour lesquels le système d’information peut générer des enregistrements de vérification. Contrôles connexes : AC-3, AU-2, AU-3, AU-6, AU-7
A10: Test Case | D10: Cas de test
A11: Test | B11: TEST-AU-12 | D11: Test | E11: TEST-AU-12
A12: Requirement ID | B12: AU-12 | D12: ID Exigence | E12: AU-12
A13: Component | D13: Composant
A14: Requirement | D14: Exigence
A15: Contextual Design Description | D15: Description contextuelle du design
A16: Evidence Provided | D16: Preuve fournie
A17: Preparer Sign Off (Initials, Date) | D17: Signataire préparateur (Initiales, Date)
A18: Owner Sign Off (Initials, Date) | D18: Signataire propriétaire (Initiales, Date)
A19: Assessor Sign Off (Initials, Date) | D19: Signataire évaluateur (Initiales, Date)
A20: Status | B20: Not Started | D20: Statut | E20: Non commencé
A21: Comments | D21: Commentaires

Sheet CA-9
A1: Control CA-9 — Evidence Tracking | D1: Contrôle CA-9 — Suivi des preuves
A2: Control Information | D2: Informations du contrôle
A3: Control Identifier | B3: CA-9 | D3: Identifiant du contrôle | E3: CA-9
A4: Family | B4: Internal System Connections | D4: Famille | E4: Connexions internes au système
A5: Profile | B5: CCCS Medium / PBMM Moderate | D5: Profil | E5: CCCS Moyen / PBMM Modéré
A6: Primary Evidence Tool | D6: Outil de preuve principal
A7: Contributing Tools | D7: Outils contributeurs
A8: Control Description | B8: (A) The organization authorizes internal connections of information system components or classes of components to the information system. (B) The organization documents, for each internal connection, the interface characteristics, security requirements, and the nature of the information communicated. | D8: Description du contrôle | E8: (A) L’organisation autorise les connexions internes de composants du système d’information ou de catégories de composants au système d’information. (B) L’organisation documente, pour chaque connexion interne, les caractéristiques de l’interface, les exigences de sécurité et la nature de l’information communiquée.
A9: Supplemental Guidance | B9: This control applies to connections between organizational information systems and (separate) constituent system components (i.e., intra-system connections) including, for example, system connections with mobile devices, notebook/desktop computers, printers, copiers, facsimile machines, scanners, sensors, and servers. Instead of authorizing each individual internal connection, organizations can authorize internal connections for a class of components with common characteristics and/or configurations, for example, all digital printers, scanners, and copiers with a specified processing, storage, and transmission capability or all smart phones with a specific baseline configuration. Related controls: AC-3, AC-4, AC-18, AC-19, AU-2, AU-12, CA-7, CM-2, IA-3, SC-7, SI-4 | D9: Directives supplémentaires | E9: Ce contrôle s’applique aux connexions entre les systèmes d’information organisationnels et les composants (distincts) des systèmes constituants (c.-à-d. les connexions intrasystème) y compris, par exemple, les connexions système avec les appareils mobiles, les ordinateurs portatifs/de bureau, les imprimantes, les photocopieurs, les télécopieurs, les numériseurs, les capteurs et les serveurs. Au lieu d’autoriser chaque connexion interne individuelle, les organisations peuvent autoriser les connexions internes pour une catégorie de composants ayant des caractéristiques ou des configurations communes, par exemple, toutes les imprimantes et tous les numériseurs et photocopieurs numériques ayant une capacité de traitement, de stockage et de transmission spécifiée ou tous les téléphones intelligents ayant une configuration de base spécifique. Contrôles connexes : AC-3, AC-4, AC-18, AC-19, AU-2, AU-12, CA-7, CM-2, IA-3, SC-7, SI-4
A10: Test Case | D10: Cas de test
A11: Test | B11: TEST-CA-9 | D11: Test | E11: TEST-CA-9
A12: Requirement ID | B12: CA-9 | D12: ID Exigence | E12: CA-9
A13: Component | D13: Composant
A14: Requirement | D14: Exigence
A15: Contextual Design Description | D15: Description contextuelle du design
A16: Evidence Provided | D16: Preuve fournie
A17: Preparer Sign Off (Initials, Date) | D17: Signataire préparateur (Initiales, Date)
A18: Owner Sign Off (Initials, Date) | D18: Signataire propriétaire (Initiales, Date)
A19: Assessor Sign Off (Initials, Date) | D19: Signataire évaluateur (Initiales, Date)
A20: Status | B20: Not Started | D20: Statut | E20: Non commencé
A21: Comments | D21: Commentaires

Sheet CM-5-1
A1: Control CM-5(1) — Evidence Tracking | D1: Contrôle CM-5(1) — Suivi des preuves
A2: Control Information | D2: Informations du contrôle
A3: Control Identifier | B3: CM-5(1) | D3: Identifiant du contrôle | E3: CM-5(1)
A4: Family | B4: Access Restrictions for Change | D4: Famille | E4: Restrictions d’accès pour les changements
A5: Profile | B5: CCCS Medium / PBMM Moderate | D5: Profil | E5: CCCS Moyen / PBMM Modéré
A6: Primary Evidence Tool | D6: Outil de preuve principal
A7: Contributing Tools | D7: Outils contributeurs
A8: Control Description | B8: ACCESS RESTRICTIONS FOR CHANGE | AUTOMATED ACCESS ENFORCEMENT / AUDITING The information system enforces access restrictions and supports auditing of the enforcement actions. | D8: Description du contrôle | E8: RESTRICTIONS D’ACCÈS POUR LES CHANGEMENTS | CONTRÔLE AUTOMATISÉ DE L’ACCÈS/VÉRIFICATION Le système d’information applique les restrictions d’accès et prend en charge la vérification des contrôles appliqués.
A9: Supplemental Guidance | B9: Related controls: AU-2, AU-12, AU-6, CM-3, and CM-6. | D9: Directives supplémentaires | E9: Contrôles connexes : AU-2, AU-12, AU-6, CM-3 et CM-6.
A10: Test Case | D10: Cas de test
A11: Test | B11: TEST-CM-5(1) | D11: Test | E11: TEST-CM-5(1)
A12: Requirement ID | B12: CM-5(1) | D12: ID Exigence | E12: CM-5(1)
A13: Component | D13: Composant
A14: Requirement | D14: Exigence
A15: Contextual Design Description | D15: Description contextuelle du design
A16: Evidence Provided | D16: Preuve fournie
A17: Preparer Sign Off (Initials, Date) | D17: Signataire préparateur (Initiales, Date)
A18: Owner Sign Off (Initials, Date) | D18: Signataire propriétaire (Initiales, Date)
A19: Assessor Sign Off (Initials, Date) | D19: Signataire évaluateur (Initiales, Date)
A20: Status | B20: Not Started | D20: Statut | E20: Non commencé
A21: Comments | D21: Commentaires

Sheet CM-5-6
A1: Control CM-5(6) — Evidence Tracking | D1: Contrôle CM-5(6) — Suivi des preuves
A2: Control Information | D2: Informations du contrôle
A3: Control Identifier | B3: CM-5(6) | D3: Identifiant du contrôle | E3: CM-5(6)
A4: Family | B4: Access Restrictions for Change | D4: Famille | E4: Restrictions d’accès pour les changements
A5: Profile | B5: CCCS Medium / PBMM Moderate | D5: Profil | E5: CCCS Moyen / PBMM Modéré
A6: Primary Evidence Tool | D6: Outil de preuve principal
A7: Contributing Tools | D7: Outils contributeurs
A8: Control Description | B8: ACCESS RESTRICTIONS FOR CHANGE | LIMIT LIBRARY PRIVILEGES The organization limits privileges to change software resident within software libraries. | D8: Description du contrôle | E8: RESTRICTIONS D’ACCÈS POUR LES CHANGEMENTS | LIMITER LES PRIVILÈGES RELATIFS AUX BIBLIOTHÈQUES L’organisation limite les privilèges relatifs aux modifications du logiciel résidant dans les bibliothèques de logiciels.
A9: Supplemental Guidance | B9: Software libraries include privileged programs. Related control: AC-2. | D9: Directives supplémentaires | E9: Les bibliothèques de logiciels comprennent des programmes privilégiés. Contrôle connexe : AC-2.
A10: Test Case | D10: Cas de test
A11: Test | B11: TEST-CM-5(6) | D11: Test | E11: TEST-CM-5(6)
A12: Requirement ID | B12: CM-5(6) | D12: ID Exigence | E12: CM-5(6)
A13: Component | D13: Composant
A14: Requirement | D14: Exigence
A15: Contextual Design Description | D15: Description contextuelle du design
A16: Evidence Provided | D16: Preuve fournie
A17: Preparer Sign Off (Initials, Date) | D17: Signataire préparateur (Initiales, Date)
A18: Owner Sign Off (Initials, Date) | D18: Signataire propriétaire (Initiales, Date)
A19: Assessor Sign Off (Initials, Date) | D19: Signataire évaluateur (Initiales, Date)
A20: Status | B20: Not Started | D20: Statut | E20: Non commencé
A21: Comments | D21: Commentaires

Sheet CM-6
A1: Control CM-6 — Evidence Tracking | D1: Contrôle CM-6 — Suivi des preuves
A2: Control Information | D2: Informations du contrôle
A3: Control Identifier | B3: CM-6 | D3: Identifiant du contrôle | E3: CM-6
A4: Family | B4: Configuration Settings | D4: Famille | E4: Paramètres de configuration
A5: Profile | B5: CCCS Medium / PBMM Moderate | D5: Profil | E5: CCCS Moyen / PBMM Modéré
A6: Primary Evidence Tool | D6: Outil de preuve principal
A7: Contributing Tools | D7: Outils contributeurs
A8: Control Description | B8: (A) The organization establishes and documents configuration settings for information technology products employed within the information system using checklists from one or more of the following Center for Internet Security (CIS), National Institute of Standards and Technology (NIST), Defense Information Systems Agency (DISA) that reflect the most restrictive mode consistent with operational requirements. (B) The organization implements the configuration settings. (C) The organization identifies, documents, and approves any deviations from established configuration settings for any configurable infomation system components. (D) The organization monitors and controls changes to the configuration settings in accordance with organizational policies and procedures. | D8: Description du contrôle | E8: (A) L’organisation établit et documente les paramètres de configuration des produits de technologie de l’information utilisés dans le système d’information à l’aide de listes de vérification provenant d’un ou de plusieurs des éléments suivants : Center for Internet Security (CIS), National Institute of Standards and Technology (NIST), Defense Information Systems Agency (DISA), qui reflètent le mode le plus restrictif conformément aux exigences opérationnelles. (B) L’organisation met en œuvre les paramètres de configuration. (C) L’organisation identifie, documente et approuve tout écart par rapport aux paramètres de configuration établis pour les composants configurables du système d’information. (D) L’organisation surveille et contrôle les changements apportés aux paramètres de configuration conformément aux politiques et aux procédures de l’organisation.
A9: Supplemental Guidance | B9: Configuration settings are the set of parameters that can be changed in hardware, software, or firmware components of the information system that affect the security posture and/or functionality of the system. Information technology products for which security-related configuration settings can be defined include, for example, mainframe computers, servers (e.g., database, electronic mail, authentication, web, proxy, file, domain name), workstations, input/output devices (e.g., scanners, copiers, and printers), network components (e.g., firewalls, routers, gateways, voice and data switches, wireless access points, network appliances, sensors), operating systems, middleware, and applications. Security-related parameters are those parameters impacting the security state of information systems including the parameters required to satisfy other security control requirements. Security-related parameters include, for example: (i) registry settings; (ii) account, file, directory permission settings; and (iii) settings for functions, ports, protocols, services, and remote connections. Organizations establish organization-wide configuration settings and subsequently derive specific settings for information systems. The established settings become part of the systems configuration baselineCommon secure configurations (also referred to as security configuration checklists, lockdown and hardening guides, security reference guides, security technical implementation guides (STIG)) provide recognized, standardized, and established benchmarks that stipulate secure configuration settings for specific information technology platforms/products and instructions for configuring those information system components to meet operational requirements. Common secure configurations can be developed by a variety of organizations including, for example, information technology product developers, manufacturers, vendors, consortia, academia, industry, federal government organizations, and others in the public and private sectors. The Security Content Automation Protocol (SCAP) and the defined standards within the protocol (e.g., Common Configuration Enumeration) provide an effective method to uniquely identify, track, and control configuration settings. Related controls: AC-19, CM-2, CM-3, CM-7, SI-4. | D9: Directives supplémentaires | E9: Les paramètres de configuration sont l’ensemble de paramètres qui peuvent être modifiés dans les composants matériels, logiciels ou micrologiciels du système d’information et qui ont une incidence sur la posture de sécurité ou la fonctionnalité du système. Les produits de technologie de l’information pour lesquels les paramètres de configuration liés à la sécurité peuvent être définis comprennent, par exemple, les ordinateurs centraux, les serveurs (p. ex., base de données, courrier électronique, authentification, Web, mandataire, fichiers, noms de domaine), les postes de travail, les périphériques d’entrée et de sortie (p. ex., numériseurs, photocopieurs et imprimantes), les composants de réseau (p. ex., pare-feu, routeurs, passerelles, commutateurs de voix et de données, points d’accès sans fil, outils de réseau, capteurs), les systèmes d’exploitation, les intergiciels et les applications. Les paramètres liés à la sécurité sont les paramètres qui influent sur l’état de sécurité des systèmes d’information, y compris les paramètres requis pour satisfaire à d’autres exigences de contrôle de sécurité. Les paramètres liés à la sécurité comprennent, par exemple : (i) les paramètres des registres; (ii) les paramètres de comptes, de fichiers, d’autorisation de répertoires; (iii) les paramètres des fonctions, des ports, des protocoles, des services et des connexions à distance. Les organisations établissent les paramètres de configuration à l’échelle de l’organisation et en déduisent ensuite les paramètres particuliers pour les systèmes d’information. Les paramètres établis font partie des configurations de base des systèmes Les configurations sécurisées communes (aussi appelées listes de vérification de la configuration de sécurité, guides de verrouillage et de renforcement, guides de référence de sécurité, guides de mise en œuvre technique de la sécurité [STIG]) fournissent des repères reconnus, normalisés et établis qui stipulent les paramètres de configuration sécurisée pour des plateformes/produits de technologie de l’information particuliers et des instructions pour configurer ces composants de système d’information de manière à répondre aux exigences opérationnelles. Les configurations sécurisées communes peuvent être mises au point par diverses organisations, y compris, par exemple, les concepteurs de produits de technologie de l’information, les fabricants, les fournisseurs, les consortiums, le milieu universitaire, l’industrie, les organisations du gouvernement fédéral et d’autres intervenants des secteurs public et privé. Le protocole d’automatisation du contenu de sécurité SCAP (Security Content Automation Protocol) et les normes définies dans le protocole (p. ex., Common Configuration Enumeration) constituent une méthode efficace pour déterminer, suivre et contrôler de façon unique les paramètres de configuration. Contrôles connexes : AC-19, CM-2, CM-3, CM-7, SI-4.
A10: Test Case | D10: Cas de test
A11: Test | B11: TEST-CM-6 | D11: Test | E11: TEST-CM-6
A12: Requirement ID | B12: CM-6 | D12: ID Exigence | E12: CM-6
A13: Component | D13: Composant
A14: Requirement | D14: Exigence
A15: Contextual Design Description | D15: Description contextuelle du design
A16: Evidence Provided | D16: Preuve fournie
A17: Preparer Sign Off (Initials, Date) | D17: Signataire préparateur (Initiales, Date)
A18: Owner Sign Off (Initials, Date) | D18: Signataire propriétaire (Initiales, Date)
A19: Assessor Sign Off (Initials, Date) | D19: Signataire évaluateur (Initiales, Date)
A20: Status | B20: Not Started | D20: Statut | E20: Non commencé
A21: Comments | D21: Commentaires

Sheet CM-7
A1: Control CM-7 — Evidence Tracking | D1: Contrôle CM-7 — Suivi des preuves
A2: Control Information | D2: Informations du contrôle
A3: Control Identifier | B3: CM-7 | D3: Identifiant du contrôle | E3: CM-7
A4: Family | B4: Least Functionality | D4: Famille | E4: Moindre fonctionnalité
A5: Profile | B5: CCCS Medium / PBMM Moderate | D5: Profil | E5: CCCS Moyen / PBMM Modéré
A6: Primary Evidence Tool | D6: Outil de preuve principal
A7: Contributing Tools | D7: Outils contributeurs
A8: Control Description | B8: (A) The organization configures the information system to provide only essential capabilities. (B) The organization prohibits or restricts the use of identified functions, ports, protocols, and/or services following one or more standards from Center for Internet Security (CIS), National Institute of Standards and Technology (NIST), or Defense Information Systems Agency (DISA). | D8: Description du contrôle | E8: (A) L’organisation configure le système d’information pour n’offrir que les capacités essentielles. (B) L’organisation interdit ou restreint l’utilisation de fonctions, de ports, de protocoles et/ou de services identifiés en respectant une ou plusieurs normes du Center for Internet Security (CIS), du National Institute of Standards and Technology (NIST) ou de la Defense Information Systems Agency (DISA).
A9: Supplemental Guidance | B9: Information systems can provide a wide variety of functions and services. Some of the functions and services, provided by default, may not be necessary to support essential organizational operations (e.g., key missions, functions). Additionally, it is sometimes convenient to provide multiple services from single information system components, but doing so increases risk over limiting the services provided by any one component. Where feasible, organizations limit component functionality to a single function per device (e.g., email servers or web servers, but not both). Organizations review functions and services provided by information systems or individual components of information systems, to determine which functions and services are candidates for elimination (e.g., Voice over Internet Protocol (VoIP), Instant Messaging, auto-execute, and file sharing). Organizations consider disabling unused or unnecessary physical and logical ports/protocols (e.g., USB, FTP, IPv6, HTTP) on information systems to prevent unauthorized connection of devices, unauthorized transfer of information, or unauthorized tunnelling. Organizations can utilize network scanning tools, intrusion detection and prevention systems, and end-point protections such as firewalls and host-based intrusion detection systems to identify and prevent the use of prohibited functions, ports, protocols, and services. Related controls: AC-6, CM-2, RA-5, SA-5, SC-7 | D9: Directives supplémentaires | E9: Les systèmes d’information peuvent offrir une grande variété de fonctions et de services. Certaines fonctions et certains services, fournis par défaut, peuvent ne pas être nécessaires au soutien des opérations essentielles de l’organisation (p. ex., missions et fonctions clés). De plus, il est parfois pratique de fournir plusieurs services à partir de composants uniques du système d’information, mais cela augmente le risque de limiter les services fournis par un seul composant. Dans la mesure du possible, les organisations limitent la fonctionnalité des composants à une seule fonction par dispositif (p. ex., serveurs de courriel ou serveurs Web, mais pas les deux). Les organisations examinent les fonctions et les services fournis par les systèmes d’information ou les composants individuels des systèmes d’information afin de déterminer quelles fonctions et quels services peuvent être éliminés (p. ex., voix sur protocole Internet [VoIP], messagerie instantanée, auto-exécution et partage de fichiers). Les organisations envisagent de désactiver les ports/protocoles physiques et logiques inutilisés ou inutiles (p. ex., USB, FTP, IPv6, HTTP) sur les systèmes d’information afin de prévenir la connexion non autorisée d’appareils, le transfert non autorisé d’information ou la tunnellisation non autorisée. Les organisations peuvent utiliser des outils de balayage de réseau, des systèmes de détection et de prévention des intrusions et des mesures de protection d’extrémité comme des pare-feu et des systèmes de détection des intrusions basés sur l’hôte, pour identifier et prévenir l’utilisation de fonctions, de ports, de protocoles et de services interdits. Contrôles connexes : AC-6, CM-2, RA-5, SA-5, SC-7
A10: Test Case | D10: Cas de test
A11: Test | B11: TEST-CM-7 | D11: Test | E11: TEST-CM-7
A12: Requirement ID | B12: CM-7 | D12: ID Exigence | E12: CM-7
A13: Component | D13: Composant
A14: Requirement | D14: Exigence
A15: Contextual Design Description | D15: Description contextuelle du design
A16: Evidence Provided | D16: Preuve fournie
A17: Preparer Sign Off (Initials, Date) | D17: Signataire préparateur (Initiales, Date)
A18: Owner Sign Off (Initials, Date) | D18: Signataire propriétaire (Initiales, Date)
A19: Assessor Sign Off (Initials, Date) | D19: Signataire évaluateur (Initiales, Date)
A20: Status | B20: Not Started | D20: Statut | E20: Non commencé
A21: Comments | D21: Commentaires

Sheet CM-7-1
A1: Control CM-7(1) — Evidence Tracking | D1: Contrôle CM-7(1) — Suivi des preuves
A2: Control Information | D2: Informations du contrôle
A3: Control Identifier | B3: CM-7(1) | D3: Identifiant du contrôle | E3: CM-7(1)
A4: Family | B4: Least Functionality | D4: Famille | E4: Moindre fonctionnalité
A5: Profile | B5: CCCS Medium / PBMM Moderate | D5: Profil | E5: CCCS Moyen / PBMM Modéré
A6: Primary Evidence Tool | D6: Outil de preuve principal
A7: Contributing Tools | D7: Outils contributeurs
A8: Control Description | B8: LEAST FUNCTIONALITY | PERIODIC REVIEW The organization reviews the information system at least annually to identify unnecessary and/or non-secure functions, ports, protocols, and services; and The organization disables all functions, ports, protocols, and services within the information system deemed to be unnecessary and/or nonsecure. | D8: Description du contrôle | E8: MOINDRE FONCTIONNALITÉ | EXAMEN PÉRIODIQUE L’organisation revoit le système d’information au moins une fois par année afin de repérer les fonctions, les ports, les protocoles et les services inutiles ou non sécurisés; L’organisation désactive toutes les fonctions, tous les ports, tous les protocoles et tous les services du système d’information jugés inutiles ou non sécurisés.
A9: Supplemental Guidance | B9: The organization can either make a determination of the relative security of the function, port, protocol, and/or service or base the security decision on the assessment of other entities. Bluetooth, FTP, and peer-to-peer networking are examples of less than secure protocols. Related controls: AC-18, CM-7, IA-2. | D9: Directives supplémentaires | E9: L’organisation peut soit déterminer la sécurité relative de la fonction, du port, du protocole ou du service, soit baser sa décision en matière de sécurité sur l’évaluation d’autres entités. Bluetooth, FTP et l’interconnexion de réseaux d’égal à égal sont des exemples de protocoles moins sécurisés. Contrôles connexes : AC-18, CM-7, IA-2.
A10: Test Case | D10: Cas de test
A11: Test | B11: TEST-CM-7(1) | D11: Test | E11: TEST-CM-7(1)
A12: Requirement ID | B12: CM-7(1) | D12: ID Exigence | E12: CM-7(1)
A13: Component | D13: Composant
A14: Requirement | D14: Exigence
A15: Contextual Design Description | D15: Description contextuelle du design
A16: Evidence Provided | D16: Preuve fournie
A17: Preparer Sign Off (Initials, Date) | D17: Signataire préparateur (Initiales, Date)
A18: Owner Sign Off (Initials, Date) | D18: Signataire propriétaire (Initiales, Date)
A19: Assessor Sign Off (Initials, Date) | D19: Signataire évaluateur (Initiales, Date)
A20: Status | B20: Not Started | D20: Statut | E20: Non commencé
A21: Comments | D21: Commentaires

Sheet CP-6
A1: Control CP-6 — Evidence Tracking | D1: Contrôle CP-6 — Suivi des preuves
A2: Control Information | D2: Informations du contrôle
A3: Control Identifier | B3: CP-6 | D3: Identifiant du contrôle | E3: CP-6
A4: Family | B4: Alternate Storage Site | D4: Famille | E4: Site de stockage auxiliaire
A5: Profile | B5: CCCS Medium / PBMM Moderate | D5: Profil | E5: CCCS Moyen / PBMM Modéré
A6: Primary Evidence Tool | D6: Outil de preuve principal
A7: Contributing Tools | D7: Outils contributeurs
A8: Control Description | B8: (A) The organization establishes an alternate storage site including necessary agreements to permit the storage and retrieval of information system backup information. (B) The organization ensures that the alternate storage site provides information security safeguards equivalent to that of the primary site. | D8: Description du contrôle | E8: (A) L’organisation établit un site de stockage auxiliaire, incluant les ententes nécessaires pour permettre le stockage et l’extraction de l’information de sauvegarde du système d’information. (B) L’organisation veille à ce que le site de stockage auxiliaire offre des mesures de sécurité de l’information équivalentes à celles du site principal.
A9: Supplemental Guidance | B9: Alternate storage sites are sites that are geographically distinct from primary storage sites. An alternate storage site maintains duplicate copies of information and data in the event that the primary storage site is not available. Items covered by alternate storage site agreements include, for example, environmental conditions at alternate sites, access rules, physical and environmental protection requirements, and coordination of delivery/retrieval of backup media. Alternate storage sites reflect the requirements in contingency plans so that organizations can maintain essential missions/business functions despite disruption, compromise, or failure in organizational information systems. Related controls: CP-2, CP-7, CP-9, CP-10, MP-4 | D9: Directives supplémentaires | E9: Les sites de stockage auxiliaires sont des sites qui sont géographiquement séparés des sites de stockage principaux. Un site de stockage auxiliaire conserve des copies de l’information et des données advenant la non-disponibilité du site de stockage principal. Les éléments couverts par les accords sur les sites de stockage auxiliaires comprennent, par exemple, les conditions environnementales aux sites auxiliaires, les règles d’accès, les exigences en matière de protection physique et environnementale, et la coordination de la livraison/récupération des supports de sauvegarde. Les sites de stockage auxiliaires reflètent les exigences des plans d’urgence afin que les organisations puissent maintenir les fonctions opérationnelles et de mission essentielles malgré la perturbation, la compromission ou la défaillance des systèmes d’information organisationnels. Contrôles connexes : CP-2, CP-7, CP-9, CP-10, MP-4
A10: Test Case | D10: Cas de test
A11: Test | B11: TEST-CP-6 | D11: Test | E11: TEST-CP-6
A12: Requirement ID | B12: CP-6 | D12: ID Exigence | E12: CP-6
A13: Component | D13: Composant
A14: Requirement | D14: Exigence
A15: Contextual Design Description | D15: Description contextuelle du design
A16: Evidence Provided | D16: Preuve fournie
A17: Preparer Sign Off (Initials, Date) | D17: Signataire préparateur (Initiales, Date)
A18: Owner Sign Off (Initials, Date) | D18: Signataire propriétaire (Initiales, Date)
A19: Assessor Sign Off (Initials, Date) | D19: Signataire évaluateur (Initiales, Date)
A20: Status | B20: Not Started | D20: Statut | E20: Non commencé
A21: Comments | D21: Commentaires

Sheet CP-6-2
A1: Control CP-6(2) — Evidence Tracking | D1: Contrôle CP-6(2) — Suivi des preuves
A2: Control Information | D2: Informations du contrôle
A3: Control Identifier | B3: CP-6(2) | D3: Identifiant du contrôle | E3: CP-6(2)
A4: Family | B4: Alternate Storage Site | D4: Famille | E4: Site de stockage auxiliaire
A5: Profile | B5: CCCS Medium / PBMM Moderate | D5: Profil | E5: CCCS Moyen / PBMM Modéré
A6: Primary Evidence Tool | D6: Outil de preuve principal
A7: Contributing Tools | D7: Outils contributeurs
A8: Control Description | B8: ALTERNATE STORAGE SITE | RECOVERY TIME / POINT OBJECTIVES The organization configures the alternate storage site to facilitate recovery operations in accordance with recovery time and recovery point objectives. | D8: Description du contrôle | E8: SITE DE STOCKAGE AUXILIAIRE | OBJECTIFS EN MATIÈRE DE DÉLAIS/POINTS DE REPRISE L’organisation configure le site de stockage auxiliaire de manière à faciliter les opérations de reprise conformément aux objectifs en matière de délais et de points de reprise.
A9: Supplemental Guidance | D9: Directives supplémentaires
A10: Test Case | D10: Cas de test
A11: Test | B11: TEST-CP-6(2) | D11: Test | E11: TEST-CP-6(2)
A12: Requirement ID | B12: CP-6(2) | D12: ID Exigence | E12: CP-6(2)
A13: Component | D13: Composant
A14: Requirement | D14: Exigence
A15: Contextual Design Description | D15: Description contextuelle du design
A16: Evidence Provided | D16: Preuve fournie
A17: Preparer Sign Off (Initials, Date) | D17: Signataire préparateur (Initiales, Date)
A18: Owner Sign Off (Initials, Date) | D18: Signataire propriétaire (Initiales, Date)
A19: Assessor Sign Off (Initials, Date) | D19: Signataire évaluateur (Initiales, Date)
A20: Status | B20: Not Started | D20: Statut | E20: Non commencé
A21: Comments | D21: Commentaires

Sheet CP-7
A1: Control CP-7 — Evidence Tracking | D1: Contrôle CP-7 — Suivi des preuves
A2: Control Information | D2: Informations du contrôle
A3: Control Identifier | B3: CP-7 | D3: Identifiant du contrôle | E3: CP-7
A4: Family | B4: Alternate Processing Site | D4: Famille | E4: Site de traitement auxiliaire
A5: Profile | B5: CCCS Medium / PBMM Moderate | D5: Profil | E5: CCCS Moyen / PBMM Modéré
A6: Primary Evidence Tool | D6: Outil de preuve principal
A7: Contributing Tools | D7: Outils contributeurs
A8: Control Description | B8: (A) The organization establishes an alternate processing site including necessary agreements to permit the transfer and resumption of organization-defined information system operations for essential missions/business functions within organization-defined time period consistent with recovery time and recovery point objectives when the primary processing capabilities are unavailable. (B) The organization ensures that equipment and supplies required to transfer and resume operations are available at the alternate processing site or contracts are in place to support delivery to the site within the organization-defined time period for transfer/resumption. (C) The organization ensures that the alternate processing site provides information security safeguards equivalent to that of the primary site. | D8: Description du contrôle | E8: (A) L’organisation établit un site de traitement auxiliaire, y compris les ententes nécessaires pour permettre le transfert et la reprise des opérations du système d’information définies par l’organisation pour les missions et les fonctions opérationnelles essentielles à l’intérieur d’une période définie par l’organisation, conformément aux objectifs en matière de délais de reprise et de points de reprise lorsque les capacités de traitement principales ne sont pas disponibles. (B) L’organisation veille à ce que l’équipement et les fournitures nécessaires au transfert et à la reprise des activités soient disponibles au site de traitement auxiliaire, ou à ce que des contrats soient en place pour soutenir la livraison au site à l’intérieur de la période définie par l’organisation pour le transfert ou la reprise. (C) L’organisation veille à ce que le site de traitement auxiliaire offre des mesures de sécurité de l’information équivalentes à celles du site principal.
A9: Supplemental Guidance | B9: Alternate processing sites are sites that are geographically distinct from primary processing sites. An alternate processing site provides processing capability in the event that the primary processing site is not available. Items covered by alternate processing site agreements include, for example, environmental conditions at alternate sites, access rules, physical and environmental protection requirements, and coordination for the transfer/assignment of personnel. Requirements are specifically allocated to alternate processing sites that reflect the requirements in contingency plans to maintain essential missions/business functions despite disruption, compromise, or failure in organizational information systems. Related controls: CP-2, CP-6, CP-8, CP-9, CP-10, MA-6 | D9: Directives supplémentaires | E9: Les sites de traitement auxiliaires sont des sites qui sont géographiquement séparés des sites de traitement principaux. Un site de traitement auxiliaire offre une capacité de traitement lorsque le site de traitement principal n’est pas disponible. Les éléments couverts par les accords sur les sites de traitement auxiliaires comprennent, par exemple, les conditions environnementales aux sites auxiliaires, les règles d’accès, les exigences en matière de protection physique et environnementale, et la coordination pour le transfert ou l’attribution du personnel. Les exigences spécifiquement attribuées aux sites de traitement auxiliaires reflètent les exigences des plans d’urgence pour maintenir les fonctions opérationnelles et de mission essentielles malgré la perturbation, la compromission ou la défaillance des systèmes d’information organisationnels. Contrôles connexes : CP-2, CP-6, CP-8, CP-9, CP-10, MA-6
A10: Test Case | D10: Cas de test
A11: Test | B11: TEST-CP-7 | D11: Test | E11: TEST-CP-7
A12: Requirement ID | B12: CP-7 | D12: ID Exigence | E12: CP-7
A13: Component | D13: Composant
A14: Requirement | D14: Exigence
A15: Contextual Design Description | D15: Description contextuelle du design
A16: Evidence Provided | D16: Preuve fournie
A17: Preparer Sign Off (Initials, Date) | D17: Signataire préparateur (Initiales, Date)
A18: Owner Sign Off (Initials, Date) | D18: Signataire propriétaire (Initiales, Date)
A19: Assessor Sign Off (Initials, Date) | D19: Signataire évaluateur (Initiales, Date)
A20: Status | B20: Not Started | D20: Statut | E20: Non commencé
A21: Comments | D21: Commentaires

Sheet CP-7-4
A1: Control CP-7(4) — Evidence Tracking | D1: Contrôle CP-7(4) — Suivi des preuves
A2: Control Information | D2: Informations du contrôle
A3: Control Identifier | B3: CP-7(4) | D3: Identifiant du contrôle | E3: CP-7(4)
A4: Family | B4: Alternate Processing Site | D4: Famille | E4: Site de traitement auxiliaire
A5: Profile | B5: CCCS Medium / PBMM Moderate | D5: Profil | E5: CCCS Moyen / PBMM Modéré
A6: Primary Evidence Tool | D6: Outil de preuve principal
A7: Contributing Tools | D7: Outils contributeurs
A8: Control Description | B8: ALTERNATE PROCESSING SITE | PREPARATION FOR USE The organization prepares the alternate processing site so that the site is ready to be used as the operational site supporting essential missions and business functions. | D8: Description du contrôle | E8: SITE DE TRAITEMENT AUXILIAIRE | PRÉPARATION À L’UTILISATION L’organisation prépare le site de traitement auxiliaire de manière à ce que le site soit prêt à être utilisé comme site opérationnel prenant en charge les fonctions opérationnelles et les missions essentielles.
A9: Supplemental Guidance | B9: Site preparation includes, for example, establishing configuration settings for information system components at the alternate processing site consistent with the requirements for such settings at the primary site and ensuring that essential supplies and other logistical considerations are in place. Related controls: CM-2, CM-6. | D9: Directives supplémentaires | E9: La préparation du site comprend, par exemple, l’établissement des paramètres de configuration pour les composants du système d’information au site de traitement auxiliaire, conformément aux exigences pour ces paramètres au site principal, et l’assurance que les fournitures essentielles et autres considérations logistiques sont en place. Contrôles connexes : CM-2, CM-6.
A10: Test Case | D10: Cas de test
A11: Test | B11: TEST-CP-7(4) | D11: Test | E11: TEST-CP-7(4)
A12: Requirement ID | B12: CP-7(4) | D12: ID Exigence | E12: CP-7(4)
A13: Component | D13: Composant
A14: Requirement | D14: Exigence
A15: Contextual Design Description | D15: Description contextuelle du design
A16: Evidence Provided | D16: Preuve fournie
A17: Preparer Sign Off (Initials, Date) | D17: Signataire préparateur (Initiales, Date)
A18: Owner Sign Off (Initials, Date) | D18: Signataire propriétaire (Initiales, Date)
A19: Assessor Sign Off (Initials, Date) | D19: Signataire évaluateur (Initiales, Date)
A20: Status | B20: Not Started | D20: Statut | E20: Non commencé
A21: Comments | D21: Commentaires

Sheet CP-9
A1: Control CP-9 — Evidence Tracking | D1: Contrôle CP-9 — Suivi des preuves
A2: Control Information | D2: Informations du contrôle
A3: Control Identifier | B3: CP-9 | D3: Identifiant du contrôle | E3: CP-9
A4: Family | B4: Information System Backup | D4: Famille | E4: Sauvegarde du système d’information
A5: Profile | B5: CCCS Medium / PBMM Moderate | D5: Profil | E5: CCCS Moyen / PBMM Modéré
A6: Primary Evidence Tool | D6: Outil de preuve principal
A7: Contributing Tools | D7: Outils contributeurs
A8: Control Description | B8: (A) The organization conducts backups of user-level information contained in the information system daily incremental; weekly full. (B) The organization conducts backups of system-level information contained in the information system daily incremental; weekly full. (C) The organization conducts backups of information system documentation including security-related documentation daily incremental; weekly full. (D) The organization protects the confidentiality, integrity, and availability of backup information at storage locations. (AA) The organization determines retention periods for essential business information and archived backups. | D8: Description du contrôle | E8: (A) L’organisation effectue des sauvegardes incrémentielles quotidiennes et des sauvegardes hebdomadaires complètes de l’information au niveau de l’utilisateur qui est contenue dans le système d’information. (B) L’organisation effectue des sauvegardes incrémentielles quotidiennes et des sauvegardes hebdomadaires complètes de l’information au niveau du système contenue dans le système d’information. (C) L’organisation effectue des sauvegardes incrémentielles quotidiennes et des sauvegardes hebdomadaires complètes de la documentation relative au système d’information, y compris la documentation liée à la sécurité. (D) L’organisation protège la confidentialité, l’intégrité et la disponibilité de l’information de sauvegarde aux emplacements de stockage. (AA) L’organisation détermine les périodes de conservation des renseignements opérationnels essentiels et des sauvegardes archivées.
A9: Supplemental Guidance | B9: System-level information includes, for example, system-state information, operating system and application software, and licenses. User-level information includes any information other than system-level information. Mechanisms employed by organizations to protect the integrity of information system backups include, for example, digital signatures and cryptographic hashes. Protection of system backup information while in transit is beyond the scope of this control. Information system backups reflect the requirements in contingency plans as well as other organizational requirements for backing up information. Related controls: CP-2, CP-6, MP-4, MP-5, SC-13 | D9: Directives supplémentaires | E9: L’information au niveau du système comprend, par exemple, l’information sur l’état du système, le système d’exploitation, les logiciels d’application et les licences. L’information au niveau de l’utilisateur comprend toute information autre que l’information au niveau du système. Les mécanismes employés par les organisations pour protéger l’intégrité des sauvegardes du système d’information comprennent, par exemple, les signatures numériques et le hachage cryptographique. La protection de l’information de sauvegarde du système pendant le transport dépasse la portée de ce contrôle. Les sauvegardes du système d’information reflètent les exigences des plans d’urgence ainsi que d’autres exigences organisationnelles relatives à la sauvegarde de l’information. Contrôles connexes : CP-2, CP-6, MP-4, MP-5, SC-13
A10: Test Case | D10: Cas de test
A11: Test | B11: TEST-CP-9 | D11: Test | E11: TEST-CP-9
A12: Requirement ID | B12: CP-9 | D12: ID Exigence | E12: CP-9
A13: Component | D13: Composant
A14: Requirement | D14: Exigence
A15: Contextual Design Description | D15: Description contextuelle du design
A16: Evidence Provided | D16: Preuve fournie
A17: Preparer Sign Off (Initials, Date) | D17: Signataire préparateur (Initiales, Date)
A18: Owner Sign Off (Initials, Date) | D18: Signataire propriétaire (Initiales, Date)
A19: Assessor Sign Off (Initials, Date) | D19: Signataire évaluateur (Initiales, Date)
A20: Status | B20: Not Started | D20: Statut | E20: Non commencé
A21: Comments | D21: Commentaires

Sheet CP-9-1
A1: Control CP-9(1) — Evidence Tracking | D1: Contrôle CP-9(1) — Suivi des preuves
A2: Control Information | D2: Informations du contrôle
A3: Control Identifier | B3: CP-9(1) | D3: Identifiant du contrôle | E3: CP-9(1)
A4: Family | B4: Information System Backup | D4: Famille | E4: Sauvegarde du système d’information
A5: Profile | B5: CCCS Medium / PBMM Moderate | D5: Profil | E5: CCCS Moyen / PBMM Modéré
A6: Primary Evidence Tool | D6: Outil de preuve principal
A7: Contributing Tools | D7: Outils contributeurs
A8: Control Description | B8: INFORMATION SYSTEM BACKUP | TESTING FOR RELIABILITY / INTEGRITY The organization tests backup information at least annually to verify media reliability and information integrity. | D8: Description du contrôle | E8: SAUVEGARDE DU SYSTÈME D’INFORMATION | VÉRIFICATION DE LA FIABILITÉ ET DE L’INTÉGRITÉ L’organisation teste l’information de sauvegarde au moins une fois par année pour vérifier la fiabilité des supports et l’intégrité de l’information.
A9: Supplemental Guidance | B9: Related control: CP-4. | D9: Directives supplémentaires | E9: Contrôle connexe : CP-4.
A10: Test Case | D10: Cas de test
A11: Test | B11: TEST-CP-9(1) | D11: Test | E11: TEST-CP-9(1)
A12: Requirement ID | B12: CP-9(1) | D12: ID Exigence | E12: CP-9(1)
A13: Component | D13: Composant
A14: Requirement | D14: Exigence
A15: Contextual Design Description | D15: Description contextuelle du design
A16: Evidence Provided | D16: Preuve fournie
A17: Preparer Sign Off (Initials, Date) | D17: Signataire préparateur (Initiales, Date)
A18: Owner Sign Off (Initials, Date) | D18: Signataire propriétaire (Initiales, Date)
A19: Assessor Sign Off (Initials, Date) | D19: Signataire évaluateur (Initiales, Date)
A20: Status | B20: Not Started | D20: Statut | E20: Non commencé
A21: Comments | D21: Commentaires

Sheet CP-9-2
A1: Control CP-9(2) — Evidence Tracking | D1: Contrôle CP-9(2) — Suivi des preuves
A2: Control Information | D2: Informations du contrôle
A3: Control Identifier | B3: CP-9(2) | D3: Identifiant du contrôle | E3: CP-9(2)
A4: Family | B4: Information System Backup | D4: Famille | E4: Sauvegarde du système d’information
A5: Profile | B5: CCCS Medium / PBMM Moderate | D5: Profil | E5: CCCS Moyen / PBMM Modéré
A6: Primary Evidence Tool | D6: Outil de preuve principal
A7: Contributing Tools | D7: Outils contributeurs
A8: Control Description | B8: INFORMATION SYSTEM BACKUP | TEST RESTORATION USING SAMPLING The organization uses a sample of backup information in the restoration of selected information system functions as part of contingency plan testing. | D8: Description du contrôle | E8: SAUVEGARDE DU SYSTÈME D’INFORMATION | ESSAIS DE RESTAURATION AU MOYEN DE L’ÉCHANTILLONNAGE L’organisation utilise un échantillon de l’information de sauvegarde pour restaurer certaines fonctions du système d’information dans le cadre de la mise à l’essai du plan d’urgence.
A9: Supplemental Guidance | B9: Related control: CP-4. | D9: Directives supplémentaires | E9: Contrôle connexe : CP-4.
A10: Test Case | D10: Cas de test
A11: Test | B11: TEST-CP-9(2) | D11: Test | E11: TEST-CP-9(2)
A12: Requirement ID | B12: CP-9(2) | D12: ID Exigence | E12: CP-9(2)
A13: Component | D13: Composant
A14: Requirement | D14: Exigence
A15: Contextual Design Description | D15: Description contextuelle du design
A16: Evidence Provided | D16: Preuve fournie
A17: Preparer Sign Off (Initials, Date) | D17: Signataire préparateur (Initiales, Date)
A18: Owner Sign Off (Initials, Date) | D18: Signataire propriétaire (Initiales, Date)
A19: Assessor Sign Off (Initials, Date) | D19: Signataire évaluateur (Initiales, Date)
A20: Status | B20: Not Started | D20: Statut | E20: Non commencé
A21: Comments | D21: Commentaires

Sheet CP-9-5
A1: Control CP-9(5) — Evidence Tracking | D1: Contrôle CP-9(5) — Suivi des preuves
A2: Control Information | D2: Informations du contrôle
A3: Control Identifier | B3: CP-9(5) | D3: Identifiant du contrôle | E3: CP-9(5)
A4: Family | B4: Information System Backup | D4: Famille | E4: Sauvegarde du système d’information
A5: Profile | B5: CCCS Medium / PBMM Moderate | D5: Profil | E5: CCCS Moyen / PBMM Modéré
A6: Primary Evidence Tool | D6: Outil de preuve principal
A7: Contributing Tools | D7: Outils contributeurs
A8: Control Description | B8: INFORMATION SYSTEM BACKUP | TRANSFER TO ALTERNATE STORAGE SITE The organization transfers information system backup information to the alternate storage site at organization-defined time period and transfer rate consistent with the recovery time and recovery point objectives. | D8: Description du contrôle | E8: SAUVEGARDE DU SYSTÈME D’INFORMATION | TRANSFERT À UN SITE DE STOCKAGE AUXILIAIRE L’organisation transfère l’information de sauvegarde du système d’information au site de stockage auxiliaire au moment et à la vitesse de transfert définis par l’organisation conformément aux objectifs en matière de délais et de points de reprise.
A9: Supplemental Guidance | B9: Information system backup information can be transferred to alternate storage sites either electronically or by physical shipment of storage media. | D9: Directives supplémentaires | E9: Les données de sauvegarde du système d’information peuvent être transférées à des sites de stockage auxiliaires par voie électronique ou par envoi physique de supports de stockage.
A10: Test Case | D10: Cas de test
A11: Test | B11: TEST-CP-9(5) | D11: Test | E11: TEST-CP-9(5)
A12: Requirement ID | B12: CP-9(5) | D12: ID Exigence | E12: CP-9(5)
A13: Component | D13: Composant
A14: Requirement | D14: Exigence
A15: Contextual Design Description | D15: Description contextuelle du design
A16: Evidence Provided | D16: Preuve fournie
A17: Preparer Sign Off (Initials, Date) | D17: Signataire préparateur (Initiales, Date)
A18: Owner Sign Off (Initials, Date) | D18: Signataire propriétaire (Initiales, Date)
A19: Assessor Sign Off (Initials, Date) | D19: Signataire évaluateur (Initiales, Date)
A20: Status | B20: Not Started | D20: Statut | E20: Non commencé
A21: Comments | D21: Commentaires

Sheet CP-10
A1: Control CP-10 — Evidence Tracking | D1: Contrôle CP-10 — Suivi des preuves
A2: Control Information | D2: Informations du contrôle
A3: Control Identifier | B3: CP-10 | D3: Identifiant du contrôle | E3: CP-10
A4: Family | B4: Information System Recovery and Reconstitution | D4: Famille | E4: Reprise et reconstitution du système d’information
A5: Profile | B5: CCCS Medium / PBMM Moderate | D5: Profil | E5: CCCS Moyen / PBMM Modéré
A6: Primary Evidence Tool | D6: Outil de preuve principal
A7: Contributing Tools | D7: Outils contributeurs
A8: Control Description | B8: (A) The organization provides for the recovery and reconstitution of the information system to a known state after a disruption, compromise, or failure. | D8: Description du contrôle | E8: (A) L’organisation assure la reprise et la reconstitution du système d’information dans un état connu après une perturbation, une compromission ou une défaillance.
A9: Supplemental Guidance | B9: Recovery is executing information system contingency plan activities to restore organizational missions/business functions. Reconstitution takes place following recovery and includes activities for returning organizational information systems to fully operational states. Recovery and reconstitution operations reflect mission and business priorities, recovery point/time and reconstitution objectives, and established organizational metrics consistent with contingency plan requirements. Reconstitution includes the deactivation of any interim information system capabilities that may have been needed during recovery operations. Reconstitution also includes assessments of fully restored information system capabilities, reestablishment of continuous monitoring activities, potential information system reauthorizations, and activities to prepare the systems against future disruptions, compromises, or failures. Recovery/reconstitution capabilities employed by organizations can include both automated mechanisms and manual procedures. Related controls: CA-2, CA-6, CA-7, CP-2, CP-4, CP-6, CP-7, CP-9, SC-24 | D9: Directives supplémentaires | E9: La reprise consiste à exécuter les activités du plan d’urgence du système d’information pour restaurer les fonctions opérationnelles et de mission de l’organisation. La reconstitution a lieu après la reprise et comprend les activités permettant de remettre les systèmes d’information organisationnels à l’état pleinement opérationnel. Les opérations de reprise et de reconstitution reflètent les priorités opérationnelles et de mission, les objectifs en matière de délais, de points de reprise et de reconstitution, de même que les paramètres organisationnels établis conformément aux exigences du plan d’urgence. La reconstitution comprend la désactivation de toute capacité provisoire du système d’information ayant pu être nécessaire pendant les opérations de reprise. La reconstitution comprend également l’évaluation des capacités entièrement restaurées du système d’information, le rétablissement des activités de surveillance continue, les réautorisations possibles du système d’information et les activités visant à préparer les systèmes à faire face aux perturbations, compromissions ou défaillances futures. Les capacités de reprise et de reconstitution utilisées par les organisations peuvent comprendre des mécanismes automatisés et des procédures manuelles. Contrôles connexes : CA-2, CA-6, CA-7, CP-2, CP-4, CP-6, CP-7, CP-9, SC-24
A10: Test Case | D10: Cas de test
A11: Test | B11: TEST-CP-10 | D11: Test | E11: TEST-CP-10
A12: Requirement ID | B12: CP-10 | D12: ID Exigence | E12: CP-10
A13: Component | D13: Composant
A14: Requirement | D14: Exigence
A15: Contextual Design Description | D15: Description contextuelle du design
A16: Evidence Provided | D16: Preuve fournie
A17: Preparer Sign Off (Initials, Date) | D17: Signataire préparateur (Initiales, Date)
A18: Owner Sign Off (Initials, Date) | D18: Signataire propriétaire (Initiales, Date)
A19: Assessor Sign Off (Initials, Date) | D19: Signataire évaluateur (Initiales, Date)
A20: Status | B20: Not Started | D20: Statut | E20: Non commencé
A21: Comments | D21: Commentaires

Sheet CP-10-2
A1: Control CP-10(2) — Evidence Tracking | D1: Contrôle CP-10(2) — Suivi des preuves
A2: Control Information | D2: Informations du contrôle
A3: Control Identifier | B3: CP-10(2) | D3: Identifiant du contrôle | E3: CP-10(2)
A4: Family | B4: Information System Recovery and Reconstitution | D4: Famille | E4: Reprise et reconstitution du système d’information
A5: Profile | B5: CCCS Medium / PBMM Moderate | D5: Profil | E5: CCCS Moyen / PBMM Modéré
A6: Primary Evidence Tool | D6: Outil de preuve principal
A7: Contributing Tools | D7: Outils contributeurs
A8: Control Description | B8: INFORMATION SYSTEM RECOVERY AND RECONSTITUTION | TRANSACTION RECOVERY The information system implements transaction recovery for systems that are transaction-based. | D8: Description du contrôle | E8: REPRISE ET RECONSTITUTION DU SYSTÈME D’INFORMATION | RÉCUPÉRATION DES TRANSACTIONS Le système d’information applique la récupération des transactions pour les systèmes transactionnels.
A9: Supplemental Guidance | B9: Transaction-based information systems include, for example, database management systems and transaction processing systems. Mechanisms supporting transaction recovery include, for example, transaction rollback and transaction journaling. | D9: Directives supplémentaires | E9: Les systèmes d’information transactionnels comprennent, par exemple, les systèmes de gestion des bases de données et les systèmes transactionnels. Les mécanismes prenant en charge la récupération des transactions comprennent, par exemple, le retour arrière programmé et la journalisation des transactions.
A10: Test Case | D10: Cas de test
A11: Test | B11: TEST-CP-10(2) | D11: Test | E11: TEST-CP-10(2)
A12: Requirement ID | B12: CP-10(2) | D12: ID Exigence | E12: CP-10(2)
A13: Component | D13: Composant
A14: Requirement | D14: Exigence
A15: Contextual Design Description | D15: Description contextuelle du design
A16: Evidence Provided | D16: Preuve fournie
A17: Preparer Sign Off (Initials, Date) | D17: Signataire préparateur (Initiales, Date)
A18: Owner Sign Off (Initials, Date) | D18: Signataire propriétaire (Initiales, Date)
A19: Assessor Sign Off (Initials, Date) | D19: Signataire évaluateur (Initiales, Date)
A20: Status | B20: Not Started | D20: Statut | E20: Non commencé
A21: Comments | D21: Commentaires

Sheet CP-10-4
A1: Control CP-10(4) — Evidence Tracking | D1: Contrôle CP-10(4) — Suivi des preuves
A2: Control Information | D2: Informations du contrôle
A3: Control Identifier | B3: CP-10(4) | D3: Identifiant du contrôle | E3: CP-10(4)
A4: Family | B4: Information System Recovery and Reconstitution | D4: Famille | E4: Reprise et reconstitution du système d’information
A5: Profile | B5: CCCS Medium / PBMM Moderate | D5: Profil | E5: CCCS Moyen / PBMM Modéré
A6: Primary Evidence Tool | D6: Outil de preuve principal
A7: Contributing Tools | D7: Outils contributeurs
A8: Control Description | B8: INFORMATION SYSTEM RECOVERY AND RECONSTITUTION | RESTORE WITHIN TIME PERIOD The organization provides the capability to restore information system components within organization-defined restoration time-periods from configuration-controlled and integrity-protected information representing a known, operational state for the components. | D8: Description du contrôle | E8: REPRISE ET RECONSTITUTION DU SYSTÈME D’INFORMATION | RESTAURATION DANS LE DÉLAI IMPARTI L’organisation fournit la capacité de restaurer les composants du système d’information dans les délais de restauration définis par l’organisation à partir de l’information contrôlée par la configuration et protégée par l’intégrité qui représente un état de fonctionnement connu pour les composants.
A9: Supplemental Guidance | B9: Restoration of information system components includes, for example, re-imaging which restores components to known, operational states. Related control: CM-2. | D9: Directives supplémentaires | E9: La restauration des composants du système d’information comprend, par exemple, la reconfiguration permettant de restaurer les composants aux états de fonctionnement connus. Contrôle connexe : CM-2.
A10: Test Case | D10: Cas de test
A11: Test | B11: TEST-CP-10(4) | D11: Test | E11: TEST-CP-10(4)
A12: Requirement ID | B12: CP-10(4) | D12: ID Exigence | E12: CP-10(4)
A13: Component | D13: Composant
A14: Requirement | D14: Exigence
A15: Contextual Design Description | D15: Description contextuelle du design
A16: Evidence Provided | D16: Preuve fournie
A17: Preparer Sign Off (Initials, Date) | D17: Signataire préparateur (Initiales, Date)
A18: Owner Sign Off (Initials, Date) | D18: Signataire propriétaire (Initiales, Date)
A19: Assessor Sign Off (Initials, Date) | D19: Signataire évaluateur (Initiales, Date)
A20: Status | B20: Not Started | D20: Statut | E20: Non commencé
A21: Comments | D21: Commentaires

Sheet IA-5-7
A1: Control IA-5(7) — Evidence Tracking | D1: Contrôle IA-5(7) — Suivi des preuves
A2: Control Information | D2: Informations du contrôle
A3: Control Identifier | B3: IA-5(7) | D3: Identifiant du contrôle | E3: IA-5(7)
A4: Family | B4: Authenticator Management | D4: Famille | E4: Gestion des authentifiants
A5: Profile | B5: CCCS Medium / PBMM Moderate | D5: Profil | E5: CCCS Moyen / PBMM Modéré
A6: Primary Evidence Tool | D6: Outil de preuve principal
A7: Contributing Tools | D7: Outils contributeurs
A8: Control Description | B8: AUTHENTICATOR MANAGEMENT | NO EMBEDDED UNENCRYPTED STATIC AUTHENTICATORS The organization ensures that unencrypted static authenticators are not embedded in applications or access scripts or stored on function keys. | D8: Description du contrôle | E8: GESTION DES AUTHENTIFIANTS | AUCUN AUTHENTIFIANT STATIQUE INTÉGRÉ NON CHIFFRÉ L’organisation veille à ce que les authentifiants statiques non chiffrés ne soient pas intégrés dans les applications ou les scripts d’accès ou stockés sur les clés de fonction.
A9: Supplemental Guidance | B9: Organizations exercise caution in determining whether embedded or stored authenticators are in encrypted or unencrypted form. If authenticators are used in the manner stored, then those representations are considered unencrypted authenticators. This is irrespective of whether that representation is perhaps an encrypted version of something else (e.g., a password). | D9: Directives supplémentaires | E9: Les organisations usent de prudence lorsqu’il s’agit de déterminer si les authentifiants intégrés ou stockés sont chiffrés ou non chiffrés. Si les authentifiants sont utilisés sous leur forme stockée, ces représentations sont alors considérées comme étant des authentifiants non chiffrés. Cela n’a rien à voir avec le fait que cette représentation puisse être une version chiffrée de quelque chose d’autre (p. ex., un mot de passe).
A10: Test Case | D10: Cas de test
A11: Test | B11: TEST-IA-5(7) | D11: Test | E11: TEST-IA-5(7)
A12: Requirement ID | B12: IA-5(7) | D12: ID Exigence | E12: IA-5(7)
A13: Component | D13: Composant
A14: Requirement | D14: Exigence
A15: Contextual Design Description | D15: Description contextuelle du design
A16: Evidence Provided | D16: Preuve fournie
A17: Preparer Sign Off (Initials, Date) | D17: Signataire préparateur (Initiales, Date)
A18: Owner Sign Off (Initials, Date) | D18: Signataire propriétaire (Initiales, Date)
A19: Assessor Sign Off (Initials, Date) | D19: Signataire évaluateur (Initiales, Date)
A20: Status | B20: Not Started | D20: Statut | E20: Non commencé
A21: Comments | D21: Commentaires

Sheet RA-5
A1: Control RA-5 — Evidence Tracking | D1: Contrôle RA-5 — Suivi des preuves
A2: Control Information | D2: Informations du contrôle
A3: Control Identifier | B3: RA-5 | D3: Identifiant du contrôle | E3: RA-5
A4: Family | B4: Vulnerability Scanning | D4: Famille | E4: Analyse des vulnérabilités
A5: Profile | B5: CCCS Medium / PBMM Moderate | D5: Profil | E5: CCCS Moyen / PBMM Modéré
A6: Primary Evidence Tool | D6: Outil de preuve principal
A7: Contributing Tools | D7: Outils contributeurs
A8: Control Description | B8: (A) The organization scans for vulnerabilities in the information system and hosted applications monthly for operating systems/infrastructure, web applications, and database management systems and when new vulnerabilities potentially affecting the system/applications are identified and reported. (B) The organization employs vulnerability scanning tools and techniques that facilitate interoperability among tools and automate parts of the vulnerability management process by using standards for: (a) Enumerating platforms, software flaws, and improper configurations; (b) Formatting checklists and test procedures; and (c) Measuring vulnerability impact. (C) The organization analyzes vulnerability scan reports and results from security control assessments. (D) The organization remediates legitimate vulnerabilities within 30 days for high-risk vulnerabilities and 90 days for moderate-risk vulnerabilities from the date of discovery in accordance with an organizational assessment of risk. (E) The organization shares information obtained from the vulnerability scanning process and security control assessments with organization-defined personnel or roles to help eliminate similar vulnerabilities in other information systems (i.e., systemic weaknesses or deficiencies). | D8: Description du contrôle | E8: (A) L’organisation analyse chaque mois les vulnérabilités du système d’information et des applications hébergées pour les systèmes et l’infrastructure d’exploitation, les applications Web et les systèmes de gestion de base de données, ainsi que les cas où de nouvelles vulnérabilités susceptibles d’affecter le système ou les applications sont repérées et signalées. (B) L’organisation utilise des outils et des techniques d’analyse des vulnérabilités qui facilitent l’interopérabilité entre les outils et automatisent des parties du processus de gestion des vulnérabilités en utilisant des normes pour : (a) recenser les plateformes, les failles logicielles et les configurations inadéquates; (b) formater les listes de contrôle et les procédures d’essai; (c) mesurer les répercussions des vulnérabilités. (C) L’organisation analyse les rapports d’analyse des vulnérabilités et les résultats des évaluations des contrôles de sécurité. (D) L’organisation remédie aux vulnérabilités légitimes dans les 30 jours pour les vulnérabilités présentant un risque élevé et dans les 90 jours pour les vulnérabilités présentant un risque modéré à partir de la date de découverte, conformément à une évaluation du risque par l’organisation. (E) L’organisation partage l’information obtenue dans le cadre du processus d’analyse des vulnérabilités et des évaluations des contrôles de sécurité avec le personnel ou les rôles définis par l’organisation pour aider à éliminer des vulnérabilités semblables dans d’autres systèmes d’information (c.-à-d. des faiblesses ou des lacunes systémiques).
A9: Supplemental Guidance | B9: Security categorization of information systems guides the frequency and comprehensiveness of vulnerability scans. Organizations determine the required vulnerability scanning for all information system components, ensuring that potential sources of vulnerabilities such as networked printers, scanners, and copiers are not overlooked. Vulnerability analyses for custom software applications may require additional approaches such as static analysis, dynamic analysis, binary analysis, or a hybrid of the three approaches. Organizations can employ these analysis approaches in a variety of tools (e.g., web-based application scanners, static analysis tools, binary analyzers) and in source code reviews. Vulnerability scanning includes, for example: (i) scanning for patch levels; (ii) scanning for functions, ports, protocols, and services that should not be accessible to users or devices; and (iii) scanning for improperly configured or incorrectly operating information flow control mechanisms | D9: Directives supplémentaires | E9: La catégorisation de la sécurité des systèmes d’information détermine la fréquence et l’exhaustivité des analyses de vulnérabilité. Les organisations déterminent le balayage des vulnérabilités requis pour tous les composants du système d’information, en veillant à ce que les sources potentielles de vulnérabilités comme les imprimantes en réseau, les numériseurs et les photocopieurs ne soient pas négligées. Les analyses de vulnérabilité pour les applications logicielles personnalisées peuvent nécessiter des approches supplémentaires comme l’analyse statique, l’analyse dynamique, l’analyse binaire ou un hybride des trois approches. Les organisations peuvent utiliser ces approches d’analyse dans divers outils (p. ex., numériseurs d’applications Web, outils d’analyse statique, analyseurs binaires) et dans l’examen des codes sources. La détection des vulnérabilités comprend, par exemple : (i) la détection des niveaux de correctifs; (ii) le balayage à la recherche de fonctions, de ports, de protocoles et de services qui ne devraient pas être accessibles aux utilisateurs ou aux appareils; (iii) la détection de mécanismes de contrôle du flux d’information mal configurés ou défectueux
A10: Test Case | D10: Cas de test
A11: Test | B11: TEST-RA-5 | D11: Test | E11: TEST-RA-5
A12: Requirement ID | B12: RA-5 | D12: ID Exigence | E12: RA-5
A13: Component | D13: Composant
A14: Requirement | D14: Exigence
A15: Contextual Design Description | D15: Description contextuelle du design
A16: Evidence Provided | D16: Preuve fournie
A17: Preparer Sign Off (Initials, Date) | D17: Signataire préparateur (Initiales, Date)
A18: Owner Sign Off (Initials, Date) | D18: Signataire propriétaire (Initiales, Date)
A19: Assessor Sign Off (Initials, Date) | D19: Signataire évaluateur (Initiales, Date)
A20: Status | B20: Not Started | D20: Statut | E20: Non commencé
A21: Comments | D21: Commentaires

Sheet RA-5-1
A1: Control RA-5(1) — Evidence Tracking | D1: Contrôle RA-5(1) — Suivi des preuves
A2: Control Information | D2: Informations du contrôle
A3: Control Identifier | B3: RA-5(1) | D3: Identifiant du contrôle | E3: RA-5(1)
A4: Family | B4: Vulnerability Scanning | D4: Famille | E4: Analyse des vulnérabilités
A5: Profile | B5: CCCS Medium / PBMM Moderate | D5: Profil | E5: CCCS Moyen / PBMM Modéré
A6: Primary Evidence Tool | D6: Outil de preuve principal
A7: Contributing Tools | D7: Outils contributeurs
A8: Control Description | B8: VULNERABILITY SCANNING | UPDATE TOOL CAPABILITY The organization employs vulnerability scanning tools that include the capability to readily update the information system vulnerabilities to be scanned. | D8: Description du contrôle | E8: ANALYSE DES VULNÉRABILITÉS | CAPACITÉ DE MISE À JOUR DES OUTILS L’organisation utilise des outils de balayage des vulnérabilités qui comprennent la capacité de mettre rapidement à jour les vulnérabilités du système d’information à analyser.
A9: Supplemental Guidance | B9: The vulnerabilities to be scanned need to be readily updated as new vulnerabilities are discovered, announced, and scanning methods developed. This updating process helps to ensure that potential vulnerabilities in the information system are identified and addressed as quickly as possible. Related controls: SI-3, SI-7. | D9: Directives supplémentaires | E9: Les vulnérabilités à analyser doivent être rapidement mises à jour dès que de nouvelles vulnérabilités sont découvertes et annoncées, et que de nouvelles méthodes de balayage sont élaborées. Ce processus de mise à jour permet de s’assurer que les vulnérabilités potentielles dans le système d’information sont repérées et traitées le plus rapidement possible. Contrôles connexes : SI-3, SI-7.
A10: Test Case | D10: Cas de test
A11: Test | B11: TEST-RA-5(1) | D11: Test | E11: TEST-RA-5(1)
A12: Requirement ID | B12: RA-5(1) | D12: ID Exigence | E12: RA-5(1)
A13: Component | D13: Composant
A14: Requirement | D14: Exigence
A15: Contextual Design Description | D15: Description contextuelle du design
A16: Evidence Provided | D16: Preuve fournie
A17: Preparer Sign Off (Initials, Date) | D17: Signataire préparateur (Initiales, Date)
A18: Owner Sign Off (Initials, Date) | D18: Signataire propriétaire (Initiales, Date)
A19: Assessor Sign Off (Initials, Date) | D19: Signataire évaluateur (Initiales, Date)
A20: Status | B20: Not Started | D20: Statut | E20: Non commencé
A21: Comments | D21: Commentaires

Sheet RA-5-2
A1: Control RA-5(2) — Evidence Tracking | D1: Contrôle RA-5(2) — Suivi des preuves
A2: Control Information | D2: Informations du contrôle
A3: Control Identifier | B3: RA-5(2) | D3: Identifiant du contrôle | E3: RA-5(2)
A4: Family | B4: Vulnerability Scanning | D4: Famille | E4: Analyse des vulnérabilités
A5: Profile | B5: CCCS Medium / PBMM Moderate | D5: Profil | E5: CCCS Moyen / PBMM Modéré
A6: Primary Evidence Tool | D6: Outil de preuve principal
A7: Contributing Tools | D7: Outils contributeurs
A8: Control Description | B8: VULNERABILITY SCANNING | UPDATE BY FREQUENCY / PRIOR TO NEW SCAN / WHEN IDENTIFIED The organization updates the information system vulnerabilities scanned prior to a new scan. | D8: Description du contrôle | E8: ANALYSE DES VULNÉRABILITÉS | MISE À JOUR EN FONCTION DE LA FRÉQUENCE, AVANT UN NOUVEAU BALAYAGE, ET DÈS QUE DES VULNÉRABILITÉS SONT REPÉRÉES L’organisation met à jour les vulnérabilités du système d’information repérées avant un nouveau balayage.
A9: Supplemental Guidance | B9: Related controls: SI-3, SI-5. | D9: Directives supplémentaires | E9: Contrôles connexes : SI-3, SI-5.
A10: Test Case | D10: Cas de test
A11: Test | B11: TEST-RA-5(2) | D11: Test | E11: TEST-RA-5(2)
A12: Requirement ID | B12: RA-5(2) | D12: ID Exigence | E12: RA-5(2)
A13: Component | D13: Composant
A14: Requirement | D14: Exigence
A15: Contextual Design Description | D15: Description contextuelle du design
A16: Evidence Provided | D16: Preuve fournie
A17: Preparer Sign Off (Initials, Date) | D17: Signataire préparateur (Initiales, Date)
A18: Owner Sign Off (Initials, Date) | D18: Signataire propriétaire (Initiales, Date)
A19: Assessor Sign Off (Initials, Date) | D19: Signataire évaluateur (Initiales, Date)
A20: Status | B20: Not Started | D20: Statut | E20: Non commencé
A21: Comments | D21: Commentaires

Sheet RA-5-3
A1: Control RA-5(3) — Evidence Tracking | D1: Contrôle RA-5(3) — Suivi des preuves
A2: Control Information | D2: Informations du contrôle
A3: Control Identifier | B3: RA-5(3) | D3: Identifiant du contrôle | E3: RA-5(3)
A4: Family | B4: Vulnerability Scanning | D4: Famille | E4: Analyse des vulnérabilités
A5: Profile | B5: CCCS Medium / PBMM Moderate | D5: Profil | E5: CCCS Moyen / PBMM Modéré
A6: Primary Evidence Tool | D6: Outil de preuve principal
A7: Contributing Tools | D7: Outils contributeurs
A8: Control Description | B8: VULNERABILITY SCANNING | BREADTH / DEPTH OF COVERAGE The organization employs vulnerability scanning procedures that can identify the breadth and depth of coverage (i.e., information system components scanned and vulnerabilities checked). | D8: Description du contrôle | E8: ANALYSE DES VULNÉRABILITÉS | ÉTENDUE/PROFONDEUR DE LA COUVERTURE L’organisation utilise des procédures de balayage des vulnérabilités qui peuvent déterminer l’étendue et la profondeur de la couverture (c.-à-d. les composants du système d’information balayés et les vulnérabilités vérifiées).
A9: Supplemental Guidance | D9: Directives supplémentaires
A10: Test Case | D10: Cas de test
A11: Test | B11: TEST-RA-5(3) | D11: Test | E11: TEST-RA-5(3)
A12: Requirement ID | B12: RA-5(3) | D12: ID Exigence | E12: RA-5(3)
A13: Component | D13: Composant
A14: Requirement | D14: Exigence
A15: Contextual Design Description | D15: Description contextuelle du design
A16: Evidence Provided | D16: Preuve fournie
A17: Preparer Sign Off (Initials, Date) | D17: Signataire préparateur (Initiales, Date)
A18: Owner Sign Off (Initials, Date) | D18: Signataire propriétaire (Initiales, Date)
A19: Assessor Sign Off (Initials, Date) | D19: Signataire évaluateur (Initiales, Date)
A20: Status | B20: Not Started | D20: Statut | E20: Non commencé
A21: Comments | D21: Commentaires

Sheet RA-5-5
A1: Control RA-5(5) — Evidence Tracking | D1: Contrôle RA-5(5) — Suivi des preuves
A2: Control Information | D2: Informations du contrôle
A3: Control Identifier | B3: RA-5(5) | D3: Identifiant du contrôle | E3: RA-5(5)
A4: Family | B4: Vulnerability Scanning | D4: Famille | E4: Analyse des vulnérabilités
A5: Profile | B5: CCCS Medium / PBMM Moderate | D5: Profil | E5: CCCS Moyen / PBMM Modéré
A6: Primary Evidence Tool | D6: Outil de preuve principal
A7: Contributing Tools | D7: Outils contributeurs
A8: Control Description | B8: VULNERABILITY SCANNING | PRIVILEGED ACCESS The information system implements privileged access authorization to operating systems, web applications, databases for selected all scans. | D8: Description du contrôle | E8: ANALYSE DES VULNÉRABILITÉS | ACCÈS PRIVILÉGIÉ Le système d’information applique l’autorisation d’accès privilégié aux systèmes d’exploitation, aux applications Web et aux bases de données pour tous les balayages sélectionnés.
A9: Supplemental Guidance | B9: In certain situations, the nature of the vulnerability scanning may be more intrusive or the information system component that is the subject of the scanning may contain highly sensitive information. Privileged access authorization to selected system components facilitates more thorough vulnerability scanning and also protects the sensitive nature of such scanning. | D9: Directives supplémentaires | E9: Dans certaines situations, la nature du balayage des vulnérabilités peut être plus intrusive, ou le composant du système d’information qui fait l’objet du balayage peut contenir des renseignements de nature très sensible. L’autorisation d’accès privilégié à certains composants du système facilite un balayage plus approfondi des vulnérabilités et protège également la nature sensible de ce balayage.
A10: Test Case | D10: Cas de test
A11: Test | B11: TEST-RA-5(5) | D11: Test | E11: TEST-RA-5(5)
A12: Requirement ID | B12: RA-5(5) | D12: ID Exigence | E12: RA-5(5)
A13: Component | D13: Composant
A14: Requirement | D14: Exigence
A15: Contextual Design Description | D15: Description contextuelle du design
A16: Evidence Provided | D16: Preuve fournie
A17: Preparer Sign Off (Initials, Date) | D17: Signataire préparateur (Initiales, Date)
A18: Owner Sign Off (Initials, Date) | D18: Signataire propriétaire (Initiales, Date)
A19: Assessor Sign Off (Initials, Date) | D19: Signataire évaluateur (Initiales, Date)
A20: Status | B20: Not Started | D20: Statut | E20: Non commencé
A21: Comments | D21: Commentaires

Sheet RA-5-6
A1: Control RA-5(6) — Evidence Tracking | D1: Contrôle RA-5(6) — Suivi des preuves
A2: Control Information | D2: Informations du contrôle
A3: Control Identifier | B3: RA-5(6) | D3: Identifiant du contrôle | E3: RA-5(6)
A4: Family | B4: Vulnerability Scanning | D4: Famille | E4: Analyse des vulnérabilités
A5: Profile | B5: CCCS Medium / PBMM Moderate | D5: Profil | E5: CCCS Moyen / PBMM Modéré
A6: Primary Evidence Tool | D6: Outil de preuve principal
A7: Contributing Tools | D7: Outils contributeurs
A8: Control Description | B8: VULNERABILITY SCANNING | AUTOMATED TREND ANALYSES The organization employs automated mechanisms to compare the results of vulnerability scans over time to determine trends in information system vulnerabilities. | D8: Description du contrôle | E8: ANALYSE DES VULNÉRABILITÉS | ANALYSES AUTOMATISÉES DES TENDANCES L’organisation utilise des mécanismes automatisés pour comparer les résultats des analyses de vulnérabilité au fil du temps afin de déterminer les tendances dans les vulnérabilités du système d’information.
A9: Supplemental Guidance | B9: Related controls: IR-4, IR-5, SI-4. | D9: Directives supplémentaires | E9: Contrôles connexes : IR-4, IR-5, SI-4.
A10: Test Case | D10: Cas de test
A11: Test | B11: TEST-RA-5(6) | D11: Test | E11: TEST-RA-5(6)
A12: Requirement ID | B12: RA-5(6) | D12: ID Exigence | E12: RA-5(6)
A13: Component | D13: Composant
A14: Requirement | D14: Exigence
A15: Contextual Design Description | D15: Description contextuelle du design
A16: Evidence Provided | D16: Preuve fournie
A17: Preparer Sign Off (Initials, Date) | D17: Signataire préparateur (Initiales, Date)
A18: Owner Sign Off (Initials, Date) | D18: Signataire propriétaire (Initiales, Date)
A19: Assessor Sign Off (Initials, Date) | D19: Signataire évaluateur (Initiales, Date)
A20: Status | B20: Not Started | D20: Statut | E20: Non commencé
A21: Comments | D21: Commentaires

Sheet RA-5-8
A1: Control RA-5(8) — Evidence Tracking | D1: Contrôle RA-5(8) — Suivi des preuves
A2: Control Information | D2: Informations du contrôle
A3: Control Identifier | B3: RA-5(8) | D3: Identifiant du contrôle | E3: RA-5(8)
A4: Family | B4: Vulnerability Scanning | D4: Famille | E4: Analyse des vulnérabilités
A5: Profile | B5: CCCS Medium / PBMM Moderate | D5: Profil | E5: CCCS Moyen / PBMM Modéré
A6: Primary Evidence Tool | D6: Outil de preuve principal
A7: Contributing Tools | D7: Outils contributeurs
A8: Control Description | B8: VULNERABILITY SCANNING | REVIEW HISTORIC AUDIT LOGS The organization reviews historic audit logs to determine if a vulnerability identified in the information system has been previously exploited. | D8: Description du contrôle | E8: ANALYSE DES VULNÉRABILITÉS | EXAMEN DES JOURNAUX DE VÉRIFICATION HISTORIQUES L’organisation examine les journaux de vérification historiques pour déterminer si une vulnérabilité repérée dans le système d’information a déjà été exploitée.
A9: Supplemental Guidance | B9: Related control: AU-6. | D9: Directives supplémentaires | E9: Contrôle connexe : AU-6.
A10: Test Case | D10: Cas de test
A11: Test | B11: TEST-RA-5(8) | D11: Test | E11: TEST-RA-5(8)
A12: Requirement ID | B12: RA-5(8) | D12: ID Exigence | E12: RA-5(8)
A13: Component | D13: Composant
A14: Requirement | D14: Exigence
A15: Contextual Design Description | D15: Description contextuelle du design
A16: Evidence Provided | D16: Preuve fournie
A17: Preparer Sign Off (Initials, Date) | D17: Signataire préparateur (Initiales, Date)
A18: Owner Sign Off (Initials, Date) | D18: Signataire propriétaire (Initiales, Date)
A19: Assessor Sign Off (Initials, Date) | D19: Signataire évaluateur (Initiales, Date)
A20: Status | B20: Not Started | D20: Statut | E20: Non commencé
A21: Comments | D21: Commentaires

Sheet SA-9-5
A1: Control SA-9(5) — Evidence Tracking | D1: Contrôle SA-9(5) — Suivi des preuves
A2: Control Information | D2: Informations du contrôle
A3: Control Identifier | B3: SA-9(5) | D3: Identifiant du contrôle | E3: SA-9(5)
A4: Family | B4: External Information System Services | D4: Famille | E4: Services de systèmes d’information externes
A5: Profile | B5: CCCS Medium / PBMM Moderate | D5: Profil | E5: CCCS Moyen / PBMM Modéré
A6: Primary Evidence Tool | D6: Outil de preuve principal
A7: Contributing Tools | D7: Outils contributeurs
A8: Control Description | B8: EXTERNAL INFORMATION SYSTEMS | PROCESSING, STORAGE, AND SERVICE LOCATION The organization restricts the location of information processing, information/data, and information system services to locations witihin Canada based on ITPIN 2017-02 for Direction on Data Residency (https://www.canada.ca/en/treasury-board-secretariat/services/information-technology/policy-implementation-notices/direction-electronic-data-residency.html). | D8: Description du contrôle | E8: SYSTÈMES D’INFORMATION EXTERNES | EMPLACEMENT DU TRAITEMENT, DU STOCKAGE ET DES SERVICES L’organisation restreint la résidence du traitement de l’information, du stockage de l’information et des données, ainsi que des services de systèmes d’information aux endroits situés à l’intérieur du Canada, conformément à l’avis AMPTI 2017-02, Orientation relative à la résidence des données électroniques (https://www.canada.ca/fr/gouvernement/systeme/gouvernement-numerique/technologiques-modernes-nouveaux/orientation-relative-residence-donnees-electroniques.html).
A9: Supplemental Guidance | B9: The location of information processing, information/data storage, or information system services that are critical to organizations can have a direct impact on the ability of those organizations to successfully execute their missions/business functions. This situation exists when external providers control the location of processing, storage or services. The criteria external providers use for the selection of processing, storage, or service locations may be different from organizational criteria. For example, organizations may want to ensure that data/information storage locations are restricted to certain locations to facilitate incident response activities (e.g., forensic analyses, after-the-fact investigations) in case of information security breaches/compromises. Such incident response activities may be adversely affected by the governing laws or protocols in the locations where processing and storage occur and/or the locations from which information system services emanate. | D9: Directives supplémentaires | E9: L’emplacement des services de traitement de l’information et de stockage de l’information et des données ou des services de systèmes d’information qui sont essentiels pour les organisations peut avoir une incidence directe sur la capacité de ces organisations d’exécuter avec succès leurs fonctions opérationnelles et de mission. Cette situation existe lorsque des fournisseurs externes contrôlent l’emplacement du traitement, de l’entreposage ou des services. Les critères utilisés par les fournisseurs externes pour choisir les lieux de traitement, d’entreposage ou de service peuvent être différents des critères de l’organisation. Par exemple, les organisations pourraient vouloir s’assurer que les emplacements de stockage des données ou de l’information se limitent à certains endroits afin de faciliter les activités d’intervention (p. ex., analyses judiciaires, enquêtes après coup) en cas d’incident représentant une atteinte à, ou une compromission de la sécurité de l’information. Ces activités d’intervention en cas d’incident peuvent être affectées négativement par les lois ou les protocoles en vigueur aux endroits où le traitement et l’entreposage ont lieu ou aux endroits d’où proviennent les services de systèmes d’information.
A10: Test Case | D10: Cas de test
A11: Test | B11: TEST-SA-9(5) | D11: Test | E11: TEST-SA-9(5)
A12: Requirement ID | B12: SA-9(5) | D12: ID Exigence | E12: SA-9(5)
A13: Component | D13: Composant
A14: Requirement | D14: Exigence
A15: Contextual Design Description | D15: Description contextuelle du design
A16: Evidence Provided | D16: Preuve fournie
A17: Preparer Sign Off (Initials, Date) | D17: Signataire préparateur (Initiales, Date)
A18: Owner Sign Off (Initials, Date) | D18: Signataire propriétaire (Initiales, Date)
A19: Assessor Sign Off (Initials, Date) | D19: Signataire évaluateur (Initiales, Date)
A20: Status | B20: Not Started | D20: Statut | E20: Non commencé
A21: Comments | D21: Commentaires

Sheet SA-11-1
A1: Control SA-11(1) — Evidence Tracking | D1: Contrôle SA-11(1) — Suivi des preuves
A2: Control Information | D2: Informations du contrôle
A3: Control Identifier | B3: SA-11(1) | D3: Identifiant du contrôle | E3: SA-11(1)
A4: Family | B4: Developer Security Testing | D4: Famille | E4: Essais de sécurité du développeur
A5: Profile | B5: CCCS Medium / PBMM Moderate | D5: Profil | E5: CCCS Moyen / PBMM Modéré
A6: Primary Evidence Tool | D6: Outil de preuve principal
A7: Contributing Tools | D7: Outils contributeurs
A8: Control Description | B8: DEVELOPER SECURITY TESTING AND EVALUATION | STATIC CODE ANALYSIS The organization requires the developer of the information system, system component, or information system service to employ static code analysis tools to identify common flaws and document the results of the analysis. | D8: Description du contrôle | E8: ESSAIS ET ÉVALUATION DE LA SÉCURITÉ PAR LE DÉVELOPPEUR | ANALYSE DU CODE STATIQUE L’organisation exige que le développeur du système d’information, du composant du système ou du service du système d’information utilise des outils d’analyse du code statique pour repérer les défauts courants et documenter les résultats de l’analyse.
A9: Supplemental Guidance | B9: Static code analysis provides a technology and methodology for security reviews. Such analysis can be used to identify security vulnerabilities and enforce security coding practices. Static code analysis is most effective when used early in the development process, when each code change can be automatically scanned for potential weaknesses. Static analysis can provide clear remediation guidance along with defects to enable developers to fix such defects. Evidence of correct implementation of static analysis can include, for example, aggregate defect density for critical defect types, evidence that defects were inspected by developers or security professionals, and evidence that defects were fixed. An excessively high density of ignored findings (commonly referred to as ignored or false positives) indicates a potential problem with the analysis process or tool. In such cases, organizations weigh the validity of the evidence against evidence from other sources. | D9: Directives supplémentaires | E9: L’analyse du code statique fournit une technologie et une méthodologie pour les examens de sécurité. Une telle analyse peut servir à déterminer les vulnérabilités en matière de sécurité et à appliquer les pratiques de codage de sécurité. L’analyse du code statique sera plus efficace si elle est utilisée tôt dans le processus de développement, alors que chaque changement de code peut automatiquement être soumis à un balayage permettant de déceler les faiblesses potentielles. L’analyse statique peut fournir des directives claires sur les mesures correctives ainsi que sur les défauts afin de permettre aux développeurs de corriger ces défauts. Les preuves de la mise en œuvre correcte de l’analyse statique peuvent comprendre, par exemple, la densité globale des défauts pour les types de défauts critiques, des preuves que les défauts ont été inspectés par des développeurs ou des professionnels de la sécurité, et des preuves que les défauts ont été corrigés. Une densité excessivement élevée de résultats ignorés (communément appelés faux positifs) indique un problème potentiel avec le processus ou l’outil d’analyse. Dans de tels cas, les organisations évaluent la validité de la preuve par rapport à celle d’autres sources.
A10: Test Case | D10: Cas de test
A11: Test | B11: TEST-SA-11(1) | D11: Test | E11: TEST-SA-11(1)
A12: Requirement ID | B12: SA-11(1) | D12: ID Exigence | E12: SA-11(1)
A13: Component | D13: Composant
A14: Requirement | D14: Exigence
A15: Contextual Design Description | D15: Description contextuelle du design
A16: Evidence Provided | D16: Preuve fournie
A17: Preparer Sign Off (Initials, Date) | D17: Signataire préparateur (Initiales, Date)
A18: Owner Sign Off (Initials, Date) | D18: Signataire propriétaire (Initiales, Date)
A19: Assessor Sign Off (Initials, Date) | D19: Signataire évaluateur (Initiales, Date)
A20: Status | B20: Not Started | D20: Statut | E20: Non commencé
A21: Comments | D21: Commentaires

Sheet SA-11-8
A1: Control SA-11(8) — Evidence Tracking | D1: Contrôle SA-11(8) — Suivi des preuves
A2: Control Information | D2: Informations du contrôle
A3: Control Identifier | B3: SA-11(8) | D3: Identifiant du contrôle | E3: SA-11(8)
A4: Family | B4: Developer Security Testing | D4: Famille | E4: Essais de sécurité du développeur
A5: Profile | B5: CCCS Medium / PBMM Moderate | D5: Profil | E5: CCCS Moyen / PBMM Modéré
A6: Primary Evidence Tool | D6: Outil de preuve principal
A7: Contributing Tools | D7: Outils contributeurs
A8: Control Description | B8: DEVELOPER SECURITY TESTING AND EVALUATION | DYNAMIC CODE ANALYSIS The organization requires the developer of the information system, system component, or information system service to employ dynamic code analysis tools to identify common flaws and document the results of the analysis. | D8: Description du contrôle | E8: ESSAIS ET ÉVALUATION DE LA SÉCURITÉ PAR LE DÉVELOPPEUR | ANALYSE DU CODE DYNAMIQUE L’organisation exige que le développeur du système d’information, du composant du système ou du service du système d’information utilise des outils d’analyse du code dynamique pour repérer les vulnérabilités courantes et documenter les résultats de l’analyse.
A9: Supplemental Guidance | B9: Dynamic code analysis provides run-time verification of software programs, using tools capable of monitoring programs for memory corruption, user privilege issues, and other potential security problems. Dynamic code analysis employs run-time tools to help to ensure that security functionality performs in the manner in which it was designed. A specialized type of dynamic analysis, known as fuzz testing, induces program failures by deliberately introducing malformed or random data into software programs. Fuzz testing strategies derive from the intended use of applications and the functional and design specifications for the applications. To understand the scope of dynamic code analysis and hence the assurance provided, organizations may also consider conducting code coverage analysis (checking the degree to which the code has been tested using metrics such as percent of subroutines tested or percent of program statements called during execution of the test suite) and/or concordance analysis. | D9: Directives supplémentaires | E9: L’analyse du code dynamique permet de vérifier le temps d’exécution des programmes logiciels à l’aide d’outils capables de surveiller les programmes en ce qui a trait à la corruption de la mémoire, aux problèmes liés aux privilèges d’utilisateur et à d’autres problèmes de sécurité potentiels. L’analyse dynamique du code fait appel à des outils à l’exécution pour s’assurer que les fonctionnalités de sécurité fonctionnent de la façon dont elles ont été conçues. Un type spécialisé d’analyse dynamique, connu sous le nom de test à données aléatoires (fuzz testing), induit des échecs du programme en introduisant délibérément des données erronées ou aléatoires dans des programmes logiciels. Les stratégies de test à données aléatoires déployées dépendent de l’utilisation prévue des applications et des spécifications fonctionnelles et de conception pour les applications. Pour comprendre la portée de l’analyse dynamique du code et, par conséquent, l’assurance fournie, les organisations peuvent également envisager d’effectuer une analyse de la couverture du code (en vérifiant la mesure dans laquelle le code a été mis à l’essai à l’aide de paramètres comme le pourcentage des sous-programmes testés ou le pourcentage des instructions du programme appelées pendant l’exécution de la série d’essais) ou une analyse de concordance.
A10: Test Case | D10: Cas de test
A11: Test | B11: TEST-SA-11(8) | D11: Test | E11: TEST-SA-11(8)
A12: Requirement ID | B12: SA-11(8) | D12: ID Exigence | E12: SA-11(8)
A13: Component | D13: Composant
A14: Requirement | D14: Exigence
A15: Contextual Design Description | D15: Description contextuelle du design
A16: Evidence Provided | D16: Preuve fournie
A17: Preparer Sign Off (Initials, Date) | D17: Signataire préparateur (Initiales, Date)
A18: Owner Sign Off (Initials, Date) | D18: Signataire propriétaire (Initiales, Date)
A19: Assessor Sign Off (Initials, Date) | D19: Signataire évaluateur (Initiales, Date)
A20: Status | B20: Not Started | D20: Statut | E20: Non commencé
A21: Comments | D21: Commentaires

Sheet SC-5
A1: Control SC-5 — Evidence Tracking | D1: Contrôle SC-5 — Suivi des preuves
A2: Control Information | D2: Informations du contrôle
A3: Control Identifier | B3: SC-5 | D3: Identifiant du contrôle | E3: SC-5
A4: Family | B4: Denial of Service Protection | D4: Famille | E4: Protection contre le déni de service
A5: Profile | B5: CCCS Medium / PBMM Moderate | D5: Profil | E5: CCCS Moyen / PBMM Modéré
A6: Primary Evidence Tool | D6: Outil de preuve principal
A7: Contributing Tools | D7: Outils contributeurs
A8: Control Description | B8: (A) The information system protects against or limits the effects of the following denial of service attempts that attack bandwidth, transactional capacity and storage by employing geo-replication, IP address blocking, and network-based DDoS protections. | D8: Description du contrôle | E8: (A) Le système d’information assure une protection ou limite les effets des tentatives de déni de service suivantes qui s’attaquent à la largeur de bande, à la capacité transactionnelle et au stockage en utilisant la géoréplication, le blocage d’adresses IP et les protections de DDoS réseau.
A9: Supplemental Guidance | B9: A variety of technologies exist to limit, or in some cases, eliminate the effects of denial of service attacks. For example, boundary protection devices can filter certain types of packets to protect information system components on internal organizational networks from being directly affected by denial of service attacks. Employing increased capacity and bandwidth combined with service redundancy may also reduce the susceptibility to denial of service attacks. Related controls: SC-6, SC-7 | D9: Directives supplémentaires | E9: Diverses technologies existent pour limiter ou, dans certains cas, éliminer les effets des attaques par déni de service. Par exemple, les dispositifs de protection des frontières peuvent filtrer certains types de paquets afin de protéger les composants du système d’information des réseaux organisationnels internes contre les répercussions directes des attaques par déni de service. L’utilisation d’une capacité et d’une bande passante accrues combinée à la redondance des services peut également réduire la susceptibilité aux attaques par déni de service. Contrôles connexes : SC-6, SC-7
A10: Test Case | D10: Cas de test
A11: Test | B11: TEST-SC-5 | D11: Test | E11: TEST-SC-5
A12: Requirement ID | B12: SC-5 | D12: ID Exigence | E12: SC-5
A13: Component | D13: Composant
A14: Requirement | D14: Exigence
A15: Contextual Design Description | D15: Description contextuelle du design
A16: Evidence Provided | D16: Preuve fournie
A17: Preparer Sign Off (Initials, Date) | D17: Signataire préparateur (Initiales, Date)
A18: Owner Sign Off (Initials, Date) | D18: Signataire propriétaire (Initiales, Date)
A19: Assessor Sign Off (Initials, Date) | D19: Signataire évaluateur (Initiales, Date)
A20: Status | B20: Not Started | D20: Statut | E20: Non commencé
A21: Comments | D21: Commentaires

Sheet SC-7
A1: Control SC-7 — Evidence Tracking | D1: Contrôle SC-7 — Suivi des preuves
A2: Control Information | D2: Informations du contrôle
A3: Control Identifier | B3: SC-7 | D3: Identifiant du contrôle | E3: SC-7
A4: Family | B4: Boundary Protection | D4: Famille | E4: Protection des frontières
A5: Profile | B5: CCCS Medium / PBMM Moderate | D5: Profil | E5: CCCS Moyen / PBMM Modéré
A6: Primary Evidence Tool | D6: Outil de preuve principal
A7: Contributing Tools | D7: Outils contributeurs
A8: Control Description | B8: (A) The information system monitors and controls communications at the external boundary of the system and at key internal boundaries within the system. (B) The information system implements sub-networks for publicly accessible system components that are physically or logically separated from internal organizational networks. (C) The information system connects to external networks or information systems only through managed interfaces consisting of boundary protection devices arranged in accordance with an organizational security architecture. | D8: Description du contrôle | E8: (A) Le système d’information surveille et contrôle les communications à la frontière externe du système et aux frontières internes clés du système. (B) Le système d’information met en œuvre des sous-réseaux pour des composants du système accessibles au public qui sont physiquement ou logiquement séparés des réseaux organisationnels internes. (C) Le système d’information ne se connecte à des réseaux ou à des systèmes d’information externes que par des interfaces gérées comprenant des dispositifs de protection des frontières organisés conformément à une architecture de sécurité organisationnelle.
A9: Supplemental Guidance | B9: Managed interfaces include, for example, gateways, routers, firewalls, guards, network-based malicious code analysis and virtualization systems, or encrypted tunnels implemented within a security architecture (e.g., routers protecting firewalls or application gateways residing on protected sub-networks). Sub-networks that are physically or logically separated from internal networks are referred to as demilitarized zones or DMZs. Restricting or prohibiting interfaces within organizational information systems includes, for example, restricting external web traffic to designated web servers within managed interfaces and prohibiting external traffic that appears to be spoofing internal addresses. Organizations consider the shared nature of commercial telecommunications services in the implementation of security controls associated with the use of such services. Commercial telecommunications services are commonly based on network components and consolidated management systems shared by all attached commercial customers, and may also include third party-provided access lines and other service elements. Such transmission services may represent sources of increased risk despite contract security provisions. Related controls: AC-4, AC-17, CA-3, CM-7, CP-8, IR-4, RA-3, SC-5, SC-13 | D9: Directives supplémentaires | E9: Les interfaces gérées comprennent, par exemple, les passerelles, les routeurs, les pare-feu, les gardiens, les systèmes d’analyse et de virtualisation de codes malveillants basés sur le réseau, ou les tunnels chiffrés mis en œuvre dans une architecture de sécurité (p. ex., les routeurs protégeant les pare-feu ou les passerelles d’application résidant sur des sous-réseaux protégés). Les sous-réseaux qui sont physiquement ou logiquement séparés des réseaux internes sont appelés « zones démilitarisées » ou « ZD ». La restriction ou l’interdiction des interfaces dans les systèmes d’information de l’organisation comprend, par exemple, la restriction du trafic Web externe aux serveurs Web désignés dans les interfaces gérées et l’interdiction du trafic externe qui semble usurper les adresses internes. Les organisations tiennent compte de la nature commune des services de télécommunications commerciaux dans la mise en œuvre des contrôles de sécurité associés à l’utilisation de tels services. Les services de télécommunications commerciaux sont généralement fondés sur des composants de réseau et des systèmes de gestion consolidés partagés par tous les clients commerciaux attenants, et peuvent également comprendre des lignes d’accès fournies par des tiers et d’autres éléments de service. Ces services de transmission peuvent représenter des sources de risque accru malgré les dispositions relatives à la sécurité dans les contrats. Contrôles connexes : AC-4, AC-17, CA-3, CM-7, CP-8, IR-4, RA-3, SC-5, SC-13
A10: Test Case | D10: Cas de test
A11: Test | B11: TEST-SC-7 | D11: Test | E11: TEST-SC-7
A12: Requirement ID | B12: SC-7 | D12: ID Exigence | E12: SC-7
A13: Component | D13: Composant
A14: Requirement | D14: Exigence
A15: Contextual Design Description | D15: Description contextuelle du design
A16: Evidence Provided | D16: Preuve fournie
A17: Preparer Sign Off (Initials, Date) | D17: Signataire préparateur (Initiales, Date)
A18: Owner Sign Off (Initials, Date) | D18: Signataire propriétaire (Initiales, Date)
A19: Assessor Sign Off (Initials, Date) | D19: Signataire évaluateur (Initiales, Date)
A20: Status | B20: Not Started | D20: Statut | E20: Non commencé
A21: Comments | D21: Commentaires

Sheet SC-13
A1: Control SC-13 — Evidence Tracking | D1: Contrôle SC-13 — Suivi des preuves
A2: Control Information | D2: Informations du contrôle
A3: Control Identifier | B3: SC-13 | D3: Identifiant du contrôle | E3: SC-13
A4: Family | B4: Cryptographic Protection | D4: Famille | E4: Protection cryptographique
A5: Profile | B5: CCCS Medium / PBMM Moderate | D5: Profil | E5: CCCS Moyen / PBMM Modéré
A6: Primary Evidence Tool | D6: Outil de preuve principal
A7: Contributing Tools | D7: Outils contributeurs
A8: Control Description | B8: (A) The information system implements CSE approved cryptography in accordance with applicable organizational policies, directives and standards. | D8: Description du contrôle | E8: (A) Le système d’information met en œuvre la cryptographie approuvée par le CST conformément aux politiques, aux directives et aux normes organisationnelles applicables.
A9: Supplemental Guidance | B9: Cryptography can be employed to support a variety of security solutions including, for example, the protection of sensitive information, the provision of digital signatures, and the enforcement of information separation when authorized individuals have the necessary clearances for such information but lack the necessary formal access approvals. Cryptography can also be used to support random number generation and hash generation. Generally applicable cryptographic standards include FIPS-validated cryptography. This control does not impose any requirements on organizations to use cryptography. However, if cryptography is required based on the selection of other security controls or policies, organizations document each type of cryptographic use and the type of cryptography required (e.g., protection of classified information: FIPS-validated cryptography). Related controls: AC-2, AC-3, AC-7, AC-17, AC-18, AU-9, AU-10, CM-11, CP-9, IA-3, IA-7, MA-4, MP-2, MP-4, MP-5, SA-4, SC-8, SC-12, SC-28, SI-7 | D9: Directives supplémentaires | E9: La cryptographie peut être utilisée pour la prise en charge d’une variété de solutions de sécurité, y compris, par exemple, la protection des renseignements de nature sensible, la fourniture de signatures numériques, et l’application de la séparation des renseignements lorsque les personnes autorisées ont les autorisations de sécurité nécessaires pour ces renseignements, mais qu’elles n’ont pas les autorisations d’accès officielles nécessaires. La cryptographie peut également être utilisée pour permettre la génération de nombres aléatoires et la génération de hachages. Les normes cryptographiques généralement applicables comprennent la cryptographie conforme aux normes FIPS. Ce contrôle n’oblige pas les organisations à utiliser la cryptographie. Toutefois, si la cryptographie est requise en fonction de la sélection d’autres contrôles ou politiques de sécurité, les organisations documentent chaque type d’utilisation cryptographique et le type de cryptographie requis (p. ex., protection de l’information classifiée : cryptographie conforme aux normes FIPS). Contrôles connexes : AC-2, AC-3, AC-7, AC-17, AC-18, AU-9, AU-10, CM-11, CP-9, IA-3, IA-7, MA-4, MP-2, MP-4, MP-5, SA-4, SC-8, SC-12, SC-28, SI-7
A10: Test Case | D10: Cas de test
A11: Test | B11: TEST-SC-13 | D11: Test | E11: TEST-SC-13
A12: Requirement ID | B12: SC-13 | D12: ID Exigence | E12: SC-13
A13: Component | D13: Composant
A14: Requirement | D14: Exigence
A15: Contextual Design Description | D15: Description contextuelle du design
A16: Evidence Provided | D16: Preuve fournie
A17: Preparer Sign Off (Initials, Date) | D17: Signataire préparateur (Initiales, Date)
A18: Owner Sign Off (Initials, Date) | D18: Signataire propriétaire (Initiales, Date)
A19: Assessor Sign Off (Initials, Date) | D19: Signataire évaluateur (Initiales, Date)
A20: Status | B20: Not Started | D20: Statut | E20: Non commencé
A21: Comments | D21: Commentaires

Sheet SC-28
A1: Control SC-28 — Evidence Tracking | D1: Contrôle SC-28 — Suivi des preuves
A2: Control Information | D2: Informations du contrôle
A3: Control Identifier | B3: SC-28 | D3: Identifiant du contrôle | E3: SC-28
A4: Family | B4: Protection of Information At Rest | D4: Famille | E4: Protection de l’information inactive
A5: Profile | B5: CCCS Medium / PBMM Moderate | D5: Profil | E5: CCCS Moyen / PBMM Modéré
A6: Primary Evidence Tool | D6: Outil de preuve principal
A7: Contributing Tools | D7: Outils contributeurs
A8: Control Description | B8: (A) The information system protects the confidentiality and integrity of all information not cleared for public release and all data with a higher than low integrity requirement. | D8: Description du contrôle | E8: (A) Le système d’information protège la confidentialité et l’intégrité de tous les renseignements dont la diffusion publique n’est pas autorisée et de toutes les données pour lesquelles les exigences d’intégrité ne sont pas faibles.
A9: Supplemental Guidance | B9: This control addresses the confidentiality and integrity of information at rest and covers user information and system information. Information at rest refers to the state of information when it is located on storage devices as specific components of information systems. System-related information requiring protection includes, for example, configurations or rule sets for firewalls, gateways, intrusion detection/prevention systems, filtering routers, and authenticator content. Organizations may employ different mechanisms to achieve confidentiality and integrity protections, including the use of cryptographic mechanisms and file share scanning. Integrity protection can be achieved, for example, by implementing Write-Once-Read-Many (WORM) technologies. Organizations may also employ other security controls including, for example, secure off-line storage in lieu of online storage when adequate protection of information at rest cannot otherwise be achieved and/or continuous monitoring to identify malicious code at rest. Related controls: AC-3, AC-6, CA-7, CM-3, CM-5, CM-6, PE-3, SC-8, SC-13, SI-3, SI-7 | D9: Directives supplémentaires | E9: Ce contrôle porte sur la confidentialité et l’intégrité de l’information inactive et couvre l’information sur les utilisateurs et le système. L’information inactive fait référence à l’état de l’information lorsqu’elle se trouve sur des dispositifs de stockage en tant que composants particuliers des systèmes d’information. Les renseignements relatifs au système qui nécessitent une protection comprennent, par exemple, les configurations ou les ensembles de règles pour les pare-feu, les passerelles, les systèmes de détection et de prévention des intrusions, les routeurs de filtrage et le contenu des authentifiants. Les organisations peuvent utiliser différents mécanismes pour assurer la protection de la confidentialité et de l’intégrité, y compris les mécanismes cryptographiques et le balayage des fichiers partagés. La protection de l’intégrité peut être assurée, par exemple, en mettant en œuvre des technologies qui rendent les supports non réinscriptibles. Les organisations peuvent également utiliser d’autres contrôles de sécurité, y compris, par exemple, le stockage hors ligne sécurisé au lieu du stockage en ligne lorsque la protection de l’information inactive ne peut être assurée autrement, ou la surveillance continue pour repérer du code malveillant inactif. Contrôles connexes : AC-3, AC-6, CA-7, CM-3, CM-5, CM-6, PE-3, SC-8, SC-13, SI-3, SI-7
A10: Test Case | D10: Cas de test
A11: Test | B11: TEST-SC-28 | D11: Test | E11: TEST-SC-28
A12: Requirement ID | B12: SC-28 | D12: ID Exigence | E12: SC-28
A13: Component | D13: Composant
A14: Requirement | D14: Exigence
A15: Contextual Design Description | D15: Description contextuelle du design
A16: Evidence Provided | D16: Preuve fournie
A17: Preparer Sign Off (Initials, Date) | D17: Signataire préparateur (Initiales, Date)
A18: Owner Sign Off (Initials, Date) | D18: Signataire propriétaire (Initiales, Date)
A19: Assessor Sign Off (Initials, Date) | D19: Signataire évaluateur (Initiales, Date)
A20: Status | B20: Not Started | D20: Statut | E20: Non commencé
A21: Comments | D21: Commentaires

Sheet SC-28-1
A1: Control SC-28(1) — Evidence Tracking | D1: Contrôle SC-28(1) — Suivi des preuves
A2: Control Information | D2: Informations du contrôle
A3: Control Identifier | B3: SC-28(1) | D3: Identifiant du contrôle | E3: SC-28(1)
A4: Family | B4: Protection of Information At Rest | D4: Famille | E4: Protection de l’information inactive
A5: Profile | B5: CCCS Medium / PBMM Moderate | D5: Profil | E5: CCCS Moyen / PBMM Modéré
A6: Primary Evidence Tool | D6: Outil de preuve principal
A7: Contributing Tools | D7: Outils contributeurs
A8: Control Description | B8: PROTECTION OF INFORMATION AT REST | CRYPTOGRAPHIC PROTECTION The information system implements cryptographic mechanisms to prevent unauthorized disclosure and modification of all information not cleared for public release and all data with a higher than low integrity requirements. | D8: Description du contrôle | E8: PROTECTION DE L’INFORMATION INACTIVE | PROTECTION CRYPTOGRAPHIQUE Le système d’information met en œuvre des mécanismes cryptographiques pour prévenir la divulgation et la modification non autorisées de tous les renseignements dont la diffusion publique n’est pas autorisée et de toutes les données pour lesquelles les exigences d’intégrité ne sont pas faibles.
A9: Supplemental Guidance | B9: Selection of cryptographic mechanisms is based on the need to protect the confidentiality and integrity of organizational information. The strength of mechanism is commensurate with the security category and/or classification of the information. This control enhancement applies to significant concentrations of digital media in organizational areas designated for media storage and also to limited quantities of media generally associated with information system components in operational environments (e.g., portable storage devices, mobile devices). Organizations have the flexibility to either encrypt all information on storage devices (i.e., full disk encryption) or encrypt specific data structures (e.g., files, records, or fields). Organizations employing cryptographic mechanisms to protect information at rest also consider cryptographic key management solutions. Related controls: AC-19, SC-12. | D9: Directives supplémentaires | E9: Le choix des mécanismes cryptographiques est fonction du besoin de protection de la confidentialité et de l’intégrité de l’information de l’organisation. La force du mécanisme est proportionnelle à la catégorie de sécurité ou à la classification de l’information. Cette amélioration du contrôle s’applique aux concentrations importantes de supports numériques dans les zones de l’organisation qui sont désignées pour le stockage des supports, et également aux quantités limitées de supports généralement associés aux composants de systèmes d’information dans les environnements opérationnels (p. ex., dispositifs de stockage portatifs, appareils mobiles). Les organisations ont la possibilité de chiffrer toute l’information sur les dispositifs de stockage (c.-à-d. le chiffrement complet du disque) ou de chiffrer des structures de données particulières (p. ex., fichiers, enregistrements ou champs). Les organisations qui utilisent des mécanismes cryptographiques pour protéger l’information inactive envisagent également des solutions de gestion des clés cryptographiques. Contrôles connexes : AC-19, SC-12.
A10: Test Case | D10: Cas de test
A11: Test | B11: TEST-SC-28(1) | D11: Test | E11: TEST-SC-28(1)
A12: Requirement ID | B12: SC-28(1) | D12: ID Exigence | E12: SC-28(1)
A13: Component | D13: Composant
A14: Requirement | D14: Exigence
A15: Contextual Design Description | D15: Description contextuelle du design
A16: Evidence Provided | D16: Preuve fournie
A17: Preparer Sign Off (Initials, Date) | D17: Signataire préparateur (Initiales, Date)
A18: Owner Sign Off (Initials, Date) | D18: Signataire propriétaire (Initiales, Date)
A19: Assessor Sign Off (Initials, Date) | D19: Signataire évaluateur (Initiales, Date)
A20: Status | B20: Not Started | D20: Statut | E20: Non commencé
A21: Comments | D21: Commentaires

Sheet SI-2
A1: Control SI-2 — Evidence Tracking | D1: Contrôle SI-2 — Suivi des preuves
A2: Control Information | D2: Informations du contrôle
A3: Control Identifier | B3: SI-2 | D3: Identifiant du contrôle | E3: SI-2
A4: Family | B4: Flaw Remediation | D4: Famille | E4: Correction des défauts
A5: Profile | B5: CCCS Medium / PBMM Moderate | D5: Profil | E5: CCCS Moyen / PBMM Modéré
A6: Primary Evidence Tool | D6: Outil de preuve principal
A7: Contributing Tools | D7: Outils contributeurs
