Workbook

Sheet DASHBOARD
A1: DASHBOARD — PBMM Evidence: Identity
A2: Control ID | B2: Control Name | C2: Primary Tool | D2: Tab | E2: Status
A3: AC-2 | B3: Account Management | D3: AC-2 | E3: ='AC-2'!B20 -> Not Started
A4: AC-2(1) | B4: Account Management | D4: AC-2-1 | E4: ='AC-2-1'!B20 -> Not Started
A5: AC-2(2) | B5: Account Management | D5: AC-2-2 | E5: ='AC-2-2'!B20 -> Not Started
A6: AC-2(3) | B6: Account Management | D6: AC-2-3 | E6: ='AC-2-3'!B20 -> Not Started
A7: AC-2(4) | B7: Account Management | D7: AC-2-4 | E7: ='AC-2-4'!B20 -> Not Started
A8: AC-2(5) | B8: Account Management | D8: AC-2-5 | E8: ='AC-2-5'!B20 -> Not Started
A9: AC-2(7) | B9: Account Management | D9: AC-2-7 | E9: ='AC-2-7'!B20 -> Not Started
A10: AC-3 | B10: Access Enforcement | D10: AC-3 | E10: ='AC-3'!B20 -> Not Started
A11: AC-6 | B11: Least Privilege | D11: AC-6 | E11: ='AC-6'!B20 -> Not Started
A12: AC-6(1) | B12: Least Privilege | D12: AC-6-1 | E12: ='AC-6-1'!B20 -> Not Started
A13: AC-6(9) | B13: Least Privilege | D13: AC-6-9 | E13: ='AC-6-9'!B20 -> Not Started
A14: AC-6(10) | B14: Least Privilege | D14: AC-6-10 | E14: ='AC-6-10'!B20 -> Not Started
A15: AC-7 | B15: Unsuccessful Login Attempts | D15: AC-7 | E15: ='AC-7'!B20 -> Not Started
A16: AC-10 | B16: Concurrent Session Control | D16: AC-10 | E16: ='AC-10'!B20 -> Not Started
A17: AC-11 | B17: Session Lock | D17: AC-11 | E17: ='AC-11'!B20 -> Not Started
A18: AC-17(1) | B18: Remote Access | D18: AC-17-1 | E18: ='AC-17-1'!B20 -> Not Started
A19: AC-17(9) | B19: Remote Access | D19: AC-17-9 | E19: ='AC-17-9'!B20 -> Not Started
A20: AC-21 | B20: User-Based Collaboration and Information Sharing | D20: AC-21 | E20: ='AC-21'!B20 -> Not Started
A21: AU-2 | B21: Auditable Events | D21: AU-2 | E21: ='AU-2'!B20 -> Not Started
A22: AU-3 | B22: Content of Audit Records | D22: AU-3 | E22: ='AU-3'!B20 -> Not Started
A23: AU-3(1) | B23: Content of Audit Records | D23: AU-3-1 | E23: ='AU-3-1'!B20 -> Not Started
A24: AU-9 | B24: Protection of Audit Information | D24: AU-9 | E24: ='AU-9'!B20 -> Not Started
A25: AU-9(2) | B25: Protection of Audit Information | D25: AU-9-2 | E25: ='AU-9-2'!B20 -> Not Started
A26: AU-9(4) | B26: Protection of Audit Information | D26: AU-9-4 | E26: ='AU-9-4'!B20 -> Not Started
A27: AU-12 | B27: Audit Generation | D27: AU-12 | E27: ='AU-12'!B20 -> Not Started
A28: CM-5(1) | B28: Access Restrictions for Change | D28: CM-5-1 | E28: ='CM-5-1'!B20 -> Not Started
A29: CM-5(5) | B29: Access Restrictions for Change | D29: CM-5-5 | E29: ='CM-5-5'!B20 -> Not Started
A30: CM-5(6) | B30: Access Restrictions for Change | D30: CM-5-6 | E30: ='CM-5-6'!B20 -> Not Started
A31: CM-6 | B31: Configuration Settings | D31: CM-6 | E31: ='CM-6'!B20 -> Not Started
A32: CM-7 | B32: Least Functionality | D32: CM-7 | E32: ='CM-7'!B20 -> Not Started
A33: CM-7(1) | B33: Least Functionality | D33: CM-7-1 | E33: ='CM-7-1'!B20 -> Not Started
A34: CP-7 | B34: Alternate Processing Site | D34: CP-7 | E34: ='CP-7'!B20 -> Not Started
A35: CP-7(4) | B35: Alternate Processing Site | D35: CP-7-4 | E35: ='CP-7-4'!B20 -> Not Started
A36: CP-10 | B36: Information System Recovery and Reconstitution | D36: CP-10 | E36: ='CP-10'!B20 -> Not Started
A37: CP-10(4) | B37: Information System Recovery and Reconstitution | D37: CP-10-4 | E37: ='CP-10-4'!B20 -> Not Started
A38: IA-2 | B38: Identification and Authentication (Organizational Users) | D38: IA-2 | E38: ='IA-2'!B20 -> Not Started
A39: IA-2(1) | B39: Identification and Authentication (Organizational Users) | D39: IA-2-1 | E39: ='IA-2-1'!B20 -> Not Started
A40: IA-2(3) | B40: Identification and Authentication (Organizational Users) | D40: IA-2-3 | E40: ='IA-2-3'!B20 -> Not Started
A41: IA-2(6) | B41: Identification and Authentication (Organizational Users) | D41: IA-2-6 | E41: ='IA-2-6'!B20 -> Not Started
A42: IA-2(8) | B42: Identification and Authentication (Organizational Users) | D42: IA-2-8 | E42: ='IA-2-8'!B20 -> Not Started
A43: IA-2(11) | B43: Identification and Authentication (Organizational Users) | D43: IA-2-11 | E43: ='IA-2-11'!B20 -> Not Started
A44: IA-4 | B44: Identifier Management | D44: IA-4 | E44: ='IA-4'!B20 -> Not Started
A45: IA-5 | B45: Authenticator Management | D45: IA-5 | E45: ='IA-5'!B20 -> Not Started
A46: IA-5(1) | B46: Authenticator Management | D46: IA-5-1 | E46: ='IA-5-1'!B20 -> Not Started
A47: IA-5(2) | B47: Authenticator Management | D47: IA-5-2 | E47: ='IA-5-2'!B20 -> Not Started
A48: IA-5(4) | B48: Authenticator Management | D48: IA-5-4 | E48: ='IA-5-4'!B20 -> Not Started
A49: IA-5(6) | B49: Authenticator Management | D49: IA-5-6 | E49: ='IA-5-6'!B20 -> Not Started
A50: IA-6 | B50: Authenticator Feedback | D50: IA-6 | E50: ='IA-6'!B20 -> Not Started
A51: IA-7 | B51: Cryptographic Module Authentication | D51: IA-7 | E51: ='IA-7'!B20 -> Not Started
A52: IA-8 | B52: Identification and Authentication (Non-Organizational Users) | D52: IA-8 | E52: ='IA-8'!B20 -> Not Started
A53: MA-4 | B53: Non-Local Maintenance | D53: MA-4 | E53: ='MA-4'!B20 -> Not Started
A54: SA-9(5) | B54: External Information System Services | D54: SA-9-5 | E54: ='SA-9-5'!B20 -> Not Started
A55: SC-13 | B55: Cryptographic Protection | D55: SC-13 | E55: ='SC-13'!B20 -> Not Started
A56: SI-4(2) | B56: Information System Monitoring | D56: SI-4-2 | E56: ='SI-4-2'!B20 -> Not Started
A57: SI-6 | B57: Security Functional Verification | D57: SI-6 | E57: ='SI-6'!B20 -> Not Started
A59: Completion Metrics
A60: Total Controls | E60: =55 -> 55
A61: Not Started | E61: =COUNTIF(E3:E57,"Not Started") -> 55
A62: In Progress | E62: =COUNTIF(E3:E57,"In Progress") -> 0
A63: Evidence Provided | E63: =COUNTIF(E3:E57,"Evidence Provided") -> 0
A64: Under Review | E64: =COUNTIF(E3:E57,"Under Review") -> 0
A65: Passed | E65: =COUNTIF(E3:E57,"Passed") -> 0
A66: Failed | E66: =COUNTIF(E3:E57,"Failed") -> 0
A67: Accepted Exception | E67: =COUNTIF(E3:E57,"Accepted Exception") -> 0
A68: % Complete | E68: =IFERROR(COUNTIF(E3:E57,"Passed")/55,0) -> 0
A69: % Not Started | E69: =IFERROR(COUNTIF(E3:E57,"Not Started")/55,0) -> 1

Sheet TABLEAU_DE_BORD
A1: TABLEAU DE BORD — Suivi PBMM : Identity
A2: ID Contrôle | B2: Nom du contrôle | C2: Outil principal | D2: Onglet | E2: Statut
A3: AC-2 | B3: Gestion des comptes | D3: AC-2 | E3: ='AC-2'!E20 -> Non commencé
A4: AC-2(1) | B4: Gestion des comptes | D4: AC-2-1 | E4: ='AC-2-1'!E20 -> Non commencé
A5: AC-2(2) | B5: Gestion des comptes | D5: AC-2-2 | E5: ='AC-2-2'!E20 -> Non commencé
A6: AC-2(3) | B6: Gestion des comptes | D6: AC-2-3 | E6: ='AC-2-3'!E20 -> Non commencé
A7: AC-2(4) | B7: Gestion des comptes | D7: AC-2-4 | E7: ='AC-2-4'!E20 -> Non commencé
A8: AC-2(5) | B8: Gestion des comptes | D8: AC-2-5 | E8: ='AC-2-5'!E20 -> Non commencé
A9: AC-2(7) | B9: Gestion des comptes | D9: AC-2-7 | E9: ='AC-2-7'!E20 -> Non commencé
A10: AC-3 | B10: Application des contrôles d’accès | D10: AC-3 | E10: ='AC-3'!E20 -> Non commencé
A11: AC-6 | B11: Moindre privilège | D11: AC-6 | E11: ='AC-6'!E20 -> Non commencé
A12: AC-6(1) | B12: Moindre privilège | D12: AC-6-1 | E12: ='AC-6-1'!E20 -> Non commencé
A13: AC-6(9) | B13: Moindre privilège | D13: AC-6-9 | E13: ='AC-6-9'!E20 -> Non commencé
A14: AC-6(10) | B14: Moindre privilège | D14: AC-6-10 | E14: ='AC-6-10'!E20 -> Non commencé
A15: AC-7 | B15: Tentatives infructueuses d’ouverture de session | D15: AC-7 | E15: ='AC-7'!E20 -> Non commencé
A16: AC-10 | B16: Contrôle des sessions simultanées | D16: AC-10 | E16: ='AC-10'!E20 -> Non commencé
A17: AC-11 | B17: Verrouillage de session | D17: AC-11 | E17: ='AC-11'!E20 -> Non commencé
A18: AC-17(1) | B18: Accès à distance | D18: AC-17-1 | E18: ='AC-17-1'!E20 -> Non commencé
A19: AC-17(9) | B19: Accès à distance | D19: AC-17-9 | E19: ='AC-17-9'!E20 -> Non commencé
A20: AC-21 | B20: Collaboration et partage d’information entre utilisateurs | D20: AC-21 | E20: ='AC-21'!E20 -> Non commencé
A21: AU-2 | B21: Événements vérifiables | D21: AU-2 | E21: ='AU-2'!E20 -> Non commencé
A22: AU-3 | B22: Contenu des enregistrements de vérification | D22: AU-3 | E22: ='AU-3'!E20 -> Non commencé
A23: AU-3(1) | B23: Contenu des enregistrements de vérification | D23: AU-3-1 | E23: ='AU-3-1'!E20 -> Non commencé
A24: AU-9 | B24: Protection des renseignements de vérification | D24: AU-9 | E24: ='AU-9'!E20 -> Non commencé
A25: AU-9(2) | B25: Protection des renseignements de vérification | D25: AU-9-2 | E25: ='AU-9-2'!E20 -> Non commencé
A26: AU-9(4) | B26: Protection des renseignements de vérification | D26: AU-9-4 | E26: ='AU-9-4'!E20 -> Non commencé
A27: AU-12 | B27: Génération des vérifications | D27: AU-12 | E27: ='AU-12'!E20 -> Non commencé
A28: CM-5(1) | B28: Restrictions d’accès pour les changements | D28: CM-5-1 | E28: ='CM-5-1'!E20 -> Non commencé
A29: CM-5(5) | B29: Restrictions d’accès pour les changements | D29: CM-5-5 | E29: ='CM-5-5'!E20 -> Non commencé
A30: CM-5(6) | B30: Restrictions d’accès pour les changements | D30: CM-5-6 | E30: ='CM-5-6'!E20 -> Non commencé
A31: CM-6 | B31: Paramètres de configuration | D31: CM-6 | E31: ='CM-6'!E20 -> Non commencé
A32: CM-7 | B32: Moindre fonctionnalité | D32: CM-7 | E32: ='CM-7'!E20 -> Non commencé
A33: CM-7(1) | B33: Moindre fonctionnalité | D33: CM-7-1 | E33: ='CM-7-1'!E20 -> Non commencé
A34: CP-7 | B34: Site de traitement auxiliaire | D34: CP-7 | E34: ='CP-7'!E20 -> Non commencé
A35: CP-7(4) | B35: Site de traitement auxiliaire | D35: CP-7-4 | E35: ='CP-7-4'!E20 -> Non commencé
A36: CP-10 | B36: Reprise et reconstitution du système d’information | D36: CP-10 | E36: ='CP-10'!E20 -> Non commencé
A37: CP-10(4) | B37: Reprise et reconstitution du système d’information | D37: CP-10-4 | E37: ='CP-10-4'!E20 -> Non commencé
A38: IA-2 | B38: Identification et authentification (utilisateurs au sein de l’organisation) | D38: IA-2 | E38: ='IA-2'!E20 -> Non commencé
A39: IA-2(1) | B39: Identification et authentification (utilisateurs au sein de l’organisation) | D39: IA-2-1 | E39: ='IA-2-1'!E20 -> Non commencé
A40: IA-2(3) | B40: Identification et authentification (utilisateurs au sein de l’organisation) | D40: IA-2-3 | E40: ='IA-2-3'!E20 -> Non commencé
A41: IA-2(6) | B41: Identification et authentification (utilisateurs au sein de l’organisation) | D41: IA-2-6 | E41: ='IA-2-6'!E20 -> Non commencé
A42: IA-2(8) | B42: Identification et authentification (utilisateurs au sein de l’organisation) | D42: IA-2-8 | E42: ='IA-2-8'!E20 -> Non commencé
A43: IA-2(11) | B43: Identification et authentification (utilisateurs au sein de l’organisation) | D43: IA-2-11 | E43: ='IA-2-11'!E20 -> Non commencé
A44: IA-4 | B44: Gestion des identifiants | D44: IA-4 | E44: ='IA-4'!E20 -> Non commencé
A45: IA-5 | B45: Gestion des authentifiants | D45: IA-5 | E45: ='IA-5'!E20 -> Non commencé
A46: IA-5(1) | B46: Gestion des authentifiants | D46: IA-5-1 | E46: ='IA-5-1'!E20 -> Non commencé
A47: IA-5(2) | B47: Gestion des authentifiants | D47: IA-5-2 | E47: ='IA-5-2'!E20 -> Non commencé
A48: IA-5(4) | B48: Gestion des authentifiants | D48: IA-5-4 | E48: ='IA-5-4'!E20 -> Non commencé
A49: IA-5(6) | B49: Gestion des authentifiants | D49: IA-5-6 | E49: ='IA-5-6'!E20 -> Non commencé
A50: IA-6 | B50: Rétroaction de l’authentifiant | D50: IA-6 | E50: ='IA-6'!E20 -> Non commencé
A51: IA-7 | B51: Authentification par module cryptographique | D51: IA-7 | E51: ='IA-7'!E20 -> Non commencé
A52: IA-8 | B52: Identification et authentification (utilisateurs extérieurs à l’organisation) | D52: IA-8 | E52: ='IA-8'!E20 -> Non commencé
A53: MA-4 | B53: Maintenance non locale | D53: MA-4 | E53: ='MA-4'!E20 -> Non commencé
A54: SA-9(5) | B54: Services de systèmes d’information externes | D54: SA-9-5 | E54: ='SA-9-5'!E20 -> Non commencé
A55: SC-13 | B55: Protection cryptographique | D55: SC-13 | E55: ='SC-13'!E20 -> Non commencé
A56: SI-4(2) | B56: Surveillance du système d’information | D56: SI-4-2 | E56: ='SI-4-2'!E20 -> Non commencé
A57: SI-6 | B57: Vérification fonctionnelle de la sécurité | D57: SI-6 | E57: ='SI-6'!E20 -> Non commencé
A59: Métriques de complétude
A60: Nombre total de contrôles | E60: =55 -> 55
A61: Non commencés | E61: =COUNTIF(E3:E57,"Non commencé") -> 55
A62: En cours | E62: =COUNTIF(E3:E57,"En cours") -> 0
A63: Preuve fournie | E63: =COUNTIF(E3:E57,"Preuve fournie") -> 0
A64: En révision | E64: =COUNTIF(E3:E57,"En révision") -> 0
A65: Réussi | E65: =COUNTIF(E3:E57,"Réussi") -> 0
A66: Échec | E66: =COUNTIF(E3:E57,"Échec") -> 0
A67: Exception acceptée | E67: =COUNTIF(E3:E57,"Exception acceptée") -> 0
A68: % Complété | E68: =IFERROR(COUNTIF(E3:E57,"Réussi")/55,0) -> 0
A69: % Non commencés | E69: =IFERROR(COUNTIF(E3:E57,"Non commencé")/55,0) -> 1

Sheet AC-2
A1: Control AC-2 — Evidence Tracking | D1: Contrôle AC-2 — Suivi des preuves
A2: Control Information | D2: Informations du contrôle
A3: Control Identifier | B3: AC-2 | D3: Identifiant du contrôle | E3: AC-2
A4: Family | B4: Account Management | D4: Famille | E4: Gestion des comptes
A5: Profile | B5: CCCS Medium / PBMM Moderate | D5: Profil | E5: CCCS Moyen / PBMM Modéré
A6: Primary Evidence Tool | D6: Outil de preuve principal
A7: Contributing Tools | D7: Outils contributeurs
A8: Control Description | B8: (A) The organization identifies and selects which types of information system accounts support organizational missions/business functions. (B) The organization assigns account managers for information system accounts. (C) The organization establishes conditions for group and role membership. (D) The organization specifies authorized users of the information system, group and role membership, and access authorizations (i.e., privileges) and other attributes (as required) for each account. (E) The organization requires approvals by responsible managers for requests to create information system accounts. (F) The organization creates, enables, modifies, disables, and removes information system accounts in accordance with information system account management procedures. (G) The organization monitors the use of information system accounts. (H) The organization notifies account managers: (a) When accounts are no longer required; (b) When users are terminated or transferred; and (c) When individual information system usage or need-to-know changes. (I) The organization authorizes access to the information system based on: (a) A valid access authorization; (b) Intended system usage; and (c) Other attributes as required by the organization or associated missions/business functions. (J) The organization reviews accounts for compliance with account management requirements at least annually. (K) The organization establishes a process for reissuing shared/group account credentials (if deployed) when individuals are removed from the group. | D8: Description du contrôle | E8: (A) L’organisation détermine et sélectionne les types de comptes du système d’information qui soutiennent les fonctions opérationnelles et de mission de l’organisation. (B) L’organisation affecte des gestionnaires de comptes aux comptes du système d’information. (C) L’organisation établit les conditions d’adhésion aux groupes et aux rôles. (D) L’organisation précise les utilisateurs autorisés du système d’information, l’adhésion aux groupes et aux rôles, et les autorisations d’accès (c.-à-d., les privilèges) et autres attributs (au besoin) pour chaque compte. (E) L’organisation requiert l’approbation des gestionnaires responsables des demandes de création de comptes de système d’information. (F) L’organisation crée, active, modifie, désactive et supprime les comptes du système d’information conformément aux procédures de gestion des comptes du système d’information. (G) L’organisation surveille l’utilisation des comptes du système d’information. (H) L’organisation avise les gestionnaires de comptes : (a) lorsque des comptes ne sont plus requis; (b) lorsque des utilisateurs sont congédiés ou transférés; (c) lorsque l’utilisation individuelle du système d’information ou le besoin de savoir change. (I) L’organisation autorise l’accès au système d’information en se basant sur : (a) une autorisation d’accès valide; (b) l’utilisation prévue du système; (c) d’autres attributs requis par l’organisation ou les fonctions opérationnelles ou de mission connexes. (J) L’organisation revoit la conformité aux exigences de gestion des comptes au moins une fois par année. (K) L’organisation établit un processus de réémission des justificatifs d’identité de compte partagé/de groupe (si déployés) lorsque des personnes sont retirées du groupe.
A9: Supplemental Guidance | B9: Information system account types include, for example, individual, shared, group, system, guest/anonymous, emergency, developer/manufacturer/vendor, temporary, and service. Some of the account management requirements listed above can be implemented by organizational information systems. The identification of authorized users of the information system and the specification of access privileges reflects the requirements in other security controls in the security plan. Users requiring administrative privileges on information system accounts receive additional scrutiny by appropriate organizational personnel (e.g., system owner, mission/business owner, or information technology security co-ordinator) responsible for approving such accounts and privileged access. Organizations may choose to define access privileges or other attributes by account, by type of account, or a combination of both. Other attributes required for authorizing access include, for example, restrictions on time-of-day, day-of-week, and point-of-origin. In defining other account attributes, organizations consider system-related requirements (e.g., scheduled maintenance, system upgrades) and mission/business requirements, (e.g., time zone differences, customer requirements, remote access to support travel requirements). Failure to consider these factors could affect information system availability. Temporary and emergency accounts are accounts intended for short-term use. Organizations establish temporary accounts as a part of normal account activation procedures when there is a need for short-term accounts without the demand for immediacy in account activation. Organizations establish emergency accounts in response to crisis situations and with the need for rapid account activation. Therefore, emergency account activation may bypass normal account authorization processes. Emergency and temporary accounts are not to be confused with infrequently used accounts (e.g., local accounts used for special tasks defined by organizations or when network resources are unavailable). Such accounts remain available and are not subject to automatic disabling or removal dates. Conditions for disabling or deactivating accounts include, for example: (i) when shared/group, emergency, or temporary accounts are no longer required; or (ii) when individuals are transferred or terminated. Some types of information system accounts may require specialized training. Related controls: AC-3, AC-4, AC-5, AC-6, AC-10, AC-17, AC-19, AC-20, AU-9, IA-2, IA-4, IA-5, IA-8, CM-5, CM-6, CM-11, MA-3, MA-4, MA-5, PL-4, SC-13 | D9: Directives supplémentaires | E9: Les types de comptes du système d’information comprennent, par exemple, les comptes individuels, partagés, de groupe, de système, d’invité/anonymes, d’urgence, de développeur/fabricant/fournisseur, temporaires et de service. Certaines des exigences de gestion des comptes énumérées ci-dessus peuvent être mises en œuvre par les systèmes d’information de l’organisation. L’identification des utilisateurs autorisés du système d’information et la spécification des privilèges d’accès reflètent les exigences dans les autres contrôles de sécurité du plan de sécurité. Les utilisateurs qui ont besoin de privilèges administratifs sur les comptes du système d’information font l’objet d’un examen plus approfondi par le personnel approprié de l’organisation (p. ex., propriétaire du système, responsable opérationnel/de mission, ou coordonnateur de la sécurité des technologies de l’information) responsable de l’approbation de ces comptes et de l’accès privilégié. Les organisations peuvent choisir de définir les privilèges d’accès ou d’autres attributs par compte, par type de compte, ou par une combinaison des deux. Les autres attributs requis pour autoriser l’accès comprennent, par exemple, les restrictions sur l’heure du jour, le jour de la semaine et le point d’origine. En définissant d’autres attributs de compte, les organisations tiennent compte des exigences liées au système (p. ex., maintenance programmée, mise à niveau du système) et des exigences opérationnelles/de mission (p. ex., différences de fuseau horaire, exigences des clients, accès à distance pour répondre aux besoins en matière de déplacements). Le défaut de tenir compte de ces facteurs pourrait avoir une incidence sur la disponibilité du système d’information. Les comptes temporaires et d’urgence sont des comptes destinés à une utilisation à court terme. Les organisations établissent des comptes temporaires dans le cadre des procédures normales d’activation des comptes lorsqu’elles ont besoin de comptes à court terme sans requérir l’activation immédiate de ces comptes. Les organisations établissent des comptes d’urgence en réponse à des situations de crise et lorsqu’elles doivent activer rapidement les comptes. Par conséquent, l’activation d’un compte d’urgence peut contourner les processus normaux d’autorisation de compte. Il ne faut pas confondre les comptes d’urgence et les comptes temporaires avec les comptes peu utilisés (p. ex., comptes locaux utilisés pour des tâches spéciales définies par les organisations ou lorsque les ressources du réseau ne sont pas disponibles). Ces comptes demeurent disponibles et ne sont pas assujettis à des dates de désactivation ou de retrait automatiques. Les conditions de désactivation des comptes comprennent, par exemple : (i) lorsque les comptes partagés/de groupe, d’urgence ou temporaires ne sont plus requis; ou (ii) lorsque des personnes sont transférées ou licenciées. Certains types de comptes de système d’information peuvent nécessiter une formation spécialisée. Contrôles connexes : AC-3, AC-4, AC-5, AC-6, AC-10, AC-17, AC-19, AC-20, AU-9, IA-2, IA-4, IA-5, IA-8, CM-5, CM-6, CM-11, MA-3, MA-4, MA-5, PL-4, SC-13
A10: Test Case | D10: Cas de test
A11: Test | B11: TEST-AC-2 | D11: Test | E11: TEST-AC-2
A12: Requirement ID | B12: AC-2 | D12: ID Exigence | E12: AC-2
A13: Component | D13: Composant
A14: Requirement | D14: Exigence
A15: Contextual Design Description | D15: Description contextuelle du design
A16: Evidence Provided | D16: Preuve fournie
A17: Preparer Sign Off (Initials, Date) | D17: Signataire préparateur (Initiales, Date)
A18: Owner Sign Off (Initials, Date) | D18: Signataire propriétaire (Initiales, Date)
A19: Assessor Sign Off (Initials, Date) | D19: Signataire évaluateur (Initiales, Date)
A20: Status | B20: Not Started | D20: Statut | E20: Non commencé
A21: Comments | D21: Commentaires

Sheet AC-2-1
A1: Control AC-2(1) — Evidence Tracking | D1: Contrôle AC-2(1) — Suivi des preuves
A2: Control Information | D2: Informations du contrôle
A3: Control Identifier | B3: AC-2(1) | D3: Identifiant du contrôle | E3: AC-2(1)
A4: Family | B4: Account Management | D4: Famille | E4: Gestion des comptes
A5: Profile | B5: CCCS Medium / PBMM Moderate | D5: Profil | E5: CCCS Moyen / PBMM Modéré
A6: Primary Evidence Tool | D6: Outil de preuve principal
A7: Contributing Tools | D7: Outils contributeurs
A8: Control Description | B8: ACCOUNT MANAGEMENT | AUTOMATED SYSTEM ACCOUNT MANAGEMENT The organization employs automated mechanisms to support the management of information system accounts. | D8: Description du contrôle | E8: GESTION DES COMPTES | GESTION AUTOMATISÉE DES COMPTES DU SYSTÈME L’organisation utilise des mécanismes automatisés pour prendre en charge la gestion des comptes du système d’information.
A9: Supplemental Guidance | B9: The use of automated mechanisms can include, for example: using email or text messaging to automatically notify account managers when users are terminated or transferred; using the information system to monitor account usage; and using telephonic notification to report atypical system account usage. | D9: Directives supplémentaires | E9: L’utilisation de mécanismes automatisés peut comprendre, par exemple, l’utilisation de courriels ou de messages texte pour aviser automatiquement les gestionnaires de comptes lorsque des utilisateurs sont licenciés ou transférés; l’utilisation du système d’information pour surveiller les statistiques d’utilisation des comptes; et l’utilisation d’une notification téléphonique pour signaler l’utilisation atypique des comptes du système.
A10: Test Case | D10: Cas de test
A11: Test | B11: TEST-AC-2(1) | D11: Test | E11: TEST-AC-2(1)
A12: Requirement ID | B12: AC-2(1) | D12: ID Exigence | E12: AC-2(1)
A13: Component | D13: Composant
A14: Requirement | D14: Exigence
A15: Contextual Design Description | D15: Description contextuelle du design
A16: Evidence Provided | D16: Preuve fournie
A17: Preparer Sign Off (Initials, Date) | D17: Signataire préparateur (Initiales, Date)
A18: Owner Sign Off (Initials, Date) | D18: Signataire propriétaire (Initiales, Date)
A19: Assessor Sign Off (Initials, Date) | D19: Signataire évaluateur (Initiales, Date)
A20: Status | B20: Not Started | D20: Statut | E20: Non commencé
A21: Comments | D21: Commentaires

Sheet AC-2-2
A1: Control AC-2(2) — Evidence Tracking | D1: Contrôle AC-2(2) — Suivi des preuves
A2: Control Information | D2: Informations du contrôle
A3: Control Identifier | B3: AC-2(2) | D3: Identifiant du contrôle | E3: AC-2(2)
A4: Family | B4: Account Management | D4: Famille | E4: Gestion des comptes
A5: Profile | B5: CCCS Medium / PBMM Moderate | D5: Profil | E5: CCCS Moyen / PBMM Modéré
A6: Primary Evidence Tool | D6: Outil de preuve principal
A7: Contributing Tools | D7: Outils contributeurs
A8: Control Description | B8: ACCOUNT MANAGEMENT | REMOVAL OF TEMPORARY / EMERGENCY ACCOUNTS The information system automatically disables temporary and emergency accounts after no more than 30 days for both temporary and emergency accounts. | D8: Description du contrôle | E8: GESTION DES COMPTES | RETRAIT DES COMPTES TEMPORAIRES/D’URGENCE Le système d’information désactive automatiquement les comptes temporaires et d’urgence après un maximum de 30 jours, pour les comptes temporaires comme pour les comptes d’urgence.
A9: Supplemental Guidance | B9: This control enhancement requires the removal of both temporary and emergency accounts automatically after a predefined period of time has elapsed, rather than at the convenience of the systems administrator. | D9: Directives supplémentaires | E9: Cette amélioration du contrôle exige le retrait automatique des comptes temporaires et d’urgence au terme d’une période prédéfinie, plutôt qu’à la convenance de l’administrateur des systèmes.
A10: Test Case | D10: Cas de test
A11: Test | B11: TEST-AC-2(2) | D11: Test | E11: TEST-AC-2(2)
A12: Requirement ID | B12: AC-2(2) | D12: ID Exigence | E12: AC-2(2)
A13: Component | D13: Composant
A14: Requirement | D14: Exigence
A15: Contextual Design Description | D15: Description contextuelle du design
A16: Evidence Provided | D16: Preuve fournie
A17: Preparer Sign Off (Initials, Date) | D17: Signataire préparateur (Initiales, Date)
A18: Owner Sign Off (Initials, Date) | D18: Signataire propriétaire (Initiales, Date)
A19: Assessor Sign Off (Initials, Date) | D19: Signataire évaluateur (Initiales, Date)
A20: Status | B20: Not Started | D20: Statut | E20: Non commencé
A21: Comments | D21: Commentaires

Sheet AC-2-3
A1: Control AC-2(3) — Evidence Tracking | D1: Contrôle AC-2(3) — Suivi des preuves
A2: Control Information | D2: Informations du contrôle
A3: Control Identifier | B3: AC-2(3) | D3: Identifiant du contrôle | E3: AC-2(3)
A4: Family | B4: Account Management | D4: Famille | E4: Gestion des comptes
A5: Profile | B5: CCCS Medium / PBMM Moderate | D5: Profil | E5: CCCS Moyen / PBMM Modéré
A6: Primary Evidence Tool | D6: Outil de preuve principal
A7: Contributing Tools | D7: Outils contributeurs
A8: Control Description | B8: ACCOUNT MANAGEMENT | DISABLE INACTIVE ACCOUNTS The information system automatically disables inactive accounts after 90 days. | D8: Description du contrôle | E8: GESTION DES COMPTES | DÉSACTIVATION DES COMPTES INACTIFS Le système d’information désactive automatiquement les comptes après 90 jours d’inactivité.
A9: Supplemental Guidance | D9: Directives supplémentaires
A10: Test Case | D10: Cas de test
A11: Test | B11: TEST-AC-2(3) | D11: Test | E11: TEST-AC-2(3)
A12: Requirement ID | B12: AC-2(3) | D12: ID Exigence | E12: AC-2(3)
A13: Component | D13: Composant
A14: Requirement | D14: Exigence
A15: Contextual Design Description | D15: Description contextuelle du design
A16: Evidence Provided | D16: Preuve fournie
A17: Preparer Sign Off (Initials, Date) | D17: Signataire préparateur (Initiales, Date)
A18: Owner Sign Off (Initials, Date) | D18: Signataire propriétaire (Initiales, Date)
A19: Assessor Sign Off (Initials, Date) | D19: Signataire évaluateur (Initiales, Date)
A20: Status | B20: Not Started | D20: Statut | E20: Non commencé
A21: Comments | D21: Commentaires

Sheet AC-2-4
A1: Control AC-2(4) — Evidence Tracking | D1: Contrôle AC-2(4) — Suivi des preuves
A2: Control Information | D2: Informations du contrôle
A3: Control Identifier | B3: AC-2(4) | D3: Identifiant du contrôle | E3: AC-2(4)
A4: Family | B4: Account Management | D4: Famille | E4: Gestion des comptes
A5: Profile | B5: CCCS Medium / PBMM Moderate | D5: Profil | E5: CCCS Moyen / PBMM Modéré
A6: Primary Evidence Tool | D6: Outil de preuve principal
A7: Contributing Tools | D7: Outils contributeurs
A8: Control Description | B8: ACCOUNT MANAGEMENT | AUTOMATED AUDIT ACTIONS The information system automatically audits account creation, modification, enabling, disabling, and removal actions, and notifies responsible managers. Related controls: AU-2, AU-12. | D8: Description du contrôle | E8: GESTION DES COMPTES | MESURES DE VÉRIFICATION AUTOMATISÉES Le système d’information vérifie automatiquement les opérations de création, de modification, d’activation, de désactivation et de retrait des comptes, et avise les gestionnaires responsables. Contrôles connexes : AU-2, AU-12.
A9: Supplemental Guidance | D9: Directives supplémentaires
A10: Test Case | D10: Cas de test
A11: Test | B11: TEST-AC-2(4) | D11: Test | E11: TEST-AC-2(4)
A12: Requirement ID | B12: AC-2(4) | D12: ID Exigence | E12: AC-2(4)
A13: Component | D13: Composant
A14: Requirement | D14: Exigence
A15: Contextual Design Description | D15: Description contextuelle du design
A16: Evidence Provided | D16: Preuve fournie
A17: Preparer Sign Off (Initials, Date) | D17: Signataire préparateur (Initiales, Date)
A18: Owner Sign Off (Initials, Date) | D18: Signataire propriétaire (Initiales, Date)
A19: Assessor Sign Off (Initials, Date) | D19: Signataire évaluateur (Initiales, Date)
A20: Status | B20: Not Started | D20: Statut | E20: Non commencé
A21: Comments | D21: Commentaires

Sheet AC-2-5
A1: Control AC-2(5) — Evidence Tracking | D1: Contrôle AC-2(5) — Suivi des preuves
A2: Control Information | D2: Informations du contrôle
A3: Control Identifier | B3: AC-2(5) | D3: Identifiant du contrôle | E3: AC-2(5)
A4: Family | B4: Account Management | D4: Famille | E4: Gestion des comptes
A5: Profile | B5: CCCS Medium / PBMM Moderate | D5: Profil | E5: CCCS Moyen / PBMM Modéré
A6: Primary Evidence Tool | D6: Outil de preuve principal
A7: Contributing Tools | D7: Outils contributeurs
A8: Control Description | B8: ACCOUNT MANAGEMENT | INACTIVITY LOGOUT The organization requires that users log out at the end of the users’ standard work period unless otherwise defined in formal organizational policy. Related controls: SC-23 | D8: Description du contrôle | E8: GESTION DES COMPTES | FERMETURE DE SESSION INACTIVE L’organisation exige que les utilisateurs ferment leur session à la fin de leur période de travail normale, à moins d’indication contraire dans la politique officielle de l’organisation. Contrôles connexes : SC-23
A9: Supplemental Guidance | D9: Directives supplémentaires
A10: Test Case | D10: Cas de test
A11: Test | B11: TEST-AC-2(5) | D11: Test | E11: TEST-AC-2(5)
A12: Requirement ID | B12: AC-2(5) | D12: ID Exigence | E12: AC-2(5)
A13: Component | D13: Composant
A14: Requirement | D14: Exigence
A15: Contextual Design Description | D15: Description contextuelle du design
A16: Evidence Provided | D16: Preuve fournie
A17: Preparer Sign Off (Initials, Date) | D17: Signataire préparateur (Initiales, Date)
A18: Owner Sign Off (Initials, Date) | D18: Signataire propriétaire (Initiales, Date)
A19: Assessor Sign Off (Initials, Date) | D19: Signataire évaluateur (Initiales, Date)
A20: Status | B20: Not Started | D20: Statut | E20: Non commencé
A21: Comments | D21: Commentaires

Sheet AC-2-7
A1: Control AC-2(7) — Evidence Tracking | D1: Contrôle AC-2(7) — Suivi des preuves
A2: Control Information | D2: Informations du contrôle
A3: Control Identifier | B3: AC-2(7) | D3: Identifiant du contrôle | E3: AC-2(7)
A4: Family | B4: Account Management | D4: Famille | E4: Gestion des comptes
A5: Profile | B5: CCCS Medium / PBMM Moderate | D5: Profil | E5: CCCS Moyen / PBMM Modéré
A6: Primary Evidence Tool | D6: Outil de preuve principal
A7: Contributing Tools | D7: Outils contributeurs
A8: Control Description | B8: ACCOUNT MANAGEMENT | ROLE-BASED SCHEMES (a) The organization establishes and administers privileged user accounts in accordance with a role-based access scheme that organizes allowed information system access and privileges into roles; (b) The organization monitors privileged role assignments; and (c) The organization disables (or revokes) privileged user assignments within 24 hours or sooner when privileged role assignments are no longer appropriate. | D8: Description du contrôle | E8: GESTION DES COMPTES | SCHÉMAS FONDÉS SUR LES RÔLES (a) L’organisation établit et administre les comptes d’utilisateurs privilégiés conformément à un système d’accès basé sur les rôles qui organise les autorisations d’accès au système d’information et les privilèges en fonction des rôles; (b) L’organisation surveille les affectations de rôles privilégiés; (c) L’organisation désactive (ou révoque) les affectations d’utilisateurs privilégiés dans les 24 heures ou plus lorsque les affectations de rôles privilégiés ne sont plus appropriées.
A9: Supplemental Guidance | B9: Privileged roles are organization-defined roles assigned to individuals that allow those individuals to perform certain security-relevant functions that ordinary users are not authorized to perform. These privileged roles include, for example, key management, account management, network and system administration, database administration, and web administration. | D9: Directives supplémentaires | E9: Les rôles privilégiés sont des rôles définis par l’organisation et attribués à des personnes pour leur permettre d’exécuter certaines fonctions ayant une influence sur la sécurité que les utilisateurs ordinaires ne sont pas autorisés à exécuter. Ces rôles privilégiés comprennent, par exemple, la gestion des clés, la gestion des comptes, l’administration des réseaux et des systèmes, l’administration des bases de données et l’administration Web.
A10: Test Case | D10: Cas de test
A11: Test | B11: TEST-AC-2(7) | D11: Test | E11: TEST-AC-2(7)
A12: Requirement ID | B12: AC-2(7) | D12: ID Exigence | E12: AC-2(7)
A13: Component | D13: Composant
A14: Requirement | D14: Exigence
A15: Contextual Design Description | D15: Description contextuelle du design
A16: Evidence Provided | D16: Preuve fournie
A17: Preparer Sign Off (Initials, Date) | D17: Signataire préparateur (Initiales, Date)
A18: Owner Sign Off (Initials, Date) | D18: Signataire propriétaire (Initiales, Date)
A19: Assessor Sign Off (Initials, Date) | D19: Signataire évaluateur (Initiales, Date)
A20: Status | B20: Not Started | D20: Statut | E20: Non commencé
A21: Comments | D21: Commentaires

Sheet AC-3
A1: Control AC-3 — Evidence Tracking | D1: Contrôle AC-3 — Suivi des preuves
A2: Control Information | D2: Informations du contrôle
A3: Control Identifier | B3: AC-3 | D3: Identifiant du contrôle | E3: AC-3
A4: Family | B4: Access Enforcement | D4: Famille | E4: Application des contrôles d’accès
A5: Profile | B5: CCCS Medium / PBMM Moderate | D5: Profil | E5: CCCS Moyen / PBMM Modéré
A6: Primary Evidence Tool | D6: Outil de preuve principal
A7: Contributing Tools | D7: Outils contributeurs
A8: Control Description | B8: (A) The information system enforces approved authorizations for logical access to information and system resources in accordance with applicable access control policies. | D8: Description du contrôle | E8: (A) Le système d’information applique les autorisations approuvées pour l’accès logique à l’information et aux ressources du système conformément aux politiques de contrôle d’accès applicables.
A9: Supplemental Guidance | B9: Access control policies (e.g., identity-based policies, role-based policies, attribute-based policies) and access enforcement mechanisms (e.g.: access control lists, access control matrices, cryptography) control access between active entities or subjects (i.e., users or processes acting on behalf of users) and passive entities or objects (e.g., devices, files, records, domains) in information systems. In addition to enforcing authorized access at the information system level and recognizing that information systems can host many applications and services in support of organizational missions and business operations, access enforcement mechanisms can also be employed at the application and service level to provide increased information security. Related controls: AC-2, AC-4, AC-5, AC-6, AC-16, AC-17, AC-18, AC-19, AC-20, AC-21, AC-22, AU-9, CM-5, CM-6, CM-11, MA-3, MA-4, MA-5, PE-3 | D9: Directives supplémentaires | E9: Les politiques de contrôle d’accès (p. ex., politiques fondées sur l’identité, politiques fondées sur les rôles, politiques fondées sur les attributs) et les mécanismes d’application des contrôles d’accès (p. ex., listes de contrôle d’accès, matrices de contrôle d’accès, cryptographie) contrôlent l’accès entre les entités ou les sujets actifs (c.-à-d. les utilisateurs ou les processus agissant pour le compte des utilisateurs) et les entités ou objets passifs (p. ex., dispositifs, fichiers, enregistrements, domaines) dans les systèmes d’information. En plus d’appliquer l’accès autorisé au niveau du système d’information et de reconnaître que les systèmes d’information peuvent héberger de nombreuses applications et services appuyant les missions et les activités opérationnelles de l’organisation, les mécanismes d’application des contrôles d’accès peuvent également être utilisés au niveau des applications et des services pour accroître la sécurité de l’information. Contrôles connexes : AC-2, AC-4, AC-5, AC-6, AC-16, AC-17, AC-18, AC-19, AC-20, AC-21, AC-22, AU-9, CM-5, CM-6, CM-11, MA-3, MA-4, MA-5, PE-3
A10: Test Case | D10: Cas de test
A11: Test | B11: TEST-AC-3 | D11: Test | E11: TEST-AC-3
A12: Requirement ID | B12: AC-3 | D12: ID Exigence | E12: AC-3
A13: Component | D13: Composant
A14: Requirement | D14: Exigence
A15: Contextual Design Description | D15: Description contextuelle du design
A16: Evidence Provided | D16: Preuve fournie
A17: Preparer Sign Off (Initials, Date) | D17: Signataire préparateur (Initiales, Date)
A18: Owner Sign Off (Initials, Date) | D18: Signataire propriétaire (Initiales, Date)
A19: Assessor Sign Off (Initials, Date) | D19: Signataire évaluateur (Initiales, Date)
A20: Status | B20: Not Started | D20: Statut | E20: Non commencé
A21: Comments | D21: Commentaires

Sheet AC-6
A1: Control AC-6 — Evidence Tracking | D1: Contrôle AC-6 — Suivi des preuves
A2: Control Information | D2: Informations du contrôle
A3: Control Identifier | B3: AC-6 | D3: Identifiant du contrôle | E3: AC-6
A4: Family | B4: Least Privilege | D4: Famille | E4: Moindre privilège
A5: Profile | B5: CCCS Medium / PBMM Moderate | D5: Profil | E5: CCCS Moyen / PBMM Modéré
A6: Primary Evidence Tool | D6: Outil de preuve principal
A7: Contributing Tools | D7: Outils contributeurs
A8: Control Description | B8: (A) The organization employs the principle of least privilege, allowing only authorized accesses for users (or processes acting on behalf of users) which are necessary to accomplish assigned tasks in accordance with organizational missions and business functions. | D8: Description du contrôle | E8: (A) L’organisation utilise le principe du moindre privilège, qui permet seulement les accès autorisés aux utilisateurs (ou aux processus qui agissent pour le compte des utilisateurs) qui sont nécessaires pour accomplir les tâches assignées conformément aux missions et aux fonctions opérationnelles de l’organisation.
A9: Supplemental Guidance | B9: Organizations employ least privilege for specific duties and information systems. The principle of least privilege is also applied to information system processes, ensuring that the processes operate at privilege levels no higher than necessary to accomplish required organizational missions/business functions. Organizations consider the creation of additional processes, roles, and information system accounts as necessary, to achieve least privilege. Organizations also apply least privilege to the development, implementation, and operation of organizational information systems. Related controls: AC-2, AC-3, AC-5, CM-6, CM-7, PL-2 | D9: Directives supplémentaires | E9: Les organisations utilisent le moindre privilège pour certaines tâches et certains systèmes d’information. Le principe du moindre privilège s’applique également aux processus du système d’information, ce qui fait en sorte que les processus ne fonctionnent pas à des niveaux de privilège plus élevés que nécessaire pour accomplir les missions et les fonctions opérationnelles requises de l’organisation. Les organisations envisagent la création de processus, de rôles et de comptes de système d’information supplémentaires lorsque nécessaire, pour obtenir le moindre privilège. Les organisations appliquent également le moindre privilège au développement, à la mise en œuvre et à l’exploitation de leurs systèmes d’information. Contrôles connexes : AC-2, AC-3, AC-5, CM-6, CM-7, PL-2
A10: Test Case | D10: Cas de test
A11: Test | B11: TEST-AC-6 | D11: Test | E11: TEST-AC-6
A12: Requirement ID | B12: AC-6 | D12: ID Exigence | E12: AC-6
A13: Component | D13: Composant
A14: Requirement | D14: Exigence
A15: Contextual Design Description | D15: Description contextuelle du design
A16: Evidence Provided | D16: Preuve fournie
A17: Preparer Sign Off (Initials, Date) | D17: Signataire préparateur (Initiales, Date)
A18: Owner Sign Off (Initials, Date) | D18: Signataire propriétaire (Initiales, Date)
A19: Assessor Sign Off (Initials, Date) | D19: Signataire évaluateur (Initiales, Date)
A20: Status | B20: Not Started | D20: Statut | E20: Non commencé
A21: Comments | D21: Commentaires

Sheet AC-6-1
A1: Control AC-6(1) — Evidence Tracking | D1: Contrôle AC-6(1) — Suivi des preuves
A2: Control Information | D2: Informations du contrôle
A3: Control Identifier | B3: AC-6(1) | D3: Identifiant du contrôle | E3: AC-6(1)
A4: Family | B4: Least Privilege | D4: Famille | E4: Moindre privilège
A5: Profile | B5: CCCS Medium / PBMM Moderate | D5: Profil | E5: CCCS Moyen / PBMM Modéré
A6: Primary Evidence Tool | D6: Outil de preuve principal
A7: Contributing Tools | D7: Outils contributeurs
A8: Control Description | B8: LEAST PRIVILEGE | AUTHORIZE ACCESS TO SECURITY FUNCTIONS The organization explicitly authorizes access to all security functions not publicly accessible and all security-relevant information not publicly available. | D8: Description du contrôle | E8: MOINDRE PRIVILÈGE | AUTORISATION D’ACCÈS AUX FONCTIONS DE SÉCURITÉ L’organisation autorise explicitement l’accès à toutes les fonctions de sécurité qui ne sont pas accessibles au public et à toute l’information pertinente à la sécurité qui n’est pas accessible au public.
A9: Supplemental Guidance | B9: Security functions include, for example, establishing system accounts, configuring access authorizations (i.e., permissions, privileges), setting events to be audited, and setting intrusion detection parameters. Security-relevant information includes, for example, filtering rules for routers/firewalls, cryptographic key management information, configuration parameters for security services, and access control lists. Explicitly authorized personnel include, for example, security administrators, system and network administrators, system security officers, system maintenance personnel, system programmers, and other privileged users. Related controls: AC-17, AC-18, AC-19. | D9: Directives supplémentaires | E9: Les fonctions de sécurité comprennent, par exemple, l’établissement des comptes système, la configuration des autorisations d’accès (c.-à-d. les permissions, les privilèges), le réglage des événements à vérifier, et l’établissement des paramètres de détection des intrusions. Les renseignements pertinents pour la sécurité comprennent, par exemple, les règles de filtrage pour les routeurs/pare-feu, l’information de gestion des clés cryptographiques, les paramètres de configuration pour les services de sécurité et les listes de contrôle d’accès. Le personnel explicitement autorisé comprend, par exemple, les administrateurs de la sécurité, les administrateurs de systèmes et de réseaux, les agents de sécurité des systèmes, le personnel de maintenance des systèmes, les programmeurs de systèmes et d’autres utilisateurs privilégiés. Contrôles connexes : AC-17, AC-18, AC-19.
A10: Test Case | D10: Cas de test
A11: Test | B11: TEST-AC-6(1) | D11: Test | E11: TEST-AC-6(1)
A12: Requirement ID | B12: AC-6(1) | D12: ID Exigence | E12: AC-6(1)
A13: Component | D13: Composant
A14: Requirement | D14: Exigence
A15: Contextual Design Description | D15: Description contextuelle du design
A16: Evidence Provided | D16: Preuve fournie
A17: Preparer Sign Off (Initials, Date) | D17: Signataire préparateur (Initiales, Date)
A18: Owner Sign Off (Initials, Date) | D18: Signataire propriétaire (Initiales, Date)
A19: Assessor Sign Off (Initials, Date) | D19: Signataire évaluateur (Initiales, Date)
A20: Status | B20: Not Started | D20: Statut | E20: Non commencé
A21: Comments | D21: Commentaires

Sheet AC-6-9
A1: Control AC-6(9) — Evidence Tracking | D1: Contrôle AC-6(9) — Suivi des preuves
A2: Control Information | D2: Informations du contrôle
A3: Control Identifier | B3: AC-6(9) | D3: Identifiant du contrôle | E3: AC-6(9)
A4: Family | B4: Least Privilege | D4: Famille | E4: Moindre privilège
A5: Profile | B5: CCCS Medium / PBMM Moderate | D5: Profil | E5: CCCS Moyen / PBMM Modéré
A6: Primary Evidence Tool | D6: Outil de preuve principal
A7: Contributing Tools | D7: Outils contributeurs
A8: Control Description | B8: LEAST PRIVILEGE | AUDITING USE OF PRIVILEGED FUNCTIONS The information system audits the execution of privileged functions. | D8: Description du contrôle | E8: MOINDRE PRIVILÈGE | VÉRIFICATION DE L’UTILISATION DES FONCTIONS PRIVILÉGIÉES Le système d’information vérifie l’exécution des fonctions privilégiées.
A9: Supplemental Guidance | B9: Misuse of privileged functions, either intentionally or unintentionally by authorized users, or by unauthorized external entities that have compromised information system accounts, is a serious and ongoing concern and can have significant adverse impacts on organizations. Auditing the use of privileged functions is one way to detect such misuse, and in doing so, help mitigate the risk from insider threats and the advanced persistent threat (APT). Related control: AU-2. | D9: Directives supplémentaires | E9: L’utilisation abusive des fonctions privilégiées, intentionnellement ou non, par des utilisateurs autorisés ou par des entités externes non autorisées qui ont compromis des comptes de système d’information, est une préoccupation grave et constante qui peut avoir des répercussions négatives importantes sur les organisations. La vérification de l’utilisation des fonctions privilégiées est une façon de détecter un tel abus et, ce faisant, de contribuer à atténuer le risque de menaces internes et de menaces persistantes avancées (MPA). Contrôle connexe : AU-2.
A10: Test Case | D10: Cas de test
A11: Test | B11: TEST-AC-6(9) | D11: Test | E11: TEST-AC-6(9)
A12: Requirement ID | B12: AC-6(9) | D12: ID Exigence | E12: AC-6(9)
A13: Component | D13: Composant
A14: Requirement | D14: Exigence
A15: Contextual Design Description | D15: Description contextuelle du design
A16: Evidence Provided | D16: Preuve fournie
A17: Preparer Sign Off (Initials, Date) | D17: Signataire préparateur (Initiales, Date)
A18: Owner Sign Off (Initials, Date) | D18: Signataire propriétaire (Initiales, Date)
A19: Assessor Sign Off (Initials, Date) | D19: Signataire évaluateur (Initiales, Date)
A20: Status | B20: Not Started | D20: Statut | E20: Non commencé
A21: Comments | D21: Commentaires

Sheet AC-6-10
A1: Control AC-6(10) — Evidence Tracking | D1: Contrôle AC-6(10) — Suivi des preuves
A2: Control Information | D2: Informations du contrôle
A3: Control Identifier | B3: AC-6(10) | D3: Identifiant du contrôle | E3: AC-6(10)
A4: Family | B4: Least Privilege | D4: Famille | E4: Moindre privilège
A5: Profile | B5: CCCS Medium / PBMM Moderate | D5: Profil | E5: CCCS Moyen / PBMM Modéré
A6: Primary Evidence Tool | D6: Outil de preuve principal
A7: Contributing Tools | D7: Outils contributeurs
A8: Control Description | B8: LEAST PRIVILEGE | PROHIBIT NON-PRIVILEGED USERS FROM EXECUTING PRIVILEGED FUNCTIONS The information system prevents non-privileged users from executing privileged functions to include disabling, circumventing, or altering implemented security safeguards/countermeasures. | D8: Description du contrôle | E8: MOINDRE PRIVILÈGE | INTERDICTION AUX UTILISATEURS NON PRIVILÉGIÉS D’EXÉCUTER DES FONCTIONS PRIVILÉGIÉES Le système d’information empêche les utilisateurs non privilégiés d’exécuter des fonctions privilégiées, y compris la désactivation, le contournement ou la modification des mécanismes/contre-mesures de sécurité en place.
A9: Supplemental Guidance | B9: Privileged functions include, for example, establishing information system accounts, performing system integrity checks, or administering cryptographic key management activities. Non-privileged users are individuals that do not possess appropriate authorizations. Circumventing intrusion detection and prevention mechanisms or malicious code protection mechanisms are examples of privileged functions that require protection from non-privileged users. | D9: Directives supplémentaires | E9: Les fonctions privilégiées comprennent, par exemple, l’établissement des comptes du système d’information, l’exécution des vérifications de l’intégrité du système ou l’administration des activités de gestion de clés cryptographiques. Les utilisateurs non privilégiés sont des personnes qui ne possèdent pas les autorisations appropriées. Les contournements de mécanismes de détection et de prévention des intrusions ou de mécanismes de protection contre le code malveillant sont des exemples de fonctions privilégiées qui nécessitent une protection contre les utilisateurs non privilégiés.
A10: Test Case | D10: Cas de test
A11: Test | B11: TEST-AC-6(10) | D11: Test | E11: TEST-AC-6(10)
A12: Requirement ID | B12: AC-6(10) | D12: ID Exigence | E12: AC-6(10)
A13: Component | D13: Composant
A14: Requirement | D14: Exigence
A15: Contextual Design Description | D15: Description contextuelle du design
A16: Evidence Provided | D16: Preuve fournie
A17: Preparer Sign Off (Initials, Date) | D17: Signataire préparateur (Initiales, Date)
A18: Owner Sign Off (Initials, Date) | D18: Signataire propriétaire (Initiales, Date)
A19: Assessor Sign Off (Initials, Date) | D19: Signataire évaluateur (Initiales, Date)
A20: Status | B20: Not Started | D20: Statut | E20: Non commencé
A21: Comments | D21: Commentaires

Sheet AC-7
A1: Control AC-7 — Evidence Tracking | D1: Contrôle AC-7 — Suivi des preuves
A2: Control Information | D2: Informations du contrôle
A3: Control Identifier | B3: AC-7 | D3: Identifiant du contrôle | E3: AC-7
A4: Family | B4: Unsuccessful Login Attempts | D4: Famille | E4: Tentatives infructueuses d’ouverture de session
A5: Profile | B5: CCCS Medium / PBMM Moderate | D5: Profil | E5: CCCS Moyen / PBMM Modéré
A6: Primary Evidence Tool | D6: Outil de preuve principal
A7: Contributing Tools | D7: Outils contributeurs
A8: Control Description | B8: (A) The information system enforces a limit of not more than three consecutive invalid logon attempts by a user during a 15-minute time period. (B) The information system automatically locks the account/node for a minimum of three (3) hours or until unlocked by an administrator. | D8: Description du contrôle | E8: (A) Le système d’information impose une limite de trois tentatives invalides consécutives d’ouverture de session par un utilisateur pendant une période de 15 minutes. (B) Le système d’information verrouille automatiquement le compte ou le nœud pendant au moins trois (3) heures ou jusqu’à ce qu’un administrateur le déverrouille.
A9: Supplemental Guidance | B9: Due to the potential for denial of service, automatic lockouts initiated by the information system are usually temporary and automatically release after a predetermined time period established by the organization. If a delay algorithm is selected, the organization may choose to employ different algorithms for different information system components based on the capabilities of those components. Response to unsuccessful login attempts may be implemented at both the operating system and the application levels. This control applies to all accesses other than those accesses explicitly identified and documented by the organization in AC-14. This security control/enhancement requires careful balance between usability and security. Care needs to be taken to ensure that the appropriate balance between the two seemingly conflicting requirements is achieved. If possible, an increasing time-out period should be used to deter determined attackers. For example, an original time-out of 5 minutes can become 10 minutes after the next 3 unsuccessful attempts, then 20 minutes, then 40 minutes, etc. | D9: Directives supplémentaires | E9: En raison de la possibilité de refus de service, les verrouillages automatiques déclenchés par le système d’information sont habituellement temporaires et automatiquement annulés après une période prédéterminée établie par l’organisation. Si un algorithme d’attente est sélectionné, l’organisation peut choisir d’utiliser différents algorithmes pour différents composants du système d’information en fonction des capacités de ces composants. La réponse aux tentatives d’ouverture de session infructueuses peut être mise en œuvre à la fois au niveau du système d’exploitation et de l’application. Ce contrôle s’applique à tous les accès autres que ceux explicitement identifiés et documentés par l’organisation dans AC-14. Ce contrôle ou cette amélioration de sécurité exige un équilibre prudent entre la facilité d’utilisation et la sécurité. Il faut veiller à assurer l’équilibre approprié entre ces deux exigences apparemment contradictoires. Dans la mesure du possible, une période de temporisation plus longue devrait être utilisée pour dissuader les attaquants déterminés. Par exemple, une temporisation initiale de 5 minutes peut devenir 10 minutes après les 3 tentatives infructueuses suivantes, puis 20 minutes, puis 40 minutes, etc.
A10: Test Case | D10: Cas de test
A11: Test | B11: TEST-AC-7 | D11: Test | E11: TEST-AC-7
A12: Requirement ID | B12: AC-7 | D12: ID Exigence | E12: AC-7
A13: Component | D13: Composant
A14: Requirement | D14: Exigence
A15: Contextual Design Description | D15: Description contextuelle du design
A16: Evidence Provided | D16: Preuve fournie
A17: Preparer Sign Off (Initials, Date) | D17: Signataire préparateur (Initiales, Date)
A18: Owner Sign Off (Initials, Date) | D18: Signataire propriétaire (Initiales, Date)
A19: Assessor Sign Off (Initials, Date) | D19: Signataire évaluateur (Initiales, Date)
A20: Status | B20: Not Started | D20: Statut | E20: Non commencé
A21: Comments | D21: Commentaires

Sheet AC-10
A1: Control AC-10 — Evidence Tracking | D1: Contrôle AC-10 — Suivi des preuves
A2: Control Information | D2: Informations du contrôle
A3: Control Identifier | B3: AC-10 | D3: Identifiant du contrôle | E3: AC-10
A4: Family | B4: Concurrent Session Control | D4: Famille | E4: Contrôle des sessions simultanées
A5: Profile | B5: CCCS Medium / PBMM Moderate | D5: Profil | E5: CCCS Moyen / PBMM Modéré
A6: Primary Evidence Tool | D6: Outil de preuve principal
A7: Contributing Tools | D7: Outils contributeurs
A8: Control Description | B8: (A) The information system limits the number of concurrent sessions for all accounts unless justified for operation requirements to 3 sessions for privileged access and 2 sessions for non-privileged access. | D8: Description du contrôle | E8: (A) Le système d’information limite le nombre de sessions simultanées pour tous les comptes, à moins qu’elles ne soient justifiées par les exigences opérationnelles, à trois sessions pour l’accès privilégié et à deux sessions pour l’accès non privilégié.
A9: Supplemental Guidance | B9: Organizations may define the maximum number of concurrent sessions for information system accounts globally, by account type (e.g., privileged user, non-privileged user, domain, specific application), by account, or a combination. For example, organizations may limit the number of concurrent sessions for system administrators or individuals working in particularly sensitive domains or mission-critical applications. This control addresses concurrent sessions for information system accounts and does not address concurrent sessions by single users via multiple system accounts | D9: Directives supplémentaires | E9: Les organisations peuvent définir globalement le nombre maximal de sessions simultanées pour les comptes du système d’information, par type de compte (p. ex., utilisateur privilégié, utilisateur non privilégié, domaine, application particulière), par compte ou par une combinaison de ces deux critères. Par exemple, les organisations peuvent limiter le nombre de sessions simultanées pour les administrateurs de système ou les personnes qui travaillent dans des domaines particulièrement sensibles ou des applications essentielles à la mission. Ce contrôle porte sur les sessions simultanées pour des comptes du système d’information et ne traite pas des sessions simultanées par des utilisateurs uniques utilisant plusieurs comptes du système.
A10: Test Case | D10: Cas de test
A11: Test | B11: TEST-AC-10 | D11: Test | E11: TEST-AC-10
A12: Requirement ID | B12: AC-10 | D12: ID Exigence | E12: AC-10
A13: Component | D13: Composant
A14: Requirement | D14: Exigence
A15: Contextual Design Description | D15: Description contextuelle du design
A16: Evidence Provided | D16: Preuve fournie
A17: Preparer Sign Off (Initials, Date) | D17: Signataire préparateur (Initiales, Date)
A18: Owner Sign Off (Initials, Date) | D18: Signataire propriétaire (Initiales, Date)
A19: Assessor Sign Off (Initials, Date) | D19: Signataire évaluateur (Initiales, Date)
A20: Status | B20: Not Started | D20: Statut | E20: Non commencé
A21: Comments | D21: Commentaires

Sheet AC-11
A1: Control AC-11 — Evidence Tracking | D1: Contrôle AC-11 — Suivi des preuves
A2: Control Information | D2: Informations du contrôle
A3: Control Identifier | B3: AC-11 | D3: Identifiant du contrôle | E3: AC-11
A4: Family | B4: Session Lock | D4: Famille | E4: Verrouillage de session
A5: Profile | B5: CCCS Medium / PBMM Moderate | D5: Profil | E5: CCCS Moyen / PBMM Modéré
A6: Primary Evidence Tool | D6: Outil de preuve principal
A7: Contributing Tools | D7: Outils contributeurs
A8: Control Description | B8: (A) The information system prevents further access to the system by initiating a session lock after 15 minutes of inactivity or upon receiving a request from a user. (B) The information system retains the session lock until the user re-establishes access using established identification and authentication procedures. | D8: Description du contrôle | E8: (A) Le système d’information empêche tout accès supplémentaire au système en amorçant un verrouillage de session après 15 minutes d’inactivité ou après en avoir reçu la demande de la part d’un utilisateur. (B) Le système d’information maintient le verrouillage de session jusqu’à ce que l’utilisateur rétablisse l’accès en utilisant les procédures d’identification et d’authentification établies.
A9: Supplemental Guidance | B9: Session locks are temporary actions taken when users stop work and move away from the immediate vicinity of information systems but do not want to log out because of the temporary nature of their absences. Session locks are implemented where session activities can be determined. This is typically at the operating system level, but can also be at the application level. Session locks are not an acceptable substitute for logging out of information systems, for example, if organizations require users to log out at the end of workdays. Related control: AC-7 | D9: Directives supplémentaires | E9: Les verrouillages de session sont des mesures temporaires prises lorsque les utilisateurs arrêtent de travailler et s’éloignent du voisinage immédiat des systèmes d’information, mais ne veulent pas fermer leur session en raison de la nature temporaire de leur absence. Les verrouillages de session sont mis en œuvre là où les activités de session peuvent être déterminées. C’est habituellement au niveau du système d’exploitation, mais cela peut aussi être au niveau de l’application. Les verrouillages de session ne constituent pas un substitut acceptable à la déconnexion des systèmes d’information, par exemple, si les organisations demandent aux utilisateurs de fermer leur session à la fin des journées de travail. Contrôle connexe : AC-7
A10: Test Case | D10: Cas de test
A11: Test | B11: TEST-AC-11 | D11: Test | E11: TEST-AC-11
A12: Requirement ID | B12: AC-11 | D12: ID Exigence | E12: AC-11
A13: Component | D13: Composant
A14: Requirement | D14: Exigence
A15: Contextual Design Description | D15: Description contextuelle du design
A16: Evidence Provided | D16: Preuve fournie
A17: Preparer Sign Off (Initials, Date) | D17: Signataire préparateur (Initiales, Date)
A18: Owner Sign Off (Initials, Date) | D18: Signataire propriétaire (Initiales, Date)
A19: Assessor Sign Off (Initials, Date) | D19: Signataire évaluateur (Initiales, Date)
A20: Status | B20: Not Started | D20: Statut | E20: Non commencé
A21: Comments | D21: Commentaires

Sheet AC-17-1
A1: Control AC-17(1) — Evidence Tracking | D1: Contrôle AC-17(1) — Suivi des preuves
A2: Control Information | D2: Informations du contrôle
A3: Control Identifier | B3: AC-17(1) | D3: Identifiant du contrôle | E3: AC-17(1)
A4: Family | B4: Remote Access | D4: Famille | E4: Accès à distance
A5: Profile | B5: CCCS Medium / PBMM Moderate | D5: Profil | E5: CCCS Moyen / PBMM Modéré
A6: Primary Evidence Tool | D6: Outil de preuve principal
A7: Contributing Tools | D7: Outils contributeurs
A8: Control Description | B8: REMOTE ACCESS | AUTOMATED MONITORING / CONTROL The information system monitors and controls remote access methods. | D8: Description du contrôle | E8: ACCÈS À DISTANCE | SURVEILLANCE ET CONTRÔLE AUTOMATISÉS Le système d’information surveille et contrôle les méthodes d’accès à distance.
A9: Supplemental Guidance | B9: Automated monitoring and control of remote access sessions allows organizations to detect cyber-attacks and also ensure ongoing compliance with remote access policies by auditing connection activities of remote users on a variety of information system components (e.g., servers, workstations, notebook computers, smart phones, and tablets). Related controls: AU-2, AU-12. | D9: Directives supplémentaires | E9: La surveillance et le contrôle automatisés des sessions avec accès à distance permettent aux organisations de détecter les cyberattaques et d’assurer la conformité continue aux politiques d’accès à distance en vérifiant les activités de connexion des utilisateurs distants sur une variété de composants du système d’information (p. ex., serveurs, postes de travail, ordinateurs portatifs, téléphones intelligents et tablettes). Contrôles connexes : AU-2, AU-12.
A10: Test Case | D10: Cas de test
A11: Test | B11: TEST-AC-17(1) | D11: Test | E11: TEST-AC-17(1)
A12: Requirement ID | B12: AC-17(1) | D12: ID Exigence | E12: AC-17(1)
A13: Component | D13: Composant
A14: Requirement | D14: Exigence
A15: Contextual Design Description | D15: Description contextuelle du design
A16: Evidence Provided | D16: Preuve fournie
A17: Preparer Sign Off (Initials, Date) | D17: Signataire préparateur (Initiales, Date)
A18: Owner Sign Off (Initials, Date) | D18: Signataire propriétaire (Initiales, Date)
A19: Assessor Sign Off (Initials, Date) | D19: Signataire évaluateur (Initiales, Date)
A20: Status | B20: Not Started | D20: Statut | E20: Non commencé
A21: Comments | D21: Commentaires

Sheet AC-17-9
A1: Control AC-17(9) — Evidence Tracking | D1: Contrôle AC-17(9) — Suivi des preuves
A2: Control Information | D2: Informations du contrôle
A3: Control Identifier | B3: AC-17(9) | D3: Identifiant du contrôle | E3: AC-17(9)
A4: Family | B4: Remote Access | D4: Famille | E4: Accès à distance
A5: Profile | B5: CCCS Medium / PBMM Moderate | D5: Profil | E5: CCCS Moyen / PBMM Modéré
A6: Primary Evidence Tool | D6: Outil de preuve principal
A7: Contributing Tools | D7: Outils contributeurs
A8: Control Description | B8: REMOTE ACCESS | DISCONNECT / DISABLE ACCESS The organization provides the capability to expeditiously disconnect or disable remote access to the information system within a period no greater than 15 minutes. | D8: Description du contrôle | E8: ACCÈS À DISTANCE | DÉCONNECTER/DÉSACTIVER L’ACCÈS L’organisation offre la possibilité de déconnecter ou de désactiver rapidement l’accès à distance au système d’information dans un délai maximal de 15 minutes.
A9: Supplemental Guidance | B9: This control enhancement requires organizations to have the capability to rapidly disconnect current users remotely accessing the information system and/or disable further remote access. The speed of disconnect or disablement varies based on the criticality of missions/business functions and the need to eliminate immediate or future remote access to organizational information systems. | D9: Directives supplémentaires | E9: Cette amélioration du contrôle exige que les organisations soient en mesure de déconnecter rapidement les utilisateurs actuels qui accèdent à distance au système d’information ou de désactiver tout accès à distance ultérieur. La rapidité de la déconnexion ou de la désactivation varie en fonction de la criticité des missions et des fonctions opérationnelles et de la nécessité d’éliminer l’accès à distance immédiat ou futur aux systèmes d’information de l’organisation.
A10: Test Case | D10: Cas de test
A11: Test | B11: TEST-AC-17(9) | D11: Test | E11: TEST-AC-17(9)
A12: Requirement ID | B12: AC-17(9) | D12: ID Exigence | E12: AC-17(9)
A13: Component | D13: Composant
A14: Requirement | D14: Exigence
A15: Contextual Design Description | D15: Description contextuelle du design
A16: Evidence Provided | D16: Preuve fournie
A17: Preparer Sign Off (Initials, Date) | D17: Signataire préparateur (Initiales, Date)
A18: Owner Sign Off (Initials, Date) | D18: Signataire propriétaire (Initiales, Date)
A19: Assessor Sign Off (Initials, Date) | D19: Signataire évaluateur (Initiales, Date)
A20: Status | B20: Not Started | D20: Statut | E20: Non commencé
A21: Comments | D21: Commentaires

Sheet AC-21
A1: Control AC-21 — Evidence Tracking | D1: Contrôle AC-21 — Suivi des preuves
A2: Control Information | D2: Informations du contrôle
A3: Control Identifier | B3: AC-21 | D3: Identifiant du contrôle | E3: AC-21
A4: Family | B4: User-Based Collaboration and Information Sharing | D4: Famille | E4: Collaboration et partage d’information entre utilisateurs
A5: Profile | B5: CCCS Medium / PBMM Moderate | D5: Profil | E5: CCCS Moyen / PBMM Modéré
A6: Primary Evidence Tool | D6: Outil de preuve principal
A7: Contributing Tools | D7: Outils contributeurs
A8: Control Description | B8: (A) The organization facilitates information sharing by enabling authorized users to determine if access authorizations assigned to the sharing partner match the access restrictions on the information for organization-defined information sharing circumstances where user discretion is required; and (B) The organization employs organization-defined automated mechanisms or manual processes to assist users in making information sharing/collaboration decisions. | D8: Description du contrôle | E8: (A) L’organisation facilite l’échange d’information en permettant aux utilisateurs autorisés de déterminer si les autorisations d’accès attribuées au partenaire d’échange correspondent aux restrictions d’accès à l’information pour les circonstances de partage d’information définies par l’organisation dans lesquelles la décision est laissée à la discrétion de l’utilisateur; (B) L’organisation utilise des mécanismes automatisés ou des processus manuels définis par l’organisation pour aider les utilisateurs à prendre des décisions sur le partage de l’information et la collaboration.
A9: Supplemental Guidance | B9: This control applies to information that may be restricted in some manner (e.g., privileged medical information, contract-sensitive information, proprietary information, personally identifiable information, classified information related to special access programs or compartments) based on some formal or administrative determination. Depending on the particular information-sharing circumstances, sharing partners may be defined at the individual, group, or organizational level. Information may be defined by content, type, security category, or special access program/compartment. Related control: AC-3 | D9: Directives supplémentaires | E9: Ce contrôle s’applique à l’information qui peut être restreinte d’une manière ou d’une autre (p. ex., renseignements médicaux privilégiés, renseignements sensibles dans le cadre d’un contrat, information confidentielle, renseignements permettant d’identifier une personne, renseignements classifiés liés à des programmes ou à des compartiments d’accès spéciaux) conformément à une décision officielle ou administrative. Selon les circonstances particulières de l’échange d’information, les partenaires d’échange peuvent être définis au niveau individuel, collectif ou organisationnel. L’information peut être définie par le contenu, le type, la catégorie de sécurité ou le programme/compartiment d’accès spécial. Contrôle connexe : AC-3
A10: Test Case | D10: Cas de test
A11: Test | B11: TEST-AC-21 | D11: Test | E11: TEST-AC-21
A12: Requirement ID | B12: AC-21 | D12: ID Exigence | E12: AC-21
A13: Component | D13: Composant
A14: Requirement | D14: Exigence
A15: Contextual Design Description | D15: Description contextuelle du design
A16: Evidence Provided | D16: Preuve fournie
A17: Preparer Sign Off (Initials, Date) | D17: Signataire préparateur (Initiales, Date)
A18: Owner Sign Off (Initials, Date) | D18: Signataire propriétaire (Initiales, Date)
A19: Assessor Sign Off (Initials, Date) | D19: Signataire évaluateur (Initiales, Date)
A20: Status | B20: Not Started | D20: Statut | E20: Non commencé
A21: Comments | D21: Commentaires

Sheet AU-2
A1: Control AU-2 — Evidence Tracking | D1: Contrôle AU-2 — Suivi des preuves
A2: Control Information | D2: Informations du contrôle
A3: Control Identifier | B3: AU-2 | D3: Identifiant du contrôle | E3: AU-2
A4: Family | B4: Auditable Events | D4: Famille | E4: Événements vérifiables
A5: Profile | B5: CCCS Medium / PBMM Moderate | D5: Profil | E5: CCCS Moyen / PBMM Modéré
A6: Primary Evidence Tool | D6: Outil de preuve principal
A7: Contributing Tools | D7: Outils contributeurs
A8: Control Description | B8: (A) The organization determines that the information system is capable of auditing the following events: Successful and unsuccessful account logon events, account management events, object access, policy change, privilege functions, process tracking, and system events. For Web applications: all administrator activity, authentication checks, authorization checks, data deletions, data access, data changes, and permission changes. (B) The organization coordinates the security audit function with other organizational entities requiring audit-related information to enhance mutual support and to help guide the selection of auditable events. (C) The organization provides a rationale for why the auditable events are deemed to be adequate to support after-the-fact investigations of security incidents. (D) The organization determines what organizationally-defined audited events (a subset of the auditable events defined in AU-2 a.) and the frequency of (or situation requiring) auditing for each identified event. | D8: Description du contrôle | E8: (A) L’organisation détermine que le système d’information est capable de vérifier les événements suivants : événements d’ouverture de compte, réussis ou non, événements de gestion de compte, accès aux objets, changement de politique, fonctions de privilèges, suivi des processus et événements du système. Pour les applications Web : toutes les activités des administrateurs, les vérifications d’authentification, les vérifications d’autorisation, les suppressions de données, l’accès aux données, les changements de données et les changements d’autorisation. (B) L’organisation coordonne la fonction de vérification de la sécurité avec d’autres entités organisationnelles qui ont besoin de renseignements liés à la vérification pour améliorer le soutien mutuel et aider à orienter le choix des événements vérifiables. (C) L’organisation explique la raison pour laquelle les événements vérifiables sont jugés adéquats pour appuyer les enquêtes effectuées à la suite des incidents de sécurité. (D) L’organisation détermine les événements définis par l’organisation qui sont vérifiés (un sous-ensemble des événements vérifiables définis dans AU-2 a.) et la fréquence (ou la situation exigeant) des vérifications pour chaque événement identifié.
A9: Supplemental Guidance | B9: An event is any observable occurrence in an organizational information system. Organizations identify audit events as those events which are significant and relevant to the security of information systems and the environments in which those systems operate in order to meet specific and ongoing audit needs. Audit events can include, for example, password changes, failed logons, or failed accesses related to information systems, administrative privilege usage, or third-party credential usage. In determining the set of auditable events, organizations consider the auditing appropriate for each of the security controls to be implemented. To balance auditing requirements with other information system needs, this control also requires identifying that subset of auditable events that are audited at a given point in time. For example, organizations may determine that information systems must have the capability to log every file access both successful and unsuccessful, but not activate that capability except for specific circumstances due to the potential burden on system performance. Auditing requirements, including the need for auditable events, may be referenced in other security controls and control enhancements. Organizations also include auditable events that are required by applicable organizational policies, directives, and standards. Audit records can be generated at various levels of abstraction, including at the packet level as information traverses the network. Selecting the appropriate level of abstraction is a critical aspect of an audit capability and can facilitate the identification of root causes to problems. Organizations consider in the definition of auditable events, the auditing necessary to cover related events such as the steps in distributed, transaction-based processes (e.g., processes that are distributed across multiple organizations) and actions that occur in service-oriented architectures. The information system audits the following privileged user/process events at a minimum: (a) Successful and unsuccessful attempts to access, modify, or delete security objects (Security objects include audit data, system configuration files and file or users’ formal access permissions.) (b) Successful and unsuccessful logon attempts (c) Privileged activities or other system level access (see notes for AU-2 (4)) (d) Starting and ending time for user access to the system (e) Concurrent logons from different workstations (f) All program initiations (see notes for AU-2 (4)) In addition, the information system audits the following unprivileged user/process events at a minimum: (a) Successful and unsuccessful attempts to access, modify, or delete security objects (b) Successful and unsuccessful logon attempts (c) Starting and ending time for user access to the system (d) Concurrent logons from different workstations Related controls: AC-6, AC-17, AU-3, AU-12, MA-4, MP-2, MP-4, SI-4 | D9: Directives supplémentaires | E9: Un événement est toute occurrence observable dans un système d’information organisationnel. Les organisations désignent les événements vérifiables comme étant des événements importants et pertinents pour la sécurité des systèmes d’information et des environnements dans lesquels ces systèmes sont utilisés afin de répondre à des exigences de vérification particulières et continues. Les événements vérifiés peuvent comprendre, par exemple, les changements de mot de passe, les échecs d’ouverture de session ou les échecs accès liés aux systèmes d’information, l’utilisation des privilèges administratifs ou l’utilisation de justificatifs d’identité par des tiers. Lorsqu’elles déterminent l’ensemble des événements vérifiables, les organisations considèrent que la vérification est appropriée pour chacun des contrôles de sécurité à mettre en œuvre. Pour assurer l’équilibre entre les exigences en matière de vérification et les autres besoins du système d’information, ce contrôle exige également de déterminer le sous-ensemble d’événements vérifiables qui sont vérifiés à un moment donné. Par exemple, les organisations peuvent déterminer que les systèmes d’information doivent avoir la capacité d’enregistrer chaque accès aux fichiers, qu’il soit réussi ou non, mais n’activeront cette capacité que dans des circonstances particulières en raison du fardeau potentiel sur le rendement du système. Les exigences en matière de vérification, y compris la nécessité de déterminer des événements vérifiables, peuvent être mentionnées dans d’autres contrôles et améliorations des contrôles de sécurité. Les organisations incluent également les événements vérifiables qui sont exigés par les politiques, les directives et les normes organisationnelles applicables. Les enregistrements de vérification peuvent être générés à divers niveaux d’abstraction, y compris au niveau des paquets, à mesure que l’information traverse le réseau. Le choix du niveau d’abstraction approprié est un aspect essentiel d’une capacité de vérification et peut faciliter l’identification des causes profondes des problèmes. Dans la définition des événements vérifiables, les organisations prennent en compte la vérification nécessaire pour couvrir les événements connexes, comme les étapes des processus distribués, fondés sur les transactions (p. ex., les processus qui sont répartis entre de multiples organisations) et les actions qui ont lieu dans les architectures orientées service. Le système d’information vérifie au minimum les événements suivants liés aux utilisateurs/processus privilégiés : (a) Tentatives réussies et infructueuses d’accéder aux objets de sécurité, de les modifier ou de les supprimer (les objets de sécurité comprennent les données de vérification, les fichiers de configuration de système et les autorisations d’accès officielles des utilisateurs). (b) Tentatives d’ouverture de session réussies et infructueuses (c) Activités privilégiées ou autre accès au niveau du système (voir les notes pour AU-2 [4]) (d) Heures de début et de fin de l’accès des utilisateurs au système (e) Ouvertures de session simultanées à partir de différents postes de travail (f) Tous les lancements de programmes (voir les notes pour AU-2 [4]) De plus, le système d’information vérifie au minimum les événements suivants liés aux utilisateurs/processus non privilégiés : (a) Tentatives réussies et infructueuses d’accès, de modification ou de suppression d’objets de sécurité (b) Tentatives d’ouverture de session réussies et infructueuses (c) Heures de début et de fin de l’accès de l’utilisateur au système (d) Ouvertures de session simultanées à partir de différents postes de travail Contrôles connexes : AC-6, AC-17, AU-3, AU-12, MA-4, MP-2, MP-4, SI-4
A10: Test Case | D10: Cas de test
A11: Test | B11: TEST-AU-2 | D11: Test | E11: TEST-AU-2
A12: Requirement ID | B12: AU-2 | D12: ID Exigence | E12: AU-2
A13: Component | D13: Composant
A14: Requirement | D14: Exigence
A15: Contextual Design Description | D15: Description contextuelle du design
A16: Evidence Provided | D16: Preuve fournie
A17: Preparer Sign Off (Initials, Date) | D17: Signataire préparateur (Initiales, Date)
A18: Owner Sign Off (Initials, Date) | D18: Signataire propriétaire (Initiales, Date)
A19: Assessor Sign Off (Initials, Date) | D19: Signataire évaluateur (Initiales, Date)
A20: Status | B20: Not Started | D20: Statut | E20: Non commencé
A21: Comments | D21: Commentaires

Sheet AU-3
A1: Control AU-3 — Evidence Tracking | D1: Contrôle AU-3 — Suivi des preuves
A2: Control Information | D2: Informations du contrôle
A3: Control Identifier | B3: AU-3 | D3: Identifiant du contrôle | E3: AU-3
A4: Family | B4: Content of Audit Records | D4: Famille | E4: Contenu des enregistrements de vérification
A5: Profile | B5: CCCS Medium / PBMM Moderate | D5: Profil | E5: CCCS Moyen / PBMM Modéré
A6: Primary Evidence Tool | D6: Outil de preuve principal
A7: Contributing Tools | D7: Outils contributeurs
A8: Control Description | B8: (A) The information system generates audit records containing information that establishes what type of event occurred, when the event occurred, where the event occurred, the source of the event, the outcome of the event, and the identity of any individuals or subjects associated with the event. | D8: Description du contrôle | E8: (A) Le système d’information génère des enregistrements de vérification qui contiennent les renseignements permettant d’établir le type d’événement qui a eu lieu, le moment et l’endroit où l’événement a eu lieu, la source de l’événement, le résultat de l’événement, ainsi que l’identité de toute personne ou de tout sujet associé à l’événement.
A9: Supplemental Guidance | B9: Audit record content that may be necessary to satisfy the requirement of this control, includes, for example, time stamps, source and destination addresses, user/process identifiers, event descriptions, success/fail indications, filenames involved, and access control or flow control rules invoked. Event outcomes can include indicators of event success or failure and event-specific results (e.g., the security state of the information system after the event occurred). Related controls: AU-2, AU-8, AU-12, SI-11 | D9: Directives supplémentaires | E9: Le contenu des enregistrements de vérification qui peut être nécessaire pour satisfaire à l’exigence de ce contrôle comprend, par exemple, les estampilles temporelles, les adresses de source et de destination, les identifiants d’utilisateurs ou de processus, les descriptions d’événements, les indications de réussite ou d’échec, les noms des fichiers en cause et les règles de contrôle d’accès ou de flux invoquées. Les résultats de l’événement peuvent comprendre des indicateurs de réussite ou d’échec de l’événement et des résultats propres à l’événement (p. ex., l’état de sécurité du système d’information après l’événement). Contrôles connexes : AU-2, AU-8, AU-12, SI-11
A10: Test Case | D10: Cas de test
A11: Test | B11: TEST-AU-3 | D11: Test | E11: TEST-AU-3
A12: Requirement ID | B12: AU-3 | D12: ID Exigence | E12: AU-3
A13: Component | D13: Composant
A14: Requirement | D14: Exigence
A15: Contextual Design Description | D15: Description contextuelle du design
A16: Evidence Provided | D16: Preuve fournie
A17: Preparer Sign Off (Initials, Date) | D17: Signataire préparateur (Initiales, Date)
A18: Owner Sign Off (Initials, Date) | D18: Signataire propriétaire (Initiales, Date)
A19: Assessor Sign Off (Initials, Date) | D19: Signataire évaluateur (Initiales, Date)
A20: Status | B20: Not Started | D20: Statut | E20: Non commencé
A21: Comments | D21: Commentaires

Sheet AU-3-1
A1: Control AU-3(1) — Evidence Tracking | D1: Contrôle AU-3(1) — Suivi des preuves
A2: Control Information | D2: Informations du contrôle
A3: Control Identifier | B3: AU-3(1) | D3: Identifiant du contrôle | E3: AU-3(1)
A4: Family | B4: Content of Audit Records | D4: Famille | E4: Contenu des enregistrements de vérification
A5: Profile | B5: CCCS Medium / PBMM Moderate | D5: Profil | E5: CCCS Moyen / PBMM Modéré
A6: Primary Evidence Tool | D6: Outil de preuve principal
A7: Contributing Tools | D7: Outils contributeurs
A8: Control Description | B8: CONTENT OF AUDIT RECORDS | ADDITIONAL AUDIT INFORMATION The information system generates audit records containing the following additional information: session, connection, transaction, or activity duration; for client-server transactions, the number of bytes received and bytes sent; additional informational messages to diagnose or identify the event; characteristics that describe or identify the object or resource being acted upon. | D8: Description du contrôle | E8: CONTENU DES ENREGISTREMENTS DE VÉRIFICATION | RENSEIGNEMENTS DE VÉRIFICATION SUPPLÉMENTAIRES Le système d’information génère des enregistrements de vérification contenant les renseignements supplémentaires suivants : la durée de la session, de la connexion, de la transaction ou de l’activité; pour les transactions client-serveur, le nombre d’octets reçus et d’octets envoyés; des messages d’information supplémentaires pour diagnostiquer ou identifier l’événement; les caractéristiques qui décrivent ou identifient l’objet ou la ressource concernés.
A9: Supplemental Guidance | B9: Detailed information that organizations may consider in audit records includes, for example, full text recording of privileged commands or the individual identities of group account users. Organizations consider limiting the additional audit information to only that information explicitly needed for specific audit requirements. This facilitates the use of audit trails and audit logs by not including information that could potentially be misleading or could make it more difficult to locate information of interest. Additional guidance for enhancement (1): Audit events should always be capable of being associated with an individual identity. Associating audit events with a group or role is insufficient. | D9: Directives supplémentaires | E9: Les renseignements détaillés dont les organisations peuvent tenir compte dans les enregistrements de vérification comprennent, par exemple, l’enregistrement en texte intégral des commandes privilégiées ou les identités individuelles des utilisateurs de comptes de groupe. Les organisations devraient envisager de limiter les renseignements de vérification supplémentaires aux seuls renseignements explicitement nécessaires pour répondre à des exigences de vérification particulières. Cela facilitera l’utilisation des pistes de vérification et des journaux de vérification en n’incluant pas les renseignements qui pourraient être trompeurs ou rendre plus difficile la recherche de renseignements utiles. Conseils supplémentaires pour l’amélioration (1) : Les événements vérifiés devraient toujours pouvoir être associés à une identité individuelle. Associer des événements vérifiés à un groupe ou à un rôle est insuffisant.
A10: Test Case | D10: Cas de test
A11: Test | B11: TEST-AU-3(1) | D11: Test | E11: TEST-AU-3(1)
A12: Requirement ID | B12: AU-3(1) | D12: ID Exigence | E12: AU-3(1)
A13: Component | D13: Composant
A14: Requirement | D14: Exigence
A15: Contextual Design Description | D15: Description contextuelle du design
A16: Evidence Provided | D16: Preuve fournie
A17: Preparer Sign Off (Initials, Date) | D17: Signataire préparateur (Initiales, Date)
A18: Owner Sign Off (Initials, Date) | D18: Signataire propriétaire (Initiales, Date)
A19: Assessor Sign Off (Initials, Date) | D19: Signataire évaluateur (Initiales, Date)
A20: Status | B20: Not Started | D20: Statut | E20: Non commencé
A21: Comments | D21: Commentaires

Sheet AU-9
A1: Control AU-9 — Evidence Tracking | D1: Contrôle AU-9 — Suivi des preuves
A2: Control Information | D2: Informations du contrôle
A3: Control Identifier | B3: AU-9 | D3: Identifiant du contrôle | E3: AU-9
A4: Family | B4: Protection of Audit Information | D4: Famille | E4: Protection des renseignements de vérification
A5: Profile | B5: CCCS Medium / PBMM Moderate | D5: Profil | E5: CCCS Moyen / PBMM Modéré
A6: Primary Evidence Tool | D6: Outil de preuve principal
A7: Contributing Tools | D7: Outils contributeurs
A8: Control Description | B8: (A) The information system protects audit information and audit tools from unauthorized access, modification, and deletion. | D8: Description du contrôle | E8: (A) Le système d’information protège les renseignements de vérification et les outils de vérification contre l’accès, la modification et la suppression non autorisés.
A9: Supplemental Guidance | B9: Audit information includes all information (e.g., audit records, audit settings, and audit reports) needed to successfully audit information system activity. This control focuses on technical protection of audit information. Physical protection of audit information is addressed by media protection controls and physical and environmental protection controls. Related controls: AC-3, AC-6, MP-2, MP-4, PE-2, PE-3, PE-6 | D9: Directives supplémentaires | E9: Les renseignements de vérification comprennent tous les renseignements (p. ex., les enregistrements de vérification, les paramètres de vérification et les rapports de vérification) nécessaires pour vérifier avec succès l’activité du système d’information. Ce contrôle est axé sur la protection technique des renseignements de vérification. La protection physique des renseignements de vérification est assurée par des contrôles de protection des supports et des contrôles de protection physique et environnementale. Contrôles connexes : AC-3, AC-6, MP-2, MP-4, PE-2, PE-3, PE-6
A10: Test Case | D10: Cas de test
A11: Test | B11: TEST-AU-9 | D11: Test | E11: TEST-AU-9
A12: Requirement ID | B12: AU-9 | D12: ID Exigence | E12: AU-9
A13: Component | D13: Composant
A14: Requirement | D14: Exigence
A15: Contextual Design Description | D15: Description contextuelle du design
A16: Evidence Provided | D16: Preuve fournie
A17: Preparer Sign Off (Initials, Date) | D17: Signataire préparateur (Initiales, Date)
A18: Owner Sign Off (Initials, Date) | D18: Signataire propriétaire (Initiales, Date)
A19: Assessor Sign Off (Initials, Date) | D19: Signataire évaluateur (Initiales, Date)
A20: Status | B20: Not Started | D20: Statut | E20: Non commencé
A21: Comments | D21: Commentaires

Sheet AU-9-2
A1: Control AU-9(2) — Evidence Tracking | D1: Contrôle AU-9(2) — Suivi des preuves
A2: Control Information | D2: Informations du contrôle
A3: Control Identifier | B3: AU-9(2) | D3: Identifiant du contrôle | E3: AU-9(2)
A4: Family | B4: Protection of Audit Information | D4: Famille | E4: Protection des renseignements de vérification
A5: Profile | B5: CCCS Medium / PBMM Moderate | D5: Profil | E5: CCCS Moyen / PBMM Modéré
A6: Primary Evidence Tool | D6: Outil de preuve principal
A7: Contributing Tools | D7: Outils contributeurs
A8: Control Description | B8: PROTECTION OF AUDIT INFORMATION | AUDIT BACKUP ON SEPARATE PHYSICAL SYSTEMS / COMPONENTS The information system backs up audit records at least weekly onto a physically different system or system component than the system or component being audited. | D8: Description du contrôle | E8: PROTECTION DES RENSEIGNEMENTS DE VÉRIFICATION | SAUVEGARDE DES VÉRIFICATIONS SUR DES SYSTÈMES/COMPOSANTS PHYSIQUES SÉPARÉS Le système d’information sauvegarde les enregistrements de vérification au moins une fois par semaine sur un système ou un composant système physiquement différent du système ou du composant faisant l’objet de la vérification.
A9: Supplemental Guidance | B9: This control enhancement helps to ensure that a compromise of the information system being audited does not also result in a compromise of the audit records. Related controls: AU-4, AU-5, AU-11. | D9: Directives supplémentaires | E9: Cette amélioration permet de s’assurer qu’une compromission du système d’information faisant l’objet d’une vérification n’entraîne pas également la compromission des enregistrements de vérification. Contrôles connexes : AU-4, AU-5, AU-11.
A10: Test Case | D10: Cas de test
A11: Test | B11: TEST-AU-9(2) | D11: Test | E11: TEST-AU-9(2)
A12: Requirement ID | B12: AU-9(2) | D12: ID Exigence | E12: AU-9(2)
A13: Component | D13: Composant
A14: Requirement | D14: Exigence
A15: Contextual Design Description | D15: Description contextuelle du design
A16: Evidence Provided | D16: Preuve fournie
A17: Preparer Sign Off (Initials, Date) | D17: Signataire préparateur (Initiales, Date)
A18: Owner Sign Off (Initials, Date) | D18: Signataire propriétaire (Initiales, Date)
A19: Assessor Sign Off (Initials, Date) | D19: Signataire évaluateur (Initiales, Date)
A20: Status | B20: Not Started | D20: Statut | E20: Non commencé
A21: Comments | D21: Commentaires

Sheet AU-9-4
A1: Control AU-9(4) — Evidence Tracking | D1: Contrôle AU-9(4) — Suivi des preuves
A2: Control Information | D2: Informations du contrôle
A3: Control Identifier | B3: AU-9(4) | D3: Identifiant du contrôle | E3: AU-9(4)
A4: Family | B4: Protection of Audit Information | D4: Famille | E4: Protection des renseignements de vérification
A5: Profile | B5: CCCS Medium / PBMM Moderate | D5: Profil | E5: CCCS Moyen / PBMM Modéré
A6: Primary Evidence Tool | D6: Outil de preuve principal
A7: Contributing Tools | D7: Outils contributeurs
A8: Control Description | B8: PROTECTION OF AUDIT INFORMATION | ACCESS BY SUBSET OF PRIVILEGED USERS The organization authorizes access to management of audit functionality to only an organization-defined subset of privileged users. | D8: Description du contrôle | E8: PROTECTION DES RENSEIGNEMENTS DE VÉRIFICATION | ACCÈS PAR SOUS-ENSEMBLE D’UTILISATEURS PRIVILÉGIÉS L’organisation n’autorise l’accès à la fonction de gestion de la vérification qu’à un sous-ensemble d’utilisateurs privilégiés défini par l’organisation seulement.
A9: Supplemental Guidance | B9: Individuals with privileged access to an information system and who are also the subject of an audit by that system, may affect the reliability of audit information by inhibiting audit activities or modifying audit records. This control enhancement requires that privileged access be further defined between audit-related privileges and other privileges, thus limiting the users with audit-related privileges. Related control: AC-5. | D9: Directives supplémentaires | E9: Les personnes qui ont un accès privilégié à un système d’information et qui font également l’objet d’une vérification par ce système peuvent nuire à la fiabilité de l’information de vérification en entravant les activités de vérification ou en modifiant les enregistrements de vérification. Cette amélioration du contrôle exige que l’accès privilégié soit mieux défini entre les privilèges liés à la vérification et les autres privilèges, de manière à limiter le nombre d’utilisateurs ayant des privilèges liés à la vérification. Contrôle connexe : AC-5.
A10: Test Case | D10: Cas de test
A11: Test | B11: TEST-AU-9(4) | D11: Test | E11: TEST-AU-9(4)
A12: Requirement ID | B12: AU-9(4) | D12: ID Exigence | E12: AU-9(4)
A13: Component | D13: Composant
A14: Requirement | D14: Exigence
A15: Contextual Design Description | D15: Description contextuelle du design
A16: Evidence Provided | D16: Preuve fournie
A17: Preparer Sign Off (Initials, Date) | D17: Signataire préparateur (Initiales, Date)
A18: Owner Sign Off (Initials, Date) | D18: Signataire propriétaire (Initiales, Date)
A19: Assessor Sign Off (Initials, Date) | D19: Signataire évaluateur (Initiales, Date)
A20: Status | B20: Not Started | D20: Statut | E20: Non commencé
A21: Comments | D21: Commentaires

Sheet AU-12
A1: Control AU-12 — Evidence Tracking | D1: Contrôle AU-12 — Suivi des preuves
A2: Control Information | D2: Informations du contrôle
A3: Control Identifier | B3: AU-12 | D3: Identifiant du contrôle | E3: AU-12
A4: Family | B4: Audit Generation | D4: Famille | E4: Génération des vérifications
A5: Profile | B5: CCCS Medium / PBMM Moderate | D5: Profil | E5: CCCS Moyen / PBMM Modéré
A6: Primary Evidence Tool | D6: Outil de preuve principal
A7: Contributing Tools | D7: Outils contributeurs
A8: Control Description | B8: (A) The information system provides audit record generation capability for the auditable events defined in AU-2 a. of all information system and network components where audit capability is deployed/available. (B) The information system allows organization-defined personnel or roles to select which auditable events are to be audited by specific components of the information system. (C) The information system generates audit records for the events defined in AU-2 d. with the content defined in AU-3. | D8: Description du contrôle | E8: (A) Le système d’information offre une capacité de génération d’enregistrements de vérification pour les événements vérifiables définis dans AU-2 a. de tous les composants du système d’information et du réseau où la capacité de vérification est déployée/disponible. (B) Le système d’information permet au personnel ou aux rôles définis par l’organisation de choisir les événements vérifiables qui doivent être vérifiés par des composants précis du système d’information. (C) Le système d’information génère des enregistrements de vérification pour les événements définis dans AU-2 d. avec le contenu défini dans AU-3.
A9: Supplemental Guidance | B9: Audit records can be generated from many different information system components. The list of audited events is the set of events for which audits are to be generated. These events are typically a subset of all events for which the information system is capable of generating audit records. Related controls: AC-3, AU-2, AU-3, AU-6, AU-7 | D9: Directives supplémentaires | E9: Des enregistrements de vérification peuvent être générés à partir de nombreux composants du système d’information. La liste des événements vérifiés est l’ensemble des événements pour lesquels des vérifications doivent être produites. Ces événements sont habituellement un sous-ensemble de tous les événements pour lesquels le système d’information peut générer des enregistrements de vérification. Contrôles connexes : AC-3, AU-2, AU-3, AU-6, AU-7
A10: Test Case | D10: Cas de test
A11: Test | B11: TEST-AU-12 | D11: Test | E11: TEST-AU-12
A12: Requirement ID | B12: AU-12 | D12: ID Exigence | E12: AU-12
A13: Component | D13: Composant
A14: Requirement | D14: Exigence
A15: Contextual Design Description | D15: Description contextuelle du design
A16: Evidence Provided | D16: Preuve fournie
A17: Preparer Sign Off (Initials, Date) | D17: Signataire préparateur (Initiales, Date)
A18: Owner Sign Off (Initials, Date) | D18: Signataire propriétaire (Initiales, Date)
A19: Assessor Sign Off (Initials, Date) | D19: Signataire évaluateur (Initiales, Date)
A20: Status | B20: Not Started | D20: Statut | E20: Non commencé
A21: Comments | D21: Commentaires

Sheet CM-5-1
A1: Control CM-5(1) — Evidence Tracking | D1: Contrôle CM-5(1) — Suivi des preuves
A2: Control Information | D2: Informations du contrôle
A3: Control Identifier | B3: CM-5(1) | D3: Identifiant du contrôle | E3: CM-5(1)
A4: Family | B4: Access Restrictions for Change | D4: Famille | E4: Restrictions d’accès pour les changements
A5: Profile | B5: CCCS Medium / PBMM Moderate | D5: Profil | E5: CCCS Moyen / PBMM Modéré
A6: Primary Evidence Tool | D6: Outil de preuve principal
A7: Contributing Tools | D7: Outils contributeurs
A8: Control Description | B8: ACCESS RESTRICTIONS FOR CHANGE | AUTOMATED ACCESS ENFORCEMENT / AUDITING The information system enforces access restrictions and supports auditing of the enforcement actions. | D8: Description du contrôle | E8: RESTRICTIONS D’ACCÈS POUR LES CHANGEMENTS | CONTRÔLE AUTOMATISÉ DE L’ACCÈS/VÉRIFICATION Le système d’information applique les restrictions d’accès et prend en charge la vérification des contrôles appliqués.
A9: Supplemental Guidance | B9: Related controls: AU-2, AU-12, AU-6, CM-3, and CM-6. | D9: Directives supplémentaires | E9: Contrôles connexes : AU-2, AU-12, AU-6, CM-3 et CM-6.
A10: Test Case | D10: Cas de test
A11: Test | B11: TEST-CM-5(1) | D11: Test | E11: TEST-CM-5(1)
A12: Requirement ID | B12: CM-5(1) | D12: ID Exigence | E12: CM-5(1)
A13: Component | D13: Composant
A14: Requirement | D14: Exigence
A15: Contextual Design Description | D15: Description contextuelle du design
A16: Evidence Provided | D16: Preuve fournie
A17: Preparer Sign Off (Initials, Date) | D17: Signataire préparateur (Initiales, Date)
A18: Owner Sign Off (Initials, Date) | D18: Signataire propriétaire (Initiales, Date)
A19: Assessor Sign Off (Initials, Date) | D19: Signataire évaluateur (Initiales, Date)
A20: Status | B20: Not Started | D20: Statut | E20: Non commencé
A21: Comments | D21: Commentaires

Sheet CM-5-5
A1: Control CM-5(5) — Evidence Tracking | D1: Contrôle CM-5(5) — Suivi des preuves
A2: Control Information | D2: Informations du contrôle
A3: Control Identifier | B3: CM-5(5) | D3: Identifiant du contrôle | E3: CM-5(5)
A4: Family | B4: Access Restrictions for Change | D4: Famille | E4: Restrictions d’accès pour les changements
A5: Profile | B5: CCCS Medium / PBMM Moderate | D5: Profil | E5: CCCS Moyen / PBMM Modéré
A6: Primary Evidence Tool | D6: Outil de preuve principal
A7: Contributing Tools | D7: Outils contributeurs
A8: Control Description | B8: ACCESS RESTRICTIONS FOR CHANGE | LIMIT PRODUCTION / OPERATIONAL PRIVILEGES (a) The organization limits privileges to change information system components and system-related information within a production or operational environment; and (b) The organization reviews and re-evaluates privileges at least quarterly. | D8: Description du contrôle | E8: RESTRICTIONS D’ACCÈS POUR LES CHANGEMENTS | LIMITER LES PRIVILÈGES DANS UN ENVIRONNEMENT DE PRODUCTION/D’EXPLOITATION (a) L’organisation limite les privilèges de modification des composants du système d’information et de l’information liée au système dans un environnement de production ou d’exploitation; (b) L’organisation revoit et réévalue les privilèges au moins une fois par trimestre.
A9: Supplemental Guidance | B9: In many organizations, information systems support multiple core missions/business functions. Limiting privileges to change information system components with respect to operational systems is necessary because changes to a particular information system component may have far-reaching effects on mission/business processes supported by the system where the component resides. The complex, many-to-many relationships between systems and mission/business processes are in some cases, unknown to developers. Related control: AC-2. | D9: Directives supplémentaires | E9: Dans de nombreuses organisations, les systèmes d’information soutiennent de multiples fonctions opérationnelles et missions de base. Il est nécessaire de limiter les privilèges de modification des composants du système d’information en ce qui a trait aux systèmes opérationnels parce que les changements apportés à un composant particulier du système d’information peuvent avoir des répercussions profondes sur les processus opérationnels et de mission soutenus par le système dans lequel réside le composant. Les relations multiples et complexes entre les systèmes et les processus opérationnels et de mission sont parfois inconnues des développeurs. Contrôle connexe : AC-2.
A10: Test Case | D10: Cas de test
A11: Test | B11: TEST-CM-5(5) | D11: Test | E11: TEST-CM-5(5)
A12: Requirement ID | B12: CM-5(5) | D12: ID Exigence | E12: CM-5(5)
A13: Component | D13: Composant
A14: Requirement | D14: Exigence
A15: Contextual Design Description | D15: Description contextuelle du design
A16: Evidence Provided | D16: Preuve fournie
A17: Preparer Sign Off (Initials, Date) | D17: Signataire préparateur (Initiales, Date)
A18: Owner Sign Off (Initials, Date) | D18: Signataire propriétaire (Initiales, Date)
A19: Assessor Sign Off (Initials, Date) | D19: Signataire évaluateur (Initiales, Date)
A20: Status | B20: Not Started | D20: Statut | E20: Non commencé
A21: Comments | D21: Commentaires

Sheet CM-5-6
A1: Control CM-5(6) — Evidence Tracking | D1: Contrôle CM-5(6) — Suivi des preuves
A2: Control Information | D2: Informations du contrôle
A3: Control Identifier | B3: CM-5(6) | D3: Identifiant du contrôle | E3: CM-5(6)
A4: Family | B4: Access Restrictions for Change | D4: Famille | E4: Restrictions d’accès pour les changements
A5: Profile | B5: CCCS Medium / PBMM Moderate | D5: Profil | E5: CCCS Moyen / PBMM Modéré
A6: Primary Evidence Tool | D6: Outil de preuve principal
A7: Contributing Tools | D7: Outils contributeurs
A8: Control Description | B8: ACCESS RESTRICTIONS FOR CHANGE | LIMIT LIBRARY PRIVILEGES The organization limits privileges to change software resident within software libraries. | D8: Description du contrôle | E8: RESTRICTIONS D’ACCÈS POUR LES CHANGEMENTS | LIMITER LES PRIVILÈGES RELATIFS AUX BIBLIOTHÈQUES L’organisation limite les privilèges relatifs aux modifications du logiciel résidant dans les bibliothèques de logiciels.
A9: Supplemental Guidance | B9: Software libraries include privileged programs. Related control: AC-2. | D9: Directives supplémentaires | E9: Les bibliothèques de logiciels comprennent des programmes privilégiés. Contrôle connexe : AC-2.
A10: Test Case | D10: Cas de test
A11: Test | B11: TEST-CM-5(6) | D11: Test | E11: TEST-CM-5(6)
A12: Requirement ID | B12: CM-5(6) | D12: ID Exigence | E12: CM-5(6)
A13: Component | D13: Composant
A14: Requirement | D14: Exigence
A15: Contextual Design Description | D15: Description contextuelle du design
A16: Evidence Provided | D16: Preuve fournie
A17: Preparer Sign Off (Initials, Date) | D17: Signataire préparateur (Initiales, Date)
A18: Owner Sign Off (Initials, Date) | D18: Signataire propriétaire (Initiales, Date)
A19: Assessor Sign Off (Initials, Date) | D19: Signataire évaluateur (Initiales, Date)
A20: Status | B20: Not Started | D20: Statut | E20: Non commencé
A21: Comments | D21: Commentaires

Sheet CM-6
A1: Control CM-6 — Evidence Tracking | D1: Contrôle CM-6 — Suivi des preuves
A2: Control Information | D2: Informations du contrôle
A3: Control Identifier | B3: CM-6 | D3: Identifiant du contrôle | E3: CM-6
A4: Family | B4: Configuration Settings | D4: Famille | E4: Paramètres de configuration
A5: Profile | B5: CCCS Medium / PBMM Moderate | D5: Profil | E5: CCCS Moyen / PBMM Modéré
A6: Primary Evidence Tool | D6: Outil de preuve principal
A7: Contributing Tools | D7: Outils contributeurs
A8: Control Description | B8: (A) The organization establishes and documents configuration settings for information technology products employed within the information system using checklists from one or more of the following Center for Internet Security (CIS), National Institute of Standards and Technology (NIST), Defense Information Systems Agency (DISA) that reflect the most restrictive mode consistent with operational requirements. (B) The organization implements the configuration settings. (C) The organization identifies, documents, and approves any deviations from established configuration settings for any configurable infomation system components. (D) The organization monitors and controls changes to the configuration settings in accordance with organizational policies and procedures. | D8: Description du contrôle | E8: (A) L’organisation établit et documente les paramètres de configuration des produits de technologie de l’information utilisés dans le système d’information à l’aide de listes de vérification provenant d’un ou de plusieurs des éléments suivants : Center for Internet Security (CIS), National Institute of Standards and Technology (NIST), Defense Information Systems Agency (DISA), qui reflètent le mode le plus restrictif conformément aux exigences opérationnelles. (B) L’organisation met en œuvre les paramètres de configuration. (C) L’organisation identifie, documente et approuve tout écart par rapport aux paramètres de configuration établis pour les composants configurables du système d’information. (D) L’organisation surveille et contrôle les changements apportés aux paramètres de configuration conformément aux politiques et aux procédures de l’organisation.
A9: Supplemental Guidance | B9: Configuration settings are the set of parameters that can be changed in hardware, software, or firmware components of the information system that affect the security posture and/or functionality of the system. Information technology products for which security-related configuration settings can be defined include, for example, mainframe computers, servers (e.g., database, electronic mail, authentication, web, proxy, file, domain name), workstations, input/output devices (e.g., scanners, copiers, and printers), network components (e.g., firewalls, routers, gateways, voice and data switches, wireless access points, network appliances, sensors), operating systems, middleware, and applications. Security-related parameters are those parameters impacting the security state of information systems including the parameters required to satisfy other security control requirements. Security-related parameters include, for example: (i) registry settings; (ii) account, file, directory permission settings; and (iii) settings for functions, ports, protocols, services, and remote connections. Organizations establish organization-wide configuration settings and subsequently derive specific settings for information systems. The established settings become part of the systems configuration baselineCommon secure configurations (also referred to as security configuration checklists, lockdown and hardening guides, security reference guides, security technical implementation guides (STIG)) provide recognized, standardized, and established benchmarks that stipulate secure configuration settings for specific information technology platforms/products and instructions for configuring those information system components to meet operational requirements. Common secure configurations can be developed by a variety of organizations including, for example, information technology product developers, manufacturers, vendors, consortia, academia, industry, federal government organizations, and others in the public and private sectors. The Security Content Automation Protocol (SCAP) and the defined standards within the protocol (e.g., Common Configuration Enumeration) provide an effective method to uniquely identify, track, and control configuration settings. Related controls: AC-19, CM-2, CM-3, CM-7, SI-4. | D9: Directives supplémentaires | E9: Les paramètres de configuration sont l’ensemble de paramètres qui peuvent être modifiés dans les composants matériels, logiciels ou micrologiciels du système d’information et qui ont une incidence sur la posture de sécurité ou la fonctionnalité du système. Les produits de technologie de l’information pour lesquels les paramètres de configuration liés à la sécurité peuvent être définis comprennent, par exemple, les ordinateurs centraux, les serveurs (p. ex., base de données, courrier électronique, authentification, Web, mandataire, fichiers, noms de domaine), les postes de travail, les périphériques d’entrée et de sortie (p. ex., numériseurs, photocopieurs et imprimantes), les composants de réseau (p. ex., pare-feu, routeurs, passerelles, commutateurs de voix et de données, points d’accès sans fil, outils de réseau, capteurs), les systèmes d’exploitation, les intergiciels et les applications. Les paramètres liés à la sécurité sont les paramètres qui influent sur l’état de sécurité des systèmes d’information, y compris les paramètres requis pour satisfaire à d’autres exigences de contrôle de sécurité. Les paramètres liés à la sécurité comprennent, par exemple : (i) les paramètres des registres; (ii) les paramètres de comptes, de fichiers, d’autorisation de répertoires; (iii) les paramètres des fonctions, des ports, des protocoles, des services et des connexions à distance. Les organisations établissent les paramètres de configuration à l’échelle de l’organisation et en déduisent ensuite les paramètres particuliers pour les systèmes d’information. Les paramètres établis font partie des configurations de base des systèmes Les configurations sécurisées communes (aussi appelées listes de vérification de la configuration de sécurité, guides de verrouillage et de renforcement, guides de référence de sécurité, guides de mise en œuvre technique de la sécurité [STIG]) fournissent des repères reconnus, normalisés et établis qui stipulent les paramètres de configuration sécurisée pour des plateformes/produits de technologie de l’information particuliers et des instructions pour configurer ces composants de système d’information de manière à répondre aux exigences opérationnelles. Les configurations sécurisées communes peuvent être mises au point par diverses organisations, y compris, par exemple, les concepteurs de produits de technologie de l’information, les fabricants, les fournisseurs, les consortiums, le milieu universitaire, l’industrie, les organisations du gouvernement fédéral et d’autres intervenants des secteurs public et privé. Le protocole d’automatisation du contenu de sécurité SCAP (Security Content Automation Protocol) et les normes définies dans le protocole (p. ex., Common Configuration Enumeration) constituent une méthode efficace pour déterminer, suivre et contrôler de façon unique les paramètres de configuration. Contrôles connexes : AC-19, CM-2, CM-3, CM-7, SI-4.
A10: Test Case | D10: Cas de test
A11: Test | B11: TEST-CM-6 | D11: Test | E11: TEST-CM-6
A12: Requirement ID | B12: CM-6 | D12: ID Exigence | E12: CM-6
A13: Component | D13: Composant
A14: Requirement | D14: Exigence
A15: Contextual Design Description | D15: Description contextuelle du design
A16: Evidence Provided | D16: Preuve fournie
A17: Preparer Sign Off (Initials, Date) | D17: Signataire préparateur (Initiales, Date)
A18: Owner Sign Off (Initials, Date) | D18: Signataire propriétaire (Initiales, Date)
A19: Assessor Sign Off (Initials, Date) | D19: Signataire évaluateur (Initiales, Date)
A20: Status | B20: Not Started | D20: Statut | E20: Non commencé
A21: Comments | D21: Commentaires

Sheet CM-7
A1: Control CM-7 — Evidence Tracking | D1: Contrôle CM-7 — Suivi des preuves
A2: Control Information | D2: Informations du contrôle
A3: Control Identifier | B3: CM-7 | D3: Identifiant du contrôle | E3: CM-7
A4: Family | B4: Least Functionality | D4: Famille | E4: Moindre fonctionnalité
A5: Profile | B5: CCCS Medium / PBMM Moderate | D5: Profil | E5: CCCS Moyen / PBMM Modéré
A6: Primary Evidence Tool | D6: Outil de preuve principal
A7: Contributing Tools | D7: Outils contributeurs
A8: Control Description | B8: (A) The organization configures the information system to provide only essential capabilities. (B) The organization prohibits or restricts the use of identified functions, ports, protocols, and/or services following one or more standards from Center for Internet Security (CIS), National Institute of Standards and Technology (NIST), or Defense Information Systems Agency (DISA). | D8: Description du contrôle | E8: (A) L’organisation configure le système d’information pour n’offrir que les capacités essentielles. (B) L’organisation interdit ou restreint l’utilisation de fonctions, de ports, de protocoles et/ou de services identifiés en respectant une ou plusieurs normes du Center for Internet Security (CIS), du National Institute of Standards and Technology (NIST) ou de la Defense Information Systems Agency (DISA).
A9: Supplemental Guidance | B9: Information systems can provide a wide variety of functions and services. Some of the functions and services, provided by default, may not be necessary to support essential organizational operations (e.g., key missions, functions). Additionally, it is sometimes convenient to provide multiple services from single information system components, but doing so increases risk over limiting the services provided by any one component. Where feasible, organizations limit component functionality to a single function per device (e.g., email servers or web servers, but not both). Organizations review functions and services provided by information systems or individual components of information systems, to determine which functions and services are candidates for elimination (e.g., Voice over Internet Protocol (VoIP), Instant Messaging, auto-execute, and file sharing). Organizations consider disabling unused or unnecessary physical and logical ports/protocols (e.g., USB, FTP, IPv6, HTTP) on information systems to prevent unauthorized connection of devices, unauthorized transfer of information, or unauthorized tunnelling. Organizations can utilize network scanning tools, intrusion detection and prevention systems, and end-point protections such as firewalls and host-based intrusion detection systems to identify and prevent the use of prohibited functions, ports, protocols, and services. Related controls: AC-6, CM-2, RA-5, SA-5, SC-7 | D9: Directives supplémentaires | E9: Les systèmes d’information peuvent offrir une grande variété de fonctions et de services. Certaines fonctions et certains services, fournis par défaut, peuvent ne pas être nécessaires au soutien des opérations essentielles de l’organisation (p. ex., missions et fonctions clés). De plus, il est parfois pratique de fournir plusieurs services à partir de composants uniques du système d’information, mais cela augmente le risque de limiter les services fournis par un seul composant. Dans la mesure du possible, les organisations limitent la fonctionnalité des composants à une seule fonction par dispositif (p. ex., serveurs de courriel ou serveurs Web, mais pas les deux). Les organisations examinent les fonctions et les services fournis par les systèmes d’information ou les composants individuels des systèmes d’information afin de déterminer quelles fonctions et quels services peuvent être éliminés (p. ex., voix sur protocole Internet [VoIP], messagerie instantanée, auto-exécution et partage de fichiers). Les organisations envisagent de désactiver les ports/protocoles physiques et logiques inutilisés ou inutiles (p. ex., USB, FTP, IPv6, HTTP) sur les systèmes d’information afin de prévenir la connexion non autorisée d’appareils, le transfert non autorisé d’information ou la tunnellisation non autorisée. Les organisations peuvent utiliser des outils de balayage de réseau, des systèmes de détection et de prévention des intrusions et des mesures de protection d’extrémité comme des pare-feu et des systèmes de détection des intrusions basés sur l’hôte, pour identifier et prévenir l’utilisation de fonctions, de ports, de protocoles et de services interdits. Contrôles connexes : AC-6, CM-2, RA-5, SA-5, SC-7
A10: Test Case | D10: Cas de test
A11: Test | B11: TEST-CM-7 | D11: Test | E11: TEST-CM-7
A12: Requirement ID | B12: CM-7 | D12: ID Exigence | E12: CM-7
A13: Component | D13: Composant
A14: Requirement | D14: Exigence
A15: Contextual Design Description | D15: Description contextuelle du design
A16: Evidence Provided | D16: Preuve fournie
A17: Preparer Sign Off (Initials, Date) | D17: Signataire préparateur (Initiales, Date)
A18: Owner Sign Off (Initials, Date) | D18: Signataire propriétaire (Initiales, Date)
A19: Assessor Sign Off (Initials, Date) | D19: Signataire évaluateur (Initiales, Date)
A20: Status | B20: Not Started | D20: Statut | E20: Non commencé
A21: Comments | D21: Commentaires

Sheet CM-7-1
A1: Control CM-7(1) — Evidence Tracking | D1: Contrôle CM-7(1) — Suivi des preuves
A2: Control Information | D2: Informations du contrôle
A3: Control Identifier | B3: CM-7(1) | D3: Identifiant du contrôle | E3: CM-7(1)
A4: Family | B4: Least Functionality | D4: Famille | E4: Moindre fonctionnalité
A5: Profile | B5: CCCS Medium / PBMM Moderate | D5: Profil | E5: CCCS Moyen / PBMM Modéré
A6: Primary Evidence Tool | D6: Outil de preuve principal
A7: Contributing Tools | D7: Outils contributeurs
A8: Control Description | B8: LEAST FUNCTIONALITY | PERIODIC REVIEW The organization reviews the information system at least annually to identify unnecessary and/or non-secure functions, ports, protocols, and services; and The organization disables all functions, ports, protocols, and services within the information system deemed to be unnecessary and/or nonsecure. | D8: Description du contrôle | E8: MOINDRE FONCTIONNALITÉ | EXAMEN PÉRIODIQUE L’organisation revoit le système d’information au moins une fois par année afin de repérer les fonctions, les ports, les protocoles et les services inutiles ou non sécurisés; L’organisation désactive toutes les fonctions, tous les ports, tous les protocoles et tous les services du système d’information jugés inutiles ou non sécurisés.
A9: Supplemental Guidance | B9: The organization can either make a determination of the relative security of the function, port, protocol, and/or service or base the security decision on the assessment of other entities. Bluetooth, FTP, and peer-to-peer networking are examples of less than secure protocols. Related controls: AC-18, CM-7, IA-2. | D9: Directives supplémentaires | E9: L’organisation peut soit déterminer la sécurité relative de la fonction, du port, du protocole ou du service, soit baser sa décision en matière de sécurité sur l’évaluation d’autres entités. Bluetooth, FTP et l’interconnexion de réseaux d’égal à égal sont des exemples de protocoles moins sécurisés. Contrôles connexes : AC-18, CM-7, IA-2.
A10: Test Case | D10: Cas de test
A11: Test | B11: TEST-CM-7(1) | D11: Test | E11: TEST-CM-7(1)
A12: Requirement ID | B12: CM-7(1) | D12: ID Exigence | E12: CM-7(1)
A13: Component | D13: Composant
A14: Requirement | D14: Exigence
A15: Contextual Design Description | D15: Description contextuelle du design
A16: Evidence Provided | D16: Preuve fournie
A17: Preparer Sign Off (Initials, Date) | D17: Signataire préparateur (Initiales, Date)
A18: Owner Sign Off (Initials, Date) | D18: Signataire propriétaire (Initiales, Date)
A19: Assessor Sign Off (Initials, Date) | D19: Signataire évaluateur (Initiales, Date)
A20: Status | B20: Not Started | D20: Statut | E20: Non commencé
A21: Comments | D21: Commentaires

Sheet CP-7
A1: Control CP-7 — Evidence Tracking | D1: Contrôle CP-7 — Suivi des preuves
A2: Control Information | D2: Informations du contrôle
A3: Control Identifier | B3: CP-7 | D3: Identifiant du contrôle | E3: CP-7
A4: Family | B4: Alternate Processing Site | D4: Famille | E4: Site de traitement auxiliaire
A5: Profile | B5: CCCS Medium / PBMM Moderate | D5: Profil | E5: CCCS Moyen / PBMM Modéré
A6: Primary Evidence Tool | D6: Outil de preuve principal
A7: Contributing Tools | D7: Outils contributeurs
A8: Control Description | B8: (A) The organization establishes an alternate processing site including necessary agreements to permit the transfer and resumption of organization-defined information system operations for essential missions/business functions within organization-defined time period consistent with recovery time and recovery point objectives when the primary processing capabilities are unavailable. (B) The organization ensures that equipment and supplies required to transfer and resume operations are available at the alternate processing site or contracts are in place to support delivery to the site within the organization-defined time period for transfer/resumption. (C) The organization ensures that the alternate processing site provides information security safeguards equivalent to that of the primary site. | D8: Description du contrôle | E8: (A) L’organisation établit un site de traitement auxiliaire, y compris les ententes nécessaires pour permettre le transfert et la reprise des opérations du système d’information définies par l’organisation pour les missions et les fonctions opérationnelles essentielles à l’intérieur d’une période définie par l’organisation, conformément aux objectifs en matière de délais de reprise et de points de reprise lorsque les capacités de traitement principales ne sont pas disponibles. (B) L’organisation veille à ce que l’équipement et les fournitures nécessaires au transfert et à la reprise des activités soient disponibles au site de traitement auxiliaire, ou à ce que des contrats soient en place pour soutenir la livraison au site à l’intérieur de la période définie par l’organisation pour le transfert ou la reprise. (C) L’organisation veille à ce que le site de traitement auxiliaire offre des mesures de sécurité de l’information équivalentes à celles du site principal.
A9: Supplemental Guidance | B9: Alternate processing sites are sites that are geographically distinct from primary processing sites. An alternate processing site provides processing capability in the event that the primary processing site is not available. Items covered by alternate processing site agreements include, for example, environmental conditions at alternate sites, access rules, physical and environmental protection requirements, and coordination for the transfer/assignment of personnel. Requirements are specifically allocated to alternate processing sites that reflect the requirements in contingency plans to maintain essential missions/business functions despite disruption, compromise, or failure in organizational information systems. Related controls: CP-2, CP-6, CP-8, CP-9, CP-10, MA-6 | D9: Directives supplémentaires | E9: Les sites de traitement auxiliaires sont des sites qui sont géographiquement séparés des sites de traitement principaux. Un site de traitement auxiliaire offre une capacité de traitement lorsque le site de traitement principal n’est pas disponible. Les éléments couverts par les accords sur les sites de traitement auxiliaires comprennent, par exemple, les conditions environnementales aux sites auxiliaires, les règles d’accès, les exigences en matière de protection physique et environnementale, et la coordination pour le transfert ou l’attribution du personnel. Les exigences spécifiquement attribuées aux sites de traitement auxiliaires reflètent les exigences des plans d’urgence pour maintenir les fonctions opérationnelles et de mission essentielles malgré la perturbation, la compromission ou la défaillance des systèmes d’information organisationnels. Contrôles connexes : CP-2, CP-6, CP-8, CP-9, CP-10, MA-6
A10: Test Case | D10: Cas de test
A11: Test | B11: TEST-CP-7 | D11: Test | E11: TEST-CP-7
A12: Requirement ID | B12: CP-7 | D12: ID Exigence | E12: CP-7
A13: Component | D13: Composant
A14: Requirement | D14: Exigence
A15: Contextual Design Description | D15: Description contextuelle du design
A16: Evidence Provided | D16: Preuve fournie
A17: Preparer Sign Off (Initials, Date) | D17: Signataire préparateur (Initiales, Date)
A18: Owner Sign Off (Initials, Date) | D18: Signataire propriétaire (Initiales, Date)
A19: Assessor Sign Off (Initials, Date) | D19: Signataire évaluateur (Initiales, Date)
A20: Status | B20: Not Started | D20: Statut | E20: Non commencé
A21: Comments | D21: Commentaires

Sheet CP-7-4
A1: Control CP-7(4) — Evidence Tracking | D1: Contrôle CP-7(4) — Suivi des preuves
A2: Control Information | D2: Informations du contrôle
A3: Control Identifier | B3: CP-7(4) | D3: Identifiant du contrôle | E3: CP-7(4)
A4: Family | B4: Alternate Processing Site | D4: Famille | E4: Site de traitement auxiliaire
A5: Profile | B5: CCCS Medium / PBMM Moderate | D5: Profil | E5: CCCS Moyen / PBMM Modéré
A6: Primary Evidence Tool | D6: Outil de preuve principal
A7: Contributing Tools | D7: Outils contributeurs
A8: Control Description | B8: ALTERNATE PROCESSING SITE | PREPARATION FOR USE The organization prepares the alternate processing site so that the site is ready to be used as the operational site supporting essential missions and business functions. | D8: Description du contrôle | E8: SITE DE TRAITEMENT AUXILIAIRE | PRÉPARATION À L’UTILISATION L’organisation prépare le site de traitement auxiliaire de manière à ce que le site soit prêt à être utilisé comme site opérationnel prenant en charge les fonctions opérationnelles et les missions essentielles.
A9: Supplemental Guidance | B9: Site preparation includes, for example, establishing configuration settings for information system components at the alternate processing site consistent with the requirements for such settings at the primary site and ensuring that essential supplies and other logistical considerations are in place. Related controls: CM-2, CM-6. | D9: Directives supplémentaires | E9: La préparation du site comprend, par exemple, l’établissement des paramètres de configuration pour les composants du système d’information au site de traitement auxiliaire, conformément aux exigences pour ces paramètres au site principal, et l’assurance que les fournitures essentielles et autres considérations logistiques sont en place. Contrôles connexes : CM-2, CM-6.
A10: Test Case | D10: Cas de test
A11: Test | B11: TEST-CP-7(4) | D11: Test | E11: TEST-CP-7(4)
A12: Requirement ID | B12: CP-7(4) | D12: ID Exigence | E12: CP-7(4)
A13: Component | D13: Composant
A14: Requirement | D14: Exigence
A15: Contextual Design Description | D15: Description contextuelle du design
A16: Evidence Provided | D16: Preuve fournie
A17: Preparer Sign Off (Initials, Date) | D17: Signataire préparateur (Initiales, Date)
A18: Owner Sign Off (Initials, Date) | D18: Signataire propriétaire (Initiales, Date)
A19: Assessor Sign Off (Initials, Date) | D19: Signataire évaluateur (Initiales, Date)
A20: Status | B20: Not Started | D20: Statut | E20: Non commencé
A21: Comments | D21: Commentaires

Sheet CP-10
A1: Control CP-10 — Evidence Tracking | D1: Contrôle CP-10 — Suivi des preuves
A2: Control Information | D2: Informations du contrôle
A3: Control Identifier | B3: CP-10 | D3: Identifiant du contrôle | E3: CP-10
A4: Family | B4: Information System Recovery and Reconstitution | D4: Famille | E4: Reprise et reconstitution du système d’information
A5: Profile | B5: CCCS Medium / PBMM Moderate | D5: Profil | E5: CCCS Moyen / PBMM Modéré
A6: Primary Evidence Tool | D6: Outil de preuve principal
A7: Contributing Tools | D7: Outils contributeurs
A8: Control Description | B8: (A) The organization provides for the recovery and reconstitution of the information system to a known state after a disruption, compromise, or failure. | D8: Description du contrôle | E8: (A) L’organisation assure la reprise et la reconstitution du système d’information dans un état connu après une perturbation, une compromission ou une défaillance.
A9: Supplemental Guidance | B9: Recovery is executing information system contingency plan activities to restore organizational missions/business functions. Reconstitution takes place following recovery and includes activities for returning organizational information systems to fully operational states. Recovery and reconstitution operations reflect mission and business priorities, recovery point/time and reconstitution objectives, and established organizational metrics consistent with contingency plan requirements. Reconstitution includes the deactivation of any interim information system capabilities that may have been needed during recovery operations. Reconstitution also includes assessments of fully restored information system capabilities, reestablishment of continuous monitoring activities, potential information system reauthorizations, and activities to prepare the systems against future disruptions, compromises, or failures. Recovery/reconstitution capabilities employed by organizations can include both automated mechanisms and manual procedures. Related controls: CA-2, CA-6, CA-7, CP-2, CP-4, CP-6, CP-7, CP-9, SC-24 | D9: Directives supplémentaires | E9: La reprise consiste à exécuter les activités du plan d’urgence du système d’information pour restaurer les fonctions opérationnelles et de mission de l’organisation. La reconstitution a lieu après la reprise et comprend les activités permettant de remettre les systèmes d’information organisationnels à l’état pleinement opérationnel. Les opérations de reprise et de reconstitution reflètent les priorités opérationnelles et de mission, les objectifs en matière de délais, de points de reprise et de reconstitution, de même que les paramètres organisationnels établis conformément aux exigences du plan d’urgence. La reconstitution comprend la désactivation de toute capacité provisoire du système d’information ayant pu être nécessaire pendant les opérations de reprise. La reconstitution comprend également l’évaluation des capacités entièrement restaurées du système d’information, le rétablissement des activités de surveillance continue, les réautorisations possibles du système d’information et les activités visant à préparer les systèmes à faire face aux perturbations, compromissions ou défaillances futures. Les capacités de reprise et de reconstitution utilisées par les organisations peuvent comprendre des mécanismes automatisés et des procédures manuelles. Contrôles connexes : CA-2, CA-6, CA-7, CP-2, CP-4, CP-6, CP-7, CP-9, SC-24
A10: Test Case | D10: Cas de test
A11: Test | B11: TEST-CP-10 | D11: Test | E11: TEST-CP-10
A12: Requirement ID | B12: CP-10 | D12: ID Exigence | E12: CP-10
A13: Component | D13: Composant
A14: Requirement | D14: Exigence
A15: Contextual Design Description | D15: Description contextuelle du design
A16: Evidence Provided | D16: Preuve fournie
A17: Preparer Sign Off (Initials, Date) | D17: Signataire préparateur (Initiales, Date)
A18: Owner Sign Off (Initials, Date) | D18: Signataire propriétaire (Initiales, Date)
A19: Assessor Sign Off (Initials, Date) | D19: Signataire évaluateur (Initiales, Date)
A20: Status | B20: Not Started | D20: Statut | E20: Non commencé
A21: Comments | D21: Commentaires

Sheet CP-10-4
A1: Control CP-10(4) — Evidence Tracking | D1: Contrôle CP-10(4) — Suivi des preuves
A2: Control Information | D2: Informations du contrôle
A3: Control Identifier | B3: CP-10(4) | D3: Identifiant du contrôle | E3: CP-10(4)
A4: Family | B4: Information System Recovery and Reconstitution | D4: Famille | E4: Reprise et reconstitution du système d’information
A5: Profile | B5: CCCS Medium / PBMM Moderate | D5: Profil | E5: CCCS Moyen / PBMM Modéré
A6: Primary Evidence Tool | D6: Outil de preuve principal
A7: Contributing Tools | D7: Outils contributeurs
A8: Control Description | B8: INFORMATION SYSTEM RECOVERY AND RECONSTITUTION | RESTORE WITHIN TIME PERIOD The organization provides the capability to restore information system components within organization-defined restoration time-periods from configuration-controlled and integrity-protected information representing a known, operational state for the components. | D8: Description du contrôle | E8: REPRISE ET RECONSTITUTION DU SYSTÈME D’INFORMATION | RESTAURATION DANS LE DÉLAI IMPARTI L’organisation fournit la capacité de restaurer les composants du système d’information dans les délais de restauration définis par l’organisation à partir de l’information contrôlée par la configuration et protégée par l’intégrité qui représente un état de fonctionnement connu pour les composants.
A9: Supplemental Guidance | B9: Restoration of information system components includes, for example, re-imaging which restores components to known, operational states. Related control: CM-2. | D9: Directives supplémentaires | E9: La restauration des composants du système d’information comprend, par exemple, la reconfiguration permettant de restaurer les composants aux états de fonctionnement connus. Contrôle connexe : CM-2.
A10: Test Case | D10: Cas de test
A11: Test | B11: TEST-CP-10(4) | D11: Test | E11: TEST-CP-10(4)
A12: Requirement ID | B12: CP-10(4) | D12: ID Exigence | E12: CP-10(4)
A13: Component | D13: Composant
A14: Requirement | D14: Exigence
A15: Contextual Design Description | D15: Description contextuelle du design
A16: Evidence Provided | D16: Preuve fournie
A17: Preparer Sign Off (Initials, Date) | D17: Signataire préparateur (Initiales, Date)
A18: Owner Sign Off (Initials, Date) | D18: Signataire propriétaire (Initiales, Date)
A19: Assessor Sign Off (Initials, Date) | D19: Signataire évaluateur (Initiales, Date)
A20: Status | B20: Not Started | D20: Statut | E20: Non commencé
A21: Comments | D21: Commentaires

Sheet IA-2
A1: Control IA-2 — Evidence Tracking | D1: Contrôle IA-2 — Suivi des preuves
A2: Control Information | D2: Informations du contrôle
A3: Control Identifier | B3: IA-2 | D3: Identifiant du contrôle | E3: IA-2
A4: Family | B4: Identification and Authentication (Organizational Users) | D4: Famille | E4: Identification et authentification (utilisateurs au sein de l’organisation)
A5: Profile | B5: CCCS Medium / PBMM Moderate | D5: Profil | E5: CCCS Moyen / PBMM Modéré
A6: Primary Evidence Tool | D6: Outil de preuve principal
A7: Contributing Tools | D7: Outils contributeurs
A8: Control Description | B8: (A) The information system uniquely identifies and authenticates organizational users (or processes acting on behalf of organizational users). | D8: Description du contrôle | E8: (A) Le système d’information identifie et authentifie de façon unique les utilisateurs au sein de l’organisation (ou les processus agissant pour le compte d’utilisateurs au sein de l’organisation).
A9: Supplemental Guidance | B9: Organizational users include employees or individuals that organizations deem to have equivalent status of employees (e.g., contractors, guest researchers). This control applies to all accesses other than: (i) accesses that are explicitly identified and documented in AC-14; and (ii) accesses that occur through authorized use of group authenticators without individual authentication. Organizations may require unique identification of individuals in group accounts (e.g., shared privilege accounts) or for detailed accountability of individual activity. Organizations employ passwords, tokens, or biometrics to authenticate user identities, or in the case of multifactor authentication, or some combination thereof. Access to organizational information systems is defined as either local access or network access. Local access is any access to organizational information systems by users (or processes acting on behalf of users) where such access is obtained by direct connections without the use of networks. Network access is access to organizational information systems by users (or processes acting on behalf of users) where such access is obtained through network connections (i.e., nonlocal accesses). Remote access is a type of network access that involves communication through external networks (e.g., the Internet). Internal networks include local area networks and wide area networks. In addition, the use of encrypted VPNs for network connections between organization-controlled endpoints and non-organization controlled endpoints may be treated as internal networks from the perspective of protecting the confidentiality and integrity of information traversing the network. Multifactor authentication requires the use of two or more different factors to achieve authentication. The factors are defined as: (i) something you know (e.g., password, personal identification number [PIN]); (ii) something you have (e.g., cryptographic identification device, token); or (iii) something you are (e.g., biometric). Multifactor solutions that require devices separate from information systems gaining access include, for example, hardware tokens providing time-based or challenge-response authenticators and identity smart cards. In addition to identifying and authenticating users at the information system level (i.e., at logon), organizations also employ identification and authentication mechanisms at the application level, when necessary, to provide increased information security. Identification and authentication requirements for other than organizational users are described in IA-8. Related controls: AC-2, AC-3, AC-14, AC-17, AC-18, IA-4, IA-5, IA-8. | D9: Directives supplémentaires | E9: Les utilisateurs au sein de l’organisation comprennent les employés ou les personnes que les organisations jugent avoir un statut équivalent à celui des employés (p. ex., entrepreneurs, chercheurs invités). Ce contrôle s’applique à tous les accès autres que : (i) les accès qui sont explicitement identifiés et documentés dans AC-14; (ii) les accès qui ont lieu par l’entremise de l’utilisation autorisée d’authentifiants de groupe sans authentification individuelle. Les organisations peuvent avoir besoin d’une identification unique des personnes dans les comptes de groupe (p. ex., comptes à privilèges partagés) ou pour rendre compte en détail des activités individuelles. Les organisations utilisent des mots de passe, des jetons ou des données biométriques pour authentifier l’identité des utilisateurs, ou dans le cas d’une authentification multifactorielle, une combinaison quelconque de ces éléments. L’accès aux systèmes d’information organisationnels est défini comme un accès local ou un accès réseau. L’accès local est tout accès aux systèmes d’information organisationnels par des utilisateurs (ou des processus agissant pour le compte d’utilisateurs) lorsque cet accès est obtenu par des connexions directes sans l’utilisation de réseaux. L’accès au réseau est l’accès aux systèmes d’information organisationnels par les utilisateurs (ou les processus agissant pour le compte des utilisateurs) lorsque cet accès est obtenu au moyen de connexions réseau (c.-à-d., les accès non locaux). L’accès à distance est un type d’accès au réseau qui comprend la communication par l’entremise de réseaux externes (p. ex., Internet). Les réseaux internes comprennent les réseaux locaux et les réseaux étendus. En outre, les RPV chiffrés pour les connexions réseau entre les extrémités contrôlées par l’organisation et les extrémités non contrôlées par l’organisation peuvent être traités comme des réseaux internes du point de vue de la protection de la confidentialité et de l’intégrité de l’information traversant le réseau. L’authentification multifactorielle nécessite l’utilisation de deux facteurs différents ou plus pour l’authentification. Les facteurs sont définis comme suit : (i) quelque chose que vous connaissez (p. ex., mot de passe, numéro d’identification personnel [NIP]); (ii) quelque chose que vous avez (p. ex., dispositif d’identification cryptographique, jeton); ou (iii) quelque chose qui vous caractérise (p. ex., biométrie). Les solutions multifactorielles qui exigent des dispositifs séparés des systèmes d’information obtenant l’accès comprennent, par exemple, les jetons matériels qui fournissent des authentifiants à réponse temporelle ou à défi-réponse et des cartes d’identité à puce. En plus d’identifier et d’authentifier les utilisateurs au niveau du système d’information (c.-à-d. à l’ouverture de session), les organisations utilisent également des mécanismes d’identification et d’authentification au niveau de l’application, au besoin, pour assurer une sécurité accrue de l’information. Les exigences d’identification et d’authentification pour les utilisateurs autres que les utilisateurs au sein de l’organisation sont décrites dans IA-8. Contrôles connexes : AC-2, AC-3, AC-14, AC-17, AC-18, IA-4, IA-5, IA-8.
A10: Test Case | D10: Cas de test
A11: Test | B11: TEST-IA-2 | D11: Test | E11: TEST-IA-2
A12: Requirement ID | B12: IA-2 | D12: ID Exigence | E12: IA-2
A13: Component | D13: Composant
A14: Requirement | D14: Exigence
A15: Contextual Design Description | D15: Description contextuelle du design
A16: Evidence Provided | D16: Preuve fournie
A17: Preparer Sign Off (Initials, Date) | D17: Signataire préparateur (Initiales, Date)
A18: Owner Sign Off (Initials, Date) | D18: Signataire propriétaire (Initiales, Date)
A19: Assessor Sign Off (Initials, Date) | D19: Signataire évaluateur (Initiales, Date)
A20: Status | B20: Not Started | D20: Statut | E20: Non commencé
A21: Comments | D21: Commentaires

Sheet IA-2-1
A1: Control IA-2(1) — Evidence Tracking | D1: Contrôle IA-2(1) — Suivi des preuves
A2: Control Information | D2: Informations du contrôle
A3: Control Identifier | B3: IA-2(1) | D3: Identifiant du contrôle | E3: IA-2(1)
A4: Family | B4: Identification and Authentication (Organizational Users) | D4: Famille | E4: Identification et authentification (utilisateurs au sein de l’organisation)
A5: Profile | B5: CCCS Medium / PBMM Moderate | D5: Profil | E5: CCCS Moyen / PBMM Modéré
A6: Primary Evidence Tool | D6: Outil de preuve principal
A7: Contributing Tools | D7: Outils contributeurs
A8: Control Description | B8: IDENTIFICATION AND AUTHENTICATION | NETWORK ACCESS TO PRIVILEGED ACCOUNTS The information system implements multifactor authentication for network access to privileged accounts. | D8: Description du contrôle | E8: IDENTIFICATION ET AUTHENTIFICATION | ACCÈS RÉSEAU AUX COMPTES PRIVILÉGIÉS Le système d’information applique l’authentification multifactorielle pour l’accès réseau aux comptes privilégiés.
A9: Supplemental Guidance | B9: Related control: AC-6. | D9: Directives supplémentaires | E9: Contrôle connexe : AC-6.
A10: Test Case | D10: Cas de test
A11: Test | B11: TEST-IA-2(1) | D11: Test | E11: TEST-IA-2(1)
A12: Requirement ID | B12: IA-2(1) | D12: ID Exigence | E12: IA-2(1)
A13: Component | D13: Composant
A14: Requirement | D14: Exigence
A15: Contextual Design Description | D15: Description contextuelle du design
A16: Evidence Provided | D16: Preuve fournie
A17: Preparer Sign Off (Initials, Date) | D17: Signataire préparateur (Initiales, Date)
A18: Owner Sign Off (Initials, Date) | D18: Signataire propriétaire (Initiales, Date)
A19: Assessor Sign Off (Initials, Date) | D19: Signataire évaluateur (Initiales, Date)
A20: Status | B20: Not Started | D20: Statut | E20: Non commencé
A21: Comments | D21: Commentaires

Sheet IA-2-3
A1: Control IA-2(3) — Evidence Tracking | D1: Contrôle IA-2(3) — Suivi des preuves
A2: Control Information | D2: Informations du contrôle
A3: Control Identifier | B3: IA-2(3) | D3: Identifiant du contrôle | E3: IA-2(3)
A4: Family | B4: Identification and Authentication (Organizational Users) | D4: Famille | E4: Identification et authentification (utilisateurs au sein de l’organisation)
A5: Profile | B5: CCCS Medium / PBMM Moderate | D5: Profil | E5: CCCS Moyen / PBMM Modéré
A6: Primary Evidence Tool | D6: Outil de preuve principal
A7: Contributing Tools | D7: Outils contributeurs
A8: Control Description | B8: IDENTIFICATION AND AUTHENTICATION | LOCAL ACCESS TO PRIVILEGED ACCOUNTS The information system implements multifactor authentication for local access to privileged accounts. | D8: Description du contrôle | E8: IDENTIFICATION ET AUTHENTIFICATION | ACCÈS LOCAL AUX COMPTES PRIVILÉGIÉS Le système d’information applique l’authentification multifactorielle pour l’accès local aux comptes privilégiés.
A9: Supplemental Guidance | B9: Related control: AC-6. | D9: Directives supplémentaires | E9: Contrôle connexe : AC-6.
A10: Test Case | D10: Cas de test
A11: Test | B11: TEST-IA-2(3) | D11: Test | E11: TEST-IA-2(3)
A12: Requirement ID | B12: IA-2(3) | D12: ID Exigence | E12: IA-2(3)
A13: Component | D13: Composant
A14: Requirement | D14: Exigence
A15: Contextual Design Description | D15: Description contextuelle du design
A16: Evidence Provided | D16: Preuve fournie
A17: Preparer Sign Off (Initials, Date) | D17: Signataire préparateur (Initiales, Date)
A18: Owner Sign Off (Initials, Date) | D18: Signataire propriétaire (Initiales, Date)
A19: Assessor Sign Off (Initials, Date) | D19: Signataire évaluateur (Initiales, Date)
A20: Status | B20: Not Started | D20: Statut | E20: Non commencé
A21: Comments | D21: Commentaires

Sheet IA-2-6
A1: Control IA-2(6) — Evidence Tracking | D1: Contrôle IA-2(6) — Suivi des preuves
A2: Control Information | D2: Informations du contrôle
A3: Control Identifier | B3: IA-2(6) | D3: Identifiant du contrôle | E3: IA-2(6)
A4: Family | B4: Identification and Authentication (Organizational Users) | D4: Famille | E4: Identification et authentification (utilisateurs au sein de l’organisation)
A5: Profile | B5: CCCS Medium / PBMM Moderate | D5: Profil | E5: CCCS Moyen / PBMM Modéré
A6: Primary Evidence Tool | D6: Outil de preuve principal
A7: Contributing Tools | D7: Outils contributeurs
A8: Control Description | B8: IDENTIFICATION AND AUTHENTICATION | NETWORK ACCESS TO PRIVILEGED ACCOUNTS - SEPARATE DEVICE The information system implements multifactor authentication for network access to privileged accounts such that one of the factors is provided by a device separate from the system gaining access and the device meets the requirements identified in CCCS ITSP.30.031. | D8: Description du contrôle | E8: IDENTIFICATION ET AUTHENTIFICATION | ACCÈS RÉSEAU AUX COMPTES PRIVILÉGIÉS - DISPOSITIF SÉPARÉ Le système d’information applique l’authentification multifactorielle pour l’accès réseau aux comptes privilégiés, de sorte que l’un des facteurs est fourni par un dispositif séparé du système obtenant l’accès et que le dispositif répond aux exigences énoncées dans le document ITSP.30.031 du CCC.
A9: Supplemental Guidance | B9: Related control: AC-6. | D9: Directives supplémentaires | E9: Contrôle connexe : AC-6.
A10: Test Case | D10: Cas de test
A11: Test | B11: TEST-IA-2(6) | D11: Test | E11: TEST-IA-2(6)
A12: Requirement ID | B12: IA-2(6) | D12: ID Exigence | E12: IA-2(6)
A13: Component | D13: Composant
A14: Requirement | D14: Exigence
A15: Contextual Design Description | D15: Description contextuelle du design
A16: Evidence Provided | D16: Preuve fournie
A17: Preparer Sign Off (Initials, Date) | D17: Signataire préparateur (Initiales, Date)
A18: Owner Sign Off (Initials, Date) | D18: Signataire propriétaire (Initiales, Date)
A19: Assessor Sign Off (Initials, Date) | D19: Signataire évaluateur (Initiales, Date)
A20: Status | B20: Not Started | D20: Statut | E20: Non commencé
A21: Comments | D21: Commentaires

Sheet IA-2-8
A1: Control IA-2(8) — Evidence Tracking | D1: Contrôle IA-2(8) — Suivi des preuves
A2: Control Information | D2: Informations du contrôle
A3: Control Identifier | B3: IA-2(8) | D3: Identifiant du contrôle | E3: IA-2(8)
A4: Family | B4: Identification and Authentication (Organizational Users) | D4: Famille | E4: Identification et authentification (utilisateurs au sein de l’organisation)
A5: Profile | B5: CCCS Medium / PBMM Moderate | D5: Profil | E5: CCCS Moyen / PBMM Modéré
A6: Primary Evidence Tool | D6: Outil de preuve principal
A7: Contributing Tools | D7: Outils contributeurs
A8: Control Description | B8: IDENTIFICATION AND AUTHENTICATION | NETWORK ACCESS TO PRIVILEGED ACCOUNTS - REPLAY RESISTANT The information system implements replay-resistant authentication mechanisms for network access to privileged accounts. | D8: Description du contrôle | E8: IDENTIFICATION ET AUTHENTIFICATION | ACCÈS RÉSEAU AUX COMPTES PRIVILÉGIÉS - RÉSISTANT À LA RÉINSERTION Le système d’information applique des mécanismes d’authentification à l’épreuve des réinsertions pour l’accès réseau aux comptes privilégiés.
A9: Supplemental Guidance | B9: Authentication processes resist replay attacks if it is impractical to achieve successful authentications by replaying previous authentication messages. Replay-resistant techniques include, for example, protocols that use nonces or challenges such as Transport Layer Security (TLS) and time synchronous or challenge-response one-time authenticators. | D9: Directives supplémentaires | E9: Les processus d’authentification résistent aux attaques par réinsertion s’il n’est pas pratique d’obtenir des authentifications réussies en réinsérant des messages d’authentification antérieurs. Les techniques résistantes à la réinsertion comprennent, par exemple, des protocoles qui utilisent des nonces ou des défis comme la sécurité de la couche de transport (TLS pour Transport Layer Security) et des authentifiants ponctuels synchrones ou à défi-réponse.
A10: Test Case | D10: Cas de test
A11: Test | B11: TEST-IA-2(8) | D11: Test | E11: TEST-IA-2(8)
A12: Requirement ID | B12: IA-2(8) | D12: ID Exigence | E12: IA-2(8)
A13: Component | D13: Composant
A14: Requirement | D14: Exigence
A15: Contextual Design Description | D15: Description contextuelle du design
A16: Evidence Provided | D16: Preuve fournie
A17: Preparer Sign Off (Initials, Date) | D17: Signataire préparateur (Initiales, Date)
A18: Owner Sign Off (Initials, Date) | D18: Signataire propriétaire (Initiales, Date)
A19: Assessor Sign Off (Initials, Date) | D19: Signataire évaluateur (Initiales, Date)
A20: Status | B20: Not Started | D20: Statut | E20: Non commencé
A21: Comments | D21: Commentaires

Sheet IA-2-11
A1: Control IA-2(11) — Evidence Tracking | D1: Contrôle IA-2(11) — Suivi des preuves
A2: Control Information | D2: Informations du contrôle
A3: Control Identifier | B3: IA-2(11) | D3: Identifiant du contrôle | E3: IA-2(11)
A4: Family | B4: Identification and Authentication (Organizational Users) | D4: Famille | E4: Identification et authentification (utilisateurs au sein de l’organisation)
A5: Profile | B5: CCCS Medium / PBMM Moderate | D5: Profil | E5: CCCS Moyen / PBMM Modéré
A6: Primary Evidence Tool | D6: Outil de preuve principal
A7: Contributing Tools | D7: Outils contributeurs
A8: Control Description | B8: IDENTIFICATION AND AUTHENTICATION | REMOTE ACCESS - SEPARATE DEVICE The information system implements multifactor authentication for remote access to privileged and non-privileged accounts such that one of the factors is provided by a device separate from the system being accessed and the device meets the requirements in CCCS's ITSP.30.031. | D8: Description du contrôle | E8: IDENTIFICATION ET AUTHENTIFICATION | ACCÈS À DISTANCE - DISPOSITIF SÉPARÉ Le système d’information applique l’authentification multifactorielle pour l’accès à distance aux comptes privilégiés et non privilégiés, de sorte que l’un des facteurs est fourni par un dispositif séparé du système auquel on accède et que le dispositif répond aux exigences de l’ITSP.30.031 du CCC.
A9: Supplemental Guidance | B9: For remote access to privileged/non-privileged accounts, the purpose of requiring a device that is separate from the information system being accessed as one of the factors during multifactor authentication is to reduce the likelihood of compromising authentication credentials stored on the system. For example, adversaries deploying malicious code on organizational information systems can potentially compromise such credentials resident on the system and subsequently impersonate authorized users. Related control: AC-6. | D9: Directives supplémentaires | E9: Dans le cas de l’accès à distance à des comptes privilégiés ou non privilégiés, l’exigence d’un dispositif séparé du système d’information auquel on accède en tant qu’un des facteurs d’authentification multifactorielle a pour but de réduire la probabilité de compromission des justificatifs d’authentification stockés dans le système. Par exemple, les adversaires qui déploient des codes malveillants sur les systèmes d’information de l’organisation peuvent potentiellement compromettre les justificatifs d’identité qui résident sur le système et se faire passer pour des utilisateurs autorisés. Contrôle connexe : AC-6.
A10: Test Case | D10: Cas de test
A11: Test | B11: TEST-IA-2(11) | D11: Test | E11: TEST-IA-2(11)
A12: Requirement ID | B12: IA-2(11) | D12: ID Exigence | E12: IA-2(11)
A13: Component | D13: Composant
A14: Requirement | D14: Exigence
A15: Contextual Design Description | D15: Description contextuelle du design
A16: Evidence Provided | D16: Preuve fournie
A17: Preparer Sign Off (Initials, Date) | D17: Signataire préparateur (Initiales, Date)
A18: Owner Sign Off (Initials, Date) | D18: Signataire propriétaire (Initiales, Date)
A19: Assessor Sign Off (Initials, Date) | D19: Signataire évaluateur (Initiales, Date)
A20: Status | B20: Not Started | D20: Statut | E20: Non commencé
A21: Comments | D21: Commentaires

Sheet IA-4
A1: Control IA-4 — Evidence Tracking | D1: Contrôle IA-4 — Suivi des preuves
A2: Control Information | D2: Informations du contrôle
A3: Control Identifier | B3: IA-4 | D3: Identifiant du contrôle | E3: IA-4
A4: Family | B4: Identifier Management | D4: Famille | E4: Gestion des identifiants
A5: Profile | B5: CCCS Medium / PBMM Moderate | D5: Profil | E5: CCCS Moyen / PBMM Modéré
A6: Primary Evidence Tool | D6: Outil de preuve principal
A7: Contributing Tools | D7: Outils contributeurs
A8: Control Description | B8: (A) The organization manages information system identifiers by receiving authorization from organization-defined personnel or roles to assign an individual, group, role, or device identifier. (B) The organization manages information system identifiers by selecting an identifier that identifies an individual, group, role, or device. (C) The organization manages information system identifiers by assigning the identifier to the intended individual, group, role, or device. (D) The organization manages information system identifiers by preventing reuse of identifiers for at least two years. (E) The organization manages information system identifiers by disabling the identifier after 90 days for user identifiers. | D8: Description du contrôle | E8: (A) L’organisation gère les identifiants du système d’information en recevant, de la part du personnel ou des rôles définis par l’organisation, l’autorisation d’attribuer un identifiant de personne, de groupe, de rôle ou de dispositif. (B) L’organisation gère les identifiants du système d’information en sélectionnant un identifiant qui identifie une personne, un groupe, un rôle ou un dispositif. (C) L’organisation gère les identifiants du système d’information en attribuant l’identifiant à la personne, au groupe, au rôle ou au dispositif visés. (D) L’organisation gère les identifiants du système d’information en empêchant la réutilisation des identifiants pendant au moins deux ans. (E) L’organisation gère les identifiants du système d’information en désactivant l’identifiant après 90 jours pour les identifiants d’utilisateur.
A9: Supplemental Guidance | B9: Common device identifiers include, for example, MAC, IP addresses, or device-unique token identifiers. Management of individual identifiers is not applicable to shared information system accounts (e.g., guest and anonymous accounts). Typically, individual identifiers are the user names of the information system accounts assigned to those individuals. In such instances, the account management activities of AC-2 use account names provided by IA-4. This control also addresses individual identifiers not necessarily associated with information system accounts (e.g., identifiers used in physical security control databases accessed by badge reader systems for access to information systems). Preventing reuse of identifiers implies preventing the assignment of previously used individual, group, role, or device identifiers to different individuals, groups, roles, or devices. Related controls: AC-2, IA-2, IA-3, IA-5, IA-8, SC-37 | D9: Directives supplémentaires | E9: Les identifiants de dispositifs courants comprennent, par exemple, les adresses MAC, les adresses IP ou les identifiants à jeton unique au dispositif. La gestion des identifiants individuels ne s’applique pas aux comptes partagés du système d’information (p. ex., comptes d’invités et comptes anonymes). En général, les identifiants individuels sont les noms d’utilisateurs des comptes du système d’information attribués à ces personnes. Dans de tels cas, les activités de gestion des comptes de AC-2 utilisent les noms de compte fournis par IA-4. Ce contrôle porte également sur les identifiants individuels qui ne sont pas nécessairement associés à des comptes du système d’information (p. ex., les identifiants utilisés dans les bases de données de contrôle de la sécurité physique accessibles par les systèmes de lecteur d’insignes pour l’accès aux systèmes d’information). La prévention de la réutilisation des identifiants consiste à empêcher l’attribution d’identifiants de personnes, de groupes, de rôles ou de dispositifs utilisés antérieurement à des personnes, des groupes, des rôles ou des dispositifs différents. Contrôles connexes : AC-2, IA-2, IA-3, IA-5, IA-8, SC-37
A10: Test Case | D10: Cas de test
A11: Test | B11: TEST-IA-4 | D11: Test | E11: TEST-IA-4
A12: Requirement ID | B12: IA-4 | D12: ID Exigence | E12: IA-4
A13: Component | D13: Composant
A14: Requirement | D14: Exigence
A15: Contextual Design Description | D15: Description contextuelle du design
A16: Evidence Provided | D16: Preuve fournie
A17: Preparer Sign Off (Initials, Date) | D17: Signataire préparateur (Initiales, Date)
A18: Owner Sign Off (Initials, Date) | D18: Signataire propriétaire (Initiales, Date)
A19: Assessor Sign Off (Initials, Date) | D19: Signataire évaluateur (Initiales, Date)
A20: Status | B20: Not Started | D20: Statut | E20: Non commencé
A21: Comments | D21: Commentaires

Sheet IA-5
A1: Control IA-5 — Evidence Tracking | D1: Contrôle IA-5 — Suivi des preuves
A2: Control Information | D2: Informations du contrôle
A3: Control Identifier | B3: IA-5 | D3: Identifiant du contrôle | E3: IA-5
A4: Family | B4: Authenticator Management | D4: Famille | E4: Gestion des authentifiants
A5: Profile | B5: CCCS Medium / PBMM Moderate | D5: Profil | E5: CCCS Moyen / PBMM Modéré
A6: Primary Evidence Tool | D6: Outil de preuve principal
A7: Contributing Tools | D7: Outils contributeurs
A8: Control Description | B8: (A) The organization manages information system authenticators by verifying, as part of the initial authenticator distribution, the identity of the individual, group, role, or device receiving the authenticator. (B) The organization manages information system authenticators by establishing initial authenticator content for authenticators defined by the organization. (C) The organization manages information system authenticators by ensuring that authenticators have sufficient strength of mechanism for their intended use. (D) The organization manages information system authenticators by establishing and implementing administrative procedures for initial authenticator distribution, for lost/compromised or damaged authenticators, and for revoking authenticators. (E) The organization manages information system authenticators by changing the default content of authenticators prior to information system installation. (F) The organization manages information system authenticators by establishing minimum and maximum lifetime restrictions and reuse conditions for authenticators. (G) The organization manages information system authenticators by changing/refreshing authenticators in accordance with CCCS’s ITSP.30.031. (H) The organization manages information system authenticators by protecting authenticator content from unauthorized disclosure and modification. (I) The organization manages information system authenticators by requiring individuals to take, and having devices implement, specific security safeguards to protect authenticators. (J) The organization manages information system authenticators by changing authenticators for group/role accounts when membership to those accounts changes. | D8: Description du contrôle | E8: (A) L’organisation gère les authentifiants du système d’information en vérifiant, dans le cadre de la distribution initiale des authentifiants, l’identité de la personne, du groupe, du rôle ou du dispositif qui reçoit l’authentifiant. (B) L’organisation gère les authentifiants du système d’information en établissant le contenu initial de l’authentifiant pour les authentifiants définis par l’organisation. (C) L’organisation gère les authentifiants du système d’information en s’assurant que les authentifiants disposent d’un mécanisme suffisamment robuste pour leur utilisation prévue. (D) L’organisation gère les authentifiants du système d’information en établissant et en mettant en œuvre des procédures administratives pour la distribution initiale des authentifiants, pour les authentifiants perdus/compromis ou endommagés, et pour la révocation des authentifiants. (E) L’organisation gère les authentifiants du système d’information en modifiant le contenu par défaut des authentifiants avant l’installation du système d’information. (F) L’organisation gère les authentifiants du système d’information en établissant des restrictions de durée de vie minimale et maximale et des conditions de réutilisation pour les authentifiants. (G) L’organisation gère les authentifiants du système d’information en changeant/actualisant les authentifiants conformément à l’ITSP.30.031 du CCC. (H) L’organisation gère les authentifiants du système d’information en protégeant le contenu de l’authentifiant contre la divulgation et la modification non autorisées. (I) L’organisation gère les authentifiants du système d’information en exigeant des personnes qu’elles adoptent des mesures de sécurité particulières pour protéger les authentifiants et en s’assurant que les dispositifs les mettent en œuvre. (J) L’organisation gère les authentifiants du système d’information en changeant les authentifiants pour les comptes de groupe/rôle lorsque l’adhésion à ces comptes change.
A9: Supplemental Guidance | B9: Individual authenticators include, for example, passwords, tokens, biometrics, Public Key Infrastructure (PKI) certificates, and key cards. Initial authenticator content is the actual content (e.g., the initial password) as opposed to requirements about authenticator content (e.g., minimum password length). In many cases, developers ship information system components with factory default authentication credentials to allow for initial installation and configuration. Default authentication credentials are often well known, easily discoverable, and present a significant security risk. The requirement to protect individual authenticators may be implemented via control PL-4 or PS-6 for authenticators in the possession of individuals and by controls AC-3, AC-6, and SC-28 for authenticators stored within organizational information systems (e.g., passwords stored in hashed or encrypted formats, files containing encrypted or hashed passwords accessible with administrator privileges). Information systems support individual authenticator management by organization-defined settings and restrictions for various authenticator characteristics including, for example, minimum password length, password composition, validation time window for time synchronous one-time tokens, and number of allowed rejections during the verification stage of biometric authentication. Specific actions that can be taken to safeguard authenticators include, for example, maintaining possession of individual authenticators, not loaning or sharing individual authenticators with others, and reporting lost, stolen, or compromised authenticators immediately. Authenticator management includes issuing and revoking, when no longer needed, authenticators for temporary access such as that required for remote maintenance. Device authenticators include, for example, certificates and passwords. Related controls: AC-2, AC-3, AC-6, CM-6, IA-2, IA-4, IA-8, PL-4, PS-5, PS-6, SC-12, SC-13, SC-17, SC-28 | D9: Directives supplémentaires | E9: Les authentifiants individuels comprennent, par exemple, les mots de passe, les jetons, la biométrie, les certificats d’infrastructure à clé publique (ICP) et les cartes-clés. Le contenu initial de l’authentifiant est le contenu réel (p. ex., le mot de passe initial) par opposition aux exigences relatives au contenu de l’authentifiant (p. ex., longueur minimale du mot de passe). Dans de nombreux cas, les développeurs livrent les composants du système d’information avec des justificatifs d’authentification par défaut pour permettre l’installation et la configuration initiales. Les justificatifs d’authentification par défaut sont souvent bien connus, faciles à découvrir, et présentent un risque important pour la sécurité. L’exigence de protection des authentifiants individuels peut être mise en œuvre au moyen du contrôle PL-4 ou PS-6 pour les authentifiants de personnes et par les contrôles AC-3, AC-6, et SC-28 pour les authentifiants stockés dans les systèmes d’information de l’organisation (p. ex., mots de passe stockés dans des formats hachés ou chiffrés, fichiers contenant des mots de passe chiffrés ou hachés accessibles avec des privilèges d’administrateur). Les systèmes d’information prennent en charge la gestion des authentifiants individuels selon les paramètres et les restrictions définis par l’organisation pour diverses caractéristiques des authentifiants, y compris, par exemple, la longueur minimale du mot de passe, la composition du mot de passe, la période de validation pour les jetons ponctuels synchrones et le nombre de rejets permis à l’étape de vérification de l’authentification biométrique. Les mesures particulières qui peuvent être prises pour protéger les authentifiants comprennent, par exemple, demeurer en possession des authentifiants individuels, éviter de prêter ou de partager des authentifiants individuels avec d’autres, et déclarer immédiatement les authentifiants perdus, volés ou compromis. La gestion des authentifiants comprend la délivrance d’authentifiants pour l’accès temporaire, comme ceux requis pour la maintenance à distance, et leur révocation lorsqu’ils ne sont plus nécessaires. Les authentifiants de dispositifs comprennent, par exemple, les certificats et les mots de passe. Contrôles connexes : AC-2, AC-3, AC-6, CM-6, IA-2, IA-4, IA-8, PL-4, PS-5, PS-6, SC-12, SC-13, SC-17, SC-28
A10: Test Case | D10: Cas de test
A11: Test | B11: TEST-IA-5 | D11: Test | E11: TEST-IA-5
A12: Requirement ID | B12: IA-5 | D12: ID Exigence | E12: IA-5
A13: Component | D13: Composant
A14: Requirement | D14: Exigence
A15: Contextual Design Description | D15: Description contextuelle du design
A16: Evidence Provided | D16: Preuve fournie
A17: Preparer Sign Off (Initials, Date) | D17: Signataire préparateur (Initiales, Date)
A18: Owner Sign Off (Initials, Date) | D18: Signataire propriétaire (Initiales, Date)
A19: Assessor Sign Off (Initials, Date) | D19: Signataire évaluateur (Initiales, Date)
A20: Status | B20: Not Started | D20: Statut | E20: Non commencé
A21: Comments | D21: Commentaires

Sheet IA-5-1
A1: Control IA-5(1) — Evidence Tracking | D1: Contrôle IA-5(1) — Suivi des preuves
A2: Control Information | D2: Informations du contrôle
A3: Control Identifier | B3: IA-5(1) | D3: Identifiant du contrôle | E3: IA-5(1)
A4: Family | B4: Authenticator Management | D4: Famille | E4: Gestion des authentifiants
A5: Profile | B5: CCCS Medium / PBMM Moderate | D5: Profil | E5: CCCS Moyen / PBMM Modéré
A6: Primary Evidence Tool | D6: Outil de preuve principal
A7: Contributing Tools | D7: Outils contributeurs
A8: Control Description | B8: AUTHENTICATOR MANAGEMENT | PASSWORD-BASED AUTHENTICATION (a) The information system, for password-based authentication, enforces minimum password complexity of case sensitive, minimum of eight characters, and at least one each of upper-case letters, lower-case letters, numbers, and special characters; (b) The information system, for password-based authentication, enforces that at least one of the characters are changed when new passwords are created; (c) The information system, for password-based authentication, stores and transmits only cryptographically-protected passwords; (d) The information system, for password-based authentication, enforces password minimum and maximum lifetime restrictions of one-day minimum, sixty-day maximum; (e) The information system, for password-based authentication prohibits password reuse for 24 generations; and (f) The information system, for password-based authentication allows the use of a temporary password for system logons with an immediate change to a permanent password. | D8: Description du contrôle | E8: GESTION DES AUTHENTIFIANTS | AUTHENTIFICATION PAR MOT DE PASSE (a) Le système d’information, pour l’authentification par mot de passe, exige une complexité minimum du mot de passe qui doit être sensible à la casse, comporter au moins huit caractères, et au moins une lettre majuscule, une lettre minuscule, un chiffre et un caractère spécial; (b) Le système d’information, pour l’authentification par mot de passe, exige qu’au moins l’un des caractères soit modifié lorsque de nouveaux mots de passe sont créés; (c) Le système d’information, pour l’authentification par mot de passe, ne mémorise et transmet que les mots de passe protégés par cryptographie; (d) Le système d’information, pour l’authentification par mot de passe, applique des restrictions de durée de vie minimale et maximale d’un jour et de soixante jours respectivement; (e) Le système d’information, pour l’authentification par mot de passe, interdit la réutilisation du mot de passe pour 24 générations; (f) Le système d’information, pour l’authentification par mot de passe, permet l’utilisation d’un mot de passe temporaire pour les connexions au système suivies du remplacement immédiat par un mot de passe permanent.
A9: Supplemental Guidance | B9: This control enhancement applies to single-factor authentication of individuals using passwords as individual or group authenticators, and in a similar manner, when passwords are part of multifactor authenticators. This control enhancement does not apply when passwords are used to unlock hardware authenticators (e.g., Personal Identity Verification cards). The implementation of such password mechanisms may not meet all of the requirements in the enhancement. Cryptographically-protected passwords include, for example, encrypted versions of passwords and one-way cryptographic hashes of passwords. The number of changed characters refers to the number of changes required with respect to the total number of positions in the current password. Password lifetime restrictions do not apply to temporary passwords. To mitigate certain brute force attacks against passwords, organizations may also consider salting passwords. Related control: IA-6. | D9: Directives supplémentaires | E9: Cette amélioration du contrôle s’applique à l’authentification à facteur unique des personnes qui utilisent des mots de passe comme authentifiants individuels ou collectifs, et de la même manière, lorsque les mots de passe font partie d’authentifiants multifactoriels. Cette amélioration du contrôle ne s’applique pas lorsque des mots de passe sont utilisés pour déverrouiller des authentifiants matériels (p. ex., cartes de vérification de l’identité personnelle). La mise en œuvre de ces mécanismes liés aux mots de passe pourrait ne pas répondre à toutes les exigences de l’amélioration. Les mots de passe protégés par cryptographie comprennent, par exemple, les versions chiffrées de mots de passe et les hachages cryptographiques unidirectionnels de mots de passe. Le nombre de caractères modifiés correspond au nombre de changements requis par rapport au nombre total de positions dans le mot de passe actuel. Les restrictions relatives à la durée de vie du mot de passe ne s’appliquent pas aux mots de passe temporaires. Pour atténuer certaines attaques par force brute contre les mots de passe, les organisations peuvent aussi envisager le salage des mots de passe. Contrôle connexe : IA-6.
A10: Test Case | D10: Cas de test
A11: Test | B11: TEST-IA-5(1) | D11: Test | E11: TEST-IA-5(1)
A12: Requirement ID | B12: IA-5(1) | D12: ID Exigence | E12: IA-5(1)
A13: Component | D13: Composant
A14: Requirement | D14: Exigence
A15: Contextual Design Description | D15: Description contextuelle du design
A16: Evidence Provided | D16: Preuve fournie
A17: Preparer Sign Off (Initials, Date) | D17: Signataire préparateur (Initiales, Date)
A18: Owner Sign Off (Initials, Date) | D18: Signataire propriétaire (Initiales, Date)
A19: Assessor Sign Off (Initials, Date) | D19: Signataire évaluateur (Initiales, Date)
A20: Status | B20: Not Started | D20: Statut | E20: Non commencé
A21: Comments | D21: Commentaires

Sheet IA-5-2
A1: Control IA-5(2) — Evidence Tracking | D1: Contrôle IA-5(2) — Suivi des preuves
A2: Control Information | D2: Informations du contrôle
A3: Control Identifier | B3: IA-5(2) | D3: Identifiant du contrôle | E3: IA-5(2)
A4: Family | B4: Authenticator Management | D4: Famille | E4: Gestion des authentifiants
A5: Profile | B5: CCCS Medium / PBMM Moderate | D5: Profil | E5: CCCS Moyen / PBMM Modéré
A6: Primary Evidence Tool | D6: Outil de preuve principal
A7: Contributing Tools | D7: Outils contributeurs
A8: Control Description | B8: AUTHENTICATOR MANAGEMENT | PKI-BASED AUTHENTICATION (a) The information system, for PKI-based authentication, validates certifications by constructing and verifying a certification path to an accepted trust anchor including checking certificate status information; (b) The information system, for PKI-based authentication, enforces authorized access to the corresponding private key; (c) The information system, for PKI-based authentication, maps the authenticated identity to the account of the individual or group; and (d) The information system, for PKI-based authentication, implements a local cache of revocation data to support path discovery and validation in case of inability to access revocation information via the network. | D8: Description du contrôle | E8: GESTION DES AUTHENTIFIANTS | AUTHENTIFICATION BASÉE SUR L’ICP (a) Le système d’information, pour l’authentification basée sur l’ICP, valide les certifications en établissant et vérifiant un chemin de certification vers un ancrage de confiance accepté, et en vérifiant l’information relative au statut du certificat; (b) Le système d’information, pour l’authentification basée sur l’ICP, applique l’accès autorisé à la clé privée correspondante; (c) Le système d’information, pour l’authentification basée sur l’ICP, établit la correspondance entre l’identifié authentifiée et le compte de la personne ou du groupe; (d) Le système d’information, pour l’authentification basée sur l’ICP, met en œuvre une mémoire cache locale de données de révocation pour permettre la découverte et la validation des chemins lorsqu’il est impossible d’accéder à l’information de révocation par le réseau.
A9: Supplemental Guidance | B9: Status information for certification paths includes, for example, certificate revocation lists or certificate status protocol responses. Related control: IA-6. | D9: Directives supplémentaires | E9: Les renseignements sur le statut des chemins de certification comprennent, par exemple, les listes de révocation de certificats ou les réponses du protocole sur le statut des certificats. Contrôle connexe : IA-6.
A10: Test Case | D10: Cas de test
A11: Test | B11: TEST-IA-5(2) | D11: Test | E11: TEST-IA-5(2)
A12: Requirement ID | B12: IA-5(2) | D12: ID Exigence | E12: IA-5(2)
A13: Component | D13: Composant
A14: Requirement | D14: Exigence
A15: Contextual Design Description | D15: Description contextuelle du design
A16: Evidence Provided | D16: Preuve fournie
A17: Preparer Sign Off (Initials, Date) | D17: Signataire préparateur (Initiales, Date)
A18: Owner Sign Off (Initials, Date) | D18: Signataire propriétaire (Initiales, Date)
A19: Assessor Sign Off (Initials, Date) | D19: Signataire évaluateur (Initiales, Date)
A20: Status | B20: Not Started | D20: Statut | E20: Non commencé
A21: Comments | D21: Commentaires

Sheet IA-5-4
A1: Control IA-5(4) — Evidence Tracking | D1: Contrôle IA-5(4) — Suivi des preuves
A2: Control Information | D2: Informations du contrôle
A3: Control Identifier | B3: IA-5(4) | D3: Identifiant du contrôle | E3: IA-5(4)
A4: Family | B4: Authenticator Management | D4: Famille | E4: Gestion des authentifiants
A5: Profile | B5: CCCS Medium / PBMM Moderate | D5: Profil | E5: CCCS Moyen / PBMM Modéré
A6: Primary Evidence Tool | D6: Outil de preuve principal
A7: Contributing Tools | D7: Outils contributeurs
A8: Control Description | B8: AUTHENTICATOR MANAGEMENT | AUTOMATED SUPPORT FOR PASSWORD STRENGTH DETERMINATION The organization employs automated tools to determine if password authenticators are sufficiently strong to satisfy password length, complexity, rotation and lifetime restrictions established by IA-5(1). | D8: Description du contrôle | E8: GESTION DE L’AUTHENTIFIANT | SOUTIEN AUTOMATISÉ POUR LA DÉTERMINATION DE LA FORCE DES MOTS DE PASSE L’organisation utilise des outils automatisés pour déterminer si les authentifiants par mot de passe sont suffisamment forts pour respecter les restrictions relatives à la longueur, à la complexité, à la rotation et à la durée de vie établies par IA-5(1).
A9: Supplemental Guidance | B9: This control enhancement focuses on the creation of strong passwords and the characteristics of such passwords (e.g., complexity) prior to use, the enforcement of which is carried out by organizational information systems in IA-5 (1). Related controls: CA-2, CA-7, RA-5. | D9: Directives supplémentaires | E9: Cette amélioration du contrôle est axée sur la création de mots de passe forts et sur les caractéristiques de ces mots de passe (p. ex., complexité) avant leur utilisation, ce contrôle étant appliqué par les systèmes d’information organisationnels dans IA-5 (1). Contrôles connexes : CA-2, CA-7, RA-5.
A10: Test Case | D10: Cas de test
A11: Test | B11: TEST-IA-5(4) | D11: Test | E11: TEST-IA-5(4)
A12: Requirement ID | B12: IA-5(4) | D12: ID Exigence | E12: IA-5(4)
A13: Component | D13: Composant
A14: Requirement | D14: Exigence
A15: Contextual Design Description | D15: Description contextuelle du design
A16: Evidence Provided | D16: Preuve fournie
A17: Preparer Sign Off (Initials, Date) | D17: Signataire préparateur (Initiales, Date)
A18: Owner Sign Off (Initials, Date) | D18: Signataire propriétaire (Initiales, Date)
A19: Assessor Sign Off (Initials, Date) | D19: Signataire évaluateur (Initiales, Date)
A20: Status | B20: Not Started | D20: Statut | E20: Non commencé
A21: Comments | D21: Commentaires

Sheet IA-5-6
A1: Control IA-5(6) — Evidence Tracking | D1: Contrôle IA-5(6) — Suivi des preuves
A2: Control Information | D2: Informations du contrôle
A3: Control Identifier | B3: IA-5(6) | D3: Identifiant du contrôle | E3: IA-5(6)
A4: Family | B4: Authenticator Management | D4: Famille | E4: Gestion des authentifiants
A5: Profile | B5: CCCS Medium / PBMM Moderate | D5: Profil | E5: CCCS Moyen / PBMM Modéré
A6: Primary Evidence Tool | D6: Outil de preuve principal
A7: Contributing Tools | D7: Outils contributeurs
A8: Control Description | B8: AUTHENTICATOR MANAGEMENT | PROTECTION OF AUTHENTICATORS The organization protects authenticators commensurate with the security category of the information to which use of the authenticator permits access. | D8: Description du contrôle | E8: GESTION DES AUTHENTIFIANTS | PROTECTION DES AUTHENTIFIANTS L’organisation assure une protection des authentifiants qui est proportionnelle à la catégorie de sécurité de l’information à laquelle les authentifiants permettent l’accès.
A9: Supplemental Guidance | B9: For information systems containing multiple security categories of information without reliable physical or logical separation between categories, authenticators used to grant access to the systems are protected commensurate with the highest security category of information on the systems. | D9: Directives supplémentaires | E9: Dans le cas des systèmes d’information qui contiennent plusieurs catégories de sécurité de l’information sans séparation physique ou logique fiable entre les catégories, les authentifiants utilisés pour accorder l’accès aux systèmes sont protégés conformément à la catégorie de sécurité de l’information la plus élevée sur les systèmes.
A10: Test Case | D10: Cas de test
A11: Test | B11: TEST-IA-5(6) | D11: Test | E11: TEST-IA-5(6)
A12: Requirement ID | B12: IA-5(6) | D12: ID Exigence | E12: IA-5(6)
A13: Component | D13: Composant
A14: Requirement | D14: Exigence
A15: Contextual Design Description | D15: Description contextuelle du design
A16: Evidence Provided | D16: Preuve fournie
A17: Preparer Sign Off (Initials, Date) | D17: Signataire préparateur (Initiales, Date)
A18: Owner Sign Off (Initials, Date) | D18: Signataire propriétaire (Initiales, Date)
A19: Assessor Sign Off (Initials, Date) | D19: Signataire évaluateur (Initiales, Date)
A20: Status | B20: Not Started | D20: Statut | E20: Non commencé
A21: Comments | D21: Commentaires

Sheet IA-6
A1: Control IA-6 — Evidence Tracking | D1: Contrôle IA-6 — Suivi des preuves
A2: Control Information | D2: Informations du contrôle
A3: Control Identifier | B3: IA-6 | D3: Identifiant du contrôle | E3: IA-6
A4: Family | B4: Authenticator Feedback | D4: Famille | E4: Rétroaction de l’authentifiant
A5: Profile | B5: CCCS Medium / PBMM Moderate | D5: Profil | E5: CCCS Moyen / PBMM Modéré
A6: Primary Evidence Tool | D6: Outil de preuve principal
A7: Contributing Tools | D7: Outils contributeurs
A8: Control Description | B8: (A) The information system obscures feedback of authentication information during the authentication process to protect the information from possible exploitation/use by unauthorized individuals. | D8: Description du contrôle | E8: (A) Le système d’information masque la rétroaction de l’information d’authentification pendant le processus d’authentification afin de protéger cette information contre l’exploitation ou l’utilisation possibles par des personnes non autorisées.
A9: Supplemental Guidance | B9: The feedback from information systems does not provide information that would allow unauthorized individuals to compromise authentication mechanisms. For some types of information systems or system components, for example, desktops/notebooks with relatively large monitors, the threat (often referred to as shoulder surfing) may be significant. For other types of systems or components, for example, mobile devices with 2-4 inch screens, this threat may be less significant, and may need to be balanced against the increased likelihood of typographic input errors due to the small keyboards. Therefore, the means for obscuring the authenticator feedback is selected accordingly. Obscuring the feedback of authentication information includes, for example, displaying asterisks when users type passwords into input devices, or displaying feedback for a very limited time before fully obscuring it. Related control: PE-18 | D9: Directives supplémentaires | E9: La rétroaction des systèmes d’information ne fournit pas d’information qui permettrait à des personnes non autorisées de compromettre les mécanismes d’authentification. Pour certains types de systèmes d’information ou de composants de systèmes, par exemple, les ordinateurs de bureau ou les ordinateurs portatifs avec écrans relativement grands, la menace (souvent appelée « espionnage par-dessus l’épaule ») peut être importante. Pour d’autres types de systèmes ou de composants, par exemple, les appareils mobiles dotés d’écrans de 2 à 4 pouces, cette menace peut être moins importante et il peut être utile de la comparer au risque accru d’erreurs typographiques lors de la saisie sur les claviers de petite taille. Ainsi, le mécanisme de masquage de la rétroaction de l’authentifiant est sélectionné en conséquence. Le masquage de la rétroaction de l’information d’authentification comprend, par exemple, l’affichage d’astérisques lorsque les utilisateurs tapent des mots de passe dans des dispositifs de saisie, ou l’affichage très bref de la rétroaction avant son masquage complet. Contrôle connexe : PE-18
A10: Test Case | D10: Cas de test
A11: Test | B11: TEST-IA-6 | D11: Test | E11: TEST-IA-6
A12: Requirement ID | B12: IA-6 | D12: ID Exigence | E12: IA-6
A13: Component | D13: Composant
A14: Requirement | D14: Exigence
A15: Contextual Design Description | D15: Description contextuelle du design
A16: Evidence Provided | D16: Preuve fournie
A17: Preparer Sign Off (Initials, Date) | D17: Signataire préparateur (Initiales, Date)
A18: Owner Sign Off (Initials, Date) | D18: Signataire propriétaire (Initiales, Date)
A19: Assessor Sign Off (Initials, Date) | D19: Signataire évaluateur (Initiales, Date)
A20: Status | B20: Not Started | D20: Statut | E20: Non commencé
A21: Comments | D21: Commentaires

Sheet IA-7
A1: Control IA-7 — Evidence Tracking | D1: Contrôle IA-7 — Suivi des preuves
A2: Control Information | D2: Informations du contrôle
A3: Control Identifier | B3: IA-7 | D3: Identifiant du contrôle | E3: IA-7
A4: Family | B4: Cryptographic Module Authentication | D4: Famille | E4: Authentification par module cryptographique
A5: Profile | B5: CCCS Medium / PBMM Moderate | D5: Profil | E5: CCCS Moyen / PBMM Modéré
A6: Primary Evidence Tool | D6: Outil de preuve principal
A7: Contributing Tools | D7: Outils contributeurs
A8: Control Description | B8: (A) The information system implements mechanisms for authentication to a cryptographic module that meet the requirements of applicable organizational policies, directives, and standards for such authentication. | D8: Description du contrôle | E8: (A) Le système d’information met en œuvre des mécanismes d’authentification par module cryptographique qui respectent les exigences des politiques, directives et normes organisationnelles applicables pour une telle authentification.
A9: Supplemental Guidance | B9: Authentication mechanisms may be required within a cryptographic module to authenticate an operator accessing the module and to verify that the operator is authorized to assume the requested role and perform services within that role. Related controls: SC-12, SC-13 | D9: Directives supplémentaires | E9: Des mécanismes d’authentification peuvent être requis au sein d’un module cryptographique pour authentifier un opérateur qui accède au module et pour vérifier qu’il est autorisé à assumer le rôle demandé et à fournir des services dans le cadre de ce rôle. Contrôles connexes : SC-12, SC-13
A10: Test Case | D10: Cas de test
A11: Test | B11: TEST-IA-7 | D11: Test | E11: TEST-IA-7
A12: Requirement ID | B12: IA-7 | D12: ID Exigence | E12: IA-7
A13: Component | D13: Composant
A14: Requirement | D14: Exigence
A15: Contextual Design Description | D15: Description contextuelle du design
A16: Evidence Provided | D16: Preuve fournie
A17: Preparer Sign Off (Initials, Date) | D17: Signataire préparateur (Initiales, Date)
A18: Owner Sign Off (Initials, Date) | D18: Signataire propriétaire (Initiales, Date)
A19: Assessor Sign Off (Initials, Date) | D19: Signataire évaluateur (Initiales, Date)
A20: Status | B20: Not Started | D20: Statut | E20: Non commencé
A21: Comments | D21: Commentaires

Sheet IA-8
A1: Control IA-8 — Evidence Tracking | D1: Contrôle IA-8 — Suivi des preuves
A2: Control Information | D2: Informations du contrôle
A3: Control Identifier | B3: IA-8 | D3: Identifiant du contrôle | E3: IA-8
A4: Family | B4: Identification and Authentication (Non-Organizational Users) | D4: Famille | E4: Identification et authentification (utilisateurs extérieurs à l’organisation)
A5: Profile | B5: CCCS Medium / PBMM Moderate | D5: Profil | E5: CCCS Moyen / PBMM Modéré
A6: Primary Evidence Tool | D6: Outil de preuve principal
A7: Contributing Tools | D7: Outils contributeurs
A8: Control Description | B8: (A) The information system uniquely identifies and authenticates non-organizational users (or processes acting on behalf of non-organizational users). | D8: Description du contrôle | E8: (A) Le système d’information identifie et authentifie de façon unique les utilisateurs extérieurs à l’organisation (ou les processus agissant pour le compte d’utilisateurs extérieurs à l’organisation).
A9: Supplemental Guidance | B9: Non-organizational users include information system users other than organizational users explicitly covered by IA-2. These individuals are uniquely identified and authenticated for accesses other than those accesses explicitly identified and documented in AC-14. Authentication of non-organizational users accessing federal information systems may be required to protect federal, proprietary, or privacy-related information (with exceptions noted for national security systems). Organizations use risk assessments to determine authentication needs and consider scalability, practicality, and security in balancing the need to ensure ease of use for access to information and information systems with the need to protect and adequately mitigate risk. IA-2 addresses identification and authentication requirements for access to information systems by organizational users. Related controls: AC-2, AC-14, AC-17, AC-18, IA-2, IA-4, IA-5, MA-4, RA-3, SA-12, SC-8 | D9: Directives supplémentaires | E9: Les utilisateurs extérieurs à l’organisation comprennent les utilisateurs du système d’information autres que les utilisateurs au sein de l’organisation qui sont explicitement visés par l’IA-2. Ces personnes sont identifiées et authentifiées de façon unique pour des accès autres que ceux explicitement identifiés et documentés dans AC-14. L’authentification des utilisateurs extérieurs à l’organisation qui accèdent aux systèmes d’information fédéraux peut être nécessaire pour protéger les renseignements fédéraux, exclusifs, ou liés à la protection des renseignements personnels (sauf dans le cas des systèmes de sécurité nationale). Les organisations utilisent les évaluations des risques pour déterminer les besoins en matière d’authentification et prennent en compte les facteurs d’adaptabilité, de commodité et de sécurité pour établir un équilibre entre la nécessité d’assurer la facilité d’utilisation pour l’accès à l’information et aux systèmes d’information et la nécessité d’assurer une protection et d’atténuer adéquatement les risques. IA-2 traite des exigences en matière d’identification et d’authentification pour l’accès aux systèmes d’information par les utilisateurs au sein de l’organisation. Contrôles connexes : AC-2, AC-14, AC-17, AC-18, IA-2, IA-4, IA-5, MA-4, RA-3, SA-12, SC-8
A10: Test Case | D10: Cas de test
A11: Test | B11: TEST-IA-8 | D11: Test | E11: TEST-IA-8
A12: Requirement ID | B12: IA-8 | D12: ID Exigence | E12: IA-8
A13: Component | D13: Composant
A14: Requirement | D14: Exigence
A15: Contextual Design Description | D15: Description contextuelle du design
A16: Evidence Provided | D16: Preuve fournie
A17: Preparer Sign Off (Initials, Date) | D17: Signataire préparateur (Initiales, Date)
A18: Owner Sign Off (Initials, Date) | D18: Signataire propriétaire (Initiales, Date)
A19: Assessor Sign Off (Initials, Date) | D19: Signataire évaluateur (Initiales, Date)
A20: Status | B20: Not Started | D20: Statut | E20: Non commencé
A21: Comments | D21: Commentaires

Sheet MA-4
A1: Control MA-4 — Evidence Tracking | D1: Contrôle MA-4 — Suivi des preuves
A2: Control Information | D2: Informations du contrôle
A3: Control Identifier | B3: MA-4 | D3: Identifiant du contrôle | E3: MA-4
A4: Family | B4: Non-Local Maintenance | D4: Famille | E4: Maintenance non locale
A5: Profile | B5: CCCS Medium / PBMM Moderate | D5: Profil | E5: CCCS Moyen / PBMM Modéré
A6: Primary Evidence Tool | D6: Outil de preuve principal
A7: Contributing Tools | D7: Outils contributeurs
A8: Control Description | B8: (A) The organization approves and monitors nonlocal maintenance and diagnostic activities. (B) The organization allows the use of non-local maintenance and diagnostic tools only as consistent with organizational policy and as documented in the security plan for the information system. (C) The organization employs strong authenticators in the establishment of nonlocal maintenance and diagnostic sessions. (D) The organization maintains records for nonlocal maintenance and diagnostic activities. | D8: Description du contrôle | E8: (A) L’organisation approuve et surveille les activités de maintenance et de diagnostic non locales. (B) L’organisation ne permet l’utilisation d’outils de maintenance et de diagnostic non locaux que dans la mesure où ils sont conformes à la politique de l’organisation et documentés dans le plan de sécurité du système d’information. (C) L’organisation utilise des authentifiants puissants pour les ouvertures de sessions de maintenance et de diagnostic non locales. (D) L’organisation tient des registres pour les activités de maintenance et de diagnostic non locales.
