Workbook

Sheet DASHBOARD
A1: DASHBOARD — PBMM Evidence: Management and Governance
A2: Control ID | B2: Control Name | C2: Primary Tool | D2: Tab | E2: Status
A3: AC-2(1) | B3: Account Management | D3: AC-2-1 | E3: ='AC-2-1'!B20 -> Not Started
A4: AC-2(2) | B4: Account Management | D4: AC-2-2 | E4: ='AC-2-2'!B20 -> Not Started
A5: AC-2(3) | B5: Account Management | D5: AC-2-3 | E5: ='AC-2-3'!B20 -> Not Started
A6: AC-2(4) | B6: Account Management | D6: AC-2-4 | E6: ='AC-2-4'!B20 -> Not Started
A7: AC-2(5) | B7: Account Management | D7: AC-2-5 | E7: ='AC-2-5'!B20 -> Not Started
A8: AC-2(7) | B8: Account Management | D8: AC-2-7 | E8: ='AC-2-7'!B20 -> Not Started
A9: AC-6 | B9: Least Privilege | D9: AC-6 | E9: ='AC-6'!B20 -> Not Started
A10: AC-6(1) | B10: Least Privilege | D10: AC-6-1 | E10: ='AC-6-1'!B20 -> Not Started
A11: AC-6(9) | B11: Least Privilege | D11: AC-6-9 | E11: ='AC-6-9'!B20 -> Not Started
A12: AC-6(10) | B12: Least Privilege | D12: AC-6-10 | E12: ='AC-6-10'!B20 -> Not Started
A13: AC-17(1) | B13: Remote Access | D13: AC-17-1 | E13: ='AC-17-1'!B20 -> Not Started
A14: AC-17(2) | B14: Remote Access | D14: AC-17-2 | E14: ='AC-17-2'!B20 -> Not Started
A15: AU-2 | B15: Auditable Events | D15: AU-2 | E15: ='AU-2'!B20 -> Not Started
A16: AU-3 | B16: Content of Audit Records | D16: AU-3 | E16: ='AU-3'!B20 -> Not Started
A17: AU-3(1) | B17: Content of Audit Records | D17: AU-3-1 | E17: ='AU-3-1'!B20 -> Not Started
A18: AU-5 | B18: Response To Audit Processing Failures | D18: AU-5 | E18: ='AU-5'!B20 -> Not Started
A19: AU-6(1) | B19: Audit Review, Analysis, and Reporting | D19: AU-6-1 | E19: ='AU-6-1'!B20 -> Not Started
A20: AU-6(3) | B20: Audit Review, Analysis, and Reporting | D20: AU-6-3 | E20: ='AU-6-3'!B20 -> Not Started
A21: AU-7 | B21: Audit Reduction and Report Generation | D21: AU-7 | E21: ='AU-7'!B20 -> Not Started
A22: AU-7(1) | B22: Audit Reduction and Report Generation | D22: AU-7-1 | E22: ='AU-7-1'!B20 -> Not Started
A23: AU-8 | B23: Time Stamps | D23: AU-8 | E23: ='AU-8'!B20 -> Not Started
A24: AU-8(1) | B24: Time Stamps | D24: AU-8-1 | E24: ='AU-8-1'!B20 -> Not Started
A25: AU-9 | B25: Protection of Audit Information | D25: AU-9 | E25: ='AU-9'!B20 -> Not Started
A26: AU-9(2) | B26: Protection of Audit Information | D26: AU-9-2 | E26: ='AU-9-2'!B20 -> Not Started
A27: AU-9(4) | B27: Protection of Audit Information | D27: AU-9-4 | E27: ='AU-9-4'!B20 -> Not Started
A28: AU-11 | B28: Audit Record Retention | D28: AU-11 | E28: ='AU-11'!B20 -> Not Started
A29: AU-12 | B29: Audit Generation | D29: AU-12 | E29: ='AU-12'!B20 -> Not Started
A30: CA-9 | B30: Internal System Connections | D30: CA-9 | E30: ='CA-9'!B20 -> Not Started
A31: CM-2(2) | B31: Baseline Configuration | D31: CM-2-2 | E31: ='CM-2-2'!B20 -> Not Started
A32: CM-2(3) | B32: Baseline Configuration | D32: CM-2-3 | E32: ='CM-2-3'!B20 -> Not Started
A33: CM-3 | B33: Configuration Change Control | D33: CM-3 | E33: ='CM-3'!B20 -> Not Started
A34: CM-3(6) | B34: Configuration Change Control | D34: CM-3-6 | E34: ='CM-3-6'!B20 -> Not Started
A35: CM-5(1) | B35: Access Restrictions for Change | D35: CM-5-1 | E35: ='CM-5-1'!B20 -> Not Started
A36: CM-6 | B36: Configuration Settings | D36: CM-6 | E36: ='CM-6'!B20 -> Not Started
A37: CM-6(1) | B37: Configuration Settings | D37: CM-6-1 | E37: ='CM-6-1'!B20 -> Not Started
A38: CM-7 | B38: Least Functionality | D38: CM-7 | E38: ='CM-7'!B20 -> Not Started
A39: CM-7(1) | B39: Least Functionality | D39: CM-7-1 | E39: ='CM-7-1'!B20 -> Not Started
A40: CM-8(2) | B40: Information System Component Inventory | D40: CM-8-2 | E40: ='CM-8-2'!B20 -> Not Started
A41: CM-8(5) | B41: Information System Component Inventory | D41: CM-8-5 | E41: ='CM-8-5'!B20 -> Not Started
A42: CP-6 | B42: Alternate Storage Site | D42: CP-6 | E42: ='CP-6'!B20 -> Not Started
A43: CP-6(2) | B43: Alternate Storage Site | D43: CP-6-2 | E43: ='CP-6-2'!B20 -> Not Started
A44: CP-7 | B44: Alternate Processing Site | D44: CP-7 | E44: ='CP-7'!B20 -> Not Started
A45: CP-7(1) | B45: Alternate Processing Site | D45: CP-7-1 | E45: ='CP-7-1'!B20 -> Not Started
A46: CP-7(4) | B46: Alternate Processing Site | D46: CP-7-4 | E46: ='CP-7-4'!B20 -> Not Started
A47: CP-9 | B47: Information System Backup | D47: CP-9 | E47: ='CP-9'!B20 -> Not Started
A48: CP-9(1) | B48: Information System Backup | D48: CP-9-1 | E48: ='CP-9-1'!B20 -> Not Started
A49: CP-9(2) | B49: Information System Backup | D49: CP-9-2 | E49: ='CP-9-2'!B20 -> Not Started
A50: CP-9(3) | B50: Information System Backup | D50: CP-9-3 | E50: ='CP-9-3'!B20 -> Not Started
A51: CP-9(5) | B51: Information System Backup | D51: CP-9-5 | E51: ='CP-9-5'!B20 -> Not Started
A52: CP-10 | B52: Information System Recovery and Reconstitution | D52: CP-10 | E52: ='CP-10'!B20 -> Not Started
A53: CP-10(4) | B53: Information System Recovery and Reconstitution | D53: CP-10-4 | E53: ='CP-10-4'!B20 -> Not Started
A54: IA-5(7) | B54: Authenticator Management | D54: IA-5-7 | E54: ='IA-5-7'!B20 -> Not Started
A55: MA-4 | B55: Non-Local Maintenance | D55: MA-4 | E55: ='MA-4'!B20 -> Not Started
A56: MA-4(1) | B56: Non-Local Maintenance | D56: MA-4-1 | E56: ='MA-4-1'!B20 -> Not Started
A57: RA-5 | B57: Vulnerability Scanning | D57: RA-5 | E57: ='RA-5'!B20 -> Not Started
A58: RA-5(8) | B58: Vulnerability Scanning | D58: RA-5-8 | E58: ='RA-5-8'!B20 -> Not Started
A59: SA-9(5) | B59: External Information System Services | D59: SA-9-5 | E59: ='SA-9-5'!B20 -> Not Started
A60: SC-7 | B60: Boundary Protection | D60: SC-7 | E60: ='SC-7'!B20 -> Not Started
A61: SC-13 | B61: Cryptographic Protection | D61: SC-13 | E61: ='SC-13'!B20 -> Not Started
A62: SC-18 | B62: Mobile Code | D62: SC-18 | E62: ='SC-18'!B20 -> Not Started
A63: SC-28 | B63: Protection of Information At Rest | D63: SC-28 | E63: ='SC-28'!B20 -> Not Started
A64: SC-28(1) | B64: Protection of Information At Rest | D64: SC-28-1 | E64: ='SC-28-1'!B20 -> Not Started
A65: SI-2(2) | B65: Flaw Remediation | D65: SI-2-2 | E65: ='SI-2-2'!B20 -> Not Started
A66: SI-3(1) | B66: Malicious Code Protection | D66: SI-3-1 | E66: ='SI-3-1'!B20 -> Not Started
A67: SI-3(2) | B67: Malicious Code Protection | D67: SI-3-2 | E67: ='SI-3-2'!B20 -> Not Started
A68: SI-4 | B68: Information System Monitoring | D68: SI-4 | E68: ='SI-4'!B20 -> Not Started
A69: SI-4(1) | B69: Information System Monitoring | D69: SI-4-1 | E69: ='SI-4-1'!B20 -> Not Started
A70: SI-4(2) | B70: Information System Monitoring | D70: SI-4-2 | E70: ='SI-4-2'!B20 -> Not Started
A71: SI-4(4) | B71: Information System Monitoring | D71: SI-4-4 | E71: ='SI-4-4'!B20 -> Not Started
A72: SI-4(5) | B72: Information System Monitoring | D72: SI-4-5 | E72: ='SI-4-5'!B20 -> Not Started
A73: SI-4(11) | B73: Information System Monitoring | D73: SI-4-11 | E73: ='SI-4-11'!B20 -> Not Started
A74: SI-6 | B74: Security Functional Verification | D74: SI-6 | E74: ='SI-6'!B20 -> Not Started
A75: SI-7(7) | B75: Software, Firmware, and Information Integrity | D75: SI-7-7 | E75: ='SI-7-7'!B20 -> Not Started
A76: SI-11 | B76: Error Handling | D76: SI-11 | E76: ='SI-11'!B20 -> Not Started
A78: Completion Metrics
A79: Total Controls | E79: =74 -> 74
A80: Not Started | E80: =COUNTIF(E3:E76,"Not Started") -> 74
A81: In Progress | E81: =COUNTIF(E3:E76,"In Progress") -> 0
A82: Evidence Provided | E82: =COUNTIF(E3:E76,"Evidence Provided") -> 0
A83: Under Review | E83: =COUNTIF(E3:E76,"Under Review") -> 0
A84: Passed | E84: =COUNTIF(E3:E76,"Passed") -> 0
A85: Failed | E85: =COUNTIF(E3:E76,"Failed") -> 0
A86: Accepted Exception | E86: =COUNTIF(E3:E76,"Accepted Exception") -> 0
A87: % Complete | E87: =IFERROR(COUNTIF(E3:E76,"Passed")/74,0) -> 0
A88: % Not Started | E88: =IFERROR(COUNTIF(E3:E76,"Not Started")/74,0) -> 1

Sheet TABLEAU_DE_BORD
A1: TABLEAU DE BORD — Suivi PBMM : Management and Governance
A2: ID Contrôle | B2: Nom du contrôle | C2: Outil principal | D2: Onglet | E2: Statut
A3: AC-2(1) | B3: Gestion des comptes | D3: AC-2-1 | E3: ='AC-2-1'!E20 -> Non commencé
A4: AC-2(2) | B4: Gestion des comptes | D4: AC-2-2 | E4: ='AC-2-2'!E20 -> Non commencé
A5: AC-2(3) | B5: Gestion des comptes | D5: AC-2-3 | E5: ='AC-2-3'!E20 -> Non commencé
A6: AC-2(4) | B6: Gestion des comptes | D6: AC-2-4 | E6: ='AC-2-4'!E20 -> Non commencé
A7: AC-2(5) | B7: Gestion des comptes | D7: AC-2-5 | E7: ='AC-2-5'!E20 -> Non commencé
A8: AC-2(7) | B8: Gestion des comptes | D8: AC-2-7 | E8: ='AC-2-7'!E20 -> Non commencé
A9: AC-6 | B9: Moindre privilège | D9: AC-6 | E9: ='AC-6'!E20 -> Non commencé
A10: AC-6(1) | B10: Moindre privilège | D10: AC-6-1 | E10: ='AC-6-1'!E20 -> Non commencé
A11: AC-6(9) | B11: Moindre privilège | D11: AC-6-9 | E11: ='AC-6-9'!E20 -> Non commencé
A12: AC-6(10) | B12: Moindre privilège | D12: AC-6-10 | E12: ='AC-6-10'!E20 -> Non commencé
A13: AC-17(1) | B13: Accès à distance | D13: AC-17-1 | E13: ='AC-17-1'!E20 -> Non commencé
A14: AC-17(2) | B14: Accès à distance | D14: AC-17-2 | E14: ='AC-17-2'!E20 -> Non commencé
A15: AU-2 | B15: Événements vérifiables | D15: AU-2 | E15: ='AU-2'!E20 -> Non commencé
A16: AU-3 | B16: Contenu des enregistrements de vérification | D16: AU-3 | E16: ='AU-3'!E20 -> Non commencé
A17: AU-3(1) | B17: Contenu des enregistrements de vérification | D17: AU-3-1 | E17: ='AU-3-1'!E20 -> Non commencé
A18: AU-5 | B18: Réponse aux échecs de traitement de vérification | D18: AU-5 | E18: ='AU-5'!E20 -> Non commencé
A19: AU-6(1) | B19: Examen, analyse et rapport de vérification | D19: AU-6-1 | E19: ='AU-6-1'!E20 -> Non commencé
A20: AU-6(3) | B20: Examen, analyse et rapport de vérification | D20: AU-6-3 | E20: ='AU-6-3'!E20 -> Non commencé
A21: AU-7 | B21: Réduction des vérifications et production de rapports | D21: AU-7 | E21: ='AU-7'!E20 -> Non commencé
A22: AU-7(1) | B22: Réduction des vérifications et production de rapports | D22: AU-7-1 | E22: ='AU-7-1'!E20 -> Non commencé
A23: AU-8 | B23: Estampilles temporelles | D23: AU-8 | E23: ='AU-8'!E20 -> Non commencé
A24: AU-8(1) | B24: Estampilles temporelles | D24: AU-8-1 | E24: ='AU-8-1'!E20 -> Non commencé
A25: AU-9 | B25: Protection des renseignements de vérification | D25: AU-9 | E25: ='AU-9'!E20 -> Non commencé
A26: AU-9(2) | B26: Protection des renseignements de vérification | D26: AU-9-2 | E26: ='AU-9-2'!E20 -> Non commencé
A27: AU-9(4) | B27: Protection des renseignements de vérification | D27: AU-9-4 | E27: ='AU-9-4'!E20 -> Non commencé
A28: AU-11 | B28: Conservation des enregistrements de vérification | D28: AU-11 | E28: ='AU-11'!E20 -> Non commencé
A29: AU-12 | B29: Génération des vérifications | D29: AU-12 | E29: ='AU-12'!E20 -> Non commencé
A30: CA-9 | B30: Connexions internes au système | D30: CA-9 | E30: ='CA-9'!E20 -> Non commencé
A31: CM-2(2) | B31: Configuration de base | D31: CM-2-2 | E31: ='CM-2-2'!E20 -> Non commencé
A32: CM-2(3) | B32: Configuration de base | D32: CM-2-3 | E32: ='CM-2-3'!E20 -> Non commencé
A33: CM-3 | B33: Contrôle des changements de configuration | D33: CM-3 | E33: ='CM-3'!E20 -> Non commencé
A34: CM-3(6) | B34: Contrôle des changements de configuration | D34: CM-3-6 | E34: ='CM-3-6'!E20 -> Non commencé
A35: CM-5(1) | B35: Restrictions d’accès pour les changements | D35: CM-5-1 | E35: ='CM-5-1'!E20 -> Non commencé
A36: CM-6 | B36: Paramètres de configuration | D36: CM-6 | E36: ='CM-6'!E20 -> Non commencé
A37: CM-6(1) | B37: Paramètres de configuration | D37: CM-6-1 | E37: ='CM-6-1'!E20 -> Non commencé
A38: CM-7 | B38: Moindre fonctionnalité | D38: CM-7 | E38: ='CM-7'!E20 -> Non commencé
A39: CM-7(1) | B39: Moindre fonctionnalité | D39: CM-7-1 | E39: ='CM-7-1'!E20 -> Non commencé
A40: CM-8(2) | B40: Inventaire des composants du système d’information | D40: CM-8-2 | E40: ='CM-8-2'!E20 -> Non commencé
A41: CM-8(5) | B41: Inventaire des composants du système d’information | D41: CM-8-5 | E41: ='CM-8-5'!E20 -> Non commencé
A42: CP-6 | B42: Site de stockage auxiliaire | D42: CP-6 | E42: ='CP-6'!E20 -> Non commencé
A43: CP-6(2) | B43: Site de stockage auxiliaire | D43: CP-6-2 | E43: ='CP-6-2'!E20 -> Non commencé
A44: CP-7 | B44: Site de traitement auxiliaire | D44: CP-7 | E44: ='CP-7'!E20 -> Non commencé
A45: CP-7(1) | B45: Site de traitement auxiliaire | D45: CP-7-1 | E45: ='CP-7-1'!E20 -> Non commencé
A46: CP-7(4) | B46: Site de traitement auxiliaire | D46: CP-7-4 | E46: ='CP-7-4'!E20 -> Non commencé
A47: CP-9 | B47: Sauvegarde du système d’information | D47: CP-9 | E47: ='CP-9'!E20 -> Non commencé
A48: CP-9(1) | B48: Sauvegarde du système d’information | D48: CP-9-1 | E48: ='CP-9-1'!E20 -> Non commencé
A49: CP-9(2) | B49: Sauvegarde du système d’information | D49: CP-9-2 | E49: ='CP-9-2'!E20 -> Non commencé
A50: CP-9(3) | B50: Sauvegarde du système d’information | D50: CP-9-3 | E50: ='CP-9-3'!E20 -> Non commencé
A51: CP-9(5) | B51: Sauvegarde du système d’information | D51: CP-9-5 | E51: ='CP-9-5'!E20 -> Non commencé
A52: CP-10 | B52: Reprise et reconstitution du système d’information | D52: CP-10 | E52: ='CP-10'!E20 -> Non commencé
A53: CP-10(4) | B53: Reprise et reconstitution du système d’information | D53: CP-10-4 | E53: ='CP-10-4'!E20 -> Non commencé
A54: IA-5(7) | B54: Gestion des authentifiants | D54: IA-5-7 | E54: ='IA-5-7'!E20 -> Non commencé
A55: MA-4 | B55: Maintenance non locale | D55: MA-4 | E55: ='MA-4'!E20 -> Non commencé
A56: MA-4(1) | B56: Maintenance non locale | D56: MA-4-1 | E56: ='MA-4-1'!E20 -> Non commencé
A57: RA-5 | B57: Analyse des vulnérabilités | D57: RA-5 | E57: ='RA-5'!E20 -> Non commencé
A58: RA-5(8) | B58: Analyse des vulnérabilités | D58: RA-5-8 | E58: ='RA-5-8'!E20 -> Non commencé
A59: SA-9(5) | B59: Services de systèmes d’information externes | D59: SA-9-5 | E59: ='SA-9-5'!E20 -> Non commencé
A60: SC-7 | B60: Protection des frontières | D60: SC-7 | E60: ='SC-7'!E20 -> Non commencé
A61: SC-13 | B61: Protection cryptographique | D61: SC-13 | E61: ='SC-13'!E20 -> Non commencé
A62: SC-18 | B62: Code mobile | D62: SC-18 | E62: ='SC-18'!E20 -> Non commencé
A63: SC-28 | B63: Protection de l’information inactive | D63: SC-28 | E63: ='SC-28'!E20 -> Non commencé
A64: SC-28(1) | B64: Protection de l’information inactive | D64: SC-28-1 | E64: ='SC-28-1'!E20 -> Non commencé
A65: SI-2(2) | B65: Correction des défauts | D65: SI-2-2 | E65: ='SI-2-2'!E20 -> Non commencé
A66: SI-3(1) | B66: Protection contre le code malveillant | D66: SI-3-1 | E66: ='SI-3-1'!E20 -> Non commencé
A67: SI-3(2) | B67: Protection contre le code malveillant | D67: SI-3-2 | E67: ='SI-3-2'!E20 -> Non commencé
A68: SI-4 | B68: Surveillance du système d’information | D68: SI-4 | E68: ='SI-4'!E20 -> Non commencé
A69: SI-4(1) | B69: Surveillance du système d’information | D69: SI-4-1 | E69: ='SI-4-1'!E20 -> Non commencé
A70: SI-4(2) | B70: Surveillance du système d’information | D70: SI-4-2 | E70: ='SI-4-2'!E20 -> Non commencé
A71: SI-4(4) | B71: Surveillance du système d’information | D71: SI-4-4 | E71: ='SI-4-4'!E20 -> Non commencé
A72: SI-4(5) | B72: Surveillance du système d’information | D72: SI-4-5 | E72: ='SI-4-5'!E20 -> Non commencé
A73: SI-4(11) | B73: Surveillance du système d’information | D73: SI-4-11 | E73: ='SI-4-11'!E20 -> Non commencé
A74: SI-6 | B74: Vérification fonctionnelle de la sécurité | D74: SI-6 | E74: ='SI-6'!E20 -> Non commencé
A75: SI-7(7) | B75: Logiciels, micrologiciels et intégrité de l’information | D75: SI-7-7 | E75: ='SI-7-7'!E20 -> Non commencé
A76: SI-11 | B76: Traitement des erreurs | D76: SI-11 | E76: ='SI-11'!E20 -> Non commencé
A78: Métriques de complétude
A79: Nombre total de contrôles | E79: =74 -> 74
A80: Non commencés | E80: =COUNTIF(E3:E76,"Non commencé") -> 74
A81: En cours | E81: =COUNTIF(E3:E76,"En cours") -> 0
A82: Preuve fournie | E82: =COUNTIF(E3:E76,"Preuve fournie") -> 0
A83: En révision | E83: =COUNTIF(E3:E76,"En révision") -> 0
A84: Réussi | E84: =COUNTIF(E3:E76,"Réussi") -> 0
A85: Échec | E85: =COUNTIF(E3:E76,"Échec") -> 0
A86: Exception acceptée | E86: =COUNTIF(E3:E76,"Exception acceptée") -> 0
A87: % Complété | E87: =IFERROR(COUNTIF(E3:E76,"Réussi")/74,0) -> 0
A88: % Non commencés | E88: =IFERROR(COUNTIF(E3:E76,"Non commencé")/74,0) -> 1

Sheet AC-2-1
A1: Control AC-2(1) — Evidence Tracking | D1: Contrôle AC-2(1) — Suivi des preuves
A2: Control Information | D2: Informations du contrôle
A3: Control Identifier | B3: AC-2(1) | D3: Identifiant du contrôle | E3: AC-2(1)
A4: Family | B4: Account Management | D4: Famille | E4: Gestion des comptes
A5: Profile | B5: CCCS Medium / PBMM Moderate | D5: Profil | E5: CCCS Moyen / PBMM Modéré
A6: Primary Evidence Tool | D6: Outil de preuve principal
A7: Contributing Tools | D7: Outils contributeurs
A8: Control Description | B8: ACCOUNT MANAGEMENT | AUTOMATED SYSTEM ACCOUNT MANAGEMENT The organization employs automated mechanisms to support the management of information system accounts. | D8: Description du contrôle | E8: GESTION DES COMPTES | GESTION AUTOMATISÉE DES COMPTES DU SYSTÈME L’organisation utilise des mécanismes automatisés pour prendre en charge la gestion des comptes du système d’information.
A9: Supplemental Guidance | B9: The use of automated mechanisms can include, for example: using email or text messaging to automatically notify account managers when users are terminated or transferred; using the information system to monitor account usage; and using telephonic notification to report atypical system account usage. | D9: Directives supplémentaires | E9: L’utilisation de mécanismes automatisés peut comprendre, par exemple, l’utilisation de courriels ou de messages texte pour aviser automatiquement les gestionnaires de comptes lorsque des utilisateurs sont licenciés ou transférés; l’utilisation du système d’information pour surveiller les statistiques d’utilisation des comptes; et l’utilisation d’une notification téléphonique pour signaler l’utilisation atypique des comptes du système.
A10: Test Case | D10: Cas de test
A11: Test | B11: TEST-AC-2(1) | D11: Test | E11: TEST-AC-2(1)
A12: Requirement ID | B12: AC-2(1) | D12: ID Exigence | E12: AC-2(1)
A13: Component | D13: Composant
A14: Requirement | D14: Exigence
A15: Contextual Design Description | D15: Description contextuelle du design
A16: Evidence Provided | D16: Preuve fournie
A17: Preparer Sign Off (Initials, Date) | D17: Signataire préparateur (Initiales, Date)
A18: Owner Sign Off (Initials, Date) | D18: Signataire propriétaire (Initiales, Date)
A19: Assessor Sign Off (Initials, Date) | D19: Signataire évaluateur (Initiales, Date)
A20: Status | B20: Not Started | D20: Statut | E20: Non commencé
A21: Comments | D21: Commentaires

Sheet AC-2-2
A1: Control AC-2(2) — Evidence Tracking | D1: Contrôle AC-2(2) — Suivi des preuves
A2: Control Information | D2: Informations du contrôle
A3: Control Identifier | B3: AC-2(2) | D3: Identifiant du contrôle | E3: AC-2(2)
A4: Family | B4: Account Management | D4: Famille | E4: Gestion des comptes
A5: Profile | B5: CCCS Medium / PBMM Moderate | D5: Profil | E5: CCCS Moyen / PBMM Modéré
A6: Primary Evidence Tool | D6: Outil de preuve principal
A7: Contributing Tools | D7: Outils contributeurs
A8: Control Description | B8: ACCOUNT MANAGEMENT | REMOVAL OF TEMPORARY / EMERGENCY ACCOUNTS The information system automatically disables temporary and emergency accounts after no more than 30 days for both temporary and emergency accounts. | D8: Description du contrôle | E8: GESTION DES COMPTES | RETRAIT DES COMPTES TEMPORAIRES/D’URGENCE Le système d’information désactive automatiquement les comptes temporaires et d’urgence après un maximum de 30 jours, pour les comptes temporaires comme pour les comptes d’urgence.
A9: Supplemental Guidance | B9: This control enhancement requires the removal of both temporary and emergency accounts automatically after a predefined period of time has elapsed, rather than at the convenience of the systems administrator. | D9: Directives supplémentaires | E9: Cette amélioration du contrôle exige le retrait automatique des comptes temporaires et d’urgence au terme d’une période prédéfinie, plutôt qu’à la convenance de l’administrateur des systèmes.
A10: Test Case | D10: Cas de test
A11: Test | B11: TEST-AC-2(2) | D11: Test | E11: TEST-AC-2(2)
A12: Requirement ID | B12: AC-2(2) | D12: ID Exigence | E12: AC-2(2)
A13: Component | D13: Composant
A14: Requirement | D14: Exigence
A15: Contextual Design Description | D15: Description contextuelle du design
A16: Evidence Provided | D16: Preuve fournie
A17: Preparer Sign Off (Initials, Date) | D17: Signataire préparateur (Initiales, Date)
A18: Owner Sign Off (Initials, Date) | D18: Signataire propriétaire (Initiales, Date)
A19: Assessor Sign Off (Initials, Date) | D19: Signataire évaluateur (Initiales, Date)
A20: Status | B20: Not Started | D20: Statut | E20: Non commencé
A21: Comments | D21: Commentaires

Sheet AC-2-3
A1: Control AC-2(3) — Evidence Tracking | D1: Contrôle AC-2(3) — Suivi des preuves
A2: Control Information | D2: Informations du contrôle
A3: Control Identifier | B3: AC-2(3) | D3: Identifiant du contrôle | E3: AC-2(3)
A4: Family | B4: Account Management | D4: Famille | E4: Gestion des comptes
A5: Profile | B5: CCCS Medium / PBMM Moderate | D5: Profil | E5: CCCS Moyen / PBMM Modéré
A6: Primary Evidence Tool | D6: Outil de preuve principal
A7: Contributing Tools | D7: Outils contributeurs
A8: Control Description | B8: ACCOUNT MANAGEMENT | DISABLE INACTIVE ACCOUNTS The information system automatically disables inactive accounts after 90 days. | D8: Description du contrôle | E8: GESTION DES COMPTES | DÉSACTIVATION DES COMPTES INACTIFS Le système d’information désactive automatiquement les comptes après 90 jours d’inactivité.
A9: Supplemental Guidance | D9: Directives supplémentaires
A10: Test Case | D10: Cas de test
A11: Test | B11: TEST-AC-2(3) | D11: Test | E11: TEST-AC-2(3)
A12: Requirement ID | B12: AC-2(3) | D12: ID Exigence | E12: AC-2(3)
A13: Component | D13: Composant
A14: Requirement | D14: Exigence
A15: Contextual Design Description | D15: Description contextuelle du design
A16: Evidence Provided | D16: Preuve fournie
A17: Preparer Sign Off (Initials, Date) | D17: Signataire préparateur (Initiales, Date)
A18: Owner Sign Off (Initials, Date) | D18: Signataire propriétaire (Initiales, Date)
A19: Assessor Sign Off (Initials, Date) | D19: Signataire évaluateur (Initiales, Date)
A20: Status | B20: Not Started | D20: Statut | E20: Non commencé
A21: Comments | D21: Commentaires

Sheet AC-2-4
A1: Control AC-2(4) — Evidence Tracking | D1: Contrôle AC-2(4) — Suivi des preuves
A2: Control Information | D2: Informations du contrôle
A3: Control Identifier | B3: AC-2(4) | D3: Identifiant du contrôle | E3: AC-2(4)
A4: Family | B4: Account Management | D4: Famille | E4: Gestion des comptes
A5: Profile | B5: CCCS Medium / PBMM Moderate | D5: Profil | E5: CCCS Moyen / PBMM Modéré
A6: Primary Evidence Tool | D6: Outil de preuve principal
A7: Contributing Tools | D7: Outils contributeurs
A8: Control Description | B8: ACCOUNT MANAGEMENT | AUTOMATED AUDIT ACTIONS The information system automatically audits account creation, modification, enabling, disabling, and removal actions, and notifies responsible managers. Related controls: AU-2, AU-12. | D8: Description du contrôle | E8: GESTION DES COMPTES | MESURES DE VÉRIFICATION AUTOMATISÉES Le système d’information vérifie automatiquement les opérations de création, de modification, d’activation, de désactivation et de retrait des comptes, et avise les gestionnaires responsables. Contrôles connexes : AU-2, AU-12.
A9: Supplemental Guidance | D9: Directives supplémentaires
A10: Test Case | D10: Cas de test
A11: Test | B11: TEST-AC-2(4) | D11: Test | E11: TEST-AC-2(4)
A12: Requirement ID | B12: AC-2(4) | D12: ID Exigence | E12: AC-2(4)
A13: Component | D13: Composant
A14: Requirement | D14: Exigence
A15: Contextual Design Description | D15: Description contextuelle du design
A16: Evidence Provided | D16: Preuve fournie
A17: Preparer Sign Off (Initials, Date) | D17: Signataire préparateur (Initiales, Date)
A18: Owner Sign Off (Initials, Date) | D18: Signataire propriétaire (Initiales, Date)
A19: Assessor Sign Off (Initials, Date) | D19: Signataire évaluateur (Initiales, Date)
A20: Status | B20: Not Started | D20: Statut | E20: Non commencé
A21: Comments | D21: Commentaires

Sheet AC-2-5
A1: Control AC-2(5) — Evidence Tracking | D1: Contrôle AC-2(5) — Suivi des preuves
A2: Control Information | D2: Informations du contrôle
A3: Control Identifier | B3: AC-2(5) | D3: Identifiant du contrôle | E3: AC-2(5)
A4: Family | B4: Account Management | D4: Famille | E4: Gestion des comptes
A5: Profile | B5: CCCS Medium / PBMM Moderate | D5: Profil | E5: CCCS Moyen / PBMM Modéré
A6: Primary Evidence Tool | D6: Outil de preuve principal
A7: Contributing Tools | D7: Outils contributeurs
A8: Control Description | B8: ACCOUNT MANAGEMENT | INACTIVITY LOGOUT The organization requires that users log out at the end of the users’ standard work period unless otherwise defined in formal organizational policy. Related controls: SC-23 | D8: Description du contrôle | E8: GESTION DES COMPTES | FERMETURE DE SESSION INACTIVE L’organisation exige que les utilisateurs ferment leur session à la fin de leur période de travail normale, à moins d’indication contraire dans la politique officielle de l’organisation. Contrôles connexes : SC-23
A9: Supplemental Guidance | D9: Directives supplémentaires
A10: Test Case | D10: Cas de test
A11: Test | B11: TEST-AC-2(5) | D11: Test | E11: TEST-AC-2(5)
A12: Requirement ID | B12: AC-2(5) | D12: ID Exigence | E12: AC-2(5)
A13: Component | D13: Composant
A14: Requirement | D14: Exigence
A15: Contextual Design Description | D15: Description contextuelle du design
A16: Evidence Provided | D16: Preuve fournie
A17: Preparer Sign Off (Initials, Date) | D17: Signataire préparateur (Initiales, Date)
A18: Owner Sign Off (Initials, Date) | D18: Signataire propriétaire (Initiales, Date)
A19: Assessor Sign Off (Initials, Date) | D19: Signataire évaluateur (Initiales, Date)
A20: Status | B20: Not Started | D20: Statut | E20: Non commencé
A21: Comments | D21: Commentaires

Sheet AC-2-7
A1: Control AC-2(7) — Evidence Tracking | D1: Contrôle AC-2(7) — Suivi des preuves
A2: Control Information | D2: Informations du contrôle
A3: Control Identifier | B3: AC-2(7) | D3: Identifiant du contrôle | E3: AC-2(7)
A4: Family | B4: Account Management | D4: Famille | E4: Gestion des comptes
A5: Profile | B5: CCCS Medium / PBMM Moderate | D5: Profil | E5: CCCS Moyen / PBMM Modéré
A6: Primary Evidence Tool | D6: Outil de preuve principal
A7: Contributing Tools | D7: Outils contributeurs
A8: Control Description | B8: ACCOUNT MANAGEMENT | ROLE-BASED SCHEMES (a) The organization establishes and administers privileged user accounts in accordance with a role-based access scheme that organizes allowed information system access and privileges into roles; (b) The organization monitors privileged role assignments; and (c) The organization disables (or revokes) privileged user assignments within 24 hours or sooner when privileged role assignments are no longer appropriate. | D8: Description du contrôle | E8: GESTION DES COMPTES | SCHÉMAS FONDÉS SUR LES RÔLES (a) L’organisation établit et administre les comptes d’utilisateurs privilégiés conformément à un système d’accès basé sur les rôles qui organise les autorisations d’accès au système d’information et les privilèges en fonction des rôles; (b) L’organisation surveille les affectations de rôles privilégiés; (c) L’organisation désactive (ou révoque) les affectations d’utilisateurs privilégiés dans les 24 heures ou plus lorsque les affectations de rôles privilégiés ne sont plus appropriées.
A9: Supplemental Guidance | B9: Privileged roles are organization-defined roles assigned to individuals that allow those individuals to perform certain security-relevant functions that ordinary users are not authorized to perform. These privileged roles include, for example, key management, account management, network and system administration, database administration, and web administration. | D9: Directives supplémentaires | E9: Les rôles privilégiés sont des rôles définis par l’organisation et attribués à des personnes pour leur permettre d’exécuter certaines fonctions ayant une influence sur la sécurité que les utilisateurs ordinaires ne sont pas autorisés à exécuter. Ces rôles privilégiés comprennent, par exemple, la gestion des clés, la gestion des comptes, l’administration des réseaux et des systèmes, l’administration des bases de données et l’administration Web.
A10: Test Case | D10: Cas de test
A11: Test | B11: TEST-AC-2(7) | D11: Test | E11: TEST-AC-2(7)
A12: Requirement ID | B12: AC-2(7) | D12: ID Exigence | E12: AC-2(7)
A13: Component | D13: Composant
A14: Requirement | D14: Exigence
A15: Contextual Design Description | D15: Description contextuelle du design
A16: Evidence Provided | D16: Preuve fournie
A17: Preparer Sign Off (Initials, Date) | D17: Signataire préparateur (Initiales, Date)
A18: Owner Sign Off (Initials, Date) | D18: Signataire propriétaire (Initiales, Date)
A19: Assessor Sign Off (Initials, Date) | D19: Signataire évaluateur (Initiales, Date)
A20: Status | B20: Not Started | D20: Statut | E20: Non commencé
A21: Comments | D21: Commentaires

Sheet AC-6
A1: Control AC-6 — Evidence Tracking | D1: Contrôle AC-6 — Suivi des preuves
A2: Control Information | D2: Informations du contrôle
A3: Control Identifier | B3: AC-6 | D3: Identifiant du contrôle | E3: AC-6
A4: Family | B4: Least Privilege | D4: Famille | E4: Moindre privilège
A5: Profile | B5: CCCS Medium / PBMM Moderate | D5: Profil | E5: CCCS Moyen / PBMM Modéré
A6: Primary Evidence Tool | D6: Outil de preuve principal
A7: Contributing Tools | D7: Outils contributeurs
A8: Control Description | B8: (A) The organization employs the principle of least privilege, allowing only authorized accesses for users (or processes acting on behalf of users) which are necessary to accomplish assigned tasks in accordance with organizational missions and business functions. | D8: Description du contrôle | E8: (A) L’organisation utilise le principe du moindre privilège, qui permet seulement les accès autorisés aux utilisateurs (ou aux processus qui agissent pour le compte des utilisateurs) qui sont nécessaires pour accomplir les tâches assignées conformément aux missions et aux fonctions opérationnelles de l’organisation.
A9: Supplemental Guidance | B9: Organizations employ least privilege for specific duties and information systems. The principle of least privilege is also applied to information system processes, ensuring that the processes operate at privilege levels no higher than necessary to accomplish required organizational missions/business functions. Organizations consider the creation of additional processes, roles, and information system accounts as necessary, to achieve least privilege. Organizations also apply least privilege to the development, implementation, and operation of organizational information systems. Related controls: AC-2, AC-3, AC-5, CM-6, CM-7, PL-2 | D9: Directives supplémentaires | E9: Les organisations utilisent le moindre privilège pour certaines tâches et certains systèmes d’information. Le principe du moindre privilège s’applique également aux processus du système d’information, ce qui fait en sorte que les processus ne fonctionnent pas à des niveaux de privilège plus élevés que nécessaire pour accomplir les missions et les fonctions opérationnelles requises de l’organisation. Les organisations envisagent la création de processus, de rôles et de comptes de système d’information supplémentaires lorsque nécessaire, pour obtenir le moindre privilège. Les organisations appliquent également le moindre privilège au développement, à la mise en œuvre et à l’exploitation de leurs systèmes d’information. Contrôles connexes : AC-2, AC-3, AC-5, CM-6, CM-7, PL-2
A10: Test Case | D10: Cas de test
A11: Test | B11: TEST-AC-6 | D11: Test | E11: TEST-AC-6
A12: Requirement ID | B12: AC-6 | D12: ID Exigence | E12: AC-6
A13: Component | D13: Composant
A14: Requirement | D14: Exigence
A15: Contextual Design Description | D15: Description contextuelle du design
A16: Evidence Provided | D16: Preuve fournie
A17: Preparer Sign Off (Initials, Date) | D17: Signataire préparateur (Initiales, Date)
A18: Owner Sign Off (Initials, Date) | D18: Signataire propriétaire (Initiales, Date)
A19: Assessor Sign Off (Initials, Date) | D19: Signataire évaluateur (Initiales, Date)
A20: Status | B20: Not Started | D20: Statut | E20: Non commencé
A21: Comments | D21: Commentaires

Sheet AC-6-1
A1: Control AC-6(1) — Evidence Tracking | D1: Contrôle AC-6(1) — Suivi des preuves
A2: Control Information | D2: Informations du contrôle
A3: Control Identifier | B3: AC-6(1) | D3: Identifiant du contrôle | E3: AC-6(1)
A4: Family | B4: Least Privilege | D4: Famille | E4: Moindre privilège
A5: Profile | B5: CCCS Medium / PBMM Moderate | D5: Profil | E5: CCCS Moyen / PBMM Modéré
A6: Primary Evidence Tool | D6: Outil de preuve principal
A7: Contributing Tools | D7: Outils contributeurs
A8: Control Description | B8: LEAST PRIVILEGE | AUTHORIZE ACCESS TO SECURITY FUNCTIONS The organization explicitly authorizes access to all security functions not publicly accessible and all security-relevant information not publicly available. | D8: Description du contrôle | E8: MOINDRE PRIVILÈGE | AUTORISATION D’ACCÈS AUX FONCTIONS DE SÉCURITÉ L’organisation autorise explicitement l’accès à toutes les fonctions de sécurité qui ne sont pas accessibles au public et à toute l’information pertinente à la sécurité qui n’est pas accessible au public.
A9: Supplemental Guidance | B9: Security functions include, for example, establishing system accounts, configuring access authorizations (i.e., permissions, privileges), setting events to be audited, and setting intrusion detection parameters. Security-relevant information includes, for example, filtering rules for routers/firewalls, cryptographic key management information, configuration parameters for security services, and access control lists. Explicitly authorized personnel include, for example, security administrators, system and network administrators, system security officers, system maintenance personnel, system programmers, and other privileged users. Related controls: AC-17, AC-18, AC-19. | D9: Directives supplémentaires | E9: Les fonctions de sécurité comprennent, par exemple, l’établissement des comptes système, la configuration des autorisations d’accès (c.-à-d. les permissions, les privilèges), le réglage des événements à vérifier, et l’établissement des paramètres de détection des intrusions. Les renseignements pertinents pour la sécurité comprennent, par exemple, les règles de filtrage pour les routeurs/pare-feu, l’information de gestion des clés cryptographiques, les paramètres de configuration pour les services de sécurité et les listes de contrôle d’accès. Le personnel explicitement autorisé comprend, par exemple, les administrateurs de la sécurité, les administrateurs de systèmes et de réseaux, les agents de sécurité des systèmes, le personnel de maintenance des systèmes, les programmeurs de systèmes et d’autres utilisateurs privilégiés. Contrôles connexes : AC-17, AC-18, AC-19.
A10: Test Case | D10: Cas de test
A11: Test | B11: TEST-AC-6(1) | D11: Test | E11: TEST-AC-6(1)
A12: Requirement ID | B12: AC-6(1) | D12: ID Exigence | E12: AC-6(1)
A13: Component | D13: Composant
A14: Requirement | D14: Exigence
A15: Contextual Design Description | D15: Description contextuelle du design
A16: Evidence Provided | D16: Preuve fournie
A17: Preparer Sign Off (Initials, Date) | D17: Signataire préparateur (Initiales, Date)
A18: Owner Sign Off (Initials, Date) | D18: Signataire propriétaire (Initiales, Date)
A19: Assessor Sign Off (Initials, Date) | D19: Signataire évaluateur (Initiales, Date)
A20: Status | B20: Not Started | D20: Statut | E20: Non commencé
A21: Comments | D21: Commentaires

Sheet AC-6-9
A1: Control AC-6(9) — Evidence Tracking | D1: Contrôle AC-6(9) — Suivi des preuves
A2: Control Information | D2: Informations du contrôle
A3: Control Identifier | B3: AC-6(9) | D3: Identifiant du contrôle | E3: AC-6(9)
A4: Family | B4: Least Privilege | D4: Famille | E4: Moindre privilège
A5: Profile | B5: CCCS Medium / PBMM Moderate | D5: Profil | E5: CCCS Moyen / PBMM Modéré
A6: Primary Evidence Tool | D6: Outil de preuve principal
A7: Contributing Tools | D7: Outils contributeurs
A8: Control Description | B8: LEAST PRIVILEGE | AUDITING USE OF PRIVILEGED FUNCTIONS The information system audits the execution of privileged functions. | D8: Description du contrôle | E8: MOINDRE PRIVILÈGE | VÉRIFICATION DE L’UTILISATION DES FONCTIONS PRIVILÉGIÉES Le système d’information vérifie l’exécution des fonctions privilégiées.
A9: Supplemental Guidance | B9: Misuse of privileged functions, either intentionally or unintentionally by authorized users, or by unauthorized external entities that have compromised information system accounts, is a serious and ongoing concern and can have significant adverse impacts on organizations. Auditing the use of privileged functions is one way to detect such misuse, and in doing so, help mitigate the risk from insider threats and the advanced persistent threat (APT). Related control: AU-2. | D9: Directives supplémentaires | E9: L’utilisation abusive des fonctions privilégiées, intentionnellement ou non, par des utilisateurs autorisés ou par des entités externes non autorisées qui ont compromis des comptes de système d’information, est une préoccupation grave et constante qui peut avoir des répercussions négatives importantes sur les organisations. La vérification de l’utilisation des fonctions privilégiées est une façon de détecter un tel abus et, ce faisant, de contribuer à atténuer le risque de menaces internes et de menaces persistantes avancées (MPA). Contrôle connexe : AU-2.
A10: Test Case | D10: Cas de test
A11: Test | B11: TEST-AC-6(9) | D11: Test | E11: TEST-AC-6(9)
A12: Requirement ID | B12: AC-6(9) | D12: ID Exigence | E12: AC-6(9)
A13: Component | D13: Composant
A14: Requirement | D14: Exigence
A15: Contextual Design Description | D15: Description contextuelle du design
A16: Evidence Provided | D16: Preuve fournie
A17: Preparer Sign Off (Initials, Date) | D17: Signataire préparateur (Initiales, Date)
A18: Owner Sign Off (Initials, Date) | D18: Signataire propriétaire (Initiales, Date)
A19: Assessor Sign Off (Initials, Date) | D19: Signataire évaluateur (Initiales, Date)
A20: Status | B20: Not Started | D20: Statut | E20: Non commencé
A21: Comments | D21: Commentaires

Sheet AC-6-10
A1: Control AC-6(10) — Evidence Tracking | D1: Contrôle AC-6(10) — Suivi des preuves
A2: Control Information | D2: Informations du contrôle
A3: Control Identifier | B3: AC-6(10) | D3: Identifiant du contrôle | E3: AC-6(10)
A4: Family | B4: Least Privilege | D4: Famille | E4: Moindre privilège
A5: Profile | B5: CCCS Medium / PBMM Moderate | D5: Profil | E5: CCCS Moyen / PBMM Modéré
A6: Primary Evidence Tool | D6: Outil de preuve principal
A7: Contributing Tools | D7: Outils contributeurs
A8: Control Description | B8: LEAST PRIVILEGE | PROHIBIT NON-PRIVILEGED USERS FROM EXECUTING PRIVILEGED FUNCTIONS The information system prevents non-privileged users from executing privileged functions to include disabling, circumventing, or altering implemented security safeguards/countermeasures. | D8: Description du contrôle | E8: MOINDRE PRIVILÈGE | INTERDICTION AUX UTILISATEURS NON PRIVILÉGIÉS D’EXÉCUTER DES FONCTIONS PRIVILÉGIÉES Le système d’information empêche les utilisateurs non privilégiés d’exécuter des fonctions privilégiées, y compris la désactivation, le contournement ou la modification des mécanismes/contre-mesures de sécurité en place.
A9: Supplemental Guidance | B9: Privileged functions include, for example, establishing information system accounts, performing system integrity checks, or administering cryptographic key management activities. Non-privileged users are individuals that do not possess appropriate authorizations. Circumventing intrusion detection and prevention mechanisms or malicious code protection mechanisms are examples of privileged functions that require protection from non-privileged users. | D9: Directives supplémentaires | E9: Les fonctions privilégiées comprennent, par exemple, l’établissement des comptes du système d’information, l’exécution des vérifications de l’intégrité du système ou l’administration des activités de gestion de clés cryptographiques. Les utilisateurs non privilégiés sont des personnes qui ne possèdent pas les autorisations appropriées. Les contournements de mécanismes de détection et de prévention des intrusions ou de mécanismes de protection contre le code malveillant sont des exemples de fonctions privilégiées qui nécessitent une protection contre les utilisateurs non privilégiés.
A10: Test Case | D10: Cas de test
A11: Test | B11: TEST-AC-6(10) | D11: Test | E11: TEST-AC-6(10)
A12: Requirement ID | B12: AC-6(10) | D12: ID Exigence | E12: AC-6(10)
A13: Component | D13: Composant
A14: Requirement | D14: Exigence
A15: Contextual Design Description | D15: Description contextuelle du design
A16: Evidence Provided | D16: Preuve fournie
A17: Preparer Sign Off (Initials, Date) | D17: Signataire préparateur (Initiales, Date)
A18: Owner Sign Off (Initials, Date) | D18: Signataire propriétaire (Initiales, Date)
A19: Assessor Sign Off (Initials, Date) | D19: Signataire évaluateur (Initiales, Date)
A20: Status | B20: Not Started | D20: Statut | E20: Non commencé
A21: Comments | D21: Commentaires

Sheet AC-17-1
A1: Control AC-17(1) — Evidence Tracking | D1: Contrôle AC-17(1) — Suivi des preuves
A2: Control Information | D2: Informations du contrôle
A3: Control Identifier | B3: AC-17(1) | D3: Identifiant du contrôle | E3: AC-17(1)
A4: Family | B4: Remote Access | D4: Famille | E4: Accès à distance
A5: Profile | B5: CCCS Medium / PBMM Moderate | D5: Profil | E5: CCCS Moyen / PBMM Modéré
A6: Primary Evidence Tool | D6: Outil de preuve principal
A7: Contributing Tools | D7: Outils contributeurs
A8: Control Description | B8: REMOTE ACCESS | AUTOMATED MONITORING / CONTROL The information system monitors and controls remote access methods. | D8: Description du contrôle | E8: ACCÈS À DISTANCE | SURVEILLANCE ET CONTRÔLE AUTOMATISÉS Le système d’information surveille et contrôle les méthodes d’accès à distance.
A9: Supplemental Guidance | B9: Automated monitoring and control of remote access sessions allows organizations to detect cyber-attacks and also ensure ongoing compliance with remote access policies by auditing connection activities of remote users on a variety of information system components (e.g., servers, workstations, notebook computers, smart phones, and tablets). Related controls: AU-2, AU-12. | D9: Directives supplémentaires | E9: La surveillance et le contrôle automatisés des sessions avec accès à distance permettent aux organisations de détecter les cyberattaques et d’assurer la conformité continue aux politiques d’accès à distance en vérifiant les activités de connexion des utilisateurs distants sur une variété de composants du système d’information (p. ex., serveurs, postes de travail, ordinateurs portatifs, téléphones intelligents et tablettes). Contrôles connexes : AU-2, AU-12.
A10: Test Case | D10: Cas de test
A11: Test | B11: TEST-AC-17(1) | D11: Test | E11: TEST-AC-17(1)
A12: Requirement ID | B12: AC-17(1) | D12: ID Exigence | E12: AC-17(1)
A13: Component | D13: Composant
A14: Requirement | D14: Exigence
A15: Contextual Design Description | D15: Description contextuelle du design
A16: Evidence Provided | D16: Preuve fournie
A17: Preparer Sign Off (Initials, Date) | D17: Signataire préparateur (Initiales, Date)
A18: Owner Sign Off (Initials, Date) | D18: Signataire propriétaire (Initiales, Date)
A19: Assessor Sign Off (Initials, Date) | D19: Signataire évaluateur (Initiales, Date)
A20: Status | B20: Not Started | D20: Statut | E20: Non commencé
A21: Comments | D21: Commentaires

Sheet AC-17-2
A1: Control AC-17(2) — Evidence Tracking | D1: Contrôle AC-17(2) — Suivi des preuves
A2: Control Information | D2: Informations du contrôle
A3: Control Identifier | B3: AC-17(2) | D3: Identifiant du contrôle | E3: AC-17(2)
A4: Family | B4: Remote Access | D4: Famille | E4: Accès à distance
A5: Profile | B5: CCCS Medium / PBMM Moderate | D5: Profil | E5: CCCS Moyen / PBMM Modéré
A6: Primary Evidence Tool | D6: Outil de preuve principal
A7: Contributing Tools | D7: Outils contributeurs
A8: Control Description | B8: REMOTE ACCESS | PROTECTION OF CONFIDENTIALITY / INTEGRITY USING ENCRYPTION The information system implements cryptographic mechanisms to protect the confidentiality and integrity of remote access sessions. The cryptography must be compliant with the requirements of SC-13. | D8: Description du contrôle | E8: ACCÈS À DISTANCE | PROTECTION DE LA CONFIDENTIALITÉ ET DE L’INTÉGRITÉ AU MOYEN DU CHIFFREMENT Le système d’information met en œuvre des mécanismes cryptographiques pour protéger la confidentialité et l’intégrité des sessions d’accès à distance. La cryptographie doit être conforme aux exigences de SC-13.
A9: Supplemental Guidance | B9: Guidance on the encryption strength of mechanism can be obtained from CSE upon request. | D9: Directives supplémentaires | E9: Le CST peut, sur demande, conseiller l’organisation quant à la puissance de chiffrement du mécanisme.
A10: Test Case | D10: Cas de test
A11: Test | B11: TEST-AC-17(2) | D11: Test | E11: TEST-AC-17(2)
A12: Requirement ID | B12: AC-17(2) | D12: ID Exigence | E12: AC-17(2)
A13: Component | D13: Composant
A14: Requirement | D14: Exigence
A15: Contextual Design Description | D15: Description contextuelle du design
A16: Evidence Provided | D16: Preuve fournie
A17: Preparer Sign Off (Initials, Date) | D17: Signataire préparateur (Initiales, Date)
A18: Owner Sign Off (Initials, Date) | D18: Signataire propriétaire (Initiales, Date)
A19: Assessor Sign Off (Initials, Date) | D19: Signataire évaluateur (Initiales, Date)
A20: Status | B20: Not Started | D20: Statut | E20: Non commencé
A21: Comments | D21: Commentaires

Sheet AU-2
A1: Control AU-2 — Evidence Tracking | D1: Contrôle AU-2 — Suivi des preuves
A2: Control Information | D2: Informations du contrôle
A3: Control Identifier | B3: AU-2 | D3: Identifiant du contrôle | E3: AU-2
A4: Family | B4: Auditable Events | D4: Famille | E4: Événements vérifiables
A5: Profile | B5: CCCS Medium / PBMM Moderate | D5: Profil | E5: CCCS Moyen / PBMM Modéré
A6: Primary Evidence Tool | D6: Outil de preuve principal
A7: Contributing Tools | D7: Outils contributeurs
A8: Control Description | B8: (A) The organization determines that the information system is capable of auditing the following events: Successful and unsuccessful account logon events, account management events, object access, policy change, privilege functions, process tracking, and system events. For Web applications: all administrator activity, authentication checks, authorization checks, data deletions, data access, data changes, and permission changes. (B) The organization coordinates the security audit function with other organizational entities requiring audit-related information to enhance mutual support and to help guide the selection of auditable events. (C) The organization provides a rationale for why the auditable events are deemed to be adequate to support after-the-fact investigations of security incidents. (D) The organization determines what organizationally-defined audited events (a subset of the auditable events defined in AU-2 a.) and the frequency of (or situation requiring) auditing for each identified event. | D8: Description du contrôle | E8: (A) L’organisation détermine que le système d’information est capable de vérifier les événements suivants : événements d’ouverture de compte, réussis ou non, événements de gestion de compte, accès aux objets, changement de politique, fonctions de privilèges, suivi des processus et événements du système. Pour les applications Web : toutes les activités des administrateurs, les vérifications d’authentification, les vérifications d’autorisation, les suppressions de données, l’accès aux données, les changements de données et les changements d’autorisation. (B) L’organisation coordonne la fonction de vérification de la sécurité avec d’autres entités organisationnelles qui ont besoin de renseignements liés à la vérification pour améliorer le soutien mutuel et aider à orienter le choix des événements vérifiables. (C) L’organisation explique la raison pour laquelle les événements vérifiables sont jugés adéquats pour appuyer les enquêtes effectuées à la suite des incidents de sécurité. (D) L’organisation détermine les événements définis par l’organisation qui sont vérifiés (un sous-ensemble des événements vérifiables définis dans AU-2 a.) et la fréquence (ou la situation exigeant) des vérifications pour chaque événement identifié.
A9: Supplemental Guidance | B9: An event is any observable occurrence in an organizational information system. Organizations identify audit events as those events which are significant and relevant to the security of information systems and the environments in which those systems operate in order to meet specific and ongoing audit needs. Audit events can include, for example, password changes, failed logons, or failed accesses related to information systems, administrative privilege usage, or third-party credential usage. In determining the set of auditable events, organizations consider the auditing appropriate for each of the security controls to be implemented. To balance auditing requirements with other information system needs, this control also requires identifying that subset of auditable events that are audited at a given point in time. For example, organizations may determine that information systems must have the capability to log every file access both successful and unsuccessful, but not activate that capability except for specific circumstances due to the potential burden on system performance. Auditing requirements, including the need for auditable events, may be referenced in other security controls and control enhancements. Organizations also include auditable events that are required by applicable organizational policies, directives, and standards. Audit records can be generated at various levels of abstraction, including at the packet level as information traverses the network. Selecting the appropriate level of abstraction is a critical aspect of an audit capability and can facilitate the identification of root causes to problems. Organizations consider in the definition of auditable events, the auditing necessary to cover related events such as the steps in distributed, transaction-based processes (e.g., processes that are distributed across multiple organizations) and actions that occur in service-oriented architectures. The information system audits the following privileged user/process events at a minimum: (a) Successful and unsuccessful attempts to access, modify, or delete security objects (Security objects include audit data, system configuration files and file or users’ formal access permissions.) (b) Successful and unsuccessful logon attempts (c) Privileged activities or other system level access (see notes for AU-2 (4)) (d) Starting and ending time for user access to the system (e) Concurrent logons from different workstations (f) All program initiations (see notes for AU-2 (4)) In addition, the information system audits the following unprivileged user/process events at a minimum: (a) Successful and unsuccessful attempts to access, modify, or delete security objects (b) Successful and unsuccessful logon attempts (c) Starting and ending time for user access to the system (d) Concurrent logons from different workstations Related controls: AC-6, AC-17, AU-3, AU-12, MA-4, MP-2, MP-4, SI-4 | D9: Directives supplémentaires | E9: Un événement est toute occurrence observable dans un système d’information organisationnel. Les organisations désignent les événements vérifiables comme étant des événements importants et pertinents pour la sécurité des systèmes d’information et des environnements dans lesquels ces systèmes sont utilisés afin de répondre à des exigences de vérification particulières et continues. Les événements vérifiés peuvent comprendre, par exemple, les changements de mot de passe, les échecs d’ouverture de session ou les échecs accès liés aux systèmes d’information, l’utilisation des privilèges administratifs ou l’utilisation de justificatifs d’identité par des tiers. Lorsqu’elles déterminent l’ensemble des événements vérifiables, les organisations considèrent que la vérification est appropriée pour chacun des contrôles de sécurité à mettre en œuvre. Pour assurer l’équilibre entre les exigences en matière de vérification et les autres besoins du système d’information, ce contrôle exige également de déterminer le sous-ensemble d’événements vérifiables qui sont vérifiés à un moment donné. Par exemple, les organisations peuvent déterminer que les systèmes d’information doivent avoir la capacité d’enregistrer chaque accès aux fichiers, qu’il soit réussi ou non, mais n’activeront cette capacité que dans des circonstances particulières en raison du fardeau potentiel sur le rendement du système. Les exigences en matière de vérification, y compris la nécessité de déterminer des événements vérifiables, peuvent être mentionnées dans d’autres contrôles et améliorations des contrôles de sécurité. Les organisations incluent également les événements vérifiables qui sont exigés par les politiques, les directives et les normes organisationnelles applicables. Les enregistrements de vérification peuvent être générés à divers niveaux d’abstraction, y compris au niveau des paquets, à mesure que l’information traverse le réseau. Le choix du niveau d’abstraction approprié est un aspect essentiel d’une capacité de vérification et peut faciliter l’identification des causes profondes des problèmes. Dans la définition des événements vérifiables, les organisations prennent en compte la vérification nécessaire pour couvrir les événements connexes, comme les étapes des processus distribués, fondés sur les transactions (p. ex., les processus qui sont répartis entre de multiples organisations) et les actions qui ont lieu dans les architectures orientées service. Le système d’information vérifie au minimum les événements suivants liés aux utilisateurs/processus privilégiés : (a) Tentatives réussies et infructueuses d’accéder aux objets de sécurité, de les modifier ou de les supprimer (les objets de sécurité comprennent les données de vérification, les fichiers de configuration de système et les autorisations d’accès officielles des utilisateurs). (b) Tentatives d’ouverture de session réussies et infructueuses (c) Activités privilégiées ou autre accès au niveau du système (voir les notes pour AU-2 [4]) (d) Heures de début et de fin de l’accès des utilisateurs au système (e) Ouvertures de session simultanées à partir de différents postes de travail (f) Tous les lancements de programmes (voir les notes pour AU-2 [4]) De plus, le système d’information vérifie au minimum les événements suivants liés aux utilisateurs/processus non privilégiés : (a) Tentatives réussies et infructueuses d’accès, de modification ou de suppression d’objets de sécurité (b) Tentatives d’ouverture de session réussies et infructueuses (c) Heures de début et de fin de l’accès de l’utilisateur au système (d) Ouvertures de session simultanées à partir de différents postes de travail Contrôles connexes : AC-6, AC-17, AU-3, AU-12, MA-4, MP-2, MP-4, SI-4
A10: Test Case | D10: Cas de test
A11: Test | B11: TEST-AU-2 | D11: Test | E11: TEST-AU-2
A12: Requirement ID | B12: AU-2 | D12: ID Exigence | E12: AU-2
A13: Component | D13: Composant
A14: Requirement | D14: Exigence
A15: Contextual Design Description | D15: Description contextuelle du design
A16: Evidence Provided | D16: Preuve fournie
A17: Preparer Sign Off (Initials, Date) | D17: Signataire préparateur (Initiales, Date)
A18: Owner Sign Off (Initials, Date) | D18: Signataire propriétaire (Initiales, Date)
A19: Assessor Sign Off (Initials, Date) | D19: Signataire évaluateur (Initiales, Date)
A20: Status | B20: Not Started | D20: Statut | E20: Non commencé
A21: Comments | D21: Commentaires

Sheet AU-3
A1: Control AU-3 — Evidence Tracking | D1: Contrôle AU-3 — Suivi des preuves
A2: Control Information | D2: Informations du contrôle
A3: Control Identifier | B3: AU-3 | D3: Identifiant du contrôle | E3: AU-3
A4: Family | B4: Content of Audit Records | D4: Famille | E4: Contenu des enregistrements de vérification
A5: Profile | B5: CCCS Medium / PBMM Moderate | D5: Profil | E5: CCCS Moyen / PBMM Modéré
A6: Primary Evidence Tool | D6: Outil de preuve principal
A7: Contributing Tools | D7: Outils contributeurs
A8: Control Description | B8: (A) The information system generates audit records containing information that establishes what type of event occurred, when the event occurred, where the event occurred, the source of the event, the outcome of the event, and the identity of any individuals or subjects associated with the event. | D8: Description du contrôle | E8: (A) Le système d’information génère des enregistrements de vérification qui contiennent les renseignements permettant d’établir le type d’événement qui a eu lieu, le moment et l’endroit où l’événement a eu lieu, la source de l’événement, le résultat de l’événement, ainsi que l’identité de toute personne ou de tout sujet associé à l’événement.
A9: Supplemental Guidance | B9: Audit record content that may be necessary to satisfy the requirement of this control, includes, for example, time stamps, source and destination addresses, user/process identifiers, event descriptions, success/fail indications, filenames involved, and access control or flow control rules invoked. Event outcomes can include indicators of event success or failure and event-specific results (e.g., the security state of the information system after the event occurred). Related controls: AU-2, AU-8, AU-12, SI-11 | D9: Directives supplémentaires | E9: Le contenu des enregistrements de vérification qui peut être nécessaire pour satisfaire à l’exigence de ce contrôle comprend, par exemple, les estampilles temporelles, les adresses de source et de destination, les identifiants d’utilisateurs ou de processus, les descriptions d’événements, les indications de réussite ou d’échec, les noms des fichiers en cause et les règles de contrôle d’accès ou de flux invoquées. Les résultats de l’événement peuvent comprendre des indicateurs de réussite ou d’échec de l’événement et des résultats propres à l’événement (p. ex., l’état de sécurité du système d’information après l’événement). Contrôles connexes : AU-2, AU-8, AU-12, SI-11
A10: Test Case | D10: Cas de test
A11: Test | B11: TEST-AU-3 | D11: Test | E11: TEST-AU-3
A12: Requirement ID | B12: AU-3 | D12: ID Exigence | E12: AU-3
A13: Component | D13: Composant
A14: Requirement | D14: Exigence
A15: Contextual Design Description | D15: Description contextuelle du design
A16: Evidence Provided | D16: Preuve fournie
A17: Preparer Sign Off (Initials, Date) | D17: Signataire préparateur (Initiales, Date)
A18: Owner Sign Off (Initials, Date) | D18: Signataire propriétaire (Initiales, Date)
A19: Assessor Sign Off (Initials, Date) | D19: Signataire évaluateur (Initiales, Date)
A20: Status | B20: Not Started | D20: Statut | E20: Non commencé
A21: Comments | D21: Commentaires

Sheet AU-3-1
A1: Control AU-3(1) — Evidence Tracking | D1: Contrôle AU-3(1) — Suivi des preuves
A2: Control Information | D2: Informations du contrôle
A3: Control Identifier | B3: AU-3(1) | D3: Identifiant du contrôle | E3: AU-3(1)
A4: Family | B4: Content of Audit Records | D4: Famille | E4: Contenu des enregistrements de vérification
A5: Profile | B5: CCCS Medium / PBMM Moderate | D5: Profil | E5: CCCS Moyen / PBMM Modéré
A6: Primary Evidence Tool | D6: Outil de preuve principal
A7: Contributing Tools | D7: Outils contributeurs
A8: Control Description | B8: CONTENT OF AUDIT RECORDS | ADDITIONAL AUDIT INFORMATION The information system generates audit records containing the following additional information: session, connection, transaction, or activity duration; for client-server transactions, the number of bytes received and bytes sent; additional informational messages to diagnose or identify the event; characteristics that describe or identify the object or resource being acted upon. | D8: Description du contrôle | E8: CONTENU DES ENREGISTREMENTS DE VÉRIFICATION | RENSEIGNEMENTS DE VÉRIFICATION SUPPLÉMENTAIRES Le système d’information génère des enregistrements de vérification contenant les renseignements supplémentaires suivants : la durée de la session, de la connexion, de la transaction ou de l’activité; pour les transactions client-serveur, le nombre d’octets reçus et d’octets envoyés; des messages d’information supplémentaires pour diagnostiquer ou identifier l’événement; les caractéristiques qui décrivent ou identifient l’objet ou la ressource concernés.
A9: Supplemental Guidance | B9: Detailed information that organizations may consider in audit records includes, for example, full text recording of privileged commands or the individual identities of group account users. Organizations consider limiting the additional audit information to only that information explicitly needed for specific audit requirements. This facilitates the use of audit trails and audit logs by not including information that could potentially be misleading or could make it more difficult to locate information of interest. Additional guidance for enhancement (1): Audit events should always be capable of being associated with an individual identity. Associating audit events with a group or role is insufficient. | D9: Directives supplémentaires | E9: Les renseignements détaillés dont les organisations peuvent tenir compte dans les enregistrements de vérification comprennent, par exemple, l’enregistrement en texte intégral des commandes privilégiées ou les identités individuelles des utilisateurs de comptes de groupe. Les organisations devraient envisager de limiter les renseignements de vérification supplémentaires aux seuls renseignements explicitement nécessaires pour répondre à des exigences de vérification particulières. Cela facilitera l’utilisation des pistes de vérification et des journaux de vérification en n’incluant pas les renseignements qui pourraient être trompeurs ou rendre plus difficile la recherche de renseignements utiles. Conseils supplémentaires pour l’amélioration (1) : Les événements vérifiés devraient toujours pouvoir être associés à une identité individuelle. Associer des événements vérifiés à un groupe ou à un rôle est insuffisant.
A10: Test Case | D10: Cas de test
A11: Test | B11: TEST-AU-3(1) | D11: Test | E11: TEST-AU-3(1)
A12: Requirement ID | B12: AU-3(1) | D12: ID Exigence | E12: AU-3(1)
A13: Component | D13: Composant
A14: Requirement | D14: Exigence
A15: Contextual Design Description | D15: Description contextuelle du design
A16: Evidence Provided | D16: Preuve fournie
A17: Preparer Sign Off (Initials, Date) | D17: Signataire préparateur (Initiales, Date)
A18: Owner Sign Off (Initials, Date) | D18: Signataire propriétaire (Initiales, Date)
A19: Assessor Sign Off (Initials, Date) | D19: Signataire évaluateur (Initiales, Date)
A20: Status | B20: Not Started | D20: Statut | E20: Non commencé
A21: Comments | D21: Commentaires

Sheet AU-5
A1: Control AU-5 — Evidence Tracking | D1: Contrôle AU-5 — Suivi des preuves
A2: Control Information | D2: Informations du contrôle
A3: Control Identifier | B3: AU-5 | D3: Identifiant du contrôle | E3: AU-5
A4: Family | B4: Response To Audit Processing Failures | D4: Famille | E4: Réponse aux échecs de traitement de vérification
A5: Profile | B5: CCCS Medium / PBMM Moderate | D5: Profil | E5: CCCS Moyen / PBMM Modéré
A6: Primary Evidence Tool | D6: Outil de preuve principal
A7: Contributing Tools | D7: Outils contributeurs
A8: Control Description | B8: (A) The information system alerts organization-defined personnel or roles in the event of an audit processing failure; and (B) The information system overwrites the oldest audit records. | D8: Description du contrôle | E8: (A) Le système d’information alerte le personnel ou les rôles définis par l’organisation en cas d’échec de traitement de vérification; (B) Le système d’information écrase les enregistrements de vérification les plus anciens.
A9: Supplemental Guidance | B9: Audit processing failures include, for example, software/hardware errors, failures in the audit capturing mechanisms, and audit storage capacity being reached or exceeded. Organizations may choose to define additional actions for different audit processing failures (e.g., by type, by location, by severity, or a combination of such factors). This control applies to each audit data storage repository (i.e., distinct information system component where audit records are stored), the total audit storage capacity of organizations (i.e., all audit data storage repositories combined), or both. Related controls: AU-4, SI-12 | D9: Directives supplémentaires | E9: Les échecs de traitement de vérification comprennent, par exemple, les erreurs de logiciel ou de matériel, les défaillances des mécanismes de saisie des vérifications et la capacité de stockage atteinte ou dépassée pour les vérifications. Les organisations peuvent choisir de définir des mesures supplémentaires pour différents échecs de traitement de vérification (p. ex., par type, par emplacement, par gravité ou une combinaison de ces facteurs). Ce contrôle s’applique à chaque répertoire de stockage des données de vérification (c.-à -d. à chaque composant distinct du système d’information dans lequel les enregistrements de vérification sont conservés), à la capacité totale de stockage des vérifications des organisations (c.-à-d. tous les répertoires de stockage des données de vérification combinés), ou aux deux. Contrôles connexes : AU-4, SI-12
A10: Test Case | D10: Cas de test
A11: Test | B11: TEST-AU-5 | D11: Test | E11: TEST-AU-5
A12: Requirement ID | B12: AU-5 | D12: ID Exigence | E12: AU-5
A13: Component | D13: Composant
A14: Requirement | D14: Exigence
A15: Contextual Design Description | D15: Description contextuelle du design
A16: Evidence Provided | D16: Preuve fournie
A17: Preparer Sign Off (Initials, Date) | D17: Signataire préparateur (Initiales, Date)
A18: Owner Sign Off (Initials, Date) | D18: Signataire propriétaire (Initiales, Date)
A19: Assessor Sign Off (Initials, Date) | D19: Signataire évaluateur (Initiales, Date)
A20: Status | B20: Not Started | D20: Statut | E20: Non commencé
A21: Comments | D21: Commentaires

Sheet AU-6-1
A1: Control AU-6(1) — Evidence Tracking | D1: Contrôle AU-6(1) — Suivi des preuves
A2: Control Information | D2: Informations du contrôle
A3: Control Identifier | B3: AU-6(1) | D3: Identifiant du contrôle | E3: AU-6(1)
A4: Family | B4: Audit Review, Analysis, and Reporting | D4: Famille | E4: Examen, analyse et rapport de vérification
A5: Profile | B5: CCCS Medium / PBMM Moderate | D5: Profil | E5: CCCS Moyen / PBMM Modéré
A6: Primary Evidence Tool | D6: Outil de preuve principal
A7: Contributing Tools | D7: Outils contributeurs
A8: Control Description | B8: AUDIT REVIEW, ANALYSIS, AND REPORTING | PROCESS INTEGRATION The organization employs automated mechanisms to integrate audit review, analysis, and reporting processes to support organizational processes for investigation and response to suspicious activities. | D8: Description du contrôle | E8: EXAMEN, ANALYSE ET RAPPORT DE VÉRIFICATION | INTÉGRATION DES PROCESSUS L’organisation utilise des mécanismes automatisés pour intégrer les processus d’examen, d’analyse et de production de rapports de vérification afin de soutenir les processus organisationnels d’enquête et d’intervention en cas d’activités suspectes.
A9: Supplemental Guidance | B9: Organizational processes benefiting from integrated audit review, analysis, and reporting include, for example, incident response, continuous monitoring, and contingency planning. Related control: AU-12. | D9: Directives supplémentaires | E9: Les processus organisationnels qui bénéficient de l’intégration de l’examen, de l’analyse et de la production de rapports de vérification sont notamment l’intervention en cas d’incident, la surveillance continue et la planification d’urgence. Contrôle connexe : AU-12.
A10: Test Case | D10: Cas de test
A11: Test | B11: TEST-AU-6(1) | D11: Test | E11: TEST-AU-6(1)
A12: Requirement ID | B12: AU-6(1) | D12: ID Exigence | E12: AU-6(1)
A13: Component | D13: Composant
A14: Requirement | D14: Exigence
A15: Contextual Design Description | D15: Description contextuelle du design
A16: Evidence Provided | D16: Preuve fournie
A17: Preparer Sign Off (Initials, Date) | D17: Signataire préparateur (Initiales, Date)
A18: Owner Sign Off (Initials, Date) | D18: Signataire propriétaire (Initiales, Date)
A19: Assessor Sign Off (Initials, Date) | D19: Signataire évaluateur (Initiales, Date)
A20: Status | B20: Not Started | D20: Statut | E20: Non commencé
A21: Comments | D21: Commentaires

Sheet AU-6-3
A1: Control AU-6(3) — Evidence Tracking | D1: Contrôle AU-6(3) — Suivi des preuves
A2: Control Information | D2: Informations du contrôle
A3: Control Identifier | B3: AU-6(3) | D3: Identifiant du contrôle | E3: AU-6(3)
A4: Family | B4: Audit Review, Analysis, and Reporting | D4: Famille | E4: Examen, analyse et rapport de vérification
A5: Profile | B5: CCCS Medium / PBMM Moderate | D5: Profil | E5: CCCS Moyen / PBMM Modéré
A6: Primary Evidence Tool | D6: Outil de preuve principal
A7: Contributing Tools | D7: Outils contributeurs
A8: Control Description | B8: AUDIT REVIEW, ANALYSIS, AND REPORTING | CORRELATE AUDIT REPOSITORIES The organization analyzes and correlates audit records across different repositories to gain organization-wide situational awareness. | D8: Description du contrôle | E8: EXAMEN, ANALYSE ET RAPPORT DE VÉRIFICATION | MISE EN CORRÉLATION DES RÉPERTOIRES DE VÉRIFICATION L’organisation analyse et met en corrélation les enregistrements de vérification entre les différents répertoires afin d’acquérir une connaissance globale de la situation dans l’ensemble de l’organisation.
A9: Supplemental Guidance | B9: Organization-wide situational awareness includes awareness across all three tiers of risk management (i.e., organizational, mission/business process, and information system) and supports cross-organization awareness. Related controls: AU-12, IR-4. | D9: Directives supplémentaires | E9: La connaissance de la situation dans l’ensemble de l’organisation comprend la connaissance aux trois niveaux de la gestion des risques (c.-à-d. au niveau de l’organisation, de la mission/des processus opérationnels, et du système d’information) et appuie une connaissance transorganisationnelle de la situation. Contrôles connexes : AU-12, IR-4.
A10: Test Case | D10: Cas de test
A11: Test | B11: TEST-AU-6(3) | D11: Test | E11: TEST-AU-6(3)
A12: Requirement ID | B12: AU-6(3) | D12: ID Exigence | E12: AU-6(3)
A13: Component | D13: Composant
A14: Requirement | D14: Exigence
A15: Contextual Design Description | D15: Description contextuelle du design
A16: Evidence Provided | D16: Preuve fournie
A17: Preparer Sign Off (Initials, Date) | D17: Signataire préparateur (Initiales, Date)
A18: Owner Sign Off (Initials, Date) | D18: Signataire propriétaire (Initiales, Date)
A19: Assessor Sign Off (Initials, Date) | D19: Signataire évaluateur (Initiales, Date)
A20: Status | B20: Not Started | D20: Statut | E20: Non commencé
A21: Comments | D21: Commentaires

Sheet AU-7
A1: Control AU-7 — Evidence Tracking | D1: Contrôle AU-7 — Suivi des preuves
A2: Control Information | D2: Informations du contrôle
A3: Control Identifier | B3: AU-7 | D3: Identifiant du contrôle | E3: AU-7
A4: Family | B4: Audit Reduction and Report Generation | D4: Famille | E4: Réduction des vérifications et production de rapports
A5: Profile | B5: CCCS Medium / PBMM Moderate | D5: Profil | E5: CCCS Moyen / PBMM Modéré
A6: Primary Evidence Tool | D6: Outil de preuve principal
A7: Contributing Tools | D7: Outils contributeurs
A8: Control Description | B8: (A) The information system provides an audit reduction and report generation capability that supports on-demand audit review, analysis, and reporting requirements and after-the-fact investigations of security incidents. (B) The information system provides an audit reduction and report generation capability that does not alter the original content or time ordering of audit records. | D8: Description du contrôle | E8: (A) Le système d’information offre une capacité de réduction des vérifications et de production de rapports prenant en charge les examens, les analyses et les rapports de vérification sur demande ainsi que les enquêtes à la suite d’incidents de sécurité. (B) Le système d’information offre une capacité de réduction de la vérification et de production de rapports qui ne modifie pas le contenu original ou l’ordre chronologique des enregistrements de vérification.
A9: Supplemental Guidance | B9: Audit reduction is a process that manipulates collected audit information and organizes such information in a summary format that is more meaningful to analysts. Audit reduction and report generation capabilities do not always emanate from the same information system or from the same organizational entities conducting auditing activities. Audit reduction capability can include, for example, modern data mining techniques with advanced data filters to identify anomalous behaviour in audit records. The report generation capability provided by the information system can generate customizable reports. Time ordering of audit records can be a significant issue if the granularity of the timestamp in the record is insufficient. Related control: AU-6 | D9: Directives supplémentaires | E9: La réduction de la vérification est un processus qui permet de manipuler l’information recueillie et de l’organiser dans un format sommaire plus significatif pour les analystes. Les capacités de réduction des vérifications et de production de rapports ne proviennent pas toujours du système d’information ou des entités organisationnelles qui mènent les activités de vérification. La capacité de réduction des vérifications peut comprendre, par exemple, des techniques modernes d’exploration de données avec filtres de données avancés pour déceler les comportements anormaux dans les enregistrements de vérification. La capacité de production de rapports fournie par le système d’information permet de générer des rapports personnalisables. L’ordre chronologique des enregistrements de vérification peut poser un problème important si la granularité de l’estampille temporelle dans l’enregistrement est insuffisante. Contrôle connexe : AU-6
A10: Test Case | D10: Cas de test
A11: Test | B11: TEST-AU-7 | D11: Test | E11: TEST-AU-7
A12: Requirement ID | B12: AU-7 | D12: ID Exigence | E12: AU-7
A13: Component | D13: Composant
A14: Requirement | D14: Exigence
A15: Contextual Design Description | D15: Description contextuelle du design
A16: Evidence Provided | D16: Preuve fournie
A17: Preparer Sign Off (Initials, Date) | D17: Signataire préparateur (Initiales, Date)
A18: Owner Sign Off (Initials, Date) | D18: Signataire propriétaire (Initiales, Date)
A19: Assessor Sign Off (Initials, Date) | D19: Signataire évaluateur (Initiales, Date)
A20: Status | B20: Not Started | D20: Statut | E20: Non commencé
A21: Comments | D21: Commentaires

Sheet AU-7-1
A1: Control AU-7(1) — Evidence Tracking | D1: Contrôle AU-7(1) — Suivi des preuves
A2: Control Information | D2: Informations du contrôle
A3: Control Identifier | B3: AU-7(1) | D3: Identifiant du contrôle | E3: AU-7(1)
A4: Family | B4: Audit Reduction and Report Generation | D4: Famille | E4: Réduction des vérifications et production de rapports
A5: Profile | B5: CCCS Medium / PBMM Moderate | D5: Profil | E5: CCCS Moyen / PBMM Modéré
A6: Primary Evidence Tool | D6: Outil de preuve principal
A7: Contributing Tools | D7: Outils contributeurs
A8: Control Description | B8: AUDIT REDUCTION AND REPORT GENERATION | AUTOMATIC PROCESSING The information system provides the capability to process audit records for events of interest based on all audit fields specified in AU-2, AU-3 and AU-3(1). | D8: Description du contrôle | E8: RÉDUCTION DES VÉRIFICATIONS ET PRODUCTION DE RAPPORTS | TRAITEMENT AUTOMATIQUE Le système d’information permet de traiter les enregistrements de vérification relatifs aux événements d’intérêt en fonction de tous les champs de vérification précisés dans AU-2, AU-3 et AU-3(1).
A9: Supplemental Guidance | B9: Events of interest can be identified by the content of specific audit record fields including, for example, identities of individuals, event types, event locations, event times, event dates, system resources involved, IP addresses involved, or information objects accessed. Organizations may define audit event criteria to any degree of granularity required, for example, locations selectable by general networking location (e.g., by network or sub-network) or selectable by specific information system component. Related controls: AU-2, AU-12. | D9: Directives supplémentaires | E9: Les événements d’intérêt peuvent être définis par le contenu des champs particuliers de l’enregistrement de vérification, y compris, par exemple, les identités des personnes, les types d’événements, les emplacements des événements, les heures des événements, les dates des événements, les ressources du système en cause, les adresses IP en cause ou les objets d’information consultés. Les organisations peuvent définir les critères des événements de vérification à n’importe quel degré de granularité requis, par exemple, les emplacements que l’on peut sélectionner par emplacement de réseautique général (p. ex., par réseau ou sous-réseau) ou par composant de système d’information particulier. Contrôles connexes : AU-2, AU-12.
A10: Test Case | D10: Cas de test
A11: Test | B11: TEST-AU-7(1) | D11: Test | E11: TEST-AU-7(1)
A12: Requirement ID | B12: AU-7(1) | D12: ID Exigence | E12: AU-7(1)
A13: Component | D13: Composant
A14: Requirement | D14: Exigence
A15: Contextual Design Description | D15: Description contextuelle du design
A16: Evidence Provided | D16: Preuve fournie
A17: Preparer Sign Off (Initials, Date) | D17: Signataire préparateur (Initiales, Date)
A18: Owner Sign Off (Initials, Date) | D18: Signataire propriétaire (Initiales, Date)
A19: Assessor Sign Off (Initials, Date) | D19: Signataire évaluateur (Initiales, Date)
A20: Status | B20: Not Started | D20: Statut | E20: Non commencé
A21: Comments | D21: Commentaires

Sheet AU-8
A1: Control AU-8 — Evidence Tracking | D1: Contrôle AU-8 — Suivi des preuves
A2: Control Information | D2: Informations du contrôle
A3: Control Identifier | B3: AU-8 | D3: Identifiant du contrôle | E3: AU-8
A4: Family | B4: Time Stamps | D4: Famille | E4: Estampilles temporelles
A5: Profile | B5: CCCS Medium / PBMM Moderate | D5: Profil | E5: CCCS Moyen / PBMM Modéré
A6: Primary Evidence Tool | D6: Outil de preuve principal
A7: Contributing Tools | D7: Outils contributeurs
A8: Control Description | B8: (A) The information system uses internal system clocks to generate time stamps for audit records. (B) The information system records time stamps for audit records that can be mapped to Coordinated Universal Time (UTC) or Greenwich Mean Time (GMT) within 1 second precision. | D8: Description du contrôle | E8: (A) Le système d’information utilise les horloges système internes afin de générer les estampilles temporelles pour les enregistrements de vérification. (B) Le système d’information enregistre des estampilles temporelles pour les enregistrements de vérification qui peuvent être mappées sur le temps universel coordonné (UTC) ou l’heure moyenne de Greenwich (GMT) à la seconde près.
A9: Supplemental Guidance | B9: Time stamps generated by the information system include date and time. Time is commonly expressed in Coordinated Universal Time (UTC) or local time with an offset from UTC. Granularity of time measurements refers to the degree of synchronization between information system clocks and reference clocks, for example, clocks synchronizing within hundreds of milliseconds or within tens of milliseconds. Organizations may define different time granularities for different system components. Time service can also be critical to other security capabilities such as access control and identification and authentication, depending on the nature of the mechanisms used to support those capabilities. Related controls: AU-3, AU-12 | D9: Directives supplémentaires | E9: Les estampilles temporelles générées par le système d’information comprennent la date et l’heure. L’heure est généralement exprimée en temps universel coordonné (UTC) ou selon l’heure locale avec indication du décalage par rapport à l’UTC. La granularité des mesures du temps désigne le niveau de synchronisation entre les horloges du système d’information et les horloges de référence, par exemple, des horloges synchronisées à quelques centaines ou dizaines de millisecondes près. Les organisations peuvent définir différentes granularités temporelles pour différents composants du système. Le service de l’heure peut également être essentiel à d’autres capacités de sécurité comme le contrôle d’accès, l’identification et l’authentification, selon la nature des mécanismes utilisés pour soutenir ces capacités. Contrôles connexes : AU-3, AU-12
A10: Test Case | D10: Cas de test
A11: Test | B11: TEST-AU-8 | D11: Test | E11: TEST-AU-8
A12: Requirement ID | B12: AU-8 | D12: ID Exigence | E12: AU-8
A13: Component | D13: Composant
A14: Requirement | D14: Exigence
A15: Contextual Design Description | D15: Description contextuelle du design
A16: Evidence Provided | D16: Preuve fournie
A17: Preparer Sign Off (Initials, Date) | D17: Signataire préparateur (Initiales, Date)
A18: Owner Sign Off (Initials, Date) | D18: Signataire propriétaire (Initiales, Date)
A19: Assessor Sign Off (Initials, Date) | D19: Signataire évaluateur (Initiales, Date)
A20: Status | B20: Not Started | D20: Statut | E20: Non commencé
A21: Comments | D21: Commentaires

Sheet AU-8-1
A1: Control AU-8(1) — Evidence Tracking | D1: Contrôle AU-8(1) — Suivi des preuves
A2: Control Information | D2: Informations du contrôle
A3: Control Identifier | B3: AU-8(1) | D3: Identifiant du contrôle | E3: AU-8(1)
A4: Family | B4: Time Stamps | D4: Famille | E4: Estampilles temporelles
A5: Profile | B5: CCCS Medium / PBMM Moderate | D5: Profil | E5: CCCS Moyen / PBMM Modéré
A6: Primary Evidence Tool | D6: Outil de preuve principal
A7: Contributing Tools | D7: Outils contributeurs
A8: Control Description | B8: TIME STAMPS | SYNCHRONIZATION WITH AUTHORITATIVE TIME SOURCE (a) The information system compares the internal information system clocks at least every 24 hours with an organization-defined authoritative time source; and (b) The information system synchronizes the internal system clocks to the authoritative time source when the time difference is greater than 1 millisecond. | D8: Description du contrôle | E8: ESTAMPILLES TEMPORELLES | SYNCHRONISATION AVEC UNE SOURCE D’HORODATAGE RECONNUE (a) Le système d’information compare les horloges internes du système d’information au moins toutes les 24 heures avec une source d’horodatage reconnue définie par l’organisation. (b) Le système d’information synchronise les horloges internes du système avec la source d’horodatage reconnue lorsque la différence de temps est supérieure à 1 milliseconde.
A9: Supplemental Guidance | B9: This control enhancement provides uniformity of time stamps for information systems with multiple system clocks and systems connected over a network. | D9: Directives supplémentaires | E9: Cette amélioration du contrôle assure l’uniformité des estampilles temporelles pour les systèmes d’information dotés de nombreuses horloges et les systèmes sur un réseau.
A10: Test Case | D10: Cas de test
A11: Test | B11: TEST-AU-8(1) | D11: Test | E11: TEST-AU-8(1)
A12: Requirement ID | B12: AU-8(1) | D12: ID Exigence | E12: AU-8(1)
A13: Component | D13: Composant
A14: Requirement | D14: Exigence
A15: Contextual Design Description | D15: Description contextuelle du design
A16: Evidence Provided | D16: Preuve fournie
A17: Preparer Sign Off (Initials, Date) | D17: Signataire préparateur (Initiales, Date)
A18: Owner Sign Off (Initials, Date) | D18: Signataire propriétaire (Initiales, Date)
A19: Assessor Sign Off (Initials, Date) | D19: Signataire évaluateur (Initiales, Date)
A20: Status | B20: Not Started | D20: Statut | E20: Non commencé
A21: Comments | D21: Commentaires

Sheet AU-9
A1: Control AU-9 — Evidence Tracking | D1: Contrôle AU-9 — Suivi des preuves
A2: Control Information | D2: Informations du contrôle
A3: Control Identifier | B3: AU-9 | D3: Identifiant du contrôle | E3: AU-9
A4: Family | B4: Protection of Audit Information | D4: Famille | E4: Protection des renseignements de vérification
A5: Profile | B5: CCCS Medium / PBMM Moderate | D5: Profil | E5: CCCS Moyen / PBMM Modéré
A6: Primary Evidence Tool | D6: Outil de preuve principal
A7: Contributing Tools | D7: Outils contributeurs
A8: Control Description | B8: (A) The information system protects audit information and audit tools from unauthorized access, modification, and deletion. | D8: Description du contrôle | E8: (A) Le système d’information protège les renseignements de vérification et les outils de vérification contre l’accès, la modification et la suppression non autorisés.
A9: Supplemental Guidance | B9: Audit information includes all information (e.g., audit records, audit settings, and audit reports) needed to successfully audit information system activity. This control focuses on technical protection of audit information. Physical protection of audit information is addressed by media protection controls and physical and environmental protection controls. Related controls: AC-3, AC-6, MP-2, MP-4, PE-2, PE-3, PE-6 | D9: Directives supplémentaires | E9: Les renseignements de vérification comprennent tous les renseignements (p. ex., les enregistrements de vérification, les paramètres de vérification et les rapports de vérification) nécessaires pour vérifier avec succès l’activité du système d’information. Ce contrôle est axé sur la protection technique des renseignements de vérification. La protection physique des renseignements de vérification est assurée par des contrôles de protection des supports et des contrôles de protection physique et environnementale. Contrôles connexes : AC-3, AC-6, MP-2, MP-4, PE-2, PE-3, PE-6
A10: Test Case | D10: Cas de test
A11: Test | B11: TEST-AU-9 | D11: Test | E11: TEST-AU-9
A12: Requirement ID | B12: AU-9 | D12: ID Exigence | E12: AU-9
A13: Component | D13: Composant
A14: Requirement | D14: Exigence
A15: Contextual Design Description | D15: Description contextuelle du design
A16: Evidence Provided | D16: Preuve fournie
A17: Preparer Sign Off (Initials, Date) | D17: Signataire préparateur (Initiales, Date)
A18: Owner Sign Off (Initials, Date) | D18: Signataire propriétaire (Initiales, Date)
A19: Assessor Sign Off (Initials, Date) | D19: Signataire évaluateur (Initiales, Date)
A20: Status | B20: Not Started | D20: Statut | E20: Non commencé
A21: Comments | D21: Commentaires

Sheet AU-9-2
A1: Control AU-9(2) — Evidence Tracking | D1: Contrôle AU-9(2) — Suivi des preuves
A2: Control Information | D2: Informations du contrôle
A3: Control Identifier | B3: AU-9(2) | D3: Identifiant du contrôle | E3: AU-9(2)
A4: Family | B4: Protection of Audit Information | D4: Famille | E4: Protection des renseignements de vérification
A5: Profile | B5: CCCS Medium / PBMM Moderate | D5: Profil | E5: CCCS Moyen / PBMM Modéré
A6: Primary Evidence Tool | D6: Outil de preuve principal
A7: Contributing Tools | D7: Outils contributeurs
A8: Control Description | B8: PROTECTION OF AUDIT INFORMATION | AUDIT BACKUP ON SEPARATE PHYSICAL SYSTEMS / COMPONENTS The information system backs up audit records at least weekly onto a physically different system or system component than the system or component being audited. | D8: Description du contrôle | E8: PROTECTION DES RENSEIGNEMENTS DE VÉRIFICATION | SAUVEGARDE DES VÉRIFICATIONS SUR DES SYSTÈMES/COMPOSANTS PHYSIQUES SÉPARÉS Le système d’information sauvegarde les enregistrements de vérification au moins une fois par semaine sur un système ou un composant système physiquement différent du système ou du composant faisant l’objet de la vérification.
A9: Supplemental Guidance | B9: This control enhancement helps to ensure that a compromise of the information system being audited does not also result in a compromise of the audit records. Related controls: AU-4, AU-5, AU-11. | D9: Directives supplémentaires | E9: Cette amélioration permet de s’assurer qu’une compromission du système d’information faisant l’objet d’une vérification n’entraîne pas également la compromission des enregistrements de vérification. Contrôles connexes : AU-4, AU-5, AU-11.
A10: Test Case | D10: Cas de test
A11: Test | B11: TEST-AU-9(2) | D11: Test | E11: TEST-AU-9(2)
A12: Requirement ID | B12: AU-9(2) | D12: ID Exigence | E12: AU-9(2)
A13: Component | D13: Composant
A14: Requirement | D14: Exigence
A15: Contextual Design Description | D15: Description contextuelle du design
A16: Evidence Provided | D16: Preuve fournie
A17: Preparer Sign Off (Initials, Date) | D17: Signataire préparateur (Initiales, Date)
A18: Owner Sign Off (Initials, Date) | D18: Signataire propriétaire (Initiales, Date)
A19: Assessor Sign Off (Initials, Date) | D19: Signataire évaluateur (Initiales, Date)
A20: Status | B20: Not Started | D20: Statut | E20: Non commencé
A21: Comments | D21: Commentaires

Sheet AU-9-4
A1: Control AU-9(4) — Evidence Tracking | D1: Contrôle AU-9(4) — Suivi des preuves
A2: Control Information | D2: Informations du contrôle
A3: Control Identifier | B3: AU-9(4) | D3: Identifiant du contrôle | E3: AU-9(4)
A4: Family | B4: Protection of Audit Information | D4: Famille | E4: Protection des renseignements de vérification
A5: Profile | B5: CCCS Medium / PBMM Moderate | D5: Profil | E5: CCCS Moyen / PBMM Modéré
A6: Primary Evidence Tool | D6: Outil de preuve principal
A7: Contributing Tools | D7: Outils contributeurs
A8: Control Description | B8: PROTECTION OF AUDIT INFORMATION | ACCESS BY SUBSET OF PRIVILEGED USERS The organization authorizes access to management of audit functionality to only an organization-defined subset of privileged users. | D8: Description du contrôle | E8: PROTECTION DES RENSEIGNEMENTS DE VÉRIFICATION | ACCÈS PAR SOUS-ENSEMBLE D’UTILISATEURS PRIVILÉGIÉS L’organisation n’autorise l’accès à la fonction de gestion de la vérification qu’à un sous-ensemble d’utilisateurs privilégiés défini par l’organisation seulement.
A9: Supplemental Guidance | B9: Individuals with privileged access to an information system and who are also the subject of an audit by that system, may affect the reliability of audit information by inhibiting audit activities or modifying audit records. This control enhancement requires that privileged access be further defined between audit-related privileges and other privileges, thus limiting the users with audit-related privileges. Related control: AC-5. | D9: Directives supplémentaires | E9: Les personnes qui ont un accès privilégié à un système d’information et qui font également l’objet d’une vérification par ce système peuvent nuire à la fiabilité de l’information de vérification en entravant les activités de vérification ou en modifiant les enregistrements de vérification. Cette amélioration du contrôle exige que l’accès privilégié soit mieux défini entre les privilèges liés à la vérification et les autres privilèges, de manière à limiter le nombre d’utilisateurs ayant des privilèges liés à la vérification. Contrôle connexe : AC-5.
A10: Test Case | D10: Cas de test
A11: Test | B11: TEST-AU-9(4) | D11: Test | E11: TEST-AU-9(4)
A12: Requirement ID | B12: AU-9(4) | D12: ID Exigence | E12: AU-9(4)
A13: Component | D13: Composant
A14: Requirement | D14: Exigence
A15: Contextual Design Description | D15: Description contextuelle du design
A16: Evidence Provided | D16: Preuve fournie
A17: Preparer Sign Off (Initials, Date) | D17: Signataire préparateur (Initiales, Date)
A18: Owner Sign Off (Initials, Date) | D18: Signataire propriétaire (Initiales, Date)
A19: Assessor Sign Off (Initials, Date) | D19: Signataire évaluateur (Initiales, Date)
A20: Status | B20: Not Started | D20: Statut | E20: Non commencé
A21: Comments | D21: Commentaires

Sheet AU-11
A1: Control AU-11 — Evidence Tracking | D1: Contrôle AU-11 — Suivi des preuves
A2: Control Information | D2: Informations du contrôle
A3: Control Identifier | B3: AU-11 | D3: Identifiant du contrôle | E3: AU-11
A4: Family | B4: Audit Record Retention | D4: Famille | E4: Conservation des enregistrements de vérification
A5: Profile | B5: CCCS Medium / PBMM Moderate | D5: Profil | E5: CCCS Moyen / PBMM Modéré
A6: Primary Evidence Tool | D6: Outil de preuve principal
A7: Contributing Tools | D7: Outils contributeurs
A8: Control Description | B8: (A) The CSP retains audit records for at least 90 days to provide support for after-the-fact investigations of security incidents and to meet regulatory and organizational information retention requirements. (B) The client retains audit records and logs for at least 3 months online and at least 6 months in storage. (C) The client retains all audit records and logs associated with a security incident for at least 5 years. | D8: Description du contrôle | E8: (A) Le FSI conserve les enregistrements de vérification pendant au moins 90 jours afin de soutenir les enquêtes faisant suite aux incidents de sécurité et de respecter les exigences réglementaires et organisationnelles en matière de conservation de l’information. (B) Le client conserve les enregistrements et les journaux de vérification pendant au moins 3 mois en ligne et au moins 6 mois en mémoire. (C) Le client conserve pendant au moins 5 ans tous les enregistrements et journaux de vérification associés à un incident de sécurité.
A9: Supplemental Guidance | B9: Organizations retain audit records until it is determined that they are no longer needed for administrative, legal, audit, or other operational purposes. This includes, for example, retention and availability of audit records relative to legal requests, subpoenas, and law enforcement actions. Organizations develop standard categories of audit records relative to such types of actions and standard response processes for each type of action. Related controls: AU-4, AU-5, AU-9, MP-6 | D9: Directives supplémentaires | E9: Les organisations conservent les enregistrements de vérification jusqu’à ce qu’il soit déterminé qu’ils ne sont plus nécessaires à des fins administratives, juridiques, de vérification ou à d’autres fins opérationnelles. Cela comprend, par exemple, la conservation et la disponibilité des enregistrements de vérification relatifs aux demandes légales, aux citations à comparaître et aux mesures d’application de la loi. Les organisations établissent des catégories normalisées d’enregistrements de vérification par rapport à ces types de mesures ainsi que des processus de réponse normalisés pour chaque type de mesure. Contrôles connexes : AU-4, AU-5, AU-9, MP-6
A10: Test Case | D10: Cas de test
A11: Test | B11: TEST-AU-11 | D11: Test | E11: TEST-AU-11
A12: Requirement ID | B12: AU-11 | D12: ID Exigence | E12: AU-11
A13: Component | D13: Composant
A14: Requirement | D14: Exigence
A15: Contextual Design Description | D15: Description contextuelle du design
A16: Evidence Provided | D16: Preuve fournie
A17: Preparer Sign Off (Initials, Date) | D17: Signataire préparateur (Initiales, Date)
A18: Owner Sign Off (Initials, Date) | D18: Signataire propriétaire (Initiales, Date)
A19: Assessor Sign Off (Initials, Date) | D19: Signataire évaluateur (Initiales, Date)
A20: Status | B20: Not Started | D20: Statut | E20: Non commencé
A21: Comments | D21: Commentaires

Sheet AU-12
A1: Control AU-12 — Evidence Tracking | D1: Contrôle AU-12 — Suivi des preuves
A2: Control Information | D2: Informations du contrôle
A3: Control Identifier | B3: AU-12 | D3: Identifiant du contrôle | E3: AU-12
A4: Family | B4: Audit Generation | D4: Famille | E4: Génération des vérifications
A5: Profile | B5: CCCS Medium / PBMM Moderate | D5: Profil | E5: CCCS Moyen / PBMM Modéré
A6: Primary Evidence Tool | D6: Outil de preuve principal
A7: Contributing Tools | D7: Outils contributeurs
A8: Control Description | B8: (A) The information system provides audit record generation capability for the auditable events defined in AU-2 a. of all information system and network components where audit capability is deployed/available. (B) The information system allows organization-defined personnel or roles to select which auditable events are to be audited by specific components of the information system. (C) The information system generates audit records for the events defined in AU-2 d. with the content defined in AU-3. | D8: Description du contrôle | E8: (A) Le système d’information offre une capacité de génération d’enregistrements de vérification pour les événements vérifiables définis dans AU-2 a. de tous les composants du système d’information et du réseau où la capacité de vérification est déployée/disponible. (B) Le système d’information permet au personnel ou aux rôles définis par l’organisation de choisir les événements vérifiables qui doivent être vérifiés par des composants précis du système d’information. (C) Le système d’information génère des enregistrements de vérification pour les événements définis dans AU-2 d. avec le contenu défini dans AU-3.
A9: Supplemental Guidance | B9: Audit records can be generated from many different information system components. The list of audited events is the set of events for which audits are to be generated. These events are typically a subset of all events for which the information system is capable of generating audit records. Related controls: AC-3, AU-2, AU-3, AU-6, AU-7 | D9: Directives supplémentaires | E9: Des enregistrements de vérification peuvent être générés à partir de nombreux composants du système d’information. La liste des événements vérifiés est l’ensemble des événements pour lesquels des vérifications doivent être produites. Ces événements sont habituellement un sous-ensemble de tous les événements pour lesquels le système d’information peut générer des enregistrements de vérification. Contrôles connexes : AC-3, AU-2, AU-3, AU-6, AU-7
A10: Test Case | D10: Cas de test
A11: Test | B11: TEST-AU-12 | D11: Test | E11: TEST-AU-12
A12: Requirement ID | B12: AU-12 | D12: ID Exigence | E12: AU-12
A13: Component | D13: Composant
A14: Requirement | D14: Exigence
A15: Contextual Design Description | D15: Description contextuelle du design
A16: Evidence Provided | D16: Preuve fournie
A17: Preparer Sign Off (Initials, Date) | D17: Signataire préparateur (Initiales, Date)
A18: Owner Sign Off (Initials, Date) | D18: Signataire propriétaire (Initiales, Date)
A19: Assessor Sign Off (Initials, Date) | D19: Signataire évaluateur (Initiales, Date)
A20: Status | B20: Not Started | D20: Statut | E20: Non commencé
A21: Comments | D21: Commentaires

Sheet CA-9
A1: Control CA-9 — Evidence Tracking | D1: Contrôle CA-9 — Suivi des preuves
A2: Control Information | D2: Informations du contrôle
A3: Control Identifier | B3: CA-9 | D3: Identifiant du contrôle | E3: CA-9
A4: Family | B4: Internal System Connections | D4: Famille | E4: Connexions internes au système
A5: Profile | B5: CCCS Medium / PBMM Moderate | D5: Profil | E5: CCCS Moyen / PBMM Modéré
A6: Primary Evidence Tool | D6: Outil de preuve principal
A7: Contributing Tools | D7: Outils contributeurs
A8: Control Description | B8: (A) The organization authorizes internal connections of information system components or classes of components to the information system. (B) The organization documents, for each internal connection, the interface characteristics, security requirements, and the nature of the information communicated. | D8: Description du contrôle | E8: (A) L’organisation autorise les connexions internes de composants du système d’information ou de catégories de composants au système d’information. (B) L’organisation documente, pour chaque connexion interne, les caractéristiques de l’interface, les exigences de sécurité et la nature de l’information communiquée.
A9: Supplemental Guidance | B9: This control applies to connections between organizational information systems and (separate) constituent system components (i.e., intra-system connections) including, for example, system connections with mobile devices, notebook/desktop computers, printers, copiers, facsimile machines, scanners, sensors, and servers. Instead of authorizing each individual internal connection, organizations can authorize internal connections for a class of components with common characteristics and/or configurations, for example, all digital printers, scanners, and copiers with a specified processing, storage, and transmission capability or all smart phones with a specific baseline configuration. Related controls: AC-3, AC-4, AC-18, AC-19, AU-2, AU-12, CA-7, CM-2, IA-3, SC-7, SI-4 | D9: Directives supplémentaires | E9: Ce contrôle s’applique aux connexions entre les systèmes d’information organisationnels et les composants (distincts) des systèmes constituants (c.-à-d. les connexions intrasystème) y compris, par exemple, les connexions système avec les appareils mobiles, les ordinateurs portatifs/de bureau, les imprimantes, les photocopieurs, les télécopieurs, les numériseurs, les capteurs et les serveurs. Au lieu d’autoriser chaque connexion interne individuelle, les organisations peuvent autoriser les connexions internes pour une catégorie de composants ayant des caractéristiques ou des configurations communes, par exemple, toutes les imprimantes et tous les numériseurs et photocopieurs numériques ayant une capacité de traitement, de stockage et de transmission spécifiée ou tous les téléphones intelligents ayant une configuration de base spécifique. Contrôles connexes : AC-3, AC-4, AC-18, AC-19, AU-2, AU-12, CA-7, CM-2, IA-3, SC-7, SI-4
A10: Test Case | D10: Cas de test
A11: Test | B11: TEST-CA-9 | D11: Test | E11: TEST-CA-9
A12: Requirement ID | B12: CA-9 | D12: ID Exigence | E12: CA-9
A13: Component | D13: Composant
A14: Requirement | D14: Exigence
A15: Contextual Design Description | D15: Description contextuelle du design
A16: Evidence Provided | D16: Preuve fournie
A17: Preparer Sign Off (Initials, Date) | D17: Signataire préparateur (Initiales, Date)
A18: Owner Sign Off (Initials, Date) | D18: Signataire propriétaire (Initiales, Date)
A19: Assessor Sign Off (Initials, Date) | D19: Signataire évaluateur (Initiales, Date)
A20: Status | B20: Not Started | D20: Statut | E20: Non commencé
A21: Comments | D21: Commentaires

Sheet CM-2-2
A1: Control CM-2(2) — Evidence Tracking | D1: Contrôle CM-2(2) — Suivi des preuves
A2: Control Information | D2: Informations du contrôle
A3: Control Identifier | B3: CM-2(2) | D3: Identifiant du contrôle | E3: CM-2(2)
A4: Family | B4: Baseline Configuration | D4: Famille | E4: Configuration de base
A5: Profile | B5: CCCS Medium / PBMM Moderate | D5: Profil | E5: CCCS Moyen / PBMM Modéré
A6: Primary Evidence Tool | D6: Outil de preuve principal
A7: Contributing Tools | D7: Outils contributeurs
A8: Control Description | B8: BASELINE CONFIGURATION | AUTOMATION SUPPORT FOR ACCURACY / CURRENCY The organization employs automated mechanisms to maintain an up-to-date, complete, accurate, and readily available baseline configuration of the information system. | D8: Description du contrôle | E8: CONFIGURATION DE BASE | SOUTIEN DE L’AUTOMATISATION POUR UNE CONFIGURATION EXACTE ET À JOUR L’organisation utilise des mécanismes automatisés pour maintenir une configuration de base à jour, complète, exacte et facilement accessible du système d’information.
A9: Supplemental Guidance | B9: Automated mechanisms that help organizations maintain consistent baseline configurations for information systems include, for example, hardware and software inventory tools, configuration management tools, and network management tools. Such tools can be deployed and/or allocated as common controls, at the information system level, or at the operating system or component level (e.g., on workstations, servers, notebook computers, network components, or mobile devices). Tools can be used, for example, to track version numbers on operating system applications, types of software installed, and current patch levels. This control enhancement can be satisfied by the implementation of CM-8 (2) for organizations that choose to combine information system component inventory and baseline configuration activities. Related controls: CM-7, RA-5. | D9: Directives supplémentaires | E9: Les mécanismes automatisés qui aident les organisations à maintenir des configurations de base uniformes pour les systèmes d’information comprennent, par exemple, les outils d’inventaire matériel et logiciel, les outils de gestion de la configuration et les outils de gestion de réseau. Ces outils peuvent être déployés ou attribués en tant que contrôles communs, au niveau du système d’information, ou au niveau du système d’exploitation ou des composants (p. ex., sur les postes de travail, les serveurs, les ordinateurs portatifs, les composants de réseau ou les appareils mobiles). Les outils peuvent être utilisés, par exemple, pour faire le suivi des numéros de version sur les applications du système d’exploitation, des types de logiciels installés et des niveaux de correctifs actuels. Cette amélioration du contrôle peut être réalisée par la mise en œuvre du CM-8 (2) pour les organisations qui choisissent de combiner l’inventaire des composants du système d’information et les activités de configuration de base. Contrôles connexes : CM-7, RA-5.
A10: Test Case | D10: Cas de test
A11: Test | B11: TEST-CM-2(2) | D11: Test | E11: TEST-CM-2(2)
A12: Requirement ID | B12: CM-2(2) | D12: ID Exigence | E12: CM-2(2)
A13: Component | D13: Composant
A14: Requirement | D14: Exigence
A15: Contextual Design Description | D15: Description contextuelle du design
A16: Evidence Provided | D16: Preuve fournie
A17: Preparer Sign Off (Initials, Date) | D17: Signataire préparateur (Initiales, Date)
A18: Owner Sign Off (Initials, Date) | D18: Signataire propriétaire (Initiales, Date)
A19: Assessor Sign Off (Initials, Date) | D19: Signataire évaluateur (Initiales, Date)
A20: Status | B20: Not Started | D20: Statut | E20: Non commencé
A21: Comments | D21: Commentaires

Sheet CM-2-3
A1: Control CM-2(3) — Evidence Tracking | D1: Contrôle CM-2(3) — Suivi des preuves
A2: Control Information | D2: Informations du contrôle
A3: Control Identifier | B3: CM-2(3) | D3: Identifiant du contrôle | E3: CM-2(3)
A4: Family | B4: Baseline Configuration | D4: Famille | E4: Configuration de base
A5: Profile | B5: CCCS Medium / PBMM Moderate | D5: Profil | E5: CCCS Moyen / PBMM Modéré
A6: Primary Evidence Tool | D6: Outil de preuve principal
A7: Contributing Tools | D7: Outils contributeurs
A8: Control Description | B8: BASELINE CONFIGURATION | RETENTION OF PREVIOUS CONFIGURATIONS The organization retains the two most recent precious versions of baseline configurations of the information system to support rollback. | D8: Description du contrôle | E8: CONFIGURATION DE BASE | CONSERVATION DES CONFIGURATIONS PRÉCÉDENTES L’organisation conserve les deux versions utiles les plus récentes des configurations de base du système d’information pour la prise en charge des reprises.
A9: Supplemental Guidance | B9: Retaining previous versions of baseline configurations to support rollback may include, for example, hardware, software, firmware, configuration files, and configuration records. | D9: Directives supplémentaires | E9: La conservation des versions antérieures des configurations de base pour la prise en charge des reprises peut comprendre, par exemple, le matériel, les logiciels, les micrologiciels, les fichiers de configuration et les enregistrements de configuration.
A10: Test Case | D10: Cas de test
A11: Test | B11: TEST-CM-2(3) | D11: Test | E11: TEST-CM-2(3)
A12: Requirement ID | B12: CM-2(3) | D12: ID Exigence | E12: CM-2(3)
A13: Component | D13: Composant
A14: Requirement | D14: Exigence
A15: Contextual Design Description | D15: Description contextuelle du design
A16: Evidence Provided | D16: Preuve fournie
A17: Preparer Sign Off (Initials, Date) | D17: Signataire préparateur (Initiales, Date)
A18: Owner Sign Off (Initials, Date) | D18: Signataire propriétaire (Initiales, Date)
A19: Assessor Sign Off (Initials, Date) | D19: Signataire évaluateur (Initiales, Date)
A20: Status | B20: Not Started | D20: Statut | E20: Non commencé
A21: Comments | D21: Commentaires

Sheet CM-3
A1: Control CM-3 — Evidence Tracking | D1: Contrôle CM-3 — Suivi des preuves
A2: Control Information | D2: Informations du contrôle
A3: Control Identifier | B3: CM-3 | D3: Identifiant du contrôle | E3: CM-3
A4: Family | B4: Configuration Change Control | D4: Famille | E4: Contrôle des changements de configuration
A5: Profile | B5: CCCS Medium / PBMM Moderate | D5: Profil | E5: CCCS Moyen / PBMM Modéré
A6: Primary Evidence Tool | D6: Outil de preuve principal
A7: Contributing Tools | D7: Outils contributeurs
A8: Control Description | B8: (A) The organization determines the types of changes to the information system that are configuration-controlled. (B) The organization reviews proposed configuration-controlled changes to the information system and approves or disapproves such changes with explicit consideration for security impact analyses. (C) The organization documents configuration change decisions associated with the information system. (D) The organization implements approved configuration-controlled changes to the information system. (E) The organization retains records of configuration-controlled changes to the information system for at least 90 days. (F) The organization audits and reviews activities associated with configuration-controlled changes to the information system. (G) The organization coordinates and provides oversight for configuration change control activities through a central communication process that includes organizational governance bodies that convenes at least annually. | D8: Description du contrôle | E8: (A) L’organisation détermine les types de changements au système d’information qui sont contrôlés par la configuration. (B) L’organisation examine les changements proposés au système d’information qui sont contrôlés par la configuration et approuve ou désapprouve ces changements en tenant compte explicitement des analyses des répercussions sur la sécurité. (C) L’organisation documente les décisions sur les changements de configuration associés au système d’information. (D) L’organisation met en œuvre les changements approuvés au système d’information qui sont contrôlés par la configuration. (E) L’organisation conserve pendant au moins 90 jours les enregistrements des changements apportés au système d’information qui sont contrôlés par la configuration. (F) L’organisation vérifie et examine les activités associées aux changements apportés au système d’information qui sont contrôlés par la configuration. (G) L’organisation coordonne et surveille les activités de contrôle des changements de configuration au moyen d’un processus de communication central comprenant des organismes de gouvernance organisationnelle qui se réunissent au moins une fois par année.
A9: Supplemental Guidance | B9: Configuration change controls for organizational information systems involve the systematic proposal, justification, implementation, testing, review, and disposition of changes to the systems, including system upgrades and modifications. Configuration change control includes changes to baseline configurations for components and configuration items of information systems, changes to configuration settings for information technology products (e.g., operating systems, applications, firewalls, routers, and mobile devices), unscheduled/unauthorized changes, and changes to remediate vulnerabilities. Typical processes for managing configuration changes to information systems include, for example, Configuration Control Boards that approve proposed changes to systems. For new development information systems or systems undergoing major upgrades, organizations consider including representatives from development organizations on the Configuration Control Boards. Auditing of changes includes activities before and after changes are made to organizational information systems and the auditing activities required to implement such changes. Related controls: CA-7, CM-2, CM-4, CM-5, CM-6, CM-9, SA-10, SI-2, SI-12 | D9: Directives supplémentaires | E9: Les contrôles des changements de configuration pour les systèmes d’information organisationnels comprennent la proposition systématique, la justification, la mise en œuvre, les essais, l’examen et la disposition des changements aux systèmes, y compris les mises à niveau et les modifications des systèmes. Le contrôle des changements de configuration comprend les changements apportés aux configurations de base des composants et des éléments de configuration des systèmes d’information, les changements apportés aux paramètres de configuration des produits de technologie de l’information (p. ex., systèmes d’exploitation, applications, pare-feu, routeurs et appareils mobiles), les changements imprévus ou non autorisés et les changements visant à corriger les vulnérabilités. Les processus types de gestion des changements de configuration des systèmes d’information comprennent, par exemple, les comités de contrôle de la configuration qui approuvent les changements proposés aux systèmes. En ce qui concerne les nouveaux systèmes d’information en développement ou les systèmes faisant l’objet de mises à niveau importantes, les organisations envisagent d’inclure des représentants des organisations de développement dans les comités de contrôle de la configuration. La vérification des changements comprend les activités menées avant et après les changements apportés aux systèmes d’information organisationnels et les activités de vérification nécessaires à la mise en œuvre de ces changements. Contrôles connexes : CA-7, CM-2, CM-4, CM-5, CM-6, CM-9, SA-10, SI-2, SI-12
A10: Test Case | D10: Cas de test
A11: Test | B11: TEST-CM-3 | D11: Test | E11: TEST-CM-3
A12: Requirement ID | B12: CM-3 | D12: ID Exigence | E12: CM-3
A13: Component | D13: Composant
A14: Requirement | D14: Exigence
A15: Contextual Design Description | D15: Description contextuelle du design
A16: Evidence Provided | D16: Preuve fournie
A17: Preparer Sign Off (Initials, Date) | D17: Signataire préparateur (Initiales, Date)
A18: Owner Sign Off (Initials, Date) | D18: Signataire propriétaire (Initiales, Date)
A19: Assessor Sign Off (Initials, Date) | D19: Signataire évaluateur (Initiales, Date)
A20: Status | B20: Not Started | D20: Statut | E20: Non commencé
A21: Comments | D21: Commentaires

Sheet CM-3-6
A1: Control CM-3(6) — Evidence Tracking | D1: Contrôle CM-3(6) — Suivi des preuves
A2: Control Information | D2: Informations du contrôle
A3: Control Identifier | B3: CM-3(6) | D3: Identifiant du contrôle | E3: CM-3(6)
A4: Family | B4: Configuration Change Control | D4: Famille | E4: Contrôle des changements de configuration
A5: Profile | B5: CCCS Medium / PBMM Moderate | D5: Profil | E5: CCCS Moyen / PBMM Modéré
A6: Primary Evidence Tool | D6: Outil de preuve principal
A7: Contributing Tools | D7: Outils contributeurs
A8: Control Description | B8: CONFIGURATION CHANGE CONTROL | CRYPTOGRAPHY MANAGEMENT The organization ensures that cryptographic mechanisms used to provide any cryptographic-based safeguards are under configuration management. | D8: Description du contrôle | E8: CONTRÔLE DES CHANGEMENTS DE CONFIGURATION | GESTION DE LA CRYPTOGRAPHIE L’organisation s’assure que les mécanismes cryptographiques utilisés pour fournir des mesures de protection cryptographiques font l’objet d’une gestion de la configuration.
A9: Supplemental Guidance | B9: Regardless of the cryptographic means employed (e.g., public key, private key, shared secrets), organizations ensure that there are processes and procedures in place to effectively manage those means. For example, if devices use certificates as a basis for identification and authentication, there needs to be a process in place to address the expiration of those certificates. Related control: SC-13. | D9: Directives supplémentaires | E9: Peu importe les moyens cryptographiques utilisés (p. ex., clés publiques, clés privées, secrets partagés), les organisations s’assurent qu’il y a des processus et des procédures en place pour gérer efficacement ces moyens. Par exemple, si des appareils utilisent des certificats comme base d’identification et d’authentification, il doit y avoir un processus en place pour gérer la question de l’expiration de ces certificats. Contrôle connexe : SC-13.
A10: Test Case | D10: Cas de test
A11: Test | B11: TEST-CM-3(6) | D11: Test | E11: TEST-CM-3(6)
A12: Requirement ID | B12: CM-3(6) | D12: ID Exigence | E12: CM-3(6)
A13: Component | D13: Composant
A14: Requirement | D14: Exigence
A15: Contextual Design Description | D15: Description contextuelle du design
A16: Evidence Provided | D16: Preuve fournie
A17: Preparer Sign Off (Initials, Date) | D17: Signataire préparateur (Initiales, Date)
A18: Owner Sign Off (Initials, Date) | D18: Signataire propriétaire (Initiales, Date)
A19: Assessor Sign Off (Initials, Date) | D19: Signataire évaluateur (Initiales, Date)
A20: Status | B20: Not Started | D20: Statut | E20: Non commencé
A21: Comments | D21: Commentaires

Sheet CM-5-1
A1: Control CM-5(1) — Evidence Tracking | D1: Contrôle CM-5(1) — Suivi des preuves
A2: Control Information | D2: Informations du contrôle
A3: Control Identifier | B3: CM-5(1) | D3: Identifiant du contrôle | E3: CM-5(1)
A4: Family | B4: Access Restrictions for Change | D4: Famille | E4: Restrictions d’accès pour les changements
A5: Profile | B5: CCCS Medium / PBMM Moderate | D5: Profil | E5: CCCS Moyen / PBMM Modéré
A6: Primary Evidence Tool | D6: Outil de preuve principal
A7: Contributing Tools | D7: Outils contributeurs
A8: Control Description | B8: ACCESS RESTRICTIONS FOR CHANGE | AUTOMATED ACCESS ENFORCEMENT / AUDITING The information system enforces access restrictions and supports auditing of the enforcement actions. | D8: Description du contrôle | E8: RESTRICTIONS D’ACCÈS POUR LES CHANGEMENTS | CONTRÔLE AUTOMATISÉ DE L’ACCÈS/VÉRIFICATION Le système d’information applique les restrictions d’accès et prend en charge la vérification des contrôles appliqués.
A9: Supplemental Guidance | B9: Related controls: AU-2, AU-12, AU-6, CM-3, and CM-6. | D9: Directives supplémentaires | E9: Contrôles connexes : AU-2, AU-12, AU-6, CM-3 et CM-6.
A10: Test Case | D10: Cas de test
A11: Test | B11: TEST-CM-5(1) | D11: Test | E11: TEST-CM-5(1)
A12: Requirement ID | B12: CM-5(1) | D12: ID Exigence | E12: CM-5(1)
A13: Component | D13: Composant
A14: Requirement | D14: Exigence
A15: Contextual Design Description | D15: Description contextuelle du design
A16: Evidence Provided | D16: Preuve fournie
A17: Preparer Sign Off (Initials, Date) | D17: Signataire préparateur (Initiales, Date)
A18: Owner Sign Off (Initials, Date) | D18: Signataire propriétaire (Initiales, Date)
A19: Assessor Sign Off (Initials, Date) | D19: Signataire évaluateur (Initiales, Date)
A20: Status | B20: Not Started | D20: Statut | E20: Non commencé
A21: Comments | D21: Commentaires

Sheet CM-6
A1: Control CM-6 — Evidence Tracking | D1: Contrôle CM-6 — Suivi des preuves
A2: Control Information | D2: Informations du contrôle
A3: Control Identifier | B3: CM-6 | D3: Identifiant du contrôle | E3: CM-6
A4: Family | B4: Configuration Settings | D4: Famille | E4: Paramètres de configuration
A5: Profile | B5: CCCS Medium / PBMM Moderate | D5: Profil | E5: CCCS Moyen / PBMM Modéré
A6: Primary Evidence Tool | D6: Outil de preuve principal
A7: Contributing Tools | D7: Outils contributeurs
A8: Control Description | B8: (A) The organization establishes and documents configuration settings for information technology products employed within the information system using checklists from one or more of the following Center for Internet Security (CIS), National Institute of Standards and Technology (NIST), Defense Information Systems Agency (DISA) that reflect the most restrictive mode consistent with operational requirements. (B) The organization implements the configuration settings. (C) The organization identifies, documents, and approves any deviations from established configuration settings for any configurable infomation system components. (D) The organization monitors and controls changes to the configuration settings in accordance with organizational policies and procedures. | D8: Description du contrôle | E8: (A) L’organisation établit et documente les paramètres de configuration des produits de technologie de l’information utilisés dans le système d’information à l’aide de listes de vérification provenant d’un ou de plusieurs des éléments suivants : Center for Internet Security (CIS), National Institute of Standards and Technology (NIST), Defense Information Systems Agency (DISA), qui reflètent le mode le plus restrictif conformément aux exigences opérationnelles. (B) L’organisation met en œuvre les paramètres de configuration. (C) L’organisation identifie, documente et approuve tout écart par rapport aux paramètres de configuration établis pour les composants configurables du système d’information. (D) L’organisation surveille et contrôle les changements apportés aux paramètres de configuration conformément aux politiques et aux procédures de l’organisation.
A9: Supplemental Guidance | B9: Configuration settings are the set of parameters that can be changed in hardware, software, or firmware components of the information system that affect the security posture and/or functionality of the system. Information technology products for which security-related configuration settings can be defined include, for example, mainframe computers, servers (e.g., database, electronic mail, authentication, web, proxy, file, domain name), workstations, input/output devices (e.g., scanners, copiers, and printers), network components (e.g., firewalls, routers, gateways, voice and data switches, wireless access points, network appliances, sensors), operating systems, middleware, and applications. Security-related parameters are those parameters impacting the security state of information systems including the parameters required to satisfy other security control requirements. Security-related parameters include, for example: (i) registry settings; (ii) account, file, directory permission settings; and (iii) settings for functions, ports, protocols, services, and remote connections. Organizations establish organization-wide configuration settings and subsequently derive specific settings for information systems. The established settings become part of the systems configuration baselineCommon secure configurations (also referred to as security configuration checklists, lockdown and hardening guides, security reference guides, security technical implementation guides (STIG)) provide recognized, standardized, and established benchmarks that stipulate secure configuration settings for specific information technology platforms/products and instructions for configuring those information system components to meet operational requirements. Common secure configurations can be developed by a variety of organizations including, for example, information technology product developers, manufacturers, vendors, consortia, academia, industry, federal government organizations, and others in the public and private sectors. The Security Content Automation Protocol (SCAP) and the defined standards within the protocol (e.g., Common Configuration Enumeration) provide an effective method to uniquely identify, track, and control configuration settings. Related controls: AC-19, CM-2, CM-3, CM-7, SI-4. | D9: Directives supplémentaires | E9: Les paramètres de configuration sont l’ensemble de paramètres qui peuvent être modifiés dans les composants matériels, logiciels ou micrologiciels du système d’information et qui ont une incidence sur la posture de sécurité ou la fonctionnalité du système. Les produits de technologie de l’information pour lesquels les paramètres de configuration liés à la sécurité peuvent être définis comprennent, par exemple, les ordinateurs centraux, les serveurs (p. ex., base de données, courrier électronique, authentification, Web, mandataire, fichiers, noms de domaine), les postes de travail, les périphériques d’entrée et de sortie (p. ex., numériseurs, photocopieurs et imprimantes), les composants de réseau (p. ex., pare-feu, routeurs, passerelles, commutateurs de voix et de données, points d’accès sans fil, outils de réseau, capteurs), les systèmes d’exploitation, les intergiciels et les applications. Les paramètres liés à la sécurité sont les paramètres qui influent sur l’état de sécurité des systèmes d’information, y compris les paramètres requis pour satisfaire à d’autres exigences de contrôle de sécurité. Les paramètres liés à la sécurité comprennent, par exemple : (i) les paramètres des registres; (ii) les paramètres de comptes, de fichiers, d’autorisation de répertoires; (iii) les paramètres des fonctions, des ports, des protocoles, des services et des connexions à distance. Les organisations établissent les paramètres de configuration à l’échelle de l’organisation et en déduisent ensuite les paramètres particuliers pour les systèmes d’information. Les paramètres établis font partie des configurations de base des systèmes Les configurations sécurisées communes (aussi appelées listes de vérification de la configuration de sécurité, guides de verrouillage et de renforcement, guides de référence de sécurité, guides de mise en œuvre technique de la sécurité [STIG]) fournissent des repères reconnus, normalisés et établis qui stipulent les paramètres de configuration sécurisée pour des plateformes/produits de technologie de l’information particuliers et des instructions pour configurer ces composants de système d’information de manière à répondre aux exigences opérationnelles. Les configurations sécurisées communes peuvent être mises au point par diverses organisations, y compris, par exemple, les concepteurs de produits de technologie de l’information, les fabricants, les fournisseurs, les consortiums, le milieu universitaire, l’industrie, les organisations du gouvernement fédéral et d’autres intervenants des secteurs public et privé. Le protocole d’automatisation du contenu de sécurité SCAP (Security Content Automation Protocol) et les normes définies dans le protocole (p. ex., Common Configuration Enumeration) constituent une méthode efficace pour déterminer, suivre et contrôler de façon unique les paramètres de configuration. Contrôles connexes : AC-19, CM-2, CM-3, CM-7, SI-4.
A10: Test Case | D10: Cas de test
A11: Test | B11: TEST-CM-6 | D11: Test | E11: TEST-CM-6
A12: Requirement ID | B12: CM-6 | D12: ID Exigence | E12: CM-6
A13: Component | D13: Composant
A14: Requirement | D14: Exigence
A15: Contextual Design Description | D15: Description contextuelle du design
A16: Evidence Provided | D16: Preuve fournie
A17: Preparer Sign Off (Initials, Date) | D17: Signataire préparateur (Initiales, Date)
A18: Owner Sign Off (Initials, Date) | D18: Signataire propriétaire (Initiales, Date)
A19: Assessor Sign Off (Initials, Date) | D19: Signataire évaluateur (Initiales, Date)
A20: Status | B20: Not Started | D20: Statut | E20: Non commencé
A21: Comments | D21: Commentaires

Sheet CM-6-1
A1: Control CM-6(1) — Evidence Tracking | D1: Contrôle CM-6(1) — Suivi des preuves
A2: Control Information | D2: Informations du contrôle
A3: Control Identifier | B3: CM-6(1) | D3: Identifiant du contrôle | E3: CM-6(1)
A4: Family | B4: Configuration Settings | D4: Famille | E4: Paramètres de configuration
A5: Profile | B5: CCCS Medium / PBMM Moderate | D5: Profil | E5: CCCS Moyen / PBMM Modéré
A6: Primary Evidence Tool | D6: Outil de preuve principal
A7: Contributing Tools | D7: Outils contributeurs
A8: Control Description | B8: CONFIGURATION SETTINGS | AUTOMATED CENTRAL MANAGEMENT / APPLICATION / VERIFICATION The organization employs automated mechanisms to centrally manage, apply, and verify configuration settings for organization-defined information system components. | D8: Description du contrôle | E8: PARAMÈTRES DE CONFIGURATION | GESTION, APPLICATION ET VÉRIFICATION CENTRALISÉES ET AUTOMATISÉES L’organisation utilise des mécanismes automatisés pour gérer, appliquer et vérifier de manière centralisée les paramètres de configuration des composants de système d’information définis par l’organisation.
A9: Supplemental Guidance | B9: Related controls: CA-7, CM-4. | D9: Directives supplémentaires | E9: Contrôles connexes : CA-7, CM-4.
A10: Test Case | D10: Cas de test
A11: Test | B11: TEST-CM-6(1) | D11: Test | E11: TEST-CM-6(1)
A12: Requirement ID | B12: CM-6(1) | D12: ID Exigence | E12: CM-6(1)
A13: Component | D13: Composant
A14: Requirement | D14: Exigence
A15: Contextual Design Description | D15: Description contextuelle du design
A16: Evidence Provided | D16: Preuve fournie
A17: Preparer Sign Off (Initials, Date) | D17: Signataire préparateur (Initiales, Date)
A18: Owner Sign Off (Initials, Date) | D18: Signataire propriétaire (Initiales, Date)
A19: Assessor Sign Off (Initials, Date) | D19: Signataire évaluateur (Initiales, Date)
A20: Status | B20: Not Started | D20: Statut | E20: Non commencé
A21: Comments | D21: Commentaires

Sheet CM-7
A1: Control CM-7 — Evidence Tracking | D1: Contrôle CM-7 — Suivi des preuves
A2: Control Information | D2: Informations du contrôle
A3: Control Identifier | B3: CM-7 | D3: Identifiant du contrôle | E3: CM-7
A4: Family | B4: Least Functionality | D4: Famille | E4: Moindre fonctionnalité
A5: Profile | B5: CCCS Medium / PBMM Moderate | D5: Profil | E5: CCCS Moyen / PBMM Modéré
A6: Primary Evidence Tool | D6: Outil de preuve principal
A7: Contributing Tools | D7: Outils contributeurs
A8: Control Description | B8: (A) The organization configures the information system to provide only essential capabilities. (B) The organization prohibits or restricts the use of identified functions, ports, protocols, and/or services following one or more standards from Center for Internet Security (CIS), National Institute of Standards and Technology (NIST), or Defense Information Systems Agency (DISA). | D8: Description du contrôle | E8: (A) L’organisation configure le système d’information pour n’offrir que les capacités essentielles. (B) L’organisation interdit ou restreint l’utilisation de fonctions, de ports, de protocoles et/ou de services identifiés en respectant une ou plusieurs normes du Center for Internet Security (CIS), du National Institute of Standards and Technology (NIST) ou de la Defense Information Systems Agency (DISA).
A9: Supplemental Guidance | B9: Information systems can provide a wide variety of functions and services. Some of the functions and services, provided by default, may not be necessary to support essential organizational operations (e.g., key missions, functions). Additionally, it is sometimes convenient to provide multiple services from single information system components, but doing so increases risk over limiting the services provided by any one component. Where feasible, organizations limit component functionality to a single function per device (e.g., email servers or web servers, but not both). Organizations review functions and services provided by information systems or individual components of information systems, to determine which functions and services are candidates for elimination (e.g., Voice over Internet Protocol (VoIP), Instant Messaging, auto-execute, and file sharing). Organizations consider disabling unused or unnecessary physical and logical ports/protocols (e.g., USB, FTP, IPv6, HTTP) on information systems to prevent unauthorized connection of devices, unauthorized transfer of information, or unauthorized tunnelling. Organizations can utilize network scanning tools, intrusion detection and prevention systems, and end-point protections such as firewalls and host-based intrusion detection systems to identify and prevent the use of prohibited functions, ports, protocols, and services. Related controls: AC-6, CM-2, RA-5, SA-5, SC-7 | D9: Directives supplémentaires | E9: Les systèmes d’information peuvent offrir une grande variété de fonctions et de services. Certaines fonctions et certains services, fournis par défaut, peuvent ne pas être nécessaires au soutien des opérations essentielles de l’organisation (p. ex., missions et fonctions clés). De plus, il est parfois pratique de fournir plusieurs services à partir de composants uniques du système d’information, mais cela augmente le risque de limiter les services fournis par un seul composant. Dans la mesure du possible, les organisations limitent la fonctionnalité des composants à une seule fonction par dispositif (p. ex., serveurs de courriel ou serveurs Web, mais pas les deux). Les organisations examinent les fonctions et les services fournis par les systèmes d’information ou les composants individuels des systèmes d’information afin de déterminer quelles fonctions et quels services peuvent être éliminés (p. ex., voix sur protocole Internet [VoIP], messagerie instantanée, auto-exécution et partage de fichiers). Les organisations envisagent de désactiver les ports/protocoles physiques et logiques inutilisés ou inutiles (p. ex., USB, FTP, IPv6, HTTP) sur les systèmes d’information afin de prévenir la connexion non autorisée d’appareils, le transfert non autorisé d’information ou la tunnellisation non autorisée. Les organisations peuvent utiliser des outils de balayage de réseau, des systèmes de détection et de prévention des intrusions et des mesures de protection d’extrémité comme des pare-feu et des systèmes de détection des intrusions basés sur l’hôte, pour identifier et prévenir l’utilisation de fonctions, de ports, de protocoles et de services interdits. Contrôles connexes : AC-6, CM-2, RA-5, SA-5, SC-7
A10: Test Case | D10: Cas de test
A11: Test | B11: TEST-CM-7 | D11: Test | E11: TEST-CM-7
A12: Requirement ID | B12: CM-7 | D12: ID Exigence | E12: CM-7
A13: Component | D13: Composant
A14: Requirement | D14: Exigence
A15: Contextual Design Description | D15: Description contextuelle du design
A16: Evidence Provided | D16: Preuve fournie
A17: Preparer Sign Off (Initials, Date) | D17: Signataire préparateur (Initiales, Date)
A18: Owner Sign Off (Initials, Date) | D18: Signataire propriétaire (Initiales, Date)
A19: Assessor Sign Off (Initials, Date) | D19: Signataire évaluateur (Initiales, Date)
A20: Status | B20: Not Started | D20: Statut | E20: Non commencé
A21: Comments | D21: Commentaires

Sheet CM-7-1
A1: Control CM-7(1) — Evidence Tracking | D1: Contrôle CM-7(1) — Suivi des preuves
A2: Control Information | D2: Informations du contrôle
A3: Control Identifier | B3: CM-7(1) | D3: Identifiant du contrôle | E3: CM-7(1)
A4: Family | B4: Least Functionality | D4: Famille | E4: Moindre fonctionnalité
A5: Profile | B5: CCCS Medium / PBMM Moderate | D5: Profil | E5: CCCS Moyen / PBMM Modéré
A6: Primary Evidence Tool | D6: Outil de preuve principal
A7: Contributing Tools | D7: Outils contributeurs
A8: Control Description | B8: LEAST FUNCTIONALITY | PERIODIC REVIEW The organization reviews the information system at least annually to identify unnecessary and/or non-secure functions, ports, protocols, and services; and The organization disables all functions, ports, protocols, and services within the information system deemed to be unnecessary and/or nonsecure. | D8: Description du contrôle | E8: MOINDRE FONCTIONNALITÉ | EXAMEN PÉRIODIQUE L’organisation revoit le système d’information au moins une fois par année afin de repérer les fonctions, les ports, les protocoles et les services inutiles ou non sécurisés; L’organisation désactive toutes les fonctions, tous les ports, tous les protocoles et tous les services du système d’information jugés inutiles ou non sécurisés.
A9: Supplemental Guidance | B9: The organization can either make a determination of the relative security of the function, port, protocol, and/or service or base the security decision on the assessment of other entities. Bluetooth, FTP, and peer-to-peer networking are examples of less than secure protocols. Related controls: AC-18, CM-7, IA-2. | D9: Directives supplémentaires | E9: L’organisation peut soit déterminer la sécurité relative de la fonction, du port, du protocole ou du service, soit baser sa décision en matière de sécurité sur l’évaluation d’autres entités. Bluetooth, FTP et l’interconnexion de réseaux d’égal à égal sont des exemples de protocoles moins sécurisés. Contrôles connexes : AC-18, CM-7, IA-2.
A10: Test Case | D10: Cas de test
A11: Test | B11: TEST-CM-7(1) | D11: Test | E11: TEST-CM-7(1)
A12: Requirement ID | B12: CM-7(1) | D12: ID Exigence | E12: CM-7(1)
A13: Component | D13: Composant
A14: Requirement | D14: Exigence
A15: Contextual Design Description | D15: Description contextuelle du design
A16: Evidence Provided | D16: Preuve fournie
A17: Preparer Sign Off (Initials, Date) | D17: Signataire préparateur (Initiales, Date)
A18: Owner Sign Off (Initials, Date) | D18: Signataire propriétaire (Initiales, Date)
A19: Assessor Sign Off (Initials, Date) | D19: Signataire évaluateur (Initiales, Date)
A20: Status | B20: Not Started | D20: Statut | E20: Non commencé
A21: Comments | D21: Commentaires

Sheet CM-8-2
A1: Control CM-8(2) — Evidence Tracking | D1: Contrôle CM-8(2) — Suivi des preuves
A2: Control Information | D2: Informations du contrôle
A3: Control Identifier | B3: CM-8(2) | D3: Identifiant du contrôle | E3: CM-8(2)
A4: Family | B4: Information System Component Inventory | D4: Famille | E4: Inventaire des composants du système d’information
A5: Profile | B5: CCCS Medium / PBMM Moderate | D5: Profil | E5: CCCS Moyen / PBMM Modéré
A6: Primary Evidence Tool | D6: Outil de preuve principal
A7: Contributing Tools | D7: Outils contributeurs
A8: Control Description | B8: INFORMATION SYSTEM COMPONENT INVENTORY | AUTOMATED MAINTENANCE The organization employs automated mechanisms to help maintain an up-to-date, complete, accurate, and readily available inventory of information system components. | D8: Description du contrôle | E8: INVENTAIRE DES COMPOSANTS DU SYSTÈME D’INFORMATION | MAINTENANCE AUTOMATISÉE L’organisation utilise des mécanismes automatisés pour maintenir un inventaire complet, précis, à jour et facilement accessible des composants du système d’information.
A9: Supplemental Guidance | B9: Organizations maintain information system inventories to the extent feasible. Virtual machines, for example, can be difficult to monitor because such machines are not visible to the network when not in use. In such cases, organizations maintain as up-to-date, complete, and accurate an inventory as is deemed reasonable. This control enhancement can be satisfied by the implementation of CM-2 (2) for organizations that choose to combine information system component inventory and baseline configuration activities. Related control: SI-7. | D9: Directives supplémentaires | E9: Les organisations tiennent des inventaires de systèmes d’information dans la mesure où il est possible de le faire. Les machines virtuelles, par exemple, peuvent être difficiles à surveiller parce qu’elles ne sont pas visibles sur le réseau lorsqu’elles ne sont pas utilisées. Dans de tels cas, les organisations tiennent un inventaire aussi à jour, complet et exact que jugé raisonnable. Cette amélioration du contrôle peut être réalisée par la mise en œuvre du CM-2 (2) pour les organisations qui choisissent de combiner l’inventaire des composants du système d’information et les activités de configuration de base. Contrôle connexe : SI-7.
A10: Test Case | D10: Cas de test
A11: Test | B11: TEST-CM-8(2) | D11: Test | E11: TEST-CM-8(2)
A12: Requirement ID | B12: CM-8(2) | D12: ID Exigence | E12: CM-8(2)
A13: Component | D13: Composant
A14: Requirement | D14: Exigence
A15: Contextual Design Description | D15: Description contextuelle du design
A16: Evidence Provided | D16: Preuve fournie
A17: Preparer Sign Off (Initials, Date) | D17: Signataire préparateur (Initiales, Date)
A18: Owner Sign Off (Initials, Date) | D18: Signataire propriétaire (Initiales, Date)
A19: Assessor Sign Off (Initials, Date) | D19: Signataire évaluateur (Initiales, Date)
A20: Status | B20: Not Started | D20: Statut | E20: Non commencé
A21: Comments | D21: Commentaires

Sheet CM-8-5
A1: Control CM-8(5) — Evidence Tracking | D1: Contrôle CM-8(5) — Suivi des preuves
A2: Control Information | D2: Informations du contrôle
A3: Control Identifier | B3: CM-8(5) | D3: Identifiant du contrôle | E3: CM-8(5)
A4: Family | B4: Information System Component Inventory | D4: Famille | E4: Inventaire des composants du système d’information
A5: Profile | B5: CCCS Medium / PBMM Moderate | D5: Profil | E5: CCCS Moyen / PBMM Modéré
A6: Primary Evidence Tool | D6: Outil de preuve principal
A7: Contributing Tools | D7: Outils contributeurs
A8: Control Description | B8: INFORMATION SYSTEM COMPONENT INVENTORY | NO DUPLICATE ACCOUNTING OF COMPONENTS The organization verifies that all components within the authorization boundary of the information system are not duplicated in other information system component inventories. | D8: Description du contrôle | E8: INVENTAIRE DES COMPOSANTS DU SYSTÈME D’INFORMATION | AUCUNE COMPTABILISATION EN DOUBLE DES COMPOSANTS L’organisation vérifie que tous les composants à l’intérieur des limites d’autorisation du système d’information ne sont pas reproduits dans d’autres inventaires de composants du système d’information.
A9: Supplemental Guidance | B9: This control enhancement addresses the potential problem of duplicate accounting of information system components in large or complex interconnected systems. | D9: Directives supplémentaires | E9: Cette amélioration du contrôle vise à régler le problème potentiel d’une comptabilisation en double des composants du système d’information dans les grands systèmes ou les systèmes interconnectés ou complexes.
A10: Test Case | D10: Cas de test
A11: Test | B11: TEST-CM-8(5) | D11: Test | E11: TEST-CM-8(5)
A12: Requirement ID | B12: CM-8(5) | D12: ID Exigence | E12: CM-8(5)
A13: Component | D13: Composant
A14: Requirement | D14: Exigence
A15: Contextual Design Description | D15: Description contextuelle du design
A16: Evidence Provided | D16: Preuve fournie
A17: Preparer Sign Off (Initials, Date) | D17: Signataire préparateur (Initiales, Date)
A18: Owner Sign Off (Initials, Date) | D18: Signataire propriétaire (Initiales, Date)
A19: Assessor Sign Off (Initials, Date) | D19: Signataire évaluateur (Initiales, Date)
A20: Status | B20: Not Started | D20: Statut | E20: Non commencé
A21: Comments | D21: Commentaires

Sheet CP-6
A1: Control CP-6 — Evidence Tracking | D1: Contrôle CP-6 — Suivi des preuves
A2: Control Information | D2: Informations du contrôle
A3: Control Identifier | B3: CP-6 | D3: Identifiant du contrôle | E3: CP-6
A4: Family | B4: Alternate Storage Site | D4: Famille | E4: Site de stockage auxiliaire
A5: Profile | B5: CCCS Medium / PBMM Moderate | D5: Profil | E5: CCCS Moyen / PBMM Modéré
A6: Primary Evidence Tool | D6: Outil de preuve principal
A7: Contributing Tools | D7: Outils contributeurs
A8: Control Description | B8: (A) The organization establishes an alternate storage site including necessary agreements to permit the storage and retrieval of information system backup information. (B) The organization ensures that the alternate storage site provides information security safeguards equivalent to that of the primary site. | D8: Description du contrôle | E8: (A) L’organisation établit un site de stockage auxiliaire, incluant les ententes nécessaires pour permettre le stockage et l’extraction de l’information de sauvegarde du système d’information. (B) L’organisation veille à ce que le site de stockage auxiliaire offre des mesures de sécurité de l’information équivalentes à celles du site principal.
A9: Supplemental Guidance | B9: Alternate storage sites are sites that are geographically distinct from primary storage sites. An alternate storage site maintains duplicate copies of information and data in the event that the primary storage site is not available. Items covered by alternate storage site agreements include, for example, environmental conditions at alternate sites, access rules, physical and environmental protection requirements, and coordination of delivery/retrieval of backup media. Alternate storage sites reflect the requirements in contingency plans so that organizations can maintain essential missions/business functions despite disruption, compromise, or failure in organizational information systems. Related controls: CP-2, CP-7, CP-9, CP-10, MP-4 | D9: Directives supplémentaires | E9: Les sites de stockage auxiliaires sont des sites qui sont géographiquement séparés des sites de stockage principaux. Un site de stockage auxiliaire conserve des copies de l’information et des données advenant la non-disponibilité du site de stockage principal. Les éléments couverts par les accords sur les sites de stockage auxiliaires comprennent, par exemple, les conditions environnementales aux sites auxiliaires, les règles d’accès, les exigences en matière de protection physique et environnementale, et la coordination de la livraison/récupération des supports de sauvegarde. Les sites de stockage auxiliaires reflètent les exigences des plans d’urgence afin que les organisations puissent maintenir les fonctions opérationnelles et de mission essentielles malgré la perturbation, la compromission ou la défaillance des systèmes d’information organisationnels. Contrôles connexes : CP-2, CP-7, CP-9, CP-10, MP-4
A10: Test Case | D10: Cas de test
A11: Test | B11: TEST-CP-6 | D11: Test | E11: TEST-CP-6
A12: Requirement ID | B12: CP-6 | D12: ID Exigence | E12: CP-6
A13: Component | D13: Composant
A14: Requirement | D14: Exigence
A15: Contextual Design Description | D15: Description contextuelle du design
A16: Evidence Provided | D16: Preuve fournie
A17: Preparer Sign Off (Initials, Date) | D17: Signataire préparateur (Initiales, Date)
A18: Owner Sign Off (Initials, Date) | D18: Signataire propriétaire (Initiales, Date)
A19: Assessor Sign Off (Initials, Date) | D19: Signataire évaluateur (Initiales, Date)
A20: Status | B20: Not Started | D20: Statut | E20: Non commencé
A21: Comments | D21: Commentaires

Sheet CP-6-2
A1: Control CP-6(2) — Evidence Tracking | D1: Contrôle CP-6(2) — Suivi des preuves
A2: Control Information | D2: Informations du contrôle
A3: Control Identifier | B3: CP-6(2) | D3: Identifiant du contrôle | E3: CP-6(2)
A4: Family | B4: Alternate Storage Site | D4: Famille | E4: Site de stockage auxiliaire
A5: Profile | B5: CCCS Medium / PBMM Moderate | D5: Profil | E5: CCCS Moyen / PBMM Modéré
A6: Primary Evidence Tool | D6: Outil de preuve principal
A7: Contributing Tools | D7: Outils contributeurs
A8: Control Description | B8: ALTERNATE STORAGE SITE | RECOVERY TIME / POINT OBJECTIVES The organization configures the alternate storage site to facilitate recovery operations in accordance with recovery time and recovery point objectives. | D8: Description du contrôle | E8: SITE DE STOCKAGE AUXILIAIRE | OBJECTIFS EN MATIÈRE DE DÉLAIS/POINTS DE REPRISE L’organisation configure le site de stockage auxiliaire de manière à faciliter les opérations de reprise conformément aux objectifs en matière de délais et de points de reprise.
A9: Supplemental Guidance | D9: Directives supplémentaires
A10: Test Case | D10: Cas de test
A11: Test | B11: TEST-CP-6(2) | D11: Test | E11: TEST-CP-6(2)
A12: Requirement ID | B12: CP-6(2) | D12: ID Exigence | E12: CP-6(2)
A13: Component | D13: Composant
A14: Requirement | D14: Exigence
A15: Contextual Design Description | D15: Description contextuelle du design
A16: Evidence Provided | D16: Preuve fournie
A17: Preparer Sign Off (Initials, Date) | D17: Signataire préparateur (Initiales, Date)
A18: Owner Sign Off (Initials, Date) | D18: Signataire propriétaire (Initiales, Date)
A19: Assessor Sign Off (Initials, Date) | D19: Signataire évaluateur (Initiales, Date)
A20: Status | B20: Not Started | D20: Statut | E20: Non commencé
A21: Comments | D21: Commentaires

Sheet CP-7
A1: Control CP-7 — Evidence Tracking | D1: Contrôle CP-7 — Suivi des preuves
A2: Control Information | D2: Informations du contrôle
A3: Control Identifier | B3: CP-7 | D3: Identifiant du contrôle | E3: CP-7
A4: Family | B4: Alternate Processing Site | D4: Famille | E4: Site de traitement auxiliaire
A5: Profile | B5: CCCS Medium / PBMM Moderate | D5: Profil | E5: CCCS Moyen / PBMM Modéré
A6: Primary Evidence Tool | D6: Outil de preuve principal
A7: Contributing Tools | D7: Outils contributeurs
A8: Control Description | B8: (A) The organization establishes an alternate processing site including necessary agreements to permit the transfer and resumption of organization-defined information system operations for essential missions/business functions within organization-defined time period consistent with recovery time and recovery point objectives when the primary processing capabilities are unavailable. (B) The organization ensures that equipment and supplies required to transfer and resume operations are available at the alternate processing site or contracts are in place to support delivery to the site within the organization-defined time period for transfer/resumption. (C) The organization ensures that the alternate processing site provides information security safeguards equivalent to that of the primary site. | D8: Description du contrôle | E8: (A) L’organisation établit un site de traitement auxiliaire, y compris les ententes nécessaires pour permettre le transfert et la reprise des opérations du système d’information définies par l’organisation pour les missions et les fonctions opérationnelles essentielles à l’intérieur d’une période définie par l’organisation, conformément aux objectifs en matière de délais de reprise et de points de reprise lorsque les capacités de traitement principales ne sont pas disponibles. (B) L’organisation veille à ce que l’équipement et les fournitures nécessaires au transfert et à la reprise des activités soient disponibles au site de traitement auxiliaire, ou à ce que des contrats soient en place pour soutenir la livraison au site à l’intérieur de la période définie par l’organisation pour le transfert ou la reprise. (C) L’organisation veille à ce que le site de traitement auxiliaire offre des mesures de sécurité de l’information équivalentes à celles du site principal.
A9: Supplemental Guidance | B9: Alternate processing sites are sites that are geographically distinct from primary processing sites. An alternate processing site provides processing capability in the event that the primary processing site is not available. Items covered by alternate processing site agreements include, for example, environmental conditions at alternate sites, access rules, physical and environmental protection requirements, and coordination for the transfer/assignment of personnel. Requirements are specifically allocated to alternate processing sites that reflect the requirements in contingency plans to maintain essential missions/business functions despite disruption, compromise, or failure in organizational information systems. Related controls: CP-2, CP-6, CP-8, CP-9, CP-10, MA-6 | D9: Directives supplémentaires | E9: Les sites de traitement auxiliaires sont des sites qui sont géographiquement séparés des sites de traitement principaux. Un site de traitement auxiliaire offre une capacité de traitement lorsque le site de traitement principal n’est pas disponible. Les éléments couverts par les accords sur les sites de traitement auxiliaires comprennent, par exemple, les conditions environnementales aux sites auxiliaires, les règles d’accès, les exigences en matière de protection physique et environnementale, et la coordination pour le transfert ou l’attribution du personnel. Les exigences spécifiquement attribuées aux sites de traitement auxiliaires reflètent les exigences des plans d’urgence pour maintenir les fonctions opérationnelles et de mission essentielles malgré la perturbation, la compromission ou la défaillance des systèmes d’information organisationnels. Contrôles connexes : CP-2, CP-6, CP-8, CP-9, CP-10, MA-6
A10: Test Case | D10: Cas de test
A11: Test | B11: TEST-CP-7 | D11: Test | E11: TEST-CP-7
A12: Requirement ID | B12: CP-7 | D12: ID Exigence | E12: CP-7
A13: Component | D13: Composant
A14: Requirement | D14: Exigence
A15: Contextual Design Description | D15: Description contextuelle du design
A16: Evidence Provided | D16: Preuve fournie
A17: Preparer Sign Off (Initials, Date) | D17: Signataire préparateur (Initiales, Date)
A18: Owner Sign Off (Initials, Date) | D18: Signataire propriétaire (Initiales, Date)
A19: Assessor Sign Off (Initials, Date) | D19: Signataire évaluateur (Initiales, Date)
A20: Status | B20: Not Started | D20: Statut | E20: Non commencé
A21: Comments | D21: Commentaires

Sheet CP-7-1
A1: Control CP-7(1) — Evidence Tracking | D1: Contrôle CP-7(1) — Suivi des preuves
A2: Control Information | D2: Informations du contrôle
A3: Control Identifier | B3: CP-7(1) | D3: Identifiant du contrôle | E3: CP-7(1)
A4: Family | B4: Alternate Processing Site | D4: Famille | E4: Site de traitement auxiliaire
A5: Profile | B5: CCCS Medium / PBMM Moderate | D5: Profil | E5: CCCS Moyen / PBMM Modéré
A6: Primary Evidence Tool | D6: Outil de preuve principal
A7: Contributing Tools | D7: Outils contributeurs
A8: Control Description | B8: ALTERNATE PROCESSING SITE | SEPARATION FROM PRIMARY SITE The organization identifies an alternate processing site that is separated from the primary processing site to reduce susceptibility to the same threats. | D8: Description du contrôle | E8: SITE DE TRAITEMENT AUXILIAIRE | SÉPARATION DU SITE PRINCIPAL L’organisation détermine un site de traitement auxiliaire qui est séparé du site de traitement principal afin de réduire sa vulnérabilité aux mêmes menaces.
A9: Supplemental Guidance | B9: Threats that affect alternate processing sites are typically defined in organizational assessments of risk and include, for example, natural disasters, structural failures, hostile cyber-attacks, and errors of omission/commission. Organizations determine what is considered a sufficient degree of separation between primary and alternate processing sites based on the types of threats that are of concern. For one particular type of threat (i.e., hostile cyber-attack), the degree of separation between sites is less relevant. Related control: RA-3. | D9: Directives supplémentaires | E9: Les menaces qui touchent les sites de traitement auxiliaires sont généralement définies dans les évaluations organisationnelles des risques et comprennent, par exemple, les catastrophes naturelles, les défaillances structurelles, les cyberattaques hostiles et les erreurs d’omission ou de commission. Les organisations déterminent un degré de séparation considéré comme suffisant entre les sites de traitement principaux et auxiliaires en fonction des types de menaces qui sont préoccupantes. Pour un type particulier de menace (p. ex. les cyberattaques hostiles), le degré de séparation entre les sites est moins pertinent. Contrôle connexe : RA-3.
A10: Test Case | D10: Cas de test
A11: Test | B11: TEST-CP-7(1) | D11: Test | E11: TEST-CP-7(1)
A12: Requirement ID | B12: CP-7(1) | D12: ID Exigence | E12: CP-7(1)
A13: Component | D13: Composant
A14: Requirement | D14: Exigence
A15: Contextual Design Description | D15: Description contextuelle du design
A16: Evidence Provided | D16: Preuve fournie
A17: Preparer Sign Off (Initials, Date) | D17: Signataire préparateur (Initiales, Date)
A18: Owner Sign Off (Initials, Date) | D18: Signataire propriétaire (Initiales, Date)
A19: Assessor Sign Off (Initials, Date) | D19: Signataire évaluateur (Initiales, Date)
A20: Status | B20: Not Started | D20: Statut | E20: Non commencé
A21: Comments | D21: Commentaires

Sheet CP-7-4
A1: Control CP-7(4) — Evidence Tracking | D1: Contrôle CP-7(4) — Suivi des preuves
A2: Control Information | D2: Informations du contrôle
A3: Control Identifier | B3: CP-7(4) | D3: Identifiant du contrôle | E3: CP-7(4)
A4: Family | B4: Alternate Processing Site | D4: Famille | E4: Site de traitement auxiliaire
A5: Profile | B5: CCCS Medium / PBMM Moderate | D5: Profil | E5: CCCS Moyen / PBMM Modéré
A6: Primary Evidence Tool | D6: Outil de preuve principal
A7: Contributing Tools | D7: Outils contributeurs
A8: Control Description | B8: ALTERNATE PROCESSING SITE | PREPARATION FOR USE The organization prepares the alternate processing site so that the site is ready to be used as the operational site supporting essential missions and business functions. | D8: Description du contrôle | E8: SITE DE TRAITEMENT AUXILIAIRE | PRÉPARATION À L’UTILISATION L’organisation prépare le site de traitement auxiliaire de manière à ce que le site soit prêt à être utilisé comme site opérationnel prenant en charge les fonctions opérationnelles et les missions essentielles.
A9: Supplemental Guidance | B9: Site preparation includes, for example, establishing configuration settings for information system components at the alternate processing site consistent with the requirements for such settings at the primary site and ensuring that essential supplies and other logistical considerations are in place. Related controls: CM-2, CM-6. | D9: Directives supplémentaires | E9: La préparation du site comprend, par exemple, l’établissement des paramètres de configuration pour les composants du système d’information au site de traitement auxiliaire, conformément aux exigences pour ces paramètres au site principal, et l’assurance que les fournitures essentielles et autres considérations logistiques sont en place. Contrôles connexes : CM-2, CM-6.
A10: Test Case | D10: Cas de test
A11: Test | B11: TEST-CP-7(4) | D11: Test | E11: TEST-CP-7(4)
A12: Requirement ID | B12: CP-7(4) | D12: ID Exigence | E12: CP-7(4)
A13: Component | D13: Composant
A14: Requirement | D14: Exigence
A15: Contextual Design Description | D15: Description contextuelle du design
A16: Evidence Provided | D16: Preuve fournie
A17: Preparer Sign Off (Initials, Date) | D17: Signataire préparateur (Initiales, Date)
A18: Owner Sign Off (Initials, Date) | D18: Signataire propriétaire (Initiales, Date)
A19: Assessor Sign Off (Initials, Date) | D19: Signataire évaluateur (Initiales, Date)
A20: Status | B20: Not Started | D20: Statut | E20: Non commencé
A21: Comments | D21: Commentaires

Sheet CP-9
A1: Control CP-9 — Evidence Tracking | D1: Contrôle CP-9 — Suivi des preuves
A2: Control Information | D2: Informations du contrôle
A3: Control Identifier | B3: CP-9 | D3: Identifiant du contrôle | E3: CP-9
A4: Family | B4: Information System Backup | D4: Famille | E4: Sauvegarde du système d’information
A5: Profile | B5: CCCS Medium / PBMM Moderate | D5: Profil | E5: CCCS Moyen / PBMM Modéré
A6: Primary Evidence Tool | D6: Outil de preuve principal
A7: Contributing Tools | D7: Outils contributeurs
A8: Control Description | B8: (A) The organization conducts backups of user-level information contained in the information system daily incremental; weekly full. (B) The organization conducts backups of system-level information contained in the information system daily incremental; weekly full. (C) The organization conducts backups of information system documentation including security-related documentation daily incremental; weekly full. (D) The organization protects the confidentiality, integrity, and availability of backup information at storage locations. (AA) The organization determines retention periods for essential business information and archived backups. | D8: Description du contrôle | E8: (A) L’organisation effectue des sauvegardes incrémentielles quotidiennes et des sauvegardes hebdomadaires complètes de l’information au niveau de l’utilisateur qui est contenue dans le système d’information. (B) L’organisation effectue des sauvegardes incrémentielles quotidiennes et des sauvegardes hebdomadaires complètes de l’information au niveau du système contenue dans le système d’information. (C) L’organisation effectue des sauvegardes incrémentielles quotidiennes et des sauvegardes hebdomadaires complètes de la documentation relative au système d’information, y compris la documentation liée à la sécurité. (D) L’organisation protège la confidentialité, l’intégrité et la disponibilité de l’information de sauvegarde aux emplacements de stockage. (AA) L’organisation détermine les périodes de conservation des renseignements opérationnels essentiels et des sauvegardes archivées.
A9: Supplemental Guidance | B9: System-level information includes, for example, system-state information, operating system and application software, and licenses. User-level information includes any information other than system-level information. Mechanisms employed by organizations to protect the integrity of information system backups include, for example, digital signatures and cryptographic hashes. Protection of system backup information while in transit is beyond the scope of this control. Information system backups reflect the requirements in contingency plans as well as other organizational requirements for backing up information. Related controls: CP-2, CP-6, MP-4, MP-5, SC-13 | D9: Directives supplémentaires | E9: L’information au niveau du système comprend, par exemple, l’information sur l’état du système, le système d’exploitation, les logiciels d’application et les licences. L’information au niveau de l’utilisateur comprend toute information autre que l’information au niveau du système. Les mécanismes employés par les organisations pour protéger l’intégrité des sauvegardes du système d’information comprennent, par exemple, les signatures numériques et le hachage cryptographique. La protection de l’information de sauvegarde du système pendant le transport dépasse la portée de ce contrôle. Les sauvegardes du système d’information reflètent les exigences des plans d’urgence ainsi que d’autres exigences organisationnelles relatives à la sauvegarde de l’information. Contrôles connexes : CP-2, CP-6, MP-4, MP-5, SC-13
A10: Test Case | D10: Cas de test
A11: Test | B11: TEST-CP-9 | D11: Test | E11: TEST-CP-9
A12: Requirement ID | B12: CP-9 | D12: ID Exigence | E12: CP-9
A13: Component | D13: Composant
A14: Requirement | D14: Exigence
A15: Contextual Design Description | D15: Description contextuelle du design
A16: Evidence Provided | D16: Preuve fournie
A17: Preparer Sign Off (Initials, Date) | D17: Signataire préparateur (Initiales, Date)
A18: Owner Sign Off (Initials, Date) | D18: Signataire propriétaire (Initiales, Date)
A19: Assessor Sign Off (Initials, Date) | D19: Signataire évaluateur (Initiales, Date)
A20: Status | B20: Not Started | D20: Statut | E20: Non commencé
A21: Comments | D21: Commentaires

Sheet CP-9-1
A1: Control CP-9(1) — Evidence Tracking | D1: Contrôle CP-9(1) — Suivi des preuves
A2: Control Information | D2: Informations du contrôle
A3: Control Identifier | B3: CP-9(1) | D3: Identifiant du contrôle | E3: CP-9(1)
A4: Family | B4: Information System Backup | D4: Famille | E4: Sauvegarde du système d’information
A5: Profile | B5: CCCS Medium / PBMM Moderate | D5: Profil | E5: CCCS Moyen / PBMM Modéré
A6: Primary Evidence Tool | D6: Outil de preuve principal
A7: Contributing Tools | D7: Outils contributeurs
A8: Control Description | B8: INFORMATION SYSTEM BACKUP | TESTING FOR RELIABILITY / INTEGRITY The organization tests backup information at least annually to verify media reliability and information integrity. | D8: Description du contrôle | E8: SAUVEGARDE DU SYSTÈME D’INFORMATION | VÉRIFICATION DE LA FIABILITÉ ET DE L’INTÉGRITÉ L’organisation teste l’information de sauvegarde au moins une fois par année pour vérifier la fiabilité des supports et l’intégrité de l’information.
A9: Supplemental Guidance | B9: Related control: CP-4. | D9: Directives supplémentaires | E9: Contrôle connexe : CP-4.
A10: Test Case | D10: Cas de test
A11: Test | B11: TEST-CP-9(1) | D11: Test | E11: TEST-CP-9(1)
A12: Requirement ID | B12: CP-9(1) | D12: ID Exigence | E12: CP-9(1)
A13: Component | D13: Composant
A14: Requirement | D14: Exigence
A15: Contextual Design Description | D15: Description contextuelle du design
A16: Evidence Provided | D16: Preuve fournie
A17: Preparer Sign Off (Initials, Date) | D17: Signataire préparateur (Initiales, Date)
A18: Owner Sign Off (Initials, Date) | D18: Signataire propriétaire (Initiales, Date)
A19: Assessor Sign Off (Initials, Date) | D19: Signataire évaluateur (Initiales, Date)
A20: Status | B20: Not Started | D20: Statut | E20: Non commencé
A21: Comments | D21: Commentaires

Sheet CP-9-2
A1: Control CP-9(2) — Evidence Tracking | D1: Contrôle CP-9(2) — Suivi des preuves
A2: Control Information | D2: Informations du contrôle
A3: Control Identifier | B3: CP-9(2) | D3: Identifiant du contrôle | E3: CP-9(2)
A4: Family | B4: Information System Backup | D4: Famille | E4: Sauvegarde du système d’information
A5: Profile | B5: CCCS Medium / PBMM Moderate | D5: Profil | E5: CCCS Moyen / PBMM Modéré
A6: Primary Evidence Tool | D6: Outil de preuve principal
A7: Contributing Tools | D7: Outils contributeurs
A8: Control Description | B8: INFORMATION SYSTEM BACKUP | TEST RESTORATION USING SAMPLING The organization uses a sample of backup information in the restoration of selected information system functions as part of contingency plan testing. | D8: Description du contrôle | E8: SAUVEGARDE DU SYSTÈME D’INFORMATION | ESSAIS DE RESTAURATION AU MOYEN DE L’ÉCHANTILLONNAGE L’organisation utilise un échantillon de l’information de sauvegarde pour restaurer certaines fonctions du système d’information dans le cadre de la mise à l’essai du plan d’urgence.
A9: Supplemental Guidance | B9: Related control: CP-4. | D9: Directives supplémentaires | E9: Contrôle connexe : CP-4.
A10: Test Case | D10: Cas de test
A11: Test | B11: TEST-CP-9(2) | D11: Test | E11: TEST-CP-9(2)
A12: Requirement ID | B12: CP-9(2) | D12: ID Exigence | E12: CP-9(2)
A13: Component | D13: Composant
A14: Requirement | D14: Exigence
A15: Contextual Design Description | D15: Description contextuelle du design
A16: Evidence Provided | D16: Preuve fournie
A17: Preparer Sign Off (Initials, Date) | D17: Signataire préparateur (Initiales, Date)
A18: Owner Sign Off (Initials, Date) | D18: Signataire propriétaire (Initiales, Date)
A19: Assessor Sign Off (Initials, Date) | D19: Signataire évaluateur (Initiales, Date)
A20: Status | B20: Not Started | D20: Statut | E20: Non commencé
A21: Comments | D21: Commentaires

Sheet CP-9-3
A1: Control CP-9(3) — Evidence Tracking | D1: Contrôle CP-9(3) — Suivi des preuves
A2: Control Information | D2: Informations du contrôle
A3: Control Identifier | B3: CP-9(3) | D3: Identifiant du contrôle | E3: CP-9(3)
A4: Family | B4: Information System Backup | D4: Famille | E4: Sauvegarde du système d’information
A5: Profile | B5: CCCS Medium / PBMM Moderate | D5: Profil | E5: CCCS Moyen / PBMM Modéré
A6: Primary Evidence Tool | D6: Outil de preuve principal
A7: Contributing Tools | D7: Outils contributeurs
A8: Control Description | B8: INFORMATION SYSTEM BACKUP | SEPARATE STORAGE FOR CRITICAL INFORMATION The organization stores backup copies of all operating system and critical software code in a separate facility or in a fire-rated container that is not collocated with the operational system. | D8: Description du contrôle | E8: SAUVEGARDE DU SYSTÈME D’INFORMATION | STOCKAGE SÉPARÉ POUR L’INFORMATION ESSENTIELLE L’organisation stocke des copies de sauvegarde de tous les systèmes d’exploitation et du code logiciel essentiel dans une installation séparée ou dans un contenant résistant au feu qui n’est pas situé au même endroit que le système opérationnel.
A9: Supplemental Guidance | B9: Critical information system software includes, for example, operating systems, cryptographic key management systems, and intrusion detection/prevention systems. Security-related information includes, for example, organizational inventories of hardware, software, and firmware components. Alternate storage sites typically serve as separate storage facilities for organizations. Related controls: CM-2, CM-8. | D9: Directives supplémentaires | E9: Le logiciel essentiel du système d’information comprend, par exemple, les systèmes d’exploitation, les systèmes de gestion des clés cryptographiques et les systèmes de détection et de prévention des intrusions. L’information liée à la sécurité comprend, par exemple, les inventaires organisationnels des composants matériels, logiciels et micrologiciels. Les sites de stockage auxiliaires servent habituellement d’installations de stockage distinctes pour les organisations. Contrôles connexes : CM-2, CM-8.
A10: Test Case | D10: Cas de test
A11: Test | B11: TEST-CP-9(3) | D11: Test | E11: TEST-CP-9(3)
A12: Requirement ID | B12: CP-9(3) | D12: ID Exigence | E12: CP-9(3)
A13: Component | D13: Composant
A14: Requirement | D14: Exigence
A15: Contextual Design Description | D15: Description contextuelle du design
A16: Evidence Provided | D16: Preuve fournie
A17: Preparer Sign Off (Initials, Date) | D17: Signataire préparateur (Initiales, Date)
A18: Owner Sign Off (Initials, Date) | D18: Signataire propriétaire (Initiales, Date)
A19: Assessor Sign Off (Initials, Date) | D19: Signataire évaluateur (Initiales, Date)
A20: Status | B20: Not Started | D20: Statut | E20: Non commencé
A21: Comments | D21: Commentaires

Sheet CP-9-5
A1: Control CP-9(5) — Evidence Tracking | D1: Contrôle CP-9(5) — Suivi des preuves
A2: Control Information | D2: Informations du contrôle
A3: Control Identifier | B3: CP-9(5) | D3: Identifiant du contrôle | E3: CP-9(5)
A4: Family | B4: Information System Backup | D4: Famille | E4: Sauvegarde du système d’information
A5: Profile | B5: CCCS Medium / PBMM Moderate | D5: Profil | E5: CCCS Moyen / PBMM Modéré
A6: Primary Evidence Tool | D6: Outil de preuve principal
A7: Contributing Tools | D7: Outils contributeurs
A8: Control Description | B8: INFORMATION SYSTEM BACKUP | TRANSFER TO ALTERNATE STORAGE SITE The organization transfers information system backup information to the alternate storage site at organization-defined time period and transfer rate consistent with the recovery time and recovery point objectives. | D8: Description du contrôle | E8: SAUVEGARDE DU SYSTÈME D’INFORMATION | TRANSFERT À UN SITE DE STOCKAGE AUXILIAIRE L’organisation transfère l’information de sauvegarde du système d’information au site de stockage auxiliaire au moment et à la vitesse de transfert définis par l’organisation conformément aux objectifs en matière de délais et de points de reprise.
A9: Supplemental Guidance | B9: Information system backup information can be transferred to alternate storage sites either electronically or by physical shipment of storage media. | D9: Directives supplémentaires | E9: Les données de sauvegarde du système d’information peuvent être transférées à des sites de stockage auxiliaires par voie électronique ou par envoi physique de supports de stockage.
A10: Test Case | D10: Cas de test
A11: Test | B11: TEST-CP-9(5) | D11: Test | E11: TEST-CP-9(5)
A12: Requirement ID | B12: CP-9(5) | D12: ID Exigence | E12: CP-9(5)
A13: Component | D13: Composant
A14: Requirement | D14: Exigence
A15: Contextual Design Description | D15: Description contextuelle du design
A16: Evidence Provided | D16: Preuve fournie
A17: Preparer Sign Off (Initials, Date) | D17: Signataire préparateur (Initiales, Date)
A18: Owner Sign Off (Initials, Date) | D18: Signataire propriétaire (Initiales, Date)
A19: Assessor Sign Off (Initials, Date) | D19: Signataire évaluateur (Initiales, Date)
A20: Status | B20: Not Started | D20: Statut | E20: Non commencé
A21: Comments | D21: Commentaires

Sheet CP-10
A1: Control CP-10 — Evidence Tracking | D1: Contrôle CP-10 — Suivi des preuves
A2: Control Information | D2: Informations du contrôle
A3: Control Identifier | B3: CP-10 | D3: Identifiant du contrôle | E3: CP-10
A4: Family | B4: Information System Recovery and Reconstitution | D4: Famille | E4: Reprise et reconstitution du système d’information
A5: Profile | B5: CCCS Medium / PBMM Moderate | D5: Profil | E5: CCCS Moyen / PBMM Modéré
A6: Primary Evidence Tool | D6: Outil de preuve principal
A7: Contributing Tools | D7: Outils contributeurs
A8: Control Description | B8: (A) The organization provides for the recovery and reconstitution of the information system to a known state after a disruption, compromise, or failure. | D8: Description du contrôle | E8: (A) L’organisation assure la reprise et la reconstitution du système d’information dans un état connu après une perturbation, une compromission ou une défaillance.
A9: Supplemental Guidance | B9: Recovery is executing information system contingency plan activities to restore organizational missions/business functions. Reconstitution takes place following recovery and includes activities for returning organizational information systems to fully operational states. Recovery and reconstitution operations reflect mission and business priorities, recovery point/time and reconstitution objectives, and established organizational metrics consistent with contingency plan requirements. Reconstitution includes the deactivation of any interim information system capabilities that may have been needed during recovery operations. Reconstitution also includes assessments of fully restored information system capabilities, reestablishment of continuous monitoring activities, potential information system reauthorizations, and activities to prepare the systems against future disruptions, compromises, or failures. Recovery/reconstitution capabilities employed by organizations can include both automated mechanisms and manual procedures. Related controls: CA-2, CA-6, CA-7, CP-2, CP-4, CP-6, CP-7, CP-9, SC-24 | D9: Directives supplémentaires | E9: La reprise consiste à exécuter les activités du plan d’urgence du système d’information pour restaurer les fonctions opérationnelles et de mission de l’organisation. La reconstitution a lieu après la reprise et comprend les activités permettant de remettre les systèmes d’information organisationnels à l’état pleinement opérationnel. Les opérations de reprise et de reconstitution reflètent les priorités opérationnelles et de mission, les objectifs en matière de délais, de points de reprise et de reconstitution, de même que les paramètres organisationnels établis conformément aux exigences du plan d’urgence. La reconstitution comprend la désactivation de toute capacité provisoire du système d’information ayant pu être nécessaire pendant les opérations de reprise. La reconstitution comprend également l’évaluation des capacités entièrement restaurées du système d’information, le rétablissement des activités de surveillance continue, les réautorisations possibles du système d’information et les activités visant à préparer les systèmes à faire face aux perturbations, compromissions ou défaillances futures. Les capacités de reprise et de reconstitution utilisées par les organisations peuvent comprendre des mécanismes automatisés et des procédures manuelles. Contrôles connexes : CA-2, CA-6, CA-7, CP-2, CP-4, CP-6, CP-7, CP-9, SC-24
A10: Test Case | D10: Cas de test
A11: Test | B11: TEST-CP-10 | D11: Test | E11: TEST-CP-10
A12: Requirement ID | B12: CP-10 | D12: ID Exigence | E12: CP-10
A13: Component | D13: Composant
A14: Requirement | D14: Exigence
A15: Contextual Design Description | D15: Description contextuelle du design
A16: Evidence Provided | D16: Preuve fournie
A17: Preparer Sign Off (Initials, Date) | D17: Signataire préparateur (Initiales, Date)
A18: Owner Sign Off (Initials, Date) | D18: Signataire propriétaire (Initiales, Date)
A19: Assessor Sign Off (Initials, Date) | D19: Signataire évaluateur (Initiales, Date)
A20: Status | B20: Not Started | D20: Statut | E20: Non commencé
A21: Comments | D21: Commentaires

Sheet CP-10-4
A1: Control CP-10(4) — Evidence Tracking | D1: Contrôle CP-10(4) — Suivi des preuves
A2: Control Information | D2: Informations du contrôle
A3: Control Identifier | B3: CP-10(4) | D3: Identifiant du contrôle | E3: CP-10(4)
A4: Family | B4: Information System Recovery and Reconstitution | D4: Famille | E4: Reprise et reconstitution du système d’information
A5: Profile | B5: CCCS Medium / PBMM Moderate | D5: Profil | E5: CCCS Moyen / PBMM Modéré
A6: Primary Evidence Tool | D6: Outil de preuve principal
A7: Contributing Tools | D7: Outils contributeurs
A8: Control Description | B8: INFORMATION SYSTEM RECOVERY AND RECONSTITUTION | RESTORE WITHIN TIME PERIOD The organization provides the capability to restore information system components within organization-defined restoration time-periods from configuration-controlled and integrity-protected information representing a known, operational state for the components. | D8: Description du contrôle | E8: REPRISE ET RECONSTITUTION DU SYSTÈME D’INFORMATION | RESTAURATION DANS LE DÉLAI IMPARTI L’organisation fournit la capacité de restaurer les composants du système d’information dans les délais de restauration définis par l’organisation à partir de l’information contrôlée par la configuration et protégée par l’intégrité qui représente un état de fonctionnement connu pour les composants.
A9: Supplemental Guidance | B9: Restoration of information system components includes, for example, re-imaging which restores components to known, operational states. Related control: CM-2. | D9: Directives supplémentaires | E9: La restauration des composants du système d’information comprend, par exemple, la reconfiguration permettant de restaurer les composants aux états de fonctionnement connus. Contrôle connexe : CM-2.
A10: Test Case | D10: Cas de test
A11: Test | B11: TEST-CP-10(4) | D11: Test | E11: TEST-CP-10(4)
A12: Requirement ID | B12: CP-10(4) | D12: ID Exigence | E12: CP-10(4)
A13: Component | D13: Composant
A14: Requirement | D14: Exigence
A15: Contextual Design Description | D15: Description contextuelle du design
A16: Evidence Provided | D16: Preuve fournie
A17: Preparer Sign Off (Initials, Date) | D17: Signataire préparateur (Initiales, Date)
A18: Owner Sign Off (Initials, Date) | D18: Signataire propriétaire (Initiales, Date)
A19: Assessor Sign Off (Initials, Date) | D19: Signataire évaluateur (Initiales, Date)
A20: Status | B20: Not Started | D20: Statut | E20: Non commencé
A21: Comments | D21: Commentaires

Sheet IA-5-7
A1: Control IA-5(7) — Evidence Tracking | D1: Contrôle IA-5(7) — Suivi des preuves
A2: Control Information | D2: Informations du contrôle
A3: Control Identifier | B3: IA-5(7) | D3: Identifiant du contrôle | E3: IA-5(7)
A4: Family | B4: Authenticator Management | D4: Famille | E4: Gestion des authentifiants
A5: Profile | B5: CCCS Medium / PBMM Moderate | D5: Profil | E5: CCCS Moyen / PBMM Modéré
A6: Primary Evidence Tool | D6: Outil de preuve principal
A7: Contributing Tools | D7: Outils contributeurs
A8: Control Description | B8: AUTHENTICATOR MANAGEMENT | NO EMBEDDED UNENCRYPTED STATIC AUTHENTICATORS The organization ensures that unencrypted static authenticators are not embedded in applications or access scripts or stored on function keys. | D8: Description du contrôle | E8: GESTION DES AUTHENTIFIANTS | AUCUN AUTHENTIFIANT STATIQUE INTÉGRÉ NON CHIFFRÉ L’organisation veille à ce que les authentifiants statiques non chiffrés ne soient pas intégrés dans les applications ou les scripts d’accès ou stockés sur les clés de fonction.
A9: Supplemental Guidance | B9: Organizations exercise caution in determining whether embedded or stored authenticators are in encrypted or unencrypted form. If authenticators are used in the manner stored, then those representations are considered unencrypted authenticators. This is irrespective of whether that representation is perhaps an encrypted version of something else (e.g., a password). | D9: Directives supplémentaires | E9: Les organisations usent de prudence lorsqu’il s’agit de déterminer si les authentifiants intégrés ou stockés sont chiffrés ou non chiffrés. Si les authentifiants sont utilisés sous leur forme stockée, ces représentations sont alors considérées comme étant des authentifiants non chiffrés. Cela n’a rien à voir avec le fait que cette représentation puisse être une version chiffrée de quelque chose d’autre (p. ex., un mot de passe).
A10: Test Case | D10: Cas de test
A11: Test | B11: TEST-IA-5(7) | D11: Test | E11: TEST-IA-5(7)
A12: Requirement ID | B12: IA-5(7) | D12: ID Exigence | E12: IA-5(7)
A13: Component | D13: Composant
A14: Requirement | D14: Exigence
A15: Contextual Design Description | D15: Description contextuelle du design
A16: Evidence Provided | D16: Preuve fournie
A17: Preparer Sign Off (Initials, Date) | D17: Signataire préparateur (Initiales, Date)
A18: Owner Sign Off (Initials, Date) | D18: Signataire propriétaire (Initiales, Date)
A19: Assessor Sign Off (Initials, Date) | D19: Signataire évaluateur (Initiales, Date)
A20: Status | B20: Not Started | D20: Statut | E20: Non commencé
A21: Comments | D21: Commentaires

Sheet MA-4
A1: Control MA-4 — Evidence Tracking | D1: Contrôle MA-4 — Suivi des preuves
A2: Control Information | D2: Informations du contrôle
A3: Control Identifier | B3: MA-4 | D3: Identifiant du contrôle | E3: MA-4
A4: Family | B4: Non-Local Maintenance | D4: Famille | E4: Maintenance non locale
A5: Profile | B5: CCCS Medium / PBMM Moderate | D5: Profil | E5: CCCS Moyen / PBMM Modéré
A6: Primary Evidence Tool | D6: Outil de preuve principal
A7: Contributing Tools | D7: Outils contributeurs
A8: Control Description | B8: (A) The organization approves and monitors nonlocal maintenance and diagnostic activities. (B) The organization allows the use of non-local maintenance and diagnostic tools only as consistent with organizational policy and as documented in the security plan for the information system. (C) The organization employs strong authenticators in the establishment of nonlocal maintenance and diagnostic sessions. (D) The organization maintains records for nonlocal maintenance and diagnostic activities. | D8: Description du contrôle | E8: (A) L’organisation approuve et surveille les activités de maintenance et de diagnostic non locales. (B) L’organisation ne permet l’utilisation d’outils de maintenance et de diagnostic non locaux que dans la mesure où ils sont conformes à la politique de l’organisation et documentés dans le plan de sécurité du système d’information. (C) L’organisation utilise des authentifiants puissants pour les ouvertures de sessions de maintenance et de diagnostic non locales. (D) L’organisation tient des registres pour les activités de maintenance et de diagnostic non locales.
A9: Supplemental Guidance | B9: Nonlocal maintenance and diagnostic activities are those activities conducted by individuals communicating through a network, either an external network (e.g., the Internet) or an internal network. Local maintenance and diagnostic activities are those activities carried out by individuals physically present at the information system or information system component and not communicating across a network connection. Authentication techniques used in the establishment of nonlocal maintenance and diagnostic sessions reflect the network access requirements in IA-2. Typically, strong authentication requires authenticators that are resistant to replay attacks and employ multifactor authentication. Strong authenticators include, for example, PKI where certificates are stored on a token protected by a password, passphrase, or biometric. Enforcing requirements in MA-4 is accomplished in part by other controls. Related controls: AC-2, AC-3, AC-6, AC-17, AU-2, AU-3, IA-2, IA-4, IA-5, IA-8, MA-2, MA-5, MP-6, PL-2, SC-7, SC-10, SC-17 | D9: Directives supplémentaires | E9: Les activités de maintenance et de diagnostic non locales sont des activités menées par des personnes qui communiquent par l’entremise d’un réseau externe (p. ex., Internet) ou interne. Les activités de maintenance et de diagnostic locales sont les activités menées par des personnes physiquement présentes sur les lieux du système d’information ou du composant du système d’information et qui ne communiquent pas au moyen d’une connexion réseau. Les techniques d’authentification utilisées pour les ouvertures de sessions de maintenance et de diagnostic non locales reflètent les exigences d’accès au réseau dans IA-2. En règle générale, une authentification forte nécessite des authentifiants qui résistent aux attaques par réinsertion et utilisent l’authentification multifactorielle. Les authentifiants puissants comprennent, par exemple, l’ICP, où les certificats sont stockés sur un jeton protégé par un mot de passe, une phrase de passe ou des données biométriques. L’application des exigences du contrôle MA-4 est assurée en partie par d’autres contrôles. Contrôles connexes : AC-2, AC-3, AC-6, AC-17, AU-2, AU-3, IA-2, IA-4, IA-5, IA-8, MA-2, MA-5, MP-6, PL-2, SC-7, SC-10, SC-17
A10: Test Case | D10: Cas de test
A11: Test | B11: TEST-MA-4 | D11: Test | E11: TEST-MA-4
A12: Requirement ID | B12: MA-4 | D12: ID Exigence | E12: MA-4
A13: Component | D13: Composant
A14: Requirement | D14: Exigence
A15: Contextual Design Description | D15: Description contextuelle du design
A16: Evidence Provided | D16: Preuve fournie
A17: Preparer Sign Off (Initials, Date) | D17: Signataire préparateur (Initiales, Date)
A18: Owner Sign Off (Initials, Date) | D18: Signataire propriétaire (Initiales, Date)
A19: Assessor Sign Off (Initials, Date) | D19: Signataire évaluateur (Initiales, Date)
A20: Status | B20: Not Started | D20: Statut | E20: Non commencé
A21: Comments | D21: Commentaires

Sheet MA-4-1
A1: Control MA-4(1) — Evidence Tracking | D1: Contrôle MA-4(1) — Suivi des preuves
A2: Control Information | D2: Informations du contrôle
A3: Control Identifier | B3: MA-4(1) | D3: Identifiant du contrôle | E3: MA-4(1)
A4: Family | B4: Non-Local Maintenance | D4: Famille | E4: Maintenance non locale
A5: Profile | B5: CCCS Medium / PBMM Moderate | D5: Profil | E5: CCCS Moyen / PBMM Modéré
A6: Primary Evidence Tool | D6: Outil de preuve principal
A7: Contributing Tools | D7: Outils contributeurs
A8: Control Description | B8: NONLOCAL MAINTENANCE | AUDITING AND REVIEW (a) The organization audits nonlocal maintenance and diagnostic sessions as defined in the organizations formal audit policy (AU-2, AU-6, AU-12); and (b) The organization reviews the records of the maintenance and diagnostic sessions. | D8: Description du contrôle | E8: MAINTENANCE NON LOCALE | VÉRIFICATION ET EXAMEN (a) L’organisation vérifie les sessions de maintenance et de diagnostic non locales telles que définies dans la politique de vérification officielle de l’organisation (AU-2, AU-6, AU-12); (b) L’organisation examine les enregistrements des sessions de maintenance et de diagnostic.
A9: Supplemental Guidance | B9: Related controls: AU-2, AU-6, AU-12. | D9: Directives supplémentaires | E9: Contrôles connexes : AU-2, AU-6, AU-12.
A10: Test Case | D10: Cas de test
A11: Test | B11: TEST-MA-4(1) | D11: Test | E11: TEST-MA-4(1)
A12: Requirement ID | B12: MA-4(1) | D12: ID Exigence | E12: MA-4(1)
A13: Component | D13: Composant
A14: Requirement | D14: Exigence
A15: Contextual Design Description | D15: Description contextuelle du design
A16: Evidence Provided | D16: Preuve fournie
A17: Preparer Sign Off (Initials, Date) | D17: Signataire préparateur (Initiales, Date)
A18: Owner Sign Off (Initials, Date) | D18: Signataire propriétaire (Initiales, Date)
A19: Assessor Sign Off (Initials, Date) | D19: Signataire évaluateur (Initiales, Date)
A20: Status | B20: Not Started | D20: Statut | E20: Non commencé
A21: Comments | D21: Commentaires

Sheet RA-5
A1: Control RA-5 — Evidence Tracking | D1: Contrôle RA-5 — Suivi des preuves
A2: Control Information | D2: Informations du contrôle
A3: Control Identifier | B3: RA-5 | D3: Identifiant du contrôle | E3: RA-5
A4: Family | B4: Vulnerability Scanning | D4: Famille | E4: Analyse des vulnérabilités
A5: Profile | B5: CCCS Medium / PBMM Moderate | D5: Profil | E5: CCCS Moyen / PBMM Modéré
A6: Primary Evidence Tool | D6: Outil de preuve principal
A7: Contributing Tools | D7: Outils contributeurs
A8: Control Description | B8: (A) The organization scans for vulnerabilities in the information system and hosted applications monthly for operating systems/infrastructure, web applications, and database management systems and when new vulnerabilities potentially affecting the system/applications are identified and reported. (B) The organization employs vulnerability scanning tools and techniques that facilitate interoperability among tools and automate parts of the vulnerability management process by using standards for: (a) Enumerating platforms, software flaws, and improper configurations; (b) Formatting checklists and test procedures; and (c) Measuring vulnerability impact. (C) The organization analyzes vulnerability scan reports and results from security control assessments. (D) The organization remediates legitimate vulnerabilities within 30 days for high-risk vulnerabilities and 90 days for moderate-risk vulnerabilities from the date of discovery in accordance with an organizational assessment of risk. (E) The organization shares information obtained from the vulnerability scanning process and security control assessments with organization-defined personnel or roles to help eliminate similar vulnerabilities in other information systems (i.e., systemic weaknesses or deficiencies). | D8: Description du contrôle | E8: (A) L’organisation analyse chaque mois les vulnérabilités du système d’information et des applications hébergées pour les systèmes et l’infrastructure d’exploitation, les applications Web et les systèmes de gestion de base de données, ainsi que les cas où de nouvelles vulnérabilités susceptibles d’affecter le système ou les applications sont repérées et signalées. (B) L’organisation utilise des outils et des techniques d’analyse des vulnérabilités qui facilitent l’interopérabilité entre les outils et automatisent des parties du processus de gestion des vulnérabilités en utilisant des normes pour : (a) recenser les plateformes, les failles logicielles et les configurations inadéquates; (b) formater les listes de contrôle et les procédures d’essai; (c) mesurer les répercussions des vulnérabilités. (C) L’organisation analyse les rapports d’analyse des vulnérabilités et les résultats des évaluations des contrôles de sécurité. (D) L’organisation remédie aux vulnérabilités légitimes dans les 30 jours pour les vulnérabilités présentant un risque élevé et dans les 90 jours pour les vulnérabilités présentant un risque modéré à partir de la date de découverte, conformément à une évaluation du risque par l’organisation. (E) L’organisation partage l’information obtenue dans le cadre du processus d’analyse des vulnérabilités et des évaluations des contrôles de sécurité avec le personnel ou les rôles définis par l’organisation pour aider à éliminer des vulnérabilités semblables dans d’autres systèmes d’information (c.-à-d. des faiblesses ou des lacunes systémiques).
A9: Supplemental Guidance | B9: Security categorization of information systems guides the frequency and comprehensiveness of vulnerability scans. Organizations determine the required vulnerability scanning for all information system components, ensuring that potential sources of vulnerabilities such as networked printers, scanners, and copiers are not overlooked. Vulnerability analyses for custom software applications may require additional approaches such as static analysis, dynamic analysis, binary analysis, or a hybrid of the three approaches. Organizations can employ these analysis approaches in a variety of tools (e.g., web-based application scanners, static analysis tools, binary analyzers) and in source code reviews. Vulnerability scanning includes, for example: (i) scanning for patch levels; (ii) scanning for functions, ports, protocols, and services that should not be accessible to users or devices; and (iii) scanning for improperly configured or incorrectly operating information flow control mechanisms | D9: Directives supplémentaires | E9: La catégorisation de la sécurité des systèmes d’information détermine la fréquence et l’exhaustivité des analyses de vulnérabilité. Les organisations déterminent le balayage des vulnérabilités requis pour tous les composants du système d’information, en veillant à ce que les sources potentielles de vulnérabilités comme les imprimantes en réseau, les numériseurs et les photocopieurs ne soient pas négligées. Les analyses de vulnérabilité pour les applications logicielles personnalisées peuvent nécessiter des approches supplémentaires comme l’analyse statique, l’analyse dynamique, l’analyse binaire ou un hybride des trois approches. Les organisations peuvent utiliser ces approches d’analyse dans divers outils (p. ex., numériseurs d’applications Web, outils d’analyse statique, analyseurs binaires) et dans l’examen des codes sources. La détection des vulnérabilités comprend, par exemple : (i) la détection des niveaux de correctifs; (ii) le balayage à la recherche de fonctions, de ports, de protocoles et de services qui ne devraient pas être accessibles aux utilisateurs ou aux appareils; (iii) la détection de mécanismes de contrôle du flux d’information mal configurés ou défectueux
A10: Test Case | D10: Cas de test
A11: Test | B11: TEST-RA-5 | D11: Test | E11: TEST-RA-5
A12: Requirement ID | B12: RA-5 | D12: ID Exigence | E12: RA-5
A13: Component | D13: Composant
A14: Requirement | D14: Exigence
A15: Contextual Design Description | D15: Description contextuelle du design
A16: Evidence Provided | D16: Preuve fournie
A17: Preparer Sign Off (Initials, Date) | D17: Signataire préparateur (Initiales, Date)
A18: Owner Sign Off (Initials, Date) | D18: Signataire propriétaire (Initiales, Date)
A19: Assessor Sign Off (Initials, Date) | D19: Signataire évaluateur (Initiales, Date)
A20: Status | B20: Not Started | D20: Statut | E20: Non commencé
A21: Comments | D21: Commentaires

Sheet RA-5-8
A1: Control RA-5(8) — Evidence Tracking | D1: Contrôle RA-5(8) — Suivi des preuves
A2: Control Information | D2: Informations du contrôle
A3: Control Identifier | B3: RA-5(8) | D3: Identifiant du contrôle | E3: RA-5(8)
A4: Family | B4: Vulnerability Scanning | D4: Famille | E4: Analyse des vulnérabilités
A5: Profile | B5: CCCS Medium / PBMM Moderate | D5: Profil | E5: CCCS Moyen / PBMM Modéré
A6: Primary Evidence Tool | D6: Outil de preuve principal
A7: Contributing Tools | D7: Outils contributeurs
A8: Control Description | B8: VULNERABILITY SCANNING | REVIEW HISTORIC AUDIT LOGS The organization reviews historic audit logs to determine if a vulnerability identified in the information system has been previously exploited. | D8: Description du contrôle | E8: ANALYSE DES VULNÉRABILITÉS | EXAMEN DES JOURNAUX DE VÉRIFICATION HISTORIQUES L’organisation examine les journaux de vérification historiques pour déterminer si une vulnérabilité repérée dans le système d’information a déjà été exploitée.
A9: Supplemental Guidance | B9: Related control: AU-6. | D9: Directives supplémentaires | E9: Contrôle connexe : AU-6.
A10: Test Case | D10: Cas de test
A11: Test | B11: TEST-RA-5(8) | D11: Test | E11: TEST-RA-5(8)
A12: Requirement ID | B12: RA-5(8) | D12: ID Exigence | E12: RA-5(8)
A13: Component | D13: Composant
A14: Requirement | D14: Exigence
A15: Contextual Design Description | D15: Description contextuelle du design
A16: Evidence Provided | D16: Preuve fournie
A17: Preparer Sign Off (Initials, Date) | D17: Signataire préparateur (Initiales, Date)
A18: Owner Sign Off (Initials, Date) | D18: Signataire propriétaire (Initiales, Date)
A19: Assessor Sign Off (Initials, Date) | D19: Signataire évaluateur (Initiales, Date)
A20: Status | B20: Not Started | D20: Statut | E20: Non commencé
A21: Comments | D21: Commentaires

Sheet SA-9-5
A1: Control SA-9(5) — Evidence Tracking | D1: Contrôle SA-9(5) — Suivi des preuves
A2: Control Information | D2: Informations du contrôle
A3: Control Identifier | B3: SA-9(5) | D3: Identifiant du contrôle | E3: SA-9(5)
A4: Family | B4: External Information System Services | D4: Famille | E4: Services de systèmes d’information externes
A5: Profile | B5: CCCS Medium / PBMM Moderate | D5: Profil | E5: CCCS Moyen / PBMM Modéré
A6: Primary Evidence Tool | D6: Outil de preuve principal
A7: Contributing Tools | D7: Outils contributeurs
A8: Control Description | B8: EXTERNAL INFORMATION SYSTEMS | PROCESSING, STORAGE, AND SERVICE LOCATION The organization restricts the location of information processing, information/data, and information system services to locations witihin Canada based on ITPIN 2017-02 for Direction on Data Residency (https://www.canada.ca/en/treasury-board-secretariat/services/information-technology/policy-implementation-notices/direction-electronic-data-residency.html). | D8: Description du contrôle | E8: SYSTÈMES D’INFORMATION EXTERNES | EMPLACEMENT DU TRAITEMENT, DU STOCKAGE ET DES SERVICES L’organisation restreint la résidence du traitement de l’information, du stockage de l’information et des données, ainsi que des services de systèmes d’information aux endroits situés à l’intérieur du Canada, conformément à l’avis AMPTI 2017-02, Orientation relative à la résidence des données électroniques (https://www.canada.ca/fr/gouvernement/systeme/gouvernement-numerique/technologiques-modernes-nouveaux/orientation-relative-residence-donnees-electroniques.html).
