Workbook

Sheet DASHBOARD
A1: DASHBOARD — PBMM Evidence: Networking
A2: Control ID | B2: Control Name | C2: Primary Tool | D2: Tab | E2: Status
A3: AC-4 | B3: Information Flow Enforcement | D3: AC-4 | E3: ='AC-4'!B20 -> Not Started
A4: AC-4(21) | B4: Information Flow Enforcement | D4: AC-4-21 | E4: ='AC-4-21'!B20 -> Not Started
A5: AC-17(1) | B5: Remote Access | D5: AC-17-1 | E5: ='AC-17-1'!B20 -> Not Started
A6: AC-17(2) | B6: Remote Access | D6: AC-17-2 | E6: ='AC-17-2'!B20 -> Not Started
A7: AC-17(3) | B7: Remote Access | D7: AC-17-3 | E7: ='AC-17-3'!B20 -> Not Started
A8: AC-17(9) | B8: Remote Access | D8: AC-17-9 | E8: ='AC-17-9'!B20 -> Not Started
A9: AC-17(100) | B9: Remote Access | D9: AC-17-100 | E9: ='AC-17-100'!B20 -> Not Started
A10: AU-2 | B10: Auditable Events | D10: AU-2 | E10: ='AU-2'!B20 -> Not Started
A11: AU-3 | B11: Content of Audit Records | D11: AU-3 | E11: ='AU-3'!B20 -> Not Started
A12: AU-3(1) | B12: Content of Audit Records | D12: AU-3-1 | E12: ='AU-3-1'!B20 -> Not Started
A13: AU-9(2) | B13: Protection of Audit Information | D13: AU-9-2 | E13: ='AU-9-2'!B20 -> Not Started
A14: AU-12 | B14: Audit Generation | D14: AU-12 | E14: ='AU-12'!B20 -> Not Started
A15: CA-3(5) | B15: Information System Connections | D15: CA-3-5 | E15: ='CA-3-5'!B20 -> Not Started
A16: CA-9 | B16: Internal System Connections | D16: CA-9 | E16: ='CA-9'!B20 -> Not Started
A17: CM-6 | B17: Configuration Settings | D17: CM-6 | E17: ='CM-6'!B20 -> Not Started
A18: CM-7 | B18: Least Functionality | D18: CM-7 | E18: ='CM-7'!B20 -> Not Started
A19: CM-7(1) | B19: Least Functionality | D19: CM-7-1 | E19: ='CM-7-1'!B20 -> Not Started
A20: CM-10 | B20: Software Usage Restrictions | D20: CM-10 | E20: ='CM-10'!B20 -> Not Started
A21: CP-7 | B21: Alternate Processing Site | D21: CP-7 | E21: ='CP-7'!B20 -> Not Started
A22: CP-7(4) | B22: Alternate Processing Site | D22: CP-7-4 | E22: ='CP-7-4'!B20 -> Not Started
A23: CP-10 | B23: Information System Recovery and Reconstitution | D23: CP-10 | E23: ='CP-10'!B20 -> Not Started
A24: CP-10(4) | B24: Information System Recovery and Reconstitution | D24: CP-10-4 | E24: ='CP-10-4'!B20 -> Not Started
A25: IA-3 | B25: Device Identification and Authentication | D25: IA-3 | E25: ='IA-3'!B20 -> Not Started
A26: MA-4(6) | B26: Non-Local Maintenance | D26: MA-4-6 | E26: ='MA-4-6'!B20 -> Not Started
A27: SA-9(5) | B27: External Information System Services | D27: SA-9-5 | E27: ='SA-9-5'!B20 -> Not Started
A28: SC-2 | B28: Application Partitioning | D28: SC-2 | E28: ='SC-2'!B20 -> Not Started
A29: SC-4 | B29: Information in Shared Resources | D29: SC-4 | E29: ='SC-4'!B20 -> Not Started
A30: SC-5 | B30: Denial of Service Protection | D30: SC-5 | E30: ='SC-5'!B20 -> Not Started
A31: SC-7 | B31: Boundary Protection | D31: SC-7 | E31: ='SC-7'!B20 -> Not Started
A32: SC-7(3) | B32: Boundary Protection | D32: SC-7-3 | E32: ='SC-7-3'!B20 -> Not Started
A33: SC-7(4) | B33: Boundary Protection | D33: SC-7-4 | E33: ='SC-7-4'!B20 -> Not Started
A34: SC-7(5) | B34: Boundary Protection | D34: SC-7-5 | E34: ='SC-7-5'!B20 -> Not Started
A35: SC-7(8) | B35: Boundary Protection | D35: SC-7-8 | E35: ='SC-7-8'!B20 -> Not Started
A36: SC-7(13) | B36: Boundary Protection | D36: SC-7-13 | E36: ='SC-7-13'!B20 -> Not Started
A37: SC-7(18) | B37: Boundary Protection | D37: SC-7-18 | E37: ='SC-7-18'!B20 -> Not Started
A38: SC-8 | B38: Transmission Confidentiality and Integrity | D38: SC-8 | E38: ='SC-8'!B20 -> Not Started
A39: SC-8(1) | B39: Transmission Confidentiality and Integrity | D39: SC-8-1 | E39: ='SC-8-1'!B20 -> Not Started
A40: SC-10 | B40: Network Disconnect | D40: SC-10 | E40: ='SC-10'!B20 -> Not Started
A41: SC-12(3) | B41: Cryptographic Key Establishment and Management | D41: SC-12-3 | E41: ='SC-12-3'!B20 -> Not Started
A42: SC-13 | B42: Cryptographic Protection | D42: SC-13 | E42: ='SC-13'!B20 -> Not Started
A43: SC-18 | B43: Mobile Code | D43: SC-18 | E43: ='SC-18'!B20 -> Not Started
A44: SC-20 | B44: Secure Name / Address Resolution Service (Authoritative Source) | D44: SC-20 | E44: ='SC-20'!B20 -> Not Started
A45: SC-21 | B45: Secure Name / Address Resolution Service (Recursive or Caching Resolver) | D45: SC-21 | E45: ='SC-21'!B20 -> Not Started
A46: SC-22 | B46: Architecture and Provisioning for Name / Address Resolution Service | D46: SC-22 | E46: ='SC-22'!B20 -> Not Started
A47: SC-23 | B47: Session Authenticity | D47: SC-23 | E47: ='SC-23'!B20 -> Not Started
A48: SC-23(1) | B48: Session Authenticity | D48: SC-23-1 | E48: ='SC-23-1'!B20 -> Not Started
A49: SC-28 | B49: Protection of Information At Rest | D49: SC-28 | E49: ='SC-28'!B20 -> Not Started
A50: SI-3 | B50: Malicious Code Protection | D50: SI-3 | E50: ='SI-3'!B20 -> Not Started
A51: SI-4 | B51: Information System Monitoring | D51: SI-4 | E51: ='SI-4'!B20 -> Not Started
A52: SI-4(1) | B52: Information System Monitoring | D52: SI-4-1 | E52: ='SI-4-1'!B20 -> Not Started
A53: SI-4(2) | B53: Information System Monitoring | D53: SI-4-2 | E53: ='SI-4-2'!B20 -> Not Started
A54: SI-4(4) | B54: Information System Monitoring | D54: SI-4-4 | E54: ='SI-4-4'!B20 -> Not Started
A55: SI-4(5) | B55: Information System Monitoring | D55: SI-4-5 | E55: ='SI-4-5'!B20 -> Not Started
A56: SI-4(11) | B56: Information System Monitoring | D56: SI-4-11 | E56: ='SI-4-11'!B20 -> Not Started
A57: SI-6 | B57: Security Functional Verification | D57: SI-6 | E57: ='SI-6'!B20 -> Not Started
A58: SI-8 | B58: Spam Protection | D58: SI-8 | E58: ='SI-8'!B20 -> Not Started
A59: SI-8(1) | B59: Spam Protection | D59: SI-8-1 | E59: ='SI-8-1'!B20 -> Not Started
A60: SI-8(2) | B60: Spam Protection | D60: SI-8-2 | E60: ='SI-8-2'!B20 -> Not Started
A61: SI-11 | B61: Error Handling | D61: SI-11 | E61: ='SI-11'!B20 -> Not Started
A63: Completion Metrics
A64: Total Controls | E64: =59 -> 59
A65: Not Started | E65: =COUNTIF(E3:E61,"Not Started") -> 59
A66: In Progress | E66: =COUNTIF(E3:E61,"In Progress") -> 0
A67: Evidence Provided | E67: =COUNTIF(E3:E61,"Evidence Provided") -> 0
A68: Under Review | E68: =COUNTIF(E3:E61,"Under Review") -> 0
A69: Passed | E69: =COUNTIF(E3:E61,"Passed") -> 0
A70: Failed | E70: =COUNTIF(E3:E61,"Failed") -> 0
A71: Accepted Exception | E71: =COUNTIF(E3:E61,"Accepted Exception") -> 0
A72: % Complete | E72: =IFERROR(COUNTIF(E3:E61,"Passed")/59,0) -> 0
A73: % Not Started | E73: =IFERROR(COUNTIF(E3:E61,"Not Started")/59,0) -> 1

Sheet TABLEAU_DE_BORD
A1: TABLEAU DE BORD — Suivi PBMM : Networking
A2: ID Contrôle | B2: Nom du contrôle | C2: Outil principal | D2: Onglet | E2: Statut
A3: AC-4 | B3: Application des contrôles du flux d’information | D3: AC-4 | E3: ='AC-4'!E20 -> Non commencé
A4: AC-4(21) | B4: Application des contrôles du flux d’information | D4: AC-4-21 | E4: ='AC-4-21'!E20 -> Non commencé
A5: AC-17(1) | B5: Accès à distance | D5: AC-17-1 | E5: ='AC-17-1'!E20 -> Non commencé
A6: AC-17(2) | B6: Accès à distance | D6: AC-17-2 | E6: ='AC-17-2'!E20 -> Non commencé
A7: AC-17(3) | B7: Accès à distance | D7: AC-17-3 | E7: ='AC-17-3'!E20 -> Non commencé
A8: AC-17(9) | B8: Accès à distance | D8: AC-17-9 | E8: ='AC-17-9'!E20 -> Non commencé
A9: AC-17(100) | B9: Accès à distance | D9: AC-17-100 | E9: ='AC-17-100'!E20 -> Non commencé
A10: AU-2 | B10: Événements vérifiables | D10: AU-2 | E10: ='AU-2'!E20 -> Non commencé
A11: AU-3 | B11: Contenu des enregistrements de vérification | D11: AU-3 | E11: ='AU-3'!E20 -> Non commencé
A12: AU-3(1) | B12: Contenu des enregistrements de vérification | D12: AU-3-1 | E12: ='AU-3-1'!E20 -> Non commencé
A13: AU-9(2) | B13: Protection des renseignements de vérification | D13: AU-9-2 | E13: ='AU-9-2'!E20 -> Non commencé
A14: AU-12 | B14: Génération des vérifications | D14: AU-12 | E14: ='AU-12'!E20 -> Non commencé
A15: CA-3(5) | B15: Connexions aux systèmes d’information | D15: CA-3-5 | E15: ='CA-3-5'!E20 -> Non commencé
A16: CA-9 | B16: Connexions internes au système | D16: CA-9 | E16: ='CA-9'!E20 -> Non commencé
A17: CM-6 | B17: Paramètres de configuration | D17: CM-6 | E17: ='CM-6'!E20 -> Non commencé
A18: CM-7 | B18: Moindre fonctionnalité | D18: CM-7 | E18: ='CM-7'!E20 -> Non commencé
A19: CM-7(1) | B19: Moindre fonctionnalité | D19: CM-7-1 | E19: ='CM-7-1'!E20 -> Non commencé
A20: CM-10 | B20: Restrictions d’utilisation des logiciels | D20: CM-10 | E20: ='CM-10'!E20 -> Non commencé
A21: CP-7 | B21: Site de traitement auxiliaire | D21: CP-7 | E21: ='CP-7'!E20 -> Non commencé
A22: CP-7(4) | B22: Site de traitement auxiliaire | D22: CP-7-4 | E22: ='CP-7-4'!E20 -> Non commencé
A23: CP-10 | B23: Reprise et reconstitution du système d’information | D23: CP-10 | E23: ='CP-10'!E20 -> Non commencé
A24: CP-10(4) | B24: Reprise et reconstitution du système d’information | D24: CP-10-4 | E24: ='CP-10-4'!E20 -> Non commencé
A25: IA-3 | B25: Identification et authentification des dispositifs | D25: IA-3 | E25: ='IA-3'!E20 -> Non commencé
A26: MA-4(6) | B26: Maintenance non locale | D26: MA-4-6 | E26: ='MA-4-6'!E20 -> Non commencé
A27: SA-9(5) | B27: Services de systèmes d’information externes | D27: SA-9-5 | E27: ='SA-9-5'!E20 -> Non commencé
A28: SC-2 | B28: Partitionnement des applications | D28: SC-2 | E28: ='SC-2'!E20 -> Non commencé
A29: SC-4 | B29: Information dans les ressources partagées | D29: SC-4 | E29: ='SC-4'!E20 -> Non commencé
A30: SC-5 | B30: Protection contre le déni de service | D30: SC-5 | E30: ='SC-5'!E20 -> Non commencé
A31: SC-7 | B31: Protection des frontières | D31: SC-7 | E31: ='SC-7'!E20 -> Non commencé
A32: SC-7(3) | B32: Protection des frontières | D32: SC-7-3 | E32: ='SC-7-3'!E20 -> Non commencé
A33: SC-7(4) | B33: Protection des frontières | D33: SC-7-4 | E33: ='SC-7-4'!E20 -> Non commencé
A34: SC-7(5) | B34: Protection des frontières | D34: SC-7-5 | E34: ='SC-7-5'!E20 -> Non commencé
A35: SC-7(8) | B35: Protection des frontières | D35: SC-7-8 | E35: ='SC-7-8'!E20 -> Non commencé
A36: SC-7(13) | B36: Protection des frontières | D36: SC-7-13 | E36: ='SC-7-13'!E20 -> Non commencé
A37: SC-7(18) | B37: Protection des frontières | D37: SC-7-18 | E37: ='SC-7-18'!E20 -> Non commencé
A38: SC-8 | B38: Confidentialité et intégrité des transmissions | D38: SC-8 | E38: ='SC-8'!E20 -> Non commencé
A39: SC-8(1) | B39: Confidentialité et intégrité des transmissions | D39: SC-8-1 | E39: ='SC-8-1'!E20 -> Non commencé
A40: SC-10 | B40: Débranchement du réseau | D40: SC-10 | E40: ='SC-10'!E20 -> Non commencé
A41: SC-12(3) | B41: Établissement et gestion des clés cryptographiques | D41: SC-12-3 | E41: ='SC-12-3'!E20 -> Non commencé
A42: SC-13 | B42: Protection cryptographique | D42: SC-13 | E42: ='SC-13'!E20 -> Non commencé
A43: SC-18 | B43: Code mobile | D43: SC-18 | E43: ='SC-18'!E20 -> Non commencé
A44: SC-20 | B44: Service sécurisé de résolution de nom et d’adresse (source reconnue) | D44: SC-20 | E44: ='SC-20'!E20 -> Non commencé
A45: SC-21 | B45: Service sécurisé de résolution de nom et d’adresse (résolveur récursif ou de mise en cache) | D45: SC-21 | E45: ='SC-21'!E20 -> Non commencé
A46: SC-22 | B46: Architecture et provisionnement du service de résolution de nom et d’adresse | D46: SC-22 | E46: ='SC-22'!E20 -> Non commencé
A47: SC-23 | B47: Authenticité des sessions | D47: SC-23 | E47: ='SC-23'!E20 -> Non commencé
A48: SC-23(1) | B48: Authenticité des sessions | D48: SC-23-1 | E48: ='SC-23-1'!E20 -> Non commencé
A49: SC-28 | B49: Protection de l’information inactive | D49: SC-28 | E49: ='SC-28'!E20 -> Non commencé
A50: SI-3 | B50: Protection contre le code malveillant | D50: SI-3 | E50: ='SI-3'!E20 -> Non commencé
A51: SI-4 | B51: Surveillance du système d’information | D51: SI-4 | E51: ='SI-4'!E20 -> Non commencé
A52: SI-4(1) | B52: Surveillance du système d’information | D52: SI-4-1 | E52: ='SI-4-1'!E20 -> Non commencé
A53: SI-4(2) | B53: Surveillance du système d’information | D53: SI-4-2 | E53: ='SI-4-2'!E20 -> Non commencé
A54: SI-4(4) | B54: Surveillance du système d’information | D54: SI-4-4 | E54: ='SI-4-4'!E20 -> Non commencé
A55: SI-4(5) | B55: Surveillance du système d’information | D55: SI-4-5 | E55: ='SI-4-5'!E20 -> Non commencé
A56: SI-4(11) | B56: Surveillance du système d’information | D56: SI-4-11 | E56: ='SI-4-11'!E20 -> Non commencé
A57: SI-6 | B57: Vérification fonctionnelle de la sécurité | D57: SI-6 | E57: ='SI-6'!E20 -> Non commencé
A58: SI-8 | B58: Protection contre les pourriels | D58: SI-8 | E58: ='SI-8'!E20 -> Non commencé
A59: SI-8(1) | B59: Protection contre les pourriels | D59: SI-8-1 | E59: ='SI-8-1'!E20 -> Non commencé
A60: SI-8(2) | B60: Protection contre les pourriels | D60: SI-8-2 | E60: ='SI-8-2'!E20 -> Non commencé
A61: SI-11 | B61: Traitement des erreurs | D61: SI-11 | E61: ='SI-11'!E20 -> Non commencé
A63: Métriques de complétude
A64: Nombre total de contrôles | E64: =59 -> 59
A65: Non commencés | E65: =COUNTIF(E3:E61,"Non commencé") -> 59
A66: En cours | E66: =COUNTIF(E3:E61,"En cours") -> 0
A67: Preuve fournie | E67: =COUNTIF(E3:E61,"Preuve fournie") -> 0
A68: En révision | E68: =COUNTIF(E3:E61,"En révision") -> 0
A69: Réussi | E69: =COUNTIF(E3:E61,"Réussi") -> 0
A70: Échec | E70: =COUNTIF(E3:E61,"Échec") -> 0
A71: Exception acceptée | E71: =COUNTIF(E3:E61,"Exception acceptée") -> 0
A72: % Complété | E72: =IFERROR(COUNTIF(E3:E61,"Réussi")/59,0) -> 0
A73: % Non commencés | E73: =IFERROR(COUNTIF(E3:E61,"Non commencé")/59,0) -> 1

Sheet AC-4
A1: Control AC-4 — Evidence Tracking | D1: Contrôle AC-4 — Suivi des preuves
A2: Control Information | D2: Informations du contrôle
A3: Control Identifier | B3: AC-4 | D3: Identifiant du contrôle | E3: AC-4
A4: Family | B4: Information Flow Enforcement | D4: Famille | E4: Application des contrôles du flux d’information
A5: Profile | B5: CCCS Medium / PBMM Moderate | D5: Profil | E5: CCCS Moyen / PBMM Modéré
A6: Primary Evidence Tool | D6: Outil de preuve principal
A7: Contributing Tools | D7: Outils contributeurs
A8: Control Description | B8: (A) The information system enforces approved authorizations for controlling the flow of information within the system and between interconnected systems based on deny all, approve by exception information flow policies. | D8: Description du contrôle | E8: (A) Le système d’information applique les autorisations approuvées pour contrôler le flux d’information à l’intérieur du système et entre les systèmes interconnectés en fonction des politiques « Refuser tous, approuver par exception » concernant les flux d’information.
A9: Supplemental Guidance | B9: Information flow control regulates where information is allowed to travel within an information system and between information systems (as opposed to who is allowed to access the information) and without explicit regard to subsequent accesses to that information. Flow control restrictions include, for example, keeping export-controlled information from being transmitted in the clear to the Internet, blocking outside traffic that claims to be from within the organization, restricting web requests to the Internet that are not from the internal web proxy server, and limiting information transfers between organizations based on data structures and content. Transferring information between information systems representing different security domains with different security policies introduces risk that such transfers violate one or more domain security policies. In such situations, information owners/stewards provide guidance at designated policy enforcement points between interconnected systems. Organizations should consider mandating specific architectural solutions when required to enforce specific security policies. Enforcement includes, for example: (i) prohibiting information transfers between interconnected systems (i.e., allowing access only); (ii) employing hardware mechanisms to enforce one-way information flows; and (iii) implementing trustworthy re-grading mechanisms to reassign security attributes and security labels. Organizations commonly employ information flow control policies and enforcement mechanisms to control the flow of information between designated sources and destinations (e.g., networks, individuals, and devices) within information systems and between interconnected systems. Flow control is based on the characteristics of the information and/or the information path. Enforcement occurs, for example, in boundary protection devices (e.g., gateways, routers, guards, encrypted tunnels, firewalls) that employ rule sets or establish configuration settings that restrict information system services, provide a packet-filtering capability based on header information, or message-filtering capability based on message content (e.g., implementing key word searches or using document characteristics). Organizations also consider the trustworthiness of filtering/inspection mechanisms (i.e., hardware, firmware, and software components) that are critical to information flow enforcement. Related controls: AC-3, AC-17, AC-19, AC-21, CM-6, CM-7, SA-8, SC-2, SC-5, SC-7, SC-18. | D9: Directives supplémentaires | E9: Le contrôle du flux d’information détermine les endroits auxquels l’information peut être acheminée au sein d’un système d’information et entre des systèmes d’information (et non les personnes autorisées à accéder à l’information) et sans égard explicite aux accès subséquents à cette information. Les restrictions en matière de contrôle du flux consistent, par exemple, à empêcher la transmission en clair sur l’Internet de l’information dont l’exportation est contrôlée, à bloquer le trafic extérieur qui prétend provenir de l’intérieur de l’organisation, à restreindre les demandes Web à l’Internet qui ne proviennent pas du serveur mandataire Web interne, et à limiter les transferts d’information entre les organisations en fonction des structures et du contenu des données. Les transferts d’information entre systèmes d’information représentant différents domaines de sécurité avec différentes politiques de sécurité présentent le risque que de tels transferts contreviennent à une ou plusieurs politiques de sécurité de domaine. Dans de telles situations, les propriétaires/gardiens de l’information donnent des conseils aux points désignés d’application des politiques entre les systèmes interconnectés. Les organisations devraient envisager d’imposer des solutions architecturales particulières au besoin pour appliquer des politiques de sécurité particulières. L’application des contrôles consiste notamment à : (i) interdire le transfert d’information entre des systèmes interconnectés (c.-à-d. permettre l’accès seulement); (ii) utiliser des mécanismes matériels pour imposer les flux d’information unidirectionnels; et (iii) mettre en œuvre des mécanismes de réévaluation fiables pour réaffecter les attributs de sécurité et les étiquettes de sécurité. Les organisations utilisent couramment des politiques de contrôle du flux d’information et des mécanismes d’application entre des sources et des destinations désignées (p. ex., les réseaux, les personnes et les périphériques) au sein des systèmes d’information et entre les systèmes interconnectés. Le contrôle du flux est fonction des caractéristiques de l’information ou du chemin de l’information. Le contrôle a lieu, par exemple, dans les dispositifs de protection des frontières (p. ex., passerelles, routeurs, gardiens, tunnels chiffrés, pare-feu) qui utilisent des ensembles de règles ou établissent des paramètres de configuration restreignant les services du système d’information, et offrent une capacité de filtrage des paquets en fonction de l’information d’en-tête, ou une capacité de filtrage des messages en fonction de leur contenu (p. ex., la mise en œuvre de recherches par mots clés ou l’utilisation des caractéristiques du document). Les organisations tiennent également compte de la fiabilité des mécanismes de filtrage et d’inspection (c.-à-d. le matériel, les micrologiciels et les composants logiciels) qui sont essentiels au contrôle du flux d’information. Contrôles connexes : AC-3, AC-17, AC-19, AC-21, CM-6, CM-7, SA-8, SC-2, SC-5, SC-7, SC-18.
A10: Test Case | D10: Cas de test
A11: Test | B11: TEST-AC-4 | D11: Test | E11: TEST-AC-4
A12: Requirement ID | B12: AC-4 | D12: ID Exigence | E12: AC-4
A13: Component | D13: Composant
A14: Requirement | D14: Exigence
A15: Contextual Design Description | D15: Description contextuelle du design
A16: Evidence Provided | D16: Preuve fournie
A17: Preparer Sign Off (Initials, Date) | D17: Signataire préparateur (Initiales, Date)
A18: Owner Sign Off (Initials, Date) | D18: Signataire propriétaire (Initiales, Date)
A19: Assessor Sign Off (Initials, Date) | D19: Signataire évaluateur (Initiales, Date)
A20: Status | B20: Not Started | D20: Statut | E20: Non commencé
A21: Comments | D21: Commentaires

Sheet AC-4-21
A1: Control AC-4(21) — Evidence Tracking | D1: Contrôle AC-4(21) — Suivi des preuves
A2: Control Information | D2: Informations du contrôle
A3: Control Identifier | B3: AC-4(21) | D3: Identifiant du contrôle | E3: AC-4(21)
A4: Family | B4: Information Flow Enforcement | D4: Famille | E4: Application des contrôles du flux d’information
A5: Profile | B5: CCCS Medium / PBMM Moderate | D5: Profil | E5: CCCS Moyen / PBMM Modéré
A6: Primary Evidence Tool | D6: Outil de preuve principal
A7: Contributing Tools | D7: Outils contributeurs
A8: Control Description | B8: INFORMATION FLOW ENFORCEMENT | PHYSICAL / LOGICAL SEPARATION OF INFORMATION FLOWS The information system separates information flows logically or physically using session encryption to accomplish separation of all sessions. | D8: Description du contrôle | E8: APPLICATION DES CONTRÔLES DU FLUX D’INFORMATION | SÉPARATION PHYSIQUE/LOGIQUE DES FLUX D’INFORMATION Le système d’information sépare les flux d’information de façon logique ou physique en utilisant le chiffrement des sessions pour effectuer la séparation de toutes les sessions.
A9: Supplemental Guidance | B9: Enforcing the separation of information flows by type can enhance protection by ensuring that information is not commingled while in transit and by enabling flow control by transmission paths perhaps not otherwise achievable. Types of separable information include, for example, inbound and outbound communications traffic, service requests and responses, and information of differing security categories. | D9: Directives supplémentaires | E9: La mise en application de la séparation des flux d’information par type peut améliorer la protection en veillant à ce que l’information ne soit pas mélangée pendant le transport et en permettant un contrôle du flux par les voies de transmission qui ne serait peut-être pas possible autrement. Les types d’information séparable comprennent, par exemple, le trafic des communications entrantes et sortantes, les demandes de service et les réponses, ainsi que l’information de différentes catégories de sécurité.
A10: Test Case | D10: Cas de test
A11: Test | B11: TEST-AC-4(21) | D11: Test | E11: TEST-AC-4(21)
A12: Requirement ID | B12: AC-4(21) | D12: ID Exigence | E12: AC-4(21)
A13: Component | D13: Composant
A14: Requirement | D14: Exigence
A15: Contextual Design Description | D15: Description contextuelle du design
A16: Evidence Provided | D16: Preuve fournie
A17: Preparer Sign Off (Initials, Date) | D17: Signataire préparateur (Initiales, Date)
A18: Owner Sign Off (Initials, Date) | D18: Signataire propriétaire (Initiales, Date)
A19: Assessor Sign Off (Initials, Date) | D19: Signataire évaluateur (Initiales, Date)
A20: Status | B20: Not Started | D20: Statut | E20: Non commencé
A21: Comments | D21: Commentaires

Sheet AC-17-1
A1: Control AC-17(1) — Evidence Tracking | D1: Contrôle AC-17(1) — Suivi des preuves
A2: Control Information | D2: Informations du contrôle
A3: Control Identifier | B3: AC-17(1) | D3: Identifiant du contrôle | E3: AC-17(1)
A4: Family | B4: Remote Access | D4: Famille | E4: Accès à distance
A5: Profile | B5: CCCS Medium / PBMM Moderate | D5: Profil | E5: CCCS Moyen / PBMM Modéré
A6: Primary Evidence Tool | D6: Outil de preuve principal
A7: Contributing Tools | D7: Outils contributeurs
A8: Control Description | B8: REMOTE ACCESS | AUTOMATED MONITORING / CONTROL The information system monitors and controls remote access methods. | D8: Description du contrôle | E8: ACCÈS À DISTANCE | SURVEILLANCE ET CONTRÔLE AUTOMATISÉS Le système d’information surveille et contrôle les méthodes d’accès à distance.
A9: Supplemental Guidance | B9: Automated monitoring and control of remote access sessions allows organizations to detect cyber-attacks and also ensure ongoing compliance with remote access policies by auditing connection activities of remote users on a variety of information system components (e.g., servers, workstations, notebook computers, smart phones, and tablets). Related controls: AU-2, AU-12. | D9: Directives supplémentaires | E9: La surveillance et le contrôle automatisés des sessions avec accès à distance permettent aux organisations de détecter les cyberattaques et d’assurer la conformité continue aux politiques d’accès à distance en vérifiant les activités de connexion des utilisateurs distants sur une variété de composants du système d’information (p. ex., serveurs, postes de travail, ordinateurs portatifs, téléphones intelligents et tablettes). Contrôles connexes : AU-2, AU-12.
A10: Test Case | D10: Cas de test
A11: Test | B11: TEST-AC-17(1) | D11: Test | E11: TEST-AC-17(1)
A12: Requirement ID | B12: AC-17(1) | D12: ID Exigence | E12: AC-17(1)
A13: Component | D13: Composant
A14: Requirement | D14: Exigence
A15: Contextual Design Description | D15: Description contextuelle du design
A16: Evidence Provided | D16: Preuve fournie
A17: Preparer Sign Off (Initials, Date) | D17: Signataire préparateur (Initiales, Date)
A18: Owner Sign Off (Initials, Date) | D18: Signataire propriétaire (Initiales, Date)
A19: Assessor Sign Off (Initials, Date) | D19: Signataire évaluateur (Initiales, Date)
A20: Status | B20: Not Started | D20: Statut | E20: Non commencé
A21: Comments | D21: Commentaires

Sheet AC-17-2
A1: Control AC-17(2) — Evidence Tracking | D1: Contrôle AC-17(2) — Suivi des preuves
A2: Control Information | D2: Informations du contrôle
A3: Control Identifier | B3: AC-17(2) | D3: Identifiant du contrôle | E3: AC-17(2)
A4: Family | B4: Remote Access | D4: Famille | E4: Accès à distance
A5: Profile | B5: CCCS Medium / PBMM Moderate | D5: Profil | E5: CCCS Moyen / PBMM Modéré
A6: Primary Evidence Tool | D6: Outil de preuve principal
A7: Contributing Tools | D7: Outils contributeurs
A8: Control Description | B8: REMOTE ACCESS | PROTECTION OF CONFIDENTIALITY / INTEGRITY USING ENCRYPTION The information system implements cryptographic mechanisms to protect the confidentiality and integrity of remote access sessions. The cryptography must be compliant with the requirements of SC-13. | D8: Description du contrôle | E8: ACCÈS À DISTANCE | PROTECTION DE LA CONFIDENTIALITÉ ET DE L’INTÉGRITÉ AU MOYEN DU CHIFFREMENT Le système d’information met en œuvre des mécanismes cryptographiques pour protéger la confidentialité et l’intégrité des sessions d’accès à distance. La cryptographie doit être conforme aux exigences de SC-13.
A9: Supplemental Guidance | B9: Guidance on the encryption strength of mechanism can be obtained from CSE upon request. | D9: Directives supplémentaires | E9: Le CST peut, sur demande, conseiller l’organisation quant à la puissance de chiffrement du mécanisme.
A10: Test Case | D10: Cas de test
A11: Test | B11: TEST-AC-17(2) | D11: Test | E11: TEST-AC-17(2)
A12: Requirement ID | B12: AC-17(2) | D12: ID Exigence | E12: AC-17(2)
A13: Component | D13: Composant
A14: Requirement | D14: Exigence
A15: Contextual Design Description | D15: Description contextuelle du design
A16: Evidence Provided | D16: Preuve fournie
A17: Preparer Sign Off (Initials, Date) | D17: Signataire préparateur (Initiales, Date)
A18: Owner Sign Off (Initials, Date) | D18: Signataire propriétaire (Initiales, Date)
A19: Assessor Sign Off (Initials, Date) | D19: Signataire évaluateur (Initiales, Date)
A20: Status | B20: Not Started | D20: Statut | E20: Non commencé
A21: Comments | D21: Commentaires

Sheet AC-17-3
A1: Control AC-17(3) — Evidence Tracking | D1: Contrôle AC-17(3) — Suivi des preuves
A2: Control Information | D2: Informations du contrôle
A3: Control Identifier | B3: AC-17(3) | D3: Identifiant du contrôle | E3: AC-17(3)
A4: Family | B4: Remote Access | D4: Famille | E4: Accès à distance
A5: Profile | B5: CCCS Medium / PBMM Moderate | D5: Profil | E5: CCCS Moyen / PBMM Modéré
A6: Primary Evidence Tool | D6: Outil de preuve principal
A7: Contributing Tools | D7: Outils contributeurs
A8: Control Description | B8: REMOTE ACCESS | MANAGED ACCESS CONTROL POINTS The information system routes all remote accesses through approved managed network access control points. | D8: Description du contrôle | E8: ACCÈS À DISTANCE | POINTS DE CONTRÔLE D’ACCÈS GÉRÉS Le système d’information achemine tous les accès à distance au moyen de points de contrôle d’accès au réseau gérés et approuvés.
A9: Supplemental Guidance | B9: Limiting the number of access control points for remote accesses reduces the attack surface for organizations. Related control: SC-7. | D9: Directives supplémentaires | E9: Une limitation du nombre de points de contrôle d’accès à distance réduit la surface d’attaque pour les organisations. Contrôle connexe : SC-7.
A10: Test Case | D10: Cas de test
A11: Test | B11: TEST-AC-17(3) | D11: Test | E11: TEST-AC-17(3)
A12: Requirement ID | B12: AC-17(3) | D12: ID Exigence | E12: AC-17(3)
A13: Component | D13: Composant
A14: Requirement | D14: Exigence
A15: Contextual Design Description | D15: Description contextuelle du design
A16: Evidence Provided | D16: Preuve fournie
A17: Preparer Sign Off (Initials, Date) | D17: Signataire préparateur (Initiales, Date)
A18: Owner Sign Off (Initials, Date) | D18: Signataire propriétaire (Initiales, Date)
A19: Assessor Sign Off (Initials, Date) | D19: Signataire évaluateur (Initiales, Date)
A20: Status | B20: Not Started | D20: Statut | E20: Non commencé
A21: Comments | D21: Commentaires

Sheet AC-17-9
A1: Control AC-17(9) — Evidence Tracking | D1: Contrôle AC-17(9) — Suivi des preuves
A2: Control Information | D2: Informations du contrôle
A3: Control Identifier | B3: AC-17(9) | D3: Identifiant du contrôle | E3: AC-17(9)
A4: Family | B4: Remote Access | D4: Famille | E4: Accès à distance
A5: Profile | B5: CCCS Medium / PBMM Moderate | D5: Profil | E5: CCCS Moyen / PBMM Modéré
A6: Primary Evidence Tool | D6: Outil de preuve principal
A7: Contributing Tools | D7: Outils contributeurs
A8: Control Description | B8: REMOTE ACCESS | DISCONNECT / DISABLE ACCESS The organization provides the capability to expeditiously disconnect or disable remote access to the information system within a period no greater than 15 minutes. | D8: Description du contrôle | E8: ACCÈS À DISTANCE | DÉCONNECTER/DÉSACTIVER L’ACCÈS L’organisation offre la possibilité de déconnecter ou de désactiver rapidement l’accès à distance au système d’information dans un délai maximal de 15 minutes.
A9: Supplemental Guidance | B9: This control enhancement requires organizations to have the capability to rapidly disconnect current users remotely accessing the information system and/or disable further remote access. The speed of disconnect or disablement varies based on the criticality of missions/business functions and the need to eliminate immediate or future remote access to organizational information systems. | D9: Directives supplémentaires | E9: Cette amélioration du contrôle exige que les organisations soient en mesure de déconnecter rapidement les utilisateurs actuels qui accèdent à distance au système d’information ou de désactiver tout accès à distance ultérieur. La rapidité de la déconnexion ou de la désactivation varie en fonction de la criticité des missions et des fonctions opérationnelles et de la nécessité d’éliminer l’accès à distance immédiat ou futur aux systèmes d’information de l’organisation.
A10: Test Case | D10: Cas de test
A11: Test | B11: TEST-AC-17(9) | D11: Test | E11: TEST-AC-17(9)
A12: Requirement ID | B12: AC-17(9) | D12: ID Exigence | E12: AC-17(9)
A13: Component | D13: Composant
A14: Requirement | D14: Exigence
A15: Contextual Design Description | D15: Description contextuelle du design
A16: Evidence Provided | D16: Preuve fournie
A17: Preparer Sign Off (Initials, Date) | D17: Signataire préparateur (Initiales, Date)
A18: Owner Sign Off (Initials, Date) | D18: Signataire propriétaire (Initiales, Date)
A19: Assessor Sign Off (Initials, Date) | D19: Signataire évaluateur (Initiales, Date)
A20: Status | B20: Not Started | D20: Statut | E20: Non commencé
A21: Comments | D21: Commentaires

Sheet AC-17-100
A1: Control AC-17(100) — Evidence Tracking | D1: Contrôle AC-17(100) — Suivi des preuves
A2: Control Information | D2: Informations du contrôle
A3: Control Identifier | B3: AC-17(100) | D3: Identifiant du contrôle | E3: AC-17(100)
A4: Family | B4: Remote Access | D4: Famille | E4: Accès à distance
A5: Profile | B5: CCCS Medium / PBMM Moderate | D5: Profil | E5: CCCS Moyen / PBMM Modéré
A6: Primary Evidence Tool | D6: Outil de preuve principal
A7: Contributing Tools | D7: Outils contributeurs
A8: Control Description | B8: Remote access to privileged accounts is performed on dedicated management consoles governed entirely by the system’s security policies and used exclusively for this purpose (e.g. Internet access not allowed). | D8: Description du contrôle | E8: L’accès à distance aux comptes privilégiés se fait sur des consoles de gestion dédiées entièrement régies par les politiques de sécurité du système et utilisées exclusivement à cette fin (p. ex., accès Internet interdit).
A9: Supplemental Guidance | D9: Directives supplémentaires
A10: Test Case | D10: Cas de test
A11: Test | B11: TEST-AC-17(100) | D11: Test | E11: TEST-AC-17(100)
A12: Requirement ID | B12: AC-17(100) | D12: ID Exigence | E12: AC-17(100)
A13: Component | D13: Composant
A14: Requirement | D14: Exigence
A15: Contextual Design Description | D15: Description contextuelle du design
A16: Evidence Provided | D16: Preuve fournie
A17: Preparer Sign Off (Initials, Date) | D17: Signataire préparateur (Initiales, Date)
A18: Owner Sign Off (Initials, Date) | D18: Signataire propriétaire (Initiales, Date)
A19: Assessor Sign Off (Initials, Date) | D19: Signataire évaluateur (Initiales, Date)
A20: Status | B20: Not Started | D20: Statut | E20: Non commencé
A21: Comments | D21: Commentaires

Sheet AU-2
A1: Control AU-2 — Evidence Tracking | D1: Contrôle AU-2 — Suivi des preuves
A2: Control Information | D2: Informations du contrôle
A3: Control Identifier | B3: AU-2 | D3: Identifiant du contrôle | E3: AU-2
A4: Family | B4: Auditable Events | D4: Famille | E4: Événements vérifiables
A5: Profile | B5: CCCS Medium / PBMM Moderate | D5: Profil | E5: CCCS Moyen / PBMM Modéré
A6: Primary Evidence Tool | D6: Outil de preuve principal
A7: Contributing Tools | D7: Outils contributeurs
A8: Control Description | B8: (A) The organization determines that the information system is capable of auditing the following events: Successful and unsuccessful account logon events, account management events, object access, policy change, privilege functions, process tracking, and system events. For Web applications: all administrator activity, authentication checks, authorization checks, data deletions, data access, data changes, and permission changes. (B) The organization coordinates the security audit function with other organizational entities requiring audit-related information to enhance mutual support and to help guide the selection of auditable events. (C) The organization provides a rationale for why the auditable events are deemed to be adequate to support after-the-fact investigations of security incidents. (D) The organization determines what organizationally-defined audited events (a subset of the auditable events defined in AU-2 a.) and the frequency of (or situation requiring) auditing for each identified event. | D8: Description du contrôle | E8: (A) L’organisation détermine que le système d’information est capable de vérifier les événements suivants : événements d’ouverture de compte, réussis ou non, événements de gestion de compte, accès aux objets, changement de politique, fonctions de privilèges, suivi des processus et événements du système. Pour les applications Web : toutes les activités des administrateurs, les vérifications d’authentification, les vérifications d’autorisation, les suppressions de données, l’accès aux données, les changements de données et les changements d’autorisation. (B) L’organisation coordonne la fonction de vérification de la sécurité avec d’autres entités organisationnelles qui ont besoin de renseignements liés à la vérification pour améliorer le soutien mutuel et aider à orienter le choix des événements vérifiables. (C) L’organisation explique la raison pour laquelle les événements vérifiables sont jugés adéquats pour appuyer les enquêtes effectuées à la suite des incidents de sécurité. (D) L’organisation détermine les événements définis par l’organisation qui sont vérifiés (un sous-ensemble des événements vérifiables définis dans AU-2 a.) et la fréquence (ou la situation exigeant) des vérifications pour chaque événement identifié.
A9: Supplemental Guidance | B9: An event is any observable occurrence in an organizational information system. Organizations identify audit events as those events which are significant and relevant to the security of information systems and the environments in which those systems operate in order to meet specific and ongoing audit needs. Audit events can include, for example, password changes, failed logons, or failed accesses related to information systems, administrative privilege usage, or third-party credential usage. In determining the set of auditable events, organizations consider the auditing appropriate for each of the security controls to be implemented. To balance auditing requirements with other information system needs, this control also requires identifying that subset of auditable events that are audited at a given point in time. For example, organizations may determine that information systems must have the capability to log every file access both successful and unsuccessful, but not activate that capability except for specific circumstances due to the potential burden on system performance. Auditing requirements, including the need for auditable events, may be referenced in other security controls and control enhancements. Organizations also include auditable events that are required by applicable organizational policies, directives, and standards. Audit records can be generated at various levels of abstraction, including at the packet level as information traverses the network. Selecting the appropriate level of abstraction is a critical aspect of an audit capability and can facilitate the identification of root causes to problems. Organizations consider in the definition of auditable events, the auditing necessary to cover related events such as the steps in distributed, transaction-based processes (e.g., processes that are distributed across multiple organizations) and actions that occur in service-oriented architectures. The information system audits the following privileged user/process events at a minimum: (a) Successful and unsuccessful attempts to access, modify, or delete security objects (Security objects include audit data, system configuration files and file or users’ formal access permissions.) (b) Successful and unsuccessful logon attempts (c) Privileged activities or other system level access (see notes for AU-2 (4)) (d) Starting and ending time for user access to the system (e) Concurrent logons from different workstations (f) All program initiations (see notes for AU-2 (4)) In addition, the information system audits the following unprivileged user/process events at a minimum: (a) Successful and unsuccessful attempts to access, modify, or delete security objects (b) Successful and unsuccessful logon attempts (c) Starting and ending time for user access to the system (d) Concurrent logons from different workstations Related controls: AC-6, AC-17, AU-3, AU-12, MA-4, MP-2, MP-4, SI-4 | D9: Directives supplémentaires | E9: Un événement est toute occurrence observable dans un système d’information organisationnel. Les organisations désignent les événements vérifiables comme étant des événements importants et pertinents pour la sécurité des systèmes d’information et des environnements dans lesquels ces systèmes sont utilisés afin de répondre à des exigences de vérification particulières et continues. Les événements vérifiés peuvent comprendre, par exemple, les changements de mot de passe, les échecs d’ouverture de session ou les échecs accès liés aux systèmes d’information, l’utilisation des privilèges administratifs ou l’utilisation de justificatifs d’identité par des tiers. Lorsqu’elles déterminent l’ensemble des événements vérifiables, les organisations considèrent que la vérification est appropriée pour chacun des contrôles de sécurité à mettre en œuvre. Pour assurer l’équilibre entre les exigences en matière de vérification et les autres besoins du système d’information, ce contrôle exige également de déterminer le sous-ensemble d’événements vérifiables qui sont vérifiés à un moment donné. Par exemple, les organisations peuvent déterminer que les systèmes d’information doivent avoir la capacité d’enregistrer chaque accès aux fichiers, qu’il soit réussi ou non, mais n’activeront cette capacité que dans des circonstances particulières en raison du fardeau potentiel sur le rendement du système. Les exigences en matière de vérification, y compris la nécessité de déterminer des événements vérifiables, peuvent être mentionnées dans d’autres contrôles et améliorations des contrôles de sécurité. Les organisations incluent également les événements vérifiables qui sont exigés par les politiques, les directives et les normes organisationnelles applicables. Les enregistrements de vérification peuvent être générés à divers niveaux d’abstraction, y compris au niveau des paquets, à mesure que l’information traverse le réseau. Le choix du niveau d’abstraction approprié est un aspect essentiel d’une capacité de vérification et peut faciliter l’identification des causes profondes des problèmes. Dans la définition des événements vérifiables, les organisations prennent en compte la vérification nécessaire pour couvrir les événements connexes, comme les étapes des processus distribués, fondés sur les transactions (p. ex., les processus qui sont répartis entre de multiples organisations) et les actions qui ont lieu dans les architectures orientées service. Le système d’information vérifie au minimum les événements suivants liés aux utilisateurs/processus privilégiés : (a) Tentatives réussies et infructueuses d’accéder aux objets de sécurité, de les modifier ou de les supprimer (les objets de sécurité comprennent les données de vérification, les fichiers de configuration de système et les autorisations d’accès officielles des utilisateurs). (b) Tentatives d’ouverture de session réussies et infructueuses (c) Activités privilégiées ou autre accès au niveau du système (voir les notes pour AU-2 [4]) (d) Heures de début et de fin de l’accès des utilisateurs au système (e) Ouvertures de session simultanées à partir de différents postes de travail (f) Tous les lancements de programmes (voir les notes pour AU-2 [4]) De plus, le système d’information vérifie au minimum les événements suivants liés aux utilisateurs/processus non privilégiés : (a) Tentatives réussies et infructueuses d’accès, de modification ou de suppression d’objets de sécurité (b) Tentatives d’ouverture de session réussies et infructueuses (c) Heures de début et de fin de l’accès de l’utilisateur au système (d) Ouvertures de session simultanées à partir de différents postes de travail Contrôles connexes : AC-6, AC-17, AU-3, AU-12, MA-4, MP-2, MP-4, SI-4
A10: Test Case | D10: Cas de test
A11: Test | B11: TEST-AU-2 | D11: Test | E11: TEST-AU-2
A12: Requirement ID | B12: AU-2 | D12: ID Exigence | E12: AU-2
A13: Component | D13: Composant
A14: Requirement | D14: Exigence
A15: Contextual Design Description | D15: Description contextuelle du design
A16: Evidence Provided | D16: Preuve fournie
A17: Preparer Sign Off (Initials, Date) | D17: Signataire préparateur (Initiales, Date)
A18: Owner Sign Off (Initials, Date) | D18: Signataire propriétaire (Initiales, Date)
A19: Assessor Sign Off (Initials, Date) | D19: Signataire évaluateur (Initiales, Date)
A20: Status | B20: Not Started | D20: Statut | E20: Non commencé
A21: Comments | D21: Commentaires

Sheet AU-3
A1: Control AU-3 — Evidence Tracking | D1: Contrôle AU-3 — Suivi des preuves
A2: Control Information | D2: Informations du contrôle
A3: Control Identifier | B3: AU-3 | D3: Identifiant du contrôle | E3: AU-3
A4: Family | B4: Content of Audit Records | D4: Famille | E4: Contenu des enregistrements de vérification
A5: Profile | B5: CCCS Medium / PBMM Moderate | D5: Profil | E5: CCCS Moyen / PBMM Modéré
A6: Primary Evidence Tool | D6: Outil de preuve principal
A7: Contributing Tools | D7: Outils contributeurs
A8: Control Description | B8: (A) The information system generates audit records containing information that establishes what type of event occurred, when the event occurred, where the event occurred, the source of the event, the outcome of the event, and the identity of any individuals or subjects associated with the event. | D8: Description du contrôle | E8: (A) Le système d’information génère des enregistrements de vérification qui contiennent les renseignements permettant d’établir le type d’événement qui a eu lieu, le moment et l’endroit où l’événement a eu lieu, la source de l’événement, le résultat de l’événement, ainsi que l’identité de toute personne ou de tout sujet associé à l’événement.
A9: Supplemental Guidance | B9: Audit record content that may be necessary to satisfy the requirement of this control, includes, for example, time stamps, source and destination addresses, user/process identifiers, event descriptions, success/fail indications, filenames involved, and access control or flow control rules invoked. Event outcomes can include indicators of event success or failure and event-specific results (e.g., the security state of the information system after the event occurred). Related controls: AU-2, AU-8, AU-12, SI-11 | D9: Directives supplémentaires | E9: Le contenu des enregistrements de vérification qui peut être nécessaire pour satisfaire à l’exigence de ce contrôle comprend, par exemple, les estampilles temporelles, les adresses de source et de destination, les identifiants d’utilisateurs ou de processus, les descriptions d’événements, les indications de réussite ou d’échec, les noms des fichiers en cause et les règles de contrôle d’accès ou de flux invoquées. Les résultats de l’événement peuvent comprendre des indicateurs de réussite ou d’échec de l’événement et des résultats propres à l’événement (p. ex., l’état de sécurité du système d’information après l’événement). Contrôles connexes : AU-2, AU-8, AU-12, SI-11
A10: Test Case | D10: Cas de test
A11: Test | B11: TEST-AU-3 | D11: Test | E11: TEST-AU-3
A12: Requirement ID | B12: AU-3 | D12: ID Exigence | E12: AU-3
A13: Component | D13: Composant
A14: Requirement | D14: Exigence
A15: Contextual Design Description | D15: Description contextuelle du design
A16: Evidence Provided | D16: Preuve fournie
A17: Preparer Sign Off (Initials, Date) | D17: Signataire préparateur (Initiales, Date)
A18: Owner Sign Off (Initials, Date) | D18: Signataire propriétaire (Initiales, Date)
A19: Assessor Sign Off (Initials, Date) | D19: Signataire évaluateur (Initiales, Date)
A20: Status | B20: Not Started | D20: Statut | E20: Non commencé
A21: Comments | D21: Commentaires

Sheet AU-3-1
A1: Control AU-3(1) — Evidence Tracking | D1: Contrôle AU-3(1) — Suivi des preuves
A2: Control Information | D2: Informations du contrôle
A3: Control Identifier | B3: AU-3(1) | D3: Identifiant du contrôle | E3: AU-3(1)
A4: Family | B4: Content of Audit Records | D4: Famille | E4: Contenu des enregistrements de vérification
A5: Profile | B5: CCCS Medium / PBMM Moderate | D5: Profil | E5: CCCS Moyen / PBMM Modéré
A6: Primary Evidence Tool | D6: Outil de preuve principal
A7: Contributing Tools | D7: Outils contributeurs
A8: Control Description | B8: CONTENT OF AUDIT RECORDS | ADDITIONAL AUDIT INFORMATION The information system generates audit records containing the following additional information: session, connection, transaction, or activity duration; for client-server transactions, the number of bytes received and bytes sent; additional informational messages to diagnose or identify the event; characteristics that describe or identify the object or resource being acted upon. | D8: Description du contrôle | E8: CONTENU DES ENREGISTREMENTS DE VÉRIFICATION | RENSEIGNEMENTS DE VÉRIFICATION SUPPLÉMENTAIRES Le système d’information génère des enregistrements de vérification contenant les renseignements supplémentaires suivants : la durée de la session, de la connexion, de la transaction ou de l’activité; pour les transactions client-serveur, le nombre d’octets reçus et d’octets envoyés; des messages d’information supplémentaires pour diagnostiquer ou identifier l’événement; les caractéristiques qui décrivent ou identifient l’objet ou la ressource concernés.
A9: Supplemental Guidance | B9: Detailed information that organizations may consider in audit records includes, for example, full text recording of privileged commands or the individual identities of group account users. Organizations consider limiting the additional audit information to only that information explicitly needed for specific audit requirements. This facilitates the use of audit trails and audit logs by not including information that could potentially be misleading or could make it more difficult to locate information of interest. Additional guidance for enhancement (1): Audit events should always be capable of being associated with an individual identity. Associating audit events with a group or role is insufficient. | D9: Directives supplémentaires | E9: Les renseignements détaillés dont les organisations peuvent tenir compte dans les enregistrements de vérification comprennent, par exemple, l’enregistrement en texte intégral des commandes privilégiées ou les identités individuelles des utilisateurs de comptes de groupe. Les organisations devraient envisager de limiter les renseignements de vérification supplémentaires aux seuls renseignements explicitement nécessaires pour répondre à des exigences de vérification particulières. Cela facilitera l’utilisation des pistes de vérification et des journaux de vérification en n’incluant pas les renseignements qui pourraient être trompeurs ou rendre plus difficile la recherche de renseignements utiles. Conseils supplémentaires pour l’amélioration (1) : Les événements vérifiés devraient toujours pouvoir être associés à une identité individuelle. Associer des événements vérifiés à un groupe ou à un rôle est insuffisant.
A10: Test Case | D10: Cas de test
A11: Test | B11: TEST-AU-3(1) | D11: Test | E11: TEST-AU-3(1)
A12: Requirement ID | B12: AU-3(1) | D12: ID Exigence | E12: AU-3(1)
A13: Component | D13: Composant
A14: Requirement | D14: Exigence
A15: Contextual Design Description | D15: Description contextuelle du design
A16: Evidence Provided | D16: Preuve fournie
A17: Preparer Sign Off (Initials, Date) | D17: Signataire préparateur (Initiales, Date)
A18: Owner Sign Off (Initials, Date) | D18: Signataire propriétaire (Initiales, Date)
A19: Assessor Sign Off (Initials, Date) | D19: Signataire évaluateur (Initiales, Date)
A20: Status | B20: Not Started | D20: Statut | E20: Non commencé
A21: Comments | D21: Commentaires

Sheet AU-9-2
A1: Control AU-9(2) — Evidence Tracking | D1: Contrôle AU-9(2) — Suivi des preuves
A2: Control Information | D2: Informations du contrôle
A3: Control Identifier | B3: AU-9(2) | D3: Identifiant du contrôle | E3: AU-9(2)
A4: Family | B4: Protection of Audit Information | D4: Famille | E4: Protection des renseignements de vérification
A5: Profile | B5: CCCS Medium / PBMM Moderate | D5: Profil | E5: CCCS Moyen / PBMM Modéré
A6: Primary Evidence Tool | D6: Outil de preuve principal
A7: Contributing Tools | D7: Outils contributeurs
A8: Control Description | B8: PROTECTION OF AUDIT INFORMATION | AUDIT BACKUP ON SEPARATE PHYSICAL SYSTEMS / COMPONENTS The information system backs up audit records at least weekly onto a physically different system or system component than the system or component being audited. | D8: Description du contrôle | E8: PROTECTION DES RENSEIGNEMENTS DE VÉRIFICATION | SAUVEGARDE DES VÉRIFICATIONS SUR DES SYSTÈMES/COMPOSANTS PHYSIQUES SÉPARÉS Le système d’information sauvegarde les enregistrements de vérification au moins une fois par semaine sur un système ou un composant système physiquement différent du système ou du composant faisant l’objet de la vérification.
A9: Supplemental Guidance | B9: This control enhancement helps to ensure that a compromise of the information system being audited does not also result in a compromise of the audit records. Related controls: AU-4, AU-5, AU-11. | D9: Directives supplémentaires | E9: Cette amélioration permet de s’assurer qu’une compromission du système d’information faisant l’objet d’une vérification n’entraîne pas également la compromission des enregistrements de vérification. Contrôles connexes : AU-4, AU-5, AU-11.
A10: Test Case | D10: Cas de test
A11: Test | B11: TEST-AU-9(2) | D11: Test | E11: TEST-AU-9(2)
A12: Requirement ID | B12: AU-9(2) | D12: ID Exigence | E12: AU-9(2)
A13: Component | D13: Composant
A14: Requirement | D14: Exigence
A15: Contextual Design Description | D15: Description contextuelle du design
A16: Evidence Provided | D16: Preuve fournie
A17: Preparer Sign Off (Initials, Date) | D17: Signataire préparateur (Initiales, Date)
A18: Owner Sign Off (Initials, Date) | D18: Signataire propriétaire (Initiales, Date)
A19: Assessor Sign Off (Initials, Date) | D19: Signataire évaluateur (Initiales, Date)
A20: Status | B20: Not Started | D20: Statut | E20: Non commencé
A21: Comments | D21: Commentaires

Sheet AU-12
A1: Control AU-12 — Evidence Tracking | D1: Contrôle AU-12 — Suivi des preuves
A2: Control Information | D2: Informations du contrôle
A3: Control Identifier | B3: AU-12 | D3: Identifiant du contrôle | E3: AU-12
A4: Family | B4: Audit Generation | D4: Famille | E4: Génération des vérifications
A5: Profile | B5: CCCS Medium / PBMM Moderate | D5: Profil | E5: CCCS Moyen / PBMM Modéré
A6: Primary Evidence Tool | D6: Outil de preuve principal
A7: Contributing Tools | D7: Outils contributeurs
A8: Control Description | B8: (A) The information system provides audit record generation capability for the auditable events defined in AU-2 a. of all information system and network components where audit capability is deployed/available. (B) The information system allows organization-defined personnel or roles to select which auditable events are to be audited by specific components of the information system. (C) The information system generates audit records for the events defined in AU-2 d. with the content defined in AU-3. | D8: Description du contrôle | E8: (A) Le système d’information offre une capacité de génération d’enregistrements de vérification pour les événements vérifiables définis dans AU-2 a. de tous les composants du système d’information et du réseau où la capacité de vérification est déployée/disponible. (B) Le système d’information permet au personnel ou aux rôles définis par l’organisation de choisir les événements vérifiables qui doivent être vérifiés par des composants précis du système d’information. (C) Le système d’information génère des enregistrements de vérification pour les événements définis dans AU-2 d. avec le contenu défini dans AU-3.
A9: Supplemental Guidance | B9: Audit records can be generated from many different information system components. The list of audited events is the set of events for which audits are to be generated. These events are typically a subset of all events for which the information system is capable of generating audit records. Related controls: AC-3, AU-2, AU-3, AU-6, AU-7 | D9: Directives supplémentaires | E9: Des enregistrements de vérification peuvent être générés à partir de nombreux composants du système d’information. La liste des événements vérifiés est l’ensemble des événements pour lesquels des vérifications doivent être produites. Ces événements sont habituellement un sous-ensemble de tous les événements pour lesquels le système d’information peut générer des enregistrements de vérification. Contrôles connexes : AC-3, AU-2, AU-3, AU-6, AU-7
A10: Test Case | D10: Cas de test
A11: Test | B11: TEST-AU-12 | D11: Test | E11: TEST-AU-12
A12: Requirement ID | B12: AU-12 | D12: ID Exigence | E12: AU-12
A13: Component | D13: Composant
A14: Requirement | D14: Exigence
A15: Contextual Design Description | D15: Description contextuelle du design
A16: Evidence Provided | D16: Preuve fournie
A17: Preparer Sign Off (Initials, Date) | D17: Signataire préparateur (Initiales, Date)
A18: Owner Sign Off (Initials, Date) | D18: Signataire propriétaire (Initiales, Date)
A19: Assessor Sign Off (Initials, Date) | D19: Signataire évaluateur (Initiales, Date)
A20: Status | B20: Not Started | D20: Statut | E20: Non commencé
A21: Comments | D21: Commentaires

Sheet CA-3-5
A1: Control CA-3(5) — Evidence Tracking | D1: Contrôle CA-3(5) — Suivi des preuves
A2: Control Information | D2: Informations du contrôle
A3: Control Identifier | B3: CA-3(5) | D3: Identifiant du contrôle | E3: CA-3(5)
A4: Family | B4: Information System Connections | D4: Famille | E4: Connexions aux systèmes d’information
A5: Profile | B5: CCCS Medium / PBMM Moderate | D5: Profil | E5: CCCS Moyen / PBMM Modéré
A6: Primary Evidence Tool | D6: Outil de preuve principal
A7: Contributing Tools | D7: Outils contributeurs
A8: Control Description | B8: SYSTEM INTERCONNECTIONS | RESTRICTIONS ON EXTERNAL SYSTEM CONNECTIONS The organization employs allow-all, deny-by-exception; deny-all policy for allowing any systems to connect to external information systems. | D8: Description du contrôle | E8: INTERCONNEXIONS DES SYSTÈMES | RESTRICTIONS SUR LES CONNEXIONS AUX RÉSEAUX EXTERNES L’organisation a recours à la méthode « permettre tout, refuser par exception, refuser tout » pour permettre aux systèmes de se connecter à des systèmes d’information externes.
A9: Supplemental Guidance | B9: Organizations can constrain information system connectivity to external domains (e.g., websites) by employing one of two policies with regard to such connectivity: (i) allow-all, deny by exception, also known as blacklisting (the weaker of the two policies); or (ii) deny-all, allow by exception, also known as whitelisting (the stronger of the two policies). For either policy, organizations determine what exceptions, if any, are acceptable. Related control: CM-7. | D9: Directives supplémentaires | E9: Les organisations peuvent limiter la connectivité des systèmes d’information à des domaines externes (p. ex., sites Web) en utilisant l’une des deux politiques relatives à cette connectivité : (i) permettre tout, refuser par exception, aussi appelée liste noire (la plus faible des deux politiques); ou (ii) refuser tout, permettre par exception, aussi appelée liste blanche (la plus forte des deux politiques). Pour l’une ou l’autre politique, les organisations déterminent les exceptions applicables, le cas échéant. Contrôle connexe : CM-7.
A10: Test Case | D10: Cas de test
A11: Test | B11: TEST-CA-3(5) | D11: Test | E11: TEST-CA-3(5)
A12: Requirement ID | B12: CA-3(5) | D12: ID Exigence | E12: CA-3(5)
A13: Component | D13: Composant
A14: Requirement | D14: Exigence
A15: Contextual Design Description | D15: Description contextuelle du design
A16: Evidence Provided | D16: Preuve fournie
A17: Preparer Sign Off (Initials, Date) | D17: Signataire préparateur (Initiales, Date)
A18: Owner Sign Off (Initials, Date) | D18: Signataire propriétaire (Initiales, Date)
A19: Assessor Sign Off (Initials, Date) | D19: Signataire évaluateur (Initiales, Date)
A20: Status | B20: Not Started | D20: Statut | E20: Non commencé
A21: Comments | D21: Commentaires

Sheet CA-9
A1: Control CA-9 — Evidence Tracking | D1: Contrôle CA-9 — Suivi des preuves
A2: Control Information | D2: Informations du contrôle
A3: Control Identifier | B3: CA-9 | D3: Identifiant du contrôle | E3: CA-9
A4: Family | B4: Internal System Connections | D4: Famille | E4: Connexions internes au système
A5: Profile | B5: CCCS Medium / PBMM Moderate | D5: Profil | E5: CCCS Moyen / PBMM Modéré
A6: Primary Evidence Tool | D6: Outil de preuve principal
A7: Contributing Tools | D7: Outils contributeurs
A8: Control Description | B8: (A) The organization authorizes internal connections of information system components or classes of components to the information system. (B) The organization documents, for each internal connection, the interface characteristics, security requirements, and the nature of the information communicated. | D8: Description du contrôle | E8: (A) L’organisation autorise les connexions internes de composants du système d’information ou de catégories de composants au système d’information. (B) L’organisation documente, pour chaque connexion interne, les caractéristiques de l’interface, les exigences de sécurité et la nature de l’information communiquée.
A9: Supplemental Guidance | B9: This control applies to connections between organizational information systems and (separate) constituent system components (i.e., intra-system connections) including, for example, system connections with mobile devices, notebook/desktop computers, printers, copiers, facsimile machines, scanners, sensors, and servers. Instead of authorizing each individual internal connection, organizations can authorize internal connections for a class of components with common characteristics and/or configurations, for example, all digital printers, scanners, and copiers with a specified processing, storage, and transmission capability or all smart phones with a specific baseline configuration. Related controls: AC-3, AC-4, AC-18, AC-19, AU-2, AU-12, CA-7, CM-2, IA-3, SC-7, SI-4 | D9: Directives supplémentaires | E9: Ce contrôle s’applique aux connexions entre les systèmes d’information organisationnels et les composants (distincts) des systèmes constituants (c.-à-d. les connexions intrasystème) y compris, par exemple, les connexions système avec les appareils mobiles, les ordinateurs portatifs/de bureau, les imprimantes, les photocopieurs, les télécopieurs, les numériseurs, les capteurs et les serveurs. Au lieu d’autoriser chaque connexion interne individuelle, les organisations peuvent autoriser les connexions internes pour une catégorie de composants ayant des caractéristiques ou des configurations communes, par exemple, toutes les imprimantes et tous les numériseurs et photocopieurs numériques ayant une capacité de traitement, de stockage et de transmission spécifiée ou tous les téléphones intelligents ayant une configuration de base spécifique. Contrôles connexes : AC-3, AC-4, AC-18, AC-19, AU-2, AU-12, CA-7, CM-2, IA-3, SC-7, SI-4
A10: Test Case | D10: Cas de test
A11: Test | B11: TEST-CA-9 | D11: Test | E11: TEST-CA-9
A12: Requirement ID | B12: CA-9 | D12: ID Exigence | E12: CA-9
A13: Component | D13: Composant
A14: Requirement | D14: Exigence
A15: Contextual Design Description | D15: Description contextuelle du design
A16: Evidence Provided | D16: Preuve fournie
A17: Preparer Sign Off (Initials, Date) | D17: Signataire préparateur (Initiales, Date)
A18: Owner Sign Off (Initials, Date) | D18: Signataire propriétaire (Initiales, Date)
A19: Assessor Sign Off (Initials, Date) | D19: Signataire évaluateur (Initiales, Date)
A20: Status | B20: Not Started | D20: Statut | E20: Non commencé
A21: Comments | D21: Commentaires

Sheet CM-6
A1: Control CM-6 — Evidence Tracking | D1: Contrôle CM-6 — Suivi des preuves
A2: Control Information | D2: Informations du contrôle
A3: Control Identifier | B3: CM-6 | D3: Identifiant du contrôle | E3: CM-6
A4: Family | B4: Configuration Settings | D4: Famille | E4: Paramètres de configuration
A5: Profile | B5: CCCS Medium / PBMM Moderate | D5: Profil | E5: CCCS Moyen / PBMM Modéré
A6: Primary Evidence Tool | D6: Outil de preuve principal
A7: Contributing Tools | D7: Outils contributeurs
A8: Control Description | B8: (A) The organization establishes and documents configuration settings for information technology products employed within the information system using checklists from one or more of the following Center for Internet Security (CIS), National Institute of Standards and Technology (NIST), Defense Information Systems Agency (DISA) that reflect the most restrictive mode consistent with operational requirements. (B) The organization implements the configuration settings. (C) The organization identifies, documents, and approves any deviations from established configuration settings for any configurable infomation system components. (D) The organization monitors and controls changes to the configuration settings in accordance with organizational policies and procedures. | D8: Description du contrôle | E8: (A) L’organisation établit et documente les paramètres de configuration des produits de technologie de l’information utilisés dans le système d’information à l’aide de listes de vérification provenant d’un ou de plusieurs des éléments suivants : Center for Internet Security (CIS), National Institute of Standards and Technology (NIST), Defense Information Systems Agency (DISA), qui reflètent le mode le plus restrictif conformément aux exigences opérationnelles. (B) L’organisation met en œuvre les paramètres de configuration. (C) L’organisation identifie, documente et approuve tout écart par rapport aux paramètres de configuration établis pour les composants configurables du système d’information. (D) L’organisation surveille et contrôle les changements apportés aux paramètres de configuration conformément aux politiques et aux procédures de l’organisation.
A9: Supplemental Guidance | B9: Configuration settings are the set of parameters that can be changed in hardware, software, or firmware components of the information system that affect the security posture and/or functionality of the system. Information technology products for which security-related configuration settings can be defined include, for example, mainframe computers, servers (e.g., database, electronic mail, authentication, web, proxy, file, domain name), workstations, input/output devices (e.g., scanners, copiers, and printers), network components (e.g., firewalls, routers, gateways, voice and data switches, wireless access points, network appliances, sensors), operating systems, middleware, and applications. Security-related parameters are those parameters impacting the security state of information systems including the parameters required to satisfy other security control requirements. Security-related parameters include, for example: (i) registry settings; (ii) account, file, directory permission settings; and (iii) settings for functions, ports, protocols, services, and remote connections. Organizations establish organization-wide configuration settings and subsequently derive specific settings for information systems. The established settings become part of the systems configuration baselineCommon secure configurations (also referred to as security configuration checklists, lockdown and hardening guides, security reference guides, security technical implementation guides (STIG)) provide recognized, standardized, and established benchmarks that stipulate secure configuration settings for specific information technology platforms/products and instructions for configuring those information system components to meet operational requirements. Common secure configurations can be developed by a variety of organizations including, for example, information technology product developers, manufacturers, vendors, consortia, academia, industry, federal government organizations, and others in the public and private sectors. The Security Content Automation Protocol (SCAP) and the defined standards within the protocol (e.g., Common Configuration Enumeration) provide an effective method to uniquely identify, track, and control configuration settings. Related controls: AC-19, CM-2, CM-3, CM-7, SI-4. | D9: Directives supplémentaires | E9: Les paramètres de configuration sont l’ensemble de paramètres qui peuvent être modifiés dans les composants matériels, logiciels ou micrologiciels du système d’information et qui ont une incidence sur la posture de sécurité ou la fonctionnalité du système. Les produits de technologie de l’information pour lesquels les paramètres de configuration liés à la sécurité peuvent être définis comprennent, par exemple, les ordinateurs centraux, les serveurs (p. ex., base de données, courrier électronique, authentification, Web, mandataire, fichiers, noms de domaine), les postes de travail, les périphériques d’entrée et de sortie (p. ex., numériseurs, photocopieurs et imprimantes), les composants de réseau (p. ex., pare-feu, routeurs, passerelles, commutateurs de voix et de données, points d’accès sans fil, outils de réseau, capteurs), les systèmes d’exploitation, les intergiciels et les applications. Les paramètres liés à la sécurité sont les paramètres qui influent sur l’état de sécurité des systèmes d’information, y compris les paramètres requis pour satisfaire à d’autres exigences de contrôle de sécurité. Les paramètres liés à la sécurité comprennent, par exemple : (i) les paramètres des registres; (ii) les paramètres de comptes, de fichiers, d’autorisation de répertoires; (iii) les paramètres des fonctions, des ports, des protocoles, des services et des connexions à distance. Les organisations établissent les paramètres de configuration à l’échelle de l’organisation et en déduisent ensuite les paramètres particuliers pour les systèmes d’information. Les paramètres établis font partie des configurations de base des systèmes Les configurations sécurisées communes (aussi appelées listes de vérification de la configuration de sécurité, guides de verrouillage et de renforcement, guides de référence de sécurité, guides de mise en œuvre technique de la sécurité [STIG]) fournissent des repères reconnus, normalisés et établis qui stipulent les paramètres de configuration sécurisée pour des plateformes/produits de technologie de l’information particuliers et des instructions pour configurer ces composants de système d’information de manière à répondre aux exigences opérationnelles. Les configurations sécurisées communes peuvent être mises au point par diverses organisations, y compris, par exemple, les concepteurs de produits de technologie de l’information, les fabricants, les fournisseurs, les consortiums, le milieu universitaire, l’industrie, les organisations du gouvernement fédéral et d’autres intervenants des secteurs public et privé. Le protocole d’automatisation du contenu de sécurité SCAP (Security Content Automation Protocol) et les normes définies dans le protocole (p. ex., Common Configuration Enumeration) constituent une méthode efficace pour déterminer, suivre et contrôler de façon unique les paramètres de configuration. Contrôles connexes : AC-19, CM-2, CM-3, CM-7, SI-4.
A10: Test Case | D10: Cas de test
A11: Test | B11: TEST-CM-6 | D11: Test | E11: TEST-CM-6
A12: Requirement ID | B12: CM-6 | D12: ID Exigence | E12: CM-6
A13: Component | D13: Composant
A14: Requirement | D14: Exigence
A15: Contextual Design Description | D15: Description contextuelle du design
A16: Evidence Provided | D16: Preuve fournie
A17: Preparer Sign Off (Initials, Date) | D17: Signataire préparateur (Initiales, Date)
A18: Owner Sign Off (Initials, Date) | D18: Signataire propriétaire (Initiales, Date)
A19: Assessor Sign Off (Initials, Date) | D19: Signataire évaluateur (Initiales, Date)
A20: Status | B20: Not Started | D20: Statut | E20: Non commencé
A21: Comments | D21: Commentaires

Sheet CM-7
A1: Control CM-7 — Evidence Tracking | D1: Contrôle CM-7 — Suivi des preuves
A2: Control Information | D2: Informations du contrôle
A3: Control Identifier | B3: CM-7 | D3: Identifiant du contrôle | E3: CM-7
A4: Family | B4: Least Functionality | D4: Famille | E4: Moindre fonctionnalité
A5: Profile | B5: CCCS Medium / PBMM Moderate | D5: Profil | E5: CCCS Moyen / PBMM Modéré
A6: Primary Evidence Tool | D6: Outil de preuve principal
A7: Contributing Tools | D7: Outils contributeurs
A8: Control Description | B8: (A) The organization configures the information system to provide only essential capabilities. (B) The organization prohibits or restricts the use of identified functions, ports, protocols, and/or services following one or more standards from Center for Internet Security (CIS), National Institute of Standards and Technology (NIST), or Defense Information Systems Agency (DISA). | D8: Description du contrôle | E8: (A) L’organisation configure le système d’information pour n’offrir que les capacités essentielles. (B) L’organisation interdit ou restreint l’utilisation de fonctions, de ports, de protocoles et/ou de services identifiés en respectant une ou plusieurs normes du Center for Internet Security (CIS), du National Institute of Standards and Technology (NIST) ou de la Defense Information Systems Agency (DISA).
A9: Supplemental Guidance | B9: Information systems can provide a wide variety of functions and services. Some of the functions and services, provided by default, may not be necessary to support essential organizational operations (e.g., key missions, functions). Additionally, it is sometimes convenient to provide multiple services from single information system components, but doing so increases risk over limiting the services provided by any one component. Where feasible, organizations limit component functionality to a single function per device (e.g., email servers or web servers, but not both). Organizations review functions and services provided by information systems or individual components of information systems, to determine which functions and services are candidates for elimination (e.g., Voice over Internet Protocol (VoIP), Instant Messaging, auto-execute, and file sharing). Organizations consider disabling unused or unnecessary physical and logical ports/protocols (e.g., USB, FTP, IPv6, HTTP) on information systems to prevent unauthorized connection of devices, unauthorized transfer of information, or unauthorized tunnelling. Organizations can utilize network scanning tools, intrusion detection and prevention systems, and end-point protections such as firewalls and host-based intrusion detection systems to identify and prevent the use of prohibited functions, ports, protocols, and services. Related controls: AC-6, CM-2, RA-5, SA-5, SC-7 | D9: Directives supplémentaires | E9: Les systèmes d’information peuvent offrir une grande variété de fonctions et de services. Certaines fonctions et certains services, fournis par défaut, peuvent ne pas être nécessaires au soutien des opérations essentielles de l’organisation (p. ex., missions et fonctions clés). De plus, il est parfois pratique de fournir plusieurs services à partir de composants uniques du système d’information, mais cela augmente le risque de limiter les services fournis par un seul composant. Dans la mesure du possible, les organisations limitent la fonctionnalité des composants à une seule fonction par dispositif (p. ex., serveurs de courriel ou serveurs Web, mais pas les deux). Les organisations examinent les fonctions et les services fournis par les systèmes d’information ou les composants individuels des systèmes d’information afin de déterminer quelles fonctions et quels services peuvent être éliminés (p. ex., voix sur protocole Internet [VoIP], messagerie instantanée, auto-exécution et partage de fichiers). Les organisations envisagent de désactiver les ports/protocoles physiques et logiques inutilisés ou inutiles (p. ex., USB, FTP, IPv6, HTTP) sur les systèmes d’information afin de prévenir la connexion non autorisée d’appareils, le transfert non autorisé d’information ou la tunnellisation non autorisée. Les organisations peuvent utiliser des outils de balayage de réseau, des systèmes de détection et de prévention des intrusions et des mesures de protection d’extrémité comme des pare-feu et des systèmes de détection des intrusions basés sur l’hôte, pour identifier et prévenir l’utilisation de fonctions, de ports, de protocoles et de services interdits. Contrôles connexes : AC-6, CM-2, RA-5, SA-5, SC-7
A10: Test Case | D10: Cas de test
A11: Test | B11: TEST-CM-7 | D11: Test | E11: TEST-CM-7
A12: Requirement ID | B12: CM-7 | D12: ID Exigence | E12: CM-7
A13: Component | D13: Composant
A14: Requirement | D14: Exigence
A15: Contextual Design Description | D15: Description contextuelle du design
A16: Evidence Provided | D16: Preuve fournie
A17: Preparer Sign Off (Initials, Date) | D17: Signataire préparateur (Initiales, Date)
A18: Owner Sign Off (Initials, Date) | D18: Signataire propriétaire (Initiales, Date)
A19: Assessor Sign Off (Initials, Date) | D19: Signataire évaluateur (Initiales, Date)
A20: Status | B20: Not Started | D20: Statut | E20: Non commencé
A21: Comments | D21: Commentaires

Sheet CM-7-1
A1: Control CM-7(1) — Evidence Tracking | D1: Contrôle CM-7(1) — Suivi des preuves
A2: Control Information | D2: Informations du contrôle
A3: Control Identifier | B3: CM-7(1) | D3: Identifiant du contrôle | E3: CM-7(1)
A4: Family | B4: Least Functionality | D4: Famille | E4: Moindre fonctionnalité
A5: Profile | B5: CCCS Medium / PBMM Moderate | D5: Profil | E5: CCCS Moyen / PBMM Modéré
A6: Primary Evidence Tool | D6: Outil de preuve principal
A7: Contributing Tools | D7: Outils contributeurs
A8: Control Description | B8: LEAST FUNCTIONALITY | PERIODIC REVIEW The organization reviews the information system at least annually to identify unnecessary and/or non-secure functions, ports, protocols, and services; and The organization disables all functions, ports, protocols, and services within the information system deemed to be unnecessary and/or nonsecure. | D8: Description du contrôle | E8: MOINDRE FONCTIONNALITÉ | EXAMEN PÉRIODIQUE L’organisation revoit le système d’information au moins une fois par année afin de repérer les fonctions, les ports, les protocoles et les services inutiles ou non sécurisés; L’organisation désactive toutes les fonctions, tous les ports, tous les protocoles et tous les services du système d’information jugés inutiles ou non sécurisés.
A9: Supplemental Guidance | B9: The organization can either make a determination of the relative security of the function, port, protocol, and/or service or base the security decision on the assessment of other entities. Bluetooth, FTP, and peer-to-peer networking are examples of less than secure protocols. Related controls: AC-18, CM-7, IA-2. | D9: Directives supplémentaires | E9: L’organisation peut soit déterminer la sécurité relative de la fonction, du port, du protocole ou du service, soit baser sa décision en matière de sécurité sur l’évaluation d’autres entités. Bluetooth, FTP et l’interconnexion de réseaux d’égal à égal sont des exemples de protocoles moins sécurisés. Contrôles connexes : AC-18, CM-7, IA-2.
A10: Test Case | D10: Cas de test
A11: Test | B11: TEST-CM-7(1) | D11: Test | E11: TEST-CM-7(1)
A12: Requirement ID | B12: CM-7(1) | D12: ID Exigence | E12: CM-7(1)
A13: Component | D13: Composant
A14: Requirement | D14: Exigence
A15: Contextual Design Description | D15: Description contextuelle du design
A16: Evidence Provided | D16: Preuve fournie
A17: Preparer Sign Off (Initials, Date) | D17: Signataire préparateur (Initiales, Date)
A18: Owner Sign Off (Initials, Date) | D18: Signataire propriétaire (Initiales, Date)
A19: Assessor Sign Off (Initials, Date) | D19: Signataire évaluateur (Initiales, Date)
A20: Status | B20: Not Started | D20: Statut | E20: Non commencé
A21: Comments | D21: Commentaires

Sheet CM-10
A1: Control CM-10 — Evidence Tracking | D1: Contrôle CM-10 — Suivi des preuves
A2: Control Information | D2: Informations du contrôle
A3: Control Identifier | B3: CM-10 | D3: Identifiant du contrôle | E3: CM-10
A4: Family | B4: Software Usage Restrictions | D4: Famille | E4: Restrictions d’utilisation des logiciels
A5: Profile | B5: CCCS Medium / PBMM Moderate | D5: Profil | E5: CCCS Moyen / PBMM Modéré
A6: Primary Evidence Tool | D6: Outil de preuve principal
A7: Contributing Tools | D7: Outils contributeurs
A8: Control Description | B8: (A) The organization uses software and associated documentation in accordance with contract agreements and copyright laws. (B) The organization tracks the use of software and associated documentation protected by quantity licenses to control copying and distribution. (C) The organization controls and documents the use of peer-to-peer file sharing technology to ensure that this capability is not used for the unauthorized distribution, display, performance, or reproduction of copyrighted work. | D8: Description du contrôle | E8: (A) L’organisation utilise les logiciels et la documentation connexe conformément aux ententes contractuelles et aux lois sur le droit d’auteur. (B) L’organisation assure le suivi de l’utilisation des logiciels et de la documentation connexe protégés par des licences limitant la quantité afin de contrôler la reproduction et la distribution. (C) L’organisation contrôle et documente l’utilisation de la technologie de partage de fichiers poste-à-poste pour s’assurer que cette capacité n’est pas utilisée pour la distribution, l’affichage, l’exécution ou la reproduction non autorisés d’une œuvre protégée par le droit d’auteur.
A9: Supplemental Guidance | B9: Software license tracking can be accomplished by manual methods (e.g., simple spreadsheets) or automated methods (e.g., specialized tracking applications) depending on organizational needs. Related controls: AC-17, CM-8, SC-7 | D9: Directives supplémentaires | E9: Le suivi des licences logicielles peut se faire par des méthodes manuelles (p. ex., simples tableurs) ou automatisées (p. ex., applications de suivi spécialisées) selon les besoins organisationnels. Contrôles connexes : AC-17, CM-8, SC-7
A10: Test Case | D10: Cas de test
A11: Test | B11: TEST-CM-10 | D11: Test | E11: TEST-CM-10
A12: Requirement ID | B12: CM-10 | D12: ID Exigence | E12: CM-10
A13: Component | D13: Composant
A14: Requirement | D14: Exigence
A15: Contextual Design Description | D15: Description contextuelle du design
A16: Evidence Provided | D16: Preuve fournie
A17: Preparer Sign Off (Initials, Date) | D17: Signataire préparateur (Initiales, Date)
A18: Owner Sign Off (Initials, Date) | D18: Signataire propriétaire (Initiales, Date)
A19: Assessor Sign Off (Initials, Date) | D19: Signataire évaluateur (Initiales, Date)
A20: Status | B20: Not Started | D20: Statut | E20: Non commencé
A21: Comments | D21: Commentaires

Sheet CP-7
A1: Control CP-7 — Evidence Tracking | D1: Contrôle CP-7 — Suivi des preuves
A2: Control Information | D2: Informations du contrôle
A3: Control Identifier | B3: CP-7 | D3: Identifiant du contrôle | E3: CP-7
A4: Family | B4: Alternate Processing Site | D4: Famille | E4: Site de traitement auxiliaire
A5: Profile | B5: CCCS Medium / PBMM Moderate | D5: Profil | E5: CCCS Moyen / PBMM Modéré
A6: Primary Evidence Tool | D6: Outil de preuve principal
A7: Contributing Tools | D7: Outils contributeurs
A8: Control Description | B8: (A) The organization establishes an alternate processing site including necessary agreements to permit the transfer and resumption of organization-defined information system operations for essential missions/business functions within organization-defined time period consistent with recovery time and recovery point objectives when the primary processing capabilities are unavailable. (B) The organization ensures that equipment and supplies required to transfer and resume operations are available at the alternate processing site or contracts are in place to support delivery to the site within the organization-defined time period for transfer/resumption. (C) The organization ensures that the alternate processing site provides information security safeguards equivalent to that of the primary site. | D8: Description du contrôle | E8: (A) L’organisation établit un site de traitement auxiliaire, y compris les ententes nécessaires pour permettre le transfert et la reprise des opérations du système d’information définies par l’organisation pour les missions et les fonctions opérationnelles essentielles à l’intérieur d’une période définie par l’organisation, conformément aux objectifs en matière de délais de reprise et de points de reprise lorsque les capacités de traitement principales ne sont pas disponibles. (B) L’organisation veille à ce que l’équipement et les fournitures nécessaires au transfert et à la reprise des activités soient disponibles au site de traitement auxiliaire, ou à ce que des contrats soient en place pour soutenir la livraison au site à l’intérieur de la période définie par l’organisation pour le transfert ou la reprise. (C) L’organisation veille à ce que le site de traitement auxiliaire offre des mesures de sécurité de l’information équivalentes à celles du site principal.
A9: Supplemental Guidance | B9: Alternate processing sites are sites that are geographically distinct from primary processing sites. An alternate processing site provides processing capability in the event that the primary processing site is not available. Items covered by alternate processing site agreements include, for example, environmental conditions at alternate sites, access rules, physical and environmental protection requirements, and coordination for the transfer/assignment of personnel. Requirements are specifically allocated to alternate processing sites that reflect the requirements in contingency plans to maintain essential missions/business functions despite disruption, compromise, or failure in organizational information systems. Related controls: CP-2, CP-6, CP-8, CP-9, CP-10, MA-6 | D9: Directives supplémentaires | E9: Les sites de traitement auxiliaires sont des sites qui sont géographiquement séparés des sites de traitement principaux. Un site de traitement auxiliaire offre une capacité de traitement lorsque le site de traitement principal n’est pas disponible. Les éléments couverts par les accords sur les sites de traitement auxiliaires comprennent, par exemple, les conditions environnementales aux sites auxiliaires, les règles d’accès, les exigences en matière de protection physique et environnementale, et la coordination pour le transfert ou l’attribution du personnel. Les exigences spécifiquement attribuées aux sites de traitement auxiliaires reflètent les exigences des plans d’urgence pour maintenir les fonctions opérationnelles et de mission essentielles malgré la perturbation, la compromission ou la défaillance des systèmes d’information organisationnels. Contrôles connexes : CP-2, CP-6, CP-8, CP-9, CP-10, MA-6
A10: Test Case | D10: Cas de test
A11: Test | B11: TEST-CP-7 | D11: Test | E11: TEST-CP-7
A12: Requirement ID | B12: CP-7 | D12: ID Exigence | E12: CP-7
A13: Component | D13: Composant
A14: Requirement | D14: Exigence
A15: Contextual Design Description | D15: Description contextuelle du design
A16: Evidence Provided | D16: Preuve fournie
A17: Preparer Sign Off (Initials, Date) | D17: Signataire préparateur (Initiales, Date)
A18: Owner Sign Off (Initials, Date) | D18: Signataire propriétaire (Initiales, Date)
A19: Assessor Sign Off (Initials, Date) | D19: Signataire évaluateur (Initiales, Date)
A20: Status | B20: Not Started | D20: Statut | E20: Non commencé
A21: Comments | D21: Commentaires

Sheet CP-7-4
A1: Control CP-7(4) — Evidence Tracking | D1: Contrôle CP-7(4) — Suivi des preuves
A2: Control Information | D2: Informations du contrôle
A3: Control Identifier | B3: CP-7(4) | D3: Identifiant du contrôle | E3: CP-7(4)
A4: Family | B4: Alternate Processing Site | D4: Famille | E4: Site de traitement auxiliaire
A5: Profile | B5: CCCS Medium / PBMM Moderate | D5: Profil | E5: CCCS Moyen / PBMM Modéré
A6: Primary Evidence Tool | D6: Outil de preuve principal
A7: Contributing Tools | D7: Outils contributeurs
A8: Control Description | B8: ALTERNATE PROCESSING SITE | PREPARATION FOR USE The organization prepares the alternate processing site so that the site is ready to be used as the operational site supporting essential missions and business functions. | D8: Description du contrôle | E8: SITE DE TRAITEMENT AUXILIAIRE | PRÉPARATION À L’UTILISATION L’organisation prépare le site de traitement auxiliaire de manière à ce que le site soit prêt à être utilisé comme site opérationnel prenant en charge les fonctions opérationnelles et les missions essentielles.
A9: Supplemental Guidance | B9: Site preparation includes, for example, establishing configuration settings for information system components at the alternate processing site consistent with the requirements for such settings at the primary site and ensuring that essential supplies and other logistical considerations are in place. Related controls: CM-2, CM-6. | D9: Directives supplémentaires | E9: La préparation du site comprend, par exemple, l’établissement des paramètres de configuration pour les composants du système d’information au site de traitement auxiliaire, conformément aux exigences pour ces paramètres au site principal, et l’assurance que les fournitures essentielles et autres considérations logistiques sont en place. Contrôles connexes : CM-2, CM-6.
A10: Test Case | D10: Cas de test
A11: Test | B11: TEST-CP-7(4) | D11: Test | E11: TEST-CP-7(4)
A12: Requirement ID | B12: CP-7(4) | D12: ID Exigence | E12: CP-7(4)
A13: Component | D13: Composant
A14: Requirement | D14: Exigence
A15: Contextual Design Description | D15: Description contextuelle du design
A16: Evidence Provided | D16: Preuve fournie
A17: Preparer Sign Off (Initials, Date) | D17: Signataire préparateur (Initiales, Date)
A18: Owner Sign Off (Initials, Date) | D18: Signataire propriétaire (Initiales, Date)
A19: Assessor Sign Off (Initials, Date) | D19: Signataire évaluateur (Initiales, Date)
A20: Status | B20: Not Started | D20: Statut | E20: Non commencé
A21: Comments | D21: Commentaires

Sheet CP-10
A1: Control CP-10 — Evidence Tracking | D1: Contrôle CP-10 — Suivi des preuves
A2: Control Information | D2: Informations du contrôle
A3: Control Identifier | B3: CP-10 | D3: Identifiant du contrôle | E3: CP-10
A4: Family | B4: Information System Recovery and Reconstitution | D4: Famille | E4: Reprise et reconstitution du système d’information
A5: Profile | B5: CCCS Medium / PBMM Moderate | D5: Profil | E5: CCCS Moyen / PBMM Modéré
A6: Primary Evidence Tool | D6: Outil de preuve principal
A7: Contributing Tools | D7: Outils contributeurs
A8: Control Description | B8: (A) The organization provides for the recovery and reconstitution of the information system to a known state after a disruption, compromise, or failure. | D8: Description du contrôle | E8: (A) L’organisation assure la reprise et la reconstitution du système d’information dans un état connu après une perturbation, une compromission ou une défaillance.
A9: Supplemental Guidance | B9: Recovery is executing information system contingency plan activities to restore organizational missions/business functions. Reconstitution takes place following recovery and includes activities for returning organizational information systems to fully operational states. Recovery and reconstitution operations reflect mission and business priorities, recovery point/time and reconstitution objectives, and established organizational metrics consistent with contingency plan requirements. Reconstitution includes the deactivation of any interim information system capabilities that may have been needed during recovery operations. Reconstitution also includes assessments of fully restored information system capabilities, reestablishment of continuous monitoring activities, potential information system reauthorizations, and activities to prepare the systems against future disruptions, compromises, or failures. Recovery/reconstitution capabilities employed by organizations can include both automated mechanisms and manual procedures. Related controls: CA-2, CA-6, CA-7, CP-2, CP-4, CP-6, CP-7, CP-9, SC-24 | D9: Directives supplémentaires | E9: La reprise consiste à exécuter les activités du plan d’urgence du système d’information pour restaurer les fonctions opérationnelles et de mission de l’organisation. La reconstitution a lieu après la reprise et comprend les activités permettant de remettre les systèmes d’information organisationnels à l’état pleinement opérationnel. Les opérations de reprise et de reconstitution reflètent les priorités opérationnelles et de mission, les objectifs en matière de délais, de points de reprise et de reconstitution, de même que les paramètres organisationnels établis conformément aux exigences du plan d’urgence. La reconstitution comprend la désactivation de toute capacité provisoire du système d’information ayant pu être nécessaire pendant les opérations de reprise. La reconstitution comprend également l’évaluation des capacités entièrement restaurées du système d’information, le rétablissement des activités de surveillance continue, les réautorisations possibles du système d’information et les activités visant à préparer les systèmes à faire face aux perturbations, compromissions ou défaillances futures. Les capacités de reprise et de reconstitution utilisées par les organisations peuvent comprendre des mécanismes automatisés et des procédures manuelles. Contrôles connexes : CA-2, CA-6, CA-7, CP-2, CP-4, CP-6, CP-7, CP-9, SC-24
A10: Test Case | D10: Cas de test
A11: Test | B11: TEST-CP-10 | D11: Test | E11: TEST-CP-10
A12: Requirement ID | B12: CP-10 | D12: ID Exigence | E12: CP-10
A13: Component | D13: Composant
A14: Requirement | D14: Exigence
A15: Contextual Design Description | D15: Description contextuelle du design
A16: Evidence Provided | D16: Preuve fournie
A17: Preparer Sign Off (Initials, Date) | D17: Signataire préparateur (Initiales, Date)
A18: Owner Sign Off (Initials, Date) | D18: Signataire propriétaire (Initiales, Date)
A19: Assessor Sign Off (Initials, Date) | D19: Signataire évaluateur (Initiales, Date)
A20: Status | B20: Not Started | D20: Statut | E20: Non commencé
A21: Comments | D21: Commentaires

Sheet CP-10-4
A1: Control CP-10(4) — Evidence Tracking | D1: Contrôle CP-10(4) — Suivi des preuves
A2: Control Information | D2: Informations du contrôle
A3: Control Identifier | B3: CP-10(4) | D3: Identifiant du contrôle | E3: CP-10(4)
A4: Family | B4: Information System Recovery and Reconstitution | D4: Famille | E4: Reprise et reconstitution du système d’information
A5: Profile | B5: CCCS Medium / PBMM Moderate | D5: Profil | E5: CCCS Moyen / PBMM Modéré
A6: Primary Evidence Tool | D6: Outil de preuve principal
A7: Contributing Tools | D7: Outils contributeurs
A8: Control Description | B8: INFORMATION SYSTEM RECOVERY AND RECONSTITUTION | RESTORE WITHIN TIME PERIOD The organization provides the capability to restore information system components within organization-defined restoration time-periods from configuration-controlled and integrity-protected information representing a known, operational state for the components. | D8: Description du contrôle | E8: REPRISE ET RECONSTITUTION DU SYSTÈME D’INFORMATION | RESTAURATION DANS LE DÉLAI IMPARTI L’organisation fournit la capacité de restaurer les composants du système d’information dans les délais de restauration définis par l’organisation à partir de l’information contrôlée par la configuration et protégée par l’intégrité qui représente un état de fonctionnement connu pour les composants.
A9: Supplemental Guidance | B9: Restoration of information system components includes, for example, re-imaging which restores components to known, operational states. Related control: CM-2. | D9: Directives supplémentaires | E9: La restauration des composants du système d’information comprend, par exemple, la reconfiguration permettant de restaurer les composants aux états de fonctionnement connus. Contrôle connexe : CM-2.
A10: Test Case | D10: Cas de test
A11: Test | B11: TEST-CP-10(4) | D11: Test | E11: TEST-CP-10(4)
A12: Requirement ID | B12: CP-10(4) | D12: ID Exigence | E12: CP-10(4)
A13: Component | D13: Composant
A14: Requirement | D14: Exigence
A15: Contextual Design Description | D15: Description contextuelle du design
A16: Evidence Provided | D16: Preuve fournie
A17: Preparer Sign Off (Initials, Date) | D17: Signataire préparateur (Initiales, Date)
A18: Owner Sign Off (Initials, Date) | D18: Signataire propriétaire (Initiales, Date)
A19: Assessor Sign Off (Initials, Date) | D19: Signataire évaluateur (Initiales, Date)
A20: Status | B20: Not Started | D20: Statut | E20: Non commencé
A21: Comments | D21: Commentaires

Sheet IA-3
A1: Control IA-3 — Evidence Tracking | D1: Contrôle IA-3 — Suivi des preuves
A2: Control Information | D2: Informations du contrôle
A3: Control Identifier | B3: IA-3 | D3: Identifiant du contrôle | E3: IA-3
A4: Family | B4: Device Identification and Authentication | D4: Famille | E4: Identification et authentification des dispositifs
A5: Profile | B5: CCCS Medium / PBMM Moderate | D5: Profil | E5: CCCS Moyen / PBMM Modéré
A6: Primary Evidence Tool | D6: Outil de preuve principal
A7: Contributing Tools | D7: Outils contributeurs
A8: Control Description | B8: (A) The information system uniquely identifies and authenticates organization-defined specific and/or types of devices before establishing network connections. | D8: Description du contrôle | E8: (A) Le système d’information identifie et authentifie de façon unique des dispositifs spécifiques ou des types de dispositifs définis par l’organisation avant d’établir des connexions réseau.
A9: Supplemental Guidance | B9: Organizational devices requiring unique device-to-device identification and authentication may be defined by type, by device, or by a combination of type/device. Information systems typically use either shared known information (e.g., Media Access Control [MAC] or Transmission Control Protocol/Internet Protocol [TCP/IP] addresses) for device identification or organizational authentication solutions (e.g., IEEE 802.1x and EAP, Radius server with EAP-TLS authentication, Kerberos) to identify/authenticate devices on local and/or wide area networks. Organizations determine the required strength of authentication mechanisms by the security categories of information systems. Because of the challenges of applying this control on large scale, organizations are encouraged to only apply the control to those limited number (and type) of devices that truly need to support this capability. Related controls: AC-17, AC-18, AC-19, CA-3, IA-4, IA-5 | D9: Directives supplémentaires | E9: Les dispositifs organisationnels nécessitant une identification et une authentification uniques d’un dispositif à l’autre peuvent être définis par type, par dispositif ou par une combinaison de type/dispositif. Les systèmes d’information utilisent habituellement de l’information connue partagée (p. ex., adresses MAC ou TCP/IP) pour l’identification des dispositifs ou des solutions d’authentification organisationnelle (p. ex., IEEE 802.1x et EAP, serveur RADIUS avec authentification EAP-TLS, Kerberos) pour identifier et authentifier les dispositifs sur les réseaux locaux ou étendus. Les organisations déterminent la force requise pour les mécanismes d’authentification en fonction des catégories de sécurité des systèmes d’information. En raison des défis que pose l’application de ce contrôle à grande échelle, les organisations sont encouragées à appliquer le contrôle seulement à un nombre (et un type) limité de dispositifs qui ont véritablement besoin de prendre en charge cette capacité. Contrôles connexes : AC-17, AC-18, AC-19, CA-3, IA-4, IA-5
A10: Test Case | D10: Cas de test
A11: Test | B11: TEST-IA-3 | D11: Test | E11: TEST-IA-3
A12: Requirement ID | B12: IA-3 | D12: ID Exigence | E12: IA-3
A13: Component | D13: Composant
A14: Requirement | D14: Exigence
A15: Contextual Design Description | D15: Description contextuelle du design
A16: Evidence Provided | D16: Preuve fournie
A17: Preparer Sign Off (Initials, Date) | D17: Signataire préparateur (Initiales, Date)
A18: Owner Sign Off (Initials, Date) | D18: Signataire propriétaire (Initiales, Date)
A19: Assessor Sign Off (Initials, Date) | D19: Signataire évaluateur (Initiales, Date)
A20: Status | B20: Not Started | D20: Statut | E20: Non commencé
A21: Comments | D21: Commentaires

Sheet MA-4-6
A1: Control MA-4(6) — Evidence Tracking | D1: Contrôle MA-4(6) — Suivi des preuves
A2: Control Information | D2: Informations du contrôle
A3: Control Identifier | B3: MA-4(6) | D3: Identifiant du contrôle | E3: MA-4(6)
A4: Family | B4: Non-Local Maintenance | D4: Famille | E4: Maintenance non locale
A5: Profile | B5: CCCS Medium / PBMM Moderate | D5: Profil | E5: CCCS Moyen / PBMM Modéré
A6: Primary Evidence Tool | D6: Outil de preuve principal
A7: Contributing Tools | D7: Outils contributeurs
A8: Control Description | B8: NONLOCAL MAINTENANCE | CRYPTOGRAPHIC PROTECTION The information system implements cryptographic mechanisms to protect the integrity and confidentiality of nonlocal maintenance and diagnostic communications. | D8: Description du contrôle | E8: MAINTENANCE NON LOCALE | PROTECTION CRYPTOGRAPHIQUE Le système d’information met en œuvre des mécanismes cryptographiques pour protéger l’intégrité et la confidentialité des communications de maintenance et de diagnostic non locales.
A9: Supplemental Guidance | B9: Related controls: SC-8, SC-13. | D9: Directives supplémentaires | E9: Contrôles connexes : SC-8, SC-13.
A10: Test Case | D10: Cas de test
A11: Test | B11: TEST-MA-4(6) | D11: Test | E11: TEST-MA-4(6)
A12: Requirement ID | B12: MA-4(6) | D12: ID Exigence | E12: MA-4(6)
A13: Component | D13: Composant
A14: Requirement | D14: Exigence
A15: Contextual Design Description | D15: Description contextuelle du design
A16: Evidence Provided | D16: Preuve fournie
A17: Preparer Sign Off (Initials, Date) | D17: Signataire préparateur (Initiales, Date)
A18: Owner Sign Off (Initials, Date) | D18: Signataire propriétaire (Initiales, Date)
A19: Assessor Sign Off (Initials, Date) | D19: Signataire évaluateur (Initiales, Date)
A20: Status | B20: Not Started | D20: Statut | E20: Non commencé
A21: Comments | D21: Commentaires

Sheet SA-9-5
A1: Control SA-9(5) — Evidence Tracking | D1: Contrôle SA-9(5) — Suivi des preuves
A2: Control Information | D2: Informations du contrôle
A3: Control Identifier | B3: SA-9(5) | D3: Identifiant du contrôle | E3: SA-9(5)
A4: Family | B4: External Information System Services | D4: Famille | E4: Services de systèmes d’information externes
A5: Profile | B5: CCCS Medium / PBMM Moderate | D5: Profil | E5: CCCS Moyen / PBMM Modéré
A6: Primary Evidence Tool | D6: Outil de preuve principal
A7: Contributing Tools | D7: Outils contributeurs
A8: Control Description | B8: EXTERNAL INFORMATION SYSTEMS | PROCESSING, STORAGE, AND SERVICE LOCATION The organization restricts the location of information processing, information/data, and information system services to locations witihin Canada based on ITPIN 2017-02 for Direction on Data Residency (https://www.canada.ca/en/treasury-board-secretariat/services/information-technology/policy-implementation-notices/direction-electronic-data-residency.html). | D8: Description du contrôle | E8: SYSTÈMES D’INFORMATION EXTERNES | EMPLACEMENT DU TRAITEMENT, DU STOCKAGE ET DES SERVICES L’organisation restreint la résidence du traitement de l’information, du stockage de l’information et des données, ainsi que des services de systèmes d’information aux endroits situés à l’intérieur du Canada, conformément à l’avis AMPTI 2017-02, Orientation relative à la résidence des données électroniques (https://www.canada.ca/fr/gouvernement/systeme/gouvernement-numerique/technologiques-modernes-nouveaux/orientation-relative-residence-donnees-electroniques.html).
A9: Supplemental Guidance | B9: The location of information processing, information/data storage, or information system services that are critical to organizations can have a direct impact on the ability of those organizations to successfully execute their missions/business functions. This situation exists when external providers control the location of processing, storage or services. The criteria external providers use for the selection of processing, storage, or service locations may be different from organizational criteria. For example, organizations may want to ensure that data/information storage locations are restricted to certain locations to facilitate incident response activities (e.g., forensic analyses, after-the-fact investigations) in case of information security breaches/compromises. Such incident response activities may be adversely affected by the governing laws or protocols in the locations where processing and storage occur and/or the locations from which information system services emanate. | D9: Directives supplémentaires | E9: L’emplacement des services de traitement de l’information et de stockage de l’information et des données ou des services de systèmes d’information qui sont essentiels pour les organisations peut avoir une incidence directe sur la capacité de ces organisations d’exécuter avec succès leurs fonctions opérationnelles et de mission. Cette situation existe lorsque des fournisseurs externes contrôlent l’emplacement du traitement, de l’entreposage ou des services. Les critères utilisés par les fournisseurs externes pour choisir les lieux de traitement, d’entreposage ou de service peuvent être différents des critères de l’organisation. Par exemple, les organisations pourraient vouloir s’assurer que les emplacements de stockage des données ou de l’information se limitent à certains endroits afin de faciliter les activités d’intervention (p. ex., analyses judiciaires, enquêtes après coup) en cas d’incident représentant une atteinte à, ou une compromission de la sécurité de l’information. Ces activités d’intervention en cas d’incident peuvent être affectées négativement par les lois ou les protocoles en vigueur aux endroits où le traitement et l’entreposage ont lieu ou aux endroits d’où proviennent les services de systèmes d’information.
A10: Test Case | D10: Cas de test
A11: Test | B11: TEST-SA-9(5) | D11: Test | E11: TEST-SA-9(5)
A12: Requirement ID | B12: SA-9(5) | D12: ID Exigence | E12: SA-9(5)
A13: Component | D13: Composant
A14: Requirement | D14: Exigence
A15: Contextual Design Description | D15: Description contextuelle du design
A16: Evidence Provided | D16: Preuve fournie
A17: Preparer Sign Off (Initials, Date) | D17: Signataire préparateur (Initiales, Date)
A18: Owner Sign Off (Initials, Date) | D18: Signataire propriétaire (Initiales, Date)
A19: Assessor Sign Off (Initials, Date) | D19: Signataire évaluateur (Initiales, Date)
A20: Status | B20: Not Started | D20: Statut | E20: Non commencé
A21: Comments | D21: Commentaires

Sheet SC-2
A1: Control SC-2 — Evidence Tracking | D1: Contrôle SC-2 — Suivi des preuves
A2: Control Information | D2: Informations du contrôle
A3: Control Identifier | B3: SC-2 | D3: Identifiant du contrôle | E3: SC-2
A4: Family | B4: Application Partitioning | D4: Famille | E4: Partitionnement des applications
A5: Profile | B5: CCCS Medium / PBMM Moderate | D5: Profil | E5: CCCS Moyen / PBMM Modéré
A6: Primary Evidence Tool | D6: Outil de preuve principal
A7: Contributing Tools | D7: Outils contributeurs
A8: Control Description | B8: (A) The information system separates user functionality (including user interface services) from information system management functionality. | D8: Description du contrôle | E8: (A) Le système d’information sépare la fonctionnalité de l’utilisateur (y compris les services d’interface utilisateur) de la fonctionnalité de gestion du système d’information.
A9: Supplemental Guidance | B9: Information system management functionality includes, for example, functions necessary to administer databases, network components, workstations, or servers, and typically requires privileged user access. The separation of user functionality from information system management functionality is either physical or logical. Organizations implement separation of system management-related functionality from user functionality by using different computers, different central processing units, different instances of operating systems, different network addresses, virtualization techniques, or combinations of these or other methods, as appropriate. This type of separation includes, for example, web administrative interfaces that use separate authentication methods (e.g., using a logical separation, web administrators would use 2-factor authentication and normal users of the web application would use username/password authentication). Separation of system and user functionality may include isolating administrative interfaces on different domains and with additional access controls. Related controls: SA-4, SA-8, SC-3 | D9: Directives supplémentaires | E9: La fonctionnalité de gestion du système d’information comprend, par exemple, les fonctions nécessaires à l’administration des bases de données, des composants de réseau, des postes de travail ou des serveurs, et exige habituellement un accès utilisateur privilégié. La séparation de la fonctionnalité de l’utilisateur de la fonctionnalité de gestion du système d’information est soit physique, soit logique. Les organisations mettent en œuvre la séparation de la fonctionnalité de gestion du système de la fonctionnalité de l’utilisateur en utilisant différents ordinateurs, différentes unités centrales de traitement, différentes instances de systèmes d’exploitation, différentes adresses réseau, des techniques de virtualisation ou des combinaisons de ces méthodes ou d’autres méthodes, selon le cas. Ce type de séparation comprend, par exemple, les interfaces administratives Web qui utilisent des méthodes d’authentification séparées (p. ex., en utilisant une séparation logique, les administrateurs Web utiliseraient l’authentification à deux facteurs et les utilisateurs habituels de l’application Web utiliseraient l’authentification par nom d’utilisateur/mot de passe). La séparation des fonctions du système et de l’utilisateur peut comprendre l’isolement des interfaces administratives dans différents domaines et avec des contrôles d’accès supplémentaires. Contrôles connexes : SA-4, SA-8, SC-3
A10: Test Case | D10: Cas de test
A11: Test | B11: TEST-SC-2 | D11: Test | E11: TEST-SC-2
A12: Requirement ID | B12: SC-2 | D12: ID Exigence | E12: SC-2
A13: Component | D13: Composant
A14: Requirement | D14: Exigence
A15: Contextual Design Description | D15: Description contextuelle du design
A16: Evidence Provided | D16: Preuve fournie
A17: Preparer Sign Off (Initials, Date) | D17: Signataire préparateur (Initiales, Date)
A18: Owner Sign Off (Initials, Date) | D18: Signataire propriétaire (Initiales, Date)
A19: Assessor Sign Off (Initials, Date) | D19: Signataire évaluateur (Initiales, Date)
A20: Status | B20: Not Started | D20: Statut | E20: Non commencé
A21: Comments | D21: Commentaires

Sheet SC-4
A1: Control SC-4 — Evidence Tracking | D1: Contrôle SC-4 — Suivi des preuves
A2: Control Information | D2: Informations du contrôle
A3: Control Identifier | B3: SC-4 | D3: Identifiant du contrôle | E3: SC-4
A4: Family | B4: Information in Shared Resources | D4: Famille | E4: Information dans les ressources partagées
A5: Profile | B5: CCCS Medium / PBMM Moderate | D5: Profil | E5: CCCS Moyen / PBMM Modéré
A6: Primary Evidence Tool | D6: Outil de preuve principal
A7: Contributing Tools | D7: Outils contributeurs
A8: Control Description | B8: (A) The information system prevents unauthorized and unintended information transfer via shared system resources. | D8: Description du contrôle | E8: (A) Le système d’information empêche le transfert non autorisé et non intentionnel d’information par le biais des ressources partagées du système.
A9: Supplemental Guidance | B9: This control prevents information, including encrypted representations of information, produced by the actions of prior users/roles (or the actions of processes acting on behalf of prior users/roles) from being available to any current users/roles (or current processes) that obtain access to shared system resources (e.g., registers, main memory, hard disks) after those resources have been released back to information systems. The control of information in shared resources is also commonly referred to as object reuse and residual information protection. This control does not address: (i) information remanence which refers to residual representation of data that has been nominally erased or removed; (ii) covert channels (including storage and/or timing channels) where shared resources are manipulated to violate information flow restrictions; or (iii) components within information systems for which there are only single users/roles. Related controls: AC-3, AC-4, MP-6 | D9: Directives supplémentaires | E9: Ce contrôle empêche l’information, y compris les représentations chiffrées de l’information, produites par les actions des utilisateurs/rôles antérieurs (ou les actions des processus agissant pour le compte des utilisateurs/rôles antérieurs) d’être accessible aux utilisateurs/rôles actuels (ou aux processus actuels) qui obtiennent l’accès aux ressources partagées du système (p. ex., registres, mémoire principale, disques durs) après que ces ressources ont été retournées aux systèmes d’information. Le contrôle de l’information dans les ressources partagées est aussi communément appelé réutilisation d’objets et protection de l’information résiduelle. Ce contrôle ne porte pas sur : (i) la rémanence de l’information qui désigne la représentation résiduelle des données qui ont été nominalement effacées ou supprimées; (ii) les canaux cachés (y compris les canaux de stockage ou de synchronisation) où les ressources partagées sont manipulées pour violer les restrictions de circulation de l’information; ou (iii) les composants des systèmes d’information pour lesquels il n’y a qu’un seul utilisateur/rôle. Contrôles connexes : AC-3, AC-4, MP-6
A10: Test Case | D10: Cas de test
A11: Test | B11: TEST-SC-4 | D11: Test | E11: TEST-SC-4
A12: Requirement ID | B12: SC-4 | D12: ID Exigence | E12: SC-4
A13: Component | D13: Composant
A14: Requirement | D14: Exigence
A15: Contextual Design Description | D15: Description contextuelle du design
A16: Evidence Provided | D16: Preuve fournie
A17: Preparer Sign Off (Initials, Date) | D17: Signataire préparateur (Initiales, Date)
A18: Owner Sign Off (Initials, Date) | D18: Signataire propriétaire (Initiales, Date)
A19: Assessor Sign Off (Initials, Date) | D19: Signataire évaluateur (Initiales, Date)
A20: Status | B20: Not Started | D20: Statut | E20: Non commencé
A21: Comments | D21: Commentaires

Sheet SC-5
A1: Control SC-5 — Evidence Tracking | D1: Contrôle SC-5 — Suivi des preuves
A2: Control Information | D2: Informations du contrôle
A3: Control Identifier | B3: SC-5 | D3: Identifiant du contrôle | E3: SC-5
A4: Family | B4: Denial of Service Protection | D4: Famille | E4: Protection contre le déni de service
A5: Profile | B5: CCCS Medium / PBMM Moderate | D5: Profil | E5: CCCS Moyen / PBMM Modéré
A6: Primary Evidence Tool | D6: Outil de preuve principal
A7: Contributing Tools | D7: Outils contributeurs
A8: Control Description | B8: (A) The information system protects against or limits the effects of the following denial of service attempts that attack bandwidth, transactional capacity and storage by employing geo-replication, IP address blocking, and network-based DDoS protections. | D8: Description du contrôle | E8: (A) Le système d’information assure une protection ou limite les effets des tentatives de déni de service suivantes qui s’attaquent à la largeur de bande, à la capacité transactionnelle et au stockage en utilisant la géoréplication, le blocage d’adresses IP et les protections de DDoS réseau.
A9: Supplemental Guidance | B9: A variety of technologies exist to limit, or in some cases, eliminate the effects of denial of service attacks. For example, boundary protection devices can filter certain types of packets to protect information system components on internal organizational networks from being directly affected by denial of service attacks. Employing increased capacity and bandwidth combined with service redundancy may also reduce the susceptibility to denial of service attacks. Related controls: SC-6, SC-7 | D9: Directives supplémentaires | E9: Diverses technologies existent pour limiter ou, dans certains cas, éliminer les effets des attaques par déni de service. Par exemple, les dispositifs de protection des frontières peuvent filtrer certains types de paquets afin de protéger les composants du système d’information des réseaux organisationnels internes contre les répercussions directes des attaques par déni de service. L’utilisation d’une capacité et d’une bande passante accrues combinée à la redondance des services peut également réduire la susceptibilité aux attaques par déni de service. Contrôles connexes : SC-6, SC-7
A10: Test Case | D10: Cas de test
A11: Test | B11: TEST-SC-5 | D11: Test | E11: TEST-SC-5
A12: Requirement ID | B12: SC-5 | D12: ID Exigence | E12: SC-5
A13: Component | D13: Composant
A14: Requirement | D14: Exigence
A15: Contextual Design Description | D15: Description contextuelle du design
A16: Evidence Provided | D16: Preuve fournie
A17: Preparer Sign Off (Initials, Date) | D17: Signataire préparateur (Initiales, Date)
A18: Owner Sign Off (Initials, Date) | D18: Signataire propriétaire (Initiales, Date)
A19: Assessor Sign Off (Initials, Date) | D19: Signataire évaluateur (Initiales, Date)
A20: Status | B20: Not Started | D20: Statut | E20: Non commencé
A21: Comments | D21: Commentaires

Sheet SC-7
A1: Control SC-7 — Evidence Tracking | D1: Contrôle SC-7 — Suivi des preuves
A2: Control Information | D2: Informations du contrôle
A3: Control Identifier | B3: SC-7 | D3: Identifiant du contrôle | E3: SC-7
A4: Family | B4: Boundary Protection | D4: Famille | E4: Protection des frontières
A5: Profile | B5: CCCS Medium / PBMM Moderate | D5: Profil | E5: CCCS Moyen / PBMM Modéré
A6: Primary Evidence Tool | D6: Outil de preuve principal
A7: Contributing Tools | D7: Outils contributeurs
A8: Control Description | B8: (A) The information system monitors and controls communications at the external boundary of the system and at key internal boundaries within the system. (B) The information system implements sub-networks for publicly accessible system components that are physically or logically separated from internal organizational networks. (C) The information system connects to external networks or information systems only through managed interfaces consisting of boundary protection devices arranged in accordance with an organizational security architecture. | D8: Description du contrôle | E8: (A) Le système d’information surveille et contrôle les communications à la frontière externe du système et aux frontières internes clés du système. (B) Le système d’information met en œuvre des sous-réseaux pour des composants du système accessibles au public qui sont physiquement ou logiquement séparés des réseaux organisationnels internes. (C) Le système d’information ne se connecte à des réseaux ou à des systèmes d’information externes que par des interfaces gérées comprenant des dispositifs de protection des frontières organisés conformément à une architecture de sécurité organisationnelle.
A9: Supplemental Guidance | B9: Managed interfaces include, for example, gateways, routers, firewalls, guards, network-based malicious code analysis and virtualization systems, or encrypted tunnels implemented within a security architecture (e.g., routers protecting firewalls or application gateways residing on protected sub-networks). Sub-networks that are physically or logically separated from internal networks are referred to as demilitarized zones or DMZs. Restricting or prohibiting interfaces within organizational information systems includes, for example, restricting external web traffic to designated web servers within managed interfaces and prohibiting external traffic that appears to be spoofing internal addresses. Organizations consider the shared nature of commercial telecommunications services in the implementation of security controls associated with the use of such services. Commercial telecommunications services are commonly based on network components and consolidated management systems shared by all attached commercial customers, and may also include third party-provided access lines and other service elements. Such transmission services may represent sources of increased risk despite contract security provisions. Related controls: AC-4, AC-17, CA-3, CM-7, CP-8, IR-4, RA-3, SC-5, SC-13 | D9: Directives supplémentaires | E9: Les interfaces gérées comprennent, par exemple, les passerelles, les routeurs, les pare-feu, les gardiens, les systèmes d’analyse et de virtualisation de codes malveillants basés sur le réseau, ou les tunnels chiffrés mis en œuvre dans une architecture de sécurité (p. ex., les routeurs protégeant les pare-feu ou les passerelles d’application résidant sur des sous-réseaux protégés). Les sous-réseaux qui sont physiquement ou logiquement séparés des réseaux internes sont appelés « zones démilitarisées » ou « ZD ». La restriction ou l’interdiction des interfaces dans les systèmes d’information de l’organisation comprend, par exemple, la restriction du trafic Web externe aux serveurs Web désignés dans les interfaces gérées et l’interdiction du trafic externe qui semble usurper les adresses internes. Les organisations tiennent compte de la nature commune des services de télécommunications commerciaux dans la mise en œuvre des contrôles de sécurité associés à l’utilisation de tels services. Les services de télécommunications commerciaux sont généralement fondés sur des composants de réseau et des systèmes de gestion consolidés partagés par tous les clients commerciaux attenants, et peuvent également comprendre des lignes d’accès fournies par des tiers et d’autres éléments de service. Ces services de transmission peuvent représenter des sources de risque accru malgré les dispositions relatives à la sécurité dans les contrats. Contrôles connexes : AC-4, AC-17, CA-3, CM-7, CP-8, IR-4, RA-3, SC-5, SC-13
A10: Test Case | D10: Cas de test
A11: Test | B11: TEST-SC-7 | D11: Test | E11: TEST-SC-7
A12: Requirement ID | B12: SC-7 | D12: ID Exigence | E12: SC-7
A13: Component | D13: Composant
A14: Requirement | D14: Exigence
A15: Contextual Design Description | D15: Description contextuelle du design
A16: Evidence Provided | D16: Preuve fournie
A17: Preparer Sign Off (Initials, Date) | D17: Signataire préparateur (Initiales, Date)
A18: Owner Sign Off (Initials, Date) | D18: Signataire propriétaire (Initiales, Date)
A19: Assessor Sign Off (Initials, Date) | D19: Signataire évaluateur (Initiales, Date)
A20: Status | B20: Not Started | D20: Statut | E20: Non commencé
A21: Comments | D21: Commentaires

Sheet SC-7-3
A1: Control SC-7(3) — Evidence Tracking | D1: Contrôle SC-7(3) — Suivi des preuves
A2: Control Information | D2: Informations du contrôle
A3: Control Identifier | B3: SC-7(3) | D3: Identifiant du contrôle | E3: SC-7(3)
A4: Family | B4: Boundary Protection | D4: Famille | E4: Protection des frontières
A5: Profile | B5: CCCS Medium / PBMM Moderate | D5: Profil | E5: CCCS Moyen / PBMM Modéré
A6: Primary Evidence Tool | D6: Outil de preuve principal
A7: Contributing Tools | D7: Outils contributeurs
A8: Control Description | B8: BOUNDARY PROTECTION | ACCESS POINTS The organization limits the number of external network connections to the information system. | D8: Description du contrôle | E8: PROTECTION DES FRONTIÈRES | POINTS D’ACCÈS L’organisation limite le nombre de connexions réseau externes au système d’information.
A9: Supplemental Guidance | B9: Limiting the number of external network connections facilitates more comprehensive monitoring of inbound and outbound communications traffic. | D9: Directives supplémentaires | E9: La limitation du nombre de connexions réseau externes facilite une surveillance plus complète du trafic des communications entrantes et sortantes.
A10: Test Case | D10: Cas de test
A11: Test | B11: TEST-SC-7(3) | D11: Test | E11: TEST-SC-7(3)
A12: Requirement ID | B12: SC-7(3) | D12: ID Exigence | E12: SC-7(3)
A13: Component | D13: Composant
A14: Requirement | D14: Exigence
A15: Contextual Design Description | D15: Description contextuelle du design
A16: Evidence Provided | D16: Preuve fournie
A17: Preparer Sign Off (Initials, Date) | D17: Signataire préparateur (Initiales, Date)
A18: Owner Sign Off (Initials, Date) | D18: Signataire propriétaire (Initiales, Date)
A19: Assessor Sign Off (Initials, Date) | D19: Signataire évaluateur (Initiales, Date)
A20: Status | B20: Not Started | D20: Statut | E20: Non commencé
A21: Comments | D21: Commentaires

Sheet SC-7-4
A1: Control SC-7(4) — Evidence Tracking | D1: Contrôle SC-7(4) — Suivi des preuves
A2: Control Information | D2: Informations du contrôle
A3: Control Identifier | B3: SC-7(4) | D3: Identifiant du contrôle | E3: SC-7(4)
A4: Family | B4: Boundary Protection | D4: Famille | E4: Protection des frontières
A5: Profile | B5: CCCS Medium / PBMM Moderate | D5: Profil | E5: CCCS Moyen / PBMM Modéré
A6: Primary Evidence Tool | D6: Outil de preuve principal
A7: Contributing Tools | D7: Outils contributeurs
A8: Control Description | B8: BOUNDARY PROTECTION | EXTERNAL TELECOMMUNICATIONS SERVICES (a) The organization implements a managed interface for each external telecommunication service; (b) The organization establishes a traffic flow policy for each managed interface; (c) The organization protects the confidentiality and integrity of the information being transmitted across each interface; (d) The organization documents each exception to the traffic flow policy with a supporting mission/business need and duration of that need; and (e) The organization reviews exceptions to the traffic flow policy at least annually and removes exceptions that are no longer supported by an explicit mission/business need. | D8: Description du contrôle | E8: PROTECTION DES FRONTIÈRES | SERVICES DE TÉLÉCOMMUNICATIONS EXTERNES (a) L’organisation met en œuvre une interface gérée pour chaque service de télécommunications externe; (b) L’organisation établit une politique relative à l’écoulement du trafic pour chaque interface gérée; (c) L’organisation protège la confidentialité et l’intégrité de l’information transmise sur chaque interface; (d) L’organisation documente chaque exception à la politique relative à l’écoulement du trafic en indiquant le besoin opérationnel et de mission à l’appui et la durée de ce besoin; (e) L’organisation revoit les exceptions à la politique relative à l’écoulement du trafic au moins une fois l’an, et retire les exceptions qui ne sont plus appuyées par un besoin opérationnel/de mission explicite.
A9: Supplemental Guidance | B9: Related control: SC-8. | D9: Directives supplémentaires | E9: Contrôle connexe : SC-8.
A10: Test Case | D10: Cas de test
A11: Test | B11: TEST-SC-7(4) | D11: Test | E11: TEST-SC-7(4)
A12: Requirement ID | B12: SC-7(4) | D12: ID Exigence | E12: SC-7(4)
A13: Component | D13: Composant
A14: Requirement | D14: Exigence
A15: Contextual Design Description | D15: Description contextuelle du design
A16: Evidence Provided | D16: Preuve fournie
A17: Preparer Sign Off (Initials, Date) | D17: Signataire préparateur (Initiales, Date)
A18: Owner Sign Off (Initials, Date) | D18: Signataire propriétaire (Initiales, Date)
A19: Assessor Sign Off (Initials, Date) | D19: Signataire évaluateur (Initiales, Date)
A20: Status | B20: Not Started | D20: Statut | E20: Non commencé
A21: Comments | D21: Commentaires

Sheet SC-7-5
A1: Control SC-7(5) — Evidence Tracking | D1: Contrôle SC-7(5) — Suivi des preuves
A2: Control Information | D2: Informations du contrôle
A3: Control Identifier | B3: SC-7(5) | D3: Identifiant du contrôle | E3: SC-7(5)
A4: Family | B4: Boundary Protection | D4: Famille | E4: Protection des frontières
A5: Profile | B5: CCCS Medium / PBMM Moderate | D5: Profil | E5: CCCS Moyen / PBMM Modéré
A6: Primary Evidence Tool | D6: Outil de preuve principal
A7: Contributing Tools | D7: Outils contributeurs
A8: Control Description | B8: BOUNDARY PROTECTION | DENY BY DEFAULT / ALLOW BY EXCEPTION The information system at managed interfaces denies network communications traffic by default and allows network communications traffic by exception (i.e., deny all, permit by exception). | D8: Description du contrôle | E8: PROTECTION DES FRONTIÈRES | REFUSER PAR DÉFAUT/PERMETTRE PAR EXCEPTION Le système d’information aux interfaces gérées refuse par défaut les communications réseau et permet par exception les communications réseau (c.-à-d. refuser tout, permettre par exception).
A9: Supplemental Guidance | B9: This control enhancement applies to both inbound and outbound network communications traffic. A deny-all, permit-by-exception network communications traffic policy ensures that only those connections which are essential and approved are allowed. | D9: Directives supplémentaires | E9: Cette amélioration de contrôle s’applique aux communications réseau entrantes et sortantes. Une politique « refuser tout, permettre par exception » relativement aux communications réseau garantit que seules les connexions qui sont essentielles et approuvées sont autorisées.
A10: Test Case | D10: Cas de test
A11: Test | B11: TEST-SC-7(5) | D11: Test | E11: TEST-SC-7(5)
A12: Requirement ID | B12: SC-7(5) | D12: ID Exigence | E12: SC-7(5)
A13: Component | D13: Composant
A14: Requirement | D14: Exigence
A15: Contextual Design Description | D15: Description contextuelle du design
A16: Evidence Provided | D16: Preuve fournie
A17: Preparer Sign Off (Initials, Date) | D17: Signataire préparateur (Initiales, Date)
A18: Owner Sign Off (Initials, Date) | D18: Signataire propriétaire (Initiales, Date)
A19: Assessor Sign Off (Initials, Date) | D19: Signataire évaluateur (Initiales, Date)
A20: Status | B20: Not Started | D20: Statut | E20: Non commencé
A21: Comments | D21: Commentaires

Sheet SC-7-8
A1: Control SC-7(8) — Evidence Tracking | D1: Contrôle SC-7(8) — Suivi des preuves
A2: Control Information | D2: Informations du contrôle
A3: Control Identifier | B3: SC-7(8) | D3: Identifiant du contrôle | E3: SC-7(8)
A4: Family | B4: Boundary Protection | D4: Famille | E4: Protection des frontières
A5: Profile | B5: CCCS Medium / PBMM Moderate | D5: Profil | E5: CCCS Moyen / PBMM Modéré
A6: Primary Evidence Tool | D6: Outil de preuve principal
A7: Contributing Tools | D7: Outils contributeurs
A8: Control Description | B8: BOUNDARY PROTECTION | ROUTE TRAFFIC TO AUTHENTICATED PROXY SERVERS The information system routes organization-defined internal communications traffic to all untrusted networks ouside the control of the organization through authenticated proxy servers at managed interfaces. | D8: Description du contrôle | E8: PROTECTION DES FRONTIÈRES | ACHEMINEMENT DU TRAFIC VERS LES SERVEURS MANDATAIRES AUTHENTIFIÉS Le système d’information achemine le trafic de communications internes défini par l’organisation vers tous les réseaux non fiables hors du contrôle de l’organisation par le biais de serveurs mandataires authentifiés aux interfaces gérées.
A9: Supplemental Guidance | B9: External networks are networks outside of organizational control. A proxy server is a server (i.e., information system or application) that acts as an intermediary for clients requesting information system resources (e.g., files, connections, web pages, or services) from other organizational servers. Client requests established through an initial connection to the proxy server are evaluated to manage complexity and to provide additional protection by limiting direct connectivity. Web content filtering devices are one of the most common proxy servers providing access to the Internet. Proxy servers support logging individual Transmission Control Protocol (TCP) sessions and blocking specific Uniform Resource Locators (URLs), domain names, and Internet Protocol (IP) addresses. Web proxies can be configured with organization-defined lists of authorized and unauthorized websites. Related controls: AC-3, AU-2. | D9: Directives supplémentaires | E9: Les réseaux externes sont des réseaux qui échappent au contrôle de l’organisation. Un serveur mandataire est un serveur (c.-à-d. un système d’information ou une application) qui sert d’intermédiaire pour les clients qui demandent des ressources du système d’information (p. ex., fichiers, connexions, pages Web ou services) à d’autres serveurs de l’organisation. Les demandes des clients établies au moyen d’une connexion initiale au serveur mandataire sont évaluées afin de gérer la complexité et de fournir une protection supplémentaire en limitant la connectivité directe. Les dispositifs de filtrage du contenu Web sont parmi les serveurs mandataires les plus courants donnant accès à Internet. Les serveurs mandataires permettent l’ouverture de sessions individuelles de protocole de contrôle de transmission (TCP) et bloquent des localisateurs de ressources uniformes (URL), des noms de domaine et des adresses IP particuliers. Les mandataires Web peuvent être configurés avec des listes de sites Web autorisés et non autorisés définies par l’organisation. Contrôles connexes : AC-3, AU-2.
A10: Test Case | D10: Cas de test
A11: Test | B11: TEST-SC-7(8) | D11: Test | E11: TEST-SC-7(8)
A12: Requirement ID | B12: SC-7(8) | D12: ID Exigence | E12: SC-7(8)
A13: Component | D13: Composant
A14: Requirement | D14: Exigence
A15: Contextual Design Description | D15: Description contextuelle du design
A16: Evidence Provided | D16: Preuve fournie
A17: Preparer Sign Off (Initials, Date) | D17: Signataire préparateur (Initiales, Date)
A18: Owner Sign Off (Initials, Date) | D18: Signataire propriétaire (Initiales, Date)
A19: Assessor Sign Off (Initials, Date) | D19: Signataire évaluateur (Initiales, Date)
A20: Status | B20: Not Started | D20: Statut | E20: Non commencé
A21: Comments | D21: Commentaires

Sheet SC-7-13
A1: Control SC-7(13) — Evidence Tracking | D1: Contrôle SC-7(13) — Suivi des preuves
A2: Control Information | D2: Informations du contrôle
A3: Control Identifier | B3: SC-7(13) | D3: Identifiant du contrôle | E3: SC-7(13)
A4: Family | B4: Boundary Protection | D4: Famille | E4: Protection des frontières
A5: Profile | B5: CCCS Medium / PBMM Moderate | D5: Profil | E5: CCCS Moyen / PBMM Modéré
A6: Primary Evidence Tool | D6: Outil de preuve principal
A7: Contributing Tools | D7: Outils contributeurs
A8: Control Description | B8: BOUNDARY PROTECTION | ISOLATION OF SECURITY TOOLS / MECHANISMS / SUPPORT COMPONENTS The organization isolates organization-defined information security tools, mechanisms, and support components from other internal information system components by implementing physically separate sub-networks with managed interfaces to other components of the system. | D8: Description du contrôle | E8: PROTECTION DES FRONTIÈRES | ISOLATION DES OUTILS/MÉCANISMES/COMPOSANTS DE SOUTIEN DE LA SÉCURITÉ L’organisation isole les outils, les mécanismes et les composants de soutien de la sécurité des autres composants du système d’information interne en mettant en œuvre des sous-réseaux physiquement séparés avec des interfaces gérées à d’autres composants du système.
A9: Supplemental Guidance | B9: Separate sub-networks with managed interfaces are useful, for example, in isolating computer network defences from critical operational processing networks to prevent adversaries from discovering the analysis and forensics techniques of organizations. The service provider defines key information security tools, mechanisms, and support components associated with system and security administration and isolates those tools, mechanisms, and support components from other internal information system components via physically or logically separate subnets. Related controls: SA-8, SC-2, SC-3. | D9: Directives supplémentaires | E9: Les sous-réseaux séparés dotés d’interfaces gérées sont utiles, par exemple, pour isoler les moyens de défense des réseaux informatiques des réseaux opérationnels critiques afin d’empêcher les adversaires de découvrir les techniques d’analyse et de criminalistique des organisations. Le fournisseur de services définit les principaux outils, mécanismes et composants de soutien de la sécurité de l’information associés à l’administration du système et de la sécurité, et isole ces outils, mécanismes et composants de soutien des autres composants internes du système d’information au moyen de sous-réseaux physiquement ou logiquement séparés. Contrôles connexes : SA-8, SC-2, SC-3.
A10: Test Case | D10: Cas de test
A11: Test | B11: TEST-SC-7(13) | D11: Test | E11: TEST-SC-7(13)
A12: Requirement ID | B12: SC-7(13) | D12: ID Exigence | E12: SC-7(13)
A13: Component | D13: Composant
A14: Requirement | D14: Exigence
A15: Contextual Design Description | D15: Description contextuelle du design
A16: Evidence Provided | D16: Preuve fournie
A17: Preparer Sign Off (Initials, Date) | D17: Signataire préparateur (Initiales, Date)
A18: Owner Sign Off (Initials, Date) | D18: Signataire propriétaire (Initiales, Date)
A19: Assessor Sign Off (Initials, Date) | D19: Signataire évaluateur (Initiales, Date)
A20: Status | B20: Not Started | D20: Statut | E20: Non commencé
A21: Comments | D21: Commentaires

Sheet SC-7-18
A1: Control SC-7(18) — Evidence Tracking | D1: Contrôle SC-7(18) — Suivi des preuves
A2: Control Information | D2: Informations du contrôle
A3: Control Identifier | B3: SC-7(18) | D3: Identifiant du contrôle | E3: SC-7(18)
A4: Family | B4: Boundary Protection | D4: Famille | E4: Protection des frontières
A5: Profile | B5: CCCS Medium / PBMM Moderate | D5: Profil | E5: CCCS Moyen / PBMM Modéré
A6: Primary Evidence Tool | D6: Outil de preuve principal
A7: Contributing Tools | D7: Outils contributeurs
A8: Control Description | B8: BOUNDARY PROTECTION | FAIL SECURE The information system fails securely in the event of an operational failure of a boundary protection device. | D8: Description du contrôle | E8: PROTECTION DES FRONTIÈRES | SÉCURITÉ INTÉGRÉE Le système d’information tombe en panne de façon sécurisée en cas de défaillance opérationnelle d’un dispositif de protection des frontières.
A9: Supplemental Guidance | B9: Fail secure is a condition achieved by employing information system mechanisms to ensure that in the event of operational failures of boundary protection devices at managed interfaces (e.g., routers, firewalls, guards, and application gateways residing on protected sub-networks commonly referred to as demilitarized zones), information systems do not enter into insecure states where intended security properties no longer hold. Failures of boundary protection devices cannot lead to, or cause information external to the devices to enter the devices, nor can failures permit unauthorized information releases. Related controls: CP-2, SC-24. | D9: Directives supplémentaires | E9: La sécurité intégrée est une condition obtenue en utilisant des mécanismes du système d’information pour s’assurer qu’en cas de défaillance opérationnelle des dispositifs de protection des frontières aux interfaces gérées (p. ex., routeurs, pare-feu, gardiens et passerelles d’application résidant sur des sous-réseaux protégés communément appelés zones démilitarisées), les systèmes d’information n’entrent pas dans des états non sécurisés où les propriétés de sécurité prévues ne tiennent plus. Les défaillances des dispositifs de protection des frontières ne doivent pas entraîner ou faire entrer de l’information externe dans les dispositifs, et les défaillances ne doivent pas non plus permettre la diffusion non autorisée d’information. Contrôles connexes : CP-2, SC-24.
A10: Test Case | D10: Cas de test
A11: Test | B11: TEST-SC-7(18) | D11: Test | E11: TEST-SC-7(18)
A12: Requirement ID | B12: SC-7(18) | D12: ID Exigence | E12: SC-7(18)
A13: Component | D13: Composant
A14: Requirement | D14: Exigence
A15: Contextual Design Description | D15: Description contextuelle du design
A16: Evidence Provided | D16: Preuve fournie
A17: Preparer Sign Off (Initials, Date) | D17: Signataire préparateur (Initiales, Date)
A18: Owner Sign Off (Initials, Date) | D18: Signataire propriétaire (Initiales, Date)
A19: Assessor Sign Off (Initials, Date) | D19: Signataire évaluateur (Initiales, Date)
A20: Status | B20: Not Started | D20: Statut | E20: Non commencé
A21: Comments | D21: Commentaires

Sheet SC-8
A1: Control SC-8 — Evidence Tracking | D1: Contrôle SC-8 — Suivi des preuves
A2: Control Information | D2: Informations du contrôle
A3: Control Identifier | B3: SC-8 | D3: Identifiant du contrôle | E3: SC-8
A4: Family | B4: Transmission Confidentiality and Integrity | D4: Famille | E4: Confidentialité et intégrité des transmissions
A5: Profile | B5: CCCS Medium / PBMM Moderate | D5: Profil | E5: CCCS Moyen / PBMM Modéré
A6: Primary Evidence Tool | D6: Outil de preuve principal
A7: Contributing Tools | D7: Outils contributeurs
A8: Control Description | B8: (A) The information system protects the confidentiality and integrity of transmitted information. | D8: Description du contrôle | E8: (A) Le système d’information protège la confidentialité et l’intégrité de l’information transmise.
A9: Supplemental Guidance | B9: This control applies to both internal and external networks and all types of information system components from which information can be transmitted (e.g., servers, mobile devices, notebook computers, printers, copiers, scanners, facsimile machines). Communication paths outside the physical protection of a controlled boundary are exposed to the possibility of interception and modification. Protecting the confidentiality and/or integrity of organizational information can be accomplished by physical means (e.g., by employing protected distribution systems) or by logical means (e.g., employing encryption techniques). Organizations relying on commercial providers offering transmission services as commodity services rather than as fully dedicated services (i.e., services which can be highly specialized to individual customer needs), may find it difficult to obtain the necessary assurances regarding the implementation of needed security controls for transmission confidentiality/integrity. In such situations, organizations determine what types of confidentiality/integrity services are available in standard, commercial telecommunication service packages. If it is infeasible or impractical to obtain the necessary security controls and assurances of control effectiveness through appropriate contracting vehicles, organizations implement appropriate compensating security controls or explicitly accept the additional risk. Related controls: AC-17, PE-4 | D9: Directives supplémentaires | E9: Ce contrôle s’applique aux réseaux internes et externes et à tous les types de composants du système d’information à partir desquels de l’information peut être transmise (p. ex., serveurs, appareils mobiles, ordinateurs portatifs, imprimantes, photocopieurs, numériseurs, télécopieurs). Les voies de communication à l’extérieur de la protection physique d’une frontière contrôlée sont exposées à des risques d’interception et de modification. La protection de la confidentialité ou de l’intégrité de l’information organisationnelle peut se faire par des moyens physiques (p. ex., en utilisant des systèmes de distribution protégés) ou logiques (p. ex., en utilisant des techniques de chiffrement). Les organisations qui comptent sur des fournisseurs commerciaux offrant des services de transmission à titre de services de base plutôt que de services entièrement dédiés (c.-à-d. des services qui peuvent être hautement spécialisés pour répondre aux besoins de clients individuels), peuvent avoir de la difficulté à obtenir les assurances nécessaires concernant la mise en œuvre des contrôles de sécurité nécessaires pour la confidentialité et l’intégrité des transmissions. Dans de telles situations, les organisations déterminent les types de services de confidentialité et d’intégrité disponibles dans les forfaits de services de télécommunications commerciaux standard. S’il n’est pas pratique ou s’il est impossible d’obtenir les contrôles de sécurité nécessaires et l’assurance de l’efficacité des contrôles au moyen des mécanismes de passation de marchés appropriés, les organisations mettent en œuvre des contrôles de sécurité compensatoires appropriés ou acceptent explicitement le risque supplémentaire. Contrôles connexes : AC-17, PE-4
A10: Test Case | D10: Cas de test
A11: Test | B11: TEST-SC-8 | D11: Test | E11: TEST-SC-8
A12: Requirement ID | B12: SC-8 | D12: ID Exigence | E12: SC-8
A13: Component | D13: Composant
A14: Requirement | D14: Exigence
A15: Contextual Design Description | D15: Description contextuelle du design
A16: Evidence Provided | D16: Preuve fournie
A17: Preparer Sign Off (Initials, Date) | D17: Signataire préparateur (Initiales, Date)
A18: Owner Sign Off (Initials, Date) | D18: Signataire propriétaire (Initiales, Date)
A19: Assessor Sign Off (Initials, Date) | D19: Signataire évaluateur (Initiales, Date)
A20: Status | B20: Not Started | D20: Statut | E20: Non commencé
A21: Comments | D21: Commentaires

Sheet SC-8-1
A1: Control SC-8(1) — Evidence Tracking | D1: Contrôle SC-8(1) — Suivi des preuves
A2: Control Information | D2: Informations du contrôle
A3: Control Identifier | B3: SC-8(1) | D3: Identifiant du contrôle | E3: SC-8(1)
A4: Family | B4: Transmission Confidentiality and Integrity | D4: Famille | E4: Confidentialité et intégrité des transmissions
A5: Profile | B5: CCCS Medium / PBMM Moderate | D5: Profil | E5: CCCS Moyen / PBMM Modéré
A6: Primary Evidence Tool | D6: Outil de preuve principal
A7: Contributing Tools | D7: Outils contributeurs
A8: Control Description | B8: TRANSMISSION CONFIDENTIALITY AND INTEGRITY | CRYPTOGRAPHIC OR ALTERNATE PHYSICAL PROTECTION The information system implements cryptographic mechanisms to prevent unauthorized disclosure of information and detect changes to information during transmission unless otherwise protected by physical security safeguards applied in applied in accordance with, or uses an adequate risk-based approach aligned with the practices specified in TBS and RCMP physical security standards and any related provisions of the Industrial Security Program. The cryptography must be compliant with the requirements of control SC-13. | D8: Description du contrôle | E8: CONFIDENTIALITÉ ET INTÉGRITÉ DES TRANSMISSIONS | PROTECTION CRYPTOGRAPHIQUE OU AUTRE PROTECTION PHYSIQUE Le système d’information déploie des mécanismes cryptographiques pour prévenir la divulgation non autorisée d’information et détecter les modifications de l’information durant la transmission, à moins d’être autrement protégé par des mesures de sécurité physiques appliquées selon une approche adéquate en fonction du risque qui s’harmonise avec les pratiques spécifiées dans les normes de sécurité physique du SCT et de la GRC et les dispositions connexes du Programme de sécurité industrielle. La cryptographie doit être conforme aux exigences du contrôle SC-13.
A9: Supplemental Guidance | B9: Encrypting information for transmission protects information from unauthorized disclosure and modification. Cryptographic mechanisms implemented to protect information integrity include, for example, cryptographic hash functions which have common application in digital signatures, checksums, and message authentication codes. Alternative physical security safeguards include, for example, protected distribution systems. Related control: SC-13. | D9: Directives supplémentaires | E9: Le chiffrement de l’information pour la transmission protège l’information contre la divulgation et la modification non autorisées. Les mécanismes cryptographiques mis en œuvre pour protéger l’intégrité de l’information comprennent, par exemple, les fonctions de hachage cryptographique qui ont une application commune dans les signatures numériques, les sommes de contrôle et les codes d’authentification des messages. Les autres mesures de sécurité physiques comprennent, par exemple, les réseaux de distribution protégés. Contrôle connexe : SC-13.
A10: Test Case | D10: Cas de test
A11: Test | B11: TEST-SC-8(1) | D11: Test | E11: TEST-SC-8(1)
A12: Requirement ID | B12: SC-8(1) | D12: ID Exigence | E12: SC-8(1)
A13: Component | D13: Composant
A14: Requirement | D14: Exigence
A15: Contextual Design Description | D15: Description contextuelle du design
A16: Evidence Provided | D16: Preuve fournie
A17: Preparer Sign Off (Initials, Date) | D17: Signataire préparateur (Initiales, Date)
A18: Owner Sign Off (Initials, Date) | D18: Signataire propriétaire (Initiales, Date)
A19: Assessor Sign Off (Initials, Date) | D19: Signataire évaluateur (Initiales, Date)
A20: Status | B20: Not Started | D20: Statut | E20: Non commencé
A21: Comments | D21: Commentaires

Sheet SC-10
A1: Control SC-10 — Evidence Tracking | D1: Contrôle SC-10 — Suivi des preuves
A2: Control Information | D2: Informations du contrôle
A3: Control Identifier | B3: SC-10 | D3: Identifiant du contrôle | E3: SC-10
A4: Family | B4: Network Disconnect | D4: Famille | E4: Débranchement du réseau
A5: Profile | B5: CCCS Medium / PBMM Moderate | D5: Profil | E5: CCCS Moyen / PBMM Modéré
A6: Primary Evidence Tool | D6: Outil de preuve principal
A7: Contributing Tools | D7: Outils contributeurs
A8: Control Description | B8: (A) The information system terminates the network connection associated with a communications session at the end of the session or after no longer than 30 minutes for RAS-based sessions or no longer than 60 minutes for non-interactive user sessions of inactivity. | D8: Description du contrôle | E8: (A) Le système d’information met fin à la connexion réseau associée à une session de communication à la fin de la séance ou après un maximum de 30 minutes pour les sessions basées sur le service d’accès à distance (SAD) ou de 60 minutes d’inactivité pour les sessions d’utilisateur non interactives.
A9: Supplemental Guidance | B9: This control applies to both internal and external networks. Terminating network connections associated with communications sessions include, for example, de-allocating associated TCP/IP address/port pairs at the operating system level, or de-allocating networking assignments at the application level if multiple application sessions are using a single, operating system-level network connection. Time periods of inactivity may be established by organizations and include, for example, time periods by type of network access or for specific network accesses | D9: Directives supplémentaires | E9: Ce contrôle s’applique aux réseaux internes et externes. La fin des connexions réseau associées aux sessions de communication comprend, par exemple, la désattribution des paires d’adresses/ports TCP/IP associées au niveau du système d’exploitation, ou la désattribution des tâches de réseautique au niveau de l’application si plusieurs sessions d’application utilisent une seule connexion réseau au niveau du système d’exploitation. Des périodes d’inactivité peuvent être établies par les organisations et comprendre, par exemple, des périodes par type d’accès au réseau ou pour des accès réseau particuliers.
A10: Test Case | D10: Cas de test
A11: Test | B11: TEST-SC-10 | D11: Test | E11: TEST-SC-10
A12: Requirement ID | B12: SC-10 | D12: ID Exigence | E12: SC-10
A13: Component | D13: Composant
A14: Requirement | D14: Exigence
A15: Contextual Design Description | D15: Description contextuelle du design
A16: Evidence Provided | D16: Preuve fournie
A17: Preparer Sign Off (Initials, Date) | D17: Signataire préparateur (Initiales, Date)
A18: Owner Sign Off (Initials, Date) | D18: Signataire propriétaire (Initiales, Date)
A19: Assessor Sign Off (Initials, Date) | D19: Signataire évaluateur (Initiales, Date)
A20: Status | B20: Not Started | D20: Statut | E20: Non commencé
A21: Comments | D21: Commentaires

Sheet SC-12-3
A1: Control SC-12(3) — Evidence Tracking | D1: Contrôle SC-12(3) — Suivi des preuves
A2: Control Information | D2: Informations du contrôle
A3: Control Identifier | B3: SC-12(3) | D3: Identifiant du contrôle | E3: SC-12(3)
A4: Family | B4: Cryptographic Key Establishment and Management | D4: Famille | E4: Établissement et gestion des clés cryptographiques
A5: Profile | B5: CCCS Medium / PBMM Moderate | D5: Profil | E5: CCCS Moyen / PBMM Modéré
A6: Primary Evidence Tool | D6: Outil de preuve principal
A7: Contributing Tools | D7: Outils contributeurs
A8: Control Description | B8: CRYPTOGRAPHIC KEY ESTABLISHMENT AND MANAGEMENT | ASYMMETRIC KEYS The organization produces, controls, and distributes asymmetric cryptographic keys using CSE-approved key management technology and processes; approved PKI medium assurance certificates or prepositioned keying material; approved medium assurance or high assurance certificates and hardware security tokens that protect the user’s private key. | D8: Description du contrôle | E8: ÉTABLISSEMENT ET GESTION DES CLÉS CRYPTOGRAPHIQUES | CLÉS ASYMÉTRIQUES L’organisation produit, contrôle et distribue des clés cryptographiques asymétriques à l’aide de la technologie et des processus de gestion des clés approuvés par le CST; des certificats d’assurance moyenne de l’ICP approuvés ou du matériel de chargement de clés prépositionné; des certificats d’assurance moyenne ou d’assurance élevée approuvés et des jetons de sécurité matérielle qui protègent la clé privée de l’utilisateur.
A9: Supplemental Guidance | D9: Directives supplémentaires
A10: Test Case | D10: Cas de test
A11: Test | B11: TEST-SC-12(3) | D11: Test | E11: TEST-SC-12(3)
A12: Requirement ID | B12: SC-12(3) | D12: ID Exigence | E12: SC-12(3)
A13: Component | D13: Composant
A14: Requirement | D14: Exigence
A15: Contextual Design Description | D15: Description contextuelle du design
A16: Evidence Provided | D16: Preuve fournie
A17: Preparer Sign Off (Initials, Date) | D17: Signataire préparateur (Initiales, Date)
A18: Owner Sign Off (Initials, Date) | D18: Signataire propriétaire (Initiales, Date)
A19: Assessor Sign Off (Initials, Date) | D19: Signataire évaluateur (Initiales, Date)
A20: Status | B20: Not Started | D20: Statut | E20: Non commencé
A21: Comments | D21: Commentaires

Sheet SC-13
A1: Control SC-13 — Evidence Tracking | D1: Contrôle SC-13 — Suivi des preuves
A2: Control Information | D2: Informations du contrôle
A3: Control Identifier | B3: SC-13 | D3: Identifiant du contrôle | E3: SC-13
A4: Family | B4: Cryptographic Protection | D4: Famille | E4: Protection cryptographique
A5: Profile | B5: CCCS Medium / PBMM Moderate | D5: Profil | E5: CCCS Moyen / PBMM Modéré
A6: Primary Evidence Tool | D6: Outil de preuve principal
A7: Contributing Tools | D7: Outils contributeurs
A8: Control Description | B8: (A) The information system implements CSE approved cryptography in accordance with applicable organizational policies, directives and standards. | D8: Description du contrôle | E8: (A) Le système d’information met en œuvre la cryptographie approuvée par le CST conformément aux politiques, aux directives et aux normes organisationnelles applicables.
A9: Supplemental Guidance | B9: Cryptography can be employed to support a variety of security solutions including, for example, the protection of sensitive information, the provision of digital signatures, and the enforcement of information separation when authorized individuals have the necessary clearances for such information but lack the necessary formal access approvals. Cryptography can also be used to support random number generation and hash generation. Generally applicable cryptographic standards include FIPS-validated cryptography. This control does not impose any requirements on organizations to use cryptography. However, if cryptography is required based on the selection of other security controls or policies, organizations document each type of cryptographic use and the type of cryptography required (e.g., protection of classified information: FIPS-validated cryptography). Related controls: AC-2, AC-3, AC-7, AC-17, AC-18, AU-9, AU-10, CM-11, CP-9, IA-3, IA-7, MA-4, MP-2, MP-4, MP-5, SA-4, SC-8, SC-12, SC-28, SI-7 | D9: Directives supplémentaires | E9: La cryptographie peut être utilisée pour la prise en charge d’une variété de solutions de sécurité, y compris, par exemple, la protection des renseignements de nature sensible, la fourniture de signatures numériques, et l’application de la séparation des renseignements lorsque les personnes autorisées ont les autorisations de sécurité nécessaires pour ces renseignements, mais qu’elles n’ont pas les autorisations d’accès officielles nécessaires. La cryptographie peut également être utilisée pour permettre la génération de nombres aléatoires et la génération de hachages. Les normes cryptographiques généralement applicables comprennent la cryptographie conforme aux normes FIPS. Ce contrôle n’oblige pas les organisations à utiliser la cryptographie. Toutefois, si la cryptographie est requise en fonction de la sélection d’autres contrôles ou politiques de sécurité, les organisations documentent chaque type d’utilisation cryptographique et le type de cryptographie requis (p. ex., protection de l’information classifiée : cryptographie conforme aux normes FIPS). Contrôles connexes : AC-2, AC-3, AC-7, AC-17, AC-18, AU-9, AU-10, CM-11, CP-9, IA-3, IA-7, MA-4, MP-2, MP-4, MP-5, SA-4, SC-8, SC-12, SC-28, SI-7
A10: Test Case | D10: Cas de test
A11: Test | B11: TEST-SC-13 | D11: Test | E11: TEST-SC-13
A12: Requirement ID | B12: SC-13 | D12: ID Exigence | E12: SC-13
A13: Component | D13: Composant
A14: Requirement | D14: Exigence
A15: Contextual Design Description | D15: Description contextuelle du design
A16: Evidence Provided | D16: Preuve fournie
A17: Preparer Sign Off (Initials, Date) | D17: Signataire préparateur (Initiales, Date)
A18: Owner Sign Off (Initials, Date) | D18: Signataire propriétaire (Initiales, Date)
A19: Assessor Sign Off (Initials, Date) | D19: Signataire évaluateur (Initiales, Date)
A20: Status | B20: Not Started | D20: Statut | E20: Non commencé
A21: Comments | D21: Commentaires

Sheet SC-18
A1: Control SC-18 — Evidence Tracking | D1: Contrôle SC-18 — Suivi des preuves
A2: Control Information | D2: Informations du contrôle
A3: Control Identifier | B3: SC-18 | D3: Identifiant du contrôle | E3: SC-18
A4: Family | B4: Mobile Code | D4: Famille | E4: Code mobile
A5: Profile | B5: CCCS Medium / PBMM Moderate | D5: Profil | E5: CCCS Moyen / PBMM Modéré
A6: Primary Evidence Tool | D6: Outil de preuve principal
A7: Contributing Tools | D7: Outils contributeurs
A8: Control Description | B8: (A) The organization defines acceptable and unacceptable mobile code and mobile code technologies. (B) The organization establishes usage restrictions and implementation guidance for acceptable mobile code and mobile code technologies. (C) The organization authorizes, monitors, and controls the use of mobile code within the information system. | D8: Description du contrôle | E8: (A) L’organisation définit les codes mobiles et les technologies de codes mobiles acceptables et inacceptables. (B) L’organisation établit des restrictions d’utilisation et des directives de mise en œuvre pour le code mobile et les technologies de code mobile acceptables. (C) L’organisation autorise, surveille et contrôle l’utilisation du code mobile dans le système d’information.
A9: Supplemental Guidance | B9: Decisions regarding the employment of mobile code within organizational information systems are based on the potential for the code to cause damage to the systems if used maliciously. Mobile code technologies include, for example, Java, JavaScript, ActiveX, Postscript, PDF, Shockwave movies, Flash animations, and VBScript. Usage restrictions and implementation guidance apply to both the selection and use of mobile code installed on servers and mobile code downloaded and executed on individual workstations and devices (e.g., smart phones). Mobile code policy and procedures address preventing the development, acquisition, or introduction of unacceptable mobile code within organizational information systems. Related controls: AU-2, AU-12, CM-2, CM-6, SI-3 | D9: Directives supplémentaires | E9: Les décisions concernant l’utilisation du code mobile dans les systèmes d’information de l’organisation sont basées sur le potentiel de dommages causés aux systèmes si le code est utilisé de façon malveillante. Les technologies de code mobile comprennent, par exemple, Java, JavaScript, ActiveX, Postcript, PDF, les films Shockwave, les animations Flash et VBScript. Les restrictions d’utilisation et les directives de mise en œuvre s’appliquent à la fois à la sélection et à l’utilisation du code mobile installé sur les serveurs et du code mobile téléchargé et exécuté sur des postes de travail et des appareils individuels (p. ex., téléphones intelligents). La politique et les procédures relatives au code mobile visent à prévenir l’élaboration, l’acquisition ou l’introduction de code mobile inacceptable dans les systèmes d’information de l’organisation. Contrôles connexes : AU-2, AU-12, CM-2, CM-6, SI-3
A10: Test Case | D10: Cas de test
A11: Test | B11: TEST-SC-18 | D11: Test | E11: TEST-SC-18
A12: Requirement ID | B12: SC-18 | D12: ID Exigence | E12: SC-18
A13: Component | D13: Composant
A14: Requirement | D14: Exigence
A15: Contextual Design Description | D15: Description contextuelle du design
A16: Evidence Provided | D16: Preuve fournie
A17: Preparer Sign Off (Initials, Date) | D17: Signataire préparateur (Initiales, Date)
A18: Owner Sign Off (Initials, Date) | D18: Signataire propriétaire (Initiales, Date)
A19: Assessor Sign Off (Initials, Date) | D19: Signataire évaluateur (Initiales, Date)
A20: Status | B20: Not Started | D20: Statut | E20: Non commencé
A21: Comments | D21: Commentaires

Sheet SC-20
A1: Control SC-20 — Evidence Tracking | D1: Contrôle SC-20 — Suivi des preuves
A2: Control Information | D2: Informations du contrôle
A3: Control Identifier | B3: SC-20 | D3: Identifiant du contrôle | E3: SC-20
A4: Family | B4: Secure Name / Address Resolution Service (Authoritative Source) | D4: Famille | E4: Service sécurisé de résolution de nom et d’adresse (source reconnue)
A5: Profile | B5: CCCS Medium / PBMM Moderate | D5: Profil | E5: CCCS Moyen / PBMM Modéré
A6: Primary Evidence Tool | D6: Outil de preuve principal
A7: Contributing Tools | D7: Outils contributeurs
A8: Control Description | B8: (A) The information system provides additional data origin authentication and integrity verification artifacts along with the authoritative name resolution data the system returns in response to external name/address resolution queries. (B) The information system provides the means to indicate the security status of child zones and (if the child supports secure resolution services) to enable verification of a chain of trust among parent and child domains, when operating as part of a distributed, hierarchical namespace. | D8: Description du contrôle | E8: (A) Le système d’information fournit des artefacts supplémentaires d’authentification et de vérification de l’intégrité de l’origine des données, ainsi que les données de résolution de nom faisant autorité que le système renvoie en réponse à des requêtes externes de résolution de nom ou d’adresse. (B) Le système d’information fournit les moyens d’indiquer l’état de sécurité des zones enfants et (si l’enfant prend en charge les services de résolution sécurisée) de permettre la vérification d’une chaîne de confiance entre les domaines parents et enfants, lorsqu’il est exploité au sein d’un espace de nommage hiérarchique distribué.
A9: Supplemental Guidance | B9: This control enables external clients including, for example, remote Internet clients, to obtain origin authentication and integrity verification assurances for the host/service name to network address resolution information obtained through the service. Information systems that provide name and address resolution services include, for example, domain name system (DNS) servers. Additional artifacts include, for example, DNS Security (DNSSEC) digital signatures and cryptographic keys. DNS resource records are examples of authoritative data. The means to indicate the security status of child zones includes, for example, the use of delegation signer resource records in the DNS. Information systems that use technologies other than the DNS to map between host/service names and network addresses provide other means to assure the authenticity and integrity of response data. Related controls: AU-10, SC-8, SC-12, SC-13, SC-21, SC-22 | D9: Directives supplémentaires | E9: Ce contrôle permet aux clients externes, y compris, par exemple, les clients Internet à distance, d’obtenir des garanties d’authentification de l’origine et de vérification de l’intégrité pour le nom de l’hôte ou du service pour l’information de résolution de l’adresse réseau obtenue au moyen du service. Les systèmes d’information qui fournissent des services de résolution de nom et d’adresse comprennent, par exemple, les serveurs de systèmes de noms de domaine (DNS). D’autres artefacts comprennent, par exemple, les signatures numériques DNS Security (DNSSEC) et les clés cryptographiques. Les enregistrements des ressources DNS sont des exemples de données faisant autorité. Les moyens d’indiquer l’état de sécurité des zones enfants comprennent, par exemple, l’utilisation des enregistrements de ressources DS (Delegation Signer) dans le DNS. Les systèmes d’information qui utilisent des technologies autres que le DNS pour établir les correspondances entre les noms d’hôte ou de service et les adresses réseau offrent d’autres moyens d’assurer l’authenticité et l’intégrité des données de réponse. Contrôles connexes : AU-10, SC-8, SC-12, SC-13, SC-21, SC-22
A10: Test Case | D10: Cas de test
A11: Test | B11: TEST-SC-20 | D11: Test | E11: TEST-SC-20
A12: Requirement ID | B12: SC-20 | D12: ID Exigence | E12: SC-20
A13: Component | D13: Composant
A14: Requirement | D14: Exigence
A15: Contextual Design Description | D15: Description contextuelle du design
A16: Evidence Provided | D16: Preuve fournie
A17: Preparer Sign Off (Initials, Date) | D17: Signataire préparateur (Initiales, Date)
A18: Owner Sign Off (Initials, Date) | D18: Signataire propriétaire (Initiales, Date)
A19: Assessor Sign Off (Initials, Date) | D19: Signataire évaluateur (Initiales, Date)
A20: Status | B20: Not Started | D20: Statut | E20: Non commencé
A21: Comments | D21: Commentaires

Sheet SC-21
A1: Control SC-21 — Evidence Tracking | D1: Contrôle SC-21 — Suivi des preuves
A2: Control Information | D2: Informations du contrôle
A3: Control Identifier | B3: SC-21 | D3: Identifiant du contrôle | E3: SC-21
A4: Family | B4: Secure Name / Address Resolution Service (Recursive or Caching Resolver) | D4: Famille | E4: Service sécurisé de résolution de nom et d’adresse (résolveur récursif ou de mise en cache)
A5: Profile | B5: CCCS Medium / PBMM Moderate | D5: Profil | E5: CCCS Moyen / PBMM Modéré
A6: Primary Evidence Tool | D6: Outil de preuve principal
A7: Contributing Tools | D7: Outils contributeurs
A8: Control Description | B8: (A) The information system requests and performs data origin authentication and data integrity verification on the name/address resolution responses the system receives from authoritative sources. | D8: Description du contrôle | E8: (A) Le système d’information demande et effectue l’authentification de l’origine des données et la vérification de l’intégrité des données sur les réponses de résolution de nom et d’adresse que le système reçoit de sources faisant autorité.
A9: Supplemental Guidance | B9: Each client of name resolution services either performs this validation on its own, or has authenticated channels to trusted validation providers. Information systems that provide name and address resolution services for local clients include, for example, recursive resolving or caching domain name system (DNS) servers. DNS client resolvers either perform validation of DNSSEC signatures, or clients use authenticated channels to recursive resolvers that perform such validations. Information systems that use technologies other than the DNS to map between host/service names and network addresses provide other means to enable clients to verify the authenticity and integrity of response data. Related controls: SC-20, SC-22 | D9: Directives supplémentaires | E9: Chaque client des services de résolution de noms effectue cette validation par lui-même ou par le biais de canaux authentifiés vers des fournisseurs de validation de confiance. Les systèmes d’information qui fournissent des services de résolution de noms et d’adresses aux clients locaux comprennent, par exemple, des serveurs résolveurs récursifs ou de mise en cache de systèmes de noms de domaine (DNS). Soit les résolveurs des clients DNS effectuent la validation des signatures DNSSEC, soit les clients utilisent des canaux authentifiés vers des résolveurs récursifs qui effectuent de telles validations. Les systèmes d’information qui utilisent des technologies autres que le DNS pour établir les correspondances entre les noms d’hôte ou de service et les adresses réseau offrent d’autres moyens permettant aux clients de vérifier l’authenticité et l’intégrité des données de réponse. Contrôles connexes : SC-20, SC-22
A10: Test Case | D10: Cas de test
A11: Test | B11: TEST-SC-21 | D11: Test | E11: TEST-SC-21
A12: Requirement ID | B12: SC-21 | D12: ID Exigence | E12: SC-21
A13: Component | D13: Composant
A14: Requirement | D14: Exigence
A15: Contextual Design Description | D15: Description contextuelle du design
A16: Evidence Provided | D16: Preuve fournie
A17: Preparer Sign Off (Initials, Date) | D17: Signataire préparateur (Initiales, Date)
A18: Owner Sign Off (Initials, Date) | D18: Signataire propriétaire (Initiales, Date)
A19: Assessor Sign Off (Initials, Date) | D19: Signataire évaluateur (Initiales, Date)
A20: Status | B20: Not Started | D20: Statut | E20: Non commencé
A21: Comments | D21: Commentaires

Sheet SC-22
A1: Control SC-22 — Evidence Tracking | D1: Contrôle SC-22 — Suivi des preuves
A2: Control Information | D2: Informations du contrôle
A3: Control Identifier | B3: SC-22 | D3: Identifiant du contrôle | E3: SC-22
A4: Family | B4: Architecture and Provisioning for Name / Address Resolution Service | D4: Famille | E4: Architecture et provisionnement du service de résolution de nom et d’adresse
A5: Profile | B5: CCCS Medium / PBMM Moderate | D5: Profil | E5: CCCS Moyen / PBMM Modéré
A6: Primary Evidence Tool | D6: Outil de preuve principal
A7: Contributing Tools | D7: Outils contributeurs
A8: Control Description | B8: (A) The information systems that collectively provide name/address resolution service for an organization are fault-tolerant and implement internal/external role separation. | D8: Description du contrôle | E8: (A) Les systèmes d’information qui fournissent collectivement un service de résolution de nom et d’adresse pour une organisation sont tolérants aux défaillances et mettent en œuvre une séparation des rôles interne et externe.
A9: Supplemental Guidance | B9: Information systems that provide name and address resolution services include, for example, domain name system (DNS) servers. To eliminate single points of failure and to enhance redundancy, organizations employ at least two authoritative domain name system servers, one configured as the primary server and the other configured as the secondary server. Additionally, organizations typically deploy the servers in two geographically separated network sub-networks (i.e., not located in the same physical facility). For role separation, DNS servers with internal roles only process name and address resolution requests from within organizations (i.e., from internal clients). DNS servers with external roles only process name and address resolution information requests from clients external to organizations (i.e., on external networks including the Internet). Organizations specify clients that can access authoritative DNS servers in particular roles (e.g., by address ranges, explicit lists). Related controls: SC-2, SC-20, SC-21, SC-24 | D9: Directives supplémentaires | E9: Les systèmes d’information qui fournissent des services de résolution de nom et d’adresse comprennent, par exemple, les serveurs de systèmes de noms de domaine (DNS). Pour éliminer les points de défaillance uniques et améliorer la redondance, les organisations utilisent au moins deux serveurs de systèmes de noms de domaine faisant autorité, l’un étant configuré comme serveur principal et l’autre comme serveur secondaire. De plus, les organisations déploient habituellement les serveurs dans deux sous-réseaux géographiquement séparés (c.-à-d. non situés dans la même installation physique). Pour la séparation des rôles, les serveurs DNS avec rôles internes ne traitent que le nom et l’adresse des demandes de résolution provenant de l’intérieur des organisations (c.-à-d. des clients internes). Les serveurs DNS qui ont des rôles externes traitent uniquement les demandes d’information de résolution de nom et d’adresse provenant des clients externes (c.-à-d. sur les réseaux externes, y compris Internet). Les organisations spécifient quels sont les clients pouvant accéder à des serveurs DNS faisant autorité dans des rôles particuliers (p. ex., par gammes d’adresses, listes explicites). Contrôles connexes : SC-2, SC-20, SC-21, SC-24
A10: Test Case | D10: Cas de test
A11: Test | B11: TEST-SC-22 | D11: Test | E11: TEST-SC-22
A12: Requirement ID | B12: SC-22 | D12: ID Exigence | E12: SC-22
A13: Component | D13: Composant
A14: Requirement | D14: Exigence
A15: Contextual Design Description | D15: Description contextuelle du design
A16: Evidence Provided | D16: Preuve fournie
A17: Preparer Sign Off (Initials, Date) | D17: Signataire préparateur (Initiales, Date)
A18: Owner Sign Off (Initials, Date) | D18: Signataire propriétaire (Initiales, Date)
A19: Assessor Sign Off (Initials, Date) | D19: Signataire évaluateur (Initiales, Date)
A20: Status | B20: Not Started | D20: Statut | E20: Non commencé
A21: Comments | D21: Commentaires

Sheet SC-23
A1: Control SC-23 — Evidence Tracking | D1: Contrôle SC-23 — Suivi des preuves
A2: Control Information | D2: Informations du contrôle
A3: Control Identifier | B3: SC-23 | D3: Identifiant du contrôle | E3: SC-23
A4: Family | B4: Session Authenticity | D4: Famille | E4: Authenticité des sessions
A5: Profile | B5: CCCS Medium / PBMM Moderate | D5: Profil | E5: CCCS Moyen / PBMM Modéré
A6: Primary Evidence Tool | D6: Outil de preuve principal
A7: Contributing Tools | D7: Outils contributeurs
A8: Control Description | B8: (A) The information system protects the authenticity of communications sessions. | D8: Description du contrôle | E8: (A) Le système d’information protège l’authenticité des sessions de communication.
A9: Supplemental Guidance | B9: This control addresses communications protection at the session, versus packet level (e.g., sessions in service-oriented architectures providing web-based services) and establishes grounds for confidence at both ends of communications sessions in ongoing identities of other parties and in the validity of information transmitted. Authenticity protection includes, for example, protecting against man-in-the-middle attacks/session hijacking and the insertion of false information into sessions. Related controls: SC-8, SC-10, SC-11 | D9: Directives supplémentaires | E9: Ce contrôle porte sur la protection des communications au niveau des sessions plutôt qu’au niveau des paquets (p. ex., les sessions dans les architectures orientées service fournissant des services Web) et établit des motifs de confiance, aux deux extrémités des sessions de communication, dans les identités continues des autres parties et dans la validité de l’information transmise. La protection de l’authenticité comprend, par exemple, la protection contre les attaques de l’intercepteur ou les détournements de sessions et l’insertion de faux renseignements dans les sessions. Contrôles connexes : SC-8, SC-10, SC-11
A10: Test Case | D10: Cas de test
A11: Test | B11: TEST-SC-23 | D11: Test | E11: TEST-SC-23
A12: Requirement ID | B12: SC-23 | D12: ID Exigence | E12: SC-23
A13: Component | D13: Composant
A14: Requirement | D14: Exigence
A15: Contextual Design Description | D15: Description contextuelle du design
A16: Evidence Provided | D16: Preuve fournie
A17: Preparer Sign Off (Initials, Date) | D17: Signataire préparateur (Initiales, Date)
A18: Owner Sign Off (Initials, Date) | D18: Signataire propriétaire (Initiales, Date)
A19: Assessor Sign Off (Initials, Date) | D19: Signataire évaluateur (Initiales, Date)
A20: Status | B20: Not Started | D20: Statut | E20: Non commencé
A21: Comments | D21: Commentaires

Sheet SC-23-1
A1: Control SC-23(1) — Evidence Tracking | D1: Contrôle SC-23(1) — Suivi des preuves
A2: Control Information | D2: Informations du contrôle
A3: Control Identifier | B3: SC-23(1) | D3: Identifiant du contrôle | E3: SC-23(1)
A4: Family | B4: Session Authenticity | D4: Famille | E4: Authenticité des sessions
A5: Profile | B5: CCCS Medium / PBMM Moderate | D5: Profil | E5: CCCS Moyen / PBMM Modéré
A6: Primary Evidence Tool | D6: Outil de preuve principal
A7: Contributing Tools | D7: Outils contributeurs
A8: Control Description | B8: SESSION AUTHENTICITY | INVALIDATE SESSION IDENTIFIERS AT LOGOUT The information system invalidates session identifiers upon user logout or other session termination. | D8: Description du contrôle | E8: AUTHENTICITÉ DES SESSIONS | INVALIDATION DES IDENTIFIANTS DE SESSION DÈS LA FERMETURE DE SESSION Le système d’information invalide les identifiants de session dès la fermeture de session par l’utilisateur ou à toute autre fin de session.
A9: Supplemental Guidance | B9: This control enhancement curtails the ability of adversaries from capturing and continuing to employ previously valid session IDs. | D9: Directives supplémentaires | E9: Cette amélioration du contrôle empêche les adversaires de saisir et de continuer d’utiliser des ID de session valides.
A10: Test Case | D10: Cas de test
A11: Test | B11: TEST-SC-23(1) | D11: Test | E11: TEST-SC-23(1)
A12: Requirement ID | B12: SC-23(1) | D12: ID Exigence | E12: SC-23(1)
A13: Component | D13: Composant
A14: Requirement | D14: Exigence
A15: Contextual Design Description | D15: Description contextuelle du design
A16: Evidence Provided | D16: Preuve fournie
A17: Preparer Sign Off (Initials, Date) | D17: Signataire préparateur (Initiales, Date)
A18: Owner Sign Off (Initials, Date) | D18: Signataire propriétaire (Initiales, Date)
A19: Assessor Sign Off (Initials, Date) | D19: Signataire évaluateur (Initiales, Date)
A20: Status | B20: Not Started | D20: Statut | E20: Non commencé
A21: Comments | D21: Commentaires

Sheet SC-28
A1: Control SC-28 — Evidence Tracking | D1: Contrôle SC-28 — Suivi des preuves
A2: Control Information | D2: Informations du contrôle
A3: Control Identifier | B3: SC-28 | D3: Identifiant du contrôle | E3: SC-28
A4: Family | B4: Protection of Information At Rest | D4: Famille | E4: Protection de l’information inactive
A5: Profile | B5: CCCS Medium / PBMM Moderate | D5: Profil | E5: CCCS Moyen / PBMM Modéré
A6: Primary Evidence Tool | D6: Outil de preuve principal
A7: Contributing Tools | D7: Outils contributeurs
A8: Control Description | B8: (A) The information system protects the confidentiality and integrity of all information not cleared for public release and all data with a higher than low integrity requirement. | D8: Description du contrôle | E8: (A) Le système d’information protège la confidentialité et l’intégrité de tous les renseignements dont la diffusion publique n’est pas autorisée et de toutes les données pour lesquelles les exigences d’intégrité ne sont pas faibles.
A9: Supplemental Guidance | B9: This control addresses the confidentiality and integrity of information at rest and covers user information and system information. Information at rest refers to the state of information when it is located on storage devices as specific components of information systems. System-related information requiring protection includes, for example, configurations or rule sets for firewalls, gateways, intrusion detection/prevention systems, filtering routers, and authenticator content. Organizations may employ different mechanisms to achieve confidentiality and integrity protections, including the use of cryptographic mechanisms and file share scanning. Integrity protection can be achieved, for example, by implementing Write-Once-Read-Many (WORM) technologies. Organizations may also employ other security controls including, for example, secure off-line storage in lieu of online storage when adequate protection of information at rest cannot otherwise be achieved and/or continuous monitoring to identify malicious code at rest. Related controls: AC-3, AC-6, CA-7, CM-3, CM-5, CM-6, PE-3, SC-8, SC-13, SI-3, SI-7 | D9: Directives supplémentaires | E9: Ce contrôle porte sur la confidentialité et l’intégrité de l’information inactive et couvre l’information sur les utilisateurs et le système. L’information inactive fait référence à l’état de l’information lorsqu’elle se trouve sur des dispositifs de stockage en tant que composants particuliers des systèmes d’information. Les renseignements relatifs au système qui nécessitent une protection comprennent, par exemple, les configurations ou les ensembles de règles pour les pare-feu, les passerelles, les systèmes de détection et de prévention des intrusions, les routeurs de filtrage et le contenu des authentifiants. Les organisations peuvent utiliser différents mécanismes pour assurer la protection de la confidentialité et de l’intégrité, y compris les mécanismes cryptographiques et le balayage des fichiers partagés. La protection de l’intégrité peut être assurée, par exemple, en mettant en œuvre des technologies qui rendent les supports non réinscriptibles. Les organisations peuvent également utiliser d’autres contrôles de sécurité, y compris, par exemple, le stockage hors ligne sécurisé au lieu du stockage en ligne lorsque la protection de l’information inactive ne peut être assurée autrement, ou la surveillance continue pour repérer du code malveillant inactif. Contrôles connexes : AC-3, AC-6, CA-7, CM-3, CM-5, CM-6, PE-3, SC-8, SC-13, SI-3, SI-7
A10: Test Case | D10: Cas de test
A11: Test | B11: TEST-SC-28 | D11: Test | E11: TEST-SC-28
A12: Requirement ID | B12: SC-28 | D12: ID Exigence | E12: SC-28
A13: Component | D13: Composant
A14: Requirement | D14: Exigence
A15: Contextual Design Description | D15: Description contextuelle du design
A16: Evidence Provided | D16: Preuve fournie
A17: Preparer Sign Off (Initials, Date) | D17: Signataire préparateur (Initiales, Date)
A18: Owner Sign Off (Initials, Date) | D18: Signataire propriétaire (Initiales, Date)
A19: Assessor Sign Off (Initials, Date) | D19: Signataire évaluateur (Initiales, Date)
A20: Status | B20: Not Started | D20: Statut | E20: Non commencé
A21: Comments | D21: Commentaires

Sheet SI-3
A1: Control SI-3 — Evidence Tracking | D1: Contrôle SI-3 — Suivi des preuves
A2: Control Information | D2: Informations du contrôle
A3: Control Identifier | B3: SI-3 | D3: Identifiant du contrôle | E3: SI-3
A4: Family | B4: Malicious Code Protection | D4: Famille | E4: Protection contre le code malveillant
A5: Profile | B5: CCCS Medium / PBMM Moderate | D5: Profil | E5: CCCS Moyen / PBMM Modéré
A6: Primary Evidence Tool | D6: Outil de preuve principal
A7: Contributing Tools | D7: Outils contributeurs
A8: Control Description | B8: (A) The organization employs malicious code protection mechanisms at information system entry and exit points to detect and eradicate malicious code. (B) The organization updates malicious code protection mechanisms whenever new releases are available in accordance with organizational configuration management policy and procedures. (C) The organization configures malicious code protection mechanisms to: (a) Perform periodic scans of the information system at least weekly and real-time scans of files from external sources at endpoints and network entry/exit points as the files are downloaded, opened, or executed in accordance with organizational security policy; and (b) Block and quarantine malicious code; send alert to the key role as defined in the system and information integrity policy in response to malicious code detection. (D) The organization addresses the receipt of false positives during malicious code detection and eradication and the resulting potential impact on the availability of the information system. | D8: Description du contrôle | E8: (A) L’organisation utilise des mécanismes de protection contre le code malveillant aux points d’entrée et de sortie du système d’information pour détecter et éradiquer le code malveillant. (B) L’organisation met à jour les mécanismes de protection contre le code malveillant chaque fois que de nouvelles versions sont disponibles, conformément à la politique et aux procédures de gestion de la configuration de l’organisation. (C) L’organisation configure des mécanismes de protection contre le code malveillant pour : (a) effectuer des balayages périodiques du système d’information au moins une fois par semaine et des balayages en temps réel des fichiers provenant de sources externes aux extrémités et aux points d’entrée et de sortie du réseau à mesure que les fichiers sont téléchargés, ouverts ou exécutés, conformément à la politique sur la sécurité de l’organisation; (b) bloquer et mettre en quarantaine le code malveillant; envoyer une alerte au rôle clé tel que défini dans la politique sur l’intégrité du système et de l’information en réponse à la détection du code malveillant. (D) L’organisation résout les faux positifs reçus lors de la détection et de l’éradication du code malveillant ainsi que l’incidence potentielle sur la disponibilité du système d’information.
A9: Supplemental Guidance | B9: Information system entry and exit points include, for example, firewalls, electronic mail servers, web servers, proxy servers, remote-access servers, workstations, notebook computers, and mobile devices. Malicious code includes, for example, viruses, worms, Trojan horses, and spyware. Malicious code can also be encoded in various formats (e.g., UUENCODE, Unicode), contained within compressed or hidden files, or hidden in files using steganography. Malicious code can be transported by different means including, for example, web accesses, electronic mail, electronic mail attachments, and portable storage devices. Malicious code insertions occur through the exploitation of information system vulnerabilities. Malicious code protection mechanisms include, for example, anti-virus signature definitions and reputation-based technologies. A variety of technologies and methods exist to limit or eliminate the effects of malicious code. Pervasive configuration management and comprehensive software integrity controls may be effective in preventing execution of unauthorized code. In addition to commercial off-the-shelf software, malicious code may also be present in custom-built software. This could include, for example, logic bombs, back doors, and other types of cyber-attacks that could affect organizational missions/business functions. Traditional malicious code protection mechanisms cannot always detect such code. In these situations, organizations rely instead on other safeguards including, for example, secure coding practices, configuration management and control, trusted procurement processes, and monitoring practices to help ensure that software does not perform functions other than the functions intended. Organizations may determine that in response to the detection of malicious code, different actions may be warranted. For example, organizations can define actions in response to malicious code detection during periodic scans, actions in response to detection of malicious downloads, and/or actions in response to detection of maliciousness when attempting to open or execute files. Related controls: CM-3, MP-2, SA-4, SA-8, SA-12, SA-13, SC-7, SC-26, SC-44, SI-2, SI-4, SI-7. | D9: Directives supplémentaires | E9: Les points d’entrée et de sortie du système d’information comprennent, par exemple, les pare-feu, les serveurs de courrier électronique, les serveurs Web, les serveurs mandataires, les serveurs à accès à distance, les postes de travail, les ordinateurs portatifs et les appareils mobiles. Le code malveillant comprend, par exemple, les virus, les vers, les chevaux de Troie et les logiciels espions. Le code malveillant peut également avoir divers formats (p. ex., UUENCODE, Unicode), et être intégré à des fichiers compressés ou cachés, ou être dissimulé dans des fichiers par stéganographie. Le code malveillant peut être transporté par différents moyens, y compris, par exemple, les accès Web, le courrier électronique, les pièces jointes de courrier électronique et les dispositifs de stockage portatifs. Le code malveillant est inséré en exploitant les vulnérabilités du système d’information. Les mécanismes de protection contre le code malveillant comprennent, par exemple, les définitions de signature antivirus et les technologies fondées sur la réputation. Diverses technologies et méthodes permettent de limiter ou d’éliminer les effets du code malveillant. Une gestion généralisée de la configuration et des contrôles d’intégrité du logiciel exhaustifs peuvent être efficaces pour prévenir l’exécution de code non autorisé. En plus des logiciels commerciaux, le code malveillant peut également être présent dans les logiciels développés sur mesure. Cela pourrait comprendre, par exemple, des bombes logiques, des portes dérobées et d’autres types de cyberattaques qui pourraient avoir une incidence sur les missions et les fonctions opérationnelles de l’organisation. Les mécanismes traditionnels de protection contre le code malveillant ne peuvent pas toujours détecter ce type de code. Dans ces situations, les organisations se fient plutôt à d’autres mesures de protection, comme des pratiques de codage sécurisé, une gestion et un contrôle de la configuration, des processus d’approvisionnement auprès de fournisseurs de confiance et des pratiques de surveillance pour veiller à ce que les logiciels n’exécutent pas de fonctions autres que celles prévues. Les organisations peuvent déterminer que différentes mesures sont justifiées en réponse à la détection du code malveillant. Par exemple, les organisations peuvent définir des mesures en réponse à la détection de code malveillant lors des balayages périodiques, des mesures en réponse à la détection de téléchargements malveillants ou des mesures en réponse à la détection de malveillance lorsqu’on tente d’ouvrir ou d’exécuter des fichiers. Contrôles connexes : CM-3, MP-2, SA-4, SA-8, SA-12, SA-13, SC-7, SC-26, SC-44, SI-2, SI-4, SI-7.
A10: Test Case | D10: Cas de test
A11: Test | B11: TEST-SI-3 | D11: Test | E11: TEST-SI-3
A12: Requirement ID | B12: SI-3 | D12: ID Exigence | E12: SI-3
A13: Component | D13: Composant
A14: Requirement | D14: Exigence
A15: Contextual Design Description | D15: Description contextuelle du design
A16: Evidence Provided | D16: Preuve fournie
A17: Preparer Sign Off (Initials, Date) | D17: Signataire préparateur (Initiales, Date)
A18: Owner Sign Off (Initials, Date) | D18: Signataire propriétaire (Initiales, Date)
A19: Assessor Sign Off (Initials, Date) | D19: Signataire évaluateur (Initiales, Date)
A20: Status | B20: Not Started | D20: Statut | E20: Non commencé
A21: Comments | D21: Commentaires

Sheet SI-4
A1: Control SI-4 — Evidence Tracking | D1: Contrôle SI-4 — Suivi des preuves
A2: Control Information | D2: Informations du contrôle
A3: Control Identifier | B3: SI-4 | D3: Identifiant du contrôle | E3: SI-4
A4: Family | B4: Information System Monitoring | D4: Famille | E4: Surveillance du système d’information
A5: Profile | B5: CCCS Medium / PBMM Moderate | D5: Profil | E5: CCCS Moyen / PBMM Modéré
A6: Primary Evidence Tool | D6: Outil de preuve principal
A7: Contributing Tools | D7: Outils contributeurs
A8: Control Description | B8: (A) The organization monitors the information system to detect: (a) Attacks and indicators of potential attacks in accordance with organization-defined monitoring objectives; and (b) Unauthorized local, network, and remote connections; (B) The organization identifies unauthorized use of the information system through organization-defined techniques and methods. (C) The organization deploys monitoring devices: (i) strategically within the information system to collect organization-determined essential information; and (ii) at ad hoc locations within the system to track specific types of transactions of interest to the organization. (D) The organization protects information obtained from intrusion-monitoring tools from unauthorized access, modification, and deletion. (E) The organization heightens the level of information system monitoring activity whenever there is an indication of increased risk to organizational operations and assets, individuals, other organizations, or Canada based on law enforcement information, intelligence information, or other credible sources of information. (F) The organization obtains legal opinion with regard to information system monitoring activities in accordance with orgnanizational policies, directives and standards. (G) The organization provides organization-defined information system monitoring information to organization-defined personnel or roles at an organization-defined frequency. | D8: Description du contrôle | E8: (A) L’organisation surveille le système d’information pour détecter : (a) les attaques et indicateurs d’attaques potentielles conformément aux objectifs de surveillance définis par l’organisation; (b) les connexions locales, de réseau et à distance non autorisées; (B) L’organisation détecte l’utilisation non autorisée du système d’information au moyen de techniques et de méthodes définies par l’organisation. (C) L’organisation déploie des dispositifs de surveillance : (i) de façon stratégique au sein du système d’information pour recueillir les renseignements essentiels déterminés par l’organisation; (ii) à des endroits spéciaux dans le système pour faire le suivi de certains types de transactions d’intérêt pour l’organisation. (D) L’organisation protège l’information obtenue des outils de surveillance des intrusions contre l’accès, la modification et la suppression non autorisés. (E) L’organisation augmente le niveau de l’activité de surveillance du système d’information chaque fois qu’il y a indication d’un risque accru pour les opérations et les biens de l’organisation, les personnes, les autres organisations ou le Canada sur la base de renseignements concernant l’application de la loi, de renseignements de sécurité ou d’autres sources d’information crédibles. (F) L’organisation obtient un avis juridique concernant les activités de surveillance du système d’information conformément aux politiques, aux directives et aux normes de l’organisation. (G) L’organisation fournit les renseignements relatifs à la surveillance du système d’information définis par l’organisation au personnel ou aux rôles définis par l’organisation à une fréquence définie par l’organisation.
